{
  "type": "Feature",
  "properties": {
    "gn:admin1_code":"11.0",
    "gn:asciiname":"Zherendyk",
    "gn:country_code":"KZ",
    "gn:dem":112,
    "gn:feature_class":"P",
    "gn:feature_code":"PPL",
    "gn:name":"Zherendyk",
    "gn:population":0,
    "gn:timezone":"Asia/Almaty",
    "iso:country":"KZ",
    "name:rus_x_preferred":[
        "\u0416\u0435\u0440\u0435\u043d\u0434\u044b\u043a"
    ],
    "wof:name":"Zherendyk",
    "wof:placetype":"locality"
},
  "geometry": {"coordinates":[76.19386,52.66361],"type":"Point"}
}