{
  "type": "Feature",
  "properties": {
    "gn:admin1_code":"0.0",
    "gn:asciiname":"Akozek",
    "gn:country_code":"KZ",
    "gn:dem":424,
    "gn:feature_class":"P",
    "gn:feature_code":"PPL",
    "gn:name":"Akozek",
    "gn:population":0,
    "gn:timezone":"Asia/Almaty",
    "iso:country":"KZ",
    "name:ceb_x_preferred":[
        "Akozek"
    ],
    "name:fas_x_preferred":[
        "\u0627\u06a9\u0648\u0632\u06a9"
    ],
    "name:kaz_x_preferred":[
        "\u0410\u049b\u04e9\u0437\u0435\u043a"
    ],
    "name:mkd_x_preferred":[
        "\u0410\u043a\u043e\u0437\u0435\u043a"
    ],
    "name:msa_x_preferred":[
        "Akozek"
    ],
    "name:rus_x_preferred":[
        "\u0410\u043a\u043e\u0437\u0435\u043a"
    ],
    "name:swe_x_preferred":[
        "Akozek"
    ],
    "name:ukr_x_preferred":[
        "\u0410\u043a\u043e\u0437\u0435\u043a"
    ],
    "wof:name":"Akozek",
    "wof:placetype":"locality"
},
  "geometry": {"coordinates":[78.86667,45.75],"type":"Point"}
}