{
  "type": "Feature",
  "properties": {
    "gn:admin1_code":"0.0",
    "gn:asciiname":"Akozek",
    "gn:country_code":"KZ",
    "gn:dem":424,
    "gn:feature_class":"P",
    "gn:feature_code":"PPL",
    "gn:name":"Akozek",
    "gn:population":0,
    "gn:timezone":"Asia/Almaty",
    "iso:country":"KZ",
    "wof:name":"Akozek",
    "wof:placetype":"locality"
},
  "geometry": {"coordinates":[78.86667,45.75],"type":"Point"}
}