{
  "type": "Feature",
  "properties": {
    "gn:admin1_code":"16.0",
    "gn:asciiname":"Imeni Papanina",
    "gn:country_code":"KZ",
    "gn:dem":74,
    "gn:feature_class":"P",
    "gn:feature_code":"PPL",
    "gn:name":"Imeni Papanina",
    "gn:population":0,
    "gn:timezone":"Asia/Almaty",
    "iso:country":"KZ",
    "wof:name":"Imeni Papanina",
    "wof:placetype":"locality"
},
  "geometry": {"coordinates":[73.73333000000002,52.78333000000001],"type":"Point"}
}