{
  "type": "Feature",
  "properties": {
    "gn:admin1_code":"6.0",
    "gn:asciiname":"Ushtaghan",
    "gn:country_code":"KZ",
    "gn:dem":-15,
    "gn:feature_class":"P",
    "gn:feature_code":"PPL",
    "gn:name":"\u00dcshtaghan",
    "gn:population":0,
    "gn:timezone":"Asia/Atyrau",
    "iso:country":"KZ",
    "name:eng_x_preferred":[
        "\u00dcshtaghan"
    ],
    "name:rus_x_preferred":[
        "\u0423\u0448\u0442\u0430\u0433\u0430\u043d"
    ],
    "name:und_x_variant":[
        "Ushtagan",
        "Novyy Ushtagan",
        "\u00dcshtaghan"
    ],
    "wof:name":"Ushtaghan",
    "wof:placetype":"locality"
},
  "geometry": {"coordinates":[48.80203,47.90365],"type":"Point"}
}