{
  "type": "Feature",
  "properties": {
    "gn:admin1_code":"4.0",
    "gn:asciiname":"Karachayevskiy",
    "gn:country_code":"KZ",
    "gn:dem":274,
    "gn:feature_class":"P",
    "gn:feature_code":"PPL",
    "gn:name":"Karachayevskiy",
    "gn:population":0,
    "gn:timezone":"Asia/Aqtobe",
    "iso:country":"KZ",
    "name:eng_x_preferred":[
        "Karachayevskiy"
    ],
    "name:rus_x_preferred":[
        "\u041a\u0430\u0440\u0430\u0447\u0430\u0435\u0432\u043a\u0430"
    ],
    "name:und_x_variant":[
        "Karagachevskiy",
        "Karachayevskiy"
    ],
    "wof:name":"Karachayevskiy",
    "wof:placetype":"locality"
},
  "geometry": {"coordinates":[56.83333,50.85],"type":"Point"}
}