{
  "type": "Feature",
  "properties": {
    "gn:admin1_code":"10.0",
    "gn:asciiname":"Uchastok Shestoy Gidrouzla",
    "gn:country_code":"KZ",
    "gn:dem":267,
    "gn:feature_class":"P",
    "gn:feature_code":"PPL",
    "gn:name":"Uchastok Shestoy Gidrouzla",
    "gn:population":0,
    "gn:timezone":"Asia/Almaty",
    "iso:country":"KZ",
    "name:rus_x_preferred":[
        "\u0423\u0447\u0430\u0441\u0442\u043e\u043a \u0428\u0435\u0441\u0442\u043e\u0439 \u0413\u0438\u0434\u0440\u043e\u0443\u0437\u043b\u0430"
    ],
    "wof:name":"Uchastok Shestoy Gidrouzla",
    "wof:placetype":"locality"
},
  "geometry": {"coordinates":[68.3626,40.7591],"type":"Point"}
}