{
  "type": "Feature",
  "properties": {
    "gn:admin1_code":"10.0",
    "gn:asciiname":"Urbulak",
    "gn:country_code":"KZ",
    "gn:dem":557,
    "gn:feature_class":"P",
    "gn:feature_code":"PPL",
    "gn:name":"Urbulak",
    "gn:population":0,
    "gn:timezone":"Asia/Almaty",
    "iso:country":"KZ",
    "name:rus_x_preferred":[
        "\u0423\u0440\u0431\u0443\u043b\u0430\u043a"
    ],
    "wof:name":"Urbulak",
    "wof:placetype":"locality"
},
  "geometry": {"coordinates":[70.09305000000001,42.58055],"type":"Point"}
}