{
  "type": "Feature",
  "properties": {
    "gn:admin1_code":"10.0",
    "gn:asciiname":"Tortkol",
    "gn:country_code":"KZ",
    "gn:dem":234,
    "gn:feature_class":"P",
    "gn:feature_code":"PPL",
    "gn:name":"T\u00f6rtk\u00f6l",
    "gn:population":0,
    "gn:timezone":"Asia/Almaty",
    "iso:country":"KZ",
    "name:kaz_x_preferred":[
        "\u0422\u04e9\u0440\u0442\u043a\u04e9\u043b"
    ],
    "name:rus_x_preferred":[
        "Tortkol\u2019"
    ],
    "name:rus_x_variant":[
        "\u0422\u043e\u0440\u0442\u043a\u043e\u043b\u044c"
    ],
    "name:und_x_variant":[
        "Tortkoll\u2019",
        "Tortkul\u2019",
        "T\u00f6rtk\u00f6l"
    ],
    "wof:name":"Tortkol",
    "wof:placetype":"locality"
},
  "geometry": {"coordinates":[68.94843,42.92973],"type":"Point"}
}