{
  "type": "Feature",
  "properties": {
    "gn:admin1_code":"11.0",
    "gn:asciiname":"Qarakol",
    "gn:country_code":"KZ",
    "gn:dem":107,
    "gn:feature_class":"P",
    "gn:feature_code":"PPL",
    "gn:name":"Qarak\u00f6l",
    "gn:population":0,
    "gn:timezone":"Asia/Almaty",
    "iso:country":"KZ",
    "name:kaz_x_preferred":[
        "Qarak\u00f6l"
    ],
    "name:kaz_x_variant":[
        "\u049a\u0430\u0440\u0430\u043a\u04e9\u043b"
    ],
    "name:rus_x_preferred":[
        "Karakol\u2019"
    ],
    "name:rus_x_variant":[
        "\u041a\u0430\u0440\u0430\u043a\u043e\u043b\u044c"
    ],
    "wof:name":"Qarakol",
    "wof:placetype":"locality"
},
  "geometry": {"coordinates":[76.68904000000001,52.43731999999999],"type":"Point"}
}