{
  "type": "Feature",
  "properties": {
    "gn:admin1_code":"11.0",
    "gn:asciiname":"Tselinnoye",
    "gn:country_code":"KZ",
    "gn:dem":137,
    "gn:feature_class":"P",
    "gn:feature_code":"PPL",
    "gn:name":"Tselinnoye",
    "gn:population":0,
    "gn:timezone":"Asia/Almaty",
    "iso:country":"KZ",
    "name:kaz_x_preferred":[
        "Tselinnoe"
    ],
    "name:kaz_x_variant":[
        "Tsel\u012bnnoe",
        "\u0426\u0435\u043b\u0438\u043d\u043d\u043e\u0435"
    ],
    "name:und_x_variant":[
        "Tselinnyy",
        "Tselinnoye"
    ],
    "wof:name":"Tselinnoye",
    "wof:placetype":"locality"
},
  "geometry": {"coordinates":[76.73727,51.63597],"type":"Point"}
}