{
  "type": "Feature",
  "properties": {
    "gn:admin1_code":"0.0",
    "gn:asciiname":"Svobodnyy",
    "gn:country_code":"KZ",
    "gn:dem":271,
    "gn:feature_class":"P",
    "gn:feature_code":"PPL",
    "gn:name":"Svobodnyy",
    "gn:population":0,
    "gn:timezone":"Asia/Qyzylorda",
    "iso:country":"KZ",
    "name:eng_x_preferred":[
        "Svobodnyy"
    ],
    "name:rus_x_preferred":[
        "\u0421\u0432\u043e\u0431\u043e\u0434\u043d\u044b\u0439"
    ],
    "wof:name":"Svobodnyy",
    "wof:placetype":"locality"
},
  "geometry": {"coordinates":[62.56267,51.63155],"type":"Point"}
}