{
  "type": "Feature",
  "properties": {
    "gn:admin1_code":"16.0",
    "gn:asciiname":"Chernozubovka",
    "gn:country_code":"KZ",
    "gn:dem":187,
    "gn:feature_class":"P",
    "gn:feature_code":"PPL",
    "gn:name":"Chernozubovka",
    "gn:population":0,
    "gn:timezone":"Asia/Almaty",
    "iso:country":"KZ",
    "name:eng_x_preferred":[
        "Chernoz\u016bbovka"
    ],
    "name:kaz_x_preferred":[
        "Chernoz\u016bbovka"
    ],
    "name:kaz_x_variant":[
        "\u0427\u0435\u0440\u043d\u043e\u0437\u0443\u0431\u043e\u0432\u043a\u0430"
    ],
    "name:rus_x_preferred":[
        "\u0427\u0435\u0440\u043d\u043e\u0437\u0443\u0431\u043e\u0432\u043a\u0430"
    ],
    "name:und_x_variant":[
        "Borovskoy",
        "Sovkhoz Borovskiy",
        "Sovkhoz Borovskoy"
    ],
    "wof:name":"Chernozubovka",
    "wof:placetype":"locality"
},
  "geometry": {"coordinates":[66.6297,52.69291],"type":"Point"}
}