{
  "type": "Feature",
  "properties": {
    "gn:admin1_code":"6.0",
    "gn:asciiname":"Kamal",
    "gn:country_code":"KZ",
    "gn:dem":-27,
    "gn:feature_class":"P",
    "gn:feature_code":"PPL",
    "gn:name":"Kamal",
    "gn:population":0,
    "gn:timezone":"Asia/Atyrau",
    "iso:country":"KZ",
    "wof:name":"Kamal",
    "wof:placetype":"locality"
},
  "geometry": {"coordinates":[48.975,46.59444000000001],"type":"Point"}
}