{
  "type": "Feature",
  "properties": {
    "gn:admin1_code":"10.0",
    "gn:asciiname":"Zhanaaryk",
    "gn:country_code":"KZ",
    "gn:dem":214,
    "gn:feature_class":"P",
    "gn:feature_code":"PPL",
    "gn:name":"Zhanaaryk",
    "gn:population":0,
    "gn:timezone":"Asia/Almaty",
    "iso:country":"KZ",
    "wof:name":"Zhanaaryk",
    "wof:placetype":"locality"
},
  "geometry": {"coordinates":[68.71666999999999,42.78333],"type":"Point"}
}