{
  "type": "Feature",
  "properties": {
    "gn:admin1_code":"16.0",
    "gn:asciiname":"Semipalatnoye",
    "gn:country_code":"KZ",
    "gn:dem":110,
    "gn:feature_class":"P",
    "gn:feature_code":"PPL",
    "gn:name":"Semipalatnoye",
    "gn:population":0,
    "gn:timezone":"Asia/Almaty",
    "iso:country":"KZ",
    "name:eng_x_preferred":[
        "Semipalatnoye"
    ],
    "name:kaz_x_preferred":[
        "Sem\u012bpalatnoe"
    ],
    "name:kaz_x_variant":[
        "\u0421\u0435\u043c\u0438\u043f\u0430\u043b\u0430\u0442\u043d\u043e\u0435"
    ],
    "name:rus_x_preferred":[
        "\u0421\u0435\u043c\u0438\u043f\u0430\u043b\u0430\u0442\u043d\u043e\u0435"
    ],
    "wof:name":"Semipalatnoye",
    "wof:placetype":"locality"
},
  "geometry": {"coordinates":[68.64654,54.44796],"type":"Point"}
}