{
  "type": "Feature",
  "properties": {
    "gn:admin1_code":"14.0",
    "gn:asciiname":"Kyzylabad",
    "gn:country_code":"KZ",
    "gn:dem":657,
    "gn:feature_class":"P",
    "gn:feature_code":"PPLF",
    "gn:name":"Kyzylabad",
    "gn:population":0,
    "gn:timezone":"Asia/Almaty",
    "iso:country":"KZ",
    "name:rus_x_preferred":[
        "\u041a\u044b\u0437\u044b\u043b\u0430\u0431\u0430\u0434"
    ],
    "wof:name":"Kyzylabad",
    "wof:placetype":"locality"
},
  "geometry": {"coordinates":[71.34168000000003,42.84408],"type":"Point"}
}