{
  "type": "Feature",
  "properties": {
    "gn:admin1_code":"1.0",
    "gn:asciiname":"Qyzylzhar",
    "gn:country_code":"KZ",
    "gn:dem":895,
    "gn:feature_class":"P",
    "gn:feature_code":"PPL",
    "gn:name":"Qyzylzhar",
    "gn:population":0,
    "gn:timezone":"Asia/Almaty",
    "iso:country":"KZ",
    "name:kaz_x_preferred":[
        "Qyzylzhar"
    ],
    "name:und_x_variant":[
        "Kizyl-Dzhar",
        "Kyzyl-Dzhar",
        "Kizyl-jar",
        "Kiz\u00f6l-jar",
        "Kyzylzhar"
    ],
    "wof:name":"Qyzylzhar",
    "wof:placetype":"locality"
},
  "geometry": {"coordinates":[78.13348000000001,44.43594],"type":"Point"}
}