{
  "type": "Feature",
  "properties": {
    "gn:admin1_code":"10.0",
    "gn:asciiname":"Pechinkhana",
    "gn:country_code":"KZ",
    "gn:dem":1817,
    "gn:feature_class":"P",
    "gn:feature_code":"PPL",
    "gn:name":"Pechinkhana",
    "gn:population":0,
    "gn:timezone":"Asia/Almaty",
    "iso:country":"KZ",
    "wof:name":"Pechinkhana",
    "wof:placetype":"locality"
},
  "geometry": {"coordinates":[69.96083,41.78611],"type":"Point"}
}