{
  "type": "Feature",
  "properties": {
    "gn:admin1_code":"6.0",
    "gn:asciiname":"Malaya Damba",
    "gn:country_code":"KZ",
    "gn:dem":-28,
    "gn:feature_class":"P",
    "gn:feature_code":"PPL",
    "gn:name":"Malaya Damba",
    "gn:population":0,
    "gn:timezone":"Asia/Atyrau",
    "iso:country":"KZ",
    "name:rus_x_preferred":[
        "\u0411\u0430\u0437\u0430 \u0421\u0435\u0432\u0435\u0440\u043e-\u041a\u0430\u0441\u043f\u0438\u0439\u0441\u043a\u043e\u0439 \u041b\u0438\u043a\u0432\u0438\u0434\u0430\u0446\u0438\u0438 \u0421\u043b\u0443\u0447\u0430\u0439\u043d\u044b\u0445 \u0420\u0430\u0437\u043b\u0438\u0432\u043e\u0432 \u041d\u0435\u0444\u0442\u0438"
    ],
    "name:und_x_variant":[
        "Baza Severo-Kaspiyskoy Likvidatsii Sluchaynykh Razlivov Nefti"
    ],
    "wof:name":"Malaya Damba",
    "wof:placetype":"locality"
},
  "geometry": {"coordinates":[51.71667,46.91667],"type":"Point"}
}