{
  "type": "Feature",
  "properties": {
    "gn:admin1_code":"0.0",
    "gn:asciiname":"Baytles",
    "gn:country_code":"KZ",
    "gn:dem":658,
    "gn:feature_class":"P",
    "gn:feature_code":"PPL",
    "gn:name":"Baytles",
    "gn:population":0,
    "gn:timezone":"Asia/Almaty",
    "iso:country":"KZ",
    "wof:name":"Baytles",
    "wof:placetype":"locality"
},
  "geometry": {"coordinates":[76.66667,43.41667],"type":"Point"}
}