{
  "type": "Feature",
  "properties": {
    "gn:admin1_code":"11.0",
    "gn:asciiname":"Paramonovka Staraya",
    "gn:country_code":"KZ",
    "gn:dem":127,
    "gn:feature_class":"P",
    "gn:feature_code":"PPL",
    "gn:name":"Paramonovka Staraya",
    "gn:population":0,
    "gn:timezone":"Asia/Almaty",
    "iso:country":"KZ",
    "name:eng_x_preferred":[
        "Paramonovka"
    ],
    "name:kaz_x_preferred":[
        "Paramonovka Staraya"
    ],
    "name:kaz_x_variant":[
        "\u041f\u0430\u0440\u0430\u043c\u043e\u043d\u043e\u0432\u043a\u0430 \u0421\u0442\u0430\u0440\u0430\u044f"
    ],
    "name:rus_x_preferred":[
        "\u041f\u0430\u0440\u0430\u043c\u043e\u043d\u043e\u0432\u043a\u0430"
    ],
    "wof:name":"Paramonovka Staraya",
    "wof:placetype":"locality"
},
  "geometry": {"coordinates":[76.14719000000002,52.06271],"type":"Point"}
}