{
  "type": "Feature",
  "properties": {
    "gn:admin1_code":"16.0",
    "gn:asciiname":"Sarytubek",
    "gn:country_code":"KZ",
    "gn:dem":265,
    "gn:feature_class":"P",
    "gn:feature_code":"PPL",
    "gn:name":"Sarytubek",
    "gn:population":0,
    "gn:timezone":"Asia/Almaty",
    "iso:country":"KZ",
    "name:rus_x_preferred":[
        "\u0421\u0430\u0440\u044b\u0442\u0443\u0431\u0435\u043a"
    ],
    "name:rus_x_variant":[
        "\u0410\u043a\u043c\u0430\u043b\u044b\u0448"
    ],
    "name:und_x_variant":[
        "Akmalysh",
        "Sarytyubek",
        "Sarytubek"
    ],
    "wof:name":"Sarytubek",
    "wof:placetype":"locality"
},
  "geometry": {"coordinates":[67.94479,53.20205],"type":"Point"}
}