{
  "type": "Feature",
  "properties": {
    "gn:admin1_code":"0.0",
    "gn:asciiname":"Noven'kiy",
    "gn:country_code":"KZ",
    "gn:dem":42,
    "gn:feature_class":"P",
    "gn:feature_code":"PPL",
    "gn:name":"Noven\u2019kiy",
    "gn:population":0,
    "gn:timezone":"Asia/Oral",
    "iso:country":"KZ",
    "wof:name":"Noven'kiy",
    "wof:placetype":"locality"
},
  "geometry": {"coordinates":[51.88333,51.46667],"type":"Point"}
}