{
  "type": "Feature",
  "properties": {
    "gn:admin1_code":"17.0",
    "gn:asciiname":"Qyrghyzstan",
    "gn:country_code":"KZ",
    "gn:dem":1022,
    "gn:feature_class":"P",
    "gn:feature_code":"PPL",
    "gn:name":"Qyrghyzstan",
    "gn:population":0,
    "gn:timezone":"Asia/Almaty",
    "iso:country":"KZ",
    "name:kaz_x_preferred":[
        "Qyrghyzstan"
    ],
    "name:kaz_x_variant":[
        "\u049a\u044b\u0440\u0493\u044b\u0437\u0441\u0442\u0430\u043d"
    ],
    "name:run_x_preferred":[
        "\u0411\u0435\u043b\u044c"
    ],
    "name:rus_x_preferred":[
        "Bel\u2019"
    ],
    "wof:name":"Qyrghyzstan",
    "wof:placetype":"locality"
},
  "geometry": {"coordinates":[74.69275999999998,43.74377],"type":"Point"}
}