{
  "type": "Feature",
  "properties": {
    "gn:admin1_code":"0.0",
    "gn:asciiname":"Aleksandrovka",
    "gn:country_code":"KZ",
    "gn:dem":837,
    "gn:feature_class":"P",
    "gn:feature_code":"PPL",
    "gn:name":"Aleksandrovka",
    "gn:population":0,
    "gn:timezone":"Asia/Almaty",
    "iso:country":"KZ",
    "wof:name":"Aleksandrovka",
    "wof:placetype":"locality"
},
  "geometry": {"coordinates":[83.15748000000001,49.09307],"type":"Point"}
}