{
  "type": "Feature",
  "properties": {
    "gn:admin1_code":"12.0",
    "gn:asciiname":"Burbaza",
    "gn:country_code":"KZ",
    "gn:dem":658,
    "gn:feature_class":"P",
    "gn:feature_code":"PPL",
    "gn:name":"Burbaza",
    "gn:population":0,
    "gn:timezone":"Asia/Almaty",
    "iso:country":"KZ",
    "wof:name":"Burbaza",
    "wof:placetype":"locality"
},
  "geometry": {"coordinates":[73.53319,49.35084000000001],"type":"Point"}
}