{
  "type": "Feature",
  "properties": {
    "gn:admin1_code":"3.0",
    "gn:asciiname":"Viktorovka",
    "gn:country_code":"KZ",
    "gn:dem":437,
    "gn:feature_class":"P",
    "gn:feature_code":"PPL",
    "gn:name":"Viktorovka",
    "gn:population":0,
    "gn:timezone":"Asia/Almaty",
    "iso:country":"KZ",
    "name:kaz_x_preferred":[
        "V\u012bktorovka"
    ],
    "name:kaz_x_variant":[
        "\u0412\u0438\u043a\u0442\u043e\u0440\u043e\u0432\u043a\u0430"
    ],
    "wof:name":"Viktorovka",
    "wof:placetype":"locality"
},
  "geometry": {"coordinates":[69.11612,52.75574],"type":"Point"}
}