{
  "type": "Feature",
  "properties": {
    "gn:admin1_code":"13.0",
    "gn:asciiname":"Shevchenkovka",
    "gn:country_code":"KZ",
    "gn:dem":328,
    "gn:feature_class":"P",
    "gn:feature_code":"PPL",
    "gn:name":"Shevchenkovka",
    "gn:population":0,
    "gn:timezone":"Asia/Qyzylorda",
    "iso:country":"KZ",
    "name:eng_x_preferred":[
        "Shevchenkovka"
    ],
    "name:rus_x_preferred":[
        "\u0428\u0435\u0432\u0447\u0435\u043d\u043a\u043e\u0432\u043a\u0430"
    ],
    "name:und_x_variant":[
        "Shevchenkovskiy",
        "Shevchenkovski",
        "Shevchenovka",
        "Shevchenkovka"
    ],
    "wof:name":"Shevchenkovka",
    "wof:placetype":"locality"
},
  "geometry": {"coordinates":[60.81181,51.92218],"type":"Point"}
}