{
  "type": "Feature",
  "properties": {
    "gn:admin1_code":"0.0",
    "gn:asciiname":"Borly",
    "gn:country_code":"KZ",
    "gn:dem":347,
    "gn:feature_class":"P",
    "gn:feature_code":"PPL",
    "gn:name":"Borly",
    "gn:population":0,
    "gn:timezone":"Asia/Almaty",
    "iso:country":"KZ",
    "name:eng_x_preferred":[
        "Borly"
    ],
    "name:rus_x_preferred":[
        "\u0410\u0440\u043a\u0430\u043b\u044b\u043a"
    ],
    "name:und_x_variant":[
        "Piket Arkalyskiy",
        "Arkalyskiy",
        "Arkalyk",
        "Borly"
    ],
    "wof:name":"Borly",
    "wof:placetype":"locality"
},
  "geometry": {"coordinates":[80.32212,49.97719],"type":"Point"}
}