{
  "type": "Feature",
  "properties": {
    "gn:admin1_code":"12.0",
    "gn:asciiname":"Qaraqogha",
    "gn:country_code":"KZ",
    "gn:dem":492,
    "gn:feature_class":"P",
    "gn:feature_code":"PPL",
    "gn:name":"Qaraqogha",
    "gn:population":0,
    "gn:timezone":"Asia/Almaty",
    "iso:country":"KZ",
    "name:kaz_x_preferred":[
        "Qaraqogha"
    ],
    "name:kaz_x_variant":[
        "\u049a\u0430\u0440\u0430\u049b\u043e\u0493\u0430"
    ],
    "name:rus_x_preferred":[
        "\u041a\u0430\u0440\u0430\u043a\u043e\u0433\u0430"
    ],
    "name:und_x_variant":[
        "Karagocha Pervaya",
        "Karakoga Pervaya",
        "Karakoga"
    ],
    "wof:name":"Qaraqogha",
    "wof:placetype":"locality"
},
  "geometry": {"coordinates":[72.55,49.63333],"type":"Point"}
}