{
  "type": "Feature",
  "properties": {
    "gn:admin1_code":"16.0",
    "gn:asciiname":"Kondratovka",
    "gn:country_code":"KZ",
    "gn:dem":130,
    "gn:feature_class":"P",
    "gn:feature_code":"PPL",
    "gn:name":"Kondratovka",
    "gn:population":0,
    "gn:timezone":"Asia/Almaty",
    "iso:country":"KZ",
    "name:rus_x_preferred":[
        "\u041a\u043e\u043d\u0434\u0440\u0430\u0442\u043e\u0432\u043a\u0430"
    ],
    "wof:name":"Kondratovka",
    "wof:placetype":"locality"
},
  "geometry": {"coordinates":[68.81383000000001,54.88653000000001],"type":"Point"}
}