{
  "type": "Feature",
  "properties": {
    "gn:admin1_code":"0.0",
    "gn:asciiname":"Staraya Shul'ba",
    "gn:country_code":"KZ",
    "gn:dem":241,
    "gn:feature_class":"P",
    "gn:feature_code":"PPL",
    "gn:name":"Staraya Shul\u2019ba",
    "gn:population":0,
    "gn:timezone":"Asia/Almaty",
    "iso:country":"KZ",
    "name:eng_x_preferred":[
        "Staraya Shul'ba"
    ],
    "name:rus_x_preferred":[
        "\u0421\u0442\u0430\u0440.\u0428\u0443\u043b\u044c\u0431\u0430"
    ],
    "name:und_x_variant":[
        "Shul\u2019ba",
        "Shul\u2019binskiy",
        "Staraya Shul\u2019ba"
    ],
    "wof:name":"Staraya Shul'ba",
    "wof:placetype":"locality"
},
  "geometry": {"coordinates":[81.13755999999999,50.38746],"type":"Point"}
}