{
  "type": "Feature",
  "properties": {
    "gn:admin1_code":"0.0",
    "gn:asciiname":"Gurbchen'",
    "gn:country_code":"KZ",
    "gn:dem":-15,
    "gn:feature_class":"P",
    "gn:feature_code":"PPL",
    "gn:name":"Gurbchen\u2019",
    "gn:population":0,
    "gn:timezone":"Asia/Oral",
    "iso:country":"KZ",
    "name:und_x_variant":[
        "Gurbshchen",
        "Gurbchen\u2019"
    ],
    "wof:name":"Gurbchen'",
    "wof:placetype":"locality"
},
  "geometry": {"coordinates":[48.15,48.23333],"type":"Point"}
}