{
  "type": "Feature",
  "properties": {
    "gn:admin1_code":"16.0",
    "gn:asciiname":"Ryazanka",
    "gn:country_code":"KZ",
    "gn:dem":132,
    "gn:feature_class":"P",
    "gn:feature_code":"PPL",
    "gn:name":"Ryazanka",
    "gn:population":0,
    "gn:timezone":"Asia/Almaty",
    "iso:country":"KZ",
    "name:rus_x_preferred":[
        "\u0420\u044f\u0437\u0430\u043d\u043a\u0430"
    ],
    "wof:name":"Ryazanka",
    "wof:placetype":"locality"
},
  "geometry": {"coordinates":[70.38875999999998,55.18018000000001],"type":"Point"}
}