{
  "type": "Feature",
  "properties": {
    "gn:admin1_code":"16.0",
    "gn:asciiname":"Shalkar",
    "gn:country_code":"KZ",
    "gn:dem":324,
    "gn:feature_class":"P",
    "gn:feature_code":"PPL",
    "gn:name":"Shalkar",
    "gn:population":0,
    "gn:timezone":"Asia/Almaty",
    "iso:country":"KZ",
    "name:deu_x_preferred":[
        "Schalqar"
    ],
    "name:eng_x_preferred":[
        "Shalqar"
    ],
    "name:fra_x_preferred":[
        "Chalkar"
    ],
    "name:hsb_x_preferred":[
        "\u0160alkar"
    ],
    "name:kaz_x_preferred":[
        "Shalqar"
    ],
    "name:kaz_x_variant":[
        "\u0428\u0430\u043b\u049b\u0430\u0440"
    ],
    "name:lit_x_preferred":[
        "\u0160alkaras"
    ],
    "name:msa_x_preferred":[
        "Shalkar"
    ],
    "name:pol_x_preferred":[
        "Sza\u0142kar"
    ],
    "name:rus_x_preferred":[
        "\u0428\u0430\u043b\u043a\u0430\u0440"
    ],
    "name:tat_x_preferred":[
        "\u0427\u0430\u043b\u043a\u0430\u0440"
    ],
    "name:ukr_x_preferred":[
        "\u0428\u0430\u043b\u043a\u0430\u0440"
    ],
    "name:und_x_variant":[
        "Chalkar",
        "Shalkar",
        "Chelkarskiy",
        "Shalkarskiy"
    ],
    "name:zho_x_preferred":[
        "\u6c99\u723e\u5361\u723e"
    ],
    "wof:name":"Shalkar",
    "wof:placetype":"locality"
},
  "geometry": {"coordinates":[68.51529000000001,53.17567],"type":"Point"}
}