{
  "type": "Feature",
  "properties": {
    "gn:admin1_code":"13.0",
    "gn:asciiname":"Tyuntyugur",
    "gn:country_code":"KZ",
    "gn:dem":255,
    "gn:feature_class":"P",
    "gn:feature_code":"PPL",
    "gn:name":"Tyuntyugur",
    "gn:population":0,
    "gn:timezone":"Asia/Almaty",
    "iso:country":"KZ",
    "name:kaz_x_preferred":[
        "Timt\u00fcyir"
    ],
    "name:kaz_x_variant":[
        "\u0422\u0456\u043c\u0442\u04af\u0439\u0456\u0440"
    ],
    "name:rus_x_preferred":[
        "\u0422\u044e\u043d\u0442\u044e\u0433\u0443\u0440"
    ],
    "wof:name":"Tyuntyugur",
    "wof:placetype":"locality"
},
  "geometry": {"coordinates":[65.4474,52.18392],"type":"Point"}
}