{
  "type": "Feature",
  "properties": {
    "gn:admin1_code":"0.0",
    "gn:asciiname":"Zhulandy",
    "gn:country_code":"KZ",
    "gn:dem":401,
    "gn:feature_class":"P",
    "gn:feature_code":"PPL",
    "gn:name":"Zhulandy",
    "gn:population":0,
    "gn:timezone":"Asia/Almaty",
    "iso:country":"KZ",
    "wof:name":"Zhulandy",
    "wof:placetype":"locality"
},
  "geometry": {"coordinates":[82.1071,46.04519000000001],"type":"Point"}
}