{
  "type": "Feature",
  "properties": {
    "gn:admin1_code":"1.0",
    "gn:asciiname":"Ekpindi",
    "gn:country_code":"KZ",
    "gn:dem":728,
    "gn:feature_class":"P",
    "gn:feature_code":"PPL",
    "gn:name":"Ekpindi",
    "gn:population":0,
    "gn:timezone":"Asia/Almaty",
    "iso:country":"KZ",
    "name:und_x_variant":[
        "Yekpindy",
        "Ekpindi"
    ],
    "wof:name":"Ekpindi",
    "wof:placetype":"locality"
},
  "geometry": {"coordinates":[80.62687,45.74004],"type":"Point"}
}