{
  "type": "Feature",
  "properties": {
    "gn:admin1_code":"15.0",
    "gn:asciiname":"Koktal",
    "gn:country_code":"KZ",
    "gn:dem":359,
    "gn:feature_class":"P",
    "gn:feature_code":"PPL",
    "gn:name":"K\u00f6ktal",
    "gn:population":0,
    "gn:timezone":"Asia/Almaty",
    "iso:country":"KZ",
    "name:ceb_x_preferred":[
        "Koktal"
    ],
    "name:che_x_preferred":[
        "\u041a\u043e\u043a\u0442\u0430\u043b"
    ],
    "name:ell_x_preferred":[
        "\u039a\u03bf\u03ba\u03c4\u03ac\u03bb"
    ],
    "name:kaz_x_preferred":[
        "K\u00f6ktal"
    ],
    "name:kaz_x_variant":[
        "\u041a\u04e9\u043a\u0442\u0430\u043b"
    ],
    "name:msa_x_preferred":[
        "Koktal"
    ],
    "name:rus_x_preferred":[
        "\u041a\u043e\u043a\u0442\u0430\u043b"
    ],
    "name:swe_x_preferred":[
        "Koktal"
    ],
    "name:ukr_x_preferred":[
        "\u041a\u043e\u043a\u0442\u0430\u043b"
    ],
    "wof:name":"Koktal",
    "wof:placetype":"locality"
},
  "geometry": {"coordinates":[81.84747,46.45807],"type":"Point"}
}