{
  "type": "Feature",
  "properties": {
    "gn:admin1_code":"10.0",
    "gn:asciiname":"Taldybulak",
    "gn:country_code":"KZ",
    "gn:dem":672,
    "gn:feature_class":"P",
    "gn:feature_code":"PPL",
    "gn:name":"Taldybulak",
    "gn:population":0,
    "gn:timezone":"Asia/Almaty",
    "iso:country":"KZ",
    "name:rus_x_preferred":[
        "\u0422\u0430\u043b\u0434\u044b\u0431\u0443\u043b\u0430\u043a"
    ],
    "wof:name":"Taldybulak",
    "wof:placetype":"locality"
},
  "geometry": {"coordinates":[69.38121,41.89032],"type":"Point"}
}