{
  "type": "Feature",
  "properties": {
    "gn:admin1_code":"3.0",
    "gn:asciiname":"Zhambay",
    "gn:country_code":"KZ",
    "gn:dem":231,
    "gn:feature_class":"P",
    "gn:feature_code":"PPL",
    "gn:name":"Zhambay",
    "gn:population":0,
    "gn:timezone":"Asia/Almaty",
    "iso:country":"KZ",
    "name:kaz_x_preferred":[
        "Zhambay"
    ],
    "name:kaz_x_variant":[
        "\u0416\u0430\u043c\u0431\u0430\u0439"
    ],
    "name:rus_x_preferred":[
        "\u0417\u0438\u043c\u043e\u0432\u043a\u0430 \u0416\u0435\u043c\u0431\u0430\u0439"
    ],
    "name:und_x_variant":[
        "Zimovka Zhembay"
    ],
    "wof:name":"Zhambay",
    "wof:placetype":"locality"
},
  "geometry": {"coordinates":[71.89782,52.67907],"type":"Point"}
}