{
  "type": "Feature",
  "properties": {
    "gn:admin1_code":"16.0",
    "gn:asciiname":"Astrakhanka",
    "gn:country_code":"KZ",
    "gn:dem":137,
    "gn:feature_class":"P",
    "gn:feature_code":"PPL",
    "gn:name":"Astrakhanka",
    "gn:population":0,
    "gn:timezone":"Asia/Almaty",
    "iso:country":"KZ",
    "name:ceb_x_preferred":[
        "Astrakhanka"
    ],
    "name:eng_x_preferred":[
        "Astrakhanka"
    ],
    "name:kaz_x_preferred":[
        "Astrakhanka"
    ],
    "name:kaz_x_variant":[
        "\u0410\u0441\u0442\u0440\u0430\u0445\u0430\u043d\u043a\u0430"
    ],
    "name:rus_x_preferred":[
        "\u0410\u0441\u0442\u0440\u0430\u0445\u0430\u043d\u043a\u0430"
    ],
    "name:swe_x_preferred":[
        "Astrakhanka"
    ],
    "name:und_x_variant":[
        "Astrankhanskoye"
    ],
    "wof:name":"Astrakhanka",
    "wof:placetype":"locality"
},
  "geometry": {"coordinates":[69.23232,54.51123000000001],"type":"Point"}
}