{
  "type": "Feature",
  "properties": {
    "gn:admin1_code":"4.0",
    "gn:asciiname":"Kuznetsovskoye",
    "gn:cc2":"KZ",
    "gn:country_code":"KZ",
    "gn:dem":248,
    "gn:feature_class":"P",
    "gn:feature_code":"PPL",
    "gn:name":"Kuznetsovskoye",
    "gn:population":0,
    "gn:timezone":"Asia/Aqtobe",
    "iso:country":"KZ",
    "name:eng_x_preferred":[
        "Kuznetsovskoye"
    ],
    "name:rus_x_preferred":[
        "\u041a\u0443\u0437\u043d\u0435\u0446\u043e\u0432\u0441\u043a\u043e\u0435"
    ],
    "name:und_x_variant":[
        "Kuznetsovskiy",
        "Kuznetsovskoye"
    ],
    "wof:name":"Kuznetsovskoye",
    "wof:placetype":"locality"
},
  "geometry": {"coordinates":[57.61333000000001,49.13278],"type":"Point"}
}