{
  "type": "Feature",
  "properties": {
    "gn:admin1_code":"0.0",
    "gn:asciiname":"Koktobe",
    "gn:country_code":"KZ",
    "gn:dem":731,
    "gn:feature_class":"P",
    "gn:feature_code":"PPL",
    "gn:name":"Koktobe",
    "gn:population":0,
    "gn:timezone":"Asia/Almaty",
    "iso:country":"KZ",
    "wof:name":"Koktobe",
    "wof:placetype":"locality"
},
  "geometry": {"coordinates":[81.99585999999999,47.91108],"type":"Point"}
}