{
  "type": "Feature",
  "properties": {
    "gn:admin1_code":"15.0",
    "gn:asciiname":"Novaya Ul'binka",
    "gn:country_code":"KZ",
    "gn:dem":359,
    "gn:feature_class":"P",
    "gn:feature_code":"PPL",
    "gn:name":"Novaya \u016al\u2019b\u012bnka",
    "gn:population":0,
    "gn:timezone":"Asia/Almaty",
    "iso:country":"KZ",
    "name:kaz_x_preferred":[
        "Novaya \u016al\u2019b\u012bnka"
    ],
    "name:kaz_x_variant":[
        "\u041d\u043e\u0432\u0430\u044f \u0423\u043b\u044c\u0431\u0438\u043d\u043a\u0430"
    ],
    "name:rus_x_preferred":[
        "Novaya Ul\u2019binka"
    ],
    "wof:name":"Novaya Ul'binka",
    "wof:placetype":"locality"
},
  "geometry": {"coordinates":[82.86933000000001,50.02461],"type":"Point"}
}