{
  "type": "Feature",
  "properties": {
    "gn:admin1_code":"16.0",
    "gn:asciiname":"Burumbay",
    "gn:country_code":"KZ",
    "gn:dem":92,
    "gn:feature_class":"P",
    "gn:feature_code":"PPL",
    "gn:name":"Burumbay",
    "gn:population":0,
    "gn:timezone":"Asia/Almaty",
    "iso:country":"KZ",
    "wof:name":"Burumbay",
    "wof:placetype":"locality"
},
  "geometry": {"coordinates":[71.90000000000001,54.16667],"type":"Point"}
}