{
  "type": "Feature",
  "properties": {
    "gn:admin1_code":"13.0",
    "gn:asciiname":"Stepnoy",
    "gn:country_code":"KZ",
    "gn:dem":236,
    "gn:feature_class":"P",
    "gn:feature_code":"PPL",
    "gn:name":"Stepnoy",
    "gn:population":0,
    "gn:timezone":"Asia/Almaty",
    "iso:country":"KZ",
    "name:kaz_x_preferred":[
        "\u0421\u0442\u0435\u043f\u043d\u043e\u0439"
    ],
    "name:und_x_variant":[
        "Iskra",
        "Stepnoy"
    ],
    "wof:name":"Stepnoy",
    "wof:placetype":"locality"
},
  "geometry": {"coordinates":[65.36516999999999,52.28862],"type":"Point"}
}