{
  "type": "Feature",
  "properties": {
    "gn:admin1_code":"3.0",
    "gn:asciiname":"Krasnyy May",
    "gn:country_code":"KZ",
    "gn:dem":346,
    "gn:feature_class":"P",
    "gn:feature_code":"PPL",
    "gn:name":"Krasnyy May",
    "gn:population":0,
    "gn:timezone":"Asia/Almaty",
    "iso:country":"KZ",
    "name:rus_x_preferred":[
        "\u041a\u0440\u0430\u0441\u043d\u044b\u0439 \u041c\u0430\u0439"
    ],
    "name:rus_x_variant":[
        "\u041b\u0435\u0431\u0435\u0434\u0435\u0432\u043a\u0430"
    ],
    "name:und_x_variant":[
        "Lebedevka"
    ],
    "wof:name":"Krasnyy May",
    "wof:placetype":"locality"
},
  "geometry": {"coordinates":[70.80717,52.19155],"type":"Point"}
}