{
  "type": "Feature",
  "properties": {
    "gn:admin1_code":"14.0",
    "gn:asciiname":"Koszhar",
    "gn:country_code":"KZ",
    "gn:dem":55,
    "gn:feature_class":"P",
    "gn:feature_code":"PPL",
    "gn:name":"Koszhar",
    "gn:population":0,
    "gn:timezone":"Asia/Qyzylorda",
    "iso:country":"KZ",
    "name:kaz_x_preferred":[
        "Qoszhar"
    ],
    "name:kaz_x_variant":[
        "\u049a\u043e\u0441\u0436\u0430\u0440"
    ],
    "name:und_x_variant":[
        "Kutzhar",
        "Koszhar"
    ],
    "wof:name":"Koszhar",
    "wof:placetype":"locality"
},
  "geometry": {"coordinates":[61.78333000000001,46.16667],"type":"Point"}
}