{
  "type": "Feature",
  "properties": {
    "gn:admin1_code":"15.0",
    "gn:asciiname":"Beryozovskoe",
    "gn:country_code":"KZ",
    "gn:dem":493,
    "gn:feature_class":"P",
    "gn:feature_code":"PPL",
    "gn:name":"Beryozovskoe",
    "gn:population":0,
    "gn:timezone":"Asia/Almaty",
    "iso:country":"KZ",
    "name:kaz_x_preferred":[
        "Beryozovskoe"
    ],
    "name:kaz_x_variant":[
        "\u0411\u0435\u0440\u0451\u0437\u043e\u0432\u0441\u043a\u043e\u0435"
    ],
    "name:rus_x_preferred":[
        "Ber\u00ebzovka"
    ],
    "name:rus_x_variant":[
        "\u0411\u0435\u0440\u0451\u0437\u043e\u0432\u043a\u0430"
    ],
    "wof:name":"Beryozovskoe",
    "wof:placetype":"locality"
},
  "geometry": {"coordinates":[84.23483,49.7106],"type":"Point"}
}