{
  "type": "Feature",
  "properties": {
    "gn:admin1_code":"17.0",
    "gn:asciiname":"Zhanakonys",
    "gn:country_code":"KZ",
    "gn:dem":406,
    "gn:feature_class":"P",
    "gn:feature_code":"PPL",
    "gn:name":"Zhanakonys",
    "gn:population":0,
    "gn:timezone":"Asia/Almaty",
    "iso:country":"KZ",
    "name:rus_x_preferred":[
        "\u0416\u0430\u043d\u0430\u043a\u043e\u043d\u044b\u0441"
    ],
    "wof:name":"Zhanakonys",
    "wof:placetype":"locality"
},
  "geometry": {"coordinates":[71.30714,43.61144],"type":"Point"}
}