{
  "type": "Feature",
  "properties": {
    "gn:admin1_code":"10.0",
    "gn:asciiname":"Oymaut",
    "gn:country_code":"KZ",
    "gn:dem":360,
    "gn:feature_class":"P",
    "gn:feature_code":"PPL",
    "gn:name":"Oymaut",
    "gn:population":0,
    "gn:timezone":"Asia/Almaty",
    "iso:country":"KZ",
    "name:rus_x_preferred":[
        "\u041e\u0439\u043c\u0430\u0443\u0442"
    ],
    "name:rus_x_variant":[
        "Kyzyloktyabr\u2019",
        "\u041a\u044b\u0437\u044b\u043b\u043e\u043a\u0442\u044f\u0431\u0440\u044c"
    ],
    "wof:name":"Oymaut",
    "wof:placetype":"locality"
},
  "geometry": {"coordinates":[69.54609000000001,42.61495],"type":"Point"}
}