{
  "type": "Feature",
  "properties": {
    "gn:admin1_code":"0.0",
    "gn:asciiname":"Andreyevka",
    "gn:country_code":"KZ",
    "gn:dem":2223,
    "gn:feature_class":"P",
    "gn:feature_code":"PPL",
    "gn:name":"Andreyevka",
    "gn:population":0,
    "gn:timezone":"Asia/Urumqi",
    "iso:country":"KZ",
    "wof:name":"Andreyevka",
    "wof:placetype":"locality"
},
  "geometry": {"coordinates":[80.31667,44.95],"type":"Point"}
}