{
  "type": "Feature",
  "properties": {
    "gn:admin1_code":"13.0",
    "gn:asciiname":"Altybay",
    "gn:cc2":"KZ",
    "gn:country_code":"KZ",
    "gn:dem":126,
    "gn:feature_class":"P",
    "gn:feature_code":"PPL",
    "gn:name":"Altybay",
    "gn:population":0,
    "gn:timezone":"Asia/Almaty",
    "iso:country":"KZ",
    "name:eng_x_preferred":[
        "Altybay"
    ],
    "name:rus_x_preferred":[
        "\u0410\u043b\u0442\u044b\u0431\u0430\u0439"
    ],
    "name:und_x_variant":[
        "Altynbay",
        "Altybay"
    ],
    "wof:name":"Altybay",
    "wof:placetype":"locality"
},
  "geometry": {"coordinates":[64.27639000000001,49.14444],"type":"Point"}
}