{
  "type": "Feature",
  "properties": {
    "gn:admin1_code":"0.0",
    "gn:asciiname":"Kense-Basy",
    "gn:country_code":"KZ",
    "gn:dem":36,
    "gn:feature_class":"P",
    "gn:feature_code":"PPL",
    "gn:name":"Kense-Basy",
    "gn:population":0,
    "gn:timezone":"Asia/Oral",
    "iso:country":"KZ",
    "wof:name":"Kense-Basy",
    "wof:placetype":"locality"
},
  "geometry": {"coordinates":[47.41667,49.28333],"type":"Point"}
}