{
  "type": "Feature",
  "properties": {
    "gn:admin1_code":"0.0",
    "gn:asciiname":"Kyzbel'",
    "gn:country_code":"KZ",
    "gn:dem":142,
    "gn:feature_class":"P",
    "gn:feature_code":"PPL",
    "gn:name":"Kyzbel\u2019",
    "gn:population":0,
    "gn:timezone":"Asia/Qyzylorda",
    "iso:country":"KZ",
    "name:und_x_variant":[
        "Kizbel",
        "Kyzbel\u2019"
    ],
    "wof:name":"Kyzbel'",
    "wof:placetype":"locality"
},
  "geometry": {"coordinates":[64.31667,51.08333],"type":"Point"}
}