{
  "type": "Feature",
  "properties": {
    "gn:admin1_code":"16.0",
    "gn:asciiname":"Kurleut",
    "gn:country_code":"KZ",
    "gn:dem":121,
    "gn:feature_class":"P",
    "gn:feature_code":"PPL",
    "gn:name":"Kurleut",
    "gn:population":0,
    "gn:timezone":"Asia/Almaty",
    "iso:country":"KZ",
    "name:eng_x_preferred":[
        "Kurleut"
    ],
    "name:kaz_x_preferred":[
        "K\u00fcrle\u016bit"
    ],
    "name:kaz_x_variant":[
        "\u041a\u04af\u0440\u043b\u0435\u0443\u0456\u0442",
        "K\u00fcrle\u016bt",
        "\u041a\u04af\u0440\u043b\u0435\u0443\u0442"
    ],
    "name:rus_x_preferred":[
        "\u041a\u0443\u0440\u043b\u0435\u0443\u0442"
    ],
    "wof:name":"Kurleut",
    "wof:placetype":"locality"
},
  "geometry": {"coordinates":[73.65709,53.92211999999999],"type":"Point"}
}