{
  "type": "Feature",
  "properties": {
    "gn:admin1_code":"0.0",
    "gn:asciiname":"Kyzylshilik",
    "gn:country_code":"KZ",
    "gn:dem":275,
    "gn:feature_class":"P",
    "gn:feature_code":"PPL",
    "gn:name":"Kyzylshilik",
    "gn:population":0,
    "gn:timezone":"Asia/Almaty",
    "iso:country":"KZ",
    "name:eng_x_preferred":[
        "Kyzylshilik"
    ],
    "name:rus_x_preferred":[
        "\u041a\u044b\u0437\u044b\u043b-\u0427\u0438\u043b\u0438\u043a"
    ],
    "name:und_x_variant":[
        "Kizyl-Chilik",
        "Kzyl-Shilik",
        "Kyzylshilik"
    ],
    "wof:name":"Kyzylshilik",
    "wof:placetype":"locality"
},
  "geometry": {"coordinates":[81.00693000000003,50.05308],"type":"Point"}
}