{
  "type": "Feature",
  "properties": {
    "gn:admin1_code":"13.0",
    "gn:asciiname":"Lesnoy",
    "gn:country_code":"KZ",
    "gn:dem":177,
    "gn:feature_class":"P",
    "gn:feature_code":"PPL",
    "gn:name":"Lesnoy",
    "gn:population":0,
    "gn:timezone":"Asia/Qyzylorda",
    "iso:country":"KZ",
    "name:kaz_x_preferred":[
        "Lesnoy"
    ],
    "name:kaz_x_variant":[
        "\u041b\u0435\u0441\u043d\u043e\u0439"
    ],
    "wof:name":"Lesnoy",
    "wof:placetype":"locality"
},
  "geometry": {"coordinates":[64.26942,53.76439],"type":"Point"}
}