{
  "type": "Feature",
  "properties": {
    "gn:admin1_code":"16.0",
    "gn:asciiname":"Malosergeyevka",
    "gn:country_code":"KZ",
    "gn:dem":332,
    "gn:feature_class":"P",
    "gn:feature_code":"PPL",
    "gn:name":"Malosergeyevka",
    "gn:population":0,
    "gn:timezone":"Asia/Almaty",
    "iso:country":"KZ",
    "name:eng_x_preferred":[
        "Malosergeyevka"
    ],
    "name:kaz_x_preferred":[
        "Malosergeevka"
    ],
    "name:kaz_x_variant":[
        "\u041c\u0430\u043b\u043e\u0441\u0435\u0440\u0433\u0435\u0435\u0432\u043a\u0430"
    ],
    "name:rus_x_preferred":[
        "\u041c\u0430\u043b\u043e\u0441\u0435\u0440\u0433\u0435\u0435\u0432\u043a\u0430"
    ],
    "name:und_x_variant":[
        "Yermolovka",
        "Malosergeyevka"
    ],
    "wof:name":"Malosergeyevka",
    "wof:placetype":"locality"
},
  "geometry": {"coordinates":[67.63276999999999,52.83945],"type":"Point"}
}