{
  "type": "Feature",
  "properties": {
    "gn:admin1_code":"0.0",
    "gn:asciiname":"Baysak",
    "gn:country_code":"KZ",
    "gn:dem":120,
    "gn:feature_class":"P",
    "gn:feature_code":"PPL",
    "gn:name":"Baysak",
    "gn:population":0,
    "gn:timezone":"Asia/Almaty",
    "iso:country":"KZ",
    "wof:name":"Baysak",
    "wof:placetype":"locality"
},
  "geometry": {"coordinates":[78.01666999999998,51.83333],"type":"Point"}
}