{
  "type": "Feature",
  "properties": {
    "gn:admin1_code":"15.0",
    "gn:asciiname":"Belaghash",
    "gn:country_code":"KZ",
    "gn:dem":392,
    "gn:feature_class":"P",
    "gn:feature_code":"PPL",
    "gn:name":"Belaghash",
    "gn:population":0,
    "gn:timezone":"Asia/Almaty",
    "iso:country":"KZ",
    "name:eng_x_preferred":[
        "Belaghash"
    ],
    "name:kaz_x_preferred":[
        "\u0411\u0435\u043b\u0430\u0493\u0430\u0448"
    ],
    "name:rus_x_preferred":[
        "\u0411\u0435\u043b\u044c\u0430\u0433\u0430\u0448"
    ],
    "name:und_x_variant":[
        "Bel\u2019-Agach",
        "Belagatchskoe Zimovie",
        "Bel\u2019agachskiy",
        "Bel\u2019agash"
    ],
    "wof:name":"Belaghash",
    "wof:placetype":"locality"
},
  "geometry": {"coordinates":[80.66379999999999,50.76882],"type":"Point"}
}