{
  "type": "Feature",
  "properties": {
    "gn:admin1_code":"3.0",
    "gn:asciiname":"Qoytas",
    "gn:country_code":"KZ",
    "gn:dem":259,
    "gn:feature_class":"P",
    "gn:feature_code":"PPL",
    "gn:name":"Qoytas",
    "gn:population":0,
    "gn:timezone":"Asia/Almaty",
    "iso:country":"KZ",
    "name:kaz_x_preferred":[
        "Qoytas"
    ],
    "name:kaz_x_variant":[
        "\u049a\u043e\u0439\u0442\u0430\u0441"
    ],
    "name:rus_x_preferred":[
        "\u041a\u043e\u0439\u0442\u0430\u0441"
    ],
    "name:und_x_variant":[
        "Koytas"
    ],
    "wof:name":"Qoytas",
    "wof:placetype":"locality"
},
  "geometry": {"coordinates":[73.79774999999999,51.7993],"type":"Point"}
}