{
  "type": "Feature",
  "properties": {
    "gn:admin1_code":"1.0",
    "gn:asciiname":"Uzun-Agach",
    "gn:country_code":"KZ",
    "gn:dem":628,
    "gn:feature_class":"P",
    "gn:feature_code":"PPL",
    "gn:name":"Uzun-Agach",
    "gn:population":0,
    "gn:timezone":"Asia/Almaty",
    "iso:country":"KZ",
    "name:rus_x_preferred":[
        "\u0423\u0437\u0443\u043d-\u0410\u0433\u0430\u0447"
    ],
    "wof:name":"Uzun-Agach",
    "wof:placetype":"locality"
},
  "geometry": {"coordinates":[76.31918,43.59273],"type":"Point"}
}