{
  "type": "Feature",
  "properties": {
    "gn:admin1_code":"3.0",
    "gn:asciiname":"Novopetropavlovka",
    "gn:country_code":"KZ",
    "gn:dem":278,
    "gn:feature_class":"P",
    "gn:feature_code":"PPL",
    "gn:name":"Novopetropavlovka",
    "gn:population":0,
    "gn:timezone":"Asia/Almaty",
    "iso:country":"KZ",
    "wof:name":"Novopetropavlovka",
    "wof:placetype":"locality"
},
  "geometry": {"coordinates":[68.76992,51.70075],"type":"Point"}
}