{
  "type": "Feature",
  "properties": {
    "gn:admin1_code":"10.0",
    "gn:asciiname":"Kyzyltu",
    "gn:country_code":"KZ",
    "gn:dem":841,
    "gn:feature_class":"P",
    "gn:feature_code":"PPL",
    "gn:name":"Kyzyltu",
    "gn:population":0,
    "gn:timezone":"Asia/Almaty",
    "iso:country":"KZ",
    "name:und_x_variant":[
        "Kzyl-Tu",
        "Kyzyltu"
    ],
    "wof:name":"Kyzyltu",
    "wof:placetype":"locality"
},
  "geometry": {"coordinates":[68.43333,43.66667],"type":"Point"}
}