{
  "type": "Feature",
  "properties": {
    "gn:admin1_code":"0.0",
    "gn:asciiname":"Perelom",
    "gn:country_code":"KZ",
    "gn:dem":431,
    "gn:feature_class":"P",
    "gn:feature_code":"PPL",
    "gn:name":"Perelom",
    "gn:population":0,
    "gn:timezone":"Asia/Almaty",
    "iso:country":"KZ",
    "wof:name":"Perelom",
    "wof:placetype":"locality"
},
  "geometry": {"coordinates":[82.43333,50.36667],"type":"Point"}
}