{
  "type": "Feature",
  "properties": {
    "gn:admin1_code":"13.0",
    "gn:asciiname":"Qaraterek",
    "gn:country_code":"KZ",
    "gn:dem":174,
    "gn:feature_class":"P",
    "gn:feature_code":"PPL",
    "gn:name":"Qaraterek",
    "gn:population":0,
    "gn:timezone":"Asia/Qyzylorda",
    "iso:country":"KZ",
    "name:kaz_x_preferred":[
        "Qaraterek"
    ],
    "name:kaz_x_variant":[
        "\u049a\u0430\u0440\u0430\u0442\u0435\u0440\u0435\u043a"
    ],
    "name:rus_x_preferred":[
        "\u041a\u0430\u0440\u0430\u0442\u0435\u0440\u0435\u043a"
    ],
    "name:und_x_variant":[
        "Karaterek"
    ],
    "wof:name":"Qaraterek",
    "wof:placetype":"locality"
},
  "geometry": {"coordinates":[65.53156,54.02003000000001],"type":"Point"}
}