{
  "type": "Feature",
  "properties": {
    "gn:admin1_code":"11.0",
    "gn:asciiname":"Bekmurat",
    "gn:country_code":"KZ",
    "gn:dem":108,
    "gn:feature_class":"P",
    "gn:feature_code":"PPL",
    "gn:name":"Bekmurat",
    "gn:population":0,
    "gn:timezone":"Asia/Almaty",
    "iso:country":"KZ",
    "name:rus_x_preferred":[
        "\u0411\u0435\u043a\u043c\u0443\u0440\u0430\u0442"
    ],
    "wof:name":"Bekmurat",
    "wof:placetype":"locality"
},
  "geometry": {"coordinates":[76.70843000000001,53.58825],"type":"Point"}
}