{
  "type": "Feature",
  "properties": {
    "gn:admin1_code":"0.0",
    "gn:asciiname":"Steklyanka",
    "gn:country_code":"KZ",
    "gn:dem":410,
    "gn:feature_class":"P",
    "gn:feature_code":"PPL",
    "gn:name":"Steklyanka",
    "gn:population":0,
    "gn:timezone":"Asia/Almaty",
    "iso:country":"KZ",
    "name:eng_x_preferred":[
        "Steklyanka"
    ],
    "name:rus_x_preferred":[
        "\u0421\u0442\u0435\u043a\u043b\u044f\u043d\u043a\u0430"
    ],
    "wof:name":"Steklyanka",
    "wof:placetype":"locality"
},
  "geometry": {"coordinates":[81.33927,50.64411],"type":"Point"}
}