{
  "type": "Feature",
  "properties": {
    "gn:admin1_code":"11.0",
    "gn:asciiname":"Ol'khovka",
    "gn:country_code":"KZ",
    "gn:dem":107,
    "gn:feature_class":"P",
    "gn:feature_code":"PPL",
    "gn:name":"Ol\u2019khovka",
    "gn:population":0,
    "gn:timezone":"Asia/Almaty",
    "iso:country":"KZ",
    "name:kaz_x_preferred":[
        "\u041e\u043b\u044c\u0445\u043e\u0432\u043a\u0430"
    ],
    "name:und_x_variant":[
        "Ol\u2019khovskoye",
        "Ol\u2019khovka"
    ],
    "wof:name":"Ol'khovka",
    "wof:placetype":"locality"
},
  "geometry": {"coordinates":[77.10945,52.95995],"type":"Point"}
}