{
  "type": "Feature",
  "properties": {
    "gn:admin1_code":"10.0",
    "gn:asciiname":"Dzhetygen-Aryk",
    "gn:cc2":"KZ",
    "gn:country_code":"KZ",
    "gn:dem":615,
    "gn:feature_class":"P",
    "gn:feature_code":"PPL",
    "gn:name":"Dzhetygen-Aryk",
    "gn:population":0,
    "gn:timezone":"Asia/Almaty",
    "iso:country":"KZ",
    "name:und_x_variant":[
        "Dzhetygen"
    ],
    "wof:name":"Dzhetygen-Aryk",
    "wof:placetype":"locality"
},
  "geometry": {"coordinates":[69.41667,41.85],"type":"Point"}
}