{
  "type": "Feature",
  "properties": {
    "gn:admin1_code":"10.0",
    "gn:asciiname":"Aqqum",
    "gn:country_code":"KZ",
    "gn:dem":187,
    "gn:feature_class":"P",
    "gn:feature_code":"PPL",
    "gn:name":"Aqqum",
    "gn:population":0,
    "gn:timezone":"Asia/Almaty",
    "iso:country":"KZ",
    "name:kaz_x_preferred":[
        "Aqqum"
    ],
    "name:kaz_x_variant":[
        "\u0410\u049b\u049b\u04b1\u043c"
    ],
    "name:msa_x_preferred":[
        "Aqqum"
    ],
    "name:rus_x_preferred":[
        "\u0410\u043a\u043a\u0443\u043c"
    ],
    "name:und_x_variant":[
        "Akkum"
    ],
    "wof:name":"Aqqum",
    "wof:placetype":"locality"
},
  "geometry": {"coordinates":[67.88323000000001,42.94322],"type":"Point"}
}