{
  "type": "Feature",
  "properties": {
    "gn:admin1_code":"16.0",
    "gn:asciiname":"Aqqudyq",
    "gn:country_code":"KZ",
    "gn:dem":171,
    "gn:feature_class":"P",
    "gn:feature_code":"PPL",
    "gn:name":"Aqqudyq",
    "gn:population":0,
    "gn:timezone":"Asia/Almaty",
    "iso:country":"KZ",
    "name:eng_x_preferred":[
        "Komsomol'skoe"
    ],
    "name:kaz_x_preferred":[
        "Aqqudyq"
    ],
    "name:kaz_x_variant":[
        "\u041a\u043e\u043c\u0441\u043e\u043c\u043e\u043b\u044c\u0441\u043a\u043e\u0435",
        "\u0410\u049b\u049b\u04b1\u0434\u044b\u049b"
    ],
    "name:rus_x_preferred":[
        "\u041a\u043e\u043c\u0441\u043e\u043c\u043e\u043b\u044c\u0441\u043a\u043e\u0435"
    ],
    "name:und_x_variant":[
        "Komsomol",
        "Komsomol\u2019skoye",
        "Komsomol\u2019skoe"
    ],
    "wof:name":"Aqqudyq",
    "wof:placetype":"locality"
},
  "geometry": {"coordinates":[72.3419,53.12899],"type":"Point"}
}