{
  "type": "Feature",
  "properties": {
    "gn:admin1_code":"1.0",
    "gn:asciiname":"Tekes",
    "gn:country_code":"KZ",
    "gn:dem":1790,
    "gn:feature_class":"P",
    "gn:feature_code":"PPL",
    "gn:name":"Tekes",
    "gn:population":0,
    "gn:timezone":"Asia/Almaty",
    "iso:country":"KZ",
    "name:kaz_x_preferred":[
        "Tekes"
    ],
    "name:kaz_x_variant":[
        "\u0422\u0435\u043a\u0435\u0441"
    ],
    "wof:name":"Tekes",
    "wof:placetype":"locality"
},
  "geometry": {"coordinates":[80.04845999999998,42.82767],"type":"Point"}
}