{
  "type": "Feature",
  "properties": {
    "gn:admin1_code":"0.0",
    "gn:asciiname":"Atshapkan",
    "gn:country_code":"KZ",
    "gn:dem":198,
    "gn:feature_class":"P",
    "gn:feature_code":"PPL",
    "gn:name":"Atshapkan",
    "gn:population":0,
    "gn:timezone":"Asia/Almaty",
    "iso:country":"KZ",
    "wof:name":"Atshapkan",
    "wof:placetype":"locality"
},
  "geometry": {"coordinates":[79.15000000000001,51.26667],"type":"Point"}
}