{
  "type": "Feature",
  "properties": {
    "gn:admin1_code":"7.0",
    "gn:asciiname":"Ayak",
    "gn:country_code":"KZ",
    "gn:dem":25,
    "gn:feature_class":"P",
    "gn:feature_code":"PPL",
    "gn:name":"Ayak",
    "gn:population":0,
    "gn:timezone":"Asia/Oral",
    "iso:country":"KZ",
    "wof:name":"Ayak",
    "wof:placetype":"locality"
},
  "geometry": {"coordinates":[49.86333,50.74056],"type":"Point"}
}