{
  "type": "Feature",
  "properties": {
    "gn:admin1_code":"17.0",
    "gn:asciiname":"Unguyrlyu",
    "gn:country_code":"KZ",
    "gn:dem":790,
    "gn:feature_class":"P",
    "gn:feature_code":"PPL",
    "gn:name":"Unguyrlyu",
    "gn:population":0,
    "gn:timezone":"Asia/Almaty",
    "iso:country":"KZ",
    "wof:name":"Unguyrlyu",
    "wof:placetype":"locality"
},
  "geometry": {"coordinates":[74.18333,43.56667],"type":"Point"}
}