{
  "type": "Feature",
  "properties": {
    "gn:admin1_code":"17.0",
    "gn:asciiname":"Teris",
    "gn:country_code":"KZ",
    "gn:dem":958,
    "gn:feature_class":"P",
    "gn:feature_code":"PPL",
    "gn:name":"Teris",
    "gn:population":0,
    "gn:timezone":"Asia/Almaty",
    "iso:country":"KZ",
    "name:rus_x_preferred":[
        "\u0422\u0435\u0440\u0438\u0441"
    ],
    "wof:name":"Teris",
    "wof:placetype":"locality"
},
  "geometry": {"coordinates":[70.82524000000002,42.66869000000001],"type":"Point"}
}