{
  "type": "Feature",
  "properties": {
    "gn:admin1_code":"15.0",
    "gn:asciiname":"Murat",
    "gn:country_code":"KZ",
    "gn:dem":188,
    "gn:feature_class":"P",
    "gn:feature_code":"PPL",
    "gn:name":"Murat",
    "gn:population":0,
    "gn:timezone":"Asia/Almaty",
    "iso:country":"KZ",
    "name:eng_x_preferred":[
        "Murat"
    ],
    "name:kaz_x_preferred":[
        "\u041c\u04b1\u0440\u0430\u0442"
    ],
    "name:rus_x_preferred":[
        "\u041c\u0443\u0440\u0430\u0442"
    ],
    "wof:name":"Murat",
    "wof:placetype":"locality"
},
  "geometry": {"coordinates":[80.13596,50.4376],"type":"Point"}
}