{
  "type": "Feature",
  "properties": {
    "gn:admin1_code":"11.0",
    "gn:asciiname":"Dekene",
    "gn:country_code":"KZ",
    "gn:dem":124,
    "gn:feature_class":"P",
    "gn:feature_code":"PPL",
    "gn:name":"Dekene",
    "gn:population":0,
    "gn:timezone":"Asia/Almaty",
    "iso:country":"KZ",
    "name:rus_x_preferred":[
        "\u0414\u0435\u043a\u0435\u043d\u0435"
    ],
    "wof:name":"Dekene",
    "wof:placetype":"locality"
},
  "geometry": {"coordinates":[75.97874,52.41981],"type":"Point"}
}