{
  "type": "Feature",
  "properties": {
    "gn:admin1_code":"0.0",
    "gn:asciiname":"Karazhar",
    "gn:country_code":"KZ",
    "gn:dem":172,
    "gn:feature_class":"P",
    "gn:feature_code":"PPL",
    "gn:name":"Karazhar",
    "gn:population":0,
    "gn:timezone":"Asia/Almaty",
    "iso:country":"KZ",
    "wof:name":"Karazhar",
    "wof:placetype":"locality"
},
  "geometry": {"coordinates":[65.71679,50.4745],"type":"Point"}
}