{
  "type": "Feature",
  "properties": {
    "gn:admin1_code":"10.0",
    "gn:asciiname":"Novoselovka",
    "gn:country_code":"KZ",
    "gn:dem":552,
    "gn:feature_class":"P",
    "gn:feature_code":"PPL",
    "gn:name":"Novos\u00eblovka",
    "gn:population":0,
    "gn:timezone":"Asia/Almaty",
    "iso:country":"KZ",
    "name:rus_x_preferred":[
        "Novos\u00eblovka"
    ],
    "name:rus_x_variant":[
        "\u041d\u043e\u0432\u043e\u0441\u0451\u043b\u043e\u0432\u043a\u0430"
    ],
    "wof:name":"Novoselovka",
    "wof:placetype":"locality"
},
  "geometry": {"coordinates":[69.75269,42.43049],"type":"Point"}
}