{
  "type": "Feature",
  "properties": {
    "gn:admin1_code":"15.0",
    "gn:asciiname":"Voznesenovka",
    "gn:country_code":"KZ",
    "gn:dem":304,
    "gn:feature_class":"P",
    "gn:feature_code":"PPL",
    "gn:name":"Voznesenovka",
    "gn:population":0,
    "gn:timezone":"Asia/Almaty",
    "iso:country":"KZ",
    "name:eng_x_preferred":[
        "Voznesenovka"
    ],
    "name:kaz_x_preferred":[
        "\u0412\u043e\u0437\u043d\u0435\u0441\u0435\u043d\u043e\u0432\u043a\u0430"
    ],
    "name:rus_x_preferred":[
        "\u0412\u043e\u0437\u043d\u0435\u0441\u0435\u043d\u043e\u0432\u043a\u0430"
    ],
    "name:und_x_variant":[
        "Voznesenka",
        "Voznesenskiy",
        "Voznesenovka"
    ],
    "wof:name":"Voznesenovka",
    "wof:placetype":"locality"
},
  "geometry": {"coordinates":[80.54266,50.87831],"type":"Point"}
}