{
  "type": "Feature",
  "properties": {
    "gn:admin1_code":"12.0",
    "gn:asciiname":"Aynabulaq",
    "gn:country_code":"KZ",
    "gn:dem":696,
    "gn:feature_class":"P",
    "gn:feature_code":"PPL",
    "gn:name":"Aynabulaq",
    "gn:population":0,
    "gn:timezone":"Asia/Almaty",
    "iso:country":"KZ",
    "name:kaz_x_preferred":[
        "Aynabulaq"
    ],
    "name:kaz_x_variant":[
        "\u0410\u0439\u043d\u0430\u0431\u04b1\u043b\u0430\u049b"
    ],
    "name:und_x_variant":[
        "Aynabulak"
    ],
    "wof:name":"Aynabulaq",
    "wof:placetype":"locality"
},
  "geometry": {"coordinates":[77.00806999999998,49.92361],"type":"Point"}
}