{
  "type": "Feature",
  "properties": {
    "gn:admin1_code":"12.0",
    "gn:asciiname":"Taldybulaq",
    "gn:country_code":"KZ",
    "gn:dem":538,
    "gn:feature_class":"P",
    "gn:feature_code":"PPL",
    "gn:name":"Taldybulaq",
    "gn:population":0,
    "gn:timezone":"Asia/Almaty",
    "iso:country":"KZ",
    "name:und_x_variant":[
        "Taldybulak",
        "Taldybulaq"
    ],
    "wof:name":"Taldybulaq",
    "wof:placetype":"locality"
},
  "geometry": {"coordinates":[71.37839,48.84428],"type":"Point"}
}