{
  "type": "Feature",
  "properties": {
    "gn:admin1_code":"12.0",
    "gn:asciiname":"Kurminskoye",
    "gn:country_code":"KZ",
    "gn:dem":544,
    "gn:feature_class":"P",
    "gn:feature_code":"PPL",
    "gn:name":"Kurminskoye",
    "gn:population":0,
    "gn:timezone":"Asia/Almaty",
    "iso:country":"KZ",
    "name:kaz_x_preferred":[
        "Qurma"
    ],
    "name:kaz_x_variant":[
        "\u049a\u04b1\u0440\u043c\u0430"
    ],
    "name:rus_x_preferred":[
        "\u041a\u0443\u0440\u043c\u0438\u043d\u0441\u043a\u043e\u0435"
    ],
    "name:und_x_variant":[
        "Kurminskaya Ptitsefabrika",
        "Kurminskoye"
    ],
    "wof:name":"Kurminskoye",
    "wof:placetype":"locality"
},
  "geometry": {"coordinates":[73.20761,49.61437],"type":"Point"}
}