{
  "type": "Feature",
  "properties": {
    "gn:admin1_code":"15.0",
    "gn:asciiname":"Vesyoloe",
    "gn:country_code":"KZ",
    "gn:dem":352,
    "gn:feature_class":"P",
    "gn:feature_code":"PPL",
    "gn:name":"Vesyoloe",
    "gn:population":0,
    "gn:timezone":"Asia/Almaty",
    "iso:country":"KZ",
    "name:kaz_x_preferred":[
        "Vesyoloe"
    ],
    "name:kaz_x_variant":[
        "\u0412\u0435\u0441\u0451\u043b\u043e\u0435"
    ],
    "name:rus_x_preferred":[
        "Ves\u00ebloye"
    ],
    "wof:name":"Vesyoloe",
    "wof:placetype":"locality"
},
  "geometry": {"coordinates":[82.83371,50.09779],"type":"Point"}
}