{
  "type": "Feature",
  "properties": {
    "gn:admin1_code":"13.0",
    "gn:asciiname":"Ushsorka",
    "gn:country_code":"KZ",
    "gn:dem":237,
    "gn:feature_class":"P",
    "gn:feature_code":"PPL",
    "gn:name":"Ushsorka",
    "gn:population":0,
    "gn:timezone":"Asia/Qyzylorda",
    "iso:country":"KZ",
    "name:eng_x_preferred":[
        "Ushsorka"
    ],
    "name:rus_x_preferred":[
        "\u0423\u0448\u0441\u043e\u0440\u0441\u043a\u0438\u0439"
    ],
    "name:und_x_variant":[
        "Ushsorskiy",
        "Ushsovskiy"
    ],
    "wof:name":"Ushsorka",
    "wof:placetype":"locality"
},
  "geometry": {"coordinates":[62.54861999999999,52.06715],"type":"Point"}
}