{
  "type": "Feature",
  "properties": {
    "gn:admin1_code":"16.0",
    "gn:asciiname":"Privol'noye",
    "gn:country_code":"KZ",
    "gn:dem":312,
    "gn:feature_class":"P",
    "gn:feature_code":"PPL",
    "gn:name":"Privol\u2019noye",
    "gn:population":0,
    "gn:timezone":"Asia/Almaty",
    "iso:country":"KZ",
    "name:kaz_x_preferred":[
        "Pr\u012bvol\u2019noe"
    ],
    "name:kaz_x_variant":[
        "\u041f\u0440\u0438\u0432\u043e\u043b\u044c\u043d\u043e\u0435"
    ],
    "name:rus_x_preferred":[
        "Privol\u2019noye"
    ],
    "wof:name":"Privol'noye",
    "wof:placetype":"locality"
},
  "geometry": {"coordinates":[67.82467,52.59994],"type":"Point"}
}