{
  "type": "Feature",
  "properties": {
    "gn:admin1_code":"12.0",
    "gn:asciiname":"Orkendeu",
    "gn:country_code":"KZ",
    "gn:dem":456,
    "gn:feature_class":"P",
    "gn:feature_code":"PPL",
    "gn:name":"\u00d6rkende\u016b",
    "gn:population":0,
    "gn:timezone":"Asia/Almaty",
    "iso:country":"KZ",
    "name:und_x_variant":[
        "Urkendeu",
        "\u00d6rkende\u016b"
    ],
    "wof:name":"Orkendeu",
    "wof:placetype":"locality"
},
  "geometry": {"coordinates":[70.94659,48.68218],"type":"Point"}
}