{
  "type": "Feature",
  "properties": {
    "gn:admin1_code":"0.0",
    "gn:asciiname":"Kremlevskiy",
    "gn:cc2":"KZ",
    "gn:country_code":"KZ",
    "gn:dem":449,
    "gn:feature_class":"P",
    "gn:feature_code":"PPL",
    "gn:name":"Kreml\u00ebvskiy",
    "gn:population":0,
    "gn:timezone":"Asia/Almaty",
    "iso:country":"KZ",
    "name:und_x_variant":[
        "Kremlevka",
        "Kreml\u00ebvskiy"
    ],
    "wof:name":"Kremlevskiy",
    "wof:placetype":"locality"
},
  "geometry": {"coordinates":[82.59999999999999,49.83333],"type":"Point"}
}