{
  "type": "Feature",
  "properties": {
    "gn:admin1_code":"12.0",
    "gn:asciiname":"Ushtobe",
    "gn:country_code":"KZ",
    "gn:dem":563,
    "gn:feature_class":"P",
    "gn:feature_code":"PPL",
    "gn:name":"Ushtobe",
    "gn:population":0,
    "gn:timezone":"Asia/Almaty",
    "iso:country":"KZ",
    "name:ceb_x_preferred":[
        "Ush-Tyube"
    ],
    "name:deu_x_preferred":[
        "\u00dcscht\u00f6be"
    ],
    "name:ell_x_preferred":[
        "\u039f\u03c5\u03c3\u03c4\u03bf\u03bc\u03c0\u03ad"
    ],
    "name:fas_x_preferred":[
        "\u0627\u0648\u0686\u200c\u062a\u067e\u0647"
    ],
    "name:hsb_x_preferred":[
        "U\u0161tobe"
    ],
    "name:kaz_x_preferred":[
        "\u00dcsht\u00f6be"
    ],
    "name:kaz_x_variant":[
        "\u04ae\u0448\u0442\u04e9\u0431\u0435"
    ],
    "name:lit_x_preferred":[
        "U\u0161tob\u0117"
    ],
    "name:mkd_x_preferred":[
        "\u0423\u0448\u0442\u043e\u0431\u0435"
    ],
    "name:msa_x_preferred":[
        "Ushtobe"
    ],
    "name:pol_x_preferred":[
        "\u00dcszt\u00f6be"
    ],
    "name:rus_x_preferred":[
        "\u0423\u0448\u0442\u043e\u0431\u0435"
    ],
    "name:swe_x_preferred":[
        "Usjtobe"
    ],
    "name:tat_x_preferred":[
        "\u04e8\u0447\u0442\u04af\u0431\u04d9"
    ],
    "name:ukr_x_preferred":[
        "\u0423\u0448\u0442\u043e\u0431\u0435"
    ],
    "name:und_x_variant":[
        "Oktyabr\u2019skoye"
    ],
    "name:uzb_x_preferred":[
        "Uchtepa"
    ],
    "wof:name":"Ushtobe",
    "wof:placetype":"locality"
},
  "geometry": {"coordinates":[73.23716999999998,49.77401],"type":"Point"}
}