{
  "type": "Feature",
  "properties": {
    "gn:admin1_code":"12.0",
    "gn:asciiname":"Ushtobe",
    "gn:country_code":"KZ",
    "gn:dem":563,
    "gn:feature_class":"P",
    "gn:feature_code":"PPL",
    "gn:name":"Ushtobe",
    "gn:population":0,
    "gn:timezone":"Asia/Almaty",
    "iso:country":"KZ",
    "name:ara_x_preferred":[
        "\u0623\u0648\u0634\u062a\u0648\u0628"
    ],
    "name:ben_x_preferred":[
        "\u0989\u09b6\u09a4\u09cb\u09ac\u09c7"
    ],
    "name:ceb_x_preferred":[
        "Ush-Tyube"
    ],
    "name:deu_x_preferred":[
        "\u00dcscht\u00f6be"
    ],
    "name:ell_x_preferred":[
        "\u039f\u03c5\u03c3\u03c4\u03bf\u03bc\u03c0\u03ad"
    ],
    "name:fas_x_preferred":[
        "\u0627\u0648\u0686\u200c\u062a\u067e\u0647"
    ],
    "name:fra_x_preferred":[
        "Ushtobe"
    ],
    "name:heb_x_preferred":[
        "\u05d0\u05d5\u05e9\u05d8\u05d5\u05d1\u05d4"
    ],
    "name:hin_x_preferred":[
        "\u0909\u0936\u091f\u094b\u092c\u0947"
    ],
    "name:hsb_x_preferred":[
        "U\u0161tobe"
    ],
    "name:hun_x_preferred":[
        "Ushtobe"
    ],
    "name:ind_x_preferred":[
        "Ushtobe"
    ],
    "name:ita_x_preferred":[
        "Ushtobe"
    ],
    "name:kaz_x_preferred":[
        "\u00dcsht\u00f6be"
    ],
    "name:kaz_x_variant":[
        "\u04ae\u0448\u0442\u04e9\u0431\u0435"
    ],
    "name:kor_x_preferred":[
        "\uc6b0\uc288\ud1a0\ubca0"
    ],
    "name:lit_x_preferred":[
        "U\u0161tob\u0117"
    ],
    "name:mkd_x_preferred":[
        "\u0423\u0448\u0442\u043e\u0431\u0435"
    ],
    "name:msa_x_preferred":[
        "Ushtobe"
    ],
    "name:pol_x_preferred":[
        "\u00dcszt\u00f6be"
    ],
    "name:por_x_preferred":[
        "Ushtobe"
    ],
    "name:rus_x_preferred":[
        "\u0423\u0448\u0442\u043e\u0431\u0435"
    ],
    "name:spa_x_preferred":[
        "Ushtobe"
    ],
    "name:swe_x_preferred":[
        "Usjtobe"
    ],
    "name:tat_x_preferred":[
        "\u04e8\u0447\u0442\u04af\u0431\u04d9"
    ],
    "name:tur_x_preferred":[
        "Ushtobe"
    ],
    "name:ukr_x_preferred":[
        "\u0423\u0448\u0442\u043e\u0431\u0435"
    ],
    "name:und_x_variant":[
        "Oktyabr\u2019skoye"
    ],
    "name:urd_x_preferred":[
        "\u0627\u0634\u0679\u0648\u0628\u06d2"
    ],
    "name:uzb_x_preferred":[
        "Uchtepa"
    ],
    "name:vie_x_preferred":[
        "Ushtobe"
    ],
    "wof:name":"Ushtobe",
    "wof:placetype":"locality"
},
  "geometry": {"coordinates":[73.23717000000001,49.77401],"type":"Point"}
}