{
  "type": "Feature",
  "properties": {
    "gn:admin1_code":"12.0",
    "gn:asciiname":"Ushtobe",
    "gn:country_code":"KZ",
    "gn:dem":563,
    "gn:feature_class":"P",
    "gn:feature_code":"PPL",
    "gn:name":"Ushtobe",
    "gn:population":0,
    "gn:timezone":"Asia/Almaty",
    "iso:country":"KZ",
    "name:kaz_x_preferred":[
        "\u00dcsht\u00f6be"
    ],
    "name:kaz_x_variant":[
        "\u04ae\u0448\u0442\u04e9\u0431\u0435"
    ],
    "name:rus_x_preferred":[
        "\u0423\u0448\u0442\u043e\u0431\u0435"
    ],
    "name:und_x_variant":[
        "Oktyabr\u2019skoye"
    ],
    "wof:name":"Ushtobe",
    "wof:placetype":"locality"
},
  "geometry": {"coordinates":[73.23716999999998,49.77401],"type":"Point"}
}