{
  "type": "Feature",
  "properties": {
    "gn:admin1_code":"0.0",
    "gn:asciiname":"Kylyshpay",
    "gn:cc2":"KZ",
    "gn:country_code":"KZ",
    "gn:dem":283,
    "gn:feature_class":"P",
    "gn:feature_code":"PPL",
    "gn:name":"Kylyshpay",
    "gn:population":0,
    "gn:timezone":"Asia/Almaty",
    "iso:country":"KZ",
    "name:und_x_variant":[
        "Klyshpay",
        "Kylyshpay"
    ],
    "wof:name":"Kylyshpay",
    "wof:placetype":"locality"
},
  "geometry": {"coordinates":[79.76666999999998,50.28333],"type":"Point"}
}