{
  "type": "Feature",
  "properties": {
    "gn:admin1_code":"0.0",
    "gn:asciiname":"Koyandy",
    "gn:country_code":"KZ",
    "gn:dem":245,
    "gn:feature_class":"P",
    "gn:feature_code":"PPL",
    "gn:name":"Koyandy",
    "gn:population":0,
    "gn:timezone":"Asia/Qyzylorda",
    "iso:country":"KZ",
    "name:eng_x_preferred":[
        "Koyandy"
    ],
    "name:rus_x_preferred":[
        "\u041a\u043e\u044f\u043d\u0434\u044b"
    ],
    "wof:name":"Koyandy",
    "wof:placetype":"locality"
},
  "geometry": {"coordinates":[62.16845,51.98425],"type":"Point"}
}