{
  "type": "Feature",
  "properties": {
    "gn:admin1_code":"0.0",
    "gn:asciiname":"Gogolevskiy",
    "gn:country_code":"KZ",
    "gn:dem":263,
    "gn:feature_class":"P",
    "gn:feature_code":"PPL",
    "gn:name":"Gogolevskiy",
    "gn:population":0,
    "gn:timezone":"Asia/Almaty",
    "iso:country":"KZ",
    "wof:name":"Gogolevskiy",
    "wof:placetype":"locality"
},
  "geometry": {"coordinates":[66.76666999999999,50.93333],"type":"Point"}
}