{
  "type": "Feature",
  "properties": {
    "gn:admin1_code":"14.0",
    "gn:asciiname":"Abay",
    "gn:country_code":"KZ",
    "gn:dem":123,
    "gn:feature_class":"P",
    "gn:feature_code":"PPL",
    "gn:name":"Abay",
    "gn:population":0,
    "gn:timezone":"Asia/Qyzylorda",
    "iso:country":"KZ",
    "name:ceb_x_preferred":[
        "Abay"
    ],
    "name:deu_x_preferred":[
        "Abay"
    ],
    "name:est_x_preferred":[
        "Abai"
    ],
    "name:kaa_x_preferred":[
        "Abay"
    ],
    "name:kaz_x_preferred":[
        "\u0410\u0431\u0430\u0439"
    ],
    "name:lit_x_preferred":[
        "Abajus"
    ],
    "name:rus_x_preferred":[
        "\u0410\u0431\u0430\u0439"
    ],
    "name:spa_x_preferred":[
        "Abay"
    ],
    "name:swe_x_preferred":[
        "Abay"
    ],
    "name:uzb_x_preferred":[
        "Abay"
    ],
    "wof:name":"Abay",
    "wof:placetype":"locality"
},
  "geometry": {"coordinates":[65.54583000000001,44.95111],"type":"Point"}
}