{
  "type": "Feature",
  "properties": {
    "gn:admin1_code":"14.0",
    "gn:asciiname":"Abay",
    "gn:country_code":"KZ",
    "gn:dem":123,
    "gn:feature_class":"P",
    "gn:feature_code":"PPL",
    "gn:name":"Abay",
    "gn:population":0,
    "gn:timezone":"Asia/Qyzylorda",
    "iso:country":"KZ",
    "wof:name":"Abay",
    "wof:placetype":"locality"
},
  "geometry": {"coordinates":[65.54583000000001,44.95111],"type":"Point"}
}