{
  "type": "Feature",
  "properties": {
    "gn:admin1_code":"13.0",
    "gn:asciiname":"Alakol",
    "gn:country_code":"KZ",
    "gn:dem":125,
    "gn:feature_class":"P",
    "gn:feature_code":"PPL",
    "gn:name":"Alak\u00f6l",
    "gn:population":0,
    "gn:timezone":"Asia/Almaty",
    "iso:country":"KZ",
    "name:ceb_x_preferred":[
        "Alakol"
    ],
    "name:eng_x_preferred":[
        "Alakol'"
    ],
    "name:kaz_x_preferred":[
        "Alak\u00f6l"
    ],
    "name:rus_x_preferred":[
        "\u0410\u043b\u0430\u043a\u043e\u043b\u044c"
    ],
    "name:swe_x_preferred":[
        "Alakol"
    ],
    "name:und_x_variant":[
        "Zhanaiyum",
        "Alakol\u2019"
    ],
    "wof:name":"Alakol",
    "wof:placetype":"locality"
},
  "geometry": {"coordinates":[64.9477,49.95457],"type":"Point"}
}