{
  "type": "Feature",
  "properties": {
    "gn:admin1_code":"10.0",
    "gn:asciiname":"Pervomayevka",
    "gn:country_code":"KZ",
    "gn:dem":853,
    "gn:feature_class":"P",
    "gn:feature_code":"PPL",
    "gn:name":"Pervomayevka",
    "gn:population":0,
    "gn:timezone":"Asia/Almaty",
    "iso:country":"KZ",
    "name:kaz_x_preferred":[
        "\u041f\u0435\u0440\u0432\u043e\u043c\u0430\u0435\u0432\u043a\u0430"
    ],
    "name:und_x_variant":[
        "Dorofeyevka",
        "Pervomayevka",
        "Pervomayka",
        "Pervomayskoye",
        "Pervomaevka"
    ],
    "wof:name":"Pervomayevka",
    "wof:placetype":"locality"
},
  "geometry": {"coordinates":[69.87483,42.09328],"type":"Point"}
}