{
  "type": "Feature",
  "properties": {
    "gn:admin1_code":"0.0",
    "gn:asciiname":"Zhetiaral",
    "gn:country_code":"KZ",
    "gn:dem":726,
    "gn:feature_class":"P",
    "gn:feature_code":"PPL",
    "gn:name":"Zhetiaral",
    "gn:population":0,
    "gn:timezone":"Asia/Almaty",
    "iso:country":"KZ",
    "name:und_x_variant":[
        "Komsomol",
        "Zhetiaral"
    ],
    "wof:name":"Zhetiaral",
    "wof:placetype":"locality"
},
  "geometry": {"coordinates":[83.7324,47.48535],"type":"Point"}
}