{
  "type": "Feature",
  "properties": {
    "gn:admin1_code":"16.0",
    "gn:asciiname":"Zhaksy-Zhangyztau",
    "gn:country_code":"KZ",
    "gn:dem":368,
    "gn:feature_class":"P",
    "gn:feature_code":"PPL",
    "gn:name":"Zhaksy-Zhangyztau",
    "gn:population":0,
    "gn:timezone":"Asia/Almaty",
    "iso:country":"KZ",
    "name:eng_x_preferred":[
        "Zhaksy-Zhangyztau"
    ],
    "name:kaz_x_preferred":[
        "Zhaqsy Zhanghyzta\u016b"
    ],
    "name:kaz_x_variant":[
        "Zhaqsy-Zhangghyzta\u016b",
        "\u0416\u0430\u049b\u0441\u044b-\u0416\u0430\u04a3\u0493\u044b\u0437\u0442\u0430\u0443"
    ],
    "name:rus_x_preferred":[
        "\u042f\u043a\u0448\u0438-\u042f\u043d\u0433\u0438\u0441\u0442\u0430\u0443"
    ],
    "name:rus_x_variant":[
        "\u0416\u0430\u043a\u0441\u044b-\u0416\u0430\u043d\u0433\u044b\u0437\u0442\u0430\u0443"
    ],
    "name:und_x_variant":[
        "Yakshi-Yangiztavskoye",
        "Yakshi-Yangiztau"
    ],
    "wof:name":"Zhaksy-Zhangyztau",
    "wof:placetype":"locality"
},
  "geometry": {"coordinates":[68.22125,52.64106],"type":"Point"}
}