{
  "type": "Feature",
  "properties": {
    "gn:admin1_code":"0.0",
    "gn:asciiname":"Burli",
    "gn:cc2":"KZ",
    "gn:country_code":"KZ",
    "gn:dem":11,
    "gn:feature_class":"P",
    "gn:feature_code":"PPL",
    "gn:name":"Burli",
    "gn:population":0,
    "gn:timezone":"Asia/Oral",
    "iso:country":"KZ",
    "name:deu_x_preferred":[
        "Burli"
    ],
    "name:eng_x_preferred":[
        "Burli"
    ],
    "name:rus_x_preferred":[
        "\u0411\u0443\u0440\u043b\u0438"
    ],
    "name:und_x_variant":[
        "Borly",
        "Borle",
        "Burli"
    ],
    "wof:name":"Burli",
    "wof:placetype":"locality"
},
  "geometry": {"coordinates":[48.53333,48.86667],"type":"Point"}
}