{
  "type": "Feature",
  "properties": {
    "gn:admin1_code":"3.0",
    "gn:asciiname":"Yerofeyevka",
    "gn:country_code":"KZ",
    "gn:dem":315,
    "gn:feature_class":"P",
    "gn:feature_code":"PPL",
    "gn:name":"Yerofeyevka",
    "gn:population":0,
    "gn:timezone":"Asia/Almaty",
    "iso:country":"KZ",
    "name:und_x_variant":[
        "Yerofeyevskiy",
        "Yerofeyevka"
    ],
    "wof:name":"Yerofeyevka",
    "wof:placetype":"locality"
},
  "geometry": {"coordinates":[70.34472,51.87024],"type":"Point"}
}