{
  "type": "Feature",
  "properties": {
    "gn:admin1_code":"3.0",
    "gn:asciiname":"Terek",
    "gn:country_code":"KZ",
    "gn:dem":230,
    "gn:feature_class":"P",
    "gn:feature_code":"PPL",
    "gn:name":"Terek",
    "gn:population":0,
    "gn:timezone":"Asia/Almaty",
    "iso:country":"KZ",
    "name:eng_x_preferred":[
        "Terek"
    ],
    "name:kaz_x_preferred":[
        "\u0422\u0435\u0440\u0435\u043a"
    ],
    "name:rus_x_preferred":[
        "\u0422\u0435\u0440\u0435\u043a"
    ],
    "name:und_x_variant":[
        "Teren",
        "Terek"
    ],
    "wof:name":"Terek",
    "wof:placetype":"locality"
},
  "geometry": {"coordinates":[71.78294,52.72808000000001],"type":"Point"}
}