{
  "type": "Feature",
  "properties": {
    "gn:admin1_code":"3.0",
    "gn:asciiname":"Terek",
    "gn:country_code":"KZ",
    "gn:dem":230,
    "gn:feature_class":"P",
    "gn:feature_code":"PPL",
    "gn:name":"Terek",
    "gn:population":0,
    "gn:timezone":"Asia/Almaty",
    "iso:country":"KZ",
    "name:bak_x_preferred":[
        "\u0422\u0438\u0440\u04d9\u043a"
    ],
    "name:bel_x_preferred":[
        "\u0426\u0435\u0440\u0430\u043a"
    ],
    "name:ceb_x_preferred":[
        "Terek"
    ],
    "name:dan_x_preferred":[
        "Terek"
    ],
    "name:eng_x_preferred":[
        "Terek"
    ],
    "name:epo_x_preferred":[
        "Terek"
    ],
    "name:fra_x_preferred":[
        "Terek"
    ],
    "name:hun_x_preferred":[
        "Tyerek"
    ],
    "name:ita_x_preferred":[
        "Terek"
    ],
    "name:kaz_x_preferred":[
        "\u0422\u0435\u0440\u0435\u043a"
    ],
    "name:kbd_x_preferred":[
        "\u0422\u044d\u0440\u0447"
    ],
    "name:lez_x_preferred":[
        "\u0422\u0435\u0440\u0435\u043a"
    ],
    "name:nld_x_preferred":[
        "Terek"
    ],
    "name:nor_x_preferred":[
        "Terek"
    ],
    "name:pol_x_preferred":[
        "Tieriek"
    ],
    "name:rus_x_preferred":[
        "\u0422\u0435\u0440\u0435\u043a"
    ],
    "name:swe_x_preferred":[
        "Terek"
    ],
    "name:ukr_x_preferred":[
        "\u0422\u0435\u0440\u0435\u043a"
    ],
    "name:und_x_variant":[
        "Teren"
    ],
    "name:vep_x_preferred":[
        "Terek"
    ],
    "wof:name":"Terek",
    "wof:placetype":"locality"
},
  "geometry": {"coordinates":[71.78294,52.72808000000001],"type":"Point"}
}