{
  "type": "Feature",
  "properties": {
    "gn:admin1_code":"0.0",
    "gn:asciiname":"Krasnosel'skiy",
    "gn:country_code":"KZ",
    "gn:dem":317,
    "gn:feature_class":"P",
    "gn:feature_code":"PPL",
    "gn:name":"Krasnosel\u2019skiy",
    "gn:population":0,
    "gn:timezone":"Asia/Almaty",
    "iso:country":"KZ",
    "wof:name":"Krasnosel'skiy",
    "wof:placetype":"locality"
},
  "geometry": {"coordinates":[68.84999999999999,51.95],"type":"Point"}
}