{
  "type": "Feature",
  "properties": {
    "gn:admin1_code":"1.0",
    "gn:asciiname":"Daulet",
    "gn:country_code":"KZ",
    "gn:dem":549,
    "gn:feature_class":"P",
    "gn:feature_code":"PPL",
    "gn:name":"Daulet",
    "gn:population":0,
    "gn:timezone":"Asia/Almaty",
    "iso:country":"KZ",
    "wof:name":"Daulet",
    "wof:placetype":"locality"
},
  "geometry": {"coordinates":[77.10250000000001,43.61917],"type":"Point"}
}