{
  "type": "Feature",
  "properties": {
    "gn:admin1_code":"4.0",
    "gn:asciiname":"Alimbetovka",
    "gn:country_code":"KZ",
    "gn:dem":331,
    "gn:feature_class":"P",
    "gn:feature_code":"PPL",
    "gn:name":"Alimbetovka",
    "gn:population":0,
    "gn:timezone":"Asia/Aqtobe",
    "iso:country":"KZ",
    "name:eng_x_preferred":[
        "Alimbetovka"
    ],
    "name:kaz_x_preferred":[
        "\u00c4limbet"
    ],
    "name:rus_x_preferred":[
        "\u0410\u043b\u0438\u043c\u0431\u0435\u0442\u043e\u0432\u043a\u0430"
    ],
    "wof:name":"Alimbetovka",
    "wof:placetype":"locality"
},
  "geometry": {"coordinates":[58.42859,50.99291],"type":"Point"}
}