{
  "type": "Feature",
  "properties": {
    "gn:admin1_code":"0.0",
    "gn:asciiname":"Sulukol'",
    "gn:country_code":"KZ",
    "gn:dem":165,
    "gn:feature_class":"P",
    "gn:feature_code":"PPL",
    "gn:name":"Sulukol\u2019",
    "gn:population":0,
    "gn:timezone":"Asia/Oral",
    "iso:country":"KZ",
    "name:eng_x_preferred":[
        "Sulukol'"
    ],
    "name:rus_x_preferred":[
        "\u0421\u043b\u0443\u043a\u043e\u043b\u044c"
    ],
    "name:und_x_variant":[
        "Sulukol\u2019"
    ],
    "wof:name":"Sulukol'",
    "wof:placetype":"locality"
},
  "geometry": {"coordinates":[54.3113,50.48541],"type":"Point"}
}