{
  "type": "Feature",
  "properties": {
    "gn:admin1_code":"0.0",
    "gn:asciiname":"Kyzyltu",
    "gn:country_code":"KZ",
    "gn:dem":36,
    "gn:feature_class":"P",
    "gn:feature_code":"PPL",
    "gn:name":"Kyzyltu",
    "gn:population":0,
    "gn:timezone":"Asia/Oral",
    "iso:country":"KZ",
    "wof:name":"Kyzyltu",
    "wof:placetype":"locality"
},
  "geometry": {"coordinates":[47.58333,49.15],"type":"Point"}
}