{
  "type": "Feature",
  "properties": {
    "gn:admin1_code":"10.0",
    "gn:asciiname":"Shavrovka",
    "gn:country_code":"KZ",
    "gn:dem":745,
    "gn:feature_class":"P",
    "gn:feature_code":"PPL",
    "gn:name":"Shavrovka",
    "gn:population":0,
    "gn:timezone":"Asia/Almaty",
    "iso:country":"KZ",
    "wof:name":"Shavrovka",
    "wof:placetype":"locality"
},
  "geometry": {"coordinates":[70.13333,42.65],"type":"Point"}
}