{
  "type": "Feature",
  "properties": {
    "gn:admin1_code":"12.0",
    "gn:asciiname":"Pionerskoye",
    "gn:country_code":"KZ",
    "gn:dem":486,
    "gn:feature_class":"P",
    "gn:feature_code":"PPL",
    "gn:name":"Pionerskoye",
    "gn:population":0,
    "gn:timezone":"Asia/Almaty",
    "iso:country":"KZ",
    "name:kaz_x_preferred":[
        "Pionerskoe"
    ],
    "name:kaz_x_variant":[
        "P\u012bonerskoe",
        "\u041f\u0438\u043e\u043d\u0435\u0440\u0441\u043a\u043e\u0435"
    ],
    "name:rus_x_preferred":[
        "P\u012bonerskoye"
    ],
    "name:und_x_variant":[
        "Pionerskiy",
        "P\u012boner",
        "Pionerskoye"
    ],
    "wof:name":"Pionerskoye",
    "wof:placetype":"locality"
},
  "geometry": {"coordinates":[72.89111,50.61868],"type":"Point"}
}