{
  "type": "Feature",
  "properties": {
    "gn:admin1_code":"1.0",
    "gn:asciiname":"Urtensay",
    "gn:country_code":"KZ",
    "gn:dem":2195,
    "gn:feature_class":"P",
    "gn:feature_code":"PPL",
    "gn:name":"Urtensay",
    "gn:population":0,
    "gn:timezone":"Asia/Almaty",
    "iso:country":"KZ",
    "name:rus_x_preferred":[
        "\u0423\u0440\u0442\u0435\u043d\u0441\u0430\u0439"
    ],
    "wof:name":"Urtensay",
    "wof:placetype":"locality"
},
  "geometry": {"coordinates":[80.76826,43.15513],"type":"Point"}
}