{
  "type": "Feature",
  "properties": {
    "gn:admin1_code":"4.0",
    "gn:asciiname":"Surgali",
    "gn:country_code":"KZ",
    "gn:dem":290,
    "gn:feature_class":"P",
    "gn:feature_code":"PPL",
    "gn:name":"Surgali",
    "gn:population":0,
    "gn:timezone":"Asia/Aqtobe",
    "iso:country":"KZ",
    "wof:name":"Surgali",
    "wof:placetype":"locality"
},
  "geometry": {"coordinates":[57.88333000000001,51.06667],"type":"Point"}
}