{
  "type": "Feature",
  "properties": {
    "gn:admin1_code":"13.0",
    "gn:asciiname":"Sarykol'",
    "gn:country_code":"KZ",
    "gn:dem":221,
    "gn:feature_class":"P",
    "gn:feature_code":"PPL",
    "gn:name":"Sarykol\u2019",
    "gn:population":0,
    "gn:timezone":"Asia/Qyzylorda",
    "iso:country":"KZ",
    "name:kaz_x_preferred":[
        "Saryk\u00f6l"
    ],
    "name:kaz_x_variant":[
        "\u0421\u0430\u0440\u044b\u043a\u04e9\u043b"
    ],
    "name:rus_x_preferred":[
        "Sarykol\u2019"
    ],
    "name:rus_x_variant":[
        "\u0421\u0430\u0440\u044b\u043a\u043e\u043b\u044c"
    ],
    "wof:name":"Sarykol'",
    "wof:placetype":"locality"
},
  "geometry": {"coordinates":[61.74011,53.81952],"type":"Point"}
}