{
  "type": "Feature",
  "properties": {
    "gn:admin1_code":"1.0",
    "gn:asciiname":"Lippaysay",
    "gn:country_code":"KZ",
    "gn:dem":1717,
    "gn:feature_class":"P",
    "gn:feature_code":"PPL",
    "gn:name":"Lippaysay",
    "gn:population":0,
    "gn:timezone":"Asia/Almaty",
    "iso:country":"KZ",
    "name:rus_x_preferred":[
        "\u041b\u0438\u043f\u043f\u0430\u0439\u0441\u0430\u0439"
    ],
    "wof:name":"Lippaysay",
    "wof:placetype":"locality"
},
  "geometry": {"coordinates":[79.44162,43.11189],"type":"Point"}
}