{
  "type": "Feature",
  "properties": {
    "gn:admin1_code":"13.0",
    "gn:asciiname":"Stepnoe",
    "gn:country_code":"KZ",
    "gn:dem":179,
    "gn:feature_class":"P",
    "gn:feature_code":"PPL",
    "gn:name":"Stepnoe",
    "gn:population":0,
    "gn:timezone":"Asia/Qyzylorda",
    "iso:country":"KZ",
    "name:kaz_x_preferred":[
        "Stepnoe"
    ],
    "name:kaz_x_variant":[
        "\u0421\u0442\u0435\u043f\u043d\u043e\u0435"
    ],
    "name:und_x_variant":[
        "Stepnoye"
    ],
    "wof:name":"Stepnoe",
    "wof:placetype":"locality"
},
  "geometry": {"coordinates":[63.01351,53.87606],"type":"Point"}
}