{
  "type": "Feature",
  "properties": {
    "gn:admin1_code":"13.0",
    "gn:asciiname":"Zhanaaul",
    "gn:country_code":"KZ",
    "gn:dem":224,
    "gn:feature_class":"P",
    "gn:feature_code":"PPL",
    "gn:name":"Zhanaaul",
    "gn:population":0,
    "gn:timezone":"Asia/Qyzylorda",
    "iso:country":"KZ",
    "name:kaz_x_preferred":[
        "Zhangaa\u016byl"
    ],
    "name:kaz_x_variant":[
        "\u0416\u0430\u04a3\u0430\u0430\u0443\u044b\u043b"
    ],
    "name:rus_x_preferred":[
        "\u0416\u0430\u043d\u0430\u0430\u0443\u043b"
    ],
    "name:rus_x_variant":[
        "\u041d\u0438\u043a\u0438\u0444\u043e\u0440\u043e\u0432\u043a\u0430"
    ],
    "name:und_x_variant":[
        "Zhanaul",
        "Zhanaaul",
        "Nikiforovka"
    ],
    "wof:name":"Zhanaaul",
    "wof:placetype":"locality"
},
  "geometry": {"coordinates":[61.53514000000001,53.97201],"type":"Point"}
}