{
  "type": "Feature",
  "properties": {
    "gn:admin1_code":"10.0",
    "gn:asciiname":"Bakhabulak",
    "gn:country_code":"KZ",
    "gn:dem":440,
    "gn:feature_class":"P",
    "gn:feature_code":"PPL",
    "gn:name":"Bakhabulak",
    "gn:population":0,
    "gn:timezone":"Asia/Almaty",
    "iso:country":"KZ",
    "name:rus_x_preferred":[
        "\u0411\u0430\u0445\u0430\u0431\u0443\u043b\u0430\u043a"
    ],
    "name:und_x_variant":[
        "Bakabulak"
    ],
    "wof:name":"Bakhabulak",
    "wof:placetype":"locality"
},
  "geometry": {"coordinates":[69.00502,41.95267],"type":"Point"}
}