{
  "type": "Feature",
  "properties": {
    "gn:admin1_code":"4.0",
    "gn:asciiname":"Zhalanash",
    "gn:country_code":"KZ",
    "gn:dem":319,
    "gn:feature_class":"P",
    "gn:feature_code":"PPL",
    "gn:name":"Zhalanash",
    "gn:population":0,
    "gn:timezone":"Asia/Aqtobe",
    "iso:country":"KZ",
    "name:eng_x_preferred":[
        "Zhalanash"
    ],
    "name:rus_x_preferred":[
        "\u0416\u0430\u043b\u0430\u043d\u0430\u0448"
    ],
    "wof:name":"Zhalanash",
    "wof:placetype":"locality"
},
  "geometry": {"coordinates":[58.23333,49.21667],"type":"Point"}
}