{
  "type": "Feature",
  "properties": {
    "gn:admin1_code":"14.0",
    "gn:asciiname":"Il'ich",
    "gn:country_code":"KZ",
    "gn:dem":498,
    "gn:feature_class":"P",
    "gn:feature_code":"PPL",
    "gn:name":"Il\u2019ich",
    "gn:population":0,
    "gn:timezone":"Asia/Almaty",
    "iso:country":"KZ",
    "name:rus_x_preferred":[
        "Il\u2019ich"
    ],
    "name:rus_x_variant":[
        "\u0418\u043b\u044c\u0438\u0447"
    ],
    "wof:name":"Il'ich",
    "wof:placetype":"locality"
},
  "geometry": {"coordinates":[71.08789,43.04924000000001],"type":"Point"}
}