{
  "type": "Feature",
  "properties": {
    "gn:admin1_code":"10.0",
    "gn:asciiname":"Amansay",
    "gn:country_code":"KZ",
    "gn:dem":490,
    "gn:feature_class":"P",
    "gn:feature_code":"PPL",
    "gn:name":"Amansay",
    "gn:population":0,
    "gn:timezone":"Asia/Almaty",
    "iso:country":"KZ",
    "name:kaz_x_preferred":[
        "Amansay"
    ],
    "name:kaz_x_variant":[
        "\u0410\u043c\u0430\u043d\u0441\u0430\u0439"
    ],
    "wof:name":"Amansay",
    "wof:placetype":"locality"
},
  "geometry": {"coordinates":[69.76221,42.6684],"type":"Point"}
}