{
  "type": "Feature",
  "properties": {
    "gn:admin1_code":"12.0",
    "gn:asciiname":"Aqbay-Qyzylbay",
    "gn:country_code":"KZ",
    "gn:dem":998,
    "gn:feature_class":"P",
    "gn:feature_code":"PPL",
    "gn:name":"Aqbay-Qyzylbay",
    "gn:population":0,
    "gn:timezone":"Asia/Almaty",
    "iso:country":"KZ",
    "name:kaz_x_preferred":[
        "Aqbay-Qyzylbay"
    ],
    "name:kaz_x_variant":[
        "\u0410\u049b\u0431\u0430\u0439-\u049a\u044b\u0437\u044b\u043b\u0431\u0430\u0439"
    ],
    "name:rus_x_preferred":[
        "\u0410\u043a\u0431\u0430\u0439-\u041a\u044b\u0437\u044b\u043b\u0431\u0430\u0439"
    ],
    "name:und_x_variant":[
        "Akbay-Kyzylbay"
    ],
    "wof:name":"Aqbay-Qyzylbay",
    "wof:placetype":"locality"
},
  "geometry": {"coordinates":[76.02325,49.05194],"type":"Point"}
}