{
  "type": "Feature",
  "properties": {
    "gn:admin1_code":"11.0",
    "gn:asciiname":"Kas'yanovka",
    "gn:country_code":"KZ",
    "gn:dem":130,
    "gn:feature_class":"P",
    "gn:feature_code":"PPL",
    "gn:name":"Kas\u2019yanovka",
    "gn:population":0,
    "gn:timezone":"Asia/Almaty",
    "iso:country":"KZ",
    "name:rus_x_preferred":[
        "Kas\u2019yanovka"
    ],
    "wof:name":"Kas'yanovka",
    "wof:placetype":"locality"
},
  "geometry": {"coordinates":[77.90000000000001,52.71666999999999],"type":"Point"}
}