{
  "type": "Feature",
  "properties": {
    "gn:admin1_code":"10.0",
    "gn:asciiname":"Brigada Nomer Tri Otdeleniya Nomer Dva Sovkhoza Imeni Tridtsatiletiya Oktyabrya",
    "gn:country_code":"KZ",
    "gn:dem":261,
    "gn:feature_class":"P",
    "gn:feature_code":"PPLF",
    "gn:name":"Brigada Nomer Tri Otdeleniya Nomer Dva Sovkhoza Imeni Tridtsatiletiya Oktyabrya",
    "gn:population":0,
    "gn:timezone":"Asia/Almaty",
    "iso:country":"KZ",
    "name:rus_x_preferred":[
        "\u0411\u0440\u0438\u0433\u0430\u0434\u0430 \u041d\u043e\u043c\u0435\u0440 \u0422\u0440\u0438 \u041e\u0442\u0434\u0435\u043b\u0435\u043d\u0438\u044f \u041d\u043e\u043c\u0435\u0440 \u0414\u0432\u0430 \u0421\u043e\u0432\u0445\u043e\u0437\u0430 \u0418\u043c\u0435\u043d\u0438 \u0422\u0440\u0438\u0434\u0446\u0430\u0442\u0438\u043b\u0435\u0442\u0438\u044f \u041e\u043a\u0442\u044f\u0431\u0440\u044f"
    ],
    "wof:name":"Brigada Nomer Tri Otdeleniya Nomer Dva Sovkhoza Imeni Tridtsatiletiya Oktyabrya",
    "wof:placetype":"locality"
},
  "geometry": {"coordinates":[68.24795999999999,40.94893],"type":"Point"}
}