{
  "type": "Feature",
  "properties": {
    "gn:admin1_code":"10.0",
    "gn:asciiname":"Bairkum",
    "gn:country_code":"KZ",
    "gn:dem":213,
    "gn:feature_class":"P",
    "gn:feature_code":"PPL",
    "gn:name":"Bairkum",
    "gn:population":0,
    "gn:timezone":"Asia/Almaty",
    "iso:country":"KZ",
    "name:kaz_x_preferred":[
        "\u0411\u0430\u0439\u044b\u0440\u049b\u04b1\u043c"
    ],
    "name:rus_x_preferred":[
        "\u0411\u0430\u0438\u0440\u043a\u0443\u043c"
    ],
    "name:und_x_variant":[
        "Sovkhoz Bairkum",
        "Bayrakkum",
        "Bayrkum",
        "Bayyrqum"
    ],
    "wof:name":"Bairkum",
    "wof:placetype":"locality"
},
  "geometry": {"coordinates":[68.14446,42.11983],"type":"Point"}
}