{
  "type": "Feature",
  "properties": {
    "gn:admin1_code":"12.0",
    "gn:asciiname":"Karadyn",
    "gn:country_code":"KZ",
    "gn:dem":822,
    "gn:feature_class":"P",
    "gn:feature_code":"PPL",
    "gn:name":"Karadyn",
    "gn:population":0,
    "gn:timezone":"Asia/Almaty",
    "iso:country":"KZ",
    "name:rus_x_preferred":[
        "\u041a\u0430\u0440\u0430\u0434\u044b\u043d"
    ],
    "wof:name":"Karadyn",
    "wof:placetype":"locality"
},
  "geometry": {"coordinates":[77.03276,48.25216],"type":"Point"}
}