{
  "type": "Feature",
  "properties": {
    "gn:admin1_code":"15.0",
    "gn:asciiname":"Stolboukha",
    "gn:country_code":"KZ",
    "gn:dem":579,
    "gn:feature_class":"P",
    "gn:feature_code":"PPL",
    "gn:name":"Stolboukha",
    "gn:population":0,
    "gn:timezone":"Asia/Almaty",
    "iso:country":"KZ",
    "name:eng_x_preferred":[
        "Stolbo\u016bkha"
    ],
    "name:kaz_x_preferred":[
        "\u0421\u0442\u043e\u043b\u0431\u043e\u0443\u0445\u0430"
    ],
    "name:rus_x_preferred":[
        "\u0421\u0442\u043e\u043b\u0431\u0443\u0445\u0430"
    ],
    "name:und_x_variant":[
        "Stolboukha"
    ],
    "wof:name":"Stolboukha",
    "wof:placetype":"locality"
},
  "geometry": {"coordinates":[84.47709999999999,49.97649000000001],"type":"Point"}
}