{
  "type": "Feature",
  "properties": {
    "gn:admin1_code":"16.0",
    "gn:asciiname":"Sergino",
    "gn:country_code":"KZ",
    "gn:dem":129,
    "gn:feature_class":"P",
    "gn:feature_code":"PPL",
    "gn:name":"Sergino",
    "gn:population":0,
    "gn:timezone":"Asia/Almaty",
    "iso:country":"KZ",
    "name:rus_x_preferred":[
        "\u0421\u0435\u0440\u0433\u0438\u043d\u043e"
    ],
    "wof:name":"Sergino",
    "wof:placetype":"locality"
},
  "geometry": {"coordinates":[69.00471999999999,55.24468],"type":"Point"}
}