{
  "type": "Feature",
  "properties": {
    "gn:admin1_code":"14.0",
    "gn:asciiname":"Algabas",
    "gn:country_code":"KZ",
    "gn:dem":677,
    "gn:feature_class":"P",
    "gn:feature_code":"PPL",
    "gn:name":"Algabas",
    "gn:population":0,
    "gn:timezone":"Asia/Almaty",
    "iso:country":"KZ",
    "name:fas_x_preferred":[
        "\u0627\u0644\u06af\u0627\u0628\u0627\u0633"
    ],
    "name:mkd_x_preferred":[
        "\u0410\u043b\u0433\u0430\u0431\u0430\u0441"
    ],
    "name:msa_x_preferred":[
        "Algabas"
    ],
    "name:rus_x_preferred":[
        "\u0410\u043b\u0433\u0430\u0431\u0430\u0441"
    ],
    "wof:name":"Algabas",
    "wof:placetype":"locality"
},
  "geometry": {"coordinates":[71.89473000000002,42.95263],"type":"Point"}
}