{
  "type": "Feature",
  "properties": {
    "gn:admin1_code":"3.0",
    "gn:asciiname":"Chashke",
    "gn:country_code":"KZ",
    "gn:dem":346,
    "gn:feature_class":"P",
    "gn:feature_code":"PPL",
    "gn:name":"Chashke",
    "gn:population":0,
    "gn:timezone":"Asia/Almaty",
    "iso:country":"KZ",
    "name:eng_x_preferred":[
        "Chashke"
    ],
    "name:kaz_x_preferred":[
        "Sh\u00e4shke"
    ],
    "name:kaz_x_variant":[
        "\u0428\u04d9\u0448\u043a\u0435"
    ],
    "name:rus_x_preferred":[
        "\u0427\u0430\u0448\u043a\u0435"
    ],
    "name:und_x_variant":[
        "Shashke",
        "Barankul\u2019skiy",
        "Chashke"
    ],
    "wof:name":"Chashke",
    "wof:placetype":"locality"
},
  "geometry": {"coordinates":[68.0395,52.312],"type":"Point"}
}