{
  "type": "Feature",
  "properties": {
    "gn:admin1_code":"10.0",
    "gn:asciiname":"Kyzylsu",
    "gn:country_code":"KZ",
    "gn:dem":696,
    "gn:feature_class":"P",
    "gn:feature_code":"PPL",
    "gn:name":"Kyzylsu",
    "gn:population":0,
    "gn:timezone":"Asia/Almaty",
    "iso:country":"KZ",
    "name:rus_x_preferred":[
        "\u041a\u044b\u0437\u044b\u043b\u0441\u0443"
    ],
    "name:rus_x_variant":[
        "\u0422\u0443\u0432\u0430\u043b\u0430\u043a\u0441\u0430\u0439"
    ],
    "name:und_x_variant":[
        "Tuvalaksay"
    ],
    "wof:name":"Kyzylsu",
    "wof:placetype":"locality"
},
  "geometry": {"coordinates":[69.80959,42.3451],"type":"Point"}
}