{
  "type": "Feature",
  "properties": {
    "gn:admin1_code":"0.0",
    "gn:asciiname":"Dzhger",
    "gn:country_code":"KZ",
    "gn:dem":-2,
    "gn:feature_class":"P",
    "gn:feature_code":"PPL",
    "gn:name":"Dzhger",
    "gn:population":0,
    "gn:timezone":"Asia/Oral",
    "iso:country":"KZ",
    "wof:name":"Dzhger",
    "wof:placetype":"locality"
},
  "geometry": {"coordinates":[47.92444,48.70139],"type":"Point"}
}