{
  "type": "Feature",
  "properties": {
    "gn:admin1_code":"16.0",
    "gn:asciiname":"Oktyabr'skoye",
    "gn:country_code":"KZ",
    "gn:dem":152,
    "gn:feature_class":"P",
    "gn:feature_code":"PPL",
    "gn:name":"Oktyabr\u2019skoye",
    "gn:population":0,
    "gn:timezone":"Asia/Almaty",
    "iso:country":"KZ",
    "name:kaz_x_preferred":[
        "Oktyabr\u2019skoe"
    ],
    "name:kaz_x_variant":[
        "\u041e\u043a\u0442\u044f\u0431\u0440\u044c\u0441\u043a\u043e\u0435"
    ],
    "name:rus_x_preferred":[
        "Oktyabr\u2019skoye"
    ],
    "name:rus_x_variant":[
        "Sovkhoz Oktyabr\u2019skiy",
        "Oktyabr\u2019skiy"
    ],
    "name:und_x_variant":[
        "Oktyabr\u2019"
    ],
    "wof:name":"Oktyabr'skoye",
    "wof:placetype":"locality"
},
  "geometry": {"coordinates":[67.08083000000001,53.53764],"type":"Point"}
}