{
  "type": "Feature",
  "properties": {
    "gn:admin1_code":"0.0",
    "gn:asciiname":"Imeni Kirova",
    "gn:country_code":"KZ",
    "gn:dem":705,
    "gn:feature_class":"P",
    "gn:feature_code":"PPL",
    "gn:name":"Imeni Kirova",
    "gn:population":0,
    "gn:timezone":"Asia/Almaty",
    "iso:country":"KZ",
    "name:ceb_x_preferred":[
        "Imeni Kirova"
    ],
    "name:swe_x_preferred":[
        "Imeni Kirova"
    ],
    "wof:name":"Imeni Kirova",
    "wof:placetype":"locality"
},
  "geometry": {"coordinates":[78.68333,48.23333],"type":"Point"}
}