{
  "type": "Feature",
  "properties": {
    "gn:admin1_code":"1.0",
    "gn:asciiname":"Dzhanek",
    "gn:country_code":"KZ",
    "gn:dem":654,
    "gn:feature_class":"P",
    "gn:feature_code":"PPL",
    "gn:name":"Dzhanek",
    "gn:population":0,
    "gn:timezone":"Asia/Almaty",
    "iso:country":"KZ",
    "name:mkd_x_preferred":[
        "\u040f\u0430\u043d\u0435\u043a"
    ],
    "name:msa_x_preferred":[
        "Dzhanek"
    ],
    "wof:name":"Dzhanek",
    "wof:placetype":"locality"
},
  "geometry": {"coordinates":[76.90000000000001,43.41667],"type":"Point"}
}