{
  "type": "Feature",
  "properties": {
    "gn:admin1_code":"4.0",
    "gn:asciiname":"Novopokrovskiy",
    "gn:country_code":"KZ",
    "gn:dem":351,
    "gn:feature_class":"P",
    "gn:feature_code":"PPL",
    "gn:name":"Novopokrovskiy",
    "gn:population":0,
    "gn:timezone":"Asia/Aqtobe",
    "iso:country":"KZ",
    "wof:name":"Novopokrovskiy",
    "wof:placetype":"locality"
},
  "geometry": {"coordinates":[57.58333,50.76667],"type":"Point"}
}