{
  "type": "Feature",
  "properties": {
    "gn:admin1_code":"15.0",
    "gn:asciiname":"Aray",
    "gn:country_code":"KZ",
    "gn:dem":682,
    "gn:feature_class":"P",
    "gn:feature_code":"PPL",
    "gn:name":"Aray",
    "gn:population":0,
    "gn:timezone":"Asia/Almaty",
    "iso:country":"KZ",
    "name:rus_x_preferred":[
        "\u0410\u0440\u0430\u0439"
    ],
    "wof:name":"Aray",
    "wof:placetype":"locality"
},
  "geometry": {"coordinates":[79.93392,48.4364],"type":"Point"}
}