{
  "type": "Feature",
  "properties": {
    "gn:admin1_code":"13.0",
    "gn:asciiname":"Shcherbakovo",
    "gn:country_code":"KZ",
    "gn:dem":189,
    "gn:feature_class":"P",
    "gn:feature_code":"PPL",
    "gn:name":"Shcherbakovo",
    "gn:population":0,
    "gn:timezone":"Asia/Qyzylorda",
    "iso:country":"KZ",
    "name:eng_x_preferred":[
        "Shcherbakovo"
    ],
    "name:kaz_x_preferred":[
        "Shcherbakovo"
    ],
    "name:kaz_x_variant":[
        "\u0429\u0435\u0440\u0431\u0430\u043a\u043e\u0432\u043e"
    ],
    "name:rus_x_preferred":[
        "\u041a\u043e\u0431\u043b\u0430\u043d\u0434\u044b"
    ],
    "name:und_x_variant":[
        "Kobylandy",
        "Koblandy"
    ],
    "wof:name":"Shcherbakovo",
    "wof:placetype":"locality"
},
  "geometry": {"coordinates":[64.21172,53.17251],"type":"Point"}
}