{
  "type": "Feature",
  "properties": {
    "gn:admin1_code":"16.0",
    "gn:asciiname":"Novopokrovka",
    "gn:country_code":"KZ",
    "gn:dem":182,
    "gn:feature_class":"P",
    "gn:feature_code":"PPL",
    "gn:name":"Novopokrovka",
    "gn:population":0,
    "gn:timezone":"Asia/Almaty",
    "iso:country":"KZ",
    "name:eng_x_preferred":[
        "Novopokrovka"
    ],
    "name:kaz_x_preferred":[
        "Novopokrovka"
    ],
    "name:kaz_x_variant":[
        "\u041d\u043e\u0432\u043e\u043f\u043e\u043a\u0440\u043e\u0432\u043a\u0430"
    ],
    "name:rus_x_preferred":[
        "\u041d\u043e\u0432\u043e\u043f\u043e\u043a\u0440\u043e\u0432\u043a\u0430"
    ],
    "name:und_x_variant":[
        "Sovkhoz Novopokrovskiy",
        "Novopokrovskiy"
    ],
    "wof:name":"Novopokrovka",
    "wof:placetype":"locality"
},
  "geometry": {"coordinates":[67.75369000000001,53.73081],"type":"Point"}
}