{
  "type": "Feature",
  "properties": {
    "gn:admin1_code":"0.0",
    "gn:asciiname":"Isa",
    "gn:country_code":"KZ",
    "gn:dem":252,
    "gn:feature_class":"P",
    "gn:feature_code":"PPL",
    "gn:name":"Isa",
    "gn:population":0,
    "gn:timezone":"Asia/Almaty",
    "iso:country":"KZ",
    "name:bel_x_preferred":[
        "\u0406\u0441\u0430"
    ],
    "name:bos_x_preferred":[
        "Isa"
    ],
    "name:bul_x_preferred":[
        "\u0418\u0441\u0430"
    ],
    "name:ceb_x_preferred":[
        "Isa"
    ],
    "name:che_x_preferred":[
        "\u04c0\u0438\u0439\u0441\u0430"
    ],
    "name:deu_x_preferred":[
        "Isa"
    ],
    "name:fin_x_preferred":[
        "Isa"
    ],
    "name:heb_x_preferred":[
        "\u05e2\u05d9\u05e1\u05d0"
    ],
    "name:hin_x_preferred":[
        "\u0908\u0938\u093e"
    ],
    "name:hrv_x_preferred":[
        "Isa"
    ],
    "name:ind_x_preferred":[
        "Isa"
    ],
    "name:jpn_x_preferred":[
        "\u30a4\u30c3\u30b5"
    ],
    "name:pol_x_preferred":[
        "Isa"
    ],
    "name:por_x_preferred":[
        "Isa"
    ],
    "name:rus_x_preferred":[
        "\u0418\u0441\u0430"
    ],
    "name:spa_x_preferred":[
        "Isa"
    ],
    "name:sun_x_preferred":[
        "Isa"
    ],
    "name:swe_x_preferred":[
        "Isa"
    ],
    "name:ukr_x_preferred":[
        "\u0406\u0441\u0430"
    ],
    "wof:name":"Isa",
    "wof:placetype":"locality"
},
  "geometry": {"coordinates":[79.26666999999998,50.18333],"type":"Point"}
}