{
  "type": "Feature",
  "properties": {
    "gn:admin1_code":"0.0",
    "gn:asciiname":"Isa",
    "gn:country_code":"KZ",
    "gn:dem":252,
    "gn:feature_class":"P",
    "gn:feature_code":"PPL",
    "gn:name":"Isa",
    "gn:population":0,
    "gn:timezone":"Asia/Almaty",
    "iso:country":"KZ",
    "wof:name":"Isa",
    "wof:placetype":"locality"
},
  "geometry": {"coordinates":[79.26666999999998,50.18333],"type":"Point"}
}