{
  "type": "Feature",
  "properties": {
    "gn:admin1_code":"3.0",
    "gn:asciiname":"Kiyevskiy",
    "gn:country_code":"KZ",
    "gn:dem":360,
    "gn:feature_class":"P",
    "gn:feature_code":"PPL",
    "gn:name":"Kiyevskiy",
    "gn:population":0,
    "gn:timezone":"Asia/Almaty",
    "iso:country":"KZ",
    "name:eng_x_preferred":[
        "Kiyevskiy"
    ],
    "name:kaz_x_preferred":[
        "K\u012bevsk\u012by"
    ],
    "name:kaz_x_variant":[
        "\u041a\u0438\u0435\u0432\u0441\u043a\u0438\u0439"
    ],
    "name:rus_x_preferred":[
        "\u041a\u0438\u0435\u0432\u0441\u043a\u0438\u0439"
    ],
    "wof:name":"Kiyevskiy",
    "wof:placetype":"locality"
},
  "geometry": {"coordinates":[67.68695,52.05138],"type":"Point"}
}