{
  "type": "Feature",
  "properties": {
    "gn:admin1_code":"12.0",
    "gn:asciiname":"Yuzhnyy",
    "gn:country_code":"KZ",
    "gn:dem":554,
    "gn:feature_class":"P",
    "gn:feature_code":"PPL",
    "gn:name":"Yuzhnyy",
    "gn:population":0,
    "gn:timezone":"Asia/Almaty",
    "iso:country":"KZ",
    "name:kaz_x_preferred":[
        "Yuzhnyy"
    ],
    "name:kaz_x_variant":[
        "\u042e\u0436\u043d\u044b\u0439"
    ],
    "wof:name":"Yuzhnyy",
    "wof:placetype":"locality"
},
  "geometry": {"coordinates":[72.90512,49.35932],"type":"Point"}
}