{
  "type": "Feature",
  "properties": {
    "gn:admin1_code":"0.0",
    "gn:asciiname":"Kosoba",
    "gn:cc2":"KZ",
    "gn:country_code":"KZ",
    "gn:dem":6,
    "gn:feature_class":"P",
    "gn:feature_code":"PPL",
    "gn:name":"Kosoba",
    "gn:population":0,
    "gn:timezone":"Asia/Oral",
    "iso:country":"KZ",
    "name:und_x_variant":[
        "Kos-Uba",
        "Kosoba"
    ],
    "wof:name":"Kosoba",
    "wof:placetype":"locality"
},
  "geometry": {"coordinates":[50.55,49.76667],"type":"Point"}
}