{
  "type": "Feature",
  "properties": {
    "gn:admin1_code":"0.0",
    "gn:asciiname":"Imeni Kazakhskogo TSIKa",
    "gn:country_code":"KZ",
    "gn:dem":415,
    "gn:feature_class":"P",
    "gn:feature_code":"PPL",
    "gn:name":"Imeni Kazakhskogo TSIKa",
    "gn:population":0,
    "gn:timezone":"Asia/Almaty",
    "iso:country":"KZ",
    "wof:name":"Imeni Kazakhskogo TSIKa",
    "wof:placetype":"locality"
},
  "geometry": {"coordinates":[71.23333000000002,51.76667],"type":"Point"}
}