{
  "type": "Feature",
  "properties": {
    "gn:admin1_code":"17.0",
    "gn:asciiname":"Kak Baydybek",
    "gn:country_code":"KZ",
    "gn:dem":528,
    "gn:feature_class":"P",
    "gn:feature_code":"PPL",
    "gn:name":"Kak Baydybek",
    "gn:population":0,
    "gn:timezone":"Asia/Almaty",
    "iso:country":"KZ",
    "name:und_x_variant":[
        "Kak Bayd\u00f6bek",
        "Kak Baydybek"
    ],
    "wof:name":"Kak Baydybek",
    "wof:placetype":"locality"
},
  "geometry": {"coordinates":[75.08333,44.25],"type":"Point"}
}