{
  "type": "Feature",
  "properties": {
    "gn:admin1_code":"11.0",
    "gn:asciiname":"Maykain",
    "gn:country_code":"KZ",
    "gn:dem":152,
    "gn:feature_class":"P",
    "gn:feature_code":"PPL",
    "gn:name":"Maykain",
    "gn:population":0,
    "gn:timezone":"Asia/Almaty",
    "iso:country":"KZ",
    "wof:name":"Maykain",
    "wof:placetype":"locality"
},
  "geometry": {"coordinates":[75.63231,51.79724],"type":"Point"}
}