{
  "type": "Feature",
  "properties": {
    "gn:admin1_code":"13.0",
    "gn:asciiname":"Korzhynkol'",
    "gn:country_code":"KZ",
    "gn:dem":205,
    "gn:feature_class":"P",
    "gn:feature_code":"PPL",
    "gn:name":"Korzhynkol\u2019",
    "gn:population":0,
    "gn:timezone":"Asia/Qyzylorda",
    "iso:country":"KZ",
    "name:eng_x_preferred":[
        "Korzhynkol'"
    ],
    "name:rus_x_preferred":[
        "\u041a\u043e\u0440\u0436\u0438\u043d\u043a\u043e\u043b\u044c"
    ],
    "name:rus_x_variant":[
        "Korzhynkol\u2019"
    ],
    "name:und_x_variant":[
        "Korzhinkol\u2019"
    ],
    "wof:name":"Korzhynkol'",
    "wof:placetype":"locality"
},
  "geometry": {"coordinates":[62.90871,52.57905],"type":"Point"}
}