{
  "type": "Feature",
  "properties": {
    "gn:admin1_code":"0.0",
    "gn:asciiname":"Zamorenov",
    "gn:cc2":"KZ",
    "gn:country_code":"KZ",
    "gn:dem":31,
    "gn:feature_class":"P",
    "gn:feature_code":"PPL",
    "gn:name":"Zamorenov",
    "gn:population":0,
    "gn:timezone":"Asia/Oral",
    "iso:country":"KZ",
    "name:und_x_variant":[
        "Zamorennoye",
        "Zamorenov"
    ],
    "wof:name":"Zamorenov",
    "wof:placetype":"locality"
},
  "geometry": {"coordinates":[51.48333,51.46667],"type":"Point"}
}