{
  "type": "Feature",
  "properties": {
    "iso:country":"KZ",
    "name:eng_x_preferred":[
        "As\u016bbulaq"
    ],
    "name:rus_x_preferred":[
        "\u0410\u0441\u0443\u0431\u0443\u043b\u0430\u043a"
    ],
    "qs:gn_country":"KZ",
    "qs:gn_fcode":"PPL",
    "qs:gn_pop":5644,
    "qs:name":"Asubulak",
    "qs:name_adm0":"Kazakhstan",
    "qs:name_adm1":"Shyghys Qazaqstan",
    "qs:photos":0,
    "qs:photos_1k":0,
    "qs:photos_9k":1,
    "qs:photos_9r":1,
    "qs:photos_all":2,
    "qs:photos_sr":0,
    "qs:placetype":"Town",
    "qs:pop_sr":"5",
    "qs:woe_adm0":23424871,
    "wof:name":"Asubulak",
    "wof:placetype":"locality",
    "wof:population":5644
},
  "geometry": {"coordinates":[83.06355000000001,49.55688],"type":"Point"}
}