{
  "type": "Feature",
  "properties": {
    "gn:admin1_code":"11.0",
    "gn:asciiname":"Baskuduk",
    "gn:country_code":"KZ",
    "gn:dem":124,
    "gn:feature_class":"P",
    "gn:feature_code":"PPL",
    "gn:name":"Baskuduk",
    "gn:population":0,
    "gn:timezone":"Asia/Almaty",
    "iso:country":"KZ",
    "name:rus_x_preferred":[
        "\u0411\u0430\u0441\u043a\u0443\u0434\u0443\u043a"
    ],
    "wof:name":"Baskuduk",
    "wof:placetype":"locality"
},
  "geometry": {"coordinates":[77.44580000000001,52.29245],"type":"Point"}
}