{
  "type": "Feature",
  "properties": {
    "gn:admin1_code":"0.0",
    "gn:asciiname":"Kosyl'",
    "gn:country_code":"KZ",
    "gn:dem":40,
    "gn:feature_class":"P",
    "gn:feature_code":"PPL",
    "gn:name":"Kosyl\u2019",
    "gn:population":0,
    "gn:timezone":"Asia/Oral",
    "iso:country":"KZ",
    "wof:name":"Kosyl'",
    "wof:placetype":"locality"
},
  "geometry": {"coordinates":[48.06667,48.96667],"type":"Point"}
}