{
  "type": "Feature",
  "properties": {
    "gn:admin1_code":"4.0",
    "gn:asciiname":"Qarakol",
    "gn:country_code":"KZ",
    "gn:dem":67,
    "gn:feature_class":"P",
    "gn:feature_code":"PPL",
    "gn:name":"Qarak\u00f6l",
    "gn:population":0,
    "gn:timezone":"Asia/Aqtobe",
    "iso:country":"KZ",
    "name:und_x_variant":[
        "Kara-Kul\u2019",
        "Qarak\u00f6l"
    ],
    "wof:name":"Qarakol",
    "wof:placetype":"locality"
},
  "geometry": {"coordinates":[55.46666999999999,46.88333],"type":"Point"}
}