{
  "type": "Feature",
  "properties": {
    "gn:admin1_code":"16.0",
    "gn:asciiname":"Mokhovoye",
    "gn:country_code":"KZ",
    "gn:dem":169,
    "gn:feature_class":"P",
    "gn:feature_code":"PPL",
    "gn:name":"Mokhovoye",
    "gn:population":0,
    "gn:timezone":"Asia/Almaty",
    "iso:country":"KZ",
    "name:rus_x_preferred":[
        "\u041c\u043e\u0445\u043e\u0432\u043e\u0435"
    ],
    "wof:name":"Mokhovoye",
    "wof:placetype":"locality"
},
  "geometry": {"coordinates":[66.3518,53.81438000000001],"type":"Point"}
}