{
  "type": "Feature",
  "properties": {
    "gn:admin1_code":"4.0",
    "gn:asciiname":"Tuskainsay",
    "gn:country_code":"KZ",
    "gn:dem":306,
    "gn:feature_class":"P",
    "gn:feature_code":"PPL",
    "gn:name":"Tuskainsay",
    "gn:population":0,
    "gn:timezone":"Asia/Aqtobe",
    "iso:country":"KZ",
    "wof:name":"Tuskainsay",
    "wof:placetype":"locality"
},
  "geometry": {"coordinates":[57.71666999999999,50.23333],"type":"Point"}
}