{
  "type": "Feature",
  "properties": {
    "gn:admin1_code":"0.0",
    "gn:asciiname":"Buyre",
    "gn:cc2":"KZ",
    "gn:country_code":"KZ",
    "gn:dem":110,
    "gn:feature_class":"P",
    "gn:feature_code":"PPL",
    "gn:name":"Buyre",
    "gn:population":0,
    "gn:timezone":"Asia/Almaty",
    "iso:country":"KZ",
    "name:und_x_variant":[
        "Buyrek",
        "Buyre"
    ],
    "wof:name":"Buyre",
    "wof:placetype":"locality"
},
  "geometry": {"coordinates":[63.58333,49.45],"type":"Point"}
}