{
  "type": "Feature",
  "properties": {
    "gn:admin1_code":"6.0",
    "gn:asciiname":"Akpuka",
    "gn:country_code":"KZ",
    "gn:dem":-8,
    "gn:feature_class":"P",
    "gn:feature_code":"PPL",
    "gn:name":"Akpuka",
    "gn:population":0,
    "gn:timezone":"Asia/Atyrau",
    "iso:country":"KZ",
    "wof:name":"Akpuka",
    "wof:placetype":"locality"
},
  "geometry": {"coordinates":[47.86583,47.86583],"type":"Point"}
}