{
  "type": "Feature",
  "properties": {
    "gn:admin1_code":"0.0",
    "gn:asciiname":"Zakladnov",
    "gn:country_code":"KZ",
    "gn:dem":22,
    "gn:feature_class":"P",
    "gn:feature_code":"PPL",
    "gn:name":"Zakladnov",
    "gn:population":0,
    "gn:timezone":"Asia/Oral",
    "iso:country":"KZ",
    "wof:name":"Zakladnov",
    "wof:placetype":"locality"
},
  "geometry": {"coordinates":[50.81667,50.76667],"type":"Point"}
}