{
  "type": "Feature",
  "properties": {
    "gn:admin1_code":"0.0",
    "gn:asciiname":"Bushali",
    "gn:country_code":"KZ",
    "gn:dem":-5,
    "gn:feature_class":"P",
    "gn:feature_code":"PPL",
    "gn:name":"Bushali",
    "gn:population":0,
    "gn:timezone":"Asia/Oral",
    "iso:country":"KZ",
    "wof:name":"Bushali",
    "wof:placetype":"locality"
},
  "geometry": {"coordinates":[48.85,48.63333],"type":"Point"}
}