{
  "type": "Feature",
  "properties": {
    "gn:admin1_code":"15.0",
    "gn:asciiname":"Kryukovka",
    "gn:country_code":"KZ",
    "gn:dem":341,
    "gn:feature_class":"P",
    "gn:feature_code":"PPL",
    "gn:name":"Kryukovka",
    "gn:population":0,
    "gn:timezone":"Asia/Almaty",
    "iso:country":"KZ",
    "name:kaz_x_preferred":[
        "Kryukovka"
    ],
    "name:kaz_x_variant":[
        "\u041a\u0440\u044e\u043a\u043e\u0432\u043a\u0430"
    ],
    "wof:name":"Kryukovka",
    "wof:placetype":"locality"
},
  "geometry": {"coordinates":[82.16715000000001,50.55718],"type":"Point"}
}