{
  "type": "Feature",
  "properties": {
    "gn:admin1_code":"11.0",
    "gn:asciiname":"Ol'gino",
    "gn:country_code":"KZ",
    "gn:dem":111,
    "gn:feature_class":"P",
    "gn:feature_code":"PPL",
    "gn:name":"Ol\u2019gino",
    "gn:population":0,
    "gn:timezone":"Asia/Almaty",
    "iso:country":"KZ",
    "name:kaz_x_preferred":[
        "Ol\u2019g\u012bno"
    ],
    "name:kaz_x_variant":[
        "\u041e\u043b\u044c\u0433\u0438\u043d\u043e"
    ],
    "name:und_x_variant":[
        "Ol\u2019ginskoye",
        "Ol\u2019gino"
    ],
    "wof:name":"Ol'gino",
    "wof:placetype":"locality"
},
  "geometry": {"coordinates":[77.02967,52.88314],"type":"Point"}
}