{
  "type": "Feature",
  "properties": {
    "gn:admin1_code":"0.0",
    "gn:asciiname":"Bestobe",
    "gn:country_code":"KZ",
    "gn:dem":264,
    "gn:feature_class":"P",
    "gn:feature_code":"PPL",
    "gn:name":"Bestobe",
    "gn:population":0,
    "gn:timezone":"Asia/Qyzylorda",
    "iso:country":"KZ",
    "name:eng_x_preferred":[
        "Bestobe"
    ],
    "name:rus_x_preferred":[
        "\u0411\u0435\u0441\u0442\u043e\u0431\u0435"
    ],
    "name:und_x_variant":[
        "Bistyubinskiy",
        "Bestobe"
    ],
    "wof:name":"Bestobe",
    "wof:placetype":"locality"
},
  "geometry": {"coordinates":[62.03235,51.9085],"type":"Point"}
}