{
  "type": "Feature",
  "properties": {
    "gn:admin1_code":"0.0",
    "gn:asciiname":"Bestobe",
    "gn:country_code":"KZ",
    "gn:dem":264,
    "gn:feature_class":"P",
    "gn:feature_code":"PPL",
    "gn:name":"Bestobe",
    "gn:population":0,
    "gn:timezone":"Asia/Qyzylorda",
    "iso:country":"KZ",
    "name:ara_x_preferred":[
        "\u0628\u064a\u0633\u062a\u0648\u0628\u064a"
    ],
    "name:ben_x_preferred":[
        "\u09ac\u09c7\u09b8\u09cd\u09a4\u09cb\u09ac\u09c7"
    ],
    "name:deu_x_preferred":[
        "Bestobe"
    ],
    "name:ell_x_preferred":[
        "\u039c\u03c0\u03ad\u03c3\u03c4\u03bf\u03bc\u03c0\u03b5"
    ],
    "name:eng_x_preferred":[
        "Bestobe"
    ],
    "name:fas_x_preferred":[
        "\u0628\u0633\u062a\u0648\u0628"
    ],
    "name:fra_x_preferred":[
        "Bestobe"
    ],
    "name:heb_x_preferred":[
        "\u05d1\u05e1\u05d8\u05d5\u05d1\u05d4"
    ],
    "name:hin_x_preferred":[
        "\u092c\u0947\u0938\u094d\u091f\u094b\u092c"
    ],
    "name:hun_x_preferred":[
        "Bestobe"
    ],
    "name:ind_x_preferred":[
        "Bestobe"
    ],
    "name:ita_x_preferred":[
        "Bestobe"
    ],
    "name:jpn_x_preferred":[
        "\u30d9\u30b9\u30c8\u30d9"
    ],
    "name:kor_x_preferred":[
        "\ubca0\uc2a4\ud1a0\ubca0"
    ],
    "name:pol_x_preferred":[
        "Bestobe"
    ],
    "name:por_x_preferred":[
        "Bestobe"
    ],
    "name:rus_x_preferred":[
        "\u0411\u0435\u0441\u0442\u043e\u0431\u0435"
    ],
    "name:swe_x_preferred":[
        "Bestobe"
    ],
    "name:tur_x_preferred":[
        "Bestobe"
    ],
    "name:und_x_variant":[
        "Bistyubinskiy"
    ],
    "name:urd_x_preferred":[
        "\u0628\u06cc\u0633\u0679\u0648\u0628\u06cc"
    ],
    "name:vie_x_preferred":[
        "Bestobe"
    ],
    "name:zho_cn_x_preferred":[
        "\u8d1d\u65af\u6258\u8d1d"
    ],
    "name:zho_tw_x_preferred":[
        "\u8c9d\u65af\u6258\u8c9d"
    ],
    "wof:name":"Bestobe",
    "wof:placetype":"locality"
},
  "geometry": {"coordinates":[62.03235,51.9085],"type":"Point"}
}