{
  "type": "Feature",
  "properties": {
    "gn:admin1_code":"16.0",
    "gn:asciiname":"Toman",
    "gn:country_code":"KZ",
    "gn:dem":120,
    "gn:feature_class":"P",
    "gn:feature_code":"PPL",
    "gn:name":"Toman",
    "gn:population":0,
    "gn:timezone":"Asia/Almaty",
    "iso:country":"KZ",
    "wof:name":"Toman",
    "wof:placetype":"locality"
},
  "geometry": {"coordinates":[71.41373,54.14641999999999],"type":"Point"}
}