{
  "type": "Feature",
  "properties": {
    "gn:admin1_code":"13.0",
    "gn:asciiname":"Bikilek",
    "gn:country_code":"KZ",
    "gn:dem":179,
    "gn:feature_class":"P",
    "gn:feature_code":"PPL",
    "gn:name":"Bikilek",
    "gn:population":0,
    "gn:timezone":"Asia/Qyzylorda",
    "iso:country":"KZ",
    "name:eng_x_preferred":[
        "Bikilek"
    ],
    "name:rus_x_preferred":[
        "\u0411\u0438\u043a\u0438\u043b\u0435\u043a"
    ],
    "wof:name":"Bikilek",
    "wof:placetype":"locality"
},
  "geometry": {"coordinates":[63.05609000000001,53.60736],"type":"Point"}
}