{
  "type": "Feature",
  "properties": {
    "gn:admin1_code":"11.0",
    "gn:asciiname":"Pavlodar Severnyy",
    "gn:country_code":"KZ",
    "gn:dem":143,
    "gn:feature_class":"P",
    "gn:feature_code":"PPL",
    "gn:name":"Pavlodar Severnyy",
    "gn:population":0,
    "gn:timezone":"Asia/Almaty",
    "iso:country":"KZ",
    "name:rus_x_preferred":[
        "\u041f\u0430\u0432\u043b\u043e\u0434\u0430\u0440 \u0421\u0435\u0432\u0435\u0440\u043d\u044b\u0439"
    ],
    "wof:name":"Pavlodar Severnyy",
    "wof:placetype":"locality"
},
  "geometry": {"coordinates":[76.95241,52.33999],"type":"Point"}
}