{
  "type": "Feature",
  "properties": {
    "gn:admin1_code":"0.0",
    "gn:asciiname":"Sergeyevka",
    "gn:country_code":"KZ",
    "gn:dem":141,
    "gn:feature_class":"P",
    "gn:feature_code":"PPL",
    "gn:name":"Sergeyevka",
    "gn:population":0,
    "gn:timezone":"Asia/Almaty",
    "iso:country":"KZ",
    "wof:name":"Sergeyevka",
    "wof:placetype":"locality"
},
  "geometry": {"coordinates":[78.11667,52.53333000000001],"type":"Point"}
}