{
  "type": "Feature",
  "properties": {
    "gn:admin1_code":"12.0",
    "gn:asciiname":"Nomer Pyat'",
    "gn:country_code":"KZ",
    "gn:dem":604,
    "gn:feature_class":"P",
    "gn:feature_code":"PPL",
    "gn:name":"Nomer Pyat\u2019",
    "gn:population":0,
    "gn:timezone":"Asia/Almaty",
    "iso:country":"KZ",
    "name:rus_x_preferred":[
        "Nomer Pyat\u2019"
    ],
    "name:rus_x_variant":[
        "\u041d\u043e\u043c\u0435\u0440 \u041f\u044f\u0442\u044c"
    ],
    "wof:name":"Nomer Pyat'",
    "wof:placetype":"locality"
},
  "geometry": {"coordinates":[74.41901999999997,49.7242],"type":"Point"}
}