{
  "type": "Feature",
  "properties": {
    "gn:country":"KZ",
    "gn:fcode":"PPL",
    "gn:pop":3822,
    "iso:country":"KZ",
    "name:unk_x_variant":[
        "Shalkiya"
    ],
    "qs:name":"Shalq\u012bya",
    "qs:photos_9r":0,
    "qs:photos_sr":0,
    "qs:pop_sr":"4",
    "wof:name":"Shalq\u012bya",
    "wof:placetype":"locality",
    "wof:population":3822
},
  "geometry": {"coordinates":[67.41061999999999,44.00947],"type":"Point"}
}