{
  "type": "Feature",
  "properties": {
    "gn:admin1_code":"0.0",
    "gn:asciiname":"Baygankol'",
    "gn:country_code":"KZ",
    "gn:dem":228,
    "gn:feature_class":"P",
    "gn:feature_code":"PPL",
    "gn:name":"Baygankol\u2019",
    "gn:population":0,
    "gn:timezone":"Asia/Qyzylorda",
    "iso:country":"KZ",
    "name:eng_x_preferred":[
        "Baygankol'"
    ],
    "name:rus_x_preferred":[
        "\u0411\u0430\u0439\u0433\u0430\u043d\u043a\u043e\u043b\u044c"
    ],
    "name:und_x_variant":[
        "Baygankol\u2019"
    ],
    "wof:name":"Baygankol'",
    "wof:placetype":"locality"
},
  "geometry": {"coordinates":[65.46006,53.04293000000001],"type":"Point"}
}