{
  "type": "Feature",
  "properties": {
    "gn:admin1_code":"4.0",
    "gn:asciiname":"Kutur-Barbatyr",
    "gn:country_code":"KZ",
    "gn:dem":304,
    "gn:feature_class":"P",
    "gn:feature_code":"PPL",
    "gn:name":"Kutur-Barbatyr",
    "gn:population":0,
    "gn:timezone":"Asia/Aqtobe",
    "iso:country":"KZ",
    "wof:name":"Kutur-Barbatyr",
    "wof:placetype":"locality"
},
  "geometry": {"coordinates":[57.51667,49.65],"type":"Point"}
}