{
  "type": "Feature",
  "properties": {
    "gn:admin1_code":"10.0",
    "gn:asciiname":"Maybulak",
    "gn:country_code":"KZ",
    "gn:dem":517,
    "gn:feature_class":"P",
    "gn:feature_code":"PPL",
    "gn:name":"Maybulak",
    "gn:population":0,
    "gn:timezone":"Asia/Almaty",
    "iso:country":"KZ",
    "name:rus_x_preferred":[
        "\u041c\u0430\u0439\u0431\u0443\u043b\u0430\u043a"
    ],
    "wof:name":"Maybulak",
    "wof:placetype":"locality"
},
  "geometry": {"coordinates":[68.99316999999999,41.86358],"type":"Point"}
}