{
  "type": "Feature",
  "properties": {
    "gn:admin1_code":"1.0",
    "gn:asciiname":"Dzhansugirov",
    "gn:country_code":"KZ",
    "gn:dem":636,
    "gn:feature_class":"P",
    "gn:feature_code":"PPL",
    "gn:name":"Dzhansugirov",
    "gn:population":0,
    "gn:timezone":"Asia/Almaty",
    "iso:country":"KZ",
    "name:ceb_x_preferred":[
        "Dzhansugirov"
    ],
    "name:ell_x_preferred":[
        "\u0396\u03b1\u03bd\u03c3\u03bf\u03c5\u03b3\u03ba\u03af\u03c1\u03bf\u03c6"
    ],
    "name:fas_x_preferred":[
        "\u0698\u0627\u0646\u0633\u0648\u06af\u06cc\u0631\u0648\u0641"
    ],
    "name:fra_x_preferred":[
        "Jansugirov"
    ],
    "name:kaz_x_preferred":[
        "Zhans\u00fcgirov"
    ],
    "name:kaz_x_variant":[
        "\u0416\u0430\u043d\u0441\u04af\u0433\u0456\u0440\u043e\u0432 \u0430\u0443\u044b\u043b\u044b"
    ],
    "name:mkd_x_preferred":[
        "\u0416\u0430\u043d\u0441\u0443\u0433\u0438\u0440\u043e\u0432"
    ],
    "name:mlg_x_preferred":[
        "Zhansugirov"
    ],
    "name:msa_x_preferred":[
        "Zhansugirov"
    ],
    "name:pol_x_preferred":[
        "\u017bans\u00fcgyrow"
    ],
    "name:rus_x_preferred":[
        "\u0416\u0430\u043d\u0441\u0443\u0433\u0443\u0440\u043e\u0432"
    ],
    "name:swe_x_preferred":[
        "Dzhansugirov"
    ],
    "name:ukr_x_preferred":[
        "\u0416\u0430\u043d\u0441\u0443\u0433\u0443\u0440\u043e\u0432"
    ],
    "name:und_x_variant":[
        "Abakumovskoye",
        "Dzhansugurov",
        "Abakumovskaya",
        "Dzhangusurov",
        "Abakumovka"
    ],
    "name:uzb_x_preferred":[
        "Jansugurov"
    ],
    "wof:name":"Dzhansugirov",
    "wof:placetype":"locality"
},
  "geometry": {"coordinates":[79.50221999999999,45.38861],"type":"Point"}
}