{
  "type": "Feature",
  "properties": {
    "gn:admin1_code":"3.0",
    "gn:asciiname":"Ostrovnoye",
    "gn:country_code":"KZ",
    "gn:dem":327,
    "gn:feature_class":"P",
    "gn:feature_code":"PPL",
    "gn:name":"Ostrovnoye",
    "gn:population":0,
    "gn:timezone":"Asia/Almaty",
    "iso:country":"KZ",
    "name:und_x_variant":[
        "Ostrovnoy",
        "Ostrovnoye"
    ],
    "wof:name":"Ostrovnoye",
    "wof:placetype":"locality"
},
  "geometry": {"coordinates":[70.90380999999999,51.28832],"type":"Point"}
}