{
  "type": "Feature",
  "properties": {
    "gn:admin1_code":"1.0",
    "gn:asciiname":"Saryzhaz",
    "gn:country_code":"KZ",
    "gn:dem":1935,
    "gn:feature_class":"P",
    "gn:feature_code":"PPL",
    "gn:name":"Saryzhaz",
    "gn:population":0,
    "gn:timezone":"Asia/Almaty",
    "iso:country":"KZ",
    "name:kaz_x_preferred":[
        "\u0421\u0430\u0440\u044b\u0436\u0430\u0437"
    ],
    "name:und_x_variant":[
        "Sary-Dzhas",
        "Sarydzhaz",
        "Saryzhas",
        "Saryzhaz"
    ],
    "wof:name":"Saryzhaz",
    "wof:placetype":"locality"
},
  "geometry": {"coordinates":[79.60814000000001,42.91475],"type":"Point"}
}