{
  "type": "Feature",
  "properties": {
    "gn:admin1_code":"12.0",
    "gn:asciiname":"Karbushevka",
    "gn:country_code":"KZ",
    "gn:dem":677,
    "gn:feature_class":"P",
    "gn:feature_code":"PPL",
    "gn:name":"Karbushevka",
    "gn:population":0,
    "gn:timezone":"Asia/Almaty",
    "iso:country":"KZ",
    "name:kaz_x_preferred":[
        "\u041a\u0430\u0440\u0431\u0443\u0448\u0435\u0432\u043a\u0430"
    ],
    "name:und_x_variant":[
        "Korobovskiy",
        "Koktas",
        "Karb\u016bshevka",
        "Karbushevka"
    ],
    "wof:name":"Karbushevka",
    "wof:placetype":"locality"
},
  "geometry": {"coordinates":[75.05637,49.59383],"type":"Point"}
}