{
  "type": "Feature",
  "properties": {
    "gn:admin1_code":"0.0",
    "gn:asciiname":"Polovinnyy Log",
    "gn:country_code":"KZ",
    "gn:dem":328,
    "gn:feature_class":"P",
    "gn:feature_code":"PPL",
    "gn:name":"Polovinnyy Log",
    "gn:population":0,
    "gn:timezone":"Asia/Almaty",
    "iso:country":"KZ",
    "wof:name":"Polovinnyy Log",
    "wof:placetype":"locality"
},
  "geometry": {"coordinates":[81.23094,50.50181],"type":"Point"}
}