{
  "type": "Feature",
  "properties": {
    "gn:admin1_code":"0.0",
    "gn:asciiname":"Tursenin",
    "gn:country_code":"KZ",
    "gn:dem":117,
    "gn:feature_class":"P",
    "gn:feature_code":"PPL",
    "gn:name":"Tursenin",
    "gn:population":0,
    "gn:timezone":"Asia/Oral",
    "iso:country":"KZ",
    "wof:name":"Tursenin",
    "wof:placetype":"locality"
},
  "geometry": {"coordinates":[50.96667,51.48333],"type":"Point"}
}