{
  "type": "Feature",
  "properties": {
    "gn:admin1_code":"14.0",
    "gn:asciiname":"Tang",
    "gn:cc2":"KZ",
    "gn:country_code":"KZ",
    "gn:dem":107,
    "gn:feature_class":"P",
    "gn:feature_code":"PPL",
    "gn:name":"Tang",
    "gn:population":0,
    "gn:timezone":"Asia/Qyzylorda",
    "iso:country":"KZ",
    "name:ceb_x_preferred":[
        "Tang"
    ],
    "name:dan_x_preferred":[
        "Tang"
    ],
    "name:deu_x_preferred":[
        "Tang"
    ],
    "name:est_x_preferred":[
        "Tang"
    ],
    "name:fin_x_preferred":[
        "Tang"
    ],
    "name:fra_x_preferred":[
        "Tang"
    ],
    "name:hun_x_preferred":[
        "Tang"
    ],
    "name:nld_x_preferred":[
        "Tang"
    ],
    "name:nor_x_preferred":[
        "Tang"
    ],
    "name:pol_x_preferred":[
        "Tang"
    ],
    "name:rus_x_preferred":[
        "\u0422\u0430\u043d\u0433"
    ],
    "name:spa_x_preferred":[
        "Tang"
    ],
    "name:swe_x_preferred":[
        "Tang"
    ],
    "name:ukr_x_preferred":[
        "\u0422\u0430\u043d\u0433"
    ],
    "name:und_x_variant":[
        "Tan",
        "Tang"
    ],
    "wof:name":"Tang",
    "wof:placetype":"locality"
},
  "geometry": {"coordinates":[64.41556,45.075],"type":"Point"}
}