{
  "type": "Feature",
  "properties": {
    "gn:admin1_code":"12.0",
    "gn:asciiname":"Kyzyltau Vtoroy",
    "gn:country_code":"KZ",
    "gn:dem":677,
    "gn:feature_class":"P",
    "gn:feature_code":"PPL",
    "gn:name":"Kyzyltau Vtoroy",
    "gn:population":0,
    "gn:timezone":"Asia/Almaty",
    "iso:country":"KZ",
    "name:rus_x_preferred":[
        "\u041a\u044b\u0437\u044b\u043b\u0442\u0430\u0443 \u0412\u0442\u043e\u0440\u043e\u0439"
    ],
    "wof:name":"Kyzyltau Vtoroy",
    "wof:placetype":"locality"
},
  "geometry": {"coordinates":[72.03542,48.02039],"type":"Point"}
}