{
  "type": "Feature",
  "properties": {
    "gn:admin1_code":"3.0",
    "gn:asciiname":"Ashchyly",
    "gn:country_code":"KZ",
    "gn:dem":351,
    "gn:feature_class":"P",
    "gn:feature_code":"PPL",
    "gn:name":"Ashchyly",
    "gn:population":0,
    "gn:timezone":"Asia/Almaty",
    "iso:country":"KZ",
    "name:rus_x_preferred":[
        "\u0410\u0449\u044b\u043b\u044b"
    ],
    "wof:name":"Ashchyly",
    "wof:placetype":"locality"
},
  "geometry": {"coordinates":[67.94671,52.18073],"type":"Point"}
}