{
  "type": "Feature",
  "properties": {
    "gn:admin1_code":"7.0",
    "gn:asciiname":"Seksenbayevo",
    "gn:country_code":"KZ",
    "gn:dem":16,
    "gn:feature_class":"P",
    "gn:feature_code":"PPL",
    "gn:name":"Seksenbayevo",
    "gn:population":0,
    "gn:timezone":"Asia/Oral",
    "iso:country":"KZ",
    "name:eng_x_preferred":[
        "Seksenbayevo"
    ],
    "name:rus_x_preferred":[
        "\u0421\u0435\u043a\u0441\u0435\u043d\u0431\u0430\u0435\u0432\u043e"
    ],
    "name:und_x_variant":[
        "Bol\u2019shevik"
    ],
    "wof:name":"Seksenbayevo",
    "wof:placetype":"locality"
},
  "geometry": {"coordinates":[48.51574,49.78031],"type":"Point"}
}