{
  "type": "Feature",
  "properties": {
    "gn:admin1_code":"7.0",
    "gn:asciiname":"Mynbay",
    "gn:country_code":"KZ",
    "gn:dem":3,
    "gn:feature_class":"P",
    "gn:feature_code":"PPL",
    "gn:name":"Mynbay",
    "gn:population":0,
    "gn:timezone":"Asia/Oral",
    "iso:country":"KZ",
    "name:eng_x_preferred":[
        "Mynbay"
    ],
    "name:rus_x_preferred":[
        "\u041c\u044b\u043d\u0431\u0430\u0439"
    ],
    "wof:name":"Mynbay",
    "wof:placetype":"locality"
},
  "geometry": {"coordinates":[49.91346,49.69637],"type":"Point"}
}