{
  "type": "Feature",
  "properties": {
    "gn:admin1_code":"13.0",
    "gn:asciiname":"Amantoghay",
    "gn:country_code":"KZ",
    "gn:dem":160,
    "gn:feature_class":"P",
    "gn:feature_code":"PPL",
    "gn:name":"Amantoghay",
    "gn:population":0,
    "gn:timezone":"Asia/Almaty",
    "iso:country":"KZ",
    "name:eng_x_preferred":[
        "Amantoghay"
    ],
    "name:rus_x_preferred":[
        "\u0410\u043c\u0430\u043d\u0442\u043e\u0433\u0430\u0439"
    ],
    "name:und_x_variant":[
        "Kermola",
        "Amantogay",
        "Amantoghay"
    ],
    "wof:name":"Amantoghay",
    "wof:placetype":"locality"
},
  "geometry": {"coordinates":[65.64041999999999,50.43479],"type":"Point"}
}