{
  "type": "Feature",
  "properties": {
    "gn:admin1_code":"0.0",
    "gn:asciiname":"Tulyuktyube",
    "gn:country_code":"KZ",
    "gn:dem":47,
    "gn:feature_class":"P",
    "gn:feature_code":"PPL",
    "gn:name":"Tulyuktyube",
    "gn:population":0,
    "gn:timezone":"Asia/Oral",
    "iso:country":"KZ",
    "wof:name":"Tulyuktyube",
    "wof:placetype":"locality"
},
  "geometry": {"coordinates":[52.23333,51.35],"type":"Point"}
}