{
  "type": "Feature",
  "properties": {
    "gn:admin1_code":"16.0",
    "gn:asciiname":"Kellerovka",
    "gn:country_code":"KZ",
    "gn:dem":168,
    "gn:feature_class":"P",
    "gn:feature_code":"PPL",
    "gn:name":"Kellerovka",
    "gn:population":0,
    "gn:timezone":"Asia/Almaty",
    "iso:country":"KZ",
    "name:eng_x_preferred":[
        "Kellerovka"
    ],
    "name:kaz_x_preferred":[
        "Kellerovka"
    ],
    "name:kaz_x_variant":[
        "\u041a\u0435\u043b\u043b\u0435\u0440\u043e\u0432\u043a\u0430"
    ],
    "name:rus_x_preferred":[
        "\u041a\u0435\u043b\u043b\u0435\u0440\u043e\u0432\u043a\u0430"
    ],
    "name:und_x_variant":[
        "Kellerevo",
        "Kellerovskiy"
    ],
    "wof:name":"Kellerovka",
    "wof:placetype":"locality"
},
  "geometry": {"coordinates":[69.29850999999999,53.83823],"type":"Point"}
}