{
  "type": "Feature",
  "properties": {
    "gn:admin1_code":"12.0",
    "gn:asciiname":"Ushtau",
    "gn:country_code":"KZ",
    "gn:dem":596,
    "gn:feature_class":"P",
    "gn:feature_code":"PPL",
    "gn:name":"Ushtau",
    "gn:population":0,
    "gn:timezone":"Asia/Almaty",
    "iso:country":"KZ",
    "name:kaz_x_preferred":[
        "\u00dcshta\u016b"
    ],
    "name:kaz_x_variant":[
        "\u04ae\u0448\u0442\u0430\u0443"
    ],
    "name:rus_x_preferred":[
        "\u0423\u0448\u0442\u0430\u0443"
    ],
    "wof:name":"Ushtau",
    "wof:placetype":"locality"
},
  "geometry": {"coordinates":[74.40883000000002,49.7586],"type":"Point"}
}