{
  "type": "Feature",
  "properties": {
    "gn:admin1_code":"1.0",
    "gn:asciiname":"Tolkyn",
    "gn:country_code":"KZ",
    "gn:dem":523,
    "gn:feature_class":"P",
    "gn:feature_code":"PPL",
    "gn:name":"Tolkyn",
    "gn:population":0,
    "gn:timezone":"Asia/Almaty",
    "iso:country":"KZ",
    "name:kaz_x_preferred":[
        "Tolqyn"
    ],
    "name:kaz_x_variant":[
        "\u0422\u043e\u043b\u049b\u044b\u043d"
    ],
    "name:rus_x_preferred":[
        "\u0422\u043e\u043b\u043a\u044b\u043d"
    ],
    "wof:name":"Tolkyn",
    "wof:placetype":"locality"
},
  "geometry": {"coordinates":[77.89246999999997,43.62953],"type":"Point"}
}