{
  "type": "Feature",
  "properties": {
    "gn:admin1_code":"12.0",
    "gn:asciiname":"Kaynarbulak",
    "gn:country_code":"KZ",
    "gn:dem":878,
    "gn:feature_class":"P",
    "gn:feature_code":"PPL",
    "gn:name":"Kaynarbulak",
    "gn:population":0,
    "gn:timezone":"Asia/Almaty",
    "iso:country":"KZ",
    "wof:name":"Kaynarbulak",
    "wof:placetype":"locality"
},
  "geometry": {"coordinates":[75.45,49.01667],"type":"Point"}
}