{
  "type": "Feature",
  "properties": {
    "gn:admin1_code":"1.0",
    "gn:asciiname":"Nura",
    "gn:country_code":"KZ",
    "gn:dem":716,
    "gn:feature_class":"P",
    "gn:feature_code":"PPL",
    "gn:name":"Nura",
    "gn:population":0,
    "gn:timezone":"Asia/Almaty",
    "iso:country":"KZ",
    "name:ceb_x_preferred":[
        "Nura"
    ],
    "name:deu_x_preferred":[
        "Nura"
    ],
    "name:kaz_x_preferred":[
        "Nura"
    ],
    "name:kaz_x_variant":[
        "\u041d\u04b1\u0440\u0430"
    ],
    "name:rus_x_preferred":[
        "\u0421\u043e\u0432\u0445\u043e\u0437 \u0421\u044e\u0433\u0430\u0442\u0438\u043d\u0441\u043a\u0438\u0439"
    ],
    "name:rus_x_variant":[
        "\u041d\u0443\u0440\u0430"
    ],
    "name:swe_x_preferred":[
        "Nura"
    ],
    "name:ukr_x_preferred":[
        "\u041d\u0443\u0440\u0430"
    ],
    "name:und_x_variant":[
        "Sovkhoz Syugatinskiy"
    ],
    "wof:name":"Nura",
    "wof:placetype":"locality"
},
  "geometry": {"coordinates":[78.47006,43.55416],"type":"Point"}
}