{
  "type": "Feature",
  "properties": {
    "gn:admin1_code":"12.0",
    "gn:asciiname":"Akkiik",
    "gn:country_code":"KZ",
    "gn:dem":677,
    "gn:feature_class":"P",
    "gn:feature_code":"PPL",
    "gn:name":"Akkiik",
    "gn:population":0,
    "gn:timezone":"Asia/Almaty",
    "iso:country":"KZ",
    "name:kaz_x_preferred":[
        "Aqq\u012byaq"
    ],
    "name:kaz_x_variant":[
        "\u0410\u049b\u049b\u0438\u044f\u049b"
    ],
    "name:rus_x_preferred":[
        "\u0410\u043a\u043a\u0438\u0438\u043a"
    ],
    "wof:name":"Akkiik",
    "wof:placetype":"locality"
},
  "geometry": {"coordinates":[73.69797,49.06504],"type":"Point"}
}