{
  "type": "Feature",
  "properties": {
    "gn:admin1_code":"4.0",
    "gn:asciiname":"May-Tyubek",
    "gn:country_code":"KZ",
    "gn:dem":103,
    "gn:feature_class":"P",
    "gn:feature_code":"PPL",
    "gn:name":"May-Tyubek",
    "gn:population":0,
    "gn:timezone":"Asia/Aqtobe",
    "iso:country":"KZ",
    "wof:name":"May-Tyubek",
    "wof:placetype":"locality"
},
  "geometry": {"coordinates":[56.26667,47.85],"type":"Point"}
}