{
  "type": "Feature",
  "properties": {
    "gn:admin1_code":"16.0",
    "gn:asciiname":"Akbulak",
    "gn:country_code":"KZ",
    "gn:dem":416,
    "gn:feature_class":"P",
    "gn:feature_code":"PPL",
    "gn:name":"Akbulak",
    "gn:population":0,
    "gn:timezone":"Asia/Almaty",
    "iso:country":"KZ",
    "name:rus_x_preferred":[
        "\u0410\u043a\u0431\u0443\u043b\u0430\u043a"
    ],
    "wof:name":"Akbulak",
    "wof:placetype":"locality"
},
  "geometry": {"coordinates":[68.58256999999999,52.85767],"type":"Point"}
}