{
  "type": "Feature",
  "properties": {
    "gn:admin1_code":"13.0",
    "gn:asciiname":"Nikiforovka",
    "gn:country_code":"KZ",
    "gn:dem":218,
    "gn:feature_class":"P",
    "gn:feature_code":"PPL",
    "gn:name":"Nikiforovka",
    "gn:population":0,
    "gn:timezone":"Asia/Qyzylorda",
    "iso:country":"KZ",
    "name:eng_x_preferred":[
        "Nikiforovka"
    ],
    "name:rus_x_preferred":[
        "\u041d\u0438\u043a\u0438\u0444\u043e\u0440\u043e\u0432\u043a\u0430"
    ],
    "wof:name":"Nikiforovka",
    "wof:placetype":"locality"
},
  "geometry": {"coordinates":[61.53333000000001,53.96666999999999],"type":"Point"}
}