{
  "type": "Feature",
  "properties": {
    "gn:admin1_code":"0.0",
    "gn:asciiname":"Dzhan-Chilik",
    "gn:country_code":"KZ",
    "gn:dem":334,
    "gn:feature_class":"P",
    "gn:feature_code":"PPL",
    "gn:name":"Dzhan-Chilik",
    "gn:population":0,
    "gn:timezone":"Asia/Almaty",
    "iso:country":"KZ",
    "wof:name":"Dzhan-Chilik",
    "wof:placetype":"locality"
},
  "geometry": {"coordinates":[68.13333,51.88333],"type":"Point"}
}