{
  "type": "Feature",
  "properties": {
    "gn:admin1_code":"11.0",
    "gn:asciiname":"Shoqtal",
    "gn:country_code":"KZ",
    "gn:dem":151,
    "gn:feature_class":"P",
    "gn:feature_code":"PPL",
    "gn:name":"Shoqtal",
    "gn:population":0,
    "gn:timezone":"Asia/Almaty",
    "iso:country":"KZ",
    "name:eng_x_preferred":[
        "Shoktal'"
    ],
    "name:kaz_x_preferred":[
        "Shoqtal"
    ],
    "name:kaz_x_variant":[
        "\u0428\u043e\u049b\u0442\u0430\u043b"
    ],
    "name:rus_x_preferred":[
        "\u0428\u043e\u043a\u0442\u044b\u043b"
    ],
    "name:rus_x_variant":[
        "\u0428\u043e\u043a\u0442\u0430\u043b"
    ],
    "name:und_x_variant":[
        "Shoktal\u2019",
        "Shoktal"
    ],
    "wof:name":"Shoqtal",
    "wof:placetype":"locality"
},
  "geometry": {"coordinates":[78.98924,51.79725],"type":"Point"}
}