{
  "type": "Feature",
  "properties": {
    "gn:admin1_code":"0.0",
    "gn:asciiname":"Vertyaskina",
    "gn:country_code":"KZ",
    "gn:dem":-1,
    "gn:feature_class":"P",
    "gn:feature_code":"PPL",
    "gn:name":"Vertyaskina",
    "gn:population":0,
    "gn:timezone":"Asia/Oral",
    "iso:country":"KZ",
    "wof:name":"Vertyaskina",
    "wof:placetype":"locality"
},
  "geometry": {"coordinates":[50.86667,49.21667],"type":"Point"}
}