{
  "type": "Feature",
  "properties": {
    "gn:admin1_code":"10.0",
    "gn:asciiname":"Maksim Gor'kiy",
    "gn:country_code":"KZ",
    "gn:dem":216,
    "gn:feature_class":"P",
    "gn:feature_code":"PPL",
    "gn:name":"Maks\u012bm Gor\u2019k\u012by",
    "gn:population":0,
    "gn:timezone":"Asia/Almaty",
    "iso:country":"KZ",
    "name:kaz_x_preferred":[
        "Maks\u012bm Gor\u2019k\u012by"
    ],
    "name:kaz_x_variant":[
        "\u041c\u0430\u043a\u0441\u0438\u043c \u0413\u043e\u0440\u044c\u043a\u0438\u0439"
    ],
    "name:rus_x_preferred":[
        "Imeni Maksima Gor\u2019kogo"
    ],
    "name:rus_x_variant":[
        "\u0418\u043c\u0435\u043d\u0438 \u041c\u0430\u043a\u0441\u0438\u043c\u0430 \u0413\u043e\u0440\u044c\u043a\u043e\u0433\u043e"
    ],
    "wof:name":"Maksim Gor'kiy",
    "wof:placetype":"locality"
},
  "geometry": {"coordinates":[68.01178,43.38868],"type":"Point"}
}