{
  "type": "Feature",
  "properties": {
    "gn:admin1_code":"17.0",
    "gn:asciiname":"Zharqudyq",
    "gn:country_code":"KZ",
    "gn:dem":318,
    "gn:feature_class":"P",
    "gn:feature_code":"PPL",
    "gn:name":"Zharqudyq",
    "gn:population":0,
    "gn:timezone":"Asia/Almaty",
    "iso:country":"KZ",
    "name:kaz_x_preferred":[
        "Zharqudyq"
    ],
    "name:kaz_x_variant":[
        "\u0416\u0430\u0440\u049b\u04b1\u0434\u044b\u049b"
    ],
    "name:rus_x_preferred":[
        "\u0416\u0430\u0440\u043a\u0443\u0434\u0443\u043a"
    ],
    "name:rus_x_variant":[
        "\u0424\u0435\u0440\u043c\u0430 \u041d\u043e\u043c\u0435\u0440 \u0422\u0440\u0438 \u0416\u0430\u0440\u043a\u0443\u0434\u0443\u043a"
    ],
    "name:und_x_variant":[
        "Zharkuduk",
        "Ferma Nomer Tri Zharkuduk"
    ],
    "wof:name":"Zharqudyq",
    "wof:placetype":"locality"
},
  "geometry": {"coordinates":[70.11548000000001,43.93283],"type":"Point"}
}