{
  "type": "Feature",
  "properties": {
    "gn:admin1_code":"0.0",
    "gn:asciiname":"Iryubay",
    "gn:country_code":"KZ",
    "gn:dem":712,
    "gn:feature_class":"P",
    "gn:feature_code":"PPL",
    "gn:name":"Iryubay",
    "gn:population":0,
    "gn:timezone":"Asia/Almaty",
    "iso:country":"KZ",
    "wof:name":"Iryubay",
    "wof:placetype":"locality"
},
  "geometry": {"coordinates":[76.68333,43.31667],"type":"Point"}
}