{
  "type": "Feature",
  "properties": {
    "gn:admin1_code":"12.0",
    "gn:asciiname":"Internatsional'nyy",
    "gn:country_code":"KZ",
    "gn:dem":487,
    "gn:feature_class":"P",
    "gn:feature_code":"PPL",
    "gn:name":"Internatsional\u2019nyy",
    "gn:population":0,
    "gn:timezone":"Asia/Almaty",
    "iso:country":"KZ",
    "name:und_x_variant":[
        "Internatsional\u2019naya",
        "Internatsional\u2019nyy"
    ],
    "wof:name":"Internatsional'nyy",
    "wof:placetype":"locality"
},
  "geometry": {"coordinates":[72.83333,50.58333],"type":"Point"}
}