{
  "type": "Feature",
  "properties": {
    "gn:admin1_code":"16.0",
    "gn:asciiname":"Garshino",
    "gn:country_code":"KZ",
    "gn:dem":238,
    "gn:feature_class":"P",
    "gn:feature_code":"PPL",
    "gn:name":"Garshino",
    "gn:population":0,
    "gn:timezone":"Asia/Almaty",
    "iso:country":"KZ",
    "name:eng_x_preferred":[
        "Garshino"
    ],
    "name:kaz_x_preferred":[
        "Garsh\u012bno"
    ],
    "name:kaz_x_variant":[
        "\u0413\u0430\u0440\u0448\u0438\u043d\u043e"
    ],
    "name:rus_x_preferred":[
        "\u0413\u0430\u0440\u0448\u0438\u043d\u043e"
    ],
    "wof:name":"Garshino",
    "wof:placetype":"locality"
},
  "geometry": {"coordinates":[67.04536999999999,52.55383000000001],"type":"Point"}
}