{
  "type": "Feature",
  "properties": {
    "gn:admin1_code":"16.0",
    "gn:asciiname":"Pchelino",
    "gn:country_code":"KZ",
    "gn:dem":145,
    "gn:feature_class":"P",
    "gn:feature_code":"PPL",
    "gn:name":"Pch\u00eblino",
    "gn:population":0,
    "gn:timezone":"Asia/Almaty",
    "iso:country":"KZ",
    "name:bul_x_preferred":[
        "\u041f\u0447\u0435\u043b\u0438\u043d\u043e"
    ],
    "name:fas_x_preferred":[
        "\u067e\u0686\u0644\u06cc\u0646\u0648"
    ],
    "name:kaz_x_preferred":[
        "\u041f\u0447\u0435\u043b\u0438\u043d\u043e"
    ],
    "name:ron_x_preferred":[
        "Pcelino"
    ],
    "name:rus_x_preferred":[
        "Pch\u00eblino"
    ],
    "name:rus_x_variant":[
        "\u041f\u0447\u0451\u043b\u0438\u043d\u043e",
        "\u041f\u0447\u0435\u043b\u0438\u043d\u043e"
    ],
    "name:ukr_x_preferred":[
        "\u041f\u0447\u0435\u043b\u0438\u043d\u043e"
    ],
    "wof:name":"Pchelino",
    "wof:placetype":"locality"
},
  "geometry": {"coordinates":[67.93808,54.77855],"type":"Point"}
}