{
  "type": "Feature",
  "properties": {
    "gn:admin1_code":"1.0",
    "gn:asciiname":"Dzerzhinskoye",
    "gn:country_code":"KZ",
    "gn:dem":927,
    "gn:feature_class":"P",
    "gn:feature_code":"PPL",
    "gn:name":"Dzerzhinskoye",
    "gn:population":0,
    "gn:timezone":"Asia/Almaty",
    "iso:country":"KZ",
    "name:kaz_x_preferred":[
        "Toqzhayla\u016b"
    ],
    "name:kaz_x_variant":[
        "\u0422\u043e\u049b\u0436\u0430\u0439\u043b\u0430\u0443"
    ],
    "name:rus_x_preferred":[
        "\u0414\u0437\u0435\u0440\u0436\u0438\u043d\u0441\u043a\u043e\u0435"
    ],
    "name:und_x_variant":[
        "Kolpakovskoye",
        "Dzerzhinskiy",
        "Dzerzhinsk",
        "Dzerzhinskoye"
    ],
    "wof:name":"Dzerzhinskoye",
    "wof:placetype":"locality"
},
  "geometry": {"coordinates":[81.07961999999998,45.81837],"type":"Point"}
}