{
  "type": "Feature",
  "properties": {
    "gn:admin1_code":"0.0",
    "gn:asciiname":"Kavkoskol'",
    "gn:country_code":"KZ",
    "gn:dem":282,
    "gn:feature_class":"P",
    "gn:feature_code":"PPL",
    "gn:name":"Kavkoskol\u2019",
    "gn:population":0,
    "gn:timezone":"Asia/Almaty",
    "iso:country":"KZ",
    "wof:name":"Kavkoskol'",
    "wof:placetype":"locality"
},
  "geometry": {"coordinates":[69.41667,51.78333],"type":"Point"}
}