{
  "type": "Feature",
  "properties": {
    "gn:admin1_code":"12.0",
    "gn:asciiname":"Unrek",
    "gn:country_code":"KZ",
    "gn:dem":687,
    "gn:feature_class":"P",
    "gn:feature_code":"PPL",
    "gn:name":"Unrek",
    "gn:population":0,
    "gn:timezone":"Asia/Almaty",
    "iso:country":"KZ",
    "name:kaz_x_preferred":[
        "\u00d6nirek"
    ],
    "name:kaz_x_variant":[
        "\u00d6ngirek",
        "\u04e8\u04a3\u0456\u0440\u0435\u043a"
    ],
    "name:rus_x_preferred":[
        "\u0423\u043d\u0440\u0435\u043a"
    ],
    "name:und_x_variant":[
        "Onirek",
        "Ornek",
        "Unrek"
    ],
    "wof:name":"Unrek",
    "wof:placetype":"locality"
},
  "geometry": {"coordinates":[72.97945,48.83600000000001],"type":"Point"}
}