{
  "type": "Feature",
  "properties": {
    "gn:admin1_code":"17.0",
    "gn:asciiname":"Aksu",
    "gn:country_code":"KZ",
    "gn:dem":535,
    "gn:feature_class":"P",
    "gn:feature_code":"PPL",
    "gn:name":"Aksu",
    "gn:population":0,
    "gn:timezone":"Asia/Almaty",
    "iso:country":"KZ",
    "name:cat_x_preferred":[
        "Aksu"
    ],
    "name:ceb_x_preferred":[
        "Aksu"
    ],
    "name:ces_x_preferred":[
        "Aksu"
    ],
    "name:deu_x_preferred":[
        "Aksu"
    ],
    "name:fra_x_preferred":[
        "Aksu"
    ],
    "name:hun_x_preferred":[
        "Aksu"
    ],
    "name:hye_x_preferred":[
        "\u0531\u0572\u057d\u0578\u0582"
    ],
    "name:ita_x_preferred":[
        "Aksu"
    ],
    "name:kaz_x_preferred":[
        "Aqs\u016b"
    ],
    "name:kaz_x_variant":[
        "\u0410\u049b\u0441\u0443"
    ],
    "name:lit_x_preferred":[
        "Aksu"
    ],
    "name:mlg_x_preferred":[
        "Aksu"
    ],
    "name:nld_x_preferred":[
        "Aksu"
    ],
    "name:nor_x_preferred":[
        "Aksu"
    ],
    "name:pnb_x_preferred":[
        "\u0627\u063a\u0633\u0648"
    ],
    "name:pol_x_preferred":[
        "Aksu"
    ],
    "name:rus_x_preferred":[
        "\u0410\u043a\u0441\u0443"
    ],
    "name:sco_x_preferred":[
        "Aksu"
    ],
    "name:spa_x_preferred":[
        "Aksu"
    ],
    "name:srp_x_preferred":[
        "\u0410\u043a\u0441\u0443"
    ],
    "name:swe_x_preferred":[
        "Aksu"
    ],
    "name:tur_x_preferred":[
        "Aksu"
    ],
    "name:ukr_x_preferred":[
        "\u0410\u043a\u0441\u0443"
    ],
    "name:und_x_variant":[
        "Kolkhoz Imeni Kalinina",
        "Aksu"
    ],
    "name:vie_x_preferred":[
        "Aksu"
    ],
    "wof:name":"Aksu",
    "wof:placetype":"locality"
},
  "geometry": {"coordinates":[74.0236,43.25762],"type":"Point"}
}