{
  "type": "Feature",
  "properties": {
    "gn:admin1_code":"17.0",
    "gn:asciiname":"Aksu",
    "gn:country_code":"KZ",
    "gn:dem":535,
    "gn:feature_class":"P",
    "gn:feature_code":"PPL",
    "gn:name":"Aksu",
    "gn:population":0,
    "gn:timezone":"Asia/Almaty",
    "iso:country":"KZ",
    "name:ara_x_preferred":[
        "\u0623\u0643\u0633\u0648"
    ],
    "name:ben_x_preferred":[
        "\u0986\u0995\u09cd\u09b8\u09c1"
    ],
    "name:cat_x_preferred":[
        "Aksu"
    ],
    "name:ceb_x_preferred":[
        "Aksu"
    ],
    "name:ces_x_preferred":[
        "Aksu"
    ],
    "name:deu_x_preferred":[
        "Aksu"
    ],
    "name:ell_x_preferred":[
        "\u0386\u03be\u03bf\u03c5"
    ],
    "name:fas_x_preferred":[
        "\u0622\u06a9\u0633\u0648"
    ],
    "name:fra_x_preferred":[
        "Aksu"
    ],
    "name:heb_x_preferred":[
        "\u05d0\u05e7\u05e1\u05d5"
    ],
    "name:hin_x_preferred":[
        "\u0905\u0915\u094d\u0938\u0942"
    ],
    "name:hun_x_preferred":[
        "Aksu"
    ],
    "name:hye_x_preferred":[
        "\u0531\u0572\u057d\u0578\u0582"
    ],
    "name:ind_x_preferred":[
        "Aksu"
    ],
    "name:ita_x_preferred":[
        "Aksu"
    ],
    "name:kaz_x_preferred":[
        "Aqs\u016b"
    ],
    "name:kaz_x_variant":[
        "\u0410\u049b\u0441\u0443"
    ],
    "name:kor_x_preferred":[
        "\uc545\uc218"
    ],
    "name:lit_x_preferred":[
        "Aksu"
    ],
    "name:mlg_x_preferred":[
        "Aksu"
    ],
    "name:nld_x_preferred":[
        "Aksu"
    ],
    "name:nor_x_preferred":[
        "Aksu"
    ],
    "name:pnb_x_preferred":[
        "\u0627\u063a\u0633\u0648"
    ],
    "name:pol_x_preferred":[
        "Aksu"
    ],
    "name:por_x_preferred":[
        "Aksu"
    ],
    "name:rus_x_preferred":[
        "\u0410\u043a\u0441\u0443"
    ],
    "name:sco_x_preferred":[
        "Aksu"
    ],
    "name:spa_x_preferred":[
        "Aksu"
    ],
    "name:srp_x_preferred":[
        "\u0410\u043a\u0441\u0443"
    ],
    "name:swe_x_preferred":[
        "Aksu"
    ],
    "name:tur_x_preferred":[
        "Aksu"
    ],
    "name:ukr_x_preferred":[
        "\u0410\u043a\u0441\u0443"
    ],
    "name:und_x_variant":[
        "Kolkhoz Imeni Kalinina"
    ],
    "name:vie_x_preferred":[
        "S\u00f4ng Aksu"
    ],
    "name:vie_x_variant":[
        "Aksu"
    ],
    "wof:name":"Aksu",
    "wof:placetype":"locality"
},
  "geometry": {"coordinates":[74.0236,43.25762],"type":"Point"}
}