{
  "type": "Feature",
  "properties": {
    "gn:admin1_code":"17.0",
    "gn:asciiname":"Aksu",
    "gn:country_code":"KZ",
    "gn:dem":535,
    "gn:feature_class":"P",
    "gn:feature_code":"PPL",
    "gn:name":"Aksu",
    "gn:population":0,
    "gn:timezone":"Asia/Almaty",
    "iso:country":"KZ",
    "name:kaz_x_preferred":[
        "Aqs\u016b"
    ],
    "name:kaz_x_variant":[
        "\u0410\u049b\u0441\u0443"
    ],
    "name:rus_x_preferred":[
        "\u0410\u043a\u0441\u0443"
    ],
    "name:und_x_variant":[
        "Kolkhoz Imeni Kalinina",
        "Aksu"
    ],
    "wof:name":"Aksu",
    "wof:placetype":"locality"
},
  "geometry": {"coordinates":[74.0236,43.25762],"type":"Point"}
}