{
  "type": "Feature",
  "properties": {
    "gn:admin1_code":"11.0",
    "gn:asciiname":"Voskresenka",
    "gn:country_code":"KZ",
    "gn:dem":104,
    "gn:feature_class":"P",
    "gn:feature_code":"PPL",
    "gn:name":"Voskresenka",
    "gn:population":0,
    "gn:timezone":"Asia/Almaty",
    "iso:country":"KZ",
    "name:eng_x_preferred":[
        "Voskresenka"
    ],
    "name:kaz_x_preferred":[
        "\u0412\u043e\u0441\u043a\u0440\u0435\u0441\u0435\u043d\u043a\u0430"
    ],
    "name:rus_x_preferred":[
        "\u0412\u043e\u0441\u043a\u0440\u0435\u0441\u0435\u043d\u043a\u0430"
    ],
    "name:und_x_variant":[
        "Plodorodnyy",
        "Voskresenskiy",
        "Voskresenka"
    ],
    "wof:name":"Voskresenka",
    "wof:placetype":"locality"
},
  "geometry": {"coordinates":[76.70869,53.35621999999999],"type":"Point"}
}