{
  "type": "Feature",
  "properties": {
    "gn:admin1_code":"10.0",
    "gn:asciiname":"Takhirkol",
    "gn:country_code":"KZ",
    "gn:dem":207,
    "gn:feature_class":"P",
    "gn:feature_code":"PPL",
    "gn:name":"Takh\u012brk\u00f6l",
    "gn:population":0,
    "gn:timezone":"Asia/Almaty",
    "iso:country":"KZ",
    "name:kaz_x_preferred":[
        "Takh\u012brk\u00f6l"
    ],
    "name:kaz_x_variant":[
        "\u0422\u0430\u0445\u0438\u0440\u043a\u04e9\u043b"
    ],
    "name:rus_x_preferred":[
        "Takhirkol\u2019"
    ],
    "name:rus_x_variant":[
        "\u0422\u0430\u0445\u0438\u0440\u043a\u043e\u043b\u044c"
    ],
    "name:und_x_variant":[
        "Takyrkol\u2019"
    ],
    "wof:name":"Takhirkol",
    "wof:placetype":"locality"
},
  "geometry": {"coordinates":[68.29120999999999,42.24558],"type":"Point"}
}