{
  "type": "Feature",
  "properties": {
    "gn:admin1_code":"6.0",
    "gn:asciiname":"Tuzdukul'",
    "gn:country_code":"KZ",
    "gn:dem":-20,
    "gn:feature_class":"P",
    "gn:feature_code":"PPL",
    "gn:name":"Tuzdukul\u2019",
    "gn:population":0,
    "gn:timezone":"Asia/Atyrau",
    "iso:country":"KZ",
    "wof:name":"Tuzdukul'",
    "wof:placetype":"locality"
},
  "geometry": {"coordinates":[53.76667,47.03333],"type":"Point"}
}