{
  "type": "Feature",
  "properties": {
    "gn:admin1_code":"0.0",
    "gn:asciiname":"Maya",
    "gn:country_code":"KZ",
    "gn:dem":172,
    "gn:feature_class":"P",
    "gn:feature_code":"PPL",
    "gn:name":"Maya",
    "gn:population":0,
    "gn:timezone":"Asia/Almaty",
    "iso:country":"KZ",
    "wof:name":"Maya",
    "wof:placetype":"locality"
},
  "geometry": {"coordinates":[79.04916999999998,51.3225],"type":"Point"}
}