{
  "type": "Feature",
  "properties": {
    "gn:admin1_code":"13.0",
    "gn:asciiname":"Tselinnyy",
    "gn:country_code":"KZ",
    "gn:dem":227,
    "gn:feature_class":"P",
    "gn:feature_code":"PPL",
    "gn:name":"Tselinnyy",
    "gn:population":0,
    "gn:timezone":"Asia/Qyzylorda",
    "iso:country":"KZ",
    "name:kaz_x_preferred":[
        "Tsel\u012bnnyy"
    ],
    "name:kaz_x_variant":[
        "\u0426\u0435\u043b\u0438\u043d\u043d\u044b\u0439"
    ],
    "wof:name":"Tselinnyy",
    "wof:placetype":"locality"
},
  "geometry": {"coordinates":[61.70823000000001,53.76691999999999],"type":"Point"}
}