{
  "type": "Feature",
  "properties": {
    "gn:admin1_code":"16.0",
    "gn:asciiname":"Chkalovo",
    "gn:country_code":"KZ",
    "gn:dem":208,
    "gn:feature_class":"P",
    "gn:feature_code":"PPL",
    "gn:name":"Chkalovo",
    "gn:population":0,
    "gn:timezone":"Asia/Almaty",
    "iso:country":"KZ",
    "name:rus_x_preferred":[
        "\u0427\u043a\u0430\u043b\u043e\u0432\u043e"
    ],
    "wof:name":"Chkalovo",
    "wof:placetype":"locality"
},
  "geometry": {"coordinates":[70.36675,53.49374],"type":"Point"}
}