{
  "type": "Feature",
  "properties": {
    "gn:admin1_code":"10.0",
    "gn:asciiname":"Yntymak",
    "gn:country_code":"KZ",
    "gn:dem":433,
    "gn:feature_class":"P",
    "gn:feature_code":"PPL",
    "gn:name":"Yntymak",
    "gn:population":0,
    "gn:timezone":"Asia/Almaty",
    "iso:country":"KZ",
    "name:kaz_x_preferred":[
        "Yntymaq"
    ],
    "name:kaz_x_variant":[
        "\u042b\u043d\u0442\u044b\u043c\u0430\u049b"
    ],
    "name:kir_x_preferred":[
        "\u042b\u043d\u0442\u044b\u043c\u0430\u043a"
    ],
    "name:rus_x_preferred":[
        "\u042b\u043d\u0442\u044b\u043c\u0430\u043a"
    ],
    "name:tat_x_preferred":[
        "\u042b\u043d\u0442\u044b\u043c\u0430\u043a"
    ],
    "name:und_x_variant":[
        "Intymak"
    ],
    "name:uzb_x_preferred":[
        "Intimoq"
    ],
    "name:zho_x_preferred":[
        "\u6069\u63d0\u9a6c\u514b"
    ],
    "wof:name":"Yntymak",
    "wof:placetype":"locality"
},
  "geometry": {"coordinates":[69.13988000000001,41.40454],"type":"Point"}
}