{
  "type": "Feature",
  "properties": {
    "gn:admin1_code":"11.0",
    "gn:asciiname":"Kurumsy",
    "gn:country_code":"KZ",
    "gn:dem":114,
    "gn:feature_class":"P",
    "gn:feature_code":"PPL",
    "gn:name":"Kurumsy",
    "gn:population":0,
    "gn:timezone":"Asia/Almaty",
    "iso:country":"KZ",
    "name:kaz_x_preferred":[
        "Q\u016brymsy"
    ],
    "name:kaz_x_variant":[
        "\u049a\u0443\u0440\u044b\u043c\u0441\u044b"
    ],
    "name:rus_x_preferred":[
        "\u041a\u0443\u0440\u0443\u043c\u0441\u044b"
    ],
    "wof:name":"Kurumsy",
    "wof:placetype":"locality"
},
  "geometry": {"coordinates":[76.39901999999999,52.41958],"type":"Point"}
}