{
  "type": "Feature",
  "properties": {
    "gn:admin1_code":"0.0",
    "gn:asciiname":"Mirzagora",
    "gn:country_code":"KZ",
    "gn:dem":70,
    "gn:feature_class":"P",
    "gn:feature_code":"PPL",
    "gn:name":"Mirzagora",
    "gn:population":0,
    "gn:timezone":"Asia/Oral",
    "iso:country":"KZ",
    "name:eng_x_preferred":[
        "Mirzagora"
    ],
    "name:rus_x_preferred":[
        "\u041c\u0443\u0440\u0437\u0430\u0433\u0430\u0440\u0430"
    ],
    "name:und_x_variant":[
        "Myrzagora",
        "Mirzagora"
    ],
    "wof:name":"Mirzagora",
    "wof:placetype":"locality"
},
  "geometry": {"coordinates":[53.74958,51.17775],"type":"Point"}
}