{
  "type": "Feature",
  "properties": {
    "gn:admin1_code":"11.0",
    "gn:asciiname":"Zhambak",
    "gn:country_code":"KZ",
    "gn:dem":449,
    "gn:feature_class":"P",
    "gn:feature_code":"PPL",
    "gn:name":"Zhambak",
    "gn:population":0,
    "gn:timezone":"Asia/Almaty",
    "iso:country":"KZ",
    "name:rus_x_preferred":[
        "\u0416\u0430\u043c\u0431\u0430\u043a"
    ],
    "wof:name":"Zhambak",
    "wof:placetype":"locality"
},
  "geometry": {"coordinates":[75.53789,50.80992],"type":"Point"}
}