{
  "type": "Feature",
  "properties": {
    "gn:admin1_code":"10.0",
    "gn:asciiname":"Akdala",
    "gn:country_code":"KZ",
    "gn:dem":187,
    "gn:feature_class":"P",
    "gn:feature_code":"PPL",
    "gn:name":"Akdala",
    "gn:population":0,
    "gn:timezone":"Asia/Almaty",
    "iso:country":"KZ",
    "name:ceb_x_preferred":[
        "Akdala"
    ],
    "name:fas_x_preferred":[
        "\u0627\u06a9\u062f\u0627\u0644\u0627"
    ],
    "name:kaz_x_preferred":[
        "\u0410\u049b\u0434\u0430\u043b\u0430"
    ],
    "name:mkd_x_preferred":[
        "\u0410\u043a\u0434\u0430\u043b\u0430"
    ],
    "name:msa_x_preferred":[
        "Akdala"
    ],
    "name:por_x_preferred":[
        "Akdala"
    ],
    "name:rus_x_preferred":[
        "\u0410\u043a\u0434\u0430\u043b\u0430"
    ],
    "name:swe_x_preferred":[
        "Akdala"
    ],
    "name:ukr_x_preferred":[
        "\u0410\u043a\u0434\u0430\u043b\u0430"
    ],
    "wof:name":"Akdala",
    "wof:placetype":"locality"
},
  "geometry": {"coordinates":[67.86190999999999,42.99965],"type":"Point"}
}