{
  "type": "Feature",
  "properties": {
    "gn:admin1_code":"13.0",
    "gn:asciiname":"Naberezhnoe",
    "gn:country_code":"KZ",
    "gn:dem":172,
    "gn:feature_class":"P",
    "gn:feature_code":"PPL",
    "gn:name":"Naberezhnoe",
    "gn:population":0,
    "gn:timezone":"Asia/Qyzylorda",
    "iso:country":"KZ",
    "name:kaz_x_preferred":[
        "Naberezhnoe"
    ],
    "name:kaz_x_variant":[
        "\u041d\u0430\u0431\u0435\u0440\u0435\u0436\u043d\u043e\u0435"
    ],
    "name:und_x_variant":[
        "Naberezhnoye"
    ],
    "wof:name":"Naberezhnoe",
    "wof:placetype":"locality"
},
  "geometry": {"coordinates":[62.80204000000001,52.86221999999999],"type":"Point"}
}