{
  "type": "Feature",
  "properties": {
    "gn:admin1_code":"7.0",
    "gn:asciiname":"Akoba",
    "gn:country_code":"KZ",
    "gn:dem":21,
    "gn:feature_class":"P",
    "gn:feature_code":"PPL",
    "gn:name":"Akoba",
    "gn:population":0,
    "gn:timezone":"Asia/Oral",
    "iso:country":"KZ",
    "name:eng_x_preferred":[
        "Akoba"
    ],
    "name:rus_x_preferred":[
        "\u0410\u043a\u043e\u0431\u0430"
    ],
    "name:und_x_variant":[
        "Shigankol\u2019",
        "Shygankol\u2019"
    ],
    "wof:name":"Akoba",
    "wof:placetype":"locality"
},
  "geometry": {"coordinates":[52.8029,49.91512],"type":"Point"}
}