{
  "type": "Feature",
  "properties": {
    "gn:admin1_code":"1.0",
    "gn:asciiname":"Aksengir",
    "gn:country_code":"KZ",
    "gn:dem":645,
    "gn:feature_class":"P",
    "gn:feature_code":"PPL",
    "gn:name":"Aksengir",
    "gn:population":0,
    "gn:timezone":"Asia/Almaty",
    "iso:country":"KZ",
    "name:kaz_x_preferred":[
        "Aqsenggir"
    ],
    "name:kaz_x_variant":[
        "\u0410\u049b\u0441\u0435\u04a3\u0433i\u0440"
    ],
    "name:rus_x_preferred":[
        "\u0410\u043a\u0441\u0435\u043d\u0433\u0438\u0440"
    ],
    "wof:name":"Aksengir",
    "wof:placetype":"locality"
},
  "geometry": {"coordinates":[76.27979000000001,43.48839],"type":"Point"}
}