{
  "type": "Feature",
  "properties": {
    "gn:admin1_code":"12.0",
    "gn:asciiname":"Nurinskiy Tretiy",
    "gn:country_code":"KZ",
    "gn:dem":385,
    "gn:feature_class":"P",
    "gn:feature_code":"PPL",
    "gn:name":"Nurinskiy Tretiy",
    "gn:population":0,
    "gn:timezone":"Asia/Almaty",
    "iso:country":"KZ",
    "wof:name":"Nurinskiy Tretiy",
    "wof:placetype":"locality"
},
  "geometry": {"coordinates":[70.95,49.75],"type":"Point"}
}