{
  "type": "Feature",
  "properties": {
    "gn:admin1_code":"16.0",
    "gn:asciiname":"Molodezhnyy",
    "gn:country_code":"KZ",
    "gn:dem":132,
    "gn:feature_class":"P",
    "gn:feature_code":"PPL",
    "gn:name":"Molod\u00ebzhnyy",
    "gn:population":0,
    "gn:timezone":"Asia/Almaty",
    "iso:country":"KZ",
    "name:rus_x_preferred":[
        "Molod\u00ebzhnyy"
    ],
    "wof:name":"Molodezhnyy",
    "wof:placetype":"locality"
},
  "geometry": {"coordinates":[70.25,55.13333000000001],"type":"Point"}
}