{
  "type": "Feature",
  "properties": {
    "gn:admin1_code":"17.0",
    "gn:asciiname":"Beskatyn",
    "gn:country_code":"KZ",
    "gn:dem":446,
    "gn:feature_class":"P",
    "gn:feature_code":"PPL",
    "gn:name":"Beskatyn",
    "gn:population":0,
    "gn:timezone":"Asia/Almaty",
    "iso:country":"KZ",
    "name:rus_x_preferred":[
        "\u0411\u0435\u0441\u043a\u0430\u0442\u044b\u043d"
    ],
    "wof:name":"Beskatyn",
    "wof:placetype":"locality"
},
  "geometry": {"coordinates":[73.02925,43.81323],"type":"Point"}
}