{
  "type": "Feature",
  "properties": {
    "gn:admin1_code":"10.0",
    "gn:asciiname":"Azatlyq",
    "gn:country_code":"KZ",
    "gn:dem":696,
    "gn:feature_class":"P",
    "gn:feature_code":"PPL",
    "gn:name":"Azatlyq",
    "gn:population":0,
    "gn:timezone":"Asia/Almaty",
    "iso:country":"KZ",
    "name:kaz_x_preferred":[
        "Azatlyq"
    ],
    "name:kaz_x_variant":[
        "\u0410\u0437\u0430\u0442\u043b\u044b\u049b"
    ],
    "name:rus_x_preferred":[
        "\u0410\u0437\u0430\u0442\u043b\u044b\u043a"
    ],
    "name:und_x_variant":[
        "Azatlyk"
    ],
    "wof:name":"Azatlyq",
    "wof:placetype":"locality"
},
  "geometry": {"coordinates":[70.28505,42.55312],"type":"Point"}
}