{
  "type": "Feature",
  "properties": {
    "gn:admin1_code":"3.0",
    "gn:asciiname":"Bulaqty",
    "gn:country_code":"KZ",
    "gn:dem":308,
    "gn:feature_class":"P",
    "gn:feature_code":"PPL",
    "gn:name":"Bulaqty",
    "gn:population":0,
    "gn:timezone":"Asia/Almaty",
    "iso:country":"KZ",
    "name:kaz_x_preferred":[
        "Bulaqty"
    ],
    "name:und_x_variant":[
        "Krasnogvardeyskiy",
        "Krasnogvardeyskoye"
    ],
    "wof:name":"Bulaqty",
    "wof:placetype":"locality"
},
  "geometry": {"coordinates":[69.30542,51.40917],"type":"Point"}
}