{
  "type": "Feature",
  "properties": {
    "gn:admin1_code":"0.0",
    "gn:asciiname":"Foma-Kuduk",
    "gn:country_code":"KZ",
    "gn:dem":14,
    "gn:feature_class":"P",
    "gn:feature_code":"PPL",
    "gn:name":"Foma-Kuduk",
    "gn:population":0,
    "gn:timezone":"Asia/Oral",
    "iso:country":"KZ",
    "wof:name":"Foma-Kuduk",
    "wof:placetype":"locality"
},
  "geometry": {"coordinates":[49.05,50.16667],"type":"Point"}
}