{
  "type": "Feature",
  "properties": {
    "gn:admin1_code":"1.0",
    "gn:asciiname":"Bayserka",
    "gn:country_code":"KZ",
    "gn:dem":689,
    "gn:feature_class":"P",
    "gn:feature_code":"PPL",
    "gn:name":"Bayserka",
    "gn:population":0,
    "gn:timezone":"Asia/Almaty",
    "iso:country":"KZ",
    "wof:name":"Bayserka",
    "wof:placetype":"locality"
},
  "geometry": {"coordinates":[77.10889,43.38361],"type":"Point"}
}