{
  "type": "Feature",
  "properties": {
    "gn:admin1_code":"1.0",
    "gn:asciiname":"Bayserka",
    "gn:country_code":"KZ",
    "gn:dem":689,
    "gn:feature_class":"P",
    "gn:feature_code":"PPL",
    "gn:name":"Bayserka",
    "gn:population":0,
    "gn:timezone":"Asia/Almaty",
    "iso:country":"KZ",
    "name:ell_x_preferred":[
        "\u039c\u03c0\u03b1\u03ca\u03c3\u03ad\u03c1\u03ba\u03b5"
    ],
    "name:mkd_x_preferred":[
        "\u0411\u0430\u0458\u0441\u0435\u0440\u043a\u0430"
    ],
    "name:msa_x_preferred":[
        "Bayserka"
    ],
    "wof:name":"Bayserka",
    "wof:placetype":"locality"
},
  "geometry": {"coordinates":[77.10889,43.38361],"type":"Point"}
}