{
  "type": "Feature",
  "properties": {
    "gn:admin1_code":"0.0",
    "gn:asciiname":"Ortashumishkol'",
    "gn:country_code":"KZ",
    "gn:dem":104,
    "gn:feature_class":"P",
    "gn:feature_code":"PPL",
    "gn:name":"Ortashumishkol\u2019",
    "gn:population":0,
    "gn:timezone":"Asia/Almaty",
    "iso:country":"KZ",
    "name:und_x_variant":[
        "Orta-Shumishkul\u2019",
        "Ortashumishkol\u2019"
    ],
    "wof:name":"Ortashumishkol'",
    "wof:placetype":"locality"
},
  "geometry": {"coordinates":[63.61666999999999,48.93333],"type":"Point"}
}