{
  "type": "Feature",
  "properties": {
    "gn:admin1_code":"6.0",
    "gn:asciiname":"Aksorke",
    "gn:country_code":"KZ",
    "gn:dem":-9,
    "gn:feature_class":"P",
    "gn:feature_code":"PPL",
    "gn:name":"Aksorke",
    "gn:population":0,
    "gn:timezone":"Asia/Atyrau",
    "iso:country":"KZ",
    "name:und_x_variant":[
        "Akserke",
        "Aksorke"
    ],
    "wof:name":"Aksorke",
    "wof:placetype":"locality"
},
  "geometry": {"coordinates":[51.63333,48.33333],"type":"Point"}
}