{
  "type": "Feature",
  "properties": {
    "gn:admin1_code":"15.0",
    "gn:asciiname":"Qabanbay",
    "gn:country_code":"KZ",
    "gn:dem":441,
    "gn:feature_class":"P",
    "gn:feature_code":"PPL",
    "gn:name":"Qabanbay",
    "gn:population":0,
    "gn:timezone":"Asia/Almaty",
    "iso:country":"KZ",
    "name:und_x_variant":[
        "Kabanbay",
        "Krupskoye",
        "Qabanbay"
    ],
    "wof:name":"Qabanbay",
    "wof:placetype":"locality"
},
  "geometry": {"coordinates":[83.5727,47.86887],"type":"Point"}
}