{
  "type": "Feature",
  "properties": {
    "gn:country":"KZ",
    "gn:fcode":"PPL",
    "gn:pop":1571,
    "iso:country":"KZ",
    "name:eng_x_preferred":[
        "Say\u00f6tesh"
    ],
    "name:rus_x_preferred":[
        "\u0421\u0430\u0439-\u0423\u0442\u0435\u0441"
    ],
    "name:unk_x_variant":[
        "Say-Ut\u00ebs"
    ],
    "qs:name":"Say\u00f6tesh",
    "qs:photos_9r":0,
    "qs:photos_sr":0,
    "qs:pop_sr":"3",
    "wof:name":"Say\u00f6tesh",
    "wof:placetype":"locality",
    "wof:population":1571
},
  "geometry": {"coordinates":[53.53246,44.32781],"type":"Point"}
}