{
  "type": "Feature",
  "properties": {
    "gn:admin1_code":"16.0",
    "gn:asciiname":"Karagash",
    "gn:country_code":"KZ",
    "gn:dem":264,
    "gn:feature_class":"P",
    "gn:feature_code":"PPL",
    "gn:name":"Karagash",
    "gn:population":0,
    "gn:timezone":"Asia/Almaty",
    "iso:country":"KZ",
    "name:eng_x_preferred":[
        "Karagash"
    ],
    "name:kaz_x_preferred":[
        "Qaraaghash"
    ],
    "name:kaz_x_variant":[
        "\u049a\u0430\u0440\u0430\u0430\u0493\u0430\u0448"
    ],
    "name:rus_x_preferred":[
        "\u041a\u0430\u0440\u0430\u0433\u0430\u0448"
    ],
    "name:rus_x_variant":[
        "\u041a\u0430\u0431\u0430\u0439"
    ],
    "name:und_x_variant":[
        "Kabay",
        "Karagash"
    ],
    "wof:name":"Karagash",
    "wof:placetype":"locality"
},
  "geometry": {"coordinates":[67.15203000000001,53.04237],"type":"Point"}
}