{
  "type": "Feature",
  "properties": {
    "gn:admin1_code":"16.0",
    "gn:asciiname":"Karagash",
    "gn:country_code":"KZ",
    "gn:dem":264,
    "gn:feature_class":"P",
    "gn:feature_code":"PPL",
    "gn:name":"Karagash",
    "gn:population":0,
    "gn:timezone":"Asia/Almaty",
    "iso:country":"KZ",
    "name:aze_x_preferred":[
        "Qaraqa\u015flar"
    ],
    "name:bel_x_preferred":[
        "\u041a\u0430\u0440\u0430\u0433\u0430\u0448\u044b"
    ],
    "name:eng_x_preferred":[
        "Karagash"
    ],
    "name:fin_x_preferred":[
        "Karaga\u0161it"
    ],
    "name:fra_x_preferred":[
        "Karagasses"
    ],
    "name:kat_x_preferred":[
        "\u10e7\u10d0\u10e0\u10d0\u10e6\u10d0\u10e8\u10d4\u10d1\u10d8"
    ],
    "name:kaz_x_preferred":[
        "Qaraaghash"
    ],
    "name:kaz_x_variant":[
        "\u049a\u0430\u0440\u0430\u0430\u0493\u0430\u0448"
    ],
    "name:rus_x_preferred":[
        "\u041a\u0430\u0440\u0430\u0433\u0430\u0448"
    ],
    "name:rus_x_variant":[
        "\u041a\u0430\u0431\u0430\u0439",
        "\u041a\u0430\u0440\u0430\u0433\u0430\u0448\u0438"
    ],
    "name:tat_x_preferred":[
        "\u041a\u0430\u0440\u0430\u0433\u0430\u0448\u043b\u0430\u0440"
    ],
    "name:und_x_variant":[
        "Kabay"
    ],
    "wof:name":"Karagash",
    "wof:placetype":"locality"
},
  "geometry": {"coordinates":[67.15203000000001,53.04237],"type":"Point"}
}