{
  "type": "Feature",
  "properties": {
    "gn:admin1_code":"10.0",
    "gn:asciiname":"Imeni Sverdlova",
    "gn:country_code":"KZ",
    "gn:dem":268,
    "gn:feature_class":"P",
    "gn:feature_code":"PPL",
    "gn:name":"Imeni Sverdlova",
    "gn:population":0,
    "gn:timezone":"Asia/Almaty",
    "iso:country":"KZ",
    "name:uzb_x_preferred":[
        "Sverdlovo"
    ],
    "wof:name":"Imeni Sverdlova",
    "wof:placetype":"locality"
},
  "geometry": {"coordinates":[68.59536999999999,40.69642],"type":"Point"}
}