{
  "type": "Feature",
  "properties": {
    "gn:admin1_code":"12.0",
    "gn:asciiname":"Kyzyluy",
    "gn:country_code":"KZ",
    "gn:dem":198,
    "gn:feature_class":"P",
    "gn:feature_code":"PPL",
    "gn:name":"Kyzyl\u00fcy",
    "gn:population":0,
    "gn:timezone":"Asia/Almaty",
    "iso:country":"KZ",
    "name:kaz_x_preferred":[
        "Kyzyl\u00fcy"
    ],
    "name:und_x_variant":[
        "Imeni Amangel\u2019dy"
    ],
    "wof:name":"Kyzyluy",
    "wof:placetype":"locality"
},
  "geometry": {"coordinates":[65.45,48.16667],"type":"Point"}
}