{
  "type": "Feature",
  "properties": {
    "gn:admin1_code":"12.0",
    "gn:asciiname":"Araltobe",
    "gn:country_code":"KZ",
    "gn:dem":531,
    "gn:feature_class":"P",
    "gn:feature_code":"PPL",
    "gn:name":"Araltobe",
    "gn:population":0,
    "gn:timezone":"Asia/Almaty",
    "iso:country":"KZ",
    "name:kaz_x_preferred":[
        "\u0410\u0440\u0430\u043b\u0442\u04e9\u0431\u0435"
    ],
    "name:rus_x_preferred":[
        "\u0410\u0440\u0430\u043b\u0442\u043e\u0431\u0435"
    ],
    "name:ukr_x_preferred":[
        "\u0410\u0440\u0430\u043b\u0442\u043e\u0431\u0435"
    ],
    "wof:name":"Araltobe",
    "wof:placetype":"locality"
},
  "geometry": {"coordinates":[66.88718,48.37571],"type":"Point"}
}