{
  "type": "Feature",
  "properties": {
    "gn:admin1_code":"14.0",
    "gn:asciiname":"Kazposyolok",
    "gn:country_code":"KZ",
    "gn:dem":599,
    "gn:feature_class":"P",
    "gn:feature_code":"PPL",
    "gn:name":"Kazposyolok",
    "gn:population":0,
    "gn:timezone":"Asia/Almaty",
    "iso:country":"KZ",
    "name:rus_x_preferred":[
        "\u041a\u0430\u0437\u043f\u043e\u0441\u0451\u043b\u043e\u043a"
    ],
    "wof:name":"Kazposyolok",
    "wof:placetype":"locality"
},
  "geometry": {"coordinates":[71.45000999999998,42.92137],"type":"Point"}
}