{
  "type": "Feature",
  "properties": {
    "gn:admin1_code":"12.0",
    "gn:asciiname":"Topan",
    "gn:country_code":"KZ",
    "gn:dem":579,
    "gn:feature_class":"P",
    "gn:feature_code":"PPL",
    "gn:name":"Topan",
    "gn:population":0,
    "gn:timezone":"Asia/Almaty",
    "iso:country":"KZ",
    "name:kaz_x_preferred":[
        "Topan"
    ],
    "name:kaz_x_variant":[
        "\u0422\u043e\u043f\u0430\u043d"
    ],
    "wof:name":"Topan",
    "wof:placetype":"locality"
},
  "geometry": {"coordinates":[72.38499,50.33691],"type":"Point"}
}