{
  "type": "Feature",
  "properties": {
    "gn:admin1_code":"0.0",
    "gn:asciiname":"Trovglazovka",
    "gn:country_code":"KZ",
    "gn:dem":878,
    "gn:feature_class":"P",
    "gn:feature_code":"PPL",
    "gn:name":"Trovglazovka",
    "gn:population":0,
    "gn:timezone":"Asia/Almaty",
    "iso:country":"KZ",
    "name:und_x_variant":[
        "Troyeglazovka",
        "Trovglazovka"
    ],
    "wof:name":"Trovglazovka",
    "wof:placetype":"locality"
},
  "geometry": {"coordinates":[83.27441999999998,49.84541],"type":"Point"}
}