{
  "type": "Feature",
  "properties": {
    "gn:admin1_code":"12.0",
    "gn:asciiname":"Sulu-Medine",
    "gn:country_code":"KZ",
    "gn:dem":572,
    "gn:feature_class":"P",
    "gn:feature_code":"PPL",
    "gn:name":"Sulu-Medine",
    "gn:population":0,
    "gn:timezone":"Asia/Almaty",
    "iso:country":"KZ",
    "name:kaz_x_preferred":[
        "S\u016bly-Med\u012bne"
    ],
    "name:kaz_x_variant":[
        "\u0421\u0443\u043b\u044b-\u041c\u0435\u0434\u0438\u043d\u0435"
    ],
    "name:rus_x_preferred":[
        "\u0421\u0443\u043b\u0443-\u041c\u0435\u0434\u0438\u043d\u0435"
    ],
    "wof:name":"Sulu-Medine",
    "wof:placetype":"locality"
},
  "geometry": {"coordinates":[72.83525999999998,49.2468],"type":"Point"}
}