{
  "type": "Feature",
  "properties": {
    "gn:admin1_code":"11.0",
    "gn:asciiname":"Qyzylshilik",
    "gn:country_code":"KZ",
    "gn:dem":366,
    "gn:feature_class":"P",
    "gn:feature_code":"PPL",
    "gn:name":"Qyzylshilik",
    "gn:population":0,
    "gn:timezone":"Asia/Almaty",
    "iso:country":"KZ",
    "name:kaz_x_preferred":[
        "Qyzylshilik"
    ],
    "name:kaz_x_variant":[
        "\u049a\u044b\u0437\u044b\u043b\u0448\u0456\u043b\u0456\u043a"
    ],
    "name:rus_x_preferred":[
        "\u041a\u044b\u0437\u044b\u043b\u0448\u0438\u043b\u0438\u043a \u041f\u0435\u0440\u0432\u044b\u0439"
    ],
    "name:und_x_variant":[
        "Kyzylshilik Pervyy"
    ],
    "wof:name":"Qyzylshilik",
    "wof:placetype":"locality"
},
  "geometry": {"coordinates":[75.6148,50.88124000000001],"type":"Point"}
}