{
  "type": "Feature",
  "properties": {
    "gn:admin1_code":"13.0",
    "gn:asciiname":"Tastyozek",
    "gn:country_code":"KZ",
    "gn:dem":226,
    "gn:feature_class":"P",
    "gn:feature_code":"PPL",
    "gn:name":"Tastyozek",
    "gn:population":0,
    "gn:timezone":"Asia/Qyzylorda",
    "iso:country":"KZ",
    "name:eng_x_preferred":[
        "Tastyozek"
    ],
    "name:kaz_x_preferred":[
        "Tasty\u00f6zek"
    ],
    "name:kaz_x_variant":[
        "\u0422\u0430\u0441\u0442\u044b\u04e9\u0437\u0435\u043a"
    ],
    "name:rus_x_preferred":[
        "\u0422\u0430\u0441\u0442\u0443\u0437\u0435\u043a"
    ],
    "name:rus_x_variant":[
        "\u0422\u0430\u0441\u0442\u044b\u043e\u0437\u0435\u043a"
    ],
    "name:und_x_variant":[
        "Tastuzek"
    ],
    "wof:name":"Tastyozek",
    "wof:placetype":"locality"
},
  "geometry": {"coordinates":[61.83648,53.39751],"type":"Point"}
}