{
  "type": "Feature",
  "properties": {
    "gn:admin1_code":"0.0",
    "gn:asciiname":"Novorybinskiy",
    "gn:country_code":"KZ",
    "gn:dem":398,
    "gn:feature_class":"P",
    "gn:feature_code":"PPL",
    "gn:name":"Novorybinskiy",
    "gn:population":0,
    "gn:timezone":"Asia/Almaty",
    "iso:country":"KZ",
    "wof:name":"Novorybinskiy",
    "wof:placetype":"locality"
},
  "geometry": {"coordinates":[71.95,51.25],"type":"Point"}
}