{
  "type": "Feature",
  "properties": {
    "gn:admin1_code":"15.0",
    "gn:asciiname":"Aqaral",
    "gn:country_code":"KZ",
    "gn:dem":395,
    "gn:feature_class":"P",
    "gn:feature_code":"PPL",
    "gn:name":"Aqaral",
    "gn:population":0,
    "gn:timezone":"Asia/Almaty",
    "iso:country":"KZ",
    "name:und_x_variant":[
        "Agaral",
        "Akaral",
        "Aqaral"
    ],
    "wof:name":"Aqaral",
    "wof:placetype":"locality"
},
  "geometry": {"coordinates":[84.78473000000002,47.76734],"type":"Point"}
}