{
  "type": "Feature",
  "properties": {
    "gn:admin1_code":"12.0",
    "gn:asciiname":"Razrez Borlinskiy",
    "gn:country_code":"KZ",
    "gn:dem":426,
    "gn:feature_class":"P",
    "gn:feature_code":"PPL",
    "gn:name":"Razrez Borlinskiy",
    "gn:population":0,
    "gn:timezone":"Asia/Almaty",
    "iso:country":"KZ",
    "name:rus_x_preferred":[
        "\u0420\u0430\u0437\u0440\u0435\u0437 \u0411\u043e\u0440\u043b\u0438\u043d\u0441\u043a\u0438\u0439"
    ],
    "wof:name":"Razrez Borlinskiy",
    "wof:placetype":"locality"
},
  "geometry": {"coordinates":[73.65561,50.85475],"type":"Point"}
}