{
  "type": "Feature",
  "properties": {
    "gn:admin1_code":"0.0",
    "gn:asciiname":"Kashkyn",
    "gn:country_code":"KZ",
    "gn:dem":144,
    "gn:feature_class":"P",
    "gn:feature_code":"PPL",
    "gn:name":"Kashkyn",
    "gn:population":0,
    "gn:timezone":"Asia/Almaty",
    "iso:country":"KZ",
    "wof:name":"Kashkyn",
    "wof:placetype":"locality"
},
  "geometry": {"coordinates":[78.13333,52.18333],"type":"Point"}
}