{
  "type": "Feature",
  "properties": {
    "gn:admin1_code":"1.0",
    "gn:asciiname":"Tauturgen",
    "gn:country_code":"KZ",
    "gn:dem":1132,
    "gn:feature_class":"P",
    "gn:feature_code":"PPL",
    "gn:name":"Tauturgen",
    "gn:population":0,
    "gn:timezone":"Asia/Almaty",
    "iso:country":"KZ",
    "name:kaz_x_preferred":[
        "Ta\u016bt\u00fcrgen"
    ],
    "name:kaz_x_variant":[
        "\u0422\u0430\u0443\u0442\u04af\u0440\u0433\u0435\u043d"
    ],
    "name:rus_x_preferred":[
        "\u0422\u0430\u0443\u0442\u0443\u0440\u0433\u0435\u043d"
    ],
    "name:und_x_variant":[
        "Tauturgyn"
    ],
    "wof:name":"Tauturgen",
    "wof:placetype":"locality"
},
  "geometry": {"coordinates":[77.61718,43.35158],"type":"Point"}
}