{
  "type": "Feature",
  "properties": {
    "gn:admin1_code":"13.0",
    "gn:asciiname":"Pridorozhnyy",
    "gn:country_code":"KZ",
    "gn:dem":185,
    "gn:feature_class":"P",
    "gn:feature_code":"PPL",
    "gn:name":"Pridorozhnyy",
    "gn:population":0,
    "gn:timezone":"Asia/Qyzylorda",
    "iso:country":"KZ",
    "name:kaz_x_preferred":[
        "Pr\u012bdorozhnyy"
    ],
    "name:kaz_x_variant":[
        "\u041f\u0440\u0438\u0434\u043e\u0440\u043e\u0436\u043d\u044b\u0439"
    ],
    "wof:name":"Pridorozhnyy",
    "wof:placetype":"locality"
},
  "geometry": {"coordinates":[63.07843,53.51031],"type":"Point"}
}