{
  "type": "Feature",
  "properties": {
    "gn:admin1_code":"15.0",
    "gn:asciiname":"Qaratal",
    "gn:country_code":"KZ",
    "gn:dem":463,
    "gn:feature_class":"P",
    "gn:feature_code":"PPL",
    "gn:name":"Qaratal",
    "gn:population":0,
    "gn:timezone":"Asia/Almaty",
    "iso:country":"KZ",
    "name:kaz_x_preferred":[
        "Qaratal"
    ],
    "name:und_x_variant":[
        "Imeni Krupskoy"
    ],
    "wof:name":"Qaratal",
    "wof:placetype":"locality"
},
  "geometry": {"coordinates":[82.09999999999999,46.75],"type":"Point"}
}