{
  "type": "Feature",
  "properties": {
    "gn:admin1_code":"16.0",
    "gn:asciiname":"Karaagash",
    "gn:country_code":"KZ",
    "gn:dem":152,
    "gn:feature_class":"P",
    "gn:feature_code":"PPL",
    "gn:name":"Karaagash",
    "gn:population":0,
    "gn:timezone":"Asia/Almaty",
    "iso:country":"KZ",
    "name:eng_x_preferred":[
        "Karaagash"
    ],
    "name:kaz_x_preferred":[
        "Qaraaghash"
    ],
    "name:kaz_x_variant":[
        "\u049a\u0430\u0440\u0430\u0430\u0493\u0430\u0448"
    ],
    "name:rus_x_preferred":[
        "\u041a\u0430\u0440\u0430\u0430\u0433\u0430\u0448"
    ],
    "name:und_x_variant":[
        "Karagash",
        "Karaagash"
    ],
    "wof:name":"Karaagash",
    "wof:placetype":"locality"
},
  "geometry": {"coordinates":[66.94289999999999,54.22506],"type":"Point"}
}