{
  "type": "Feature",
  "properties": {
    "gn:admin1_code":"4.0",
    "gn:asciiname":"Novoalekseyevka",
    "gn:country_code":"KZ",
    "gn:dem":143,
    "gn:feature_class":"P",
    "gn:feature_code":"PPL",
    "gn:name":"Novoalekseyevka",
    "gn:population":0,
    "gn:timezone":"Asia/Aqtobe",
    "iso:country":"KZ",
    "name:eng_x_preferred":[
        "Novoalekseevka"
    ],
    "name:kaz_x_preferred":[
        "Novoalekseevka"
    ],
    "name:rus_x_preferred":[
        "\u041d\u043e\u0432\u043e\u0430\u043b\u0435\u043a\u0441\u0435\u0435\u0432\u043a\u0430"
    ],
    "name:und_x_variant":[
        "Khobda",
        "Novo-Alekseyevskoye",
        "Novoakkseyevka",
        "Novo-Alekseevskoe"
    ],
    "wof:name":"Novoalekseyevka",
    "wof:placetype":"locality"
},
  "geometry": {"coordinates":[55.6722,50.15002],"type":"Point"}
}