{
  "type": "Feature",
  "properties": {
    "gn:admin1_code":"0.0",
    "gn:asciiname":"Ilekshar",
    "gn:country_code":"KZ",
    "gn:dem":88,
    "gn:feature_class":"P",
    "gn:feature_code":"PPL",
    "gn:name":"Ilekshar",
    "gn:population":0,
    "gn:timezone":"Asia/Oral",
    "iso:country":"KZ",
    "name:eng_x_preferred":[
        "Ilekshar"
    ],
    "name:rus_x_preferred":[
        "\u0418\u043b\u0435\u043a\u0448\u0430\u0440"
    ],
    "wof:name":"Ilekshar",
    "wof:placetype":"locality"
},
  "geometry": {"coordinates":[54.31404000000001,50.89067],"type":"Point"}
}