{
  "type": "Feature",
  "properties": {
    "gn:admin1_code":"13.0",
    "gn:asciiname":"Lugovoye",
    "gn:country_code":"KZ",
    "gn:dem":201,
    "gn:feature_class":"P",
    "gn:feature_code":"PPL",
    "gn:name":"Lugovoye",
    "gn:population":0,
    "gn:timezone":"Asia/Qyzylorda",
    "iso:country":"KZ",
    "name:und_x_variant":[
        "Lugovoy",
        "Lugovoye"
    ],
    "wof:name":"Lugovoye",
    "wof:placetype":"locality"
},
  "geometry": {"coordinates":[63.15797,52.70537],"type":"Point"}
}