{
  "type": "Feature",
  "properties": {
    "gn:admin1_code":"11.0",
    "gn:asciiname":"Karatomar",
    "gn:country_code":"KZ",
    "gn:dem":580,
    "gn:feature_class":"P",
    "gn:feature_code":"PPL",
    "gn:name":"Karatomar",
    "gn:population":0,
    "gn:timezone":"Asia/Almaty",
    "iso:country":"KZ",
    "name:rus_x_preferred":[
        "\u041a\u0430\u0440\u0430\u0442\u043e\u043c\u0430\u0440"
    ],
    "wof:name":"Karatomar",
    "wof:placetype":"locality"
},
  "geometry": {"coordinates":[75.17397,50.18498],"type":"Point"}
}