{
  "type": "Feature",
  "properties": {
    "gn:admin1_code":"12.0",
    "gn:asciiname":"Sarybulak",
    "gn:country_code":"KZ",
    "gn:dem":507,
    "gn:feature_class":"P",
    "gn:feature_code":"PPL",
    "gn:name":"Sarybulak",
    "gn:population":0,
    "gn:timezone":"Asia/Almaty",
    "iso:country":"KZ",
    "name:rus_x_preferred":[
        "\u0421\u0430\u0440\u044b\u0431\u0443\u043b\u0430\u043a"
    ],
    "wof:name":"Sarybulak",
    "wof:placetype":"locality"
},
  "geometry": {"coordinates":[72.20318,49.91478],"type":"Point"}
}