{
  "type": "Feature",
  "properties": {
    "gn:admin1_code":"13.0",
    "gn:asciiname":"Nikolayevka",
    "gn:country_code":"KZ",
    "gn:dem":171,
    "gn:feature_class":"P",
    "gn:feature_code":"PPL",
    "gn:name":"Nikolayevka",
    "gn:population":0,
    "gn:timezone":"Asia/Qyzylorda",
    "iso:country":"KZ",
    "name:aze_x_preferred":[
        "Nikolayevka"
    ],
    "name:deu_x_preferred":[
        "Nikolajewka"
    ],
    "name:eng_x_preferred":[
        "Nikolayevka"
    ],
    "name:hye_x_preferred":[
        "\u0546\u056b\u056f\u0578\u056c\u0561\u0587\u056f\u0561"
    ],
    "name:ita_x_preferred":[
        "Nikolaevka"
    ],
    "name:kaz_x_preferred":[
        "N\u012bkolaevka"
    ],
    "name:kaz_x_variant":[
        "\u041d\u0438\u043a\u043e\u043b\u0430\u0435\u0432\u043a\u0430"
    ],
    "name:lav_x_preferred":[
        "Nikolajevka"
    ],
    "name:nld_x_preferred":[
        "Nikolajevka"
    ],
    "name:ron_x_preferred":[
        "Nicolaevca"
    ],
    "name:rus_x_preferred":[
        "\u041d\u0438\u043a\u043e\u043b\u0430\u0435\u0432\u0441\u043a\u0438\u0439"
    ],
    "name:spa_x_preferred":[
        "Nikolaevka"
    ],
    "name:ukr_x_preferred":[
        "\u041d\u0456\u043a\u043e\u043b\u0430\u0454\u0432\u043a\u0430"
    ],
    "name:und_x_variant":[
        "Nikolayevskiy",
        "Nikolayevka"
    ],
    "wof:name":"Nikolayevka",
    "wof:placetype":"locality"
},
  "geometry": {"coordinates":[62.40136999999999,52.88499],"type":"Point"}
}