{
  "type": "Feature",
  "properties": {
    "gn:admin1_code":"4.0",
    "gn:asciiname":"Izmaylovskiy",
    "gn:country_code":"KZ",
    "gn:dem":194,
    "gn:feature_class":"P",
    "gn:feature_code":"PPL",
    "gn:name":"Izmaylovskiy",
    "gn:population":0,
    "gn:timezone":"Asia/Aqtobe",
    "iso:country":"KZ",
    "name:und_x_variant":[
        "Izmailovski",
        "Izmailovskiy",
        "Izmaylovskiy"
    ],
    "wof:name":"Izmaylovskiy",
    "wof:placetype":"locality"
},
  "geometry": {"coordinates":[55.96666999999999,49.53333],"type":"Point"}
}