{
  "type": "Feature",
  "properties": {
    "gn:admin1_code":"13.0",
    "gn:asciiname":"Voronezhskoye",
    "gn:country_code":"KZ",
    "gn:dem":171,
    "gn:feature_class":"P",
    "gn:feature_code":"PPL",
    "gn:name":"Voronezhskoye",
    "gn:population":0,
    "gn:timezone":"Asia/Qyzylorda",
    "iso:country":"KZ",
    "name:eng_x_preferred":[
        "Voronezhskoye"
    ],
    "name:kaz_x_preferred":[
        "Voronezhskoe"
    ],
    "name:kaz_x_variant":[
        "\u0412\u043e\u0440\u043e\u043d\u0435\u0436\u0441\u043a\u043e\u0435"
    ],
    "name:rus_x_preferred":[
        "\u0412\u043e\u0440\u043e\u043d\u0438\u043d\u0441\u043a\u0438\u0439"
    ],
    "name:und_x_variant":[
        "Voronenskiy",
        "Voronezhskoye"
    ],
    "wof:name":"Voronezhskoye",
    "wof:placetype":"locality"
},
  "geometry": {"coordinates":[62.67318,52.82766],"type":"Point"}
}