{
  "type": "Feature",
  "properties": {
    "gn:admin1_code":"0.0",
    "gn:asciiname":"Malshat",
    "gn:country_code":"KZ",
    "gn:dem":822,
    "gn:feature_class":"P",
    "gn:feature_code":"PPL",
    "gn:name":"Malshat",
    "gn:population":0,
    "gn:timezone":"Asia/Almaty",
    "iso:country":"KZ",
    "wof:name":"Malshat",
    "wof:placetype":"locality"
},
  "geometry": {"coordinates":[80.71431,45.75874],"type":"Point"}
}