{
  "type": "Feature",
  "properties": {
    "iso:country":"KZ",
    "name:eng_x_preferred":[
        "B\u016brabay"
    ],
    "name:rus_x_preferred":[
        "\u0411\u043e\u0440\u043e\u0432\u043e\u0435"
    ],
    "name:rus_x_variant":[
        "\u0411\u0443\u0440\u0430\u0431\u0430\u0439"
    ],
    "name:unk_x_variant":[
        "Kurort Borovoye"
    ],
    "qs:gn_country":"KZ",
    "qs:gn_fcode":"PPL",
    "qs:gn_pop":6500,
    "qs:name":"Borovoye",
    "qs:name_adm0":"Kazakhstan",
    "qs:name_adm1":"Soltustik Qazaqstan",
    "qs:photos":153,
    "qs:photos_1k":31,
    "qs:photos_9k":1,
    "qs:photos_9r":4,
    "qs:photos_all":153,
    "qs:photos_sr":4,
    "qs:placetype":"Town",
    "qs:pop_sr":"5",
    "qs:woe_adm0":23424871,
    "wof:name":"Borovoye",
    "wof:placetype":"locality",
    "wof:population":6500
},
  "geometry": {"coordinates":[70.31379,53.08382],"type":"Point"}
}