{
  "type": "Feature",
  "properties": {
    "gn:admin1_code":"0.0",
    "gn:asciiname":"Bizhe",
    "gn:cc2":"KZ",
    "gn:country_code":"KZ",
    "gn:dem":841,
    "gn:feature_class":"P",
    "gn:feature_code":"PPL",
    "gn:name":"Bizhe",
    "gn:population":0,
    "gn:timezone":"Asia/Almaty",
    "iso:country":"KZ",
    "name:und_x_variant":[
        "Bidzhe",
        "Bizhe"
    ],
    "wof:name":"Bizhe",
    "wof:placetype":"locality"
},
  "geometry": {"coordinates":[78.08333,44.66667],"type":"Point"}
}