{
  "type": "Feature",
  "properties": {
    "gn:admin1_code":"17.0",
    "gn:asciiname":"Aral-Kishlak",
    "gn:country_code":"KZ",
    "gn:dem":684,
    "gn:feature_class":"P",
    "gn:feature_code":"PPL",
    "gn:name":"Aral-Kishlak",
    "gn:population":0,
    "gn:timezone":"Asia/Almaty",
    "iso:country":"KZ",
    "name:rus_x_preferred":[
        "\u0410\u0440\u0430\u043b-\u041a\u0438\u0448\u043b\u0430\u043a"
    ],
    "wof:name":"Aral-Kishlak",
    "wof:placetype":"locality"
},
  "geometry": {"coordinates":[73.52854000000001,42.87195],"type":"Point"}
}