{
  "type": "Feature",
  "properties": {
    "gn:admin1_code":"11.0",
    "gn:asciiname":"Kulakol'",
    "gn:country_code":"KZ",
    "gn:dem":144,
    "gn:feature_class":"P",
    "gn:feature_code":"PPL",
    "gn:name":"Kulakol\u2019",
    "gn:population":0,
    "gn:timezone":"Asia/Almaty",
    "iso:country":"KZ",
    "name:kaz_x_preferred":[
        "Qulak\u00f6l"
    ],
    "name:kaz_x_variant":[
        "\u049a\u04b1\u043b\u0430\u043a\u04e9\u043b"
    ],
    "name:rus_x_preferred":[
        "\u041a\u0443\u043b\u0430\u043a\u043e\u043b\u044c"
    ],
    "name:und_x_variant":[
        "Kulakol\u2019"
    ],
    "wof:name":"Kulakol'",
    "wof:placetype":"locality"
},
  "geometry": {"coordinates":[75.65803000000002,51.80914],"type":"Point"}
}