{
  "type": "Feature",
  "properties": {
    "gn:admin1_code":"3.0",
    "gn:asciiname":"Krasnyy Kordon",
    "gn:country_code":"KZ",
    "gn:dem":400,
    "gn:feature_class":"P",
    "gn:feature_code":"PPL",
    "gn:name":"Krasnyy Kordon",
    "gn:population":0,
    "gn:timezone":"Asia/Almaty",
    "iso:country":"KZ",
    "name:eng_x_preferred":[
        "Krasnyy Kordon"
    ],
    "name:kaz_x_preferred":[
        "\u041a\u0440\u0430\u0441\u043d\u044b\u0439 \u041a\u043e\u0440\u0434\u043e\u043d"
    ],
    "name:rus_x_preferred":[
        "\u041a\u0440\u0430\u0441\u043d\u044b\u0439 \u041a\u043e\u0440\u0434\u043e\u043d"
    ],
    "wof:name":"Krasnyy Kordon",
    "wof:placetype":"locality"
},
  "geometry": {"coordinates":[69.03367,52.91569000000001],"type":"Point"}
}