{
  "type": "Feature",
  "properties": {
    "gn:admin1_code":"16.0",
    "gn:asciiname":"Otdeleniye Nomer Dva Sovkhoza Chistyakovskiy",
    "gn:country_code":"KZ",
    "gn:dem":157,
    "gn:feature_class":"P",
    "gn:feature_code":"PPL",
    "gn:name":"Otdeleniye Nomer Dva Sovkhoza Chistyakovskiy",
    "gn:population":0,
    "gn:timezone":"Asia/Almaty",
    "iso:country":"KZ",
    "name:kaz_x_preferred":[
        "Ba\u016byrqamys"
    ],
    "name:kaz_x_variant":[
        "\u0411\u0430\u0443\u044b\u0440\u049b\u0430\u043c\u044b\u0441"
    ],
    "name:rus_x_preferred":[
        "\u041e\u0442\u0434\u0435\u043b\u0435\u043d\u0438\u0435 \u041d\u043e\u043c\u0435\u0440 \u0414\u0432\u0430 \u0421\u043e\u0432\u0445\u043e\u0437\u0430 \u0427\u0438\u0441\u0442\u044f\u043a\u043e\u0432\u0441\u043a\u0438\u0439"
    ],
    "wof:name":"Otdeleniye Nomer Dva Sovkhoza Chistyakovskiy",
    "wof:placetype":"locality"
},
  "geometry": {"coordinates":[71.15375,53.54981],"type":"Point"}
}