{
  "type": "Feature",
  "properties": {
    "gn:admin1_code":"0.0",
    "gn:asciiname":"Zhumashev",
    "gn:country_code":"KZ",
    "gn:dem":31,
    "gn:feature_class":"P",
    "gn:feature_code":"PPL",
    "gn:name":"Zhumash\u00ebv",
    "gn:population":0,
    "gn:timezone":"Asia/Oral",
    "iso:country":"KZ",
    "wof:name":"Zhumashev",
    "wof:placetype":"locality"
},
  "geometry": {"coordinates":[50.75,50.93333],"type":"Point"}
}