{
  "type": "Feature",
  "properties": {
    "gn:admin1_code":"3.0",
    "gn:asciiname":"Podozernyy",
    "gn:country_code":"KZ",
    "gn:dem":379,
    "gn:feature_class":"P",
    "gn:feature_code":"PPL",
    "gn:name":"Podoz\u00ebrnyy",
    "gn:population":0,
    "gn:timezone":"Asia/Almaty",
    "iso:country":"KZ",
    "name:rus_x_preferred":[
        "Podoz\u00ebrnyy"
    ],
    "name:rus_x_variant":[
        "\u041f\u043e\u0434\u043e\u0437\u0451\u0440\u043d\u044b\u0439"
    ],
    "wof:name":"Podozernyy",
    "wof:placetype":"locality"
},
  "geometry": {"coordinates":[70.81482,52.05588],"type":"Point"}
}