{
  "type": "Feature",
  "properties": {
    "gn:admin1_code":"17.0",
    "gn:asciiname":"Tulegen",
    "gn:country_code":"KZ",
    "gn:dem":731,
    "gn:feature_class":"P",
    "gn:feature_code":"PPL",
    "gn:name":"Tulegen",
    "gn:population":0,
    "gn:timezone":"Asia/Almaty",
    "iso:country":"KZ",
    "name:rus_x_preferred":[
        "\u0422\u0443\u043b\u0435\u0433\u0435\u043d"
    ],
    "wof:name":"Tulegen",
    "wof:placetype":"locality"
},
  "geometry": {"coordinates":[72.15930999999998,42.91538],"type":"Point"}
}