{
  "type": "Feature",
  "properties": {
    "gn:admin1_code":"13.0",
    "gn:asciiname":"Alabutala",
    "gn:country_code":"KZ",
    "gn:dem":176,
    "gn:feature_class":"P",
    "gn:feature_code":"PPL",
    "gn:name":"Alabutala",
    "gn:population":0,
    "gn:timezone":"Asia/Qyzylorda",
    "iso:country":"KZ",
    "name:kaz_x_preferred":[
        "Alabutala"
    ],
    "name:kaz_x_variant":[
        "\u0410\u043b\u0430\u0431\u04b1\u0442\u0430\u043b\u0430"
    ],
    "name:rus_x_preferred":[
        "\u0410\u043b\u0430\u0431\u0443\u0442\u0430\u043b\u0430"
    ],
    "wof:name":"Alabutala",
    "wof:placetype":"locality"
},
  "geometry": {"coordinates":[63.09291,53.8387],"type":"Point"}
}