{
  "type": "Feature",
  "properties": {
    "gn:admin1_code":"3.0",
    "gn:asciiname":"Ushsart",
    "gn:country_code":"KZ",
    "gn:dem":357,
    "gn:feature_class":"P",
    "gn:feature_code":"PPL",
    "gn:name":"\u00dcshsart",
    "gn:population":0,
    "gn:timezone":"Asia/Almaty",
    "iso:country":"KZ",
    "name:und_x_variant":[
        "Kurgal\u2019dzhinskiy",
        "\u00dcshsart"
    ],
    "wof:name":"Ushsart",
    "wof:placetype":"locality"
},
  "geometry": {"coordinates":[70.05041999999999,50.30086],"type":"Point"}
}