{
  "type": "Feature",
  "properties": {
    "gn:admin1_code":"3.0",
    "gn:asciiname":"Kayrakty",
    "gn:country_code":"KZ",
    "gn:dem":276,
    "gn:feature_class":"P",
    "gn:feature_code":"PPL",
    "gn:name":"Kayrakty",
    "gn:population":0,
    "gn:timezone":"Asia/Almaty",
    "iso:country":"KZ",
    "name:ces_x_preferred":[
        "Borodinovka"
    ],
    "name:kaz_x_preferred":[
        "\u049a\u0430\u0439\u0440\u0430\u049b\u0442\u044b"
    ],
    "name:msa_x_preferred":[
        "Borodinovka"
    ],
    "name:rus_x_preferred":[
        "\u041a\u0430\u0439\u0440\u0430\u043a\u0442\u044b"
    ],
    "name:ukr_x_preferred":[
        "\u041a\u0430\u0439\u0440\u0430\u043a\u0442\u0438"
    ],
    "wof:name":"Kayrakty",
    "wof:placetype":"locality"
},
  "geometry": {"coordinates":[68.03345999999999,51.18926],"type":"Point"}
}