{
  "type": "Feature",
  "properties": {
    "gn:admin1_code":"17.0",
    "gn:asciiname":"Karabastau",
    "gn:country_code":"KZ",
    "gn:dem":460,
    "gn:feature_class":"P",
    "gn:feature_code":"PPL",
    "gn:name":"Karabastau",
    "gn:population":0,
    "gn:timezone":"Asia/Almaty",
    "iso:country":"KZ",
    "name:kaz_x_preferred":[
        "Qarabasta\u016b"
    ],
    "name:kaz_x_variant":[
        "\u049a\u0430\u0440\u0430\u0431\u0430\u0441\u0442\u0430\u0443"
    ],
    "name:rus_x_preferred":[
        "\u041a\u0430\u0440\u0430\u0431\u0430\u0441\u0442\u0430\u0443"
    ],
    "wof:name":"Karabastau",
    "wof:placetype":"locality"
},
  "geometry": {"coordinates":[70.81108,42.93011],"type":"Point"}
}