{
  "type": "Feature",
  "properties": {
    "gn:admin1_code":"15.0",
    "gn:asciiname":"Ortakuduk",
    "gn:country_code":"KZ",
    "gn:dem":172,
    "gn:feature_class":"P",
    "gn:feature_code":"PPL",
    "gn:name":"Ortakuduk",
    "gn:population":0,
    "gn:timezone":"Asia/Almaty",
    "iso:country":"KZ",
    "name:rus_x_preferred":[
        "\u041e\u0440\u0442\u0430\u043a\u0443\u0434\u0443\u043a"
    ],
    "wof:name":"Ortakuduk",
    "wof:placetype":"locality"
},
  "geometry": {"coordinates":[78.32164,51.17103],"type":"Point"}
}