{
  "type": "Feature",
  "properties": {
    "gn:admin1_code":"4.0",
    "gn:asciiname":"Masak",
    "gn:country_code":"KZ",
    "gn:dem":85,
    "gn:feature_class":"P",
    "gn:feature_code":"PPL",
    "gn:name":"Masak",
    "gn:population":0,
    "gn:timezone":"Asia/Aqtobe",
    "iso:country":"KZ",
    "wof:name":"Masak",
    "wof:placetype":"locality"
},
  "geometry": {"coordinates":[61.45,48.36667],"type":"Point"}
}