{
  "type": "Feature",
  "properties": {
    "gn:admin1_code":"0.0",
    "gn:asciiname":"Kaindy-Kara-Su",
    "gn:cc2":"KZ",
    "gn:country_code":"KZ",
    "gn:dem":123,
    "gn:feature_class":"P",
    "gn:feature_code":"PPL",
    "gn:name":"Kaindy-Kara-Su",
    "gn:population":0,
    "gn:timezone":"Asia/Qyzylorda",
    "iso:country":"KZ",
    "name:und_x_variant":[
        "Kaygy-Kara-Su",
        "Kaindy-Kara-Su"
    ],
    "wof:name":"Kaindy-Kara-Su",
    "wof:placetype":"locality"
},
  "geometry": {"coordinates":[64.40000000000001,51.48333],"type":"Point"}
}