{
  "type": "Feature",
  "properties": {
    "gn:admin1_code":"0.0",
    "gn:asciiname":"Imeni Kalinina",
    "gn:country_code":"KZ",
    "gn:dem":-7,
    "gn:feature_class":"P",
    "gn:feature_code":"PPL",
    "gn:name":"Imeni Kalinina",
    "gn:population":0,
    "gn:timezone":"Asia/Oral",
    "iso:country":"KZ",
    "name:kir_x_preferred":[
        "\u041a\u0430\u043b\u0438\u043d\u0438\u043d"
    ],
    "name:uzb_x_preferred":[
        "Kalinin"
    ],
    "wof:name":"Imeni Kalinina",
    "wof:placetype":"locality"
},
  "geometry": {"coordinates":[50.16667,48.95],"type":"Point"}
}