{
  "type": "Feature",
  "properties": {
    "gn:admin1_code":"10.0",
    "gn:asciiname":"Sultanrabat",
    "gn:country_code":"KZ",
    "gn:dem":702,
    "gn:feature_class":"P",
    "gn:feature_code":"PPL",
    "gn:name":"Sultanrabat",
    "gn:population":0,
    "gn:timezone":"Asia/Almaty",
    "iso:country":"KZ",
    "name:rus_x_preferred":[
        "\u0421\u0443\u043b\u0442\u0430\u043d\u0440\u0430\u0431\u0430\u0442"
    ],
    "name:rus_x_variant":[
        "\u041a\u0430\u0440\u0430\u044e\u043b"
    ],
    "name:und_x_variant":[
        "Proletarka",
        "Sultanrabad",
        "Sultanrabat",
        "Karayul"
    ],
    "wof:name":"Sultanrabat",
    "wof:placetype":"locality"
},
  "geometry": {"coordinates":[69.82643,42.18795],"type":"Point"}
}