{
  "type": "Feature",
  "properties": {
    "gn:admin1_code":"13.0",
    "gn:asciiname":"Alshanov",
    "gn:country_code":"KZ",
    "gn:dem":229,
    "gn:feature_class":"P",
    "gn:feature_code":"PPL",
    "gn:name":"Alshanov",
    "gn:population":0,
    "gn:timezone":"Asia/Qyzylorda",
    "iso:country":"KZ",
    "name:eng_x_preferred":[
        "Ol'shanskiy"
    ],
    "name:kaz_x_preferred":[
        "Alshanov"
    ],
    "name:kaz_x_variant":[
        "\u0410\u043b\u0448\u0430\u043d\u043e\u0432"
    ],
    "name:rus_x_preferred":[
        "\u041e\u043b\u044c\u0448\u0430\u043d\u043e\u0432\u043a\u0430"
    ],
    "name:rus_x_variant":[
        "\u0410\u043b\u0447\u0430\u043d\u043e\u0432\u043a\u0430"
    ],
    "name:und_x_variant":[
        "Ol\u2019shanskiy",
        "Alchanovka"
    ],
    "wof:name":"Alshanov",
    "wof:placetype":"locality"
},
  "geometry": {"coordinates":[61.79463000000001,52.48266],"type":"Point"}
}