{
  "type": "Feature",
  "properties": {
    "gn:admin1_code":"10.0",
    "gn:asciiname":"Chu",
    "gn:country_code":"KZ",
    "gn:dem":202,
    "gn:feature_class":"P",
    "gn:feature_code":"PPL",
    "gn:name":"Chu",
    "gn:population":0,
    "gn:timezone":"Asia/Almaty",
    "iso:country":"KZ",
    "wof:name":"Chu",
    "wof:placetype":"locality"
},
  "geometry": {"coordinates":[69.42473000000001,44.80974000000001],"type":"Point"}
}