{
  "type": "Feature",
  "properties": {
    "gn:admin1_code":"15.0",
    "gn:asciiname":"Shoshkaly",
    "gn:country_code":"KZ",
    "gn:dem":176,
    "gn:feature_class":"P",
    "gn:feature_code":"PPL",
    "gn:name":"Shoshkaly",
    "gn:population":0,
    "gn:timezone":"Asia/Almaty",
    "iso:country":"KZ",
    "name:rus_x_preferred":[
        "\u0428\u043e\u0448\u043a\u0430\u043b\u044b"
    ],
    "wof:name":"Shoshkaly",
    "wof:placetype":"locality"
},
  "geometry": {"coordinates":[78.85276,51.24438],"type":"Point"}
}