{
  "type": "Feature",
  "properties": {
    "gn:admin1_code":"15.0",
    "gn:asciiname":"Mirnyy",
    "gn:country_code":"KZ",
    "gn:dem":190,
    "gn:feature_class":"P",
    "gn:feature_code":"PPL",
    "gn:name":"Mirnyy",
    "gn:population":0,
    "gn:timezone":"Asia/Almaty",
    "iso:country":"KZ",
    "name:rus_x_preferred":[
        "\u041c\u0438\u0440\u043d\u044b\u0439"
    ],
    "wof:name":"Mirnyy",
    "wof:placetype":"locality"
},
  "geometry": {"coordinates":[80.17837,50.46545],"type":"Point"}
}