{
  "type": "Feature",
  "properties": {
    "gn:admin1_code":"10.0",
    "gn:asciiname":"Pakhtaaral",
    "gn:country_code":"KZ",
    "gn:dem":265,
    "gn:feature_class":"P",
    "gn:feature_code":"PPL",
    "gn:name":"Pakhtaaral",
    "gn:population":0,
    "gn:timezone":"Asia/Almaty",
    "iso:country":"KZ",
    "name:rus_x_preferred":[
        "\u041f\u0430\u0445\u0442\u0430\u0430\u0440\u0430\u043b"
    ],
    "wof:name":"Pakhtaaral",
    "wof:placetype":"locality"
},
  "geometry": {"coordinates":[68.49124999999999,40.83442],"type":"Point"}
}