{
  "type": "Feature",
  "properties": {
    "gn:admin1_code":"0.0",
    "gn:asciiname":"Shakhty",
    "gn:country_code":"KZ",
    "gn:dem":340,
    "gn:feature_class":"P",
    "gn:feature_code":"PPL",
    "gn:name":"Shakhty",
    "gn:population":0,
    "gn:timezone":"Asia/Almaty",
    "iso:country":"KZ",
    "name:ara_x_preferred":[
        "\u0634\u0627\u062e\u062a\u0627\u064a"
    ],
    "name:ast_x_preferred":[
        "Shajty"
    ],
    "name:azb_x_preferred":[
        "\u0634\u0627\u062e\u062a\u06cc"
    ],
    "name:aze_x_preferred":[
        "\u015eaxt\u0131"
    ],
    "name:bel_x_preferred":[
        "\u0428\u0430\u0445\u0442\u044b"
    ],
    "name:bul_x_preferred":[
        "\u0428\u0430\u0445\u0442\u0438"
    ],
    "name:ceb_x_preferred":[
        "Shakhty"
    ],
    "name:ces_x_preferred":[
        "\u0160achty"
    ],
    "name:che_x_preferred":[
        "\u0428\u0430\u0445\u0442\u044b"
    ],
    "name:dan_x_preferred":[
        "Sjakhty"
    ],
    "name:deu_x_preferred":[
        "Schachty"
    ],
    "name:epo_x_preferred":[
        "\u015ca\u0125ti"
    ],
    "name:est_x_preferred":[
        "\u0160aht\u00f5"
    ],
    "name:fas_x_preferred":[
        "\u0634\u0627\u062e\u062a\u06cc"
    ],
    "name:fin_x_preferred":[
        "\u0160ahty"
    ],
    "name:fra_x_preferred":[
        "Chakhty"
    ],
    "name:hsb_x_preferred":[
        "\u0160achty"
    ],
    "name:hye_x_preferred":[
        "\u0547\u0561\u056d\u057f\u056b"
    ],
    "name:ita_x_preferred":[
        "\u0160achty"
    ],
    "name:kat_x_preferred":[
        "\u10e8\u10d0\u10ee\u10e2\u10d8"
    ],
    "name:kor_x_preferred":[
        "\uc0e4\ud750\ud2f0"
    ],
    "name:lav_x_preferred":[
        "\u0160ahti"
    ],
    "name:lit_x_preferred":[
        "\u0160achtos"
    ],
    "name:mhr_x_preferred":[
        "\u0428\u0430\u0445\u0442\u044b"
    ],
    "name:nld_x_preferred":[
        "Sjachty"
    ],
    "name:nno_x_preferred":[
        "Sjakhty"
    ],
    "name:nor_x_preferred":[
        "Sjakhty"
    ],
    "name:oss_x_preferred":[
        "\u0428\u0430\u0445\u0442\u044b"
    ],
    "name:pnb_x_preferred":[
        "\u0634\u0627\u062e\u062a\u06cc"
    ],
    "name:pol_x_preferred":[
        "Szachty"
    ],
    "name:ron_x_preferred":[
        "\u0218aht\u00ee"
    ],
    "name:rus_x_preferred":[
        "\u0428\u0430\u0445\u0442\u044b"
    ],
    "name:spa_x_preferred":[
        "Shajty"
    ],
    "name:srp_x_preferred":[
        "\u0428\u0430\u0445\u0442\u0438"
    ],
    "name:swe_x_preferred":[
        "Sjachty"
    ],
    "name:tat_x_preferred":[
        "\u0428\u0430\u0445\u0442\u044b"
    ],
    "name:tgl_x_preferred":[
        "Shakhty"
    ],
    "name:tur_x_preferred":[
        "\u015eaht\u0131"
    ],
    "name:ukr_x_preferred":[
        "\u0428\u0430\u0445\u0442\u0438"
    ],
    "name:vie_x_preferred":[
        "Shakhty"
    ],
    "name:war_x_preferred":[
        "Shakhty"
    ],
    "name:xal_x_preferred":[
        "\u0428\u0430\u0445\u0442\u044b \u0431\u0430\u043b\u04bb\u0441\u043d"
    ],
    "name:zho_x_preferred":[
        "\u6c99\u8d6b\u8482"
    ],
    "wof:name":"Shakhty",
    "wof:placetype":"locality"
},
  "geometry": {"coordinates":[71.09999999999999,51.33333],"type":"Point"}
}