{
  "type": "Feature",
  "properties": {
    "gn:admin1_code":"0.0",
    "gn:asciiname":"Shakhty",
    "gn:country_code":"KZ",
    "gn:dem":340,
    "gn:feature_class":"P",
    "gn:feature_code":"PPL",
    "gn:name":"Shakhty",
    "gn:population":0,
    "gn:timezone":"Asia/Almaty",
    "iso:country":"KZ",
    "wof:name":"Shakhty",
    "wof:placetype":"locality"
},
  "geometry": {"coordinates":[71.09999999999999,51.33333],"type":"Point"}
}