{
  "type": "Feature",
  "properties": {
    "gn:admin1_code":"16.0",
    "gn:asciiname":"Priishimka",
    "gn:country_code":"KZ",
    "gn:dem":108,
    "gn:feature_class":"P",
    "gn:feature_code":"PPL",
    "gn:name":"Priishimka",
    "gn:population":0,
    "gn:timezone":"Asia/Almaty",
    "iso:country":"KZ",
    "name:eng_x_preferred":[
        "Priishimka"
    ],
    "name:kaz_x_preferred":[
        "Pr\u012b\u012bsh\u012bmka"
    ],
    "name:kaz_x_variant":[
        "\u041f\u0440\u0438\u0438\u0448\u0438\u043c\u043a\u0430"
    ],
    "name:rus_x_preferred":[
        "\u041f\u0440\u0438\u0438\u0448\u0438\u043c\u043a\u0430"
    ],
    "wof:name":"Priishimka",
    "wof:placetype":"locality"
},
  "geometry": {"coordinates":[68.85672,54.61196],"type":"Point"}
}