{
  "type": "Feature",
  "properties": {
    "gn:admin1_code":"10.0",
    "gn:asciiname":"Arys",
    "gn:country_code":"KZ",
    "gn:dem":214,
    "gn:feature_class":"P",
    "gn:feature_code":"PPL",
    "gn:name":"Arys",
    "gn:population":0,
    "gn:timezone":"Asia/Almaty",
    "iso:country":"KZ",
    "name:ceb_x_preferred":[
        "Arys"
    ],
    "name:ces_x_preferred":[
        "Arys"
    ],
    "name:deu_x_preferred":[
        "Arys"
    ],
    "name:kat_x_preferred":[
        "\u10d0\u10e0\u10d8\u10e1\u10d8"
    ],
    "name:kaz_x_preferred":[
        "Arys"
    ],
    "name:kaz_x_variant":[
        "\u0410\u0440\u044b\u0441"
    ],
    "name:lit_x_preferred":[
        "Arysas"
    ],
    "name:nld_x_preferred":[
        "Arys"
    ],
    "name:pol_x_preferred":[
        "Arys"
    ],
    "name:rus_x_preferred":[
        "\u0410\u043a\u0442\u0430\u043c"
    ],
    "name:rus_x_variant":[
        "\u0410\u0440\u044b\u0441\u044c"
    ],
    "name:swe_x_preferred":[
        "Arys"
    ],
    "name:ukr_x_preferred":[
        "\u0410\u0440\u0438\u0441\u044c"
    ],
    "name:und_x_variant":[
        "Aktam"
    ],
    "wof:name":"Arys",
    "wof:placetype":"locality"
},
  "geometry": {"coordinates":[68.57294,42.60903],"type":"Point"}
}