{
  "type": "Feature",
  "properties": {
    "gn:admin1_code":"10.0",
    "gn:asciiname":"Arys",
    "gn:country_code":"KZ",
    "gn:dem":214,
    "gn:feature_class":"P",
    "gn:feature_code":"PPL",
    "gn:name":"Arys",
    "gn:population":0,
    "gn:timezone":"Asia/Almaty",
    "iso:country":"KZ",
    "name:ben_x_preferred":[
        "\u0986\u09b0\u09bf\u09b8"
    ],
    "name:ceb_x_preferred":[
        "Arys"
    ],
    "name:ces_x_preferred":[
        "Arys"
    ],
    "name:deu_x_preferred":[
        "Arys"
    ],
    "name:ell_x_preferred":[
        "\u0391\u03c1\u03af\u03c2"
    ],
    "name:fas_x_preferred":[
        "\u0622\u0631\u06cc\u0633"
    ],
    "name:hin_x_preferred":[
        "\u0910\u0930\u093f\u0938"
    ],
    "name:hun_x_preferred":[
        "Arys"
    ],
    "name:ita_x_preferred":[
        "Arys"
    ],
    "name:kat_x_preferred":[
        "\u10d0\u10e0\u10d8\u10e1\u10d8"
    ],
    "name:kaz_x_preferred":[
        "Arys"
    ],
    "name:kaz_x_variant":[
        "\u0410\u0440\u044b\u0441"
    ],
    "name:lit_x_preferred":[
        "Arysas"
    ],
    "name:nld_x_preferred":[
        "Arys"
    ],
    "name:pol_x_preferred":[
        "Arys"
    ],
    "name:rus_x_preferred":[
        "\u0410\u043a\u0442\u0430\u043c"
    ],
    "name:rus_x_variant":[
        "\u0410\u0440\u044b\u0441\u044c"
    ],
    "name:spa_x_preferred":[
        "Arys"
    ],
    "name:swe_x_preferred":[
        "Arys"
    ],
    "name:tur_x_preferred":[
        "Arys"
    ],
    "name:ukr_x_preferred":[
        "\u0410\u0440\u0438\u0441\u044c"
    ],
    "name:und_x_variant":[
        "Aktam"
    ],
    "name:urd_x_preferred":[
        "\u0622\u0631\u06cc\u0632"
    ],
    "name:vie_x_preferred":[
        "Arys"
    ],
    "wof:name":"Arys",
    "wof:placetype":"locality"
},
  "geometry": {"coordinates":[68.57294,42.60903],"type":"Point"}
}