{
  "type": "Feature",
  "properties": {
    "gn:admin1_code":"12.0",
    "gn:asciiname":"Severnyy Karagan",
    "gn:country_code":"KZ",
    "gn:dem":509,
    "gn:feature_class":"P",
    "gn:feature_code":"PPL",
    "gn:name":"Severnyy Karagan",
    "gn:population":0,
    "gn:timezone":"Asia/Almaty",
    "iso:country":"KZ",
    "name:rus_x_preferred":[
        "\u0421\u0435\u0432\u0435\u0440\u043d\u044b\u0439 \u041a\u0430\u0440\u0430\u0433\u0430\u043d"
    ],
    "wof:name":"Severnyy Karagan",
    "wof:placetype":"locality"
},
  "geometry": {"coordinates":[72.83877,49.61106],"type":"Point"}
}