{
  "type": "Feature",
  "properties": {
    "gn:admin1_code":"0.0",
    "gn:asciiname":"Belousov",
    "gn:country_code":"KZ",
    "gn:dem":31,
    "gn:feature_class":"P",
    "gn:feature_code":"PPL",
    "gn:name":"Belousov",
    "gn:population":0,
    "gn:timezone":"Asia/Oral",
    "iso:country":"KZ",
    "name:fra_x_preferred":[
        "Belooussov"
    ],
    "name:rus_x_preferred":[
        "\u0411\u0435\u043b\u043e\u0443\u0441\u043e\u0432"
    ],
    "name:slv_x_preferred":[
        "Belojusov"
    ],
    "name:ukr_x_preferred":[
        "\u0411\u0454\u043b\u043e\u0443\u0441\u043e\u0432"
    ],
    "wof:name":"Belousov",
    "wof:placetype":"locality"
},
  "geometry": {"coordinates":[50.15,50.85],"type":"Point"}
}