{
  "type": "Feature",
  "properties": {
    "iso:country":"KZ",
    "name:bul_x_preferred":[
        "\u0414\u0436\u0430\u043c\u0431\u0435\u0439\u0442\u0439"
    ],
    "name:dut_x_preferred":[
        "Zhympity"
    ],
    "name:eng_x_preferred":[
        "Zhymp\u012bty"
    ],
    "name:gre_x_preferred":[
        "\u0396\u03b9\u03bc\u03c0\u03af\u03c4\u03b9"
    ],
    "name:heb_x_preferred":[
        "\u05d6'\u05d9\u05de\u05e4\u05d9\u05d8\u05d9"
    ],
    "name:kaz_x_preferred":[
        "\u0416\u044b\u043c\u043f\u0438\u0442\u044b"
    ],
    "name:kaz_x_variant":[
        "Zhymp\u012bty"
    ],
    "name:rus_x_preferred":[
        "\u0416\u044b\u043c\u043f\u0438\u0442\u044b"
    ],
    "name:rus_x_variant":[
        "\u0414\u0436\u0430\u043c\u0431\u0435\u0439\u0442\u044b"
    ],
    "name:swe_x_preferred":[
        "Dzjambejty"
    ],
    "name:ukr_x_preferred":[
        "\u0416\u0438\u043c\u043f\u0456\u0442\u0438"
    ],
    "name:unk_x_variant":[
        "Dzhambeyty"
    ],
    "qs:gn_country":"KZ",
    "qs:gn_fcode":"PPL",
    "qs:gn_pop":6262,
    "qs:name":"Zhympity",
    "qs:name_adm0":"Kazakhstan",
    "qs:name_adm1":"Batys Qazaqstan",
    "qs:photos":0,
    "qs:photos_1k":0,
    "qs:photos_9k":0,
    "qs:photos_9r":0,
    "qs:photos_all":0,
    "qs:photos_sr":0,
    "qs:placetype":"Town",
    "qs:pop_sr":"5",
    "qs:woe_adm0":23424871,
    "wd:wordcount":45,
    "wof:name":"Zhympity",
    "wof:placetype":"locality",
    "wof:population":6262
},
  "geometry": {"coordinates":[52.59895,50.25676],"type":"Point"}
}