{
  "type": "Feature",
  "properties": {
    "gn:admin1_code":"17.0",
    "gn:asciiname":"Shyghanaq",
    "gn:cc2":"KZ",
    "gn:country_code":"KZ",
    "gn:dem":351,
    "gn:feature_class":"P",
    "gn:feature_code":"PPL",
    "gn:name":"Shyghanaq",
    "gn:population":0,
    "gn:timezone":"Asia/Almaty",
    "iso:country":"KZ",
    "name:und_x_variant":[
        "Chiganak",
        "Shyghanaq"
    ],
    "wof:name":"Shyghanaq",
    "wof:placetype":"locality"
},
  "geometry": {"coordinates":[73.98528,45.10639000000001],"type":"Point"}
}