{
  "type": "Feature",
  "properties": {
    "gn:admin1_code":"3.0",
    "gn:asciiname":"Kalinino",
    "gn:country_code":"KZ",
    "gn:dem":357,
    "gn:feature_class":"P",
    "gn:feature_code":"PPL",
    "gn:name":"Kalinino",
    "gn:population":0,
    "gn:timezone":"Asia/Almaty",
    "iso:country":"KZ",
    "name:ceb_x_preferred":[
        "Kalinino"
    ],
    "name:deu_x_preferred":[
        "Kalinino"
    ],
    "name:kat_x_preferred":[
        "\u10d9\u10d0\u10da\u10d8\u10dc\u10d8\u10dc\u10dd"
    ],
    "name:swe_x_preferred":[
        "Kalinino"
    ],
    "name:und_x_variant":[
        "Imeni Kalinina"
    ],
    "wof:name":"Kalinino",
    "wof:placetype":"locality"
},
  "geometry": {"coordinates":[71.5712,51.04946],"type":"Point"}
}