{
  "type": "Feature",
  "properties": {
    "gn:admin1_code":"4.0",
    "gn:asciiname":"Kiyakty",
    "gn:country_code":"KZ",
    "gn:dem":238,
    "gn:feature_class":"P",
    "gn:feature_code":"PPL",
    "gn:name":"Kiyakty",
    "gn:population":0,
    "gn:timezone":"Asia/Aqtobe",
    "iso:country":"KZ",
    "name:und_x_variant":[
        "Kyyakty",
        "Kiyakty"
    ],
    "wof:name":"Kiyakty",
    "wof:placetype":"locality"
},
  "geometry": {"coordinates":[61.81511,50.30257],"type":"Point"}
}