{
  "type": "Feature",
  "properties": {
    "gn:admin1_code":"10.0",
    "gn:asciiname":"Aktas",
    "gn:country_code":"KZ",
    "gn:dem":481,
    "gn:feature_class":"P",
    "gn:feature_code":"PPL",
    "gn:name":"Aktas",
    "gn:population":0,
    "gn:timezone":"Asia/Almaty",
    "iso:country":"KZ",
    "name:fas_x_preferred":[
        "\u0627\u06a9\u062a\u0627\u0633"
    ],
    "name:kaz_x_preferred":[
        "\u0410\u049b\u0442\u0430\u0441"
    ],
    "name:mkd_x_preferred":[
        "\u0410\u043a\u0442\u0430\u0441"
    ],
    "name:msa_x_preferred":[
        "Aktas"
    ],
    "name:rus_x_preferred":[
        "\u0410\u043a\u0442\u0430\u0441"
    ],
    "name:ukr_x_preferred":[
        "\u0410\u043a\u0442\u0430\u0441"
    ],
    "wof:name":"Aktas",
    "wof:placetype":"locality"
},
  "geometry": {"coordinates":[69.52515,42.18834],"type":"Point"}
}