{
  "type": "Feature",
  "properties": {
    "gn:admin1_code":"15.0",
    "gn:asciiname":"Snegirevo",
    "gn:country_code":"KZ",
    "gn:dem":399,
    "gn:feature_class":"P",
    "gn:feature_code":"PPL",
    "gn:name":"Snegir\u00ebvo",
    "gn:population":0,
    "gn:timezone":"Asia/Almaty",
    "iso:country":"KZ",
    "name:eng_x_preferred":[
        "Snegirevo"
    ],
    "name:kaz_x_preferred":[
        "Sneg\u012bryovo"
    ],
    "name:kaz_x_variant":[
        "\u0421\u043d\u0435\u0433\u0438\u0440\u0451\u0432\u043e"
    ],
    "name:rus_x_preferred":[
        "\u0421\u043d\u0435\u0433\u0438\u0440\u0435\u0432\u043e"
    ],
    "name:rus_x_variant":[
        "Snegir\u00ebvo"
    ],
    "name:und_x_variant":[
        "Snegevevo",
        "Snigeveva"
    ],
    "wof:name":"Snegirevo",
    "wof:placetype":"locality"
},
  "geometry": {"coordinates":[84.06583000000001,49.74732],"type":"Point"}
}