{
  "type": "Feature",
  "properties": {
    "gn:admin1_code":"0.0",
    "gn:asciiname":"Molodezhnoye",
    "gn:cc2":"KZ",
    "gn:country_code":"KZ",
    "gn:dem":328,
    "gn:feature_class":"P",
    "gn:feature_code":"PPL",
    "gn:name":"Molodezhnoye",
    "gn:population":0,
    "gn:timezone":"Asia/Almaty",
    "iso:country":"KZ",
    "name:und_x_variant":[
        "Veniaminovskoye",
        "Molod\u00ebzhnyy",
        "Molodezhnoye"
    ],
    "wof:name":"Molodezhnoye",
    "wof:placetype":"locality"
},
  "geometry": {"coordinates":[67.55,50.21667],"type":"Point"}
}