{
  "type": "Feature",
  "properties": {
    "gn:admin1_code":"1.0",
    "gn:asciiname":"Ostemir",
    "gn:country_code":"KZ",
    "gn:dem":541,
    "gn:feature_class":"P",
    "gn:feature_code":"PPL",
    "gn:name":"Ostemir",
    "gn:population":0,
    "gn:timezone":"Asia/Almaty",
    "iso:country":"KZ",
    "name:kaz_x_preferred":[
        "M\u012brnoe"
    ],
    "name:kaz_x_variant":[
        "\u041c\u0438\u0440\u043d\u043e\u0435"
    ],
    "name:rus_x_preferred":[
        "\u041e\u0441\u0442\u0435\u043c\u0438\u0440"
    ],
    "name:rus_x_variant":[
        "\u041c\u0438\u0440\u043d\u044b\u0439"
    ],
    "name:und_x_variant":[
        "Mirnyy"
    ],
    "wof:name":"Ostemir",
    "wof:placetype":"locality"
},
  "geometry": {"coordinates":[77.26121999999999,43.62952],"type":"Point"}
}