{
  "type": "Feature",
  "properties": {
    "gn:admin1_code":"13.0",
    "gn:asciiname":"Priozernyy",
    "gn:country_code":"KZ",
    "gn:dem":117,
    "gn:feature_class":"P",
    "gn:feature_code":"PPL",
    "gn:name":"Prioz\u00ebrnyy",
    "gn:population":0,
    "gn:timezone":"Asia/Qyzylorda",
    "iso:country":"KZ",
    "name:rus_x_preferred":[
        "Prioz\u00ebrnyy"
    ],
    "name:rus_x_variant":[
        "\u041f\u0440\u0438\u043e\u0437\u0451\u0440\u043d\u044b\u0439"
    ],
    "wof:name":"Priozernyy",
    "wof:placetype":"locality"
},
  "geometry": {"coordinates":[64.55897,53.79533000000001],"type":"Point"}
}