{
  "type": "Feature",
  "properties": {
    "gn:admin1_code":"7.0",
    "gn:asciiname":"Petrovo",
    "gn:country_code":"KZ",
    "gn:dem":54,
    "gn:feature_class":"P",
    "gn:feature_code":"PPL",
    "gn:name":"Petrovo",
    "gn:population":0,
    "gn:timezone":"Asia/Oral",
    "iso:country":"KZ",
    "name:bos_x_preferred":[
        "Petrovo"
    ],
    "name:bul_x_preferred":[
        "\u041f\u0435\u0442\u0440\u043e\u0432\u043e"
    ],
    "name:ceb_x_preferred":[
        "Petrovo"
    ],
    "name:deu_x_preferred":[
        "Petrowo"
    ],
    "name:eng_x_preferred":[
        "Petrovo"
    ],
    "name:eus_x_preferred":[
        "Petrovo"
    ],
    "name:fra_x_preferred":[
        "Petrovo"
    ],
    "name:ita_x_preferred":[
        "Petrovo"
    ],
    "name:nld_x_preferred":[
        "Petrovo"
    ],
    "name:pol_x_preferred":[
        "Petrowo"
    ],
    "name:ron_x_preferred":[
        "Petrovo"
    ],
    "name:rus_x_preferred":[
        "\u041f\u0435\u0442\u0440\u043e\u0432\u043e"
    ],
    "name:srp_x_preferred":[
        "\u041f\u0435\u0442\u0440\u043e\u0432\u043e"
    ],
    "name:swe_x_preferred":[
        "Petrovo"
    ],
    "name:ukr_x_preferred":[
        "\u041f\u0435\u0442\u0440\u043e\u0432\u043e"
    ],
    "name:und_x_variant":[
        "Petrov"
    ],
    "wof:name":"Petrovo",
    "wof:placetype":"locality"
},
  "geometry": {"coordinates":[52.23855,51.54104],"type":"Point"}
}