{
  "type": "Feature",
  "properties": {
    "gn:admin1_code":"10.0",
    "gn:asciiname":"Kumaylykas",
    "gn:country_code":"KZ",
    "gn:dem":336,
    "gn:feature_class":"P",
    "gn:feature_code":"PPL",
    "gn:name":"Kumaylykas",
    "gn:population":0,
    "gn:timezone":"Asia/Almaty",
    "iso:country":"KZ",
    "name:kaz_x_preferred":[
        "Q\u016bmaylyqas"
    ],
    "name:kaz_x_variant":[
        "\u049a\u0443\u043c\u0430\u0439\u043b\u044b\u049b\u0430\u0441"
    ],
    "name:rus_x_preferred":[
        "\u041a\u0443\u043c\u0430\u0439\u043b\u044b\u043a\u0430\u0441"
    ],
    "wof:name":"Kumaylykas",
    "wof:placetype":"locality"
},
  "geometry": {"coordinates":[68.23047,43.53934],"type":"Point"}
}