{
  "type": "Feature",
  "properties": {
    "gn:admin1_code":"12.0",
    "gn:asciiname":"Zhamshi",
    "gn:country_code":"KZ",
    "gn:dem":720,
    "gn:feature_class":"P",
    "gn:feature_code":"PPL",
    "gn:name":"Zhamshi",
    "gn:population":0,
    "gn:timezone":"Asia/Almaty",
    "iso:country":"KZ",
    "name:und_x_variant":[
        "Jamchi",
        "Dzhamkhi",
        "Dzhamshi",
        "Dzhamchi",
        "Zhamshi"
    ],
    "wof:name":"Zhamshi",
    "wof:placetype":"locality"
},
  "geometry": {"coordinates":[74.58333,47.75],"type":"Point"}
}