{
  "type": "Feature",
  "properties": {
    "gn:admin1_code":"15.0",
    "gn:asciiname":"Nizhnebykovo",
    "gn:country_code":"KZ",
    "gn:dem":478,
    "gn:feature_class":"P",
    "gn:feature_code":"PPL",
    "gn:name":"Nizhnebykovo",
    "gn:population":0,
    "gn:timezone":"Asia/Almaty",
    "iso:country":"KZ",
    "name:rus_x_preferred":[
        "\u041d\u0438\u0436\u043d\u0435\u0431\u044b\u043a\u043e\u0432\u043e"
    ],
    "wof:name":"Nizhnebykovo",
    "wof:placetype":"locality"
},
  "geometry": {"coordinates":[84.55804999999999,49.7334],"type":"Point"}
}