{
  "type": "Feature",
  "properties": {
    "gn:admin1_code":"16.0",
    "gn:asciiname":"Yalty",
    "gn:country_code":"KZ",
    "gn:dem":263,
    "gn:feature_class":"P",
    "gn:feature_code":"PPL",
    "gn:name":"Yalty",
    "gn:population":0,
    "gn:timezone":"Asia/Almaty",
    "iso:country":"KZ",
    "name:eng_x_preferred":[
        "Yalty"
    ],
    "name:kaz_x_preferred":[
        "\u042f\u043b\u0442\u044b"
    ],
    "name:rus_x_preferred":[
        "\u042f\u043b\u0442\u044b"
    ],
    "name:und_x_variant":[
        "Aletinskiy",
        "Yaltinskiy"
    ],
    "wof:name":"Yalty",
    "wof:placetype":"locality"
},
  "geometry": {"coordinates":[67.18789,52.46377],"type":"Point"}
}