{
  "type": "Feature",
  "properties": {
    "gn:admin1_code":"0.0",
    "gn:asciiname":"Koskol'",
    "gn:country_code":"KZ",
    "gn:dem":180,
    "gn:feature_class":"P",
    "gn:feature_code":"PPL",
    "gn:name":"Koskol\u2019",
    "gn:population":0,
    "gn:timezone":"Asia/Qyzylorda",
    "iso:country":"KZ",
    "name:rus_x_preferred":[
        "Koskol\u2019"
    ],
    "wof:name":"Koskol'",
    "wof:placetype":"locality"
},
  "geometry": {"coordinates":[62.76667,53.91667],"type":"Point"}
}