{
  "type": "Feature",
  "properties": {
    "gn:admin1_code":"4.0",
    "gn:asciiname":"Poltavka",
    "gn:country_code":"KZ",
    "gn:dem":302,
    "gn:feature_class":"P",
    "gn:feature_code":"PPL",
    "gn:name":"Poltavka",
    "gn:population":0,
    "gn:timezone":"Asia/Aqtobe",
    "iso:country":"KZ",
    "name:ceb_x_preferred":[
        "Poltavka"
    ],
    "name:eng_x_preferred":[
        "Poltavka"
    ],
    "name:rus_x_preferred":[
        "\u041f\u043e\u043b\u0442\u0430\u0432\u043a\u0430"
    ],
    "wof:name":"Poltavka",
    "wof:placetype":"locality"
},
  "geometry": {"coordinates":[56.95316,51.0125],"type":"Point"}
}