{
  "type": "Feature",
  "properties": {
    "gn:admin1_code":"0.0",
    "gn:asciiname":"Tufanovskiy",
    "gn:country_code":"KZ",
    "gn:dem":255,
    "gn:feature_class":"P",
    "gn:feature_code":"PPL",
    "gn:name":"Tufanovskiy",
    "gn:population":0,
    "gn:timezone":"Asia/Qyzylorda",
    "iso:country":"KZ",
    "name:eng_x_preferred":[
        "Tufanovskiy"
    ],
    "name:rus_x_preferred":[
        "\u0422\u0443\u0444\u0430\u043d\u043e\u0432\u043a\u0430"
    ],
    "wof:name":"Tufanovskiy",
    "wof:placetype":"locality"
},
  "geometry": {"coordinates":[61.61877,51.61829],"type":"Point"}
}