{
  "type": "Feature",
  "properties": {
    "gn:admin1_code":"13.0",
    "gn:asciiname":"Karagayly",
    "gn:country_code":"KZ",
    "gn:dem":117,
    "gn:feature_class":"P",
    "gn:feature_code":"PPL",
    "gn:name":"Karagayly",
    "gn:population":0,
    "gn:timezone":"Asia/Qyzylorda",
    "iso:country":"KZ",
    "name:eng_x_preferred":[
        "Karagayly"
    ],
    "name:kaz_x_preferred":[
        "Qaraghayly"
    ],
    "name:kaz_x_variant":[
        "\u049a\u0430\u0440\u0430\u0493\u0430\u0439\u043b\u044b"
    ],
    "name:msa_x_preferred":[
        "Karagayly"
    ],
    "name:rus_x_preferred":[
        "\u041a\u0430\u0440\u0430\u0433\u0430\u043b\u044b"
    ],
    "name:rus_x_variant":[
        "\u041a\u0430\u0440\u0430\u0433\u0430\u0439\u043b\u044b"
    ],
    "name:und_x_variant":[
        "Karagaly",
        "Karagaylinskiy",
        "Karagun",
        "Karagayly"
    ],
    "wof:name":"Karagayly",
    "wof:placetype":"locality"
},
  "geometry": {"coordinates":[64.87572,53.36465],"type":"Point"}
}