{
  "type": "Feature",
  "properties": {
    "gn:admin1_code":"7.0",
    "gn:asciiname":"Zhaykbay",
    "gn:country_code":"KZ",
    "gn:dem":20,
    "gn:feature_class":"P",
    "gn:feature_code":"PPL",
    "gn:name":"Zhaykbay",
    "gn:population":0,
    "gn:timezone":"Asia/Oral",
    "iso:country":"KZ",
    "name:eng_x_preferred":[
        "Zhaykbay"
    ],
    "name:rus_x_preferred":[
        "\u0416\u0430\u0439\u043a\u0431\u0430\u0439"
    ],
    "name:und_x_variant":[
        "Zhaykpay",
        "Zhaykbay"
    ],
    "wof:name":"Zhaykbay",
    "wof:placetype":"locality"
},
  "geometry": {"coordinates":[49.39986,50.64981],"type":"Point"}
}