{
  "type": "Feature",
  "properties": {
    "gn:admin1_code":"13.0",
    "gn:asciiname":"Ivanovka",
    "gn:country_code":"KZ",
    "gn:dem":184,
    "gn:feature_class":"P",
    "gn:feature_code":"PPL",
    "gn:name":"Ivanovka",
    "gn:population":0,
    "gn:timezone":"Asia/Qyzylorda",
    "iso:country":"KZ",
    "name:eng_x_preferred":[
        "Ivanovka"
    ],
    "name:kaz_x_preferred":[
        "\u0418\u0432\u0430\u043d\u043e\u0432\u043a\u0430"
    ],
    "name:rus_x_preferred":[
        "\u0418\u0432\u0430\u043d\u043e\u0432\u043a\u0430"
    ],
    "wof:name":"Ivanovka",
    "wof:placetype":"locality"
},
  "geometry": {"coordinates":[64.18501999999999,53.68766],"type":"Point"}
}