{
  "type": "Feature",
  "properties": {
    "gn:admin1_code":"0.0",
    "gn:asciiname":"Komintern",
    "gn:country_code":"KZ",
    "gn:dem":602,
    "gn:feature_class":"P",
    "gn:feature_code":"PPL",
    "gn:name":"Komintern",
    "gn:population":0,
    "gn:timezone":"Asia/Almaty",
    "iso:country":"KZ",
    "wof:name":"Komintern",
    "wof:placetype":"locality"
},
  "geometry": {"coordinates":[81.93333,48.75],"type":"Point"}
}