{
  "type": "Feature",
  "properties": {
    "gn:admin1_code":"3.0",
    "gn:asciiname":"Mysok",
    "gn:country_code":"KZ",
    "gn:dem":443,
    "gn:feature_class":"P",
    "gn:feature_code":"PPL",
    "gn:name":"Mysok",
    "gn:population":0,
    "gn:timezone":"Asia/Almaty",
    "iso:country":"KZ",
    "name:eng_x_preferred":[
        "Mysok"
    ],
    "name:rus_x_preferred":[
        "\u041c\u044b\u0441\u043e\u043a"
    ],
    "wof:name":"Mysok",
    "wof:placetype":"locality"
},
  "geometry": {"coordinates":[68.7208,52.7409],"type":"Point"}
}