{
  "type": "Feature",
  "properties": {
    "gn:admin1_code":"15.0",
    "gn:asciiname":"Karashilik",
    "gn:country_code":"KZ",
    "gn:dem":819,
    "gn:feature_class":"P",
    "gn:feature_code":"PPL",
    "gn:name":"Karashilik",
    "gn:population":0,
    "gn:timezone":"Asia/Almaty",
    "iso:country":"KZ",
    "name:kaz_x_preferred":[
        "Qarashilik"
    ],
    "name:kaz_x_variant":[
        "\u049a\u0430\u0440\u0430\u0448\u0456\u043b\u0456\u043a"
    ],
    "name:rus_x_preferred":[
        "\u041a\u0430\u0440\u0430\u0448\u0438\u043b\u0438\u043a"
    ],
    "name:rus_x_variant":[
        "\u0410\u043a\u0431\u0443\u043b\u0430\u043a"
    ],
    "name:und_x_variant":[
        "Akbulak",
        "Karashilik"
    ],
    "wof:name":"Karashilik",
    "wof:placetype":"locality"
},
  "geometry": {"coordinates":[77.85743000000002,49.09617],"type":"Point"}
}