{
  "type": "Feature",
  "properties": {
    "gn:admin1_code":"13.0",
    "gn:asciiname":"Severnoe",
    "gn:country_code":"KZ",
    "gn:dem":176,
    "gn:feature_class":"P",
    "gn:feature_code":"PPL",
    "gn:name":"Severnoe",
    "gn:population":0,
    "gn:timezone":"Asia/Qyzylorda",
    "iso:country":"KZ",
    "name:kaz_x_preferred":[
        "Severnoe"
    ],
    "name:kaz_x_variant":[
        "\u0421\u0435\u0432\u0435\u0440\u043d\u043e\u0435"
    ],
    "name:und_x_variant":[
        "Severnoye"
    ],
    "wof:name":"Severnoe",
    "wof:placetype":"locality"
},
  "geometry": {"coordinates":[63.17204,53.89013000000001],"type":"Point"}
}