{
  "type": "Feature",
  "properties": {
    "gn:admin1_code":"3.0",
    "gn:asciiname":"Nikol'skoye",
    "gn:country_code":"KZ",
    "gn:dem":373,
    "gn:feature_class":"P",
    "gn:feature_code":"PPL",
    "gn:name":"Nikol\u2019skoye",
    "gn:population":0,
    "gn:timezone":"Asia/Almaty",
    "iso:country":"KZ",
    "name:eng_x_preferred":[
        "N\u012bkol'skoe"
    ],
    "name:kaz_x_preferred":[
        "\u041d\u0438\u043a\u043e\u043b\u044c\u0441\u043a\u043e\u0435"
    ],
    "name:rus_x_preferred":[
        "\u041d\u0438\u043a\u043e\u043b\u044c\u0441\u043a\u043e\u0435"
    ],
    "name:und_x_variant":[
        "Nikol\u2019skoye",
        "N\u012bkol\u2019skoe"
    ],
    "wof:name":"Nikol'skoye",
    "wof:placetype":"locality"
},
  "geometry": {"coordinates":[70.59124,52.24177],"type":"Point"}
}