{
  "type": "Feature",
  "properties": {
    "gn:admin1_code":"16.0",
    "gn:asciiname":"Yakor'",
    "gn:country_code":"KZ",
    "gn:dem":99,
    "gn:feature_class":"P",
    "gn:feature_code":"PPL",
    "gn:name":"Yakor\u2019",
    "gn:population":0,
    "gn:timezone":"Asia/Almaty",
    "iso:country":"KZ",
    "name:eng_x_preferred":[
        "Yakor'"
    ],
    "name:kaz_x_preferred":[
        "\u042f\u043a\u043e\u0440\u044c"
    ],
    "name:rus_x_preferred":[
        "\u042f\u043a\u043e\u0440\u044c"
    ],
    "name:und_x_variant":[
        "Yakor\u2019"
    ],
    "wof:name":"Yakor'",
    "wof:placetype":"locality"
},
  "geometry": {"coordinates":[69.03453,54.96124],"type":"Point"}
}