{
  "type": "Feature",
  "properties": {
    "gn:country":"KZ",
    "gn:fcode":"PPL",
    "gn:pop":2000,
    "iso:country":"KZ",
    "name:eng_x_historical":[
        "Novonikolayevka"
    ],
    "name:eng_x_preferred":[
        "Novonikolayevka"
    ],
    "name:rus_x_preferred":[
        "\u0416\u0430\u0431\u0430\u0433\u043b\u044b"
    ],
    "qs:name":"Zhabagly",
    "qs:photos_9r":0,
    "qs:photos_sr":0,
    "qs:pop_sr":"3",
    "wof:name":"Zhabagly",
    "wof:placetype":"locality",
    "wof:population":2000
},
  "geometry": {"coordinates":[70.47841,42.43781],"type":"Point"}
}