{
  "type": "Feature",
  "properties": {
    "gn:admin1_code":"16.0",
    "gn:asciiname":"Kur'ya",
    "gn:country_code":"KZ",
    "gn:dem":136,
    "gn:feature_class":"P",
    "gn:feature_code":"PPL",
    "gn:name":"Kur\u2019ya",
    "gn:population":0,
    "gn:timezone":"Asia/Almaty",
    "iso:country":"KZ",
    "name:rus_x_preferred":[
        "Kur\u2019ya"
    ],
    "name:rus_x_variant":[
        "\u041a\u0443\u0440\u044c\u044f"
    ],
    "wof:name":"Kur'ya",
    "wof:placetype":"locality"
},
  "geometry": {"coordinates":[69.98823,54.15723000000001],"type":"Point"}
}