{
  "type": "Feature",
  "properties": {
    "gn:admin1_code":"11.0",
    "gn:asciiname":"Tokbasy",
    "gn:country_code":"KZ",
    "gn:dem":349,
    "gn:feature_class":"P",
    "gn:feature_code":"PPL",
    "gn:name":"Tokbasy",
    "gn:population":0,
    "gn:timezone":"Asia/Almaty",
    "iso:country":"KZ",
    "name:rus_x_preferred":[
        "\u0422\u043e\u043a\u0431\u0430\u0441\u044b"
    ],
    "wof:name":"Tokbasy",
    "wof:placetype":"locality"
},
  "geometry": {"coordinates":[74.82881999999999,51.03867],"type":"Point"}
}