{
  "type": "Feature",
  "properties": {
    "gn:admin1_code":"7.0",
    "gn:asciiname":"Taldyapan",
    "gn:cc2":"KZ",
    "gn:country_code":"KZ",
    "gn:dem":3,
    "gn:feature_class":"P",
    "gn:feature_code":"PPL",
    "gn:name":"Taldyapan",
    "gn:population":0,
    "gn:timezone":"Asia/Oral",
    "iso:country":"KZ",
    "name:eng_x_preferred":[
        "Taldyapan"
    ],
    "name:rus_x_preferred":[
        "\u0422\u0430\u043b\u0434\u044b\u0430\u043f\u0430\u043d"
    ],
    "name:und_x_variant":[
        "Taldanak",
        "Taldapan",
        "Taldyapan"
    ],
    "wof:name":"Taldyapan",
    "wof:placetype":"locality"
},
  "geometry": {"coordinates":[50.22472,49.73639],"type":"Point"}
}