{
  "type": "Feature",
  "properties": {
    "gn:admin1_code":"11.0",
    "gn:asciiname":"Razvaliny Zhaylyauagash",
    "gn:country_code":"KZ",
    "gn:dem":107,
    "gn:feature_class":"P",
    "gn:feature_code":"PPL",
    "gn:name":"Razvaliny Zhaylyauagash",
    "gn:population":0,
    "gn:timezone":"Asia/Almaty",
    "iso:country":"KZ",
    "name:eng_x_preferred":[
        "Zhaylauagash"
    ],
    "name:rus_x_preferred":[
        "\u0416\u0430\u0439\u043b\u044f\u0443\u0430\u0433\u0430\u0448"
    ],
    "name:rus_x_variant":[
        "\u0420\u0430\u0437\u0432\u0430\u043b\u0438\u043d\u044b \u0416\u0430\u0439\u043b\u044f\u0443\u0430\u0433\u0430\u0448"
    ],
    "name:und_x_variant":[
        "Zhaylyauagach",
        "Razvaliny Zhaylyauagash"
    ],
    "wof:name":"Razvaliny Zhaylyauagash",
    "wof:placetype":"locality"
},
  "geometry": {"coordinates":[77.10138000000001,53.43202],"type":"Point"}
}