{
  "type": "Feature",
  "properties": {
    "gn:admin1_code":"0.0",
    "gn:asciiname":"Ushasha Vtoraya",
    "gn:country_code":"KZ",
    "gn:dem":236,
    "gn:feature_class":"P",
    "gn:feature_code":"PPL",
    "gn:name":"Ushasha Vtoraya",
    "gn:population":0,
    "gn:timezone":"Asia/Almaty",
    "iso:country":"KZ",
    "wof:name":"Ushasha Vtoraya",
    "wof:placetype":"locality"
},
  "geometry": {"coordinates":[79.40000000000001,50.38333],"type":"Point"}
}