{
  "type": "Feature",
  "properties": {
    "gn:admin1_code":"13.0",
    "gn:asciiname":"Amanqaraghay",
    "gn:country_code":"KZ",
    "gn:dem":189,
    "gn:feature_class":"P",
    "gn:feature_code":"PPL",
    "gn:name":"Amanqaraghay",
    "gn:population":0,
    "gn:timezone":"Asia/Qyzylorda",
    "iso:country":"KZ",
    "name:eng_x_preferred":[
        "Amankaragay"
    ],
    "name:kaz_x_preferred":[
        "Amanqaraghay"
    ],
    "name:rus_x_preferred":[
        "\u0410\u043c\u0430\u043d\u043a\u0430\u0440\u0430\u0433\u0430\u0439"
    ],
    "wof:name":"Amanqaraghay",
    "wof:placetype":"locality"
},
  "geometry": {"coordinates":[64.09059999999999,52.40491],"type":"Point"}
}