{
  "type": "Feature",
  "properties": {
    "gn:admin1_code":"3.0",
    "gn:asciiname":"Abylay",
    "gn:country_code":"KZ",
    "gn:dem":307,
    "gn:feature_class":"P",
    "gn:feature_code":"PPL",
    "gn:name":"Abylay",
    "gn:population":0,
    "gn:timezone":"Asia/Almaty",
    "iso:country":"KZ",
    "name:und_x_variant":[
        "Barzhakan",
        "Abylay"
    ],
    "wof:name":"Abylay",
    "wof:placetype":"locality"
},
  "geometry": {"coordinates":[69.37626,50.47117],"type":"Point"}
}