{
  "type": "Feature",
  "properties": {
    "gn:admin1_code":"10.0",
    "gn:asciiname":"Shakalak",
    "gn:country_code":"KZ",
    "gn:dem":810,
    "gn:feature_class":"P",
    "gn:feature_code":"PPL",
    "gn:name":"Shakalak",
    "gn:population":0,
    "gn:timezone":"Asia/Almaty",
    "iso:country":"KZ",
    "name:rus_x_preferred":[
        "\u0428\u0430\u043a\u0430\u043b\u0430\u043a"
    ],
    "name:rus_x_variant":[
        "\u0410\u043a\u0442\u0430\u0441\u0441\u0430\u0439"
    ],
    "name:und_x_variant":[
        "Aktassay"
    ],
    "wof:name":"Shakalak",
    "wof:placetype":"locality"
},
  "geometry": {"coordinates":[69.65364,42.09141],"type":"Point"}
}