{
  "type": "Feature",
  "properties": {
    "gn:admin1_code":"15.0",
    "gn:asciiname":"Engbek",
    "gn:country_code":"KZ",
    "gn:dem":599,
    "gn:feature_class":"P",
    "gn:feature_code":"PPL",
    "gn:name":"Engbek",
    "gn:population":0,
    "gn:timezone":"Asia/Almaty",
    "iso:country":"KZ",
    "name:kaz_x_preferred":[
        "Engbek"
    ],
    "name:kaz_x_variant":[
        "\u0415\u04a3\u0431\u0435\u043a"
    ],
    "name:rus_x_preferred":[
        "\u0415\u043d\u0431\u0435\u043a"
    ],
    "name:und_x_variant":[
        "Yenbek"
    ],
    "wof:name":"Engbek",
    "wof:placetype":"locality"
},
  "geometry": {"coordinates":[84.59772,48.42384000000001],"type":"Point"}
}