{
  "type": "Feature",
  "properties": {
    "iso:country":"KZ",
    "name:eng_x_preferred":[
        "Best\u00f6be"
    ],
    "name:eng_x_variant":[
        "Bestobe"
    ],
    "name:kaz_x_preferred":[
        "\u0411\u0435\u0441\u0442\u04e9\u0431\u0435"
    ],
    "name:kaz_x_variant":[
        "\u0411\u0435\u0441\u0442\u04e9\u0431\u0435 \u043a\u0435\u043d\u0442\u0456"
    ],
    "name:nld_x_preferred":[
        "Bestobe"
    ],
    "name:rus_x_preferred":[
        "\u0411\u0435\u0441\u0442\u043e\u0431\u0435"
    ],
    "name:spa_x_preferred":[
        "Bestobe"
    ],
    "name:ukr_x_preferred":[
        "\u0411\u0435\u0441\u0442\u043e\u0431\u0435"
    ],
    "name:und_x_variant":[
        "Bestyube"
    ],
    "ne:ADM0CAP":0.0,
    "ne:ADM0NAME":"Kazakhstan",
    "ne:ADM0_A3":"KAZ",
    "ne:ADM1NAME":"Aqmola",
    "ne:ADMIN1_COD":3,
    "ne:CAPALT":0,
    "ne:CHANGED":4,
    "ne:CHECKME":0,
    "ne:COMPARE":0,
    "ne:DIFFASCII":0,
    "ne:DIFFNOTE":"Population from GeoNames.",
    "ne:ELEVATION":0.0,
    "ne:FEATURECLA":"Populated place",
    "ne:FEATURE_CL":"P",
    "ne:FEATURE_CO":"PPL",
    "ne:GEONAMEID":1525376,
    "ne:GEONAMESNO":"Geonames ascii name + lat.d + long.d matching.",
    "ne:GN_ASCII":"Bestobe",
    "ne:GN_POP":7189,
    "ne:GTOPO30":174.0,
    "ne:ISO_A2":"KZ",
    "ne:LABELRANK":6,
    "ne:LATITUDE":52.499675,
    "ne:LONGITUDE":73.099713,
    "ne:LS_MATCH":0,
    "ne:LS_NAME":"Bestobe",
    "ne:MAX_AREAKM":0.0,
    "ne:MAX_AREAMI":0.0,
    "ne:MAX_BBXMAX":0.0,
    "ne:MAX_BBXMIN":0.0,
    "ne:MAX_BBYMAX":0.0,
    "ne:MAX_BBYMIN":0.0,
    "ne:MAX_NATSCA":0.0,
    "ne:MAX_PERKM":0.0,
    "ne:MAX_PERMI":0.0,
    "ne:MAX_POP10":0,
    "ne:MAX_POP20":0,
    "ne:MAX_POP300":0,
    "ne:MAX_POP310":0,
    "ne:MAX_POP50":0,
    "ne:MEAN_BBXC":0.0,
    "ne:MEAN_BBYC":0.0,
    "ne:MEGACITY":0,
    "ne:MIN_AREAKM":0.0,
    "ne:MIN_AREAMI":0.0,
    "ne:MIN_BBXMAX":0.0,
    "ne:MIN_BBXMIN":0.0,
    "ne:MIN_BBYMAX":0.0,
    "ne:MIN_BBYMIN":0.0,
    "ne:MIN_PERKM":0.0,
    "ne:MIN_PERMI":0.0,
    "ne:NAME":"Bestobe",
    "ne:NAMEASCII":"Bestobe",
    "ne:NAMEDIFF":0,
    "ne:NATSCALE":10,
    "ne:POP1950":0,
    "ne:POP1955":0,
    "ne:POP1960":0,
    "ne:POP1965":0,
    "ne:POP1970":0,
    "ne:POP1975":0,
    "ne:POP1980":0,
    "ne:POP1985":0,
    "ne:POP1990":0,
    "ne:POP1995":0,
    "ne:POP2000":0,
    "ne:POP2005":0,
    "ne:POP2010":0,
    "ne:POP2015":0,
    "ne:POP2020":0,
    "ne:POP2025":0,
    "ne:POP2050":0,
    "ne:POP_MAX":7189,
    "ne:POP_MIN":7189,
    "ne:POP_OTHER":0,
    "ne:RANK_MAX":5,
    "ne:RANK_MIN":5,
    "ne:SCALERANK":8,
    "ne:SOV0NAME":"Kazakhstan",
    "ne:SOV_A3":"KAZ",
    "ne:TIMEZONE":"Asia/Qyzylorda",
    "ne:UN_FID":0,
    "ne:UN_LAT":0.0,
    "ne:UN_LONG":0.0,
    "ne:WORLDCITY":0,
    "qs:gn_country":"KZ",
    "qs:gn_fcode":"PPL",
    "qs:gn_pop":7189,
    "qs:name":"Bestobe",
    "qs:name_adm0":"Kazakhstan",
    "qs:name_adm1":"Aqmola",
    "qs:photos":0,
    "qs:photos_1k":0,
    "qs:photos_9k":0,
    "qs:photos_9r":0,
    "qs:photos_all":0,
    "qs:photos_sr":0,
    "qs:placetype":"Town",
    "qs:pop_sr":"5",
    "qs:woe_adm0":23424871,
    "wof:name":"Bestobe",
    "wof:placetype":"locality",
    "wof:population":7189
},
  "geometry": {"coordinates":[73.09584,52.50171],"type":"Point"}
}