{
  "type": "Feature",
  "properties": {
    "gn:admin1_code":"3.0",
    "gn:asciiname":"Ladyzhenka",
    "gn:country_code":"KZ",
    "gn:dem":372,
    "gn:feature_class":"P",
    "gn:feature_code":"PPL",
    "gn:name":"Ladyzhenka",
    "gn:population":0,
    "gn:timezone":"Asia/Almaty",
    "iso:country":"KZ",
    "name:und_x_variant":[
        "Ladyzhenskoye",
        "Ladyzhenka"
    ],
    "wof:name":"Ladyzhenka",
    "wof:placetype":"locality"
},
  "geometry": {"coordinates":[68.69606,50.99266],"type":"Point"}
}