{
  "type": "Feature",
  "properties": {
    "gn:admin1_code":"6.0",
    "gn:asciiname":"Akkutyr",
    "gn:country_code":"KZ",
    "gn:dem":-27,
    "gn:feature_class":"P",
    "gn:feature_code":"PPL",
    "gn:name":"Akkutyr",
    "gn:population":0,
    "gn:timezone":"Asia/Atyrau",
    "iso:country":"KZ",
    "name:eng_x_preferred":[
        "Akkutyr"
    ],
    "name:rus_x_preferred":[
        "\u0410\u043a\u043a\u0443\u0442\u0443\u0440"
    ],
    "name:und_x_variant":[
        "Akkuter",
        "Aqqotyr"
    ],
    "wof:name":"Akkutyr",
    "wof:placetype":"locality"
},
  "geometry": {"coordinates":[51.33333,47.38333],"type":"Point"}
}