{
  "type": "Feature",
  "properties": {
    "gn:admin1_code":"12.0",
    "gn:asciiname":"Kalinin",
    "gn:country_code":"KZ",
    "gn:dem":818,
    "gn:feature_class":"P",
    "gn:feature_code":"PPL",
    "gn:name":"Kalinin",
    "gn:population":0,
    "gn:timezone":"Asia/Almaty",
    "iso:country":"KZ",
    "name:rus_x_preferred":[
        "\u041a\u0430\u043b\u0438\u043d\u0438\u043d"
    ],
    "wof:name":"Kalinin",
    "wof:placetype":"locality"
},
  "geometry": {"coordinates":[74.51071,48.31412],"type":"Point"}
}