{
  "type": "Feature",
  "properties": {
    "gn:admin1_code":"0.0",
    "gn:asciiname":"Odak",
    "gn:cc2":"KZ",
    "gn:country_code":"KZ",
    "gn:dem":434,
    "gn:feature_class":"P",
    "gn:feature_code":"PPL",
    "gn:name":"Odak",
    "gn:population":0,
    "gn:timezone":"Asia/Almaty",
    "iso:country":"KZ",
    "name:und_x_variant":[
        "Chubar-Uzek",
        "Odak"
    ],
    "wof:name":"Odak",
    "wof:placetype":"locality"
},
  "geometry": {"coordinates":[74.63333,51.23333],"type":"Point"}
}