{
  "type": "Feature",
  "properties": {
    "gn:admin1_code":"15.0",
    "gn:asciiname":"Lesnaya Pristin'",
    "gn:country_code":"KZ",
    "gn:dem":433,
    "gn:feature_class":"P",
    "gn:feature_code":"PPL",
    "gn:name":"Lesnaya Pristin\u2019",
    "gn:population":0,
    "gn:timezone":"Asia/Almaty",
    "iso:country":"KZ",
    "name:eng_x_preferred":[
        "Lesnaya Pristan'"
    ],
    "name:rus_x_preferred":[
        "\u041b\u0435\u0441\u043d\u0430\u044f-\u041f\u0440\u0438\u0441\u0442\u0430\u043d\u044c"
    ],
    "name:rus_x_variant":[
        "Lesnaya Pristin\u2019",
        "\u041b\u0435\u0441\u043d\u0430\u044f \u041f\u0440\u0438\u0441\u0442\u0438\u043d\u044c"
    ],
    "name:und_x_variant":[
        "Lesnaya Pristan\u2019"
    ],
    "wof:name":"Lesnaya Pristin'",
    "wof:placetype":"locality"
},
  "geometry": {"coordinates":[84.32281,49.81794],"type":"Point"}
}