{
  "type": "Feature",
  "properties": {
    "gn:admin1_code":"11.0",
    "gn:asciiname":"Komsomol'skiy",
    "gn:country_code":"KZ",
    "gn:dem":285,
    "gn:feature_class":"P",
    "gn:feature_code":"PPL",
    "gn:name":"Komsomol\u2019skiy",
    "gn:population":0,
    "gn:timezone":"Asia/Almaty",
    "iso:country":"KZ",
    "name:rus_x_preferred":[
        "Komsomol\u2019skiy"
    ],
    "wof:name":"Komsomol'skiy",
    "wof:placetype":"locality"
},
  "geometry": {"coordinates":[74.58604,51.44214],"type":"Point"}
}