{
  "type": "Feature",
  "properties": {
    "gn:admin1_code":"1.0",
    "gn:asciiname":"Kokkaynar",
    "gn:country_code":"KZ",
    "gn:dem":630,
    "gn:feature_class":"P",
    "gn:feature_code":"PPL",
    "gn:name":"Kokkaynar",
    "gn:population":0,
    "gn:timezone":"Asia/Almaty",
    "iso:country":"KZ",
    "name:rus_x_preferred":[
        "\u041a\u043e\u043a\u043a\u0430\u0439\u043d\u0430\u0440"
    ],
    "name:und_x_variant":[
        "Uchastok Nomer Dva Kokkaynar",
        "Kokkaynar"
    ],
    "wof:name":"Kokkaynar",
    "wof:placetype":"locality"
},
  "geometry": {"coordinates":[76.94419000000001,43.45386],"type":"Point"}
}