{
  "type": "Feature",
  "properties": {
    "gn:admin1_code":"1.0",
    "gn:asciiname":"Qanshenggel",
    "gn:country_code":"KZ",
    "gn:dem":414,
    "gn:feature_class":"P",
    "gn:feature_code":"PPL",
    "gn:name":"Qanshenggel",
    "gn:population":0,
    "gn:timezone":"Asia/Almaty",
    "iso:country":"KZ",
    "name:und_x_variant":[
        "Kanshengel\u2019",
        "Kolshyengyel",
        "Kol\u2019shengel\u2019",
        "Qanshenggel"
    ],
    "wof:name":"Qanshenggel",
    "wof:placetype":"locality"
},
  "geometry": {"coordinates":[75.54828000000001,44.32532],"type":"Point"}
}