{
  "type": "Feature",
  "properties": {
    "gn:admin1_code":"12.0",
    "gn:asciiname":"Geologicheskoye",
    "gn:country_code":"KZ",
    "gn:dem":467,
    "gn:feature_class":"P",
    "gn:feature_code":"PPL",
    "gn:name":"Geologicheskoye",
    "gn:population":0,
    "gn:timezone":"Asia/Almaty",
    "iso:country":"KZ",
    "name:rus_x_preferred":[
        "\u0413\u0435\u043e\u043b\u043e\u0433\u0438\u0447\u0435\u0441\u043a\u043e\u0435"
    ],
    "wof:name":"Geologicheskoye",
    "wof:placetype":"locality"
},
  "geometry": {"coordinates":[72.58629999999999,49.8507],"type":"Point"}
}