{
  "type": "Feature",
  "properties": {
    "gn:admin1_code":"0.0",
    "gn:asciiname":"Beloglinka",
    "gn:country_code":"KZ",
    "gn:dem":88,
    "gn:feature_class":"P",
    "gn:feature_code":"PPL",
    "gn:name":"Beloglinka",
    "gn:population":0,
    "gn:timezone":"Asia/Oral",
    "iso:country":"KZ",
    "name:eng_x_preferred":[
        "Beloglinka"
    ],
    "name:rus_x_preferred":[
        "\u0411\u0435\u043b\u043e\u0433\u043b\u0438\u043d\u043a\u0430"
    ],
    "wof:name":"Beloglinka",
    "wof:placetype":"locality"
},
  "geometry": {"coordinates":[50.81667,51.51667],"type":"Point"}
}