{
  "type": "Feature",
  "properties": {
    "gn:admin1_code":"0.0",
    "gn:asciiname":"Pervomayskiy",
    "gn:cc2":"KZ",
    "gn:country_code":"KZ",
    "gn:dem":11,
    "gn:feature_class":"P",
    "gn:feature_code":"PPL",
    "gn:name":"Pervomayskiy",
    "gn:population":0,
    "gn:timezone":"Asia/Oral",
    "iso:country":"KZ",
    "name:eng_x_preferred":[
        "Pervomayskiy"
    ],
    "name:rus_x_preferred":[
        "\u041f\u0435\u0440\u0432\u043e\u043c\u0430\u0439\u0441\u043a\u043e\u0435"
    ],
    "name:und_x_variant":[
        "Pervomayskoye"
    ],
    "wof:name":"Pervomayskiy",
    "wof:placetype":"locality"
},
  "geometry": {"coordinates":[50.61667,50.16667],"type":"Point"}
}