{
  "type": "Feature",
  "properties": {
    "gn:admin1_code":"0.0",
    "gn:asciiname":"Saymale",
    "gn:country_code":"KZ",
    "gn:dem":1219,
    "gn:feature_class":"P",
    "gn:feature_code":"PPL",
    "gn:name":"Saymale",
    "gn:population":0,
    "gn:timezone":"Asia/Almaty",
    "iso:country":"KZ",
    "wof:name":"Saymale",
    "wof:placetype":"locality"
},
  "geometry": {"coordinates":[80.08333,44.38333],"type":"Point"}
}