{
  "type": "Feature",
  "properties": {
    "gn:admin1_code":"13.0",
    "gn:asciiname":"Khar'kovskiy",
    "gn:country_code":"KZ",
    "gn:dem":114,
    "gn:feature_class":"P",
    "gn:feature_code":"PPL",
    "gn:name":"Khar\u2019kovskiy",
    "gn:population":0,
    "gn:timezone":"Asia/Qyzylorda",
    "iso:country":"KZ",
    "name:kaz_x_preferred":[
        "Khar\u2019kovsk\u012by"
    ],
    "name:kaz_x_variant":[
        "\u0425\u0430\u0440\u044c\u043a\u043e\u0432\u0441\u043a\u0438\u0439"
    ],
    "name:rus_x_preferred":[
        "Khar\u2019kovskiy"
    ],
    "wof:name":"Khar'kovskiy",
    "wof:placetype":"locality"
},
  "geometry": {"coordinates":[64.54420999999999,53.80392],"type":"Point"}
}