{
  "type": "Feature",
  "properties": {
    "gn:admin1_code":"11.0",
    "gn:asciiname":"Trofimovka",
    "gn:country_code":"KZ",
    "gn:dem":109,
    "gn:feature_class":"P",
    "gn:feature_code":"PPL",
    "gn:name":"Trofimovka",
    "gn:population":0,
    "gn:timezone":"Asia/Almaty",
    "iso:country":"KZ",
    "name:eng_x_preferred":[
        "Trof\u012bmovka"
    ],
    "name:kaz_x_preferred":[
        "\u0422\u0440\u043e\u0444\u0438\u043c\u043e\u0432\u043a\u0430"
    ],
    "name:rus_x_preferred":[
        "\u0422\u0440\u043e\u0444\u0438\u043c\u043e\u0432\u043a\u0430"
    ],
    "name:und_x_variant":[
        "Trofimovskaya",
        "Trofimovka"
    ],
    "wof:name":"Trofimovka",
    "wof:placetype":"locality"
},
  "geometry": {"coordinates":[76.94074000000001,53.51528],"type":"Point"}
}