{
  "type": "Feature",
  "properties": {
    "gn:admin1_code":"3.0",
    "gn:asciiname":"Kenes",
    "gn:country_code":"KZ",
    "gn:dem":401,
    "gn:feature_class":"P",
    "gn:feature_code":"PPL",
    "gn:name":"Kenes",
    "gn:population":0,
    "gn:timezone":"Asia/Almaty",
    "iso:country":"KZ",
    "name:eng_x_preferred":[
        "Kenes"
    ],
    "name:kaz_x_preferred":[
        "Kenges"
    ],
    "name:kaz_x_variant":[
        "\u041a\u0435\u04a3\u0435\u0441"
    ],
    "name:rus_x_preferred":[
        "\u041a\u0435\u043d\u0435\u0441"
    ],
    "wof:name":"Kenes",
    "wof:placetype":"locality"
},
  "geometry": {"coordinates":[71.2671,52.08274],"type":"Point"}
}