{
  "type": "Feature",
  "properties": {
    "gn:admin1_code":"6.0",
    "gn:asciiname":"Imeni Kuybysheva",
    "gn:country_code":"KZ",
    "gn:dem":-2,
    "gn:feature_class":"P",
    "gn:feature_code":"PPL",
    "gn:name":"Imeni Kuybysheva",
    "gn:population":0,
    "gn:timezone":"Asia/Atyrau",
    "iso:country":"KZ",
    "wof:name":"Imeni Kuybysheva",
    "wof:placetype":"locality"
},
  "geometry": {"coordinates":[47.28694,47.99944],"type":"Point"}
}