{
  "type": "Feature",
  "properties": {
    "gn:admin1_code":"10.0",
    "gn:asciiname":"Sel'khoztekhnika",
    "gn:country_code":"KZ",
    "gn:dem":268,
    "gn:feature_class":"P",
    "gn:feature_code":"PPL",
    "gn:name":"Sel\u2019khoztekhnika",
    "gn:population":0,
    "gn:timezone":"Asia/Almaty",
    "iso:country":"KZ",
    "name:rus_x_preferred":[
        "Sel\u2019khoztekhnika"
    ],
    "name:rus_x_variant":[
        "\u0421\u0435\u043b\u044c\u0445\u043e\u0437\u0442\u0435\u0445\u043d\u0438\u043a\u0430"
    ],
    "name:uzb_x_preferred":[
        "Mirzashol"
    ],
    "wof:name":"Sel'khoztekhnika",
    "wof:placetype":"locality"
},
  "geometry": {"coordinates":[68.29516,40.73811],"type":"Point"}
}