{
  "type": "Feature",
  "properties": {
    "gn:admin1_code":"0.0",
    "gn:asciiname":"Samay",
    "gn:country_code":"KZ",
    "gn:dem":225,
    "gn:feature_class":"P",
    "gn:feature_code":"PPL",
    "gn:name":"Samay",
    "gn:population":0,
    "gn:timezone":"Asia/Almaty",
    "iso:country":"KZ",
    "name:hin_x_preferred":[
        "\u0917\u093e\u092f\u0928 \u0938\u092e\u092f"
    ],
    "name:vie_x_preferred":[
        "Samay"
    ],
    "wof:name":"Samay",
    "wof:placetype":"locality"
},
  "geometry": {"coordinates":[79.11667,51.11667],"type":"Point"}
}