{
  "type": "Feature",
  "properties": {
    "gn:admin1_code":"10.0",
    "gn:asciiname":"Kyzyltu",
    "gn:country_code":"KZ",
    "gn:dem":591,
    "gn:feature_class":"P",
    "gn:feature_code":"PPL",
    "gn:name":"Kyzyltu",
    "gn:population":0,
    "gn:timezone":"Asia/Almaty",
    "iso:country":"KZ",
    "name:rus_x_preferred":[
        "\u041a\u044b\u0437\u044b\u043b\u0442\u0443"
    ],
    "name:und_x_variant":[
        "Kzyltu"
    ],
    "wof:name":"Kyzyltu",
    "wof:placetype":"locality"
},
  "geometry": {"coordinates":[69.39879999999999,41.79326],"type":"Point"}
}