{
  "type": "Feature",
  "properties": {
    "gn:admin1_code":"11.0",
    "gn:asciiname":"Shirokoye",
    "gn:country_code":"KZ",
    "gn:dem":134,
    "gn:feature_class":"P",
    "gn:feature_code":"PPL",
    "gn:name":"Shirokoye",
    "gn:population":0,
    "gn:timezone":"Asia/Almaty",
    "iso:country":"KZ",
    "name:kaz_x_preferred":[
        "Sh\u012brokoe"
    ],
    "name:kaz_x_variant":[
        "\u0428\u0438\u0440\u043e\u043a\u043e\u0435"
    ],
    "wof:name":"Shirokoye",
    "wof:placetype":"locality"
},
  "geometry": {"coordinates":[77.71923000000002,51.48461],"type":"Point"}
}