{
  "type": "Feature",
  "properties": {
    "gn:admin1_code":"16.0",
    "gn:asciiname":"Stepnoye",
    "gn:country_code":"KZ",
    "gn:dem":164,
    "gn:feature_class":"P",
    "gn:feature_code":"PPL",
    "gn:name":"Stepnoye",
    "gn:population":0,
    "gn:timezone":"Asia/Almaty",
    "iso:country":"KZ",
    "name:kaz_x_preferred":[
        "\u0421\u0442\u0435\u043f\u043d\u043e\u0435"
    ],
    "name:und_x_variant":[
        "Stepnoy",
        "Stepnoye",
        "Stepnoe"
    ],
    "wof:name":"Stepnoye",
    "wof:placetype":"locality"
},
  "geometry": {"coordinates":[66.8523,53.8968],"type":"Point"}
}