{
  "type": "Feature",
  "properties": {
    "gn:admin1_code":"15.0",
    "gn:asciiname":"Molochnotovarnaya Ferma Nomer Dva",
    "gn:country_code":"KZ",
    "gn:dem":358,
    "gn:feature_class":"P",
    "gn:feature_code":"PPL",
    "gn:name":"Molochnotovarnaya Ferma Nomer Dva",
    "gn:population":0,
    "gn:timezone":"Asia/Almaty",
    "iso:country":"KZ",
    "name:kaz_x_preferred":[
        "Krasnopart\u012bzanskoe"
    ],
    "name:kaz_x_variant":[
        "\u041a\u0440\u0430\u0441\u043d\u043e\u043f\u0430\u0440\u0442\u0438\u0437\u0430\u043d\u0441\u043a\u043e\u0435"
    ],
    "name:rus_x_preferred":[
        "\u041c\u043e\u043b\u043e\u0447\u043d\u043e\u0442\u043e\u0432\u0430\u0440\u043d\u0430\u044f \u0424\u0435\u0440\u043c\u0430 \u041d\u043e\u043c\u0435\u0440 \u0414\u0432\u0430"
    ],
    "wof:name":"Molochnotovarnaya Ferma Nomer Dva",
    "wof:placetype":"locality"
},
  "geometry": {"coordinates":[82.56461,50.15671],"type":"Point"}
}