{
  "type": "Feature",
  "properties": {
    "gn:admin1_code":"12.0",
    "gn:asciiname":"Tel'manskoye",
    "gn:country_code":"KZ",
    "gn:dem":530,
    "gn:feature_class":"P",
    "gn:feature_code":"PPL",
    "gn:name":"Tel\u2019manskoye",
    "gn:population":0,
    "gn:timezone":"Asia/Almaty",
    "iso:country":"KZ",
    "name:kaz_x_preferred":[
        "Tel\u2019manskoe"
    ],
    "name:kaz_x_variant":[
        "\u0422\u0435\u043b\u044c\u043c\u0430\u043d\u0441\u043a\u043e\u0435",
        "Tel\u2019man",
        "\u0422\u0435\u043b\u044c\u043c\u0430\u043d"
    ],
    "name:und_x_variant":[
        "Imeni Tel\u2019mana",
        "Tel\u2019manskoye"
    ],
    "wof:name":"Tel'manskoye",
    "wof:placetype":"locality"
},
  "geometry": {"coordinates":[73.29304,50.82912],"type":"Point"}
}