{
  "type": "Feature",
  "properties": {
    "gn:admin1_code":"10.0",
    "gn:asciiname":"Baltakol'",
    "gn:country_code":"KZ",
    "gn:dem":308,
    "gn:feature_class":"P",
    "gn:feature_code":"PPL",
    "gn:name":"Baltakol\u2019",
    "gn:population":0,
    "gn:timezone":"Asia/Almaty",
    "iso:country":"KZ",
    "name:rus_x_preferred":[
        "Baltakol\u2019"
    ],
    "name:rus_x_variant":[
        "\u0411\u0430\u043b\u0442\u0430\u043a\u043e\u043b\u044c"
    ],
    "wof:name":"Baltakol'",
    "wof:placetype":"locality"
},
  "geometry": {"coordinates":[68.77063000000001,41.36178],"type":"Point"}
}