{
  "type": "Feature",
  "properties": {
    "gn:admin1_code":"0.0",
    "gn:asciiname":"Zhapalak",
    "gn:country_code":"KZ",
    "gn:dem":357,
    "gn:feature_class":"P",
    "gn:feature_code":"PPL",
    "gn:name":"Zhapalak",
    "gn:population":0,
    "gn:timezone":"Asia/Almaty",
    "iso:country":"KZ",
    "wof:name":"Zhapalak",
    "wof:placetype":"locality"
},
  "geometry": {"coordinates":[70.09663,50.35752],"type":"Point"}
}