{
  "type": "Feature",
  "properties": {
    "gn:admin1_code":"12.0",
    "gn:asciiname":"Shildebay",
    "gn:country_code":"KZ",
    "gn:dem":562,
    "gn:feature_class":"P",
    "gn:feature_code":"PPL",
    "gn:name":"Shildebay",
    "gn:population":0,
    "gn:timezone":"Asia/Almaty",
    "iso:country":"KZ",
    "name:kaz_x_preferred":[
        "Shildebay"
    ],
    "name:kaz_x_variant":[
        "\u0428\u0456\u043b\u0434\u0435\u0431\u0430\u0439"
    ],
    "name:rus_x_preferred":[
        "Shel\u2019dybay"
    ],
    "name:rus_x_variant":[
        "\u0428\u0435\u043b\u044c\u0434\u044b\u0431\u0430\u0439"
    ],
    "wof:name":"Shildebay",
    "wof:placetype":"locality"
},
  "geometry": {"coordinates":[76.65059000000002,49.96675],"type":"Point"}
}