{
  "type": "Feature",
  "properties": {
    "gn:admin1_code":"0.0",
    "gn:asciiname":"Bel'-Agach",
    "gn:country_code":"KZ",
    "gn:dem":342,
    "gn:feature_class":"P",
    "gn:feature_code":"PPL",
    "gn:name":"Bel\u2019-Agach",
    "gn:population":0,
    "gn:timezone":"Asia/Almaty",
    "iso:country":"KZ",
    "wof:name":"Bel'-Agach",
    "wof:placetype":"locality"
},
  "geometry": {"coordinates":[67.26666999999999,51.96667],"type":"Point"}
}