{
  "type": "Feature",
  "properties": {
    "gn:admin1_code":"11.0",
    "gn:asciiname":"Saraypar",
    "gn:country_code":"KZ",
    "gn:dem":318,
    "gn:feature_class":"P",
    "gn:feature_code":"PPL",
    "gn:name":"Saraypar",
    "gn:population":0,
    "gn:timezone":"Asia/Almaty",
    "iso:country":"KZ",
    "name:kaz_x_preferred":[
        "Saraypar"
    ],
    "name:kaz_x_variant":[
        "\u0421\u0430\u0440\u0430\u0439\u043f\u0430\u0440"
    ],
    "wof:name":"Saraypar",
    "wof:placetype":"locality"
},
  "geometry": {"coordinates":[77.08308000000002,50.45002],"type":"Point"}
}