{
  "type": "Feature",
  "properties": {
    "gn:admin1_code":"17.0",
    "gn:asciiname":"Gagarino",
    "gn:country_code":"KZ",
    "gn:dem":992,
    "gn:feature_class":"P",
    "gn:feature_code":"PPL",
    "gn:name":"Gagarino",
    "gn:population":0,
    "gn:timezone":"Asia/Almaty",
    "iso:country":"KZ",
    "name:msa_x_preferred":[
        "Gagarino"
    ],
    "name:rus_x_preferred":[
        "\u0413\u0430\u0433\u0430\u0440\u0438\u043d\u043e"
    ],
    "wof:name":"Gagarino",
    "wof:placetype":"locality"
},
  "geometry": {"coordinates":[70.89359,42.65906],"type":"Point"}
}