{
  "type": "Feature",
  "properties": {
    "gn:admin1_code":"0.0",
    "gn:asciiname":"Klyun",
    "gn:cc2":"KZ",
    "gn:country_code":"KZ",
    "gn:dem":358,
    "gn:feature_class":"P",
    "gn:feature_code":"PPL",
    "gn:name":"Klyun",
    "gn:population":0,
    "gn:timezone":"Asia/Almaty",
    "iso:country":"KZ",
    "name:und_x_variant":[
        "Kdyun",
        "Klyun"
    ],
    "wof:name":"Klyun",
    "wof:placetype":"locality"
},
  "geometry": {"coordinates":[70.56667,50.36667],"type":"Point"}
}