{
  "type": "Feature",
  "properties": {
    "gn:admin1_code":"12.0",
    "gn:asciiname":"Zelyonaya Balka",
    "gn:country_code":"KZ",
    "gn:dem":571,
    "gn:feature_class":"P",
    "gn:feature_code":"PPL",
    "gn:name":"Zelyonaya Balka",
    "gn:population":0,
    "gn:timezone":"Asia/Almaty",
    "iso:country":"KZ",
    "name:kaz_x_preferred":[
        "Zelyonaya Balka"
    ],
    "name:kaz_x_variant":[
        "\u0417\u0435\u043b\u0451\u043d\u0430\u044f \u0411\u0430\u043b\u043a\u0430"
    ],
    "name:rus_x_preferred":[
        "Zel\u00ebnaya Balka"
    ],
    "wof:name":"Zelyonaya Balka",
    "wof:placetype":"locality"
},
  "geometry": {"coordinates":[73.26015,49.86161],"type":"Point"}
}