{
  "type": "Feature",
  "properties": {
    "gn:admin1_code":"6.0",
    "gn:asciiname":"Kiyak",
    "gn:country_code":"KZ",
    "gn:dem":-25,
    "gn:feature_class":"P",
    "gn:feature_code":"PPL",
    "gn:name":"Kiyak",
    "gn:population":0,
    "gn:timezone":"Asia/Atyrau",
    "iso:country":"KZ",
    "name:und_x_variant":[
        "Q\u012byaq Qysta\u016b"
    ],
    "wof:name":"Kiyak",
    "wof:placetype":"locality"
},
  "geometry": {"coordinates":[53.25,46.73333],"type":"Point"}
}