{
  "type": "Feature",
  "properties": {
    "gn:admin1_code":"13.0",
    "gn:asciiname":"Begezhan",
    "gn:country_code":"KZ",
    "gn:dem":210,
    "gn:feature_class":"P",
    "gn:feature_code":"PPL",
    "gn:name":"Begezhan",
    "gn:population":0,
    "gn:timezone":"Asia/Qyzylorda",
    "iso:country":"KZ",
    "name:kaz_x_preferred":[
        "Begezhan"
    ],
    "name:kaz_x_variant":[
        "\u0411\u0435\u0433\u0435\u0436\u0430\u043d"
    ],
    "wof:name":"Begezhan",
    "wof:placetype":"locality"
},
  "geometry": {"coordinates":[62.62888,53.10313000000001],"type":"Point"}
}