{
  "type": "Feature",
  "properties": {
    "gn:admin1_code":"9.0",
    "gn:asciiname":"Karakum",
    "gn:country_code":"KZ",
    "gn:dem":63,
    "gn:feature_class":"P",
    "gn:feature_code":"PPL",
    "gn:name":"Karakum",
    "gn:population":0,
    "gn:timezone":"Asia/Aqtau",
    "iso:country":"KZ",
    "name:aze_x_preferred":[
        "Qaraqum"
    ],
    "name:ceb_x_preferred":[
        "Karakum"
    ],
    "name:eng_x_preferred":[
        "Karakum"
    ],
    "name:est_x_preferred":[
        "Karakum"
    ],
    "name:fas_x_preferred":[
        "\u0642\u0631\u0647\u200c\u0642\u0648\u0645"
    ],
    "name:ita_x_preferred":[
        "Karakum"
    ],
    "name:kaz_x_preferred":[
        "Qaraqum"
    ],
    "name:kaz_x_variant":[
        "Qora-Qopsy",
        "\u049a\u0430\u0440\u0430\u049b\u04b1\u043c"
    ],
    "name:pol_x_preferred":[
        "Karakum"
    ],
    "name:rus_x_preferred":[
        "\u041a\u0430\u0440\u0430\u043a\u0443\u043c"
    ],
    "name:swe_x_preferred":[
        "Karakum"
    ],
    "name:ukr_x_preferred":[
        "\u041a\u0430\u0440\u0430\u043a\u0443\u043c"
    ],
    "wof:name":"Karakum",
    "wof:placetype":"locality"
},
  "geometry": {"coordinates":[50.61379,44.44732],"type":"Point"}
}