{
  "type": "Feature",
  "properties": {
    "gn:admin1_code":"0.0",
    "gn:asciiname":"Novotaubinka",
    "gn:country_code":"KZ",
    "gn:dem":299,
    "gn:feature_class":"P",
    "gn:feature_code":"PPL",
    "gn:name":"Novotaubinka",
    "gn:population":0,
    "gn:timezone":"Asia/Almaty",
    "iso:country":"KZ",
    "name:eng_x_preferred":[
        "Novotaubinka"
    ],
    "name:rus_x_preferred":[
        "\u041d\u043e\u0432\u043e\u0442\u0430\u0443\u0431\u0438\u043d\u043a\u0430"
    ],
    "name:und_x_variant":[
        "Taubinskoye",
        "Novaya Taubinka",
        "Taubinskaya",
        "Nova Taubinka"
    ],
    "wof:name":"Novotaubinka",
    "wof:placetype":"locality"
},
  "geometry": {"coordinates":[80.84573,49.81668],"type":"Point"}
}