{
  "type": "Feature",
  "properties": {
    "gn:admin1_code":"0.0",
    "gn:asciiname":"Qyzylegis",
    "gn:country_code":"KZ",
    "gn:dem":426,
    "gn:feature_class":"P",
    "gn:feature_code":"PPL",
    "gn:name":"Qyzylegis",
    "gn:population":0,
    "gn:timezone":"Asia/Almaty",
    "iso:country":"KZ",
    "name:eng_x_preferred":[
        "Qyzylegiz"
    ],
    "name:kaz_x_preferred":[
        "Qyzylegis"
    ],
    "name:kaz_x_variant":[
        "\u049a\u044b\u0437\u044b\u043b\u0435\u0433\u0456\u0441"
    ],
    "name:rus_x_preferred":[
        "\u041a\u044b\u0437\u044b\u043b\u0435\u0433\u0438\u0441"
    ],
    "name:und_x_variant":[
        "Kyzylegiz",
        "Kyzylegis"
    ],
    "wof:name":"Qyzylegis",
    "wof:placetype":"locality"
},
  "geometry": {"coordinates":[69.3691,52.77251999999999],"type":"Point"}
}