{
  "type": "Feature",
  "properties": {
    "gn:admin1_code":"10.0",
    "gn:asciiname":"Sorkol'",
    "gn:country_code":"KZ",
    "gn:dem":447,
    "gn:feature_class":"P",
    "gn:feature_code":"PPL",
    "gn:name":"Sorkol\u2019",
    "gn:population":0,
    "gn:timezone":"Asia/Almaty",
    "iso:country":"KZ",
    "name:rus_x_preferred":[
        "\u0421\u043e\u0440\u043a\u043e\u043b\u044c"
    ],
    "name:und_x_variant":[
        "Otdeleniye Nomer 2 Sovkhoza Imeni Engel\u2019sa",
        "Otdeleniye Nomer Dva Sovkhoza Imeni Engel\u2019sa",
        "Otdeleniye Nomer 2 (Dva) Sovkhoza Imeni Engel\u2019sa",
        "Sorkol\u2019"
    ],
    "wof:name":"Sorkol'",
    "wof:placetype":"locality"
},
  "geometry": {"coordinates":[68.90057,41.92044],"type":"Point"}
}