{
  "type": "Feature",
  "properties": {
    "gn:admin1_code":"15.0",
    "gn:asciiname":"Qaraqozha",
    "gn:country_code":"KZ",
    "gn:dem":489,
    "gn:feature_class":"P",
    "gn:feature_code":"PPL",
    "gn:name":"Qaraqozha",
    "gn:population":0,
    "gn:timezone":"Asia/Almaty",
    "iso:country":"KZ",
    "name:kaz_x_preferred":[
        "Qaraqozha"
    ],
    "name:kaz_x_variant":[
        "\u049a\u0430\u0440\u0430\u049b\u043e\u0436\u0430"
    ],
    "name:rus_x_preferred":[
        "\u0410\u043b\u0435\u043a\u0441\u0430\u043d\u0434\u0440\u0430 \u041d\u0435\u0432\u0441\u043a\u043e\u0433\u043e"
    ],
    "name:und_x_variant":[
        "Aleksandra Nevskogo",
        "Aleksandrovo-Nevskiy"
    ],
    "wof:name":"Qaraqozha",
    "wof:placetype":"locality"
},
  "geometry": {"coordinates":[81.7072,49.42512],"type":"Point"}
}