{
  "type": "Feature",
  "properties": {
    "gn:admin1_code":"0.0",
    "gn:asciiname":"Urdzhar",
    "gn:country_code":"KZ",
    "gn:dem":583,
    "gn:feature_class":"P",
    "gn:feature_code":"PPL",
    "gn:name":"Urdzhar",
    "gn:population":0,
    "gn:timezone":"Asia/Almaty",
    "iso:country":"KZ",
    "wof:name":"Urdzhar",
    "wof:placetype":"locality"
},
  "geometry": {"coordinates":[81.83333,47.06667],"type":"Point"}
}