{
  "type": "Feature",
  "properties": {
    "gn:admin1_code":"0.0",
    "gn:asciiname":"Karashigan",
    "gn:cc2":"KZ",
    "gn:country_code":"KZ",
    "gn:dem":341,
    "gn:feature_class":"P",
    "gn:feature_code":"PPL",
    "gn:name":"Karashigan",
    "gn:population":0,
    "gn:timezone":"Asia/Almaty",
    "iso:country":"KZ",
    "name:und_x_variant":[
        "Karachagan",
        "Kara-chegan",
        "Karashagan",
        "Karashigan"
    ],
    "wof:name":"Karashigan",
    "wof:placetype":"locality"
},
  "geometry": {"coordinates":[78.41667,46.28333],"type":"Point"}
}