{
  "type": "Feature",
  "properties": {
    "gn:admin1_code":"0.0",
    "gn:asciiname":"Sartyube",
    "gn:country_code":"KZ",
    "gn:dem":89,
    "gn:feature_class":"P",
    "gn:feature_code":"PPL",
    "gn:name":"Sartyube",
    "gn:population":0,
    "gn:timezone":"Asia/Almaty",
    "iso:country":"KZ",
    "wof:name":"Sartyube",
    "wof:placetype":"locality"
},
  "geometry": {"coordinates":[63.15,49.21667],"type":"Point"}
}