{
  "type": "Feature",
  "properties": {
    "gn:admin1_code":"14.0",
    "gn:asciiname":"Kurman",
    "gn:country_code":"KZ",
    "gn:dem":174,
    "gn:feature_class":"P",
    "gn:feature_code":"PPL",
    "gn:name":"Kurman",
    "gn:population":0,
    "gn:timezone":"Asia/Qyzylorda",
    "iso:country":"KZ",
    "wof:name":"Kurman",
    "wof:placetype":"locality"
},
  "geometry": {"coordinates":[67.53333000000001,43.53333],"type":"Point"}
}