{
  "type": "Feature",
  "properties": {
    "gn:admin1_code":"16.0",
    "gn:asciiname":"Karatal",
    "gn:country_code":"KZ",
    "gn:dem":81,
    "gn:feature_class":"P",
    "gn:feature_code":"PPL",
    "gn:name":"Karatal",
    "gn:population":0,
    "gn:timezone":"Asia/Almaty",
    "iso:country":"KZ",
    "name:kaz_x_preferred":[
        "Qaratal"
    ],
    "name:kaz_x_variant":[
        "\u049a\u0430\u0440\u0430\u0442\u0430\u043b"
    ],
    "name:rus_x_preferred":[
        "\u041a\u0430\u0440\u0430\u0442\u0430\u043b"
    ],
    "wof:name":"Karatal",
    "wof:placetype":"locality"
},
  "geometry": {"coordinates":[73.70522,52.74243000000001],"type":"Point"}
}