{
  "type": "Feature",
  "properties": {
    "gn:admin1_code":"12.0",
    "gn:asciiname":"Kos-Aral",
    "gn:country_code":"KZ",
    "gn:dem":379,
    "gn:feature_class":"P",
    "gn:feature_code":"PPL",
    "gn:name":"Kos-Aral",
    "gn:population":0,
    "gn:timezone":"Asia/Almaty",
    "iso:country":"KZ",
    "wof:name":"Kos-Aral",
    "wof:placetype":"locality"
},
  "geometry": {"coordinates":[70.84999999999999,49.88333],"type":"Point"}
}