{
  "type": "Feature",
  "properties": {
    "gn:admin1_code":"1.0",
    "gn:asciiname":"Kulan-Tobe",
    "gn:country_code":"KZ",
    "gn:dem":567,
    "gn:feature_class":"P",
    "gn:feature_code":"PPL",
    "gn:name":"Kulan-Tobe",
    "gn:population":0,
    "gn:timezone":"Asia/Almaty",
    "iso:country":"KZ",
    "name:kaz_x_preferred":[
        "Qulant\u00f6be"
    ],
    "name:kaz_x_variant":[
        "\u049a\u04b1\u043b\u0430\u043d\u0442\u04e9\u0431\u0435"
    ],
    "name:rus_x_preferred":[
        "\u041a\u0443\u043b\u0430\u043d-\u0422\u043e\u0431\u0435"
    ],
    "wof:name":"Kulan-Tobe",
    "wof:placetype":"locality"
},
  "geometry": {"coordinates":[77.26940999999999,43.94741],"type":"Point"}
}