{
  "type": "Feature",
  "properties": {
    "gn:admin1_code":"3.0",
    "gn:asciiname":"Shoshqaly",
    "gn:country_code":"KZ",
    "gn:dem":318,
    "gn:feature_class":"P",
    "gn:feature_code":"PPL",
    "gn:name":"Shoshqaly",
    "gn:population":0,
    "gn:timezone":"Asia/Almaty",
    "iso:country":"KZ",
    "name:kaz_x_preferred":[
        "Shoshqaly"
    ],
    "name:kaz_x_variant":[
        "\u0428\u043e\u0448\u049b\u0430\u043b\u044b"
    ],
    "name:rus_x_preferred":[
        "\u0428\u043e\u0448\u043a\u0430\u043b\u044b"
    ],
    "name:und_x_variant":[
        "Shoshkaly"
    ],
    "wof:name":"Shoshqaly",
    "wof:placetype":"locality"
},
  "geometry": {"coordinates":[70.88122,52.4013],"type":"Point"}
}