{
  "type": "Feature",
  "properties": {
    "gn:admin1_code":"7.0",
    "gn:asciiname":"Besoba",
    "gn:country_code":"KZ",
    "gn:dem":40,
    "gn:feature_class":"P",
    "gn:feature_code":"PPL",
    "gn:name":"Besoba",
    "gn:population":0,
    "gn:timezone":"Asia/Oral",
    "iso:country":"KZ",
    "name:eng_x_preferred":[
        "Besoba"
    ],
    "name:rus_x_preferred":[
        "\u0411\u0435\u0441\u043e\u0431\u0430"
    ],
    "wof:name":"Besoba",
    "wof:placetype":"locality"
},
  "geometry": {"coordinates":[53.395,49.73868],"type":"Point"}
}