{
  "type": "Feature",
  "properties": {
    "gn:admin1_code":"12.0",
    "gn:asciiname":"Taskora",
    "gn:country_code":"KZ",
    "gn:dem":695,
    "gn:feature_class":"P",
    "gn:feature_code":"PPL",
    "gn:name":"Taskora",
    "gn:population":0,
    "gn:timezone":"Asia/Almaty",
    "iso:country":"KZ",
    "name:rus_x_preferred":[
        "\u0422\u0430\u0441\u043a\u043e\u0440\u0430"
    ],
    "wof:name":"Taskora",
    "wof:placetype":"locality"
},
  "geometry": {"coordinates":[74.83856,49.5189],"type":"Point"}
}