{
  "type": "Feature",
  "properties": {
    "gn:admin1_code":"3.0",
    "gn:asciiname":"Maltabar",
    "gn:country_code":"KZ",
    "gn:dem":377,
    "gn:feature_class":"P",
    "gn:feature_code":"PPL",
    "gn:name":"Maltabar",
    "gn:population":0,
    "gn:timezone":"Asia/Almaty",
    "iso:country":"KZ",
    "name:kaz_x_preferred":[
        "Maltabar"
    ],
    "name:kaz_x_variant":[
        "\u041c\u0430\u043b\u0442\u0430\u0431\u0430\u0440"
    ],
    "wof:name":"Maltabar",
    "wof:placetype":"locality"
},
  "geometry": {"coordinates":[73.13795999999998,51.65671],"type":"Point"}
}