{
  "type": "Feature",
  "properties": {
    "gn:admin1_code":"12.0",
    "gn:asciiname":"Karashoky",
    "gn:country_code":"KZ",
    "gn:dem":952,
    "gn:feature_class":"P",
    "gn:feature_code":"PPL",
    "gn:name":"Karashoky",
    "gn:population":0,
    "gn:timezone":"Asia/Almaty",
    "iso:country":"KZ",
    "name:rus_x_preferred":[
        "\u041a\u0430\u0440\u0430\u0448\u043e\u043a\u044b"
    ],
    "wof:name":"Karashoky",
    "wof:placetype":"locality"
},
  "geometry": {"coordinates":[75.65939,48.88736],"type":"Point"}
}