{
  "type": "Feature",
  "properties": {
    "gn:admin1_code":"3.0",
    "gn:asciiname":"Kenotkel'",
    "gn:country_code":"KZ",
    "gn:dem":284,
    "gn:feature_class":"P",
    "gn:feature_code":"PPL",
    "gn:name":"Kenotkel\u2019",
    "gn:population":0,
    "gn:timezone":"Asia/Almaty",
    "iso:country":"KZ",
    "name:eng_x_preferred":[
        "Kenotkel'"
    ],
    "name:kaz_x_preferred":[
        "Keng\u00f6tkel"
    ],
    "name:kaz_x_variant":[
        "\u041a\u0435\u04a3\u04e9\u0442\u043a\u0435\u043b"
    ],
    "name:rus_x_preferred":[
        "\u041a\u0435\u043d\u043e\u0442\u043a\u0435\u043b\u044c"
    ],
    "name:und_x_variant":[
        "Kenotkel\u2019"
    ],
    "wof:name":"Kenotkel'",
    "wof:placetype":"locality"
},
  "geometry": {"coordinates":[68.99802,53.05971],"type":"Point"}
}