{
  "type": "Feature",
  "properties": {
    "gn:admin1_code":"15.0",
    "gn:asciiname":"Severnyy Bukombay",
    "gn:country_code":"KZ",
    "gn:dem":845,
    "gn:feature_class":"P",
    "gn:feature_code":"PPL",
    "gn:name":"Severnyy Bukombay",
    "gn:population":0,
    "gn:timezone":"Asia/Almaty",
    "iso:country":"KZ",
    "name:kaz_x_preferred":[
        "Teriskey B\u00f6kenbay"
    ],
    "name:kaz_x_variant":[
        "\u0422\u0435\u0440\u0456\u0441\u043a\u0435\u0439 \u0411\u04e9\u043a\u0435\u043d\u0431\u0430\u0439"
    ],
    "name:rus_x_preferred":[
        "\u0421\u0435\u0432\u0435\u0440\u043d\u044b\u0439 \u0411\u0443\u043a\u043e\u043c\u0431\u0430\u0439"
    ],
    "wof:name":"Severnyy Bukombay",
    "wof:placetype":"locality"
},
  "geometry": {"coordinates":[84.73245,48.33116],"type":"Point"}
}