{
  "type": "Feature",
  "properties": {
    "gn:admin1_code":"0.0",
    "gn:asciiname":"Batak",
    "gn:country_code":"KZ",
    "gn:dem":33,
    "gn:feature_class":"P",
    "gn:feature_code":"PPL",
    "gn:name":"Batak",
    "gn:population":0,
    "gn:timezone":"Asia/Oral",
    "iso:country":"KZ",
    "wof:name":"Batak",
    "wof:placetype":"locality"
},
  "geometry": {"coordinates":[51.85,50.25],"type":"Point"}
}