{
  "type": "Feature",
  "properties": {
    "gn:admin1_code":"0.0",
    "gn:asciiname":"Batak",
    "gn:country_code":"KZ",
    "gn:dem":33,
    "gn:feature_class":"P",
    "gn:feature_code":"PPL",
    "gn:name":"Batak",
    "gn:population":0,
    "gn:timezone":"Asia/Oral",
    "iso:country":"KZ",
    "name:ara_x_preferred":[
        "\u0628\u0627\u062a\u0627\u0642\u064a\u0648\u0646"
    ],
    "name:aze_x_preferred":[
        "Bataklar"
    ],
    "name:bul_x_preferred":[
        "\u0411\u0430\u0442\u0430\u043a\u0438"
    ],
    "name:cym_x_preferred":[
        "Batak"
    ],
    "name:deu_x_preferred":[
        "Batak"
    ],
    "name:epo_x_preferred":[
        "Batakoj"
    ],
    "name:eus_x_preferred":[
        "Batak herria"
    ],
    "name:fra_x_preferred":[
        "Batak"
    ],
    "name:hif_x_preferred":[
        "Batak"
    ],
    "name:hin_x_preferred":[
        "\u092c\u0924\u0915 \u0932\u094b\u0917"
    ],
    "name:ind_x_preferred":[
        "Suku Batak"
    ],
    "name:ita_x_preferred":[
        "Batak"
    ],
    "name:jav_x_preferred":[
        "Wong Batak"
    ],
    "name:jpn_x_preferred":[
        "\u30d0\u30bf\u30c3\u30af\u4eba"
    ],
    "name:kaz_x_preferred":[
        "\u0411\u0430\u0442\u0430\u049b\u0442\u0430\u0440"
    ],
    "name:kor_x_preferred":[
        "\ubc14\ud0c1\uc871"
    ],
    "name:lit_x_preferred":[
        "Batakai"
    ],
    "name:mal_x_preferred":[
        "\u0d2c\u0d1f\u0d3e\u0d15\u0d4d"
    ],
    "name:min_x_preferred":[
        "Urang Batak"
    ],
    "name:msa_x_preferred":[
        "Suku Batak"
    ],
    "name:nld_x_preferred":[
        "Batak"
    ],
    "name:pol_x_preferred":[
        "Batakowie"
    ],
    "name:por_x_preferred":[
        "Batak"
    ],
    "name:rus_x_preferred":[
        "\u0411\u0430\u0442\u0430\u043a\u0438"
    ],
    "name:spa_x_preferred":[
        "Batak"
    ],
    "name:sun_x_preferred":[
        "Batak"
    ],
    "name:swe_x_preferred":[
        "Bataker"
    ],
    "name:tgk_x_preferred":[
        "\u0411\u0430\u0442\u0430\u043a\u04b3\u043e"
    ],
    "name:ukr_x_preferred":[
        "\u0411\u0430\u0442\u0430\u043a\u0438"
    ],
    "name:uzb_x_preferred":[
        "Bataklar"
    ],
    "name:vie_x_preferred":[
        "Ng\u01b0\u1eddi Batak"
    ],
    "name:zho_x_preferred":[
        "\u5df4\u5854\u514b\u4eba"
    ],
    "wof:name":"Batak",
    "wof:placetype":"locality"
},
  "geometry": {"coordinates":[51.85,50.25],"type":"Point"}
}