{
  "type": "Feature",
  "properties": {
    "gn:admin1_code":"3.0",
    "gn:asciiname":"Novoromenka",
    "gn:country_code":"KZ",
    "gn:dem":307,
    "gn:feature_class":"P",
    "gn:feature_code":"PPL",
    "gn:name":"Novoromenka",
    "gn:population":0,
    "gn:timezone":"Asia/Almaty",
    "iso:country":"KZ",
    "wof:name":"Novoromenka",
    "wof:placetype":"locality"
},
  "geometry": {"coordinates":[70.19072,51.68726],"type":"Point"}
}