{
  "type": "Feature",
  "properties": {
    "gn:admin1_code":"15.0",
    "gn:asciiname":"Orgymbay",
    "gn:country_code":"KZ",
    "gn:dem":855,
    "gn:feature_class":"P",
    "gn:feature_code":"PPL",
    "gn:name":"Orgymbay",
    "gn:population":0,
    "gn:timezone":"Asia/Almaty",
    "iso:country":"KZ",
    "name:rus_x_preferred":[
        "\u041e\u0440\u0433\u044b\u043c\u0431\u0430\u0439"
    ],
    "wof:name":"Orgymbay",
    "wof:placetype":"locality"
},
  "geometry": {"coordinates":[84.96074,48.30623],"type":"Point"}
}