{
  "type": "Feature",
  "properties": {
    "gn:admin1_code":"0.0",
    "gn:asciiname":"Novaya Belokamenka",
    "gn:cc2":"KZ",
    "gn:country_code":"KZ",
    "gn:dem":171,
    "gn:feature_class":"P",
    "gn:feature_code":"PPL",
    "gn:name":"Novaya Belokamenka",
    "gn:population":0,
    "gn:timezone":"Asia/Almaty",
    "iso:country":"KZ",
    "name:eng_x_preferred":[
        "Novaya Belokamenka"
    ],
    "name:rus_x_preferred":[
        "\u0411\u0435\u043b\u043e\u043a\u0430\u043c\u0435\u043d\u043a\u0430"
    ],
    "name:und_x_variant":[
        "Belokamenka",
        "Novaya Belokamenka"
    ],
    "wof:name":"Novaya Belokamenka",
    "wof:placetype":"locality"
},
  "geometry": {"coordinates":[79.51666999999998,50.58333],"type":"Point"}
}