{
  "type": "Feature",
  "properties": {
    "gn:admin1_code":"13.0",
    "gn:asciiname":"Verenka",
    "gn:country_code":"KZ",
    "gn:dem":157,
    "gn:feature_class":"P",
    "gn:feature_code":"PPL",
    "gn:name":"Verenka",
    "gn:population":0,
    "gn:timezone":"Asia/Qyzylorda",
    "iso:country":"KZ",
    "name:eng_x_preferred":[
        "Verinskiy"
    ],
    "name:kaz_x_preferred":[
        "Verenka"
    ],
    "name:kaz_x_variant":[
        "\u0412\u0435\u0440\u0435\u043d\u043a\u0430"
    ],
    "name:rus_x_preferred":[
        "\u0412\u0435\u0440\u0438\u043d\u043a\u0430"
    ],
    "wof:name":"Verenka",
    "wof:placetype":"locality"
},
  "geometry": {"coordinates":[62.17228000000001,53.79396],"type":"Point"}
}