{
  "type": "Feature",
  "properties": {
    "gn:admin1_code":"3.0",
    "gn:asciiname":"Shkola-Internat",
    "gn:country_code":"KZ",
    "gn:dem":369,
    "gn:feature_class":"P",
    "gn:feature_code":"PPL",
    "gn:name":"Shkola-Internat",
    "gn:population":0,
    "gn:timezone":"Asia/Almaty",
    "iso:country":"KZ",
    "name:rus_x_preferred":[
        "\u0428\u043a\u043e\u043b\u0430-\u0418\u043d\u0442\u0435\u0440\u043d\u0430\u0442"
    ],
    "wof:name":"Shkola-Internat",
    "wof:placetype":"locality"
},
  "geometry": {"coordinates":[68.84028000000001,52.58755],"type":"Point"}
}