{
  "type": "Feature",
  "properties": {
    "gn:admin1_code":"11.0",
    "gn:asciiname":"Yelenovka",
    "gn:country_code":"KZ",
    "gn:dem":142,
    "gn:feature_class":"P",
    "gn:feature_code":"PPL",
    "gn:name":"Yel\u00ebnovka",
    "gn:population":0,
    "gn:timezone":"Asia/Almaty",
    "iso:country":"KZ",
    "name:aze_x_preferred":[
        "Yelenovka"
    ],
    "name:und_x_variant":[
        "Yelenovskoye",
        "Yel\u00ebnovka"
    ],
    "wof:name":"Yelenovka",
    "wof:placetype":"locality"
},
  "geometry": {"coordinates":[78.06667,52.23333],"type":"Point"}
}