{
  "type": "Feature",
  "properties": {
    "gn:admin1_code":"16.0",
    "gn:asciiname":"Kuzeusay",
    "gn:country_code":"KZ",
    "gn:dem":34,
    "gn:feature_class":"P",
    "gn:feature_code":"PPL",
    "gn:name":"Kuzeusay",
    "gn:population":0,
    "gn:timezone":"Asia/Almaty",
    "iso:country":"KZ",
    "wof:name":"Kuzeusay",
    "wof:placetype":"locality"
},
  "geometry": {"coordinates":[73.05,53.91667],"type":"Point"}
}