{
  "type": "Feature",
  "properties": {
    "iso:country":"KZ",
    "name:eng_x_preferred":[
        "Dossor"
    ],
    "name:kaz_x_preferred":[
        "\u0414\u043e\u0441\u0441\u043e\u0440"
    ],
    "name:msa_x_preferred":[
        "Dossor"
    ],
    "name:pol_x_preferred":[
        "Dossor"
    ],
    "name:rus_x_preferred":[
        "\u0414\u043e\u0441\u0441\u043e\u0440"
    ],
    "name:ukr_x_preferred":[
        "\u0414\u043e\u0441\u0441\u043e\u0440"
    ],
    "name:unk_x_variant":[
        "Bos-Sor"
    ],
    "qs:gn_country":"KZ",
    "qs:gn_fcode":"PPL",
    "qs:gn_pop":9526,
    "qs:name":"Dossor",
    "qs:name_adm0":"Kazakhstan",
    "qs:name_adm1":"Atyrau",
    "qs:photos":0,
    "qs:photos_1k":0,
    "qs:photos_9k":0,
    "qs:photos_9r":0,
    "qs:photos_all":0,
    "qs:photos_sr":0,
    "qs:placetype":"Town",
    "qs:pop_sr":"5",
    "qs:woe_adm0":23424871,
    "wd:wordcount":74,
    "wof:name":"Dossor",
    "wof:placetype":"locality",
    "wof:population":9526
},
  "geometry": {"coordinates":[52.98111,47.52722],"type":"Point"}
}