{
  "type": "Feature",
  "properties": {
    "gn:admin1_code":"12.0",
    "gn:asciiname":"Leninskiy",
    "gn:country_code":"KZ",
    "gn:dem":221,
    "gn:feature_class":"P",
    "gn:feature_code":"PPL",
    "gn:name":"Leninskiy",
    "gn:population":0,
    "gn:timezone":"Asia/Qyzylorda",
    "iso:country":"KZ",
    "name:kaz_x_preferred":[
        "Len\u012bnsk\u012by"
    ],
    "name:kaz_x_variant":[
        "\u041b\u0435\u043d\u0438\u043d\u0441\u043a\u0438\u0439"
    ],
    "name:rus_x_preferred":[
        "\u041a\u0430\u0440\u043f\u044b\u0434\u0430\u043a"
    ],
    "name:und_x_variant":[
        "Karpydak"
    ],
    "wof:name":"Leninskiy",
    "wof:placetype":"locality"
},
  "geometry": {"coordinates":[61.89046,53.18255],"type":"Point"}
}