{
  "type": "Feature",
  "properties": {
    "gn:admin1_code":"0.0",
    "gn:asciiname":"Osinovka",
    "gn:country_code":"KZ",
    "gn:dem":711,
    "gn:feature_class":"P",
    "gn:feature_code":"PPL",
    "gn:name":"Osinovka",
    "gn:population":0,
    "gn:timezone":"Asia/Almaty",
    "iso:country":"KZ",
    "name:ceb_x_preferred":[
        "Osinovka"
    ],
    "name:lav_x_preferred":[
        "Osinovka"
    ],
    "name:swe_x_preferred":[
        "Osinovka"
    ],
    "name:und_x_variant":[
        "Osinovskoye"
    ],
    "wof:name":"Osinovka",
    "wof:placetype":"locality"
},
  "geometry": {"coordinates":[80.70912,45.8258],"type":"Point"}
}