{
  "type": "Feature",
  "properties": {
    "gn:admin1_code":"14.0",
    "gn:asciiname":"Koktobe",
    "gn:country_code":"KZ",
    "gn:dem":121,
    "gn:feature_class":"P",
    "gn:feature_code":"PPL",
    "gn:name":"Koktobe",
    "gn:population":0,
    "gn:timezone":"Asia/Qyzylorda",
    "iso:country":"KZ",
    "wof:name":"Koktobe",
    "wof:placetype":"locality"
},
  "geometry": {"coordinates":[65.25,44.85],"type":"Point"}
}