{
  "type": "Feature",
  "properties": {
    "gn:admin1_code":"1.0",
    "gn:asciiname":"Kokterek",
    "gn:country_code":"KZ",
    "gn:dem":605,
    "gn:feature_class":"P",
    "gn:feature_code":"PPL",
    "gn:name":"Kokterek",
    "gn:population":0,
    "gn:timezone":"Asia/Almaty",
    "iso:country":"KZ",
    "name:rus_x_preferred":[
        "\u041a\u043e\u043a\u0442\u0435\u0440\u0435\u043a"
    ],
    "wof:name":"Kokterek",
    "wof:placetype":"locality"
},
  "geometry": {"coordinates":[77.01000999999999,43.49383],"type":"Point"}
}