{
  "type": "Feature",
  "properties": {
    "gn:asciiname":"Nsan",
    "gn:country_code":"KZ",
    "gn:dem":65,
    "gn:feature_class":"P",
    "gn:feature_code":"PPL",
    "gn:name":"Nsan",
    "gn:population":0,
    "gn:timezone":"Asia/Qyzylorda",
    "iso:country":"KZ",
    "name:rus_x_preferred":[
        "\u041d\u0441\u0430\u043d"
    ],
    "wof:name":"Nsan",
    "wof:placetype":"locality"
},
  "geometry": {"coordinates":[62.08864000000001,43.51152],"type":"Point"}
}