{
  "type": "Feature",
  "properties": {
    "gn:admin1_code":"7.0",
    "gn:asciiname":"Khayrosh",
    "gn:cc2":"KZ",
    "gn:country_code":"KZ",
    "gn:dem":12,
    "gn:feature_class":"P",
    "gn:feature_code":"PPL",
    "gn:name":"Khayrosh",
    "gn:population":0,
    "gn:timezone":"Asia/Oral",
    "iso:country":"KZ",
    "name:eng_x_preferred":[
        "Khayrosh"
    ],
    "name:rus_x_preferred":[
        "\u0425\u0430\u0439\u0440\u043e\u0448"
    ],
    "name:und_x_variant":[
        "Kyzyltan",
        "Khayrosh"
    ],
    "wof:name":"Khayrosh",
    "wof:placetype":"locality"
},
  "geometry": {"coordinates":[49.10861,50.41167],"type":"Point"}
}