{
  "type": "Feature",
  "properties": {
    "gn:admin1_code":"3.0",
    "gn:asciiname":"Aytmaambetov",
    "gn:country_code":"KZ",
    "gn:dem":296,
    "gn:feature_class":"P",
    "gn:feature_code":"PPL",
    "gn:name":"Aytmaambetov",
    "gn:population":0,
    "gn:timezone":"Asia/Almaty",
    "iso:country":"KZ",
    "wof:name":"Aytmaambetov",
    "wof:placetype":"locality"
},
  "geometry": {"coordinates":[72.96666999999999,51.86667],"type":"Point"}
}