{
  "type": "Feature",
  "properties": {
    "gn:admin1_code":"0.0",
    "gn:asciiname":"Imeni Mametovoy",
    "gn:country_code":"KZ",
    "gn:dem":377,
    "gn:feature_class":"P",
    "gn:feature_code":"PPL",
    "gn:name":"Imeni Mametovoy",
    "gn:population":0,
    "gn:timezone":"Asia/Almaty",
    "iso:country":"KZ",
    "wof:name":"Imeni Mametovoy",
    "wof:placetype":"locality"
},
  "geometry": {"coordinates":[70.83333,50.75],"type":"Point"}
}