{
  "type": "Feature",
  "properties": {
    "gn:admin1_code":"13.0",
    "gn:asciiname":"Kravtsovo",
    "gn:country_code":"KZ",
    "gn:dem":204,
    "gn:feature_class":"P",
    "gn:feature_code":"PPL",
    "gn:name":"Kravtsovo",
    "gn:population":0,
    "gn:timezone":"Asia/Qyzylorda",
    "iso:country":"KZ",
    "name:rus_x_preferred":[
        "\u041a\u0440\u0430\u0432\u0446\u043e\u0432\u043e"
    ],
    "wof:name":"Kravtsovo",
    "wof:placetype":"locality"
},
  "geometry": {"coordinates":[62.523,53.67765],"type":"Point"}
}