{
  "type": "Feature",
  "properties": {
    "gn:admin1_code":"3.0",
    "gn:asciiname":"Iskra",
    "gn:country_code":"KZ",
    "gn:dem":344,
    "gn:feature_class":"P",
    "gn:feature_code":"PPL",
    "gn:name":"Iskra",
    "gn:population":0,
    "gn:timezone":"Asia/Almaty",
    "iso:country":"KZ",
    "name:eng_x_preferred":[
        "Iskra"
    ],
    "name:kaz_x_preferred":[
        "\u012askra"
    ],
    "name:kaz_x_variant":[
        "\u0418\u0441\u043a\u0440\u0430"
    ],
    "name:rus_x_preferred":[
        "\u0418\u0441\u043a\u0440\u0430"
    ],
    "wof:name":"Iskra",
    "wof:placetype":"locality"
},
  "geometry": {"coordinates":[72.01902,52.06189000000001],"type":"Point"}
}