{
  "type": "Feature",
  "properties": {
    "gn:admin1_code":"11.0",
    "gn:asciiname":"Zhanga Baza",
    "gn:country_code":"KZ",
    "gn:dem":179,
    "gn:feature_class":"P",
    "gn:feature_code":"PPL",
    "gn:name":"Zhanga Baza",
    "gn:population":0,
    "gn:timezone":"Asia/Almaty",
    "iso:country":"KZ",
    "name:kaz_x_preferred":[
        "Zhanga Baza"
    ],
    "name:kaz_x_variant":[
        "\u0416\u0430\u04a3\u0430 \u0411\u0430\u0437\u0430"
    ],
    "wof:name":"Zhanga Baza",
    "wof:placetype":"locality"
},
  "geometry": {"coordinates":[78.10875,51.24636],"type":"Point"}
}