{
  "type": "Feature",
  "properties": {
    "gn:admin1_code":"11.0",
    "gn:asciiname":"Chistopol'",
    "gn:country_code":"KZ",
    "gn:dem":127,
    "gn:feature_class":"P",
    "gn:feature_code":"PPL",
    "gn:name":"Ch\u012bstopol\u2019",
    "gn:population":0,
    "gn:timezone":"Asia/Almaty",
    "iso:country":"KZ",
    "name:kaz_x_preferred":[
        "Ch\u012bstopol\u2019"
    ],
    "name:kaz_x_variant":[
        "\u0427\u0438\u0441\u0442\u043e\u043f\u043e\u043b\u044c"
    ],
    "name:rus_x_preferred":[
        "Chistopol\u2019"
    ],
    "wof:name":"Chistopol'",
    "wof:placetype":"locality"
},
  "geometry": {"coordinates":[77.80889999999999,52.84615],"type":"Point"}
}