{
  "type": "Feature",
  "properties": {
    "gn:admin1_code":"12.0",
    "gn:asciiname":"Aysa",
    "gn:country_code":"KZ",
    "gn:dem":619,
    "gn:feature_class":"P",
    "gn:feature_code":"PPL",
    "gn:name":"Aysa",
    "gn:population":0,
    "gn:timezone":"Asia/Almaty",
    "iso:country":"KZ",
    "name:kaz_x_preferred":[
        "Aysa"
    ],
    "name:kaz_x_variant":[
        "\u0410\u0439\u0441\u0430"
    ],
    "wof:name":"Aysa",
    "wof:placetype":"locality"
},
  "geometry": {"coordinates":[72.6266,48.52731],"type":"Point"}
}