{
  "type": "Feature",
  "properties": {
    "gn:admin1_code":"15.0",
    "gn:asciiname":"Dachnyy Poselok",
    "gn:country_code":"KZ",
    "gn:dem":198,
    "gn:feature_class":"P",
    "gn:feature_code":"PPL",
    "gn:name":"Dachnyy Pos\u00eblok",
    "gn:population":0,
    "gn:timezone":"Asia/Almaty",
    "iso:country":"KZ",
    "name:rus_x_preferred":[
        "Dachnyy Pos\u00eblok"
    ],
    "name:rus_x_variant":[
        "\u0414\u0430\u0447\u043d\u044b\u0439 \u041f\u043e\u0441\u0451\u043b\u043e\u043a"
    ],
    "wof:name":"Dachnyy Poselok",
    "wof:placetype":"locality"
},
  "geometry": {"coordinates":[80.38123,50.39908],"type":"Point"}
}