{
  "type": "Feature",
  "properties": {
    "gn:admin1_code":"6.0",
    "gn:asciiname":"Karachla",
    "gn:country_code":"KZ",
    "gn:dem":-17,
    "gn:feature_class":"P",
    "gn:feature_code":"PPL",
    "gn:name":"Karachla",
    "gn:population":0,
    "gn:timezone":"Asia/Atyrau",
    "iso:country":"KZ",
    "wof:name":"Karachla",
    "wof:placetype":"locality"
},
  "geometry": {"coordinates":[50.65,48.16667],"type":"Point"}
}