{
  "type": "Feature",
  "properties": {
    "gn:admin1_code":"0.0",
    "gn:asciiname":"Myakotikha",
    "gn:country_code":"KZ",
    "gn:dem":853,
    "gn:feature_class":"P",
    "gn:feature_code":"PPL",
    "gn:name":"Myakotikha",
    "gn:population":0,
    "gn:timezone":"Asia/Almaty",
    "iso:country":"KZ",
    "wof:name":"Myakotikha",
    "wof:placetype":"locality"
},
  "geometry": {"coordinates":[83.56667,49.83333],"type":"Point"}
}