{
  "type": "Feature",
  "properties": {
    "gn:admin1_code":"3.0",
    "gn:asciiname":"Aqbulaq",
    "gn:country_code":"KZ",
    "gn:dem":250,
    "gn:feature_class":"P",
    "gn:feature_code":"PPL",
    "gn:name":"Aqbulaq",
    "gn:population":0,
    "gn:timezone":"Asia/Almaty",
    "iso:country":"KZ",
    "name:kaz_x_preferred":[
        "Aqbulaq"
    ],
    "name:kaz_x_variant":[
        "\u0410\u049b\u0431\u04b1\u043b\u0430\u049b"
    ],
    "name:rus_x_preferred":[
        "\u041f\u0440\u0438\u0434\u043e\u0440\u043e\u0436\u043d\u043e\u0435"
    ],
    "name:rus_x_variant":[
        "Taratul\u2019gen",
        "\u0422\u0430\u0440\u0430\u0442\u0443\u043b\u044c\u0433\u0435\u043d"
    ],
    "name:und_x_variant":[
        "Pridorozhnoye"
    ],
    "wof:name":"Aqbulaq",
    "wof:placetype":"locality"
},
  "geometry": {"coordinates":[71.32426,52.84247],"type":"Point"}
}