{
  "type": "Feature",
  "properties": {
    "gn:admin1_code":"1.0",
    "gn:asciiname":"Quyghan",
    "gn:cc2":"KZ",
    "gn:country_code":"KZ",
    "gn:dem":340,
    "gn:feature_class":"P",
    "gn:feature_code":"PPL",
    "gn:name":"Quyghan",
    "gn:population":0,
    "gn:timezone":"Asia/Almaty",
    "iso:country":"KZ",
    "name:und_x_variant":[
        "Bol\u2019shoy Kuygan",
        "Kuygan",
        "Bolshoy Kuygon",
        "Quyghan"
    ],
    "wof:name":"Quyghan",
    "wof:placetype":"locality"
},
  "geometry": {"coordinates":[74.14667,45.36389000000001],"type":"Point"}
}