{
  "type": "Feature",
  "properties": {
    "gn:admin1_code":"0.0",
    "gn:asciiname":"Zhanatalap",
    "gn:cc2":"KZ",
    "gn:country_code":"KZ",
    "gn:dem":460,
    "gn:feature_class":"P",
    "gn:feature_code":"PPL",
    "gn:name":"Zhanatalap",
    "gn:population":0,
    "gn:timezone":"Asia/Almaty",
    "iso:country":"KZ",
    "name:und_x_variant":[
        "Zhanatalan",
        "Zhanatalap"
    ],
    "wof:name":"Zhanatalap",
    "wof:placetype":"locality"
},
  "geometry": {"coordinates":[80.01666999999998,49.58333],"type":"Point"}
}