{
  "type": "Feature",
  "properties": {
    "gn:admin1_code":"16.0",
    "gn:asciiname":"Yuzhnoye",
    "gn:country_code":"KZ",
    "gn:dem":154,
    "gn:feature_class":"P",
    "gn:feature_code":"PPL",
    "gn:name":"Yuzhnoye",
    "gn:population":0,
    "gn:timezone":"Asia/Almaty",
    "iso:country":"KZ",
    "name:eng_x_preferred":[
        "Yuzhnoye"
    ],
    "name:kaz_x_preferred":[
        "Yuzhnoe"
    ],
    "name:kaz_x_variant":[
        "\u042e\u0436\u043d\u043e\u0435"
    ],
    "name:rus_x_preferred":[
        "\u042e\u0436\u043d\u043e\u0435"
    ],
    "name:und_x_variant":[
        "Yuzhnyy",
        "Yuzhnoye"
    ],
    "wof:name":"Yuzhnoye",
    "wof:placetype":"locality"
},
  "geometry": {"coordinates":[68.73413000000001,53.97395],"type":"Point"}
}