{
  "type": "Feature",
  "properties": {
    "gn:admin1_code":"0.0",
    "gn:asciiname":"Burnashevo",
    "gn:country_code":"KZ",
    "gn:dem":368,
    "gn:feature_class":"P",
    "gn:feature_code":"PPL",
    "gn:name":"Burnash\u00ebvo",
    "gn:population":0,
    "gn:timezone":"Asia/Almaty",
    "iso:country":"KZ",
    "wof:name":"Burnashevo",
    "wof:placetype":"locality"
},
  "geometry": {"coordinates":[82.95,49.78333],"type":"Point"}
}