{
  "type": "Feature",
  "properties": {
    "gn:admin1_code":"3.0",
    "gn:asciiname":"Zhalayyr",
    "gn:country_code":"KZ",
    "gn:dem":413,
    "gn:feature_class":"P",
    "gn:feature_code":"PPL",
    "gn:name":"Zhalayyr",
    "gn:population":0,
    "gn:timezone":"Asia/Almaty",
    "iso:country":"KZ",
    "name:rus_x_preferred":[
        "\u0416\u0430\u043b\u0430\u0439\u044b\u0440"
    ],
    "wof:name":"Zhalayyr",
    "wof:placetype":"locality"
},
  "geometry": {"coordinates":[70.47351999999999,52.65039],"type":"Point"}
}