{
  "type": "Feature",
  "properties": {
    "gn:admin1_code":"13.0",
    "gn:asciiname":"Samany",
    "gn:country_code":"KZ",
    "gn:dem":230,
    "gn:feature_class":"P",
    "gn:feature_code":"PPL",
    "gn:name":"Samany",
    "gn:population":0,
    "gn:timezone":"Asia/Qyzylorda",
    "iso:country":"KZ",
    "name:kaz_x_preferred":[
        "\u0421\u0430\u043c\u0430\u043d\u044b"
    ],
    "wof:name":"Samany",
    "wof:placetype":"locality"
},
  "geometry": {"coordinates":[61.2635,53.57068],"type":"Point"}
}