{
  "type": "Feature",
  "properties": {
    "gn:admin1_code":"0.0",
    "gn:asciiname":"Sarsembe",
    "gn:country_code":"KZ",
    "gn:dem":568,
    "gn:feature_class":"P",
    "gn:feature_code":"PPL",
    "gn:name":"Sarsembe",
    "gn:population":0,
    "gn:timezone":"Asia/Almaty",
    "iso:country":"KZ",
    "wof:name":"Sarsembe",
    "wof:placetype":"locality"
},
  "geometry": {"coordinates":[77.36667,43.56667],"type":"Point"}
}