{
  "type": "Feature",
  "properties": {
    "gn:admin1_code":"0.0",
    "gn:asciiname":"Kaksal'skoye",
    "gn:country_code":"KZ",
    "gn:dem":281,
    "gn:feature_class":"P",
    "gn:feature_code":"PPL",
    "gn:name":"Kaksal\u2019skoye",
    "gn:population":0,
    "gn:timezone":"Asia/Almaty",
    "iso:country":"KZ",
    "name:und_x_variant":[
        "Kaksalskoe",
        "Kaksal\u2019skoye"
    ],
    "wof:name":"Kaksal'skoye",
    "wof:placetype":"locality"
},
  "geometry": {"coordinates":[69.25,51.61667],"type":"Point"}
}