{
  "type": "Feature",
  "properties": {
    "gn:admin1_code":"10.0",
    "gn:asciiname":"Aybozym",
    "gn:country_code":"KZ",
    "gn:dem":685,
    "gn:feature_class":"P",
    "gn:feature_code":"PPL",
    "gn:name":"Aybozym",
    "gn:population":0,
    "gn:timezone":"Asia/Almaty",
    "iso:country":"KZ",
    "name:rus_x_preferred":[
        "\u0410\u0439\u0431\u043e\u0437\u044b\u043c"
    ],
    "wof:name":"Aybozym",
    "wof:placetype":"locality"
},
  "geometry": {"coordinates":[69.50809,41.87742],"type":"Point"}
}