{
  "type": "Feature",
  "properties": {
    "gn:admin1_code":"10.0",
    "gn:asciiname":"Keles",
    "gn:country_code":"KZ",
    "gn:dem":768,
    "gn:feature_class":"P",
    "gn:feature_code":"PPL",
    "gn:name":"Keles",
    "gn:population":0,
    "gn:timezone":"Asia/Almaty",
    "iso:country":"KZ",
    "name:rus_x_preferred":[
        "\u041a\u0435\u043b\u0435\u0441"
    ],
    "wof:name":"Keles",
    "wof:placetype":"locality"
},
  "geometry": {"coordinates":[69.62045000000001,41.93628],"type":"Point"}
}