{
  "type": "Feature",
  "properties": {
    "gn:admin1_code":"10.0",
    "gn:asciiname":"Keles",
    "gn:country_code":"KZ",
    "gn:dem":768,
    "gn:feature_class":"P",
    "gn:feature_code":"PPL",
    "gn:name":"Keles",
    "gn:population":0,
    "gn:timezone":"Asia/Almaty",
    "iso:country":"KZ",
    "name:ceb_x_preferred":[
        "Keles \u0130l\u00e7esi"
    ],
    "name:deu_x_preferred":[
        "Keles"
    ],
    "name:fra_x_preferred":[
        "Keles"
    ],
    "name:mrj_x_preferred":[
        "\u041a\u0435\u043b\u0435\u0441"
    ],
    "name:msa_x_preferred":[
        "Keles"
    ],
    "name:nld_x_preferred":[
        "Keles"
    ],
    "name:nor_x_preferred":[
        "Keles"
    ],
    "name:pnb_x_preferred":[
        "\u0636\u0644\u0639 \u06a9\u06cc\u0644\u0633"
    ],
    "name:rus_x_preferred":[
        "\u041a\u0435\u043b\u0435\u0441"
    ],
    "name:swa_x_preferred":[
        "Keles"
    ],
    "name:tur_x_preferred":[
        "Keles"
    ],
    "name:ukr_x_preferred":[
        "\u041a\u0435\u043b\u0435\u0441"
    ],
    "name:urd_x_preferred":[
        "\u06a9\u06cc\u0644\u0633"
    ],
    "name:vie_x_preferred":[
        "Keles"
    ],
    "wof:name":"Keles",
    "wof:placetype":"locality"
},
  "geometry": {"coordinates":[69.62045000000001,41.93628],"type":"Point"}
}