{
  "type": "Feature",
  "properties": {
    "gn:admin1_code":"17.0",
    "gn:asciiname":"Abulkair",
    "gn:country_code":"KZ",
    "gn:dem":669,
    "gn:feature_class":"P",
    "gn:feature_code":"PPL",
    "gn:name":"Abulkair",
    "gn:population":0,
    "gn:timezone":"Asia/Almaty",
    "iso:country":"KZ",
    "name:kaz_x_preferred":[
        "\u00c4bilqayyr"
    ],
    "name:kaz_x_variant":[
        "\u04d8\u0431\u0456\u043b\u049b\u0430\u0439\u044b\u0440"
    ],
    "name:rus_x_preferred":[
        "\u0410\u0431\u0443\u043b\u043a\u0430\u0438\u0440"
    ],
    "wof:name":"Abulkair",
    "wof:placetype":"locality"
},
  "geometry": {"coordinates":[72.49188000000002,43.08747],"type":"Point"}
}