{
  "type": "Feature",
  "properties": {
    "gn:admin1_code":"0.0",
    "gn:asciiname":"Sary-Kul'",
    "gn:country_code":"KZ",
    "gn:dem":426,
    "gn:feature_class":"P",
    "gn:feature_code":"PPL",
    "gn:name":"Sary-Kul\u2019",
    "gn:population":0,
    "gn:timezone":"Asia/Almaty",
    "iso:country":"KZ",
    "name:rus_x_preferred":[
        "Sary-Kul\u2019"
    ],
    "wof:name":"Sary-Kul'",
    "wof:placetype":"locality"
},
  "geometry": {"coordinates":[79.96666999999999,49.58333],"type":"Point"}
}