{
  "type": "Feature",
  "properties": {
    "gn:admin1_code":"1.0",
    "gn:asciiname":"Enbekshi",
    "gn:country_code":"KZ",
    "gn:dem":426,
    "gn:feature_class":"P",
    "gn:feature_code":"PPL",
    "gn:name":"Enbekshi",
    "gn:population":0,
    "gn:timezone":"Asia/Almaty",
    "iso:country":"KZ",
    "name:mkd_x_preferred":[
        "\u0415\u043d\u0431\u0435\u043a\u0448\u0438"
    ],
    "name:msa_x_preferred":[
        "Enbekshi"
    ],
    "name:und_x_variant":[
        "Yenbekshi"
    ],
    "wof:name":"Enbekshi",
    "wof:placetype":"locality"
},
  "geometry": {"coordinates":[80.71274,46.16528],"type":"Point"}
}