{
  "type": "Feature",
  "properties": {
    "gn:admin1_code":"3.0",
    "gn:asciiname":"Engbekshilder",
    "gn:country_code":"KZ",
    "gn:dem":226,
    "gn:feature_class":"P",
    "gn:feature_code":"PPL",
    "gn:name":"Engbekshilder",
    "gn:population":0,
    "gn:timezone":"Asia/Almaty",
    "iso:country":"KZ",
    "name:eng_x_preferred":[
        "Engbekshilder"
    ],
    "name:kaz_x_preferred":[
        "\u0415\u04a3\u0431\u0435\u043a\u0448\u0456\u043b\u0434\u0435\u0440"
    ],
    "name:rus_x_preferred":[
        "\u042d\u043d\u0431\u0435\u043a\u0448\u0438\u043b\u044c\u0434\u0435\u0440\u0441\u043a\u043e\u0435"
    ],
    "name:und_x_variant":[
        "Enbekshil\u2019der",
        "Enbekshil\u2019derskiy",
        "Enbekshil\u2019derskoye",
        "Engbekshilder"
    ],
    "wof:name":"Engbekshilder",
    "wof:placetype":"locality"
},
  "geometry": {"coordinates":[71.50868,52.76651],"type":"Point"}
}