{
  "type": "Feature",
  "properties": {
    "gn:admin1_code":"11.0",
    "gn:asciiname":"Kyzyltan",
    "gn:country_code":"KZ",
    "gn:dem":93,
    "gn:feature_class":"P",
    "gn:feature_code":"PPL",
    "gn:name":"Kyzyltan",
    "gn:population":0,
    "gn:timezone":"Asia/Almaty",
    "iso:country":"KZ",
    "name:eng_x_preferred":[
        "Kyzyltan"
    ],
    "name:kaz_x_preferred":[
        "Qyzyltang"
    ],
    "name:kaz_x_variant":[
        "\u049a\u044b\u0437\u044b\u043b\u0442\u0430\u04a3"
    ],
    "name:rus_x_preferred":[
        "\u041a\u044b\u0437\u044b\u043b\u0442\u0430\u043d"
    ],
    "wof:name":"Kyzyltan",
    "wof:placetype":"locality"
},
  "geometry": {"coordinates":[76.50884000000001,52.91862],"type":"Point"}
}