{
  "type": "Feature",
  "properties": {
    "gn:admin1_code":"12.0",
    "gn:asciiname":"Aybatkazgan",
    "gn:country_code":"KZ",
    "gn:dem":368,
    "gn:feature_class":"P",
    "gn:feature_code":"PPL",
    "gn:name":"Aybatkazgan",
    "gn:population":0,
    "gn:timezone":"Asia/Almaty",
    "iso:country":"KZ",
    "name:und_x_variant":[
        "Aybad-Kazgan",
        "Aybatkazgan"
    ],
    "wof:name":"Aybatkazgan",
    "wof:placetype":"locality"
},
  "geometry": {"coordinates":[69.34999999999999,46.75],"type":"Point"}
}