{
  "type": "Feature",
  "properties": {
    "gn:admin1_code":"16.0",
    "gn:asciiname":"Bereznyaki",
    "gn:country_code":"KZ",
    "gn:dem":129,
    "gn:feature_class":"P",
    "gn:feature_code":"PPL",
    "gn:name":"Bereznyaki",
    "gn:population":0,
    "gn:timezone":"Asia/Almaty",
    "iso:country":"KZ",
    "name:rus_x_preferred":[
        "\u0411\u0435\u0440\u0435\u0437\u043d\u044f\u043a\u0438"
    ],
    "name:rus_x_variant":[
        "\u0411\u0440\u0443\u0441\u043e\u0432\u043e"
    ],
    "name:und_x_variant":[
        "Brusovo"
    ],
    "wof:name":"Bereznyaki",
    "wof:placetype":"locality"
},
  "geometry": {"coordinates":[70.65767,55.23694],"type":"Point"}
}