{
  "type": "Feature",
  "properties": {
    "gn:admin1_code":"0.0",
    "gn:asciiname":"Aktau",
    "gn:country_code":"KZ",
    "gn:dem":119,
    "gn:feature_class":"P",
    "gn:feature_code":"PPL",
    "gn:name":"Aktau",
    "gn:population":0,
    "gn:timezone":"Asia/Oral",
    "iso:country":"KZ",
    "wof:name":"Aktau",
    "wof:placetype":"locality"
},
  "geometry": {"coordinates":[53.4815,50.87979],"type":"Point"}
}