{
  "type": "Feature",
  "properties": {
    "gn:admin1_code":"0.0",
    "gn:asciiname":"Aktau",
    "gn:country_code":"KZ",
    "gn:dem":119,
    "gn:feature_class":"P",
    "gn:feature_code":"PPL",
    "gn:name":"Aktau",
    "gn:population":0,
    "gn:timezone":"Asia/Oral",
    "iso:country":"KZ",
    "name:ara_x_preferred":[
        "\u0623\u0643\u062a\u0627\u0648"
    ],
    "name:aze_x_preferred":[
        "Aktau"
    ],
    "name:bak_x_preferred":[
        "\u0410\u04a1\u0442\u0430\u0443"
    ],
    "name:bel_x_preferred":[
        "\u0410\u043a\u0442\u0430\u0443"
    ],
    "name:bul_x_preferred":[
        "\u0410\u043a\u0442\u0430\u0443"
    ],
    "name:cat_x_preferred":[
        "Akhtau"
    ],
    "name:ceb_x_preferred":[
        "Aktau"
    ],
    "name:ces_x_preferred":[
        "Aktau"
    ],
    "name:che_x_preferred":[
        "\u0410\u043a\u0442\u0430\u0443"
    ],
    "name:ckb_x_preferred":[
        "\u0626\u0627\u0642\u062a\u0627\u0648"
    ],
    "name:deu_x_preferred":[
        "Aqtau"
    ],
    "name:epo_x_preferred":[
        "Aktau"
    ],
    "name:est_x_preferred":[
        "Aktau"
    ],
    "name:eus_x_preferred":[
        "Aktau"
    ],
    "name:fas_x_preferred":[
        "\u0622\u0642\u200c\u062a\u0627\u0648"
    ],
    "name:fin_x_preferred":[
        "Aqtaw"
    ],
    "name:fra_x_preferred":[
        "Aqtaw"
    ],
    "name:hin_x_preferred":[
        "\u0905\u0915\u093c\u0924\u090a"
    ],
    "name:hsb_x_preferred":[
        "Aktau"
    ],
    "name:hun_x_preferred":[
        "Aktau"
    ],
    "name:ind_x_preferred":[
        "Aqtau"
    ],
    "name:ita_x_preferred":[
        "Aktau"
    ],
    "name:jpn_x_preferred":[
        "\u30a2\u30af\u30bf\u30a6"
    ],
    "name:kaa_x_preferred":[
        "Aqtaw"
    ],
    "name:kat_x_preferred":[
        "\u10d0\u10e5\u10d7\u10d0\u10e3"
    ],
    "name:kaz_x_preferred":[
        "\u0410\u049b\u0442\u0430\u0443"
    ],
    "name:kor_x_preferred":[
        "\uc545\ud0c0\uc6b0"
    ],
    "name:lit_x_preferred":[
        "Aktau"
    ],
    "name:nld_x_preferred":[
        "Aqtau"
    ],
    "name:nno_x_preferred":[
        "Aktau"
    ],
    "name:pnb_x_preferred":[
        "\u0622\u0642\u062a\u0627\u0624"
    ],
    "name:pol_x_preferred":[
        "Aktau"
    ],
    "name:por_x_preferred":[
        "Aktau"
    ],
    "name:ron_x_preferred":[
        "Akta\u00fa"
    ],
    "name:rus_x_preferred":[
        "\u0410\u043a\u0442\u0430\u0443"
    ],
    "name:sah_x_preferred":[
        "\u0410\u043a\u0442\u0430\u0443"
    ],
    "name:sco_x_preferred":[
        "Aktau"
    ],
    "name:spa_x_preferred":[
        "Aktau"
    ],
    "name:sqi_x_preferred":[
        "Aktau"
    ],
    "name:srp_x_preferred":[
        "\u0410\u043a\u0442\u0430\u0443"
    ],
    "name:swe_x_preferred":[
        "Aktau"
    ],
    "name:tat_x_preferred":[
        "\u0410\u043a\u0442\u0430\u0443"
    ],
    "name:tuk_x_preferred":[
        "Aktau"
    ],
    "name:tur_x_preferred":[
        "Aktav"
    ],
    "name:ukr_x_preferred":[
        "\u0410\u043a\u0442\u0430\u0443"
    ],
    "name:urd_x_preferred":[
        "\u0627\u0642\u062a\u0627\u0624"
    ],
    "name:uzb_x_preferred":[
        "Aqtau"
    ],
    "name:vie_x_preferred":[
        "Aktau"
    ],
    "name:war_x_preferred":[
        "Aktau"
    ],
    "name:zho_x_preferred":[
        "\u963f\u514b\u5957"
    ],
    "wof:name":"Aktau",
    "wof:placetype":"locality"
},
  "geometry": {"coordinates":[53.4815,50.87979],"type":"Point"}
}