{
  "type": "Feature",
  "properties": {
    "gn:admin1_code":"12.0",
    "gn:asciiname":"Karairekskiy",
    "gn:country_code":"KZ",
    "gn:dem":718,
    "gn:feature_class":"P",
    "gn:feature_code":"PPL",
    "gn:name":"Karairekskiy",
    "gn:population":0,
    "gn:timezone":"Asia/Almaty",
    "iso:country":"KZ",
    "wof:name":"Karairekskiy",
    "wof:placetype":"locality"
},
  "geometry": {"coordinates":[76.33333,49.76667],"type":"Point"}
}