{
  "type": "Feature",
  "properties": {
    "gn:admin1_code":"12.0",
    "gn:asciiname":"Airtas",
    "gn:country_code":"KZ",
    "gn:dem":765,
    "gn:feature_class":"P",
    "gn:feature_code":"PPL",
    "gn:name":"Airtas",
    "gn:population":0,
    "gn:timezone":"Asia/Almaty",
    "iso:country":"KZ",
    "wof:name":"Airtas",
    "wof:placetype":"locality"
},
  "geometry": {"coordinates":[76.66667,48.18333],"type":"Point"}
}