{
  "type": "Feature",
  "properties": {
    "gn:admin1_code":"0.0",
    "gn:asciiname":"Tileulikol'",
    "gn:country_code":"KZ",
    "gn:dem":138,
    "gn:feature_class":"P",
    "gn:feature_code":"PPL",
    "gn:name":"Tileulikol\u2019",
    "gn:population":0,
    "gn:timezone":"Asia/Oral",
    "iso:country":"KZ",
    "name:und_x_variant":[
        "Tlevlekol\u2019",
        "Tileulikol\u2019"
    ],
    "wof:name":"Tileulikol'",
    "wof:placetype":"locality"
},
  "geometry": {"coordinates":[53.73333,50.51667],"type":"Point"}
}