{
  "type": "Feature",
  "properties": {
    "gn:admin1_code":"7.0",
    "gn:asciiname":"Danilyakol'",
    "gn:country_code":"KZ",
    "gn:dem":54,
    "gn:feature_class":"P",
    "gn:feature_code":"PPL",
    "gn:name":"Danilyakol\u2019",
    "gn:population":0,
    "gn:timezone":"Asia/Oral",
    "iso:country":"KZ",
    "name:eng_x_preferred":[
        "Danilyakol'"
    ],
    "name:rus_x_preferred":[
        "\u0414\u0430\u043d\u0438\u043b\u044f\u043a\u043e\u043b\u044c"
    ],
    "name:und_x_variant":[
        "Danilekol\u2019",
        "Danilyakol\u2019"
    ],
    "wof:name":"Danilyakol'",
    "wof:placetype":"locality"
},
  "geometry": {"coordinates":[52.50267,51.36431],"type":"Point"}
}