{
  "type": "Feature",
  "properties": {
    "gn:admin1_code":"10.0",
    "gn:asciiname":"Imeni Karla Marksa",
    "gn:country_code":"KZ",
    "gn:dem":421,
    "gn:feature_class":"P",
    "gn:feature_code":"PPL",
    "gn:name":"Imeni Karla Marksa",
    "gn:population":0,
    "gn:timezone":"Asia/Almaty",
    "iso:country":"KZ",
    "wof:name":"Imeni Karla Marksa",
    "wof:placetype":"locality"
},
  "geometry": {"coordinates":[69.15000000000001,41.48333],"type":"Point"}
}