{
  "type": "Feature",
  "properties": {
    "gn:admin1_code":"0.0",
    "gn:asciiname":"Aydarlykol'",
    "gn:country_code":"KZ",
    "gn:dem":442,
    "gn:feature_class":"P",
    "gn:feature_code":"PPL",
    "gn:name":"Aydarlykol\u2019",
    "gn:population":0,
    "gn:timezone":"Asia/Almaty",
    "iso:country":"KZ",
    "name:rus_x_preferred":[
        "Aydarlykol\u2019"
    ],
    "wof:name":"Aydarlykol'",
    "wof:placetype":"locality"
},
  "geometry": {"coordinates":[72.01666999999998,50.88333],"type":"Point"}
}