{
  "type": "Feature",
  "properties": {
    "gn:admin1_code":"15.0",
    "gn:asciiname":"Dongelek",
    "gn:country_code":"KZ",
    "gn:dem":188,
    "gn:feature_class":"P",
    "gn:feature_code":"PPL",
    "gn:name":"D\u00f6ngelek",
    "gn:population":0,
    "gn:timezone":"Asia/Almaty",
    "iso:country":"KZ",
    "name:kaz_x_preferred":[
        "D\u00f6ngelek"
    ],
    "name:kaz_x_variant":[
        "\u0414\u04e9\u043d\u0433\u0435\u043b\u0435\u043a"
    ],
    "wof:name":"Dongelek",
    "wof:placetype":"locality"
},
  "geometry": {"coordinates":[79.14466,50.89027],"type":"Point"}
}