{
  "type": "Feature",
  "properties": {
    "gn:admin1_code":"12.0",
    "gn:asciiname":"Kollektivnoye",
    "gn:country_code":"KZ",
    "gn:dem":563,
    "gn:feature_class":"P",
    "gn:feature_code":"PPL",
    "gn:name":"Kollektivnoye",
    "gn:population":0,
    "gn:timezone":"Asia/Almaty",
    "iso:country":"KZ",
    "name:kaz_x_preferred":[
        "Kollekt\u012bvnoe"
    ],
    "name:kaz_x_variant":[
        "\u041a\u043e\u043b\u043b\u0435\u043a\u0442\u0438\u0432\u043d\u043e\u0435"
    ],
    "name:und_x_variant":[
        "Kollektivnyy",
        "Kollektivnoye"
    ],
    "wof:name":"Kollektivnoye",
    "wof:placetype":"locality"
},
  "geometry": {"coordinates":[73.04512,50.74565],"type":"Point"}
}