{
  "type": "Feature",
  "properties": {
    "gn:admin1_code":"0.0",
    "gn:asciiname":"Zhanalyk",
    "gn:country_code":"KZ",
    "gn:dem":921,
    "gn:feature_class":"P",
    "gn:feature_code":"PPL",
    "gn:name":"Zhanalyk",
    "gn:population":0,
    "gn:timezone":"Asia/Almaty",
    "iso:country":"KZ",
    "wof:name":"Zhanalyk",
    "wof:placetype":"locality"
},
  "geometry": {"coordinates":[79.81667,44.25],"type":"Point"}
}