{
  "type": "Feature",
  "properties": {
    "gn:admin1_code":"12.0",
    "gn:asciiname":"Chelyuskin",
    "gn:country_code":"KZ",
    "gn:dem":519,
    "gn:feature_class":"P",
    "gn:feature_code":"PPL",
    "gn:name":"Chelyuskin",
    "gn:population":0,
    "gn:timezone":"Asia/Almaty",
    "iso:country":"KZ",
    "name:bul_x_preferred":[
        "\u0427\u0435\u043b\u044e\u0441\u043a\u0438\u043d"
    ],
    "name:ces_x_preferred":[
        "\u010celjuskin"
    ],
    "name:deu_x_preferred":[
        "Tscheljuskin"
    ],
    "name:heb_x_preferred":[
        "\u05e6'\u05dc\u05d9\u05d5\u05e1\u05e7\u05d9\u05df"
    ],
    "name:hye_x_preferred":[
        "\u0549\u0565\u056c\u0575\u0578\u0582\u057d\u056f\u056b\u0576"
    ],
    "name:ita_x_preferred":[
        "\u010celjuskin"
    ],
    "name:nld_x_preferred":[
        "Tsjeljoeskin"
    ],
    "name:rus_x_preferred":[
        "\u0427\u0435\u043b\u044e\u0441\u043a\u0438\u043d"
    ],
    "wof:name":"Chelyuskin",
    "wof:placetype":"locality"
},
  "geometry": {"coordinates":[72.78333000000001,49.95],"type":"Point"}
}