{
  "type": "Feature",
  "properties": {
    "gn:admin1_code":"12.0",
    "gn:asciiname":"Chelyuskin",
    "gn:country_code":"KZ",
    "gn:dem":519,
    "gn:feature_class":"P",
    "gn:feature_code":"PPL",
    "gn:name":"Chelyuskin",
    "gn:population":0,
    "gn:timezone":"Asia/Almaty",
    "iso:country":"KZ",
    "wof:name":"Chelyuskin",
    "wof:placetype":"locality"
},
  "geometry": {"coordinates":[72.78333000000001,49.95],"type":"Point"}
}