{
  "type": "Feature",
  "properties": {
    "gn:admin1_code":"16.0",
    "gn:asciiname":"Benyash",
    "gn:country_code":"KZ",
    "gn:dem":124,
    "gn:feature_class":"P",
    "gn:feature_code":"PPL",
    "gn:name":"Benyash",
    "gn:population":0,
    "gn:timezone":"Asia/Almaty",
    "iso:country":"KZ",
    "name:eng_x_preferred":[
        "Benyash"
    ],
    "name:kaz_x_preferred":[
        "\u0411\u0435\u043d\u044f\u0448"
    ],
    "name:rus_x_preferred":[
        "\u0411\u0435\u043d\u044f\u0448"
    ],
    "wof:name":"Benyash",
    "wof:placetype":"locality"
},
  "geometry": {"coordinates":[70.881,54.82357],"type":"Point"}
}