{
  "type": "Feature",
  "properties": {
    "iso:country":"KZ",
    "name:eng_x_preferred":[
        "Torghay"
    ],
    "name:rus_x_preferred":[
        "\u0422\u0443\u0440\u0433\u0430\u0439"
    ],
    "name:unk_x_variant":[
        "Torgay"
    ],
    "ne:ADM0CAP":0.0,
    "ne:ADM0NAME":"Kazakhstan",
    "ne:ADM0_A3":"KAZ",
    "ne:ADM1NAME":"Qostanay",
    "ne:ADMIN1_COD":13,
    "ne:CAPALT":0,
    "ne:CHANGED":4,
    "ne:CHECKME":0,
    "ne:COMPARE":0,
    "ne:DIFFASCII":0,
    "ne:DIFFNOTE":"Added missing admin-1 capital. Population from GeoNames.",
    "ne:ELEVATION":0.0,
    "ne:FEATURECLA":"Admin-1 capital",
    "ne:FEATURE_CL":"P",
    "ne:FEATURE_CO":"PPL",
    "ne:GEONAMEID":1518062,
    "ne:GEONAMESNO":"GeoNames spatial join with similar names only.",
    "ne:GN_ASCII":"Torghay",
    "ne:GN_POP":5277,
    "ne:GTOPO30":96.0,
    "ne:ISO_A2":"KZ",
    "ne:LABELRANK":6,
    "ne:LATITUDE":49.626,
    "ne:LONGITUDE":63.498997,
    "ne:LS_MATCH":0,
    "ne:MAX_AREAKM":0.0,
    "ne:MAX_AREAMI":0.0,
    "ne:MAX_BBXMAX":0.0,
    "ne:MAX_BBXMIN":0.0,
    "ne:MAX_BBYMAX":0.0,
    "ne:MAX_BBYMIN":0.0,
    "ne:MAX_NATSCA":0.0,
    "ne:MAX_PERKM":0.0,
    "ne:MAX_PERMI":0.0,
    "ne:MAX_POP10":0,
    "ne:MAX_POP20":0,
    "ne:MAX_POP300":0,
    "ne:MAX_POP310":0,
    "ne:MAX_POP50":0,
    "ne:MEAN_BBXC":0.0,
    "ne:MEAN_BBYC":0.0,
    "ne:MEGACITY":0,
    "ne:MIN_AREAKM":0.0,
    "ne:MIN_AREAMI":0.0,
    "ne:MIN_BBXMAX":0.0,
    "ne:MIN_BBXMIN":0.0,
    "ne:MIN_BBYMAX":0.0,
    "ne:MIN_BBYMIN":0.0,
    "ne:MIN_PERKM":0.0,
    "ne:MIN_PERMI":0.0,
    "ne:NAME":"Turgay",
    "ne:NAMEASCII":"Turgay",
    "ne:NAMEDIFF":1,
    "ne:NATSCALE":5,
    "ne:POP1950":0,
    "ne:POP1955":0,
    "ne:POP1960":0,
    "ne:POP1965":0,
    "ne:POP1970":0,
    "ne:POP1975":0,
    "ne:POP1980":0,
    "ne:POP1985":0,
    "ne:POP1990":0,
    "ne:POP1995":0,
    "ne:POP2000":0,
    "ne:POP2005":0,
    "ne:POP2010":0,
    "ne:POP2015":0,
    "ne:POP2020":0,
    "ne:POP2025":0,
    "ne:POP2050":0,
    "ne:POP_MAX":5277,
    "ne:POP_MIN":5277,
    "ne:POP_OTHER":0,
    "ne:RANK_MAX":5,
    "ne:RANK_MIN":5,
    "ne:SCALERANK":9,
    "ne:SOV0NAME":"Kazakhstan",
    "ne:SOV_A3":"KAZ",
    "ne:TIMEZONE":"Asia/Qyzylorda",
    "ne:UN_FID":0,
    "ne:UN_LAT":0.0,
    "ne:UN_LONG":0.0,
    "ne:WORLDCITY":0,
    "qs:gn_country":"KZ",
    "qs:gn_fcode":"PPL",
    "qs:gn_pop":5277,
    "qs:name":"Torghay",
    "qs:name_adm0":"Kazakhstan",
    "qs:name_adm1":"Qostanay",
    "qs:photos":0,
    "qs:photos_1k":0,
    "qs:photos_9k":0,
    "qs:photos_9r":0,
    "qs:photos_all":0,
    "qs:photos_sr":0,
    "qs:placetype":"Town",
    "qs:pop_sr":"5",
    "qs:woe_adm0":23424871,
    "wof:name":"Torghay",
    "wof:placetype":"locality",
    "wof:population":5277
},
  "geometry": {"coordinates":[63.49806,49.63389],"type":"Point"}
}