{
  "type": "Feature",
  "properties": {
    "gn:admin1_code":"6.0",
    "gn:asciiname":"Malaya Safonovka",
    "gn:country_code":"KZ",
    "gn:dem":-28,
    "gn:feature_class":"P",
    "gn:feature_code":"PPL",
    "gn:name":"Malaya Safonovka",
    "gn:population":0,
    "gn:timezone":"Asia/Atyrau",
    "iso:country":"KZ",
    "wof:name":"Malaya Safonovka",
    "wof:placetype":"locality"
},
  "geometry": {"coordinates":[48.91944,46.49444],"type":"Point"}
}