{
  "type": "Feature",
  "properties": {
    "gn:admin1_code":"0.0",
    "gn:asciiname":"Vostochnoye Koktyube",
    "gn:cc2":"KZ",
    "gn:country_code":"KZ",
    "gn:dem":1024,
    "gn:feature_class":"P",
    "gn:feature_code":"PPL",
    "gn:name":"Vostochnoye Koktyube",
    "gn:population":0,
    "gn:timezone":"Asia/Almaty",
    "iso:country":"KZ",
    "name:und_x_variant":[
        "Kurama",
        "Vostochnoye Koktyube"
    ],
    "wof:name":"Vostochnoye Koktyube",
    "wof:placetype":"locality"
},
  "geometry": {"coordinates":[77.51306,43.36417],"type":"Point"}
}