{
  "type": "Feature",
  "properties": {
    "gn:admin1_code":"17.0",
    "gn:asciiname":"Ushbas",
    "gn:country_code":"KZ",
    "gn:dem":803,
    "gn:feature_class":"P",
    "gn:feature_code":"PPL",
    "gn:name":"Ushbas",
    "gn:population":0,
    "gn:timezone":"Asia/Almaty",
    "iso:country":"KZ",
    "name:kaz_x_preferred":[
        "\u00dcshbas"
    ],
    "name:kaz_x_variant":[
        "\u04ae\u0448\u0431\u0430\u0441"
    ],
    "name:rus_x_preferred":[
        "\u0423\u0448\u0431\u0430\u0441"
    ],
    "name:und_x_variant":[
        "Uch-Bas",
        "Ushbas"
    ],
    "wof:name":"Ushbas",
    "wof:placetype":"locality"
},
  "geometry": {"coordinates":[69.69188,43.40651],"type":"Point"}
}