{
  "type": "Feature",
  "properties": {
    "gn:admin1_code":"15.0",
    "gn:asciiname":"Almasay",
    "gn:country_code":"KZ",
    "gn:dem":403,
    "gn:feature_class":"P",
    "gn:feature_code":"PPL",
    "gn:name":"Almasay",
    "gn:population":0,
    "gn:timezone":"Asia/Almaty",
    "iso:country":"KZ",
    "name:eng_x_preferred":[
        "Almasay"
    ],
    "name:rus_x_preferred":[
        "\u0410\u043b\u043c\u0430\u0441\u0430\u0439"
    ],
    "wof:name":"Almasay",
    "wof:placetype":"locality"
},
  "geometry": {"coordinates":[82.44532,49.79265],"type":"Point"}
}