{
  "type": "Feature",
  "properties": {
    "gn:admin1_code":"16.0",
    "gn:asciiname":"Dayyndyk",
    "gn:country_code":"KZ",
    "gn:dem":138,
    "gn:feature_class":"P",
    "gn:feature_code":"PPL",
    "gn:name":"Dayyndyk",
    "gn:population":0,
    "gn:timezone":"Asia/Almaty",
    "iso:country":"KZ",
    "name:eng_x_preferred":[
        "Dayyndyk"
    ],
    "name:kaz_x_preferred":[
        "Dayyndyq"
    ],
    "name:kaz_x_variant":[
        "\u0414\u0430\u0439\u044b\u043d\u0434\u044b\u049b"
    ],
    "name:rus_x_preferred":[
        "\u0414\u0430\u0439\u044b\u043d\u0434\u044b\u043a"
    ],
    "name:rus_x_variant":[
        "\u041e\u043b\u043f\u0430\u0433\u0430\u0440"
    ],
    "name:und_x_variant":[
        "Olpagar"
    ],
    "wof:name":"Dayyndyk",
    "wof:placetype":"locality"
},
  "geometry": {"coordinates":[69.06489000000001,54.50268000000001],"type":"Point"}
}