{
  "type": "Feature",
  "properties": {
    "gn:admin1_code":"6.0",
    "gn:asciiname":"Kayshaga",
    "gn:country_code":"KZ",
    "gn:dem":-29,
    "gn:feature_class":"P",
    "gn:feature_code":"PPL",
    "gn:name":"Kayshaga",
    "gn:population":0,
    "gn:timezone":"Asia/Atyrau",
    "iso:country":"KZ",
    "wof:name":"Kayshaga",
    "wof:placetype":"locality"
},
  "geometry": {"coordinates":[49.21667,46.61667],"type":"Point"}
}