{
  "type": "Feature",
  "properties": {
    "gn:admin1_code":"15.0",
    "gn:asciiname":"Aksuat",
    "gn:country_code":"KZ",
    "gn:dem":543,
    "gn:feature_class":"P",
    "gn:feature_code":"PPL",
    "gn:name":"Aksuat",
    "gn:population":0,
    "gn:timezone":"Asia/Almaty",
    "iso:country":"KZ",
    "name:kaz_x_preferred":[
        "\u0410\u049b\u0441\u0443\u0430\u0442"
    ],
    "name:rus_x_preferred":[
        "\u0410\u043a\u0441\u0443\u0430\u0442"
    ],
    "name:und_x_variant":[
        "Aqs\u016bat"
    ],
    "wof:name":"Aksuat",
    "wof:placetype":"locality"
},
  "geometry": {"coordinates":[82.80858000000001,47.76124],"type":"Point"}
}