{
  "type": "Feature",
  "properties": {
    "gn:admin1_code":"4.0",
    "gn:asciiname":"Shibindy",
    "gn:country_code":"KZ",
    "gn:dem":75,
    "gn:feature_class":"P",
    "gn:feature_code":"PPL",
    "gn:name":"Shibindy",
    "gn:population":0,
    "gn:timezone":"Asia/Aqtobe",
    "iso:country":"KZ",
    "wof:name":"Shibindy",
    "wof:placetype":"locality"
},
  "geometry": {"coordinates":[61.95,48.21667],"type":"Point"}
}