{
  "type": "Feature",
  "properties": {
    "gn:admin1_code":"11.0",
    "gn:asciiname":"Aqkol",
    "gn:country_code":"KZ",
    "gn:dem":114,
    "gn:feature_class":"P",
    "gn:feature_code":"PPL",
    "gn:name":"Aqk\u00f6l",
    "gn:population":0,
    "gn:timezone":"Asia/Almaty",
    "iso:country":"KZ",
    "name:ceb_x_preferred":[
        "Aqkol"
    ],
    "name:eng_x_preferred":[
        "Aqk\u00f6l"
    ],
    "name:rus_x_preferred":[
        "\u0410\u043a\u043a\u043e\u043b\u044c"
    ],
    "name:swe_x_preferred":[
        "Aqkol"
    ],
    "name:und_x_variant":[
        "Akkol\u2019",
        "Akkul\u2019skiy"
    ],
    "wof:name":"Aqkol",
    "wof:placetype":"locality"
},
  "geometry": {"coordinates":[75.0569,52.33598],"type":"Point"}
}