{
  "type": "Feature",
  "properties": {
    "gn:admin1_code":"0.0",
    "gn:asciiname":"Uzun-Sor",
    "gn:country_code":"KZ",
    "gn:dem":141,
    "gn:feature_class":"P",
    "gn:feature_code":"PPL",
    "gn:name":"Uzun-Sor",
    "gn:population":0,
    "gn:timezone":"Asia/Almaty",
    "iso:country":"KZ",
    "wof:name":"Uzun-Sor",
    "wof:placetype":"locality"
},
  "geometry": {"coordinates":[77.86667,51.61667],"type":"Point"}
}