{
  "type": "Feature",
  "properties": {
    "gn:admin1_code":"0.0",
    "gn:asciiname":"Boryk",
    "gn:country_code":"KZ",
    "gn:dem":2,
    "gn:feature_class":"P",
    "gn:feature_code":"PPL",
    "gn:name":"Boryk",
    "gn:population":0,
    "gn:timezone":"Asia/Oral",
    "iso:country":"KZ",
    "name:eng_x_preferred":[
        "Boryk"
    ],
    "name:rus_x_preferred":[
        "\u0411\u043e\u0440\u0438\u043a"
    ],
    "wof:name":"Boryk",
    "wof:placetype":"locality"
},
  "geometry": {"coordinates":[50.35,49.58333],"type":"Point"}
}