{
  "type": "Feature",
  "properties": {
    "gn:admin1_code":"4.0",
    "gn:asciiname":"Taldysay",
    "gn:country_code":"KZ",
    "gn:dem":185,
    "gn:feature_class":"P",
    "gn:feature_code":"PPL",
    "gn:name":"Taldysay",
    "gn:population":0,
    "gn:timezone":"Asia/Aqtobe",
    "iso:country":"KZ",
    "name:ell_x_preferred":[
        "\u03a4\u03b1\u03bb\u03bd\u03c4\u03b9\u03c3\u03ac\u03b9"
    ],
    "name:kaz_x_preferred":[
        "\u0422\u0430\u043b\u0434\u044b\u0441\u0430\u0439"
    ],
    "name:msa_x_preferred":[
        "Taldysay"
    ],
    "name:rus_x_preferred":[
        "\u0422\u0430\u043b\u0434\u044b\u0441\u0430\u0439"
    ],
    "name:ukr_x_preferred":[
        "\u0422\u0430\u043b\u0434\u0438\u0441\u0430\u0439"
    ],
    "wof:name":"Taldysay",
    "wof:placetype":"locality"
},
  "geometry": {"coordinates":[60.68333000000001,49.26667],"type":"Point"}
}