{
  "type": "Feature",
  "properties": {
    "gn:admin1_code":"4.0",
    "gn:asciiname":"Taldysay",
    "gn:country_code":"KZ",
    "gn:dem":185,
    "gn:feature_class":"P",
    "gn:feature_code":"PPL",
    "gn:name":"Taldysay",
    "gn:population":0,
    "gn:timezone":"Asia/Aqtobe",
    "iso:country":"KZ",
    "wof:name":"Taldysay",
    "wof:placetype":"locality"
},
  "geometry": {"coordinates":[60.68333000000001,49.26667],"type":"Point"}
}