{
  "type": "Feature",
  "properties": {
    "gn:admin1_code":"4.0",
    "gn:asciiname":"Soyuznoye",
    "gn:country_code":"KZ",
    "gn:dem":382,
    "gn:feature_class":"P",
    "gn:feature_code":"PPL",
    "gn:name":"Soyuznoye",
    "gn:population":0,
    "gn:timezone":"Asia/Aqtobe",
    "iso:country":"KZ",
    "name:eng_x_preferred":[
        "Soyuznoe"
    ],
    "name:kaz_x_preferred":[
        "Soyuznoe"
    ],
    "name:rus_x_preferred":[
        "\u0421\u043e\u044e\u0437\u043d\u043e\u0435"
    ],
    "wof:name":"Soyuznoye",
    "wof:placetype":"locality"
},
  "geometry": {"coordinates":[60.15931,50.83136],"type":"Point"}
}