{
  "type": "Feature",
  "properties": {
    "gn:admin1_code":"14.0",
    "gn:asciiname":"Tabankuduk",
    "gn:country_code":"KZ",
    "gn:dem":85,
    "gn:feature_class":"P",
    "gn:feature_code":"PPL",
    "gn:name":"Tabankuduk",
    "gn:population":0,
    "gn:timezone":"Asia/Qyzylorda",
    "iso:country":"KZ",
    "wof:name":"Tabankuduk",
    "wof:placetype":"locality"
},
  "geometry": {"coordinates":[61.66667,46.43333],"type":"Point"}
}