{
  "type": "Feature",
  "properties": {
    "gn:admin1_code":"0.0",
    "gn:asciiname":"Pulykin",
    "gn:cc2":"KZ",
    "gn:country_code":"KZ",
    "gn:dem":19,
    "gn:feature_class":"P",
    "gn:feature_code":"PPL",
    "gn:name":"Pulykin",
    "gn:population":0,
    "gn:timezone":"Asia/Oral",
    "iso:country":"KZ",
    "name:und_x_variant":[
        "Pupykan",
        "Pulykin"
    ],
    "wof:name":"Pulykin",
    "wof:placetype":"locality"
},
  "geometry": {"coordinates":[50.86667,50.66667],"type":"Point"}
}