{
  "type": "Feature",
  "properties": {
    "gn:admin1_code":"15.0",
    "gn:asciiname":"Bol'shenarymskoye",
    "gn:country_code":"KZ",
    "gn:dem":403,
    "gn:feature_class":"P",
    "gn:feature_code":"PPL",
    "gn:name":"Bol\u2019shenarymskoye",
    "gn:population":0,
    "gn:timezone":"Asia/Almaty",
    "iso:country":"KZ",
    "name:eng_x_preferred":[
        "\u00dclkennaryn"
    ],
    "name:kaz_x_preferred":[
        "\u00dclkennaryn"
    ],
    "name:kaz_x_variant":[
        "Bol\u2019shenarymskoe",
        "\u0411\u043e\u043b\u044c\u0448\u0435\u043d\u0430\u0440\u044b\u043c\u0441\u043a\u043e\u0435"
    ],
    "name:rus_x_preferred":[
        "Bol\u2019shenarymskoye"
    ],
    "name:rus_x_variant":[
        "\u0411\u043e\u043b\u044c\u0448\u0435\u043d\u0430\u0440\u044b\u043c\u0441\u043a\u043e\u0435"
    ],
    "name:und_x_variant":[
        "Bol\u2019shenarym",
        "Bol\u2019shoy Narymskoye",
        "Bol\u2019shoye Narymskoye"
    ],
    "wof:name":"Bol'shenarymskoye",
    "wof:placetype":"locality"
},
  "geometry": {"coordinates":[84.50758,49.21245],"type":"Point"}
}