{
  "type": "Feature",
  "properties": {
    "gn:admin1_code":"12.0",
    "gn:asciiname":"Agashkol'",
    "gn:country_code":"KZ",
    "gn:dem":733,
    "gn:feature_class":"P",
    "gn:feature_code":"PPL",
    "gn:name":"Agashkol\u2019",
    "gn:population":0,
    "gn:timezone":"Asia/Almaty",
    "iso:country":"KZ",
    "name:rus_x_preferred":[
        "Agashkol\u2019"
    ],
    "name:rus_x_variant":[
        "\u0410\u0433\u0430\u0448\u043a\u043e\u043b\u044c"
    ],
    "wof:name":"Agashkol'",
    "wof:placetype":"locality"
},
  "geometry": {"coordinates":[75.57909000000002,48.1629],"type":"Point"}
}