{
  "type": "Feature",
  "properties": {
    "gn:admin1_code":"0.0",
    "gn:asciiname":"Sarkamys",
    "gn:cc2":"KZ",
    "gn:country_code":"KZ",
    "gn:dem":13,
    "gn:feature_class":"P",
    "gn:feature_code":"PPL",
    "gn:name":"Sarkamys",
    "gn:population":0,
    "gn:timezone":"Asia/Oral",
    "iso:country":"KZ",
    "name:und_x_variant":[
        "Sorkamysh",
        "Sar-Kamysh",
        "Sarkamys"
    ],
    "wof:name":"Sarkamys",
    "wof:placetype":"locality"
},
  "geometry": {"coordinates":[49.98333,50.51667],"type":"Point"}
}