{
  "type": "Feature",
  "properties": {
    "gn:admin1_code":"0.0",
    "gn:asciiname":"Voznesenskoye",
    "gn:country_code":"KZ",
    "gn:dem":421,
    "gn:feature_class":"P",
    "gn:feature_code":"PPL",
    "gn:name":"Voznesenskoye",
    "gn:population":0,
    "gn:timezone":"Asia/Almaty",
    "iso:country":"KZ",
    "wof:name":"Voznesenskoye",
    "wof:placetype":"locality"
},
  "geometry": {"coordinates":[72.33333,50.76667],"type":"Point"}
}