{
  "type": "Feature",
  "properties": {
    "gn:admin1_code":"0.0",
    "gn:asciiname":"Aksuat",
    "gn:country_code":"KZ",
    "gn:dem":147,
    "gn:feature_class":"P",
    "gn:feature_code":"PPL",
    "gn:name":"Aksuat",
    "gn:population":0,
    "gn:timezone":"Asia/Almaty",
    "iso:country":"KZ",
    "wof:name":"Aksuat",
    "wof:placetype":"locality"
},
  "geometry": {"coordinates":[65.53333000000001,50.33333],"type":"Point"}
}