{
  "type": "Feature",
  "properties": {
    "gn:admin1_code":"0.0",
    "gn:asciiname":"Marchikha",
    "gn:country_code":"KZ",
    "gn:dem":1104,
    "gn:feature_class":"P",
    "gn:feature_code":"PPL",
    "gn:name":"Marchikha",
    "gn:population":0,
    "gn:timezone":"Asia/Almaty",
    "iso:country":"KZ",
    "wof:name":"Marchikha",
    "wof:placetype":"locality"
},
  "geometry": {"coordinates":[83.63333,50.15],"type":"Point"}
}