{
  "type": "Feature",
  "properties": {
    "gn:admin1_code":"16.0",
    "gn:asciiname":"Peschanka",
    "gn:country_code":"KZ",
    "gn:dem":162,
    "gn:feature_class":"P",
    "gn:feature_code":"PPL",
    "gn:name":"Peschanka",
    "gn:population":0,
    "gn:timezone":"Asia/Almaty",
    "iso:country":"KZ",
    "name:rus_x_preferred":[
        "\u041f\u0435\u0441\u0447\u0430\u043d\u043a\u0430"
    ],
    "wof:name":"Peschanka",
    "wof:placetype":"locality"
},
  "geometry": {"coordinates":[66.24393000000001,54.53594],"type":"Point"}
}