{
  "type": "Feature",
  "properties": {
    "gn:admin1_code":"10.0",
    "gn:asciiname":"Bazarbay",
    "gn:country_code":"KZ",
    "gn:dem":784,
    "gn:feature_class":"P",
    "gn:feature_code":"PPL",
    "gn:name":"Bazarbay",
    "gn:population":0,
    "gn:timezone":"Asia/Almaty",
    "iso:country":"KZ",
    "wof:name":"Bazarbay",
    "wof:placetype":"locality"
},
  "geometry": {"coordinates":[69.53333000000001,41.65],"type":"Point"}
}