{
  "type": "Feature",
  "properties": {
    "gn:admin1_code":"10.0",
    "gn:asciiname":"Orgeba",
    "gn:country_code":"KZ",
    "gn:dem":265,
    "gn:feature_class":"P",
    "gn:feature_code":"PPL",
    "gn:name":"\u00d6rgeba",
    "gn:population":0,
    "gn:timezone":"Asia/Almaty",
    "iso:country":"KZ",
    "name:kaz_x_preferred":[
        "\u00d6rgeba"
    ],
    "name:kaz_x_variant":[
        "\u04e8\u0440\u0433\u0435\u0431\u0430"
    ],
    "name:uzb_x_preferred":[
        "Org\u2018abos"
    ],
    "wof:name":"Orgeba",
    "wof:placetype":"locality"
},
  "geometry": {"coordinates":[68.43987,40.63609],"type":"Point"}
}