{
  "type": "Feature",
  "properties": {
    "gn:admin1_code":"12.0",
    "gn:asciiname":"Tortkuduk",
    "gn:country_code":"KZ",
    "gn:dem":403,
    "gn:feature_class":"P",
    "gn:feature_code":"PPL",
    "gn:name":"Tortkuduk",
    "gn:population":0,
    "gn:timezone":"Asia/Almaty",
    "iso:country":"KZ",
    "name:kaz_x_preferred":[
        "T\u00f6rtqudyq"
    ],
    "name:kaz_x_variant":[
        "\u0422\u04e9\u0440\u0442\u049b\u04b1\u0434\u044b\u049b"
    ],
    "name:rus_x_preferred":[
        "\u0422\u043e\u0440\u0442\u043a\u0443\u0434\u0443\u043a"
    ],
    "wof:name":"Tortkuduk",
    "wof:placetype":"locality"
},
  "geometry": {"coordinates":[73.86506,50.9474],"type":"Point"}
}