{
  "type": "Feature",
  "properties": {
    "gn:admin1_code":"10.0",
    "gn:asciiname":"Koktas",
    "gn:country_code":"KZ",
    "gn:dem":877,
    "gn:feature_class":"P",
    "gn:feature_code":"PPL",
    "gn:name":"Koktas",
    "gn:population":0,
    "gn:timezone":"Asia/Almaty",
    "iso:country":"KZ",
    "name:rus_x_preferred":[
        "\u041a\u043e\u043a\u0442\u0430\u0441"
    ],
    "wof:name":"Koktas",
    "wof:placetype":"locality"
},
  "geometry": {"coordinates":[69.58578,41.73475],"type":"Point"}
}