{
  "type": "Feature",
  "properties": {
    "gn:admin1_code":"11.0",
    "gn:asciiname":"Kyzyloktyabr'",
    "gn:country_code":"KZ",
    "gn:dem":139,
    "gn:feature_class":"P",
    "gn:feature_code":"PPL",
    "gn:name":"Kyzyloktyabr\u2019",
    "gn:population":0,
    "gn:timezone":"Asia/Almaty",
    "iso:country":"KZ",
    "name:kaz_x_preferred":[
        "Qyzyl-Oktyabr\u2019"
    ],
    "name:kaz_x_variant":[
        "\u049a\u044b\u0437\u044b\u043b-\u041e\u043a\u0442\u044f\u0431\u0440\u044c"
    ],
    "name:rus_x_preferred":[
        "\u041a\u044b\u0437\u044b\u043b\u043e\u043a\u0442\u044f\u0431\u0440\u044c"
    ],
    "name:und_x_variant":[
        "Kyzyloktyabr\u2019",
        "Qyzyl Oktyabr\u2019"
    ],
    "wof:name":"Kyzyloktyabr'",
    "wof:placetype":"locality"
},
  "geometry": {"coordinates":[77.66529,51.35224],"type":"Point"}
}