{
  "type": "Feature",
  "properties": {
    "gn:admin1_code":"13.0",
    "gn:asciiname":"Kayyndykol'",
    "gn:country_code":"KZ",
    "gn:dem":209,
    "gn:feature_class":"P",
    "gn:feature_code":"PPL",
    "gn:name":"Kayyndykol\u2019",
    "gn:population":0,
    "gn:timezone":"Asia/Qyzylorda",
    "iso:country":"KZ",
    "name:eng_x_preferred":[
        "Kayyndykol'"
    ],
    "name:kaz_x_preferred":[
        "Qayyndyk\u00f6l"
    ],
    "name:rus_x_preferred":[
        "\u041a\u0430\u0438\u043d\u0434\u044b\u043a\u043e\u043b\u044c"
    ],
    "name:rus_x_variant":[
        "Kayyndykol\u2019"
    ],
    "name:und_x_variant":[
        "Kaindykol\u2019",
        "Imeni Belinskogo"
    ],
    "wof:name":"Kayyndykol'",
    "wof:placetype":"locality"
},
  "geometry": {"coordinates":[62.66638,52.29294],"type":"Point"}
}