{
  "type": "Feature",
  "properties": {
    "gn:admin1_code":"12.0",
    "gn:asciiname":"Kokshetau",
    "gn:country_code":"KZ",
    "gn:dem":926,
    "gn:feature_class":"P",
    "gn:feature_code":"PPL",
    "gn:name":"Kokshetau",
    "gn:population":0,
    "gn:timezone":"Asia/Almaty",
    "iso:country":"KZ",
    "name:kaz_x_preferred":[
        "K\u00f6ksheta\u016b"
    ],
    "name:kaz_x_variant":[
        "\u041a\u04e9\u043a\u0448\u0435\u0442\u0430\u0443"
    ],
    "name:rus_x_preferred":[
        "\u041a\u043e\u043a\u0448\u0435\u0442\u0430\u0443"
    ],
    "wof:name":"Kokshetau",
    "wof:placetype":"locality"
},
  "geometry": {"coordinates":[76.89723000000002,48.97836],"type":"Point"}
}