{
  "type": "Feature",
  "properties": {
    "gn:admin1_code":"1.0",
    "gn:asciiname":"Saz",
    "gn:country_code":"KZ",
    "gn:dem":630,
    "gn:feature_class":"P",
    "gn:feature_code":"PPL",
    "gn:name":"Saz",
    "gn:population":0,
    "gn:timezone":"Asia/Almaty",
    "iso:country":"KZ",
    "name:rus_x_preferred":[
        "\u0421\u0430\u0437"
    ],
    "name:tur_x_preferred":[
        "Saz"
    ],
    "wof:name":"Saz",
    "wof:placetype":"locality"
},
  "geometry": {"coordinates":[75.97933,43.5776],"type":"Point"}
}