{
  "type": "Feature",
  "properties": {
    "gn:admin1_code":"16.0",
    "gn:asciiname":"Tishchenko",
    "gn:country_code":"KZ",
    "gn:dem":126,
    "gn:feature_class":"P",
    "gn:feature_code":"PPL",
    "gn:name":"Tishchenko",
    "gn:population":0,
    "gn:timezone":"Asia/Almaty",
    "iso:country":"KZ",
    "name:rus_x_preferred":[
        "\u0422\u0438\u0449\u0435\u043d\u043a\u043e"
    ],
    "wof:name":"Tishchenko",
    "wof:placetype":"locality"
},
  "geometry": {"coordinates":[70.56941999999999,54.8671],"type":"Point"}
}