{
  "type": "Feature",
  "properties": {
    "gn:admin1_code":"16.0",
    "gn:asciiname":"Tishchenko",
    "gn:country_code":"KZ",
    "gn:dem":126,
    "gn:feature_class":"P",
    "gn:feature_code":"PPL",
    "gn:name":"Tishchenko",
    "gn:population":0,
    "gn:timezone":"Asia/Almaty",
    "iso:country":"KZ",
    "name:bel_x_preferred":[
        "\u0426\u0456\u0448\u0447\u0430\u043d\u043a\u0430"
    ],
    "name:deu_x_preferred":[
        "Tischtschenko"
    ],
    "name:fra_x_preferred":[
        "Tichtchenko"
    ],
    "name:jpn_x_preferred":[
        "\u30c6\u30a3\u30fc\u30b7\u30c1\u30a7\u30f3\u30b3"
    ],
    "name:rus_x_preferred":[
        "\u0422\u0438\u0449\u0435\u043d\u043a\u043e"
    ],
    "name:ukr_x_preferred":[
        "\u0422\u0438\u0449\u0435\u043d\u043a\u043e"
    ],
    "wof:name":"Tishchenko",
    "wof:placetype":"locality"
},
  "geometry": {"coordinates":[70.56941999999999,54.8671],"type":"Point"}
}