{
  "type": "Feature",
  "properties": {
    "gn:admin1_code":"13.0",
    "gn:asciiname":"Lenino",
    "gn:country_code":"KZ",
    "gn:dem":215,
    "gn:feature_class":"P",
    "gn:feature_code":"PPL",
    "gn:name":"Lenino",
    "gn:population":0,
    "gn:timezone":"Asia/Qyzylorda",
    "iso:country":"KZ",
    "name:bel_x_preferred":[
        "\u041b\u0435\u043d\u0456\u043d\u0430"
    ],
    "name:kaz_x_preferred":[
        "Len\u012bno"
    ],
    "name:kaz_x_variant":[
        "\u041b\u0435\u043d\u0438\u043d\u043e"
    ],
    "name:pol_x_preferred":[
        "Lenino"
    ],
    "name:rus_x_preferred":[
        "\u041b\u0435\u043d\u0438\u043d\u043e"
    ],
    "name:srp_x_preferred":[
        "\u041b\u0435\u045a\u0438\u043d\u043e"
    ],
    "name:ukr_x_preferred":[
        "\u041b\u0435\u043d\u0456\u043d\u043e"
    ],
    "wof:name":"Lenino",
    "wof:placetype":"locality"
},
  "geometry": {"coordinates":[65.42171999999999,52.52279],"type":"Point"}
}