{
  "type": "Feature",
  "properties": {
    "gn:admin1_code":"0.0",
    "gn:asciiname":"Karakuduk",
    "gn:country_code":"KZ",
    "gn:dem":89,
    "gn:feature_class":"P",
    "gn:feature_code":"PPL",
    "gn:name":"Karakuduk",
    "gn:population":0,
    "gn:timezone":"Asia/Almaty",
    "iso:country":"KZ",
    "name:eng_x_preferred":[
        "Karakuduk"
    ],
    "name:rus_x_preferred":[
        "\u041a\u0430\u0440\u0430-\u041a\u0443\u0434\u044b\u043a"
    ],
    "wof:name":"Karakuduk",
    "wof:placetype":"locality"
},
  "geometry": {"coordinates":[63.34556,49.26083],"type":"Point"}
}