{
  "type": "Feature",
  "properties": {
    "gn:admin1_code":"10.0",
    "gn:asciiname":"Mirzatay",
    "gn:country_code":"KZ",
    "gn:dem":322,
    "gn:feature_class":"P",
    "gn:feature_code":"PPL",
    "gn:name":"Mirzatay",
    "gn:population":0,
    "gn:timezone":"Asia/Almaty",
    "iso:country":"KZ",
    "wof:name":"Mirzatay",
    "wof:placetype":"locality"
},
  "geometry": {"coordinates":[68.84999999999999,41.25],"type":"Point"}
}