{
  "type": "Feature",
  "properties": {
    "gn:admin1_code":"0.0",
    "gn:asciiname":"Kerey",
    "gn:country_code":"KZ",
    "gn:dem":1,
    "gn:feature_class":"P",
    "gn:feature_code":"PPL",
    "gn:name":"Kerey",
    "gn:population":0,
    "gn:timezone":"Asia/Oral",
    "iso:country":"KZ",
    "name:eng_x_preferred":[
        "Kerey"
    ],
    "name:rus_x_preferred":[
        "\u041a\u0435\u0440\u0435\u0439"
    ],
    "wof:name":"Kerey",
    "wof:placetype":"locality"
},
  "geometry": {"coordinates":[50.05,49.46667],"type":"Point"}
}