{
  "type": "Feature",
  "properties": {
    "gn:admin1_code":"4.0",
    "gn:asciiname":"Tolybay",
    "gn:country_code":"KZ",
    "gn:dem":178,
    "gn:feature_class":"P",
    "gn:feature_code":"PPL",
    "gn:name":"Tolybay",
    "gn:population":0,
    "gn:timezone":"Asia/Aqtobe",
    "iso:country":"KZ",
    "wof:name":"Tolybay",
    "wof:placetype":"locality"
},
  "geometry": {"coordinates":[62.31667,50.51667],"type":"Point"}
}