{
  "type": "Feature",
  "properties": {
    "gn:admin1_code":"16.0",
    "gn:asciiname":"Nezhdanovka",
    "gn:country_code":"KZ",
    "gn:dem":202,
    "gn:feature_class":"P",
    "gn:feature_code":"PPL",
    "gn:name":"Nezhdanovka",
    "gn:population":0,
    "gn:timezone":"Asia/Almaty",
    "iso:country":"KZ",
    "name:eng_x_preferred":[
        "Nezhdanovka"
    ],
    "name:kaz_x_preferred":[
        "\u041d\u0435\u0436\u0434\u0430\u043d\u043e\u0432\u043a\u0430"
    ],
    "name:rus_x_preferred":[
        "\u041d\u0435\u0436\u0434\u0430\u043d\u043e\u0432\u043a\u0430"
    ],
    "wof:name":"Nezhdanovka",
    "wof:placetype":"locality"
},
  "geometry": {"coordinates":[67.71464,53.61747],"type":"Point"}
}