{
  "type": "Feature",
  "properties": {
    "gn:admin1_code":"0.0",
    "gn:asciiname":"Sary",
    "gn:country_code":"KZ",
    "gn:dem":58,
    "gn:feature_class":"P",
    "gn:feature_code":"PPL",
    "gn:name":"Sary",
    "gn:population":0,
    "gn:timezone":"Asia/Oral",
    "iso:country":"KZ",
    "name:fra_x_preferred":[
        "Sary"
    ],
    "wof:name":"Sary",
    "wof:placetype":"locality"
},
  "geometry": {"coordinates":[53.03333000000001,51.46667],"type":"Point"}
}