{
  "type": "Feature",
  "properties": {
    "gn:admin1_code":"10.0",
    "gn:asciiname":"Ashchykol'",
    "gn:country_code":"KZ",
    "gn:dem":240,
    "gn:feature_class":"P",
    "gn:feature_code":"PPL",
    "gn:name":"Ashchykol\u2019",
    "gn:population":0,
    "gn:timezone":"Asia/Almaty",
    "iso:country":"KZ",
    "name:kau_x_preferred":[
        "\u0410\u0449\u044b\u043a\u04e9\u043b"
    ],
    "name:kaz_x_preferred":[
        "Ashchyk\u00f6l"
    ],
    "name:rus_x_preferred":[
        "\u0410\u0449\u044b\u043a\u043e\u043b\u044c"
    ],
    "name:und_x_variant":[
        "Bashtul\u2019",
        "Ashchykol\u2019"
    ],
    "wof:name":"Ashchykol'",
    "wof:placetype":"locality"
},
  "geometry": {"coordinates":[68.15971999999999,41.42],"type":"Point"}
}