{
  "type": "Feature",
  "properties": {
    "gn:admin1_code":"3.0",
    "gn:asciiname":"Dorofeyevka",
    "gn:country_code":"KZ",
    "gn:dem":335,
    "gn:feature_class":"P",
    "gn:feature_code":"PPL",
    "gn:name":"Dorofeyevka",
    "gn:population":0,
    "gn:timezone":"Asia/Almaty",
    "iso:country":"KZ",
    "name:eng_x_preferred":[
        "Dorofeyevka"
    ],
    "name:kaz_x_preferred":[
        "Dorofeevka"
    ],
    "name:kaz_x_variant":[
        "\u0414\u043e\u0440\u043e\u0444\u0435\u0435\u0432\u043a\u0430"
    ],
    "name:rus_x_preferred":[
        "\u0414\u043e\u0440\u043e\u0444\u0435\u0435\u0432\u043a\u0430"
    ],
    "wof:name":"Dorofeyevka",
    "wof:placetype":"locality"
},
  "geometry": {"coordinates":[70.08504000000001,53.06773000000001],"type":"Point"}
}