{
  "type": "Feature",
  "properties": {
    "gn:admin1_code":"15.0",
    "gn:asciiname":"Uzynbulaq",
    "gn:country_code":"KZ",
    "gn:dem":591,
    "gn:feature_class":"P",
    "gn:feature_code":"PPL",
    "gn:name":"Uzynbulaq",
    "gn:population":0,
    "gn:timezone":"Asia/Almaty",
    "iso:country":"KZ",
    "name:eng_x_preferred":[
        "Uzunbulak"
    ],
    "name:kaz_x_preferred":[
        "Uzynbulaq"
    ],
    "name:msa_x_preferred":[
        "Uzynbulaq"
    ],
    "name:rus_x_preferred":[
        "\u0423\u0437\u0443\u043d\u0431\u0443\u043b\u0430\u043a"
    ],
    "name:und_x_variant":[
        "Tyulengut",
        "Uzynbulak",
        "Uzynbulakskiy",
        "Uzunbulak"
    ],
    "wof:name":"Uzynbulaq",
    "wof:placetype":"locality"
},
  "geometry": {"coordinates":[82.35863000000001,48.62303],"type":"Point"}
}