{
  "type": "Feature",
  "properties": {
    "gn:admin1_code":"15.0",
    "gn:asciiname":"Sarapan",
    "gn:country_code":"KZ",
    "gn:dem":282,
    "gn:feature_class":"P",
    "gn:feature_code":"PPL",
    "gn:name":"Sarapan",
    "gn:population":0,
    "gn:timezone":"Asia/Almaty",
    "iso:country":"KZ",
    "name:eng_x_preferred":[
        "Sarapan"
    ],
    "name:rus_x_preferred":[
        "\u0411\u0430\u0439\u0436\u0443\u043c\u0430\u0448"
    ],
    "name:und_x_variant":[
        "Bayzhumash",
        "Sarapan"
    ],
    "wof:name":"Sarapan",
    "wof:placetype":"locality"
},
  "geometry": {"coordinates":[79.13582,50.02679000000001],"type":"Point"}
}