{
  "type": "Feature",
  "properties": {
    "gn:admin1_code":"12.0",
    "gn:asciiname":"Zhylandy",
    "gn:country_code":"KZ",
    "gn:dem":577,
    "gn:feature_class":"P",
    "gn:feature_code":"PPL",
    "gn:name":"Zhylandy",
    "gn:population":0,
    "gn:timezone":"Asia/Almaty",
    "iso:country":"KZ",
    "name:kaz_x_preferred":[
        "Zhylandy"
    ],
    "name:kaz_x_variant":[
        "\u0416\u044b\u043b\u0430\u043d\u0434\u044b"
    ],
    "name:und_x_variant":[
        "Dzhelandy",
        "Zhelandy"
    ],
    "wof:name":"Zhylandy",
    "wof:placetype":"locality"
},
  "geometry": {"coordinates":[72.40855999999999,48.53533],"type":"Point"}
}