{
  "type": "Feature",
  "properties": {
    "gn:admin1_code":"10.0",
    "gn:asciiname":"Uzynaryk",
    "gn:country_code":"KZ",
    "gn:dem":1051,
    "gn:feature_class":"P",
    "gn:feature_code":"PPL",
    "gn:name":"Uzynaryk",
    "gn:population":0,
    "gn:timezone":"Asia/Almaty",
    "iso:country":"KZ",
    "name:rus_x_preferred":[
        "\u0423\u0437\u044b\u043d\u0430\u0440\u044b\u043a"
    ],
    "wof:name":"Uzynaryk",
    "wof:placetype":"locality"
},
  "geometry": {"coordinates":[70.0788,42.23637],"type":"Point"}
}