{
  "type": "Feature",
  "properties": {
    "gn:admin1_code":"4.0",
    "gn:asciiname":"Altykiben",
    "gn:country_code":"KZ",
    "gn:dem":201,
    "gn:feature_class":"P",
    "gn:feature_code":"PPL",
    "gn:name":"Altykiben",
    "gn:population":0,
    "gn:timezone":"Asia/Aqtobe",
    "iso:country":"KZ",
    "wof:name":"Altykiben",
    "wof:placetype":"locality"
},
  "geometry": {"coordinates":[61.86666999999999,50.18333],"type":"Point"}
}