{
  "type": "Feature",
  "properties": {
    "gn:admin1_code":"3.0",
    "gn:asciiname":"Kar'yer",
    "gn:country_code":"KZ",
    "gn:dem":237,
    "gn:feature_class":"P",
    "gn:feature_code":"PPL",
    "gn:name":"Kar\u2019yer",
    "gn:population":0,
    "gn:timezone":"Asia/Almaty",
    "iso:country":"KZ",
    "name:rus_x_preferred":[
        "Kar\u2019yer"
    ],
    "wof:name":"Kar'yer",
    "wof:placetype":"locality"
},
  "geometry": {"coordinates":[66.28333000000001,52.01667],"type":"Point"}
}