{
  "type": "Feature",
  "properties": {
    "gn:admin1_code":"10.0",
    "gn:asciiname":"Zharyqbas",
    "gn:country_code":"KZ",
    "gn:dem":590,
    "gn:feature_class":"P",
    "gn:feature_code":"PPL",
    "gn:name":"Zharyqbas",
    "gn:population":0,
    "gn:timezone":"Asia/Almaty",
    "iso:country":"KZ",
    "name:kaz_x_preferred":[
        "Zharyqbas"
    ],
    "name:kaz_x_variant":[
        "\u0416\u0430\u0440\u044b\u049b\u0431\u0430\u0441"
    ],
    "name:rus_x_preferred":[
        "Leont\u2019yevka"
    ],
    "name:rus_x_variant":[
        "\u041b\u0435\u043e\u043d\u0442\u044c\u0435\u0432\u043a\u0430"
    ],
    "wof:name":"Zharyqbas",
    "wof:placetype":"locality"
},
  "geometry": {"coordinates":[69.85370999999999,43.04517],"type":"Point"}
}