{
  "type": "Feature",
  "properties": {
    "gn:admin1_code":"0.0",
    "gn:asciiname":"Urumbay",
    "gn:country_code":"KZ",
    "gn:dem":179,
    "gn:feature_class":"P",
    "gn:feature_code":"PPL",
    "gn:name":"Urumbay",
    "gn:population":0,
    "gn:timezone":"Asia/Almaty",
    "iso:country":"KZ",
    "wof:name":"Urumbay",
    "wof:placetype":"locality"
},
  "geometry": {"coordinates":[78.63333,50.91667],"type":"Point"}
}