{
  "type": "Feature",
  "properties": {
    "gn:admin1_code":"4.0",
    "gn:asciiname":"Zhaksykol'",
    "gn:country_code":"KZ",
    "gn:dem":47,
    "gn:feature_class":"P",
    "gn:feature_code":"PPL",
    "gn:name":"Zhaksykol\u2019",
    "gn:population":0,
    "gn:timezone":"Asia/Aqtobe",
    "iso:country":"KZ",
    "name:eng_x_preferred":[
        "Zhaksykol'"
    ],
    "name:rus_x_preferred":[
        "\u0416\u0430\u043a\u0441\u044b\u043a\u043e\u043b\u044c"
    ],
    "name:und_x_variant":[
        "Zhaksykol\u2019"
    ],
    "wof:name":"Zhaksykol'",
    "wof:placetype":"locality"
},
  "geometry": {"coordinates":[53.80374000000001,49.47321],"type":"Point"}
}