{
  "type": "Feature",
  "properties": {
    "gn:admin1_code":"14.0",
    "gn:asciiname":"Orkendy",
    "gn:country_code":"KZ",
    "gn:dem":60,
    "gn:feature_class":"P",
    "gn:feature_code":"PPL",
    "gn:name":"Orkendy",
    "gn:population":0,
    "gn:timezone":"Asia/Qyzylorda",
    "iso:country":"KZ",
    "wof:name":"Orkendy",
    "wof:placetype":"locality"
},
  "geometry": {"coordinates":[61.88333000000001,45.58333],"type":"Point"}
}