{
  "type": "Feature",
  "properties": {
    "gn:admin1_code":"4.0",
    "gn:asciiname":"Babatay",
    "gn:country_code":"KZ",
    "gn:dem":117,
    "gn:feature_class":"P",
    "gn:feature_code":"PPL",
    "gn:name":"Babatay",
    "gn:population":0,
    "gn:timezone":"Asia/Aqtobe",
    "iso:country":"KZ",
    "name:eng_x_preferred":[
        "Babatay"
    ],
    "name:rus_x_preferred":[
        "\u0411\u0430\u0431\u0430\u0442\u0430\u0439"
    ],
    "name:und_x_variant":[
        "Bobatay",
        "Babatay"
    ],
    "wof:name":"Babatay",
    "wof:placetype":"locality"
},
  "geometry": {"coordinates":[55.66667,49.28333],"type":"Point"}
}