{
  "type": "Feature",
  "properties": {
    "gn:admin1_code":"13.0",
    "gn:asciiname":"Sasyksor",
    "gn:country_code":"KZ",
    "gn:dem":161,
    "gn:feature_class":"P",
    "gn:feature_code":"PPL",
    "gn:name":"Sasyksor",
    "gn:population":0,
    "gn:timezone":"Asia/Almaty",
    "iso:country":"KZ",
    "wof:name":"Sasyksor",
    "wof:placetype":"locality"
},
  "geometry": {"coordinates":[62.75119,50.34829000000001],"type":"Point"}
}