{
  "type": "Feature",
  "properties": {
    "gn:admin1_code":"3.0",
    "gn:asciiname":"Qaynar",
    "gn:country_code":"KZ",
    "gn:dem":285,
    "gn:feature_class":"P",
    "gn:feature_code":"PPL",
    "gn:name":"Qaynar",
    "gn:population":0,
    "gn:timezone":"Asia/Almaty",
    "iso:country":"KZ",
    "name:und_x_variant":[
        "Kaynarskiy",
        "Kaynarskoye",
        "Qaynar"
    ],
    "wof:name":"Qaynar",
    "wof:placetype":"locality"
},
  "geometry": {"coordinates":[69.24164,51.57622],"type":"Point"}
}