{
  "type": "Feature",
  "properties": {
    "gn:admin1_code":"0.0",
    "gn:asciiname":"Chistopol'ka",
    "gn:country_code":"KZ",
    "gn:dem":735,
    "gn:feature_class":"P",
    "gn:feature_code":"PPL",
    "gn:name":"Chistopol\u2019ka",
    "gn:population":0,
    "gn:timezone":"Asia/Almaty",
    "iso:country":"KZ",
    "wof:name":"Chistopol'ka",
    "wof:placetype":"locality"
},
  "geometry": {"coordinates":[83.41365999999999,49.85101],"type":"Point"}
}