{
  "type": "Feature",
  "properties": {
    "gn:admin1_code":"0.0",
    "gn:asciiname":"Borbas",
    "gn:country_code":"KZ",
    "gn:dem":35,
    "gn:feature_class":"P",
    "gn:feature_code":"PPL",
    "gn:name":"Borbas",
    "gn:population":0,
    "gn:timezone":"Asia/Oral",
    "iso:country":"KZ",
    "name:und_x_variant":[
        "Burbas",
        "Borbas"
    ],
    "wof:name":"Borbas",
    "wof:placetype":"locality"
},
  "geometry": {"coordinates":[52.34476,50.43039],"type":"Point"}
}