{
  "type": "Feature",
  "properties": {
    "gn:admin1_code":"16.0",
    "gn:asciiname":"Sardonnikovo",
    "gn:country_code":"KZ",
    "gn:dem":174,
    "gn:feature_class":"P",
    "gn:feature_code":"PPL",
    "gn:name":"Sardonnikovo",
    "gn:population":0,
    "gn:timezone":"Asia/Almaty",
    "iso:country":"KZ",
    "name:rus_x_preferred":[
        "\u0421\u0430\u0440\u0434\u043e\u043d\u043d\u0438\u043a\u043e\u0432\u043e"
    ],
    "wof:name":"Sardonnikovo",
    "wof:placetype":"locality"
},
  "geometry": {"coordinates":[67.72863000000001,53.85021],"type":"Point"}
}