{
  "type": "Feature",
  "properties": {
    "gn:admin1_code":"0.0",
    "gn:asciiname":"Antropov",
    "gn:country_code":"KZ",
    "gn:dem":13,
    "gn:feature_class":"P",
    "gn:feature_code":"PPL",
    "gn:name":"Antropov",
    "gn:population":0,
    "gn:timezone":"Asia/Oral",
    "iso:country":"KZ",
    "wof:name":"Antropov",
    "wof:placetype":"locality"
},
  "geometry": {"coordinates":[51.01667,50.26667],"type":"Point"}
}