{
  "type": "Feature",
  "properties": {
    "gn:admin1_code":"0.0",
    "gn:asciiname":"Mukashev",
    "gn:country_code":"KZ",
    "gn:dem":26,
    "gn:feature_class":"P",
    "gn:feature_code":"PPL",
    "gn:name":"Mukashev",
    "gn:population":0,
    "gn:timezone":"Asia/Oral",
    "iso:country":"KZ",
    "wof:name":"Mukashev",
    "wof:placetype":"locality"
},
  "geometry": {"coordinates":[46.98333,49.46667],"type":"Point"}
}