{
  "type": "Feature",
  "properties": {
    "gn:admin1_code":"6.0",
    "gn:asciiname":"Akshilik",
    "gn:country_code":"KZ",
    "gn:dem":134,
    "gn:feature_class":"P",
    "gn:feature_code":"PPL",
    "gn:name":"Akshilik",
    "gn:population":0,
    "gn:timezone":"Asia/Atyrau",
    "iso:country":"KZ",
    "name:und_x_variant":[
        "Ak-Chilik",
        "Akshilik"
    ],
    "wof:name":"Akshilik",
    "wof:placetype":"locality"
},
  "geometry": {"coordinates":[54.86666999999999,47.95],"type":"Point"}
}