{
  "type": "Feature",
  "properties": {
    "gn:admin1_code":"12.0",
    "gn:asciiname":"Kyzylzhuldyz",
    "gn:country_code":"KZ",
    "gn:dem":386,
    "gn:feature_class":"P",
    "gn:feature_code":"PPL",
    "gn:name":"Kyzylzhuldyz",
    "gn:population":0,
    "gn:timezone":"Asia/Almaty",
    "iso:country":"KZ",
    "name:und_x_variant":[
        "Kyzylzhulduz",
        "Kyzylzhuldyz"
    ],
    "wof:name":"Kyzylzhuldyz",
    "wof:placetype":"locality"
},
  "geometry": {"coordinates":[71.49162,50.39476],"type":"Point"}
}