{
  "type": "Feature",
  "properties": {
    "gn:admin1_code":"1.0",
    "gn:asciiname":"Kol'di",
    "gn:country_code":"KZ",
    "gn:dem":533,
    "gn:feature_class":"P",
    "gn:feature_code":"PPL",
    "gn:name":"Kol\u2019di",
    "gn:population":0,
    "gn:timezone":"Asia/Almaty",
    "iso:country":"KZ",
    "name:rus_x_preferred":[
        "Kol\u2019di"
    ],
    "name:rus_x_variant":[
        "\u041a\u043e\u043b\u044c\u0434\u0438"
    ],
    "wof:name":"Kol'di",
    "wof:placetype":"locality"
},
  "geometry": {"coordinates":[77.88479,43.61133],"type":"Point"}
}