{
  "type": "Feature",
  "properties": {
    "gn:admin1_code":"16.0",
    "gn:asciiname":"Zhana-Tlek",
    "gn:country_code":"KZ",
    "gn:dem":130,
    "gn:feature_class":"P",
    "gn:feature_code":"PPL",
    "gn:name":"Zhana-Tlek",
    "gn:population":0,
    "gn:timezone":"Asia/Almaty",
    "iso:country":"KZ",
    "wof:name":"Zhana-Tlek",
    "wof:placetype":"locality"
},
  "geometry": {"coordinates":[70.34999999999999,54.61666999999999],"type":"Point"}
}