{
  "type": "Feature",
  "properties": {
    "gn:admin1_code":"11.0",
    "gn:asciiname":"Tikhomirovka",
    "gn:country_code":"KZ",
    "gn:dem":106,
    "gn:feature_class":"P",
    "gn:feature_code":"PPL",
    "gn:name":"Tikhomirovka",
    "gn:population":0,
    "gn:timezone":"Asia/Almaty",
    "iso:country":"KZ",
    "name:eng_x_preferred":[
        "Tikhomirovka"
    ],
    "name:kaz_x_preferred":[
        "T\u012bkhom\u012brovka"
    ],
    "name:kaz_x_variant":[
        "\u0422\u0438\u0445\u043e\u043c\u0438\u0440\u043e\u0432\u043a\u0430"
    ],
    "name:rus_x_preferred":[
        "\u0422\u0438\u0445\u043e\u043c\u0438\u0440\u043e\u0432\u043a\u0430"
    ],
    "name:und_x_variant":[
        "Tikhanovka",
        "Tikhomirovka"
    ],
    "wof:name":"Tikhomirovka",
    "wof:placetype":"locality"
},
  "geometry": {"coordinates":[76.03820999999998,53.29042],"type":"Point"}
}