{
  "type": "Feature",
  "properties": {
    "gn:admin1_code":"11.0",
    "gn:asciiname":"Tursumbay",
    "gn:country_code":"KZ",
    "gn:dem":105,
    "gn:feature_class":"P",
    "gn:feature_code":"PPL",
    "gn:name":"Tursumbay",
    "gn:population":0,
    "gn:timezone":"Asia/Almaty",
    "iso:country":"KZ",
    "name:rus_x_preferred":[
        "\u0422\u0443\u0440\u0441\u0443\u043c\u0431\u0430\u0439"
    ],
    "wof:name":"Tursumbay",
    "wof:placetype":"locality"
},
  "geometry": {"coordinates":[75.59,53.83394000000001],"type":"Point"}
}