{
  "type": "Feature",
  "properties": {
    "gn:admin1_code":"0.0",
    "gn:asciiname":"Dushman",
    "gn:cc2":"KZ",
    "gn:country_code":"KZ",
    "gn:dem":10,
    "gn:feature_class":"P",
    "gn:feature_code":"PPL",
    "gn:name":"Dushman",
    "gn:population":0,
    "gn:timezone":"Asia/Oral",
    "iso:country":"KZ",
    "name:deu_x_preferred":[
        "Dushman"
    ],
    "name:hin_x_preferred":[
        "\u0926\u0941\u0936\u094d\u092e\u0928"
    ],
    "name:und_x_variant":[
        "Dosman",
        "Dushman"
    ],
    "wof:name":"Dushman",
    "wof:placetype":"locality"
},
  "geometry": {"coordinates":[52.01667,49.36667],"type":"Point"}
}