{
  "type": "Feature",
  "properties": {
    "gn:admin1_code":"7.0",
    "gn:asciiname":"Semiglavyy Mar",
    "gn:country_code":"KZ",
    "gn:dem":133,
    "gn:feature_class":"P",
    "gn:feature_code":"PPL",
    "gn:name":"Sem\u012bglavyy Mar",
    "gn:population":0,
    "gn:timezone":"Asia/Oral",
    "iso:country":"KZ",
    "name:eng_x_preferred":[
        "Sem\u012bglavyy Mar"
    ],
    "name:rus_x_preferred":[
        "\u0421\u0435\u043c\u0438\u0433\u043b\u0430\u0432\u044b\u0439_\u043c\u0430\u0440"
    ],
    "name:und_x_variant":[
        "Semiglavy Mar",
        "Semiglavi Mar",
        "Sem\u012bglavyy Mar"
    ],
    "wof:name":"Semiglavyy Mar",
    "wof:placetype":"locality"
},
  "geometry": {"coordinates":[50.05853,51.19653],"type":"Point"}
}