{
  "type": "Feature",
  "properties": {
    "gn:admin1_code":"7.0",
    "gn:asciiname":"Shoptykol'",
    "gn:country_code":"KZ",
    "gn:dem":37,
    "gn:feature_class":"P",
    "gn:feature_code":"PPL",
    "gn:name":"Shoptykol\u2019",
    "gn:population":0,
    "gn:timezone":"Asia/Oral",
    "iso:country":"KZ",
    "name:eng_x_preferred":[
        "Shoptykol'"
    ],
    "name:rus_x_preferred":[
        "\u0428\u043e\u043f\u0442\u044b\u043a\u043e\u043b\u044c"
    ],
    "name:und_x_variant":[
        "Shoptykol\u2019"
    ],
    "wof:name":"Shoptykol'",
    "wof:placetype":"locality"
},
  "geometry": {"coordinates":[53.48322,49.70452],"type":"Point"}
}