{
  "type": "Feature",
  "properties": {
    "gn:admin1_code":"17.0",
    "gn:asciiname":"Kurazaty",
    "gn:country_code":"KZ",
    "gn:dem":602,
    "gn:feature_class":"P",
    "gn:feature_code":"PPL",
    "gn:name":"Kurazaty",
    "gn:population":0,
    "gn:timezone":"Asia/Almaty",
    "iso:country":"KZ",
    "name:rus_x_preferred":[
        "\u041a\u0443\u0440\u0430\u0437\u0430\u0442\u044b"
    ],
    "wof:name":"Kurazaty",
    "wof:placetype":"locality"
},
  "geometry": {"coordinates":[72.99351,43.10339000000001],"type":"Point"}
}