{
  "type": "Feature",
  "properties": {
    "gn:admin1_code":"15.0",
    "gn:asciiname":"Zhernovka",
    "gn:country_code":"KZ",
    "gn:dem":339,
    "gn:feature_class":"P",
    "gn:feature_code":"PPL",
    "gn:name":"Zhernovka",
    "gn:population":0,
    "gn:timezone":"Asia/Almaty",
    "iso:country":"KZ",
    "name:eng_x_preferred":[
        "Zhernovka"
    ],
    "name:rus_x_preferred":[
        "\u0416\u0435\u0440\u043d\u043e\u0432\u043a\u0430"
    ],
    "name:und_x_variant":[
        "Zhernovskoe"
    ],
    "wof:name":"Zhernovka",
    "wof:placetype":"locality"
},
  "geometry": {"coordinates":[81.11444,50.51713],"type":"Point"}
}