{
  "type": "Feature",
  "properties": {
    "iso:country":"KZ",
    "name:kaz_x_preferred":[
        "Novodol\u012bnsk\u012by"
    ],
    "name:kaz_x_variant":[
        "\u041d\u043e\u0432\u043e\u0434\u043e\u043b\u0438\u043d\u0441\u043a\u0438\u0439"
    ],
    "qs:gn_country":"KZ",
    "qs:gn_fcode":"PPL",
    "qs:gn_pop":5167,
    "qs:name":"Novodolinskiy",
    "qs:name_adm0":"Kazakhstan",
    "qs:name_adm1":"Qaraghandy",
    "qs:photos":0,
    "qs:photos_1k":0,
    "qs:photos_9k":1,
    "qs:photos_9r":1,
    "qs:photos_all":1,
    "qs:photos_sr":0,
    "qs:placetype":"Town",
    "qs:pop_sr":"5",
    "qs:woe_adm0":23424871,
    "wof:name":"Novodolinskiy",
    "wof:placetype":"locality",
    "wof:population":5167
},
  "geometry": {"coordinates":[72.70807000000001,49.7065],"type":"Point"}
}