{
  "type": "Feature",
  "properties": {
    "gn:admin1_code":"0.0",
    "gn:asciiname":"Tobishek",
    "gn:country_code":"KZ",
    "gn:dem":143,
    "gn:feature_class":"P",
    "gn:feature_code":"PPL",
    "gn:name":"Tobishek",
    "gn:population":0,
    "gn:timezone":"Asia/Almaty",
    "iso:country":"KZ",
    "wof:name":"Tobishek",
    "wof:placetype":"locality"
},
  "geometry": {"coordinates":[78.40000000000001,52.15],"type":"Point"}
}