{
  "type": "Feature",
  "properties": {
    "gn:admin1_code":"12.0",
    "gn:asciiname":"Aqbulaq",
    "gn:country_code":"KZ",
    "gn:dem":436,
    "gn:feature_class":"P",
    "gn:feature_code":"PPL",
    "gn:name":"Aqbulaq",
    "gn:population":0,
    "gn:timezone":"Asia/Almaty",
    "iso:country":"KZ",
    "name:kaz_x_preferred":[
        "Aqbulaq"
    ],
    "name:kaz_x_variant":[
        "\u0410\u049b\u0431\u04b1\u043b\u0430\u049b"
    ],
    "wof:name":"Aqbulaq",
    "wof:placetype":"locality"
},
  "geometry": {"coordinates":[73.54441,50.7284],"type":"Point"}
}