{
  "type": "Feature",
  "properties": {
    "gn:admin1_code":"0.0",
    "gn:asciiname":"Barambay",
    "gn:country_code":"KZ",
    "gn:dem":105,
    "gn:feature_class":"P",
    "gn:feature_code":"PPL",
    "gn:name":"Barambay",
    "gn:population":0,
    "gn:timezone":"Asia/Oral",
    "iso:country":"KZ",
    "wof:name":"Barambay",
    "wof:placetype":"locality"
},
  "geometry": {"coordinates":[53.8013,50.15952],"type":"Point"}
}