{
  "type": "Feature",
  "properties": {
    "gn:admin1_code":"1.0",
    "gn:asciiname":"Obukhovka",
    "gn:country_code":"KZ",
    "gn:dem":380,
    "gn:feature_class":"P",
    "gn:feature_code":"PPL",
    "gn:name":"Ob\u016bkhovka",
    "gn:population":0,
    "gn:timezone":"Asia/Almaty",
    "iso:country":"KZ",
    "name:und_x_variant":[
        "Obukhovskoye",
        "Ob\u016bkhovka"
    ],
    "wof:name":"Obukhovka",
    "wof:placetype":"locality"
},
  "geometry": {"coordinates":[81.09874000000001,46.19076],"type":"Point"}
}