{
  "type": "Feature",
  "properties": {
    "gn:admin1_code":"11.0",
    "gn:asciiname":"Novyy Zhosaly",
    "gn:country_code":"KZ",
    "gn:dem":584,
    "gn:feature_class":"P",
    "gn:feature_code":"PPL",
    "gn:name":"Novyy Zhosaly",
    "gn:population":0,
    "gn:timezone":"Asia/Almaty",
    "iso:country":"KZ",
    "name:rus_x_preferred":[
        "\u041d\u043e\u0432\u044b\u0439 \u0416\u043e\u0441\u0430\u043b\u044b"
    ],
    "name:und_x_variant":[
        "Zhosalinskiy"
    ],
    "wof:name":"Novyy Zhosaly",
    "wof:placetype":"locality"
},
  "geometry": {"coordinates":[76.1891,50.42602],"type":"Point"}
}