{
  "type": "Feature",
  "properties": {
    "gn:admin1_code":"0.0",
    "gn:asciiname":"Burly-Agach",
    "gn:country_code":"KZ",
    "gn:dem":420,
    "gn:feature_class":"P",
    "gn:feature_code":"PPL",
    "gn:name":"Burly-Agach",
    "gn:population":0,
    "gn:timezone":"Asia/Almaty",
    "iso:country":"KZ",
    "name:eng_x_preferred":[
        "Burly-Agach"
    ],
    "name:rus_x_preferred":[
        "\u0411\u0443\u0440\u043b\u044b\u0430\u0433\u0430\u0448"
    ],
    "wof:name":"Burly-Agach",
    "wof:placetype":"locality"
},
  "geometry": {"coordinates":[81.51614000000002,49.27954],"type":"Point"}
}