{
  "type": "Feature",
  "properties": {
    "gn:admin1_code":"15.0",
    "gn:asciiname":"Shugla",
    "gn:country_code":"KZ",
    "gn:dem":721,
    "gn:feature_class":"P",
    "gn:feature_code":"PPL",
    "gn:name":"Shugla",
    "gn:population":0,
    "gn:timezone":"Asia/Almaty",
    "iso:country":"KZ",
    "name:rus_x_preferred":[
        "\u0428\u0443\u0433\u043b\u0430"
    ],
    "wof:name":"Shugla",
    "wof:placetype":"locality"
},
  "geometry": {"coordinates":[79.87615,48.41205],"type":"Point"}
}