{
  "type": "Feature",
  "properties": {
    "gn:admin1_code":"13.0",
    "gn:asciiname":"Lenino",
    "gn:country_code":"KZ",
    "gn:dem":176,
    "gn:feature_class":"P",
    "gn:feature_code":"PPL",
    "gn:name":"Lenino",
    "gn:population":0,
    "gn:timezone":"Asia/Qyzylorda",
    "iso:country":"KZ",
    "name:eng_x_preferred":[
        "Lenino"
    ],
    "name:kaz_x_preferred":[
        "Len\u012bno"
    ],
    "name:kaz_x_variant":[
        "\u041b\u0435\u043d\u0438\u043d\u043e"
    ],
    "name:rus_x_preferred":[
        "\u0411\u0430\u0439\u0433\u043e\u0440\u0430"
    ],
    "name:und_x_variant":[
        "Imeni Lenina",
        "Baygara",
        "Baykara",
        "Baygora",
        "Lenino"
    ],
    "wof:name":"Lenino",
    "wof:placetype":"locality"
},
  "geometry": {"coordinates":[63.27611,53.98725],"type":"Point"}
}