{
  "type": "Feature",
  "properties": {
    "gn:admin1_code":"3.0",
    "gn:asciiname":"Boztal",
    "gn:country_code":"KZ",
    "gn:dem":315,
    "gn:feature_class":"P",
    "gn:feature_code":"PPL",
    "gn:name":"Boztal",
    "gn:population":0,
    "gn:timezone":"Asia/Almaty",
    "iso:country":"KZ",
    "name:kaz_x_preferred":[
        "Boztal"
    ],
    "name:kaz_x_variant":[
        "\u0411\u043e\u0437\u0442\u0430\u043b"
    ],
    "wof:name":"Boztal",
    "wof:placetype":"locality"
},
  "geometry": {"coordinates":[73.81062,51.53717],"type":"Point"}
}