{
  "type": "Feature",
  "properties": {
    "gn:admin1_code":"13.0",
    "gn:asciiname":"Tavrichenka",
    "gn:country_code":"KZ",
    "gn:dem":260,
    "gn:feature_class":"P",
    "gn:feature_code":"PPL",
    "gn:name":"Tavrichenka",
    "gn:population":0,
    "gn:timezone":"Asia/Qyzylorda",
    "iso:country":"KZ",
    "name:eng_x_preferred":[
        "Tavrichenka"
    ],
    "name:kaz_x_preferred":[
        "Tavr\u012bchenka"
    ],
    "name:kaz_x_variant":[
        "\u0422\u0430\u0432\u0440\u0438\u0447\u0435\u043d\u043a\u0430"
    ],
    "name:rus_x_preferred":[
        "\u0422\u0430\u0432\u0440\u0438\u0447\u0435\u043d\u043a\u0430"
    ],
    "name:und_x_variant":[
        "Tavricheskiy",
        "Tavrichenka"
    ],
    "wof:name":"Tavrichenka",
    "wof:placetype":"locality"
},
  "geometry": {"coordinates":[61.52226,52.62391],"type":"Point"}
}