{
  "type": "Feature",
  "properties": {
    "gn:admin1_code":"16.0",
    "gn:asciiname":"Kokterek",
    "gn:country_code":"KZ",
    "gn:dem":137,
    "gn:feature_class":"P",
    "gn:feature_code":"PPL",
    "gn:name":"Kokterek",
    "gn:population":0,
    "gn:timezone":"Asia/Almaty",
    "iso:country":"KZ",
    "name:eng_x_preferred":[
        "Kokterek"
    ],
    "name:kaz_x_preferred":[
        "K\u00f6kterek"
    ],
    "name:kaz_x_variant":[
        "\u041a\u04e9\u043a\u0442\u0435\u0440\u0435\u043a"
    ],
    "name:rus_x_preferred":[
        "\u041a\u043e\u043a\u0442\u0435\u0440\u0435\u043a"
    ],
    "wof:name":"Kokterek",
    "wof:placetype":"locality"
},
  "geometry": {"coordinates":[67.67438,53.96186],"type":"Point"}
}