{
  "type": "Feature",
  "properties": {
    "gn:admin1_code":"10.0",
    "gn:asciiname":"Yntaly",
    "gn:country_code":"KZ",
    "gn:dem":311,
    "gn:feature_class":"P",
    "gn:feature_code":"PPL",
    "gn:name":"Yntaly",
    "gn:population":0,
    "gn:timezone":"Asia/Almaty",
    "iso:country":"KZ",
    "name:kaz_x_preferred":[
        "\u042b\u043d\u0442\u0430\u043b\u044b"
    ],
    "name:und_x_variant":[
        "Intaly",
        "Yntaly"
    ],
    "wof:name":"Yntaly",
    "wof:placetype":"locality"
},
  "geometry": {"coordinates":[67.95048,43.65122],"type":"Point"}
}