{
  "type": "Feature",
  "properties": {
    "gn:admin1_code":"10.0",
    "gn:asciiname":"Yenbekshi",
    "gn:country_code":"KZ",
    "gn:dem":260,
    "gn:feature_class":"P",
    "gn:feature_code":"PPL",
    "gn:name":"Yenbekshi",
    "gn:population":0,
    "gn:timezone":"Asia/Almaty",
    "iso:country":"KZ",
    "name:uzb_x_preferred":[
        "Yenbekshi"
    ],
    "wof:name":"Yenbekshi",
    "wof:placetype":"locality"
},
  "geometry": {"coordinates":[68.51432,40.94263],"type":"Point"}
}