{
  "type": "Feature",
  "properties": {
    "gn:admin1_code":"0.0",
    "gn:asciiname":"Okhonkol'",
    "gn:country_code":"KZ",
    "gn:dem":9,
    "gn:feature_class":"P",
    "gn:feature_code":"PPL",
    "gn:name":"Okhonkol\u2019",
    "gn:population":0,
    "gn:timezone":"Asia/Oral",
    "iso:country":"KZ",
    "name:und_x_variant":[
        "Okhon-kul\u2019",
        "Okhon-Kul\u2019 Vtoroy",
        "Okhonkol\u2019"
    ],
    "wof:name":"Okhonkol'",
    "wof:placetype":"locality"
},
  "geometry": {"coordinates":[46.96667,48.93333],"type":"Point"}
}