{
  "type": "Feature",
  "properties": {
    "gn:admin1_code":"0.0",
    "gn:asciiname":"Ubinka",
    "gn:country_code":"KZ",
    "gn:dem":247,
    "gn:feature_class":"P",
    "gn:feature_code":"PPL",
    "gn:name":"Ubinka",
    "gn:population":0,
    "gn:timezone":"Asia/Almaty",
    "iso:country":"KZ",
    "name:eng_x_preferred":[
        "Ubinka"
    ],
    "name:rus_x_preferred":[
        "\u0423\u0431\u0438\u043d\u043a\u0430"
    ],
    "name:und_x_variant":[
        "Ubinsk Pristan",
        "Ubinskoe",
        "Ubinskoye"
    ],
    "wof:name":"Ubinka",
    "wof:placetype":"locality"
},
  "geometry": {"coordinates":[81.73493000000001,50.32268],"type":"Point"}
}