{
  "type": "Feature",
  "properties": {
    "gn:admin1_code":"13.0",
    "gn:asciiname":"Novoalekseyevka",
    "gn:country_code":"KZ",
    "gn:dem":194,
    "gn:feature_class":"P",
    "gn:feature_code":"PPL",
    "gn:name":"Novoalekseyevka",
    "gn:population":0,
    "gn:timezone":"Asia/Qyzylorda",
    "iso:country":"KZ",
    "name:eng_x_preferred":[
        "Novoalekseyevka"
    ],
    "name:kaz_x_preferred":[
        "Novoalekseevka"
    ],
    "name:kaz_x_variant":[
        "\u041d\u043e\u0432\u043e\u0430\u043b\u0435\u043a\u0441\u0435\u0435\u0432\u043a\u0430"
    ],
    "name:rus_x_preferred":[
        "\u041d\u043e\u0432\u043e\u0430\u043b\u0435\u043a\u0441\u0435\u0435\u0432\u043a\u0430"
    ],
    "name:und_x_variant":[
        "Novoalekseyevskiy"
    ],
    "wof:name":"Novoalekseyevka",
    "wof:placetype":"locality"
},
  "geometry": {"coordinates":[64.67114000000001,52.90909],"type":"Point"}
}