{
  "type": "Feature",
  "properties": {
    "gn:admin1_code":"7.0",
    "gn:asciiname":"Quraylysay",
    "gn:cc2":"KZ",
    "gn:country_code":"KZ",
    "gn:dem":14,
    "gn:feature_class":"P",
    "gn:feature_code":"PPL",
    "gn:name":"Q\u016braylysay",
    "gn:population":0,
    "gn:timezone":"Asia/Oral",
    "iso:country":"KZ",
    "name:und_x_variant":[
        "Kuraylysay",
        "Q\u016braylysay"
    ],
    "wof:name":"Quraylysay",
    "wof:placetype":"locality"
},
  "geometry": {"coordinates":[51.83361,50.11056],"type":"Point"}
}