{
  "type": "Feature",
  "properties": {
    "gn:admin1_code":"0.0",
    "gn:asciiname":"Kyzyltu",
    "gn:country_code":"KZ",
    "gn:dem":695,
    "gn:feature_class":"P",
    "gn:feature_code":"PPL",
    "gn:name":"Kyzyltu",
    "gn:population":0,
    "gn:timezone":"Asia/Almaty",
    "iso:country":"KZ",
    "wof:name":"Kyzyltu",
    "wof:placetype":"locality"
},
  "geometry": {"coordinates":[82.73333000000002,49.66667],"type":"Point"}
}