{
  "type": "Feature",
  "properties": {
    "gn:admin1_code":"15.0",
    "gn:asciiname":"Kishaul",
    "gn:country_code":"KZ",
    "gn:dem":573,
    "gn:feature_class":"P",
    "gn:feature_code":"PPL",
    "gn:name":"Kishaul",
    "gn:population":0,
    "gn:timezone":"Asia/Almaty",
    "iso:country":"KZ",
    "name:eng_x_preferred":[
        "Kishaul"
    ],
    "name:rus_x_preferred":[
        "\u041a\u0438\u0448\u0430\u0443\u043b"
    ],
    "wof:name":"Kishaul",
    "wof:placetype":"locality"
},
  "geometry": {"coordinates":[82.19694,49.6204],"type":"Point"}
}