{
  "type": "Feature",
  "properties": {
    "gn:admin1_code":"10.0",
    "gn:asciiname":"Koksayak",
    "gn:country_code":"KZ",
    "gn:dem":966,
    "gn:feature_class":"P",
    "gn:feature_code":"PPL",
    "gn:name":"Koksayak",
    "gn:population":0,
    "gn:timezone":"Asia/Almaty",
    "iso:country":"KZ",
    "name:kaz_x_preferred":[
        "K\u00f6ksayyek"
    ],
    "name:kaz_x_variant":[
        "\u041a\u04e9\u043a\u0441\u0430\u0439\u0435\u043a"
    ],
    "name:rus_x_preferred":[
        "\u041a\u043e\u043a\u0441\u0430\u044f\u043a"
    ],
    "wof:name":"Koksayak",
    "wof:placetype":"locality"
},
  "geometry": {"coordinates":[70.02542,42.24901],"type":"Point"}
}