{
  "type": "Feature",
  "properties": {
    "gn:admin1_code":"15.0",
    "gn:asciiname":"Konyrtau",
    "gn:country_code":"KZ",
    "gn:dem":864,
    "gn:feature_class":"P",
    "gn:feature_code":"PPL",
    "gn:name":"Konyrtau",
    "gn:population":0,
    "gn:timezone":"Asia/Almaty",
    "iso:country":"KZ",
    "name:kaz_x_preferred":[
        "Qongyrta\u016b"
    ],
    "name:kaz_x_variant":[
        "\u049a\u043e\u04a3\u044b\u0440\u0442\u0430\u0443"
    ],
    "name:rus_x_preferred":[
        "\u041a\u043e\u043d\u044b\u0440\u0442\u0430\u0443"
    ],
    "wof:name":"Konyrtau",
    "wof:placetype":"locality"
},
  "geometry": {"coordinates":[79.74951,48.3149],"type":"Point"}
}