{
  "type": "Feature",
  "properties": {
    "gn:admin1_code":"12.0",
    "gn:asciiname":"Qyzyltau",
    "gn:country_code":"KZ",
    "gn:dem":758,
    "gn:feature_class":"P",
    "gn:feature_code":"PPL",
    "gn:name":"Qyzylta\u016b",
    "gn:population":0,
    "gn:timezone":"Asia/Almaty",
    "iso:country":"KZ",
    "name:und_x_variant":[
        "Kyzyltau",
        "Qyzylta\u016b"
    ],
    "wof:name":"Qyzyltau",
    "wof:placetype":"locality"
},
  "geometry": {"coordinates":[72.28145000000001,47.96123],"type":"Point"}
}