{
  "type": "Feature",
  "properties": {
    "gn:admin1_code":"11.0",
    "gn:asciiname":"Sakhnovka",
    "gn:country_code":"KZ",
    "gn:dem":142,
    "gn:feature_class":"P",
    "gn:feature_code":"PPL",
    "gn:name":"Sakhnovka",
    "gn:population":0,
    "gn:timezone":"Asia/Almaty",
    "iso:country":"KZ",
    "name:eng_x_preferred":[
        "Sakhnovka"
    ],
    "name:kaz_x_preferred":[
        "\u0421\u0430\u0445\u043d\u043e\u0432\u043a\u0430"
    ],
    "name:rus_x_preferred":[
        "\u0421\u043e\u0445\u043d\u043e\u0432\u043a\u0430"
    ],
    "name:und_x_variant":[
        "Karabiday",
        "Sosnovskoye",
        "Sakhovka",
        "Sakhnovka"
    ],
    "wof:name":"Sakhnovka",
    "wof:placetype":"locality"
},
  "geometry": {"coordinates":[77.99666999999999,52.26337],"type":"Point"}
}