{
  "type": "Feature",
  "properties": {
    "gn:admin1_code":"0.0",
    "gn:asciiname":"Uzynbidaik",
    "gn:country_code":"KZ",
    "gn:dem":325,
    "gn:feature_class":"P",
    "gn:feature_code":"PPL",
    "gn:name":"Uzynbidaik",
    "gn:population":0,
    "gn:timezone":"Asia/Almaty",
    "iso:country":"KZ",
    "wof:name":"Uzynbidaik",
    "wof:placetype":"locality"
},
  "geometry": {"coordinates":[69.75,50.56667],"type":"Point"}
}