{
  "type": "Feature",
  "properties": {
    "gn:admin1_code":"12.0",
    "gn:asciiname":"Koshkarbay",
    "gn:country_code":"KZ",
    "gn:dem":661,
    "gn:feature_class":"P",
    "gn:feature_code":"PPL",
    "gn:name":"Koshkarbay",
    "gn:population":0,
    "gn:timezone":"Asia/Almaty",
    "iso:country":"KZ",
    "wof:name":"Koshkarbay",
    "wof:placetype":"locality"
},
  "geometry": {"coordinates":[73.58333,49.06667],"type":"Point"}
}