{
  "type": "Feature",
  "properties": {
    "gn:admin1_code":"6.0",
    "gn:asciiname":"Khozaul",
    "gn:country_code":"KZ",
    "gn:dem":-12,
    "gn:feature_class":"P",
    "gn:feature_code":"PPL",
    "gn:name":"Khozaul",
    "gn:population":0,
    "gn:timezone":"Asia/Atyrau",
    "iso:country":"KZ",
    "wof:name":"Khozaul",
    "wof:placetype":"locality"
},
  "geometry": {"coordinates":[51.26667,48.45],"type":"Point"}
}