{
  "type": "Feature",
  "properties": {
    "gn:admin1_code":"3.0",
    "gn:asciiname":"Qaraegin",
    "gn:country_code":"KZ",
    "gn:dem":354,
    "gn:feature_class":"P",
    "gn:feature_code":"PPL",
    "gn:name":"Qaraegin",
    "gn:population":0,
    "gn:timezone":"Asia/Almaty",
    "iso:country":"KZ",
    "name:kaz_x_preferred":[
        "Qaraegin"
    ],
    "name:und_x_variant":[
        "Kara-Yegen",
        "Karayegin"
    ],
    "wof:name":"Qaraegin",
    "wof:placetype":"locality"
},
  "geometry": {"coordinates":[70.38509999999999,50.85145],"type":"Point"}
}