{
  "type": "Feature",
  "properties": {
    "gn:admin1_code":"16.0",
    "gn:asciiname":"Kreshchenka",
    "gn:country_code":"KZ",
    "gn:dem":169,
    "gn:feature_class":"P",
    "gn:feature_code":"PPL",
    "gn:name":"Kreshchenka",
    "gn:population":0,
    "gn:timezone":"Asia/Almaty",
    "iso:country":"KZ",
    "name:bak_x_preferred":[
        "\u041a\u0440\u0435\u0449\u0435\u043d\u043a\u0430"
    ],
    "name:che_x_preferred":[
        "\u041a\u0440\u0435\u0449\u0435\u043d\u043a\u0430"
    ],
    "name:eng_x_preferred":[
        "Kreshchenka"
    ],
    "name:hye_x_preferred":[
        "\u053f\u0580\u0565\u0577\u0579\u0565\u0576\u056f\u0561"
    ],
    "name:kaz_x_preferred":[
        "\u041a\u0440\u0435\u0449\u0435\u043d\u043a\u0430"
    ],
    "name:kir_x_preferred":[
        "\u041a\u0440\u0435\u0449\u0435\u043d\u043a\u0430"
    ],
    "name:rus_x_preferred":[
        "\u041a\u0440\u0435\u0449\u0435\u043d\u043a\u0430"
    ],
    "name:tat_x_preferred":[
        "\u041a\u0440\u0435\u0449\u0435\u043d\u043a\u0430"
    ],
    "name:und_x_variant":[
        "Novokreshchenskoye"
    ],
    "wof:name":"Kreshchenka",
    "wof:placetype":"locality"
},
  "geometry": {"coordinates":[67.05619,53.42789000000001],"type":"Point"}
}