{
  "type": "Feature",
  "properties": {
    "gn:admin1_code":"13.0",
    "gn:asciiname":"Shili",
    "gn:country_code":"KZ",
    "gn:dem":210,
    "gn:feature_class":"P",
    "gn:feature_code":"PPL",
    "gn:name":"Shili",
    "gn:population":0,
    "gn:timezone":"Asia/Qyzylorda",
    "iso:country":"KZ",
    "name:ara_x_preferred":[
        "\u0634\u064a\u0644\u064a"
    ],
    "name:eng_x_preferred":[
        "Shili"
    ],
    "name:fas_x_preferred":[
        "\u0634\u06cc\u0644\u06cc"
    ],
    "name:kaz_x_preferred":[
        "Sh\u012bli"
    ],
    "name:msa_x_preferred":[
        "Shili"
    ],
    "name:rus_x_preferred":[
        "\u0428\u0438\u043b\u0438"
    ],
    "name:und_x_variant":[
        "Shiyli",
        "Shili"
    ],
    "wof:name":"Shili",
    "wof:placetype":"locality"
},
  "geometry": {"coordinates":[64.74288,51.59253],"type":"Point"}
}