{
  "type": "Feature",
  "properties": {
    "gn:admin1_code":"15.0",
    "gn:asciiname":"Saranchevo",
    "gn:country_code":"KZ",
    "gn:dem":468,
    "gn:feature_class":"P",
    "gn:feature_code":"PPL",
    "gn:name":"Saranchevo",
    "gn:population":0,
    "gn:timezone":"Asia/Almaty",
    "iso:country":"KZ",
    "name:kaz_x_preferred":[
        "Saranchevo"
    ],
    "name:kaz_x_variant":[
        "\u0421\u0430\u0440\u0430\u043d\u0447\u0435\u0432\u043e"
    ],
    "wof:name":"Saranchevo",
    "wof:placetype":"locality"
},
  "geometry": {"coordinates":[82.09857,50.42766],"type":"Point"}
}