{
  "type": "Feature",
  "properties": {
    "gn:admin1_code":"16.0",
    "gn:asciiname":"Kantemirovskoye",
    "gn:country_code":"KZ",
    "gn:dem":140,
    "gn:feature_class":"P",
    "gn:feature_code":"PPL",
    "gn:name":"Kantemirovskoye",
    "gn:population":0,
    "gn:timezone":"Asia/Almaty",
    "iso:country":"KZ",
    "name:eng_x_preferred":[
        "Kantemirovskoye"
    ],
    "name:kaz_x_preferred":[
        "Kantem\u012brovskoe"
    ],
    "name:kaz_x_variant":[
        "\u041a\u0430\u043d\u0442\u0435\u043c\u0438\u0440\u043e\u0432\u0441\u043a\u043e\u0435"
    ],
    "name:rus_x_preferred":[
        "\u041a\u0430\u043d\u0442\u0435\u043c\u0438\u0440\u043e\u0432\u0441\u043a\u043e\u0435"
    ],
    "name:und_x_variant":[
        "Kantemirovets"
    ],
    "wof:name":"Kantemirovskoye",
    "wof:placetype":"locality"
},
  "geometry": {"coordinates":[70.07586999999999,54.14382],"type":"Point"}
}