{
  "type": "Feature",
  "properties": {
    "gn:admin1_code":"12.0",
    "gn:asciiname":"Al'zhantam",
    "gn:country_code":"KZ",
    "gn:dem":599,
    "gn:feature_class":"P",
    "gn:feature_code":"PPL",
    "gn:name":"Al\u2019zhantam",
    "gn:population":0,
    "gn:timezone":"Asia/Almaty",
    "iso:country":"KZ",
    "name:rus_x_preferred":[
        "Al\u2019zhantam"
    ],
    "name:rus_x_variant":[
        "\u0410\u043b\u044c\u0436\u0430\u043d\u0442\u0430\u043c"
    ],
    "wof:name":"Al'zhantam",
    "wof:placetype":"locality"
},
  "geometry": {"coordinates":[72.56364000000001,48.52896],"type":"Point"}
}