{
  "type": "Feature",
  "properties": {
    "iso:country":"KZ",
    "ne:ADM0CAP":0.0,
    "ne:ADM0NAME":"Kazakhstan",
    "ne:ADM0_A3":"KAZ",
    "ne:ADM1NAME":"Qaraghandy",
    "ne:ADMIN1_COD":12,
    "ne:CAPALT":0,
    "ne:CHANGED":0,
    "ne:CHECKME":0,
    "ne:COMPARE":0,
    "ne:DIFFASCII":0,
    "ne:ELEVATION":0.0,
    "ne:FEATURECLA":"Populated place",
    "ne:FEATURE_CL":"P",
    "ne:FEATURE_CO":"PPLA",
    "ne:GEONAMEID":1519942,
    "ne:GEONAMESNO":"GeoNames match with ascii name + lat + long whole numbers.",
    "ne:GN_ASCII":"Qaraghandy",
    "ne:GN_POP":451800,
    "ne:GTOPO30":526.0,
    "ne:ISO_A2":"KZ",
    "ne:LABELRANK":6,
    "ne:LATITUDE":49.884977,
    "ne:LONGITUDE":73.11501,
    "ne:LS_MATCH":1,
    "ne:LS_NAME":"Qaraghandy",
    "ne:MAX_AREAKM":89.0,
    "ne:MAX_AREAMI":34.0,
    "ne:MAX_BBXMAX":73.166667,
    "ne:MAX_BBXMIN":73.033333,
    "ne:MAX_BBYMAX":49.891667,
    "ne:MAX_BBYMIN":49.733333,
    "ne:MAX_NATSCA":100.0,
    "ne:MAX_PERKM":99.0,
    "ne:MAX_PERMI":62.0,
    "ne:MAX_POP10":304747,
    "ne:MAX_POP20":304747,
    "ne:MAX_POP300":304747,
    "ne:MAX_POP310":0,
    "ne:MAX_POP50":304747,
    "ne:MEAN_BBXC":73.098854,
    "ne:MEAN_BBYC":49.808073,
    "ne:MEGACITY":0,
    "ne:MIN_AREAKM":89.0,
    "ne:MIN_AREAMI":34.0,
    "ne:MIN_BBXMAX":73.166667,
    "ne:MIN_BBXMIN":73.033333,
    "ne:MIN_BBYMAX":49.891667,
    "ne:MIN_BBYMIN":49.733333,
    "ne:MIN_PERKM":99.0,
    "ne:MIN_PERMI":62.0,
    "ne:NAME":"Qaraghandy",
    "ne:NAMEASCII":"Qaraghandy",
    "ne:NAMEDIFF":0,
    "ne:NATSCALE":110,
    "ne:POP1950":0,
    "ne:POP1955":0,
    "ne:POP1960":0,
    "ne:POP1965":0,
    "ne:POP1970":0,
    "ne:POP1975":0,
    "ne:POP1980":0,
    "ne:POP1985":0,
    "ne:POP1990":0,
    "ne:POP1995":0,
    "ne:POP2000":0,
    "ne:POP2005":0,
    "ne:POP2010":0,
    "ne:POP2015":0,
    "ne:POP2020":0,
    "ne:POP2025":0,
    "ne:POP2050":0,
    "ne:POP_MAX":451800,
    "ne:POP_MIN":304747,
    "ne:POP_OTHER":282,
    "ne:RANK_MAX":10,
    "ne:RANK_MIN":10,
    "ne:SCALERANK":3,
    "ne:SOV0NAME":"Kazakhstan",
    "ne:SOV_A3":"KAZ",
    "ne:TIMEZONE":"Asia/Almaty",
    "ne:UN_FID":0,
    "ne:UN_LAT":0.0,
    "ne:UN_LONG":0.0,
    "ne:WORLDCITY":0,
    "ne:min_zoom":5.0,
    "wof:name":"Qaraghandy",
    "wof:placetype":"locality"
},
  "geometry": {"coordinates":[73.11500972381276,49.88497702951281],"type":"Point"}
}