{
  "type": "Feature",
  "properties": {
    "gn:admin1_code":"13.0",
    "gn:asciiname":"Meshit",
    "gn:country_code":"KZ",
    "gn:dem":248,
    "gn:feature_class":"P",
    "gn:feature_code":"PPL",
    "gn:name":"Meshit",
    "gn:population":0,
    "gn:timezone":"Asia/Qyzylorda",
    "iso:country":"KZ",
    "name:eng_x_preferred":[
        "Meshit"
    ],
    "name:rus_x_preferred":[
        "\u041c\u0435\u0447\u0435\u0442\u043d\u044b\u0439"
    ],
    "name:und_x_variant":[
        "Mechetny",
        "Mechetnyy"
    ],
    "wof:name":"Meshit",
    "wof:placetype":"locality"
},
  "geometry": {"coordinates":[61.5569,51.97653],"type":"Point"}
}