{
  "type": "Feature",
  "properties": {
    "gn:admin1_code":"16.0",
    "gn:asciiname":"Kazgorodok",
    "gn:country_code":"KZ",
    "gn:dem":220,
    "gn:feature_class":"P",
    "gn:feature_code":"PPL",
    "gn:name":"Kazgorodok",
    "gn:population":0,
    "gn:timezone":"Asia/Almaty",
    "iso:country":"KZ",
    "wof:name":"Kazgorodok",
    "wof:placetype":"locality"
},
  "geometry": {"coordinates":[67.98333000000001,53.46666999999999],"type":"Point"}
}