{
  "type": "Feature",
  "properties": {
    "gn:admin1_code":"6.0",
    "gn:asciiname":"Yaik",
    "gn:country_code":"KZ",
    "gn:dem":-24,
    "gn:feature_class":"P",
    "gn:feature_code":"PPL",
    "gn:name":"Yaik",
    "gn:population":0,
    "gn:timezone":"Asia/Atyrau",
    "iso:country":"KZ",
    "name:und_x_variant":[
        "Yayik",
        "Yaik"
    ],
    "wof:name":"Yaik",
    "wof:placetype":"locality"
},
  "geometry": {"coordinates":[49.05,46.55],"type":"Point"}
}