{
  "type": "Feature",
  "properties": {
    "gn:admin1_code":"0.0",
    "gn:asciiname":"Ush-Togay",
    "gn:country_code":"KZ",
    "gn:dem":124,
    "gn:feature_class":"P",
    "gn:feature_code":"PPL",
    "gn:name":"Ush-Togay",
    "gn:population":0,
    "gn:timezone":"Asia/Qyzylorda",
    "iso:country":"KZ",
    "wof:name":"Ush-Togay",
    "wof:placetype":"locality"
},
  "geometry": {"coordinates":[64.83333,50.86667],"type":"Point"}
}