{
  "type": "Feature",
  "properties": {
    "gn:admin1_code":"13.0",
    "gn:asciiname":"Novonezhinka",
    "gn:country_code":"KZ",
    "gn:dem":211,
    "gn:feature_class":"P",
    "gn:feature_code":"PPL",
    "gn:name":"Novonezhinka",
    "gn:population":0,
    "gn:timezone":"Asia/Qyzylorda",
    "iso:country":"KZ",
    "name:eng_x_preferred":[
        "Novonezh\u012bnka"
    ],
    "name:kaz_x_preferred":[
        "Novonezh\u012bnka"
    ],
    "name:rus_x_preferred":[
        "\u041d\u043e\u0432\u043e\u043d\u0435\u0436\u0438\u043d\u043a\u0430"
    ],
    "name:und_x_variant":[
        "Novonezhinskiy"
    ],
    "wof:name":"Novonezhinka",
    "wof:placetype":"locality"
},
  "geometry": {"coordinates":[64.03738,52.53358000000001],"type":"Point"}
}