{
  "type": "Feature",
  "properties": {
    "gn:admin1_code":"15.0",
    "gn:asciiname":"Matobay",
    "gn:country_code":"KZ",
    "gn:dem":1458,
    "gn:feature_class":"P",
    "gn:feature_code":"PPL",
    "gn:name":"Matobay",
    "gn:population":0,
    "gn:timezone":"Asia/Almaty",
    "iso:country":"KZ",
    "name:eng_x_preferred":[
        "Matobay"
    ],
    "name:kaz_x_preferred":[
        "Matabay"
    ],
    "name:kaz_x_variant":[
        "\u041c\u0430\u0442\u0430\u0431\u0430\u0439"
    ],
    "name:rus_x_preferred":[
        "\u041c\u0430\u0442\u043e\u0431\u0430\u0439"
    ],
    "wof:name":"Matobay",
    "wof:placetype":"locality"
},
  "geometry": {"coordinates":[85.6551,48.67001],"type":"Point"}
}