{
  "type": "Feature",
  "properties": {
    "gn:admin1_code":"10.0",
    "gn:asciiname":"Toretogan",
    "gn:country_code":"KZ",
    "gn:dem":202,
    "gn:feature_class":"P",
    "gn:feature_code":"PPL",
    "gn:name":"Toretogan",
    "gn:population":0,
    "gn:timezone":"Asia/Almaty",
    "iso:country":"KZ",
    "wof:name":"Toretogan",
    "wof:placetype":"locality"
},
  "geometry": {"coordinates":[69.64305999999999,44.78861],"type":"Point"}
}