{
  "type": "Feature",
  "properties": {
    "gn:admin1_code":"15.0",
    "gn:asciiname":"Arshaly Pervoye",
    "gn:country_code":"KZ",
    "gn:dem":375,
    "gn:feature_class":"P",
    "gn:feature_code":"PPL",
    "gn:name":"Arshaly Pervoye",
    "gn:population":0,
    "gn:timezone":"Asia/Almaty",
    "iso:country":"KZ",
    "name:und_x_variant":[
        "Arshaly 1-ye",
        "Arshaly 1 (Pervoye)",
        "Arshaly Pervoye"
    ],
    "wof:name":"Arshaly Pervoye",
    "wof:placetype":"locality"
},
  "geometry": {"coordinates":[82.28561999999999,49.93301],"type":"Point"}
}