{
  "type": "Feature",
  "properties": {
    "gn:admin1_code":"0.0",
    "gn:asciiname":"Zhanaaul",
    "gn:country_code":"KZ",
    "gn:dem":362,
    "gn:feature_class":"P",
    "gn:feature_code":"PPL",
    "gn:name":"Zhanaaul",
    "gn:population":0,
    "gn:timezone":"Asia/Almaty",
    "iso:country":"KZ",
    "wof:name":"Zhanaaul",
    "wof:placetype":"locality"
},
  "geometry": {"coordinates":[70.89230000000001,50.57925],"type":"Point"}
}