{
  "type": "Feature",
  "properties": {
    "gn:admin1_code":"6.0",
    "gn:asciiname":"Konystanu",
    "gn:country_code":"KZ",
    "gn:dem":21,
    "gn:feature_class":"P",
    "gn:feature_code":"PPL",
    "gn:name":"Konystanu",
    "gn:population":0,
    "gn:timezone":"Asia/Atyrau",
    "iso:country":"KZ",
    "name:bel_x_preferred":[
        "\u041a\u0430\u043d\u044b\u0441\u0442\u0430\u043d\u0443"
    ],
    "name:eng_x_preferred":[
        "Konystanu"
    ],
    "name:kaz_x_preferred":[
        "Qonystan\u016b"
    ],
    "name:kaz_x_variant":[
        "\u049a\u043e\u043d\u044b\u0441\u0442\u0430\u043d\u0443"
    ],
    "name:msa_x_preferred":[
        "Qonystanu"
    ],
    "name:rus_x_preferred":[
        "\u041a\u043e\u043d\u044b\u0441\u0442\u0430\u043d\u0443"
    ],
    "name:ukr_x_preferred":[
        "\u041a\u043e\u043d\u0438\u0441\u0442\u0430\u043d\u0443"
    ],
    "name:und_x_variant":[
        "Konstanu"
    ],
    "wof:name":"Konystanu",
    "wof:placetype":"locality"
},
  "geometry": {"coordinates":[53.34558000000001,48.84154],"type":"Point"}
}