{
  "type": "Feature",
  "properties": {
    "gn:admin1_code":"10.0",
    "gn:asciiname":"Savankhana",
    "gn:country_code":"KZ",
    "gn:dem":541,
    "gn:feature_class":"P",
    "gn:feature_code":"PPL",
    "gn:name":"Savankhana",
    "gn:population":0,
    "gn:timezone":"Asia/Almaty",
    "iso:country":"KZ",
    "name:rus_x_preferred":[
        "\u0421\u0430\u0432\u0430\u043d\u0445\u0430\u043d\u0430"
    ],
    "wof:name":"Savankhana",
    "wof:placetype":"locality"
},
  "geometry": {"coordinates":[69.38251,41.69206],"type":"Point"}
}