{
  "type": "Feature",
  "properties": {
    "gn:admin1_code":"12.0",
    "gn:asciiname":"Bogun-Bay",
    "gn:country_code":"KZ",
    "gn:dem":506,
    "gn:feature_class":"P",
    "gn:feature_code":"PPL",
    "gn:name":"Bogun-Bay",
    "gn:population":0,
    "gn:timezone":"Asia/Almaty",
    "iso:country":"KZ",
    "wof:name":"Bogun-Bay",
    "wof:placetype":"locality"
},
  "geometry": {"coordinates":[71.51666999999998,49.16667],"type":"Point"}
}