{
  "type": "Feature",
  "properties": {
    "gn:admin1_code":"14.0",
    "gn:asciiname":"Kosuyenki",
    "gn:country_code":"KZ",
    "gn:dem":269,
    "gn:feature_class":"P",
    "gn:feature_code":"PPL",
    "gn:name":"Kosuyenki",
    "gn:population":0,
    "gn:timezone":"Asia/Qyzylorda",
    "iso:country":"KZ",
    "name:kaz_x_preferred":[
        "Qos\u00fcyyengki"
    ],
    "name:kaz_x_variant":[
        "\u049a\u043e\u0441\u04af\u0439\u0435\u04a3\u043a\u0456"
    ],
    "name:rus_x_preferred":[
        "\u041a\u043e\u0441\u0443\u0435\u043d\u043a\u0438"
    ],
    "wof:name":"Kosuyenki",
    "wof:placetype":"locality"
},
  "geometry": {"coordinates":[67.65491999999999,43.80018],"type":"Point"}
}