{
  "type": "Feature",
  "properties": {
    "gn:admin1_code":"15.0",
    "gn:asciiname":"Mayak",
    "gn:country_code":"KZ",
    "gn:dem":213,
    "gn:feature_class":"P",
    "gn:feature_code":"PPL",
    "gn:name":"Mayak",
    "gn:population":0,
    "gn:timezone":"Asia/Almaty",
    "iso:country":"KZ",
    "name:kaz_x_preferred":[
        "Mayak"
    ],
    "name:kaz_x_variant":[
        "\u041c\u0430\u044f\u043a"
    ],
    "wof:name":"Mayak",
    "wof:placetype":"locality"
},
  "geometry": {"coordinates":[80.79714,50.34479],"type":"Point"}
}