{
  "type": "Feature",
  "properties": {
    "gn:admin1_code":"4.0",
    "gn:asciiname":"Sor-Togay",
    "gn:country_code":"KZ",
    "gn:dem":205,
    "gn:feature_class":"P",
    "gn:feature_code":"PPL",
    "gn:name":"Sor-Togay",
    "gn:population":0,
    "gn:timezone":"Asia/Aqtobe",
    "iso:country":"KZ",
    "wof:name":"Sor-Togay",
    "wof:placetype":"locality"
},
  "geometry": {"coordinates":[57.75,48.23333],"type":"Point"}
}