{
  "type": "Feature",
  "properties": {
    "gn:admin1_code":"16.0",
    "gn:asciiname":"Lenino",
    "gn:country_code":"KZ",
    "gn:dem":139,
    "gn:feature_class":"P",
    "gn:feature_code":"PPL",
    "gn:name":"Lenino",
    "gn:population":0,
    "gn:timezone":"Asia/Almaty",
    "iso:country":"KZ",
    "name:bel_x_preferred":[
        "\u041b\u0435\u043d\u0456\u043d\u0430"
    ],
    "name:kaz_x_preferred":[
        "Len\u012bno"
    ],
    "name:kaz_x_variant":[
        "\u041b\u0435\u043d\u0438\u043d\u043e"
    ],
    "name:pol_x_preferred":[
        "Lenino"
    ],
    "name:rus_x_preferred":[
        "\u041b\u0435\u043d\u0438\u043d\u043e"
    ],
    "name:srp_x_preferred":[
        "\u041b\u0435\u045a\u0438\u043d\u043e"
    ],
    "name:ukr_x_preferred":[
        "\u041b\u0435\u043d\u0456\u043d\u043e"
    ],
    "name:und_x_variant":[
        "Bastau",
        "Len\u012bn"
    ],
    "wof:name":"Lenino",
    "wof:placetype":"locality"
},
  "geometry": {"coordinates":[67.58237,53.93387],"type":"Point"}
}