{
  "type": "Feature",
  "properties": {
    "gn:admin1_code":"4.0",
    "gn:asciiname":"Kodar",
    "gn:country_code":"KZ",
    "gn:dem":203,
    "gn:feature_class":"P",
    "gn:feature_code":"PPL",
    "gn:name":"Kodar",
    "gn:population":0,
    "gn:timezone":"Asia/Aqtobe",
    "iso:country":"KZ",
    "name:ceb_x_preferred":[
        "Kodar"
    ],
    "name:swe_x_preferred":[
        "Kodar"
    ],
    "wof:name":"Kodar",
    "wof:placetype":"locality"
},
  "geometry": {"coordinates":[62.13333000000001,50.18333],"type":"Point"}
}