{
  "type": "Feature",
  "properties": {
    "gn:admin1_code":"12.0",
    "gn:asciiname":"Akshoky",
    "gn:country_code":"KZ",
    "gn:dem":867,
    "gn:feature_class":"P",
    "gn:feature_code":"PPL",
    "gn:name":"Akshoky",
    "gn:population":0,
    "gn:timezone":"Asia/Almaty",
    "iso:country":"KZ",
    "name:rus_x_preferred":[
        "\u0410\u043a\u0448\u043e\u043a\u044b"
    ],
    "wof:name":"Akshoky",
    "wof:placetype":"locality"
},
  "geometry": {"coordinates":[74.08638000000001,48.81077],"type":"Point"}
}