{
  "type": "Feature",
  "properties": {
    "gn:admin1_code":"15.0",
    "gn:asciiname":"Pervomayskiy",
    "gn:country_code":"KZ",
    "gn:dem":320,
    "gn:feature_class":"P",
    "gn:feature_code":"PPL",
    "gn:name":"Pervomaysk\u012by",
    "gn:population":0,
    "gn:timezone":"Asia/Almaty",
    "iso:country":"KZ",
    "name:eng_x_preferred":[
        "Pervomaysk\u012by"
    ],
    "name:rus_x_preferred":[
        "\u041f\u0435\u0440\u0432\u043e\u043c\u0430\u0439\u0441\u043a\u0438\u0439"
    ],
    "name:und_x_variant":[
        "Pervomaysk\u012by"
    ],
    "wof:name":"Pervomayskiy",
    "wof:placetype":"locality"
},
  "geometry": {"coordinates":[81.9932,50.2647],"type":"Point"}
}