{
  "type": "Feature",
  "properties": {
    "gn:admin1_code":"10.0",
    "gn:asciiname":"Kut",
    "gn:country_code":"KZ",
    "gn:dem":287,
    "gn:feature_class":"P",
    "gn:feature_code":"PPL",
    "gn:name":"Kut",
    "gn:population":0,
    "gn:timezone":"Asia/Almaty",
    "iso:country":"KZ",
    "wof:name":"Kut",
    "wof:placetype":"locality"
},
  "geometry": {"coordinates":[68.65000000000001,41.06],"type":"Point"}
}