{
  "type": "Feature",
  "properties": {
    "gn:admin1_code":"16.0",
    "gn:asciiname":"Karatal",
    "gn:country_code":"KZ",
    "gn:dem":250,
    "gn:feature_class":"P",
    "gn:feature_code":"PPL",
    "gn:name":"Karatal",
    "gn:population":0,
    "gn:timezone":"Asia/Almaty",
    "iso:country":"KZ",
    "name:eng_x_preferred":[
        "Karatal"
    ],
    "name:kaz_x_preferred":[
        "Qaratal"
    ],
    "name:kaz_x_variant":[
        "\u049a\u0430\u0440\u0430\u0442\u0430\u043b"
    ],
    "name:rus_x_preferred":[
        "\u041a\u0430\u0440\u0430\u0442\u0430\u043b"
    ],
    "wof:name":"Karatal",
    "wof:placetype":"locality"
},
  "geometry": {"coordinates":[67.64270999999999,53.39246],"type":"Point"}
}