{
  "type": "Feature",
  "properties": {
    "gn:admin1_code":"10.0",
    "gn:asciiname":"Akmola",
    "gn:country_code":"KZ",
    "gn:dem":283,
    "gn:feature_class":"P",
    "gn:feature_code":"PPL",
    "gn:name":"Akmola",
    "gn:population":0,
    "gn:timezone":"Asia/Almaty",
    "iso:country":"KZ",
    "wof:name":"Akmola",
    "wof:placetype":"locality"
},
  "geometry": {"coordinates":[68.63333,41.25],"type":"Point"}
}