{
  "type": "Feature",
  "properties": {
    "gn:admin1_code":"0.0",
    "gn:asciiname":"Bestamak",
    "gn:country_code":"KZ",
    "gn:dem":142,
    "gn:feature_class":"P",
    "gn:feature_code":"PPL",
    "gn:name":"Bestamak",
    "gn:population":0,
    "gn:timezone":"Asia/Almaty",
    "iso:country":"KZ",
    "name:ell_x_preferred":[
        "\u039c\u03c0\u03b5\u03c3\u03c4\u03b1\u03bc\u03ac\u03ba"
    ],
    "name:msa_x_preferred":[
        "Bestamak"
    ],
    "wof:name":"Bestamak",
    "wof:placetype":"locality"
},
  "geometry": {"coordinates":[63.51667,50.06667],"type":"Point"}
}