{
  "type": "Feature",
  "properties": {
    "gn:admin1_code":"16.0",
    "gn:asciiname":"Prirechenskiy",
    "gn:country_code":"KZ",
    "gn:dem":244,
    "gn:feature_class":"P",
    "gn:feature_code":"PPL",
    "gn:name":"Pr\u012brechensk\u012by",
    "gn:population":0,
    "gn:timezone":"Asia/Almaty",
    "iso:country":"KZ",
    "name:kaz_x_preferred":[
        "Pr\u012brechensk\u012by"
    ],
    "name:kaz_x_variant":[
        "\u041f\u0440\u0438\u0440\u0435\u0447\u0435\u043d\u0441\u043a\u0438\u0439"
    ],
    "wof:name":"Prirechenskiy",
    "wof:placetype":"locality"
},
  "geometry": {"coordinates":[67.16154,52.54603],"type":"Point"}
}