{
  "type": "Feature",
  "properties": {
    "gn:admin1_code":"3.0",
    "gn:asciiname":"Malinovka",
    "gn:country_code":"KZ",
    "gn:dem":350,
    "gn:feature_class":"P",
    "gn:feature_code":"PPL",
    "gn:name":"Malinovka",
    "gn:population":0,
    "gn:timezone":"Asia/Almaty",
    "iso:country":"KZ",
    "name:kaz_x_preferred":[
        "Mal\u012bnovka"
    ],
    "name:und_x_variant":[
        "Akmolinskiy"
    ],
    "wof:name":"Malinovka",
    "wof:placetype":"locality"
},
  "geometry": {"coordinates":[70.9791,51.06886],"type":"Point"}
}