{
  "type": "Feature",
  "properties": {
    "gn:admin1_code":"10.0",
    "gn:asciiname":"Tasqudyq",
    "gn:country_code":"KZ",
    "gn:dem":302,
    "gn:feature_class":"P",
    "gn:feature_code":"PPL",
    "gn:name":"Tasqudyq",
    "gn:population":0,
    "gn:timezone":"Asia/Almaty",
    "iso:country":"KZ",
    "name:kaz_x_preferred":[
        "Tasqudyq"
    ],
    "name:kaz_x_variant":[
        "\u0422\u0430\u0441\u049b\u04b1\u0434\u044b\u049b"
    ],
    "name:rus_x_preferred":[
        "\u0422\u0430\u0441\u043a\u0443\u0434\u0443\u043a"
    ],
    "name:und_x_variant":[
        "Taskuduk"
    ],
    "wof:name":"Tasqudyq",
    "wof:placetype":"locality"
},
  "geometry": {"coordinates":[68.57971999999999,42.15496],"type":"Point"}
}