{
  "type": "Feature",
  "properties": {
    "gn:admin1_code":"11.0",
    "gn:asciiname":"Shamshi",
    "gn:country_code":"KZ",
    "gn:dem":126,
    "gn:feature_class":"P",
    "gn:feature_code":"PPL",
    "gn:name":"Shamshi",
    "gn:population":0,
    "gn:timezone":"Asia/Almaty",
    "iso:country":"KZ",
    "name:kaz_x_preferred":[
        "Sh\u00e4mshi"
    ],
    "name:kaz_x_variant":[
        "\u0428\u04d9\u043c\u0448\u0456",
        "Shamshy",
        "\u0428\u0430\u043c\u0448\u044b"
    ],
    "name:rus_x_preferred":[
        "\u0428\u0430\u043c\u0448\u0438"
    ],
    "wof:name":"Shamshi",
    "wof:placetype":"locality"
},
  "geometry": {"coordinates":[77.55368,51.66898],"type":"Point"}
}