{
  "type": "Feature",
  "properties": {
    "gn:admin1_code":"1.0",
    "gn:asciiname":"Bozinggen",
    "gn:cc2":"KZ",
    "gn:country_code":"KZ",
    "gn:dem":362,
    "gn:feature_class":"P",
    "gn:feature_code":"PPL",
    "gn:name":"Bozinggen",
    "gn:population":0,
    "gn:timezone":"Asia/Almaty",
    "iso:country":"KZ",
    "name:mkd_x_preferred":[
        "\u0411\u043e\u0437\u0438\u043d\u0433\u0435\u043d"
    ],
    "name:msa_x_preferred":[
        "Bozinggen"
    ],
    "name:und_x_variant":[
        "Novyy Koktal",
        "Bozingen",
        "Bozinggen"
    ],
    "wof:name":"Bozinggen",
    "wof:placetype":"locality"
},
  "geometry": {"coordinates":[75.25278,45.3875],"type":"Point"}
}