{
  "type": "Feature",
  "properties": {
    "gn:admin1_code":"15.0",
    "gn:asciiname":"Gromovka",
    "gn:country_code":"KZ",
    "gn:dem":394,
    "gn:feature_class":"P",
    "gn:feature_code":"PPL",
    "gn:name":"Gromovka",
    "gn:population":0,
    "gn:timezone":"Asia/Almaty",
    "iso:country":"KZ",
    "name:eng_x_preferred":[
        "Gromovka"
    ],
    "name:kaz_x_preferred":[
        "Qongyrb\u012bik"
    ],
    "name:kaz_x_variant":[
        "\u049a\u043e\u04a3\u044b\u0440\u0431\u0438\u0456\u043a"
    ],
    "name:rus_x_preferred":[
        "\u0413\u0440\u043e\u043c\u043e\u0432\u043a\u0430"
    ],
    "name:und_x_variant":[
        "Gromovskiy",
        "Gromovka"
    ],
    "wof:name":"Gromovka",
    "wof:placetype":"locality"
},
  "geometry": {"coordinates":[81.07052,49.82389000000001],"type":"Point"}
}