{
  "type": "Feature",
  "properties": {
    "gn:admin1_code":"3.0",
    "gn:asciiname":"Korzhinkol'",
    "gn:country_code":"KZ",
    "gn:dem":370,
    "gn:feature_class":"P",
    "gn:feature_code":"PPL",
    "gn:name":"Korzhinkol\u2019",
    "gn:population":0,
    "gn:timezone":"Asia/Almaty",
    "iso:country":"KZ",
    "name:und_x_variant":[
        "Kozha-Kul\u2019",
        "Korzhinkol\u2019"
    ],
    "wof:name":"Korzhinkol'",
    "wof:placetype":"locality"
},
  "geometry": {"coordinates":[68.9586,51.11357],"type":"Point"}
}