{
  "type": "Feature",
  "properties": {
    "gn:admin1_code":"16.0",
    "gn:asciiname":"Rostovka",
    "gn:country_code":"KZ",
    "gn:dem":152,
    "gn:feature_class":"P",
    "gn:feature_code":"PPL",
    "gn:name":"Rostovka",
    "gn:population":0,
    "gn:timezone":"Asia/Almaty",
    "iso:country":"KZ",
    "name:rus_x_preferred":[
        "\u0420\u043e\u0441\u0442\u043e\u0432\u043a\u0430"
    ],
    "wof:name":"Rostovka",
    "wof:placetype":"locality"
},
  "geometry": {"coordinates":[68.91171999999999,53.96144],"type":"Point"}
}