{
  "type": "Feature",
  "properties": {
    "gn:admin1_code":"0.0",
    "gn:asciiname":"Saryozek",
    "gn:country_code":"KZ",
    "gn:dem":414,
    "gn:feature_class":"P",
    "gn:feature_code":"PPL",
    "gn:name":"Saryozek",
    "gn:population":0,
    "gn:timezone":"Asia/Almaty",
    "iso:country":"KZ",
    "wof:name":"Saryozek",
    "wof:placetype":"locality"
},
  "geometry": {"coordinates":[78.65000000000001,49.63333],"type":"Point"}
}