{
  "type": "Feature",
  "properties": {
    "gn:admin1_code":"0.0",
    "gn:asciiname":"Mechet'-Zhadyk",
    "gn:country_code":"KZ",
    "gn:dem":29,
    "gn:feature_class":"P",
    "gn:feature_code":"PPL",
    "gn:name":"Mechet\u2019-Zhadyk",
    "gn:population":0,
    "gn:timezone":"Asia/Oral",
    "iso:country":"KZ",
    "wof:name":"Mechet'-Zhadyk",
    "wof:placetype":"locality"
},
  "geometry": {"coordinates":[52.96666999999999,49.96667],"type":"Point"}
}