{
  "type": "Feature",
  "properties": {
    "gn:admin1_code":"6.0",
    "gn:asciiname":"Shkola",
    "gn:country_code":"KZ",
    "gn:dem":-30,
    "gn:feature_class":"P",
    "gn:feature_code":"PPL",
    "gn:name":"Shkola",
    "gn:population":0,
    "gn:timezone":"Asia/Atyrau",
    "iso:country":"KZ",
    "wof:name":"Shkola",
    "wof:placetype":"locality"
},
  "geometry": {"coordinates":[48.81667,46.55],"type":"Point"}
}