{
  "type": "Feature",
  "properties": {
    "gn:admin1_code":"3.0",
    "gn:asciiname":"Baymyrza",
    "gn:country_code":"KZ",
    "gn:dem":346,
    "gn:feature_class":"P",
    "gn:feature_code":"PPL",
    "gn:name":"Baymyrza",
    "gn:population":0,
    "gn:timezone":"Asia/Almaty",
    "iso:country":"KZ",
    "name:eng_x_preferred":[
        "Baymyrza"
    ],
    "name:kaz_x_preferred":[
        "\u0411\u0430\u0439\u043c\u044b\u0440\u0437\u0430"
    ],
    "name:rus_x_preferred":[
        "\u0411\u0430\u0439\u043c\u044b\u0440\u0437\u0430"
    ],
    "name:und_x_variant":[
        "Baymurza",
        "Baymyrza"
    ],
    "wof:name":"Baymyrza",
    "wof:placetype":"locality"
},
  "geometry": {"coordinates":[70.74634,52.47019],"type":"Point"}
}