{
  "type": "Feature",
  "properties": {
    "gn:admin1_code":"0.0",
    "gn:asciiname":"Shakir",
    "gn:country_code":"KZ",
    "gn:dem":17,
    "gn:feature_class":"P",
    "gn:feature_code":"PPL",
    "gn:name":"Shakir",
    "gn:population":0,
    "gn:timezone":"Asia/Oral",
    "iso:country":"KZ",
    "wof:name":"Shakir",
    "wof:placetype":"locality"
},
  "geometry": {"coordinates":[49.03333,50.41667],"type":"Point"}
}