{
  "type": "Feature",
  "properties": {
    "gn:admin1_code":"15.0",
    "gn:asciiname":"Shumovsk",
    "gn:country_code":"KZ",
    "gn:dem":472,
    "gn:feature_class":"P",
    "gn:feature_code":"PPL",
    "gn:name":"Shumovsk",
    "gn:population":0,
    "gn:timezone":"Asia/Almaty",
    "iso:country":"KZ",
    "name:eng_x_preferred":[
        "Shumovsk"
    ],
    "name:kaz_x_preferred":[
        "Sh\u016bmovsk"
    ],
    "name:kaz_x_variant":[
        "\u0428\u0443\u043c\u043e\u0432\u0441\u043a"
    ],
    "name:rus_x_preferred":[
        "\u0428\u0443\u043c\u043e\u0432\u0441\u043a"
    ],
    "wof:name":"Shumovsk",
    "wof:placetype":"locality"
},
  "geometry": {"coordinates":[84.40080999999998,49.8884],"type":"Point"}
}