{
  "type": "Feature",
  "properties": {
    "gn:admin1_code":"0.0",
    "gn:asciiname":"Suzdal'skiy",
    "gn:country_code":"KZ",
    "gn:dem":324,
    "gn:feature_class":"P",
    "gn:feature_code":"PPL",
    "gn:name":"Suzdal\u2019skiy",
    "gn:population":0,
    "gn:timezone":"Asia/Almaty",
    "iso:country":"KZ",
    "wof:name":"Suzdal'skiy",
    "wof:placetype":"locality"
},
  "geometry": {"coordinates":[79.75099,50.03722],"type":"Point"}
}