{
  "type": "Feature",
  "properties": {
    "gn:admin1_code":"15.0",
    "gn:asciiname":"Ukrainka",
    "gn:country_code":"KZ",
    "gn:dem":273,
    "gn:feature_class":"P",
    "gn:feature_code":"PPL",
    "gn:name":"Ukrainka",
    "gn:population":0,
    "gn:timezone":"Asia/Almaty",
    "iso:country":"KZ",
    "name:eng_x_preferred":[
        "Ukrainka"
    ],
    "name:kaz_x_preferred":[
        "\u016akra\u012bnka"
    ],
    "name:kaz_x_variant":[
        "\u0423\u043a\u0440\u0430\u0438\u043d\u043a\u0430"
    ],
    "name:rus_x_preferred":[
        "\u0423\u043a\u0440\u0430\u0438\u043d\u043a\u0430"
    ],
    "wof:name":"Ukrainka",
    "wof:placetype":"locality"
},
  "geometry": {"coordinates":[82.41543,50.02072],"type":"Point"}
}