{
  "type": "Feature",
  "properties": {
    "gn:admin1_code":"12.0",
    "gn:asciiname":"Semizbughy",
    "gn:country_code":"KZ",
    "gn:dem":719,
    "gn:feature_class":"P",
    "gn:feature_code":"PPL",
    "gn:name":"Semizbughy",
    "gn:population":0,
    "gn:timezone":"Asia/Almaty",
    "iso:country":"KZ",
    "name:kaz_x_preferred":[
        "\u0421\u0435\u043c\u0456\u0437\u0431\u04b1\u0493\u044b"
    ],
    "name:rus_x_preferred":[
        "\u0421\u0435\u043c\u0438\u0437\u0431\u0443\u0433\u0430"
    ],
    "name:und_x_variant":[
        "Semie Bugu",
        "Semiz-Buga",
        "Semizbugy",
        "Semiye-Bugu",
        "Semiz-Bugu",
        "Semizbughy",
        "Semizbuga"
    ],
    "wof:name":"Semizbughy",
    "wof:placetype":"locality"
},
  "geometry": {"coordinates":[74.83159999999999,50.19841],"type":"Point"}
}