{
  "type": "Feature",
  "properties": {
    "gn:admin1_code":"0.0",
    "gn:asciiname":"Kuzhan",
    "gn:cc2":"KZ",
    "gn:country_code":"KZ",
    "gn:dem":-10,
    "gn:feature_class":"P",
    "gn:feature_code":"PPL",
    "gn:name":"Kuzhan",
    "gn:population":0,
    "gn:timezone":"Asia/Oral",
    "iso:country":"KZ",
    "name:und_x_variant":[
        "Kushan",
        "Kuzhan"
    ],
    "wof:name":"Kuzhan",
    "wof:placetype":"locality"
},
  "geometry": {"coordinates":[48.63333,48.25],"type":"Point"}
}