{
  "type": "Feature",
  "properties": {
    "gn:admin1_code":"10.0",
    "gn:asciiname":"Karakonyr",
    "gn:country_code":"KZ",
    "gn:dem":217,
    "gn:feature_class":"P",
    "gn:feature_code":"PPL",
    "gn:name":"Karakonyr",
    "gn:population":0,
    "gn:timezone":"Asia/Almaty",
    "iso:country":"KZ",
    "name:kaz_x_preferred":[
        "Qaraqongyr"
    ],
    "name:kaz_x_variant":[
        "\u049a\u0430\u0440\u0430\u049b\u043e\u04a3\u044b\u0440"
    ],
    "name:rus_x_preferred":[
        "\u041a\u0430\u0440\u0430\u043a\u043e\u043d\u044b\u0440"
    ],
    "wof:name":"Karakonyr",
    "wof:placetype":"locality"
},
  "geometry": {"coordinates":[68.60705,42.59268],"type":"Point"}
}