{
  "type": "Feature",
  "properties": {
    "gn:admin1_code":"14.0",
    "gn:asciiname":"Kusak",
    "gn:country_code":"KZ",
    "gn:dem":539,
    "gn:feature_class":"P",
    "gn:feature_code":"PPL",
    "gn:name":"Kusak",
    "gn:population":0,
    "gn:timezone":"Asia/Almaty",
    "iso:country":"KZ",
    "name:rus_x_preferred":[
        "\u041a\u0443\u0441\u0430\u043a"
    ],
    "wof:name":"Kusak",
    "wof:placetype":"locality"
},
  "geometry": {"coordinates":[71.49184,43.02634000000001],"type":"Point"}
}