{
  "type": "Feature",
  "properties": {
    "gn:admin1_code":"1.0",
    "gn:asciiname":"Uzyntam",
    "gn:country_code":"KZ",
    "gn:dem":604,
    "gn:feature_class":"P",
    "gn:feature_code":"PPL",
    "gn:name":"Uzyntam",
    "gn:population":0,
    "gn:timezone":"Asia/Almaty",
    "iso:country":"KZ",
    "name:kaz_x_preferred":[
        "Uzyntam"
    ],
    "name:kaz_x_variant":[
        "\u04b0\u0437\u044b\u043d\u0442\u0430\u043c"
    ],
    "name:rus_x_preferred":[
        "\u0423\u0437\u044b\u043a\u0442\u0430\u043c"
    ],
    "name:und_x_variant":[
        "Uzuntam",
        "Uzyktam"
    ],
    "wof:name":"Uzyntam",
    "wof:placetype":"locality"
},
  "geometry": {"coordinates":[79.68774000000001,43.64377],"type":"Point"}
}