{
  "type": "Feature",
  "properties": {
    "gn:admin1_code":"10.0",
    "gn:asciiname":"Zhogharghy Boralday",
    "gn:country_code":"KZ",
    "gn:dem":433,
    "gn:feature_class":"P",
    "gn:feature_code":"PPL",
    "gn:name":"Zhogharghy Boralday",
    "gn:population":0,
    "gn:timezone":"Asia/Almaty",
    "iso:country":"KZ",
    "name:kaz_x_preferred":[
        "Zhogharghy Boralday"
    ],
    "name:kaz_x_variant":[
        "\u0416\u043e\u0493\u0430\u0440\u0493\u044b \u0411\u043e\u0440\u0430\u043b\u0434\u0430\u0439"
    ],
    "name:rus_x_preferred":[
        "\u0412\u0435\u0440\u0445\u043d\u0438\u0439 \u0411\u043e\u0440\u0430\u043b\u0434\u0430\u0439"
    ],
    "name:und_x_variant":[
        "Verkhniy Boralday"
    ],
    "wof:name":"Zhogharghy Boralday",
    "wof:placetype":"locality"
},
  "geometry": {"coordinates":[69.6484,42.78422],"type":"Point"}
}