{
  "type": "Feature",
  "properties": {
    "gn:admin1_code":"10.0",
    "gn:asciiname":"Shashtobe",
    "gn:country_code":"KZ",
    "gn:dem":406,
    "gn:feature_class":"P",
    "gn:feature_code":"PPL",
    "gn:name":"Shashtobe",
    "gn:population":0,
    "gn:timezone":"Asia/Almaty",
    "iso:country":"KZ",
    "name:kaz_x_preferred":[
        "Shasht\u00f6be"
    ],
    "name:kaz_x_variant":[
        "\u0428\u0430\u0448\u0442\u04e9\u0431\u0435"
    ],
    "name:rus_x_preferred":[
        "\u0428\u0430\u0448\u0442\u043e\u0431\u0435"
    ],
    "wof:name":"Shashtobe",
    "wof:placetype":"locality"
},
  "geometry": {"coordinates":[68.35732,43.55032],"type":"Point"}
}