{
  "type": "Feature",
  "properties": {
    "gn:admin1_code":"1.0",
    "gn:asciiname":"Almaly",
    "gn:country_code":"KZ",
    "gn:dem":791,
    "gn:feature_class":"P",
    "gn:feature_code":"PPL",
    "gn:name":"Almaly",
    "gn:population":0,
    "gn:timezone":"Asia/Almaty",
    "iso:country":"KZ",
    "name:ceb_x_preferred":[
        "Almaly"
    ],
    "name:kaz_x_preferred":[
        "Almaly"
    ],
    "name:swe_x_preferred":[
        "Almaly"
    ],
    "name:und_x_variant":[
        "Pokrovka",
        "Novopokrovka"
    ],
    "wof:name":"Almaly",
    "wof:placetype":"locality"
},
  "geometry": {"coordinates":[79.98673000000002,45.44971],"type":"Point"}
}