{
  "type": "Feature",
  "properties": {
    "gn:admin1_code":"4.0",
    "gn:asciiname":"Karabulak",
    "gn:country_code":"KZ",
    "gn:dem":99,
    "gn:feature_class":"P",
    "gn:feature_code":"PPL",
    "gn:name":"Karabulak",
    "gn:population":0,
    "gn:timezone":"Asia/Aqtobe",
    "iso:country":"KZ",
    "wof:name":"Karabulak",
    "wof:placetype":"locality"
},
  "geometry": {"coordinates":[55.91667,47.63333],"type":"Point"}
}