{
  "type": "Feature",
  "properties": {
    "gn:admin1_code":"17.0",
    "gn:asciiname":"Yntymaq",
    "gn:country_code":"KZ",
    "gn:dem":1041,
    "gn:feature_class":"P",
    "gn:feature_code":"PPL",
    "gn:name":"Yntymaq",
    "gn:population":0,
    "gn:timezone":"Asia/Almaty",
    "iso:country":"KZ",
    "name:kaz_x_preferred":[
        "Yntymaq"
    ],
    "name:kaz_x_variant":[
        "\u042b\u043d\u0442\u044b\u043c\u0430\u049b"
    ],
    "name:rus_x_preferred":[
        "\u0418\u043d\u0442\u044b\u043c\u0430\u043a"
    ],
    "name:und_x_variant":[
        "Intymak"
    ],
    "wof:name":"Yntymaq",
    "wof:placetype":"locality"
},
  "geometry": {"coordinates":[70.62619000000002,42.58618],"type":"Point"}
}