{
  "type": "Feature",
  "properties": {
    "gn:admin1_code":"4.0",
    "gn:asciiname":"Leninskoye",
    "gn:country_code":"KZ",
    "gn:dem":341,
    "gn:feature_class":"P",
    "gn:feature_code":"PPL",
    "gn:name":"Leninskoye",
    "gn:population":0,
    "gn:timezone":"Asia/Aqtobe",
    "iso:country":"KZ",
    "name:eng_x_preferred":[
        "Leninskoye"
    ],
    "name:kaz_x_preferred":[
        "Len\u012bnskoe"
    ],
    "name:rus_x_preferred":[
        "\u041b\u0435\u043d\u0438\u043d\u0441\u043a\u043e\u0435"
    ],
    "name:und_x_variant":[
        "Kos-Istek"
    ],
    "wof:name":"Leninskoye",
    "wof:placetype":"locality"
},
  "geometry": {"coordinates":[57.88636,50.74068],"type":"Point"}
}