{
  "type": "Feature",
  "properties": {
    "gn:admin1_code":"0.0",
    "gn:asciiname":"Burkhanka",
    "gn:country_code":"KZ",
    "gn:dem":426,
    "gn:feature_class":"P",
    "gn:feature_code":"PPL",
    "gn:name":"Burkhanka",
    "gn:population":0,
    "gn:timezone":"Asia/Almaty",
    "iso:country":"KZ",
    "wof:name":"Burkhanka",
    "wof:placetype":"locality"
},
  "geometry": {"coordinates":[83.32308,47.91181],"type":"Point"}
}