{
  "type": "Feature",
  "properties": {
    "gn:admin1_code":"3.0",
    "gn:asciiname":"Naumovka",
    "gn:country_code":"KZ",
    "gn:dem":365,
    "gn:feature_class":"P",
    "gn:feature_code":"PPL",
    "gn:name":"Naumovka",
    "gn:population":0,
    "gn:timezone":"Asia/Almaty",
    "iso:country":"KZ",
    "name:eng_x_preferred":[
        "Na\u016bmovka"
    ],
    "name:kaz_x_preferred":[
        "\u041d\u0430\u0443\u043c\u043e\u0432\u043a\u0430"
    ],
    "name:rus_x_preferred":[
        "\u041d\u0430\u0443\u043c\u043e\u0432\u043a\u0430"
    ],
    "name:und_x_variant":[
        "Na\u016bmovka",
        "Naumovka"
    ],
    "wof:name":"Naumovka",
    "wof:placetype":"locality"
},
  "geometry": {"coordinates":[70.35353000000001,52.13015],"type":"Point"}
}