{
  "type": "Feature",
  "properties": {
    "gn:admin1_code":"12.0",
    "gn:asciiname":"Yagodnoye",
    "gn:country_code":"KZ",
    "gn:dem":494,
    "gn:feature_class":"P",
    "gn:feature_code":"PPL",
    "gn:name":"Yagodnoye",
    "gn:population":0,
    "gn:timezone":"Asia/Almaty",
    "iso:country":"KZ",
    "name:rus_x_preferred":[
        "\u042f\u0433\u043e\u0434\u043d\u043e\u0435"
    ],
    "wof:name":"Yagodnoye",
    "wof:placetype":"locality"
},
  "geometry": {"coordinates":[72.71162,49.64861],"type":"Point"}
}