{
  "type": "Feature",
  "properties": {
    "gn:admin1_code":"0.0",
    "gn:asciiname":"Poltavka",
    "gn:country_code":"KZ",
    "gn:dem":120,
    "gn:feature_class":"P",
    "gn:feature_code":"PPL",
    "gn:name":"Poltavka",
    "gn:population":0,
    "gn:timezone":"Asia/Oral",
    "iso:country":"KZ",
    "name:eng_x_preferred":[
        "Poltavka"
    ],
    "name:rus_x_preferred":[
        "\u041f\u043e\u043b\u0442\u0430\u0432\u043a\u0430"
    ],
    "name:und_x_variant":[
        "Poltavskiy",
        "Poltavka"
    ],
    "wof:name":"Poltavka",
    "wof:placetype":"locality"
},
  "geometry": {"coordinates":[53.68923,50.89289],"type":"Point"}
}