{
  "type": "Feature",
  "properties": {
    "gn:admin1_code":"0.0",
    "gn:asciiname":"Mechet'",
    "gn:country_code":"KZ",
    "gn:dem":63,
    "gn:feature_class":"P",
    "gn:feature_code":"PPL",
    "gn:name":"Mechet\u2019",
    "gn:population":0,
    "gn:timezone":"Asia/Oral",
    "iso:country":"KZ",
    "wof:name":"Mechet'",
    "wof:placetype":"locality"
},
  "geometry": {"coordinates":[53.53333000000001,49.91667],"type":"Point"}
}