{
  "type": "Feature",
  "properties": {
    "gn:admin1_code":"0.0",
    "gn:asciiname":"Kamambayevskiy",
    "gn:country_code":"KZ",
    "gn:dem":98,
    "gn:feature_class":"P",
    "gn:feature_code":"PPL",
    "gn:name":"Kamambayevskiy",
    "gn:population":0,
    "gn:timezone":"Asia/Oral",
    "iso:country":"KZ",
    "wof:name":"Kamambayevskiy",
    "wof:placetype":"locality"
},
  "geometry": {"coordinates":[52.52058,50.86563],"type":"Point"}
}