{
  "type": "Feature",
  "properties": {
    "gn:admin1_code":"10.0",
    "gn:asciiname":"Chernyayevka",
    "gn:country_code":"KZ",
    "gn:dem":533,
    "gn:feature_class":"P",
    "gn:feature_code":"PPL",
    "gn:name":"Chernyayevka",
    "gn:population":0,
    "gn:timezone":"Asia/Almaty",
    "iso:country":"KZ",
    "name:kaz_x_preferred":[
        "\u0416\u0456\u0431\u0435\u043a \u0416\u043e\u043b\u044b"
    ],
    "name:rus_x_preferred":[
        "\u0427\u0435\u0440\u043d\u044f\u0435\u0432\u043a\u0430"
    ],
    "name:und_x_variant":[
        "Poltoratskoye",
        "Zhibek Zholy"
    ],
    "wof:name":"Chernyayevka",
    "wof:placetype":"locality"
},
  "geometry": {"coordinates":[69.36497,41.4759],"type":"Point"}
}