{
  "type": "Feature",
  "properties": {
    "gn:admin1_code":"13.0",
    "gn:asciiname":"Maykol'",
    "gn:country_code":"KZ",
    "gn:dem":190,
    "gn:feature_class":"P",
    "gn:feature_code":"PPL",
    "gn:name":"Maykol\u2019",
    "gn:population":0,
    "gn:timezone":"Asia/Qyzylorda",
    "iso:country":"KZ",
    "name:eng_x_preferred":[
        "Maykol'"
    ],
    "name:rus_x_preferred":[
        "\u041c\u0430\u0439\u043a\u043e\u043b\u044c"
    ],
    "name:rus_x_variant":[
        "Maykol\u2019"
    ],
    "name:und_x_variant":[
        "May-Kul\u2019",
        "Maykul\u2019skiy"
    ],
    "wof:name":"Maykol'",
    "wof:placetype":"locality"
},
  "geometry": {"coordinates":[63.34441999999999,53.28724],"type":"Point"}
}