{
  "type": "Feature",
  "properties": {
    "gn:admin1_code":"12.0",
    "gn:asciiname":"Orkendei",
    "gn:country_code":"KZ",
    "gn:dem":430,
    "gn:feature_class":"P",
    "gn:feature_code":"PPL",
    "gn:name":"Orkendei",
    "gn:population":0,
    "gn:timezone":"Asia/Almaty",
    "iso:country":"KZ",
    "wof:name":"Orkendei",
    "wof:placetype":"locality"
},
  "geometry": {"coordinates":[71.98839,49.68852],"type":"Point"}
}