{
  "type": "Feature",
  "properties": {
    "gn:admin1_code":"13.0",
    "gn:asciiname":"Novoshumnoye",
    "gn:country_code":"KZ",
    "gn:dem":183,
    "gn:feature_class":"P",
    "gn:feature_code":"PPL",
    "gn:name":"Novoshumnoye",
    "gn:population":0,
    "gn:timezone":"Asia/Qyzylorda",
    "iso:country":"KZ",
    "name:eng_x_preferred":[
        "Novoshumnoye"
    ],
    "name:kaz_x_preferred":[
        "Novosh\u016bmnoe"
    ],
    "name:kaz_x_variant":[
        "\u041d\u043e\u0432\u043e\u0448\u0443\u043c\u043d\u043e\u0435"
    ],
    "name:rus_x_preferred":[
        "\u041d\u043e\u0432\u043e\u0448\u0443\u043c\u043d\u044b\u0439"
    ],
    "name:und_x_variant":[
        "Shumnyy",
        "Novoshumnyy",
        "Novoshumnoye"
    ],
    "wof:name":"Novoshumnoye",
    "wof:placetype":"locality"
},
  "geometry": {"coordinates":[62.86151,53.92411],"type":"Point"}
}