{
  "type": "Feature",
  "properties": {
    "gn:admin1_code":"11.0",
    "gn:asciiname":"Staryy Shakat",
    "gn:country_code":"KZ",
    "gn:dem":130,
    "gn:feature_class":"P",
    "gn:feature_code":"PPL",
    "gn:name":"Staryy Shakat",
    "gn:population":0,
    "gn:timezone":"Asia/Almaty",
    "iso:country":"KZ",
    "name:kaz_x_preferred":[
        "K\u00f6pe Shaqat"
    ],
    "name:kaz_x_variant":[
        "\u041a\u04e9\u043f\u0435 \u0428\u0430\u049b\u0430\u0442"
    ],
    "name:rus_x_preferred":[
        "\u0421\u0442\u0430\u0440\u044b\u0439 \u0428\u0430\u043a\u0430\u0442"
    ],
    "wof:name":"Staryy Shakat",
    "wof:placetype":"locality"
},
  "geometry": {"coordinates":[77.35245999999999,52.37799],"type":"Point"}
}