{
  "type": "Feature",
  "properties": {
    "gn:admin1_code":"12.0",
    "gn:asciiname":"Atobi",
    "gn:country_code":"KZ",
    "gn:dem":477,
    "gn:feature_class":"P",
    "gn:feature_code":"PPL",
    "gn:name":"Atobi",
    "gn:population":0,
    "gn:timezone":"Asia/Almaty",
    "iso:country":"KZ",
    "name:rus_x_preferred":[
        "\u0410\u0442\u043e\u0431\u0438"
    ],
    "wof:name":"Atobi",
    "wof:placetype":"locality"
},
  "geometry": {"coordinates":[76.62466999999999,50.16953],"type":"Point"}
}