{
  "type": "Feature",
  "properties": {
    "gn:admin1_code":"4.0",
    "gn:asciiname":"Zhiren'kupa",
    "gn:country_code":"KZ",
    "gn:dem":112,
    "gn:feature_class":"P",
    "gn:feature_code":"PPL",
    "gn:name":"Zhiren\u2019kupa",
    "gn:population":0,
    "gn:timezone":"Asia/Aqtobe",
    "iso:country":"KZ",
    "name:und_x_variant":[
        "Dzhiren\u2019-Kupa",
        "Zhiren\u2019kupa"
    ],
    "wof:name":"Zhiren'kupa",
    "wof:placetype":"locality"
},
  "geometry": {"coordinates":[54.93333000000001,50.75],"type":"Point"}
}