{
  "type": "Feature",
  "properties": {
    "gn:admin1_code":"0.0",
    "gn:asciiname":"Sergeyev",
    "gn:country_code":"KZ",
    "gn:dem":8,
    "gn:feature_class":"P",
    "gn:feature_code":"PPL",
    "gn:name":"Sergeyev",
    "gn:population":0,
    "gn:timezone":"Asia/Oral",
    "iso:country":"KZ",
    "name:bel_x_preferred":[
        "\u0421\u044f\u0440\u0433\u0435\u0435\u045e"
    ],
    "name:chv_x_preferred":[
        "\u0421\u0435\u0440\u0433\u0435\u0435\u0432"
    ],
    "name:deu_x_preferred":[
        "Sergejew"
    ],
    "name:fra_x_preferred":[
        "Sergue\u00efev"
    ],
    "name:jpn_x_preferred":[
        "\u30bb\u30eb\u30b2\u30fc\u30a8\u30d5"
    ],
    "name:nld_x_preferred":[
        "Sergejev"
    ],
    "name:pol_x_preferred":[
        "Siergiejew"
    ],
    "name:rus_x_preferred":[
        "\u0421\u0435\u0440\u0433\u0435\u0435\u0432"
    ],
    "name:slv_x_preferred":[
        "Sergejev"
    ],
    "name:ukr_x_preferred":[
        "\u0421\u0435\u0440\u0433\u0454\u0454\u0432"
    ],
    "wof:name":"Sergeyev",
    "wof:placetype":"locality"
},
  "geometry": {"coordinates":[51.06667,50.05],"type":"Point"}
}