{
  "type": "Feature",
  "properties": {
    "gn:admin1_code":"0.0",
    "gn:asciiname":"Sergeyev",
    "gn:country_code":"KZ",
    "gn:dem":8,
    "gn:feature_class":"P",
    "gn:feature_code":"PPL",
    "gn:name":"Sergeyev",
    "gn:population":0,
    "gn:timezone":"Asia/Oral",
    "iso:country":"KZ",
    "wof:name":"Sergeyev",
    "wof:placetype":"locality"
},
  "geometry": {"coordinates":[51.06667,50.05],"type":"Point"}
}