{
  "type": "Feature",
  "properties": {
    "gn:admin1_code":"10.0",
    "gn:asciiname":"Zhdanovo",
    "gn:country_code":"KZ",
    "gn:dem":675,
    "gn:feature_class":"P",
    "gn:feature_code":"PPL",
    "gn:name":"Zhdanovo",
    "gn:population":0,
    "gn:timezone":"Asia/Almaty",
    "iso:country":"KZ",
    "name:rus_x_preferred":[
        "\u0416\u0434\u0430\u043d\u043e\u0432\u043e"
    ],
    "wof:name":"Zhdanovo",
    "wof:placetype":"locality"
},
  "geometry": {"coordinates":[70.19629999999999,42.51941],"type":"Point"}
}