{
  "type": "Feature",
  "properties": {
    "gn:admin1_code":"6.0",
    "gn:asciiname":"Madeniyet",
    "gn:country_code":"KZ",
    "gn:dem":-19,
    "gn:feature_class":"P",
    "gn:feature_code":"PPL",
    "gn:name":"Madeniy\u00ebt",
    "gn:population":0,
    "gn:timezone":"Asia/Atyrau",
    "iso:country":"KZ",
    "name:ell_x_preferred":[
        "\u039c\u03b1\u03bd\u03c4\u03b5\u03bd\u03b9\u03b3\u03b9\u03ad\u03c4"
    ],
    "name:msa_x_preferred":[
        "Madeniyet"
    ],
    "name:rus_x_preferred":[
        "\u041c\u0430\u0434\u0435\u043d\u0438\u0435\u0442"
    ],
    "name:und_x_variant":[
        "Modyn\u2019yat",
        "Madeniy\u00ebt"
    ],
    "name:urd_x_preferred":[
        "\u0645\u06cc\u0688\u06cc\u0646\u06cc\u06cc\u06cc\u0679"
    ],
    "wof:name":"Madeniyet",
    "wof:placetype":"locality"
},
  "geometry": {"coordinates":[50.86667,47.95],"type":"Point"}
}