{
  "type": "Feature",
  "properties": {
    "gn:admin1_code":"6.0",
    "gn:asciiname":"Madeniyet",
    "gn:country_code":"KZ",
    "gn:dem":-19,
    "gn:feature_class":"P",
    "gn:feature_code":"PPL",
    "gn:name":"Madeniy\u00ebt",
    "gn:population":0,
    "gn:timezone":"Asia/Atyrau",
    "iso:country":"KZ",
    "name:und_x_variant":[
        "Modyn\u2019yat",
        "Madeniy\u00ebt"
    ],
    "wof:name":"Madeniyet",
    "wof:placetype":"locality"
},
  "geometry": {"coordinates":[50.86667,47.95],"type":"Point"}
}