{
  "type": "Feature",
  "properties": {
    "gn:admin1_code":"11.0",
    "gn:asciiname":"Zhartas",
    "gn:country_code":"KZ",
    "gn:dem":156,
    "gn:feature_class":"P",
    "gn:feature_code":"PPL",
    "gn:name":"Zhartas",
    "gn:population":0,
    "gn:timezone":"Asia/Almaty",
    "iso:country":"KZ",
    "name:kaz_x_preferred":[
        "Zhartas"
    ],
    "name:kaz_x_variant":[
        "\u0416\u0430\u0440\u0442\u0430\u0441"
    ],
    "wof:name":"Zhartas",
    "wof:placetype":"locality"
},
  "geometry": {"coordinates":[74.49639999999999,52.1379],"type":"Point"}
}