{
  "type": "Feature",
  "properties": {
    "gn:admin1_code":"15.0",
    "gn:asciiname":"Progress",
    "gn:country_code":"KZ",
    "gn:dem":299,
    "gn:feature_class":"P",
    "gn:feature_code":"PPL",
    "gn:name":"Progress",
    "gn:population":0,
    "gn:timezone":"Asia/Almaty",
    "iso:country":"KZ",
    "name:eng_x_preferred":[
        "Progress"
    ],
    "name:kaz_x_preferred":[
        "\u041f\u0440\u043e\u0433\u0440\u0435\u0441\u0441"
    ],
    "name:rus_x_preferred":[
        "\u041f\u0440\u043e\u0433\u0440\u0435\u0441\u0441"
    ],
    "wof:name":"Progress",
    "wof:placetype":"locality"
},
  "geometry": {"coordinates":[82.39019,50.13864],"type":"Point"}
}