{
  "type": "Feature",
  "properties": {
    "gn:admin1_code":"10.0",
    "gn:asciiname":"Dimitrovo",
    "gn:country_code":"KZ",
    "gn:dem":624,
    "gn:feature_class":"P",
    "gn:feature_code":"PPL",
    "gn:name":"Dimitrovo",
    "gn:population":0,
    "gn:timezone":"Asia/Almaty",
    "iso:country":"KZ",
    "name:ceb_x_preferred":[
        "Dimitrovo"
    ],
    "name:rus_x_preferred":[
        "\u0414\u0438\u043c\u0438\u0442\u0440\u043e\u0432\u043e"
    ],
    "name:swe_x_preferred":[
        "Dimitrovo"
    ],
    "wof:name":"Dimitrovo",
    "wof:placetype":"locality"
},
  "geometry": {"coordinates":[70.00576,42.48283],"type":"Point"}
}