{
  "type": "Feature",
  "properties": {
    "gn:admin1_code":"7.0",
    "gn:asciiname":"Zhanazhol",
    "gn:country_code":"KZ",
    "gn:dem":-2,
    "gn:feature_class":"P",
    "gn:feature_code":"PPL",
    "gn:name":"Zhanazhol",
    "gn:population":0,
    "gn:timezone":"Asia/Oral",
    "iso:country":"KZ",
    "name:eng_x_preferred":[
        "Zhanazhol"
    ],
    "name:rus_x_preferred":[
        "\u041c\u043e\u043a\u0440\u0438\u043d\u0441\u043a\u043e\u0435"
    ],
    "name:und_x_variant":[
        "Mokrinskiy",
        "Mokrinskoye",
        "Zhanazhol"
    ],
    "wof:name":"Zhanazhol",
    "wof:placetype":"locality"
},
  "geometry": {"coordinates":[49.79258,49.0928],"type":"Point"}
}