{
  "type": "Feature",
  "properties": {
    "gn:admin1_code":"0.0",
    "gn:asciiname":"Terektibulak",
    "gn:country_code":"KZ",
    "gn:dem":533,
    "gn:feature_class":"P",
    "gn:feature_code":"PPL",
    "gn:name":"Terektibulak",
    "gn:population":0,
    "gn:timezone":"Asia/Almaty",
    "iso:country":"KZ",
    "wof:name":"Terektibulak",
    "wof:placetype":"locality"
},
  "geometry": {"coordinates":[84.04472,48.66667],"type":"Point"}
}