{
  "type": "Feature",
  "properties": {
    "gn:admin1_code":"16.0",
    "gn:asciiname":"Kenashchy",
    "gn:country_code":"KZ",
    "gn:dem":73,
    "gn:feature_class":"P",
    "gn:feature_code":"PPL",
    "gn:name":"Kenashchy",
    "gn:population":0,
    "gn:timezone":"Asia/Almaty",
    "iso:country":"KZ",
    "name:eng_x_preferred":[
        "Kenashchy"
    ],
    "name:rus_x_preferred":[
        "\u041a\u0435\u043d\u0430\u0449\u0438"
    ],
    "name:rus_x_variant":[
        "\u041a\u0435\u043d\u0430\u0449\u044b"
    ],
    "wof:name":"Kenashchy",
    "wof:placetype":"locality"
},
  "geometry": {"coordinates":[71.16378,54.05337],"type":"Point"}
}