{
  "type": "Feature",
  "properties": {
    "gn:admin1_code":"14.0",
    "gn:asciiname":"Talas",
    "gn:country_code":"KZ",
    "gn:dem":587,
    "gn:feature_class":"P",
    "gn:feature_code":"PPL",
    "gn:name":"Talas",
    "gn:population":0,
    "gn:timezone":"Asia/Almaty",
    "iso:country":"KZ",
    "name:kaz_x_preferred":[
        "Talas"
    ],
    "name:kaz_x_variant":[
        "\u0422\u0430\u043b\u0430\u0441"
    ],
    "wof:name":"Talas",
    "wof:placetype":"locality"
},
  "geometry": {"coordinates":[71.47171999999998,42.93708],"type":"Point"}
}