{
  "type": "Feature",
  "properties": {
    "gn:admin1_code":"1.0",
    "gn:asciiname":"Kazakhstan",
    "gn:country_code":"KZ",
    "gn:dem":633,
    "gn:feature_class":"P",
    "gn:feature_code":"PPL",
    "gn:name":"Kazakhstan",
    "gn:population":0,
    "gn:timezone":"Asia/Almaty",
    "iso:country":"KZ",
    "name:kaz_x_preferred":[
        "Qazaqstan"
    ],
    "name:kaz_x_variant":[
        "\u049a\u0430\u0437\u0430\u049b\u0441\u0442\u0430\u043d"
    ],
    "name:rus_x_preferred":[
        "\u041a\u0430\u0437\u0430\u0445\u0441\u0442\u0430\u043d"
    ],
    "name:und_x_variant":[
        "Sovkhoz Kazakhstan"
    ],
    "wof:name":"Kazakhstan",
    "wof:placetype":"locality"
},
  "geometry": {"coordinates":[77.77509000000001,43.52007],"type":"Point"}
}