{
  "type": "Feature",
  "properties": {
    "gn:admin1_code":"12.0",
    "gn:asciiname":"Novomoskovskiy",
    "gn:country_code":"KZ",
    "gn:dem":572,
    "gn:feature_class":"P",
    "gn:feature_code":"PPL",
    "gn:name":"Novomoskovskiy",
    "gn:population":0,
    "gn:timezone":"Asia/Almaty",
    "iso:country":"KZ",
    "wof:name":"Novomoskovskiy",
    "wof:placetype":"locality"
},
  "geometry": {"coordinates":[72.90000000000001,50.35],"type":"Point"}
}