{
  "type": "Feature",
  "properties": {
    "gn:admin1_code":"3.0",
    "gn:asciiname":"Borisovka",
    "gn:country_code":"KZ",
    "gn:dem":286,
    "gn:feature_class":"P",
    "gn:feature_code":"PPL",
    "gn:name":"Bor\u012bsovka",
    "gn:population":0,
    "gn:timezone":"Asia/Almaty",
    "iso:country":"KZ",
    "name:lav_x_preferred":[
        "Borisovka"
    ],
    "name:und_x_variant":[
        "Vladimiroborisovka",
        "Borisovskiy",
        "Bor\u012bsovka"
    ],
    "wof:name":"Borisovka",
    "wof:placetype":"locality"
},
  "geometry": {"coordinates":[68.53771,51.89166],"type":"Point"}
}