{
  "type": "Feature",
  "properties": {
    "gn:admin1_code":"12.0",
    "gn:asciiname":"Zavodskiy",
    "gn:country_code":"KZ",
    "gn:dem":734,
    "gn:feature_class":"P",
    "gn:feature_code":"PPL",
    "gn:name":"Zavodskiy",
    "gn:population":0,
    "gn:timezone":"Asia/Almaty",
    "iso:country":"KZ",
    "name:und_x_variant":[
        "Zavodskoy",
        "Zavodskiy"
    ],
    "wof:name":"Zavodskiy",
    "wof:placetype":"locality"
},
  "geometry": {"coordinates":[75.76666999999998,50.08333],"type":"Point"}
}