{
  "type": "Feature",
  "properties": {
    "gn:admin1_code":"15.0",
    "gn:asciiname":"Bobrovka",
    "gn:country_code":"KZ",
    "gn:dem":375,
    "gn:feature_class":"P",
    "gn:feature_code":"PPL",
    "gn:name":"Bobrovka",
    "gn:population":0,
    "gn:timezone":"Asia/Almaty",
    "iso:country":"KZ",
    "name:eng_x_preferred":[
        "Bobrovka"
    ],
    "name:kaz_x_preferred":[
        "\u0411\u043e\u0431\u0440\u043e\u0432\u043a\u0430"
    ],
    "name:rus_x_preferred":[
        "\u0411\u043e\u0431\u0440\u043e\u0432\u043a\u0430"
    ],
    "name:und_x_variant":[
        "Bobrovskoye",
        "Bobrovskoe"
    ],
    "wof:name":"Bobrovka",
    "wof:placetype":"locality"
},
  "geometry": {"coordinates":[82.7212,50.16496],"type":"Point"}
}