{
  "type": "Feature",
  "properties": {
    "gn:admin1_code":"12.0",
    "gn:asciiname":"Sarlyq",
    "gn:country_code":"KZ",
    "gn:dem":400,
    "gn:feature_class":"P",
    "gn:feature_code":"PPL",
    "gn:name":"Sarlyq",
    "gn:population":0,
    "gn:timezone":"Asia/Almaty",
    "iso:country":"KZ",
    "name:kaz_x_preferred":[
        "Sarlyq"
    ],
    "name:und_x_variant":[
        "Sarlyk"
    ],
    "wof:name":"Sarlyq",
    "wof:placetype":"locality"
},
  "geometry": {"coordinates":[66.62849,48.75866],"type":"Point"}
}