{
  "type": "Feature",
  "properties": {
    "gn:admin1_code":"12.0",
    "gn:asciiname":"Dulyghaly Meshiti",
    "gn:country_code":"KZ",
    "gn:dem":234,
    "gn:feature_class":"P",
    "gn:feature_code":"PPL",
    "gn:name":"Dulyghaly Meshiti",
    "gn:population":0,
    "gn:timezone":"Asia/Almaty",
    "iso:country":"KZ",
    "name:eng_x_preferred":[
        "Dulygalinskaya Mechet'"
    ],
    "name:kaz_x_preferred":[
        "Dulyghaly Meshiti"
    ],
    "name:rus_x_preferred":[
        "\u0414\u0443\u043b\u044b\u0433\u0430\u043b\u0438\u043d\u0441\u043a\u0430\u044f-\u041c\u0435\u0447\u0435\u0442\u044c"
    ],
    "name:und_x_variant":[
        "Dulygalinskaya Mechet\u2019"
    ],
    "wof:name":"Dulyghaly Meshiti",
    "wof:placetype":"locality"
},
  "geometry": {"coordinates":[65.75,48.53333],"type":"Point"}
}