{
  "type": "Feature",
  "properties": {
    "gn:admin1_code":"13.0",
    "gn:asciiname":"Aral",
    "gn:country_code":"KZ",
    "gn:dem":176,
    "gn:feature_class":"P",
    "gn:feature_code":"PPL",
    "gn:name":"Aral",
    "gn:population":0,
    "gn:timezone":"Asia/Qyzylorda",
    "iso:country":"KZ",
    "name:cat_x_preferred":[
        "Aral"
    ],
    "name:ceb_x_preferred":[
        "Aral"
    ],
    "name:ces_x_preferred":[
        "Aral"
    ],
    "name:deu_x_preferred":[
        "Aral"
    ],
    "name:eng_x_preferred":[
        "Aral'skoye"
    ],
    "name:fas_x_preferred":[
        "\u0622\u0631\u0627\u0644"
    ],
    "name:fra_x_preferred":[
        "Aral"
    ],
    "name:glg_x_preferred":[
        "Aral"
    ],
    "name:ita_x_preferred":[
        "Aral"
    ],
    "name:kat_x_preferred":[
        "\u10d0\u10e0\u10d0\u10da\u10d8"
    ],
    "name:kaz_x_preferred":[
        "Aral"
    ],
    "name:kaz_x_variant":[
        "\u0410\u0440\u0430\u043b"
    ],
    "name:kir_x_preferred":[
        "\u0410\u0440\u0430\u043b"
    ],
    "name:mlg_x_preferred":[
        "Aral"
    ],
    "name:mon_x_preferred":[
        "\u0410\u0440\u0430\u043b"
    ],
    "name:nld_x_preferred":[
        "Aral"
    ],
    "name:nor_x_preferred":[
        "Aral"
    ],
    "name:pol_x_preferred":[
        "Aral"
    ],
    "name:por_x_preferred":[
        "Aral"
    ],
    "name:ron_x_preferred":[
        "Aral"
    ],
    "name:rus_x_preferred":[
        "\u0410\u0440\u0430\u043b\u044c\u0441\u043a\u0438\u0439"
    ],
    "name:rus_x_variant":[
        "Aral\u2019skoye",
        "\u0410\u0440\u0430\u043b\u044c\u0441\u043a\u043e\u0435"
    ],
    "name:spa_x_preferred":[
        "Aral"
    ],
    "name:swe_x_preferred":[
        "Aral"
    ],
    "name:tur_x_preferred":[
        "Aral"
    ],
    "name:und_x_variant":[
        "Aral\u2019skiy"
    ],
    "name:vie_x_preferred":[
        "Aral"
    ],
    "wof:name":"Aral",
    "wof:placetype":"locality"
},
  "geometry": {"coordinates":[63.33881,53.8989],"type":"Point"}
}