{
  "type": "Feature",
  "properties": {
    "gn:admin1_code":"13.0",
    "gn:asciiname":"Aral",
    "gn:country_code":"KZ",
    "gn:dem":176,
    "gn:feature_class":"P",
    "gn:feature_code":"PPL",
    "gn:name":"Aral",
    "gn:population":0,
    "gn:timezone":"Asia/Qyzylorda",
    "iso:country":"KZ",
    "name:eng_x_preferred":[
        "Aral'skoye"
    ],
    "name:kaz_x_preferred":[
        "Aral"
    ],
    "name:kaz_x_variant":[
        "\u0410\u0440\u0430\u043b"
    ],
    "name:rus_x_preferred":[
        "\u0410\u0440\u0430\u043b\u044c\u0441\u043a\u0438\u0439"
    ],
    "name:rus_x_variant":[
        "Aral\u2019skoye",
        "\u0410\u0440\u0430\u043b\u044c\u0441\u043a\u043e\u0435"
    ],
    "name:und_x_variant":[
        "Aral\u2019skiy"
    ],
    "wof:name":"Aral",
    "wof:placetype":"locality"
},
  "geometry": {"coordinates":[63.33881,53.8989],"type":"Point"}
}