{
  "type": "Feature",
  "properties": {
    "gn:admin1_code":"15.0",
    "gn:asciiname":"Mangyraq",
    "gn:country_code":"KZ",
    "gn:dem":816,
    "gn:feature_class":"P",
    "gn:feature_code":"PPL",
    "gn:name":"Mangyraq",
    "gn:population":0,
    "gn:timezone":"Asia/Almaty",
    "iso:country":"KZ",
    "name:und_x_variant":[
        "Pokrovka",
        "Manyrak",
        "Mangyraq"
    ],
    "wof:name":"Mangyraq",
    "wof:placetype":"locality"
},
  "geometry": {"coordinates":[83.86253000000001,47.42939000000001],"type":"Point"}
}