{
  "type": "Feature",
  "properties": {
    "gn:admin1_code":"7.0",
    "gn:asciiname":"Orda",
    "gn:cc2":"KZ",
    "gn:country_code":"KZ",
    "gn:dem":-2,
    "gn:feature_class":"P",
    "gn:feature_code":"PPL",
    "gn:name":"Orda",
    "gn:population":0,
    "gn:timezone":"Asia/Oral",
    "iso:country":"KZ",
    "name:bel_x_preferred":[
        "\u0410\u0440\u0434\u0430"
    ],
    "name:cat_x_preferred":[
        "Orda"
    ],
    "name:ceb_x_preferred":[
        "Orda"
    ],
    "name:deu_x_preferred":[
        "Orda"
    ],
    "name:eng_x_preferred":[
        "Orda"
    ],
    "name:fra_x_preferred":[
        "Orda"
    ],
    "name:hun_x_preferred":[
        "Orda"
    ],
    "name:kaz_x_preferred":[
        "\u041e\u0440\u0434\u0430"
    ],
    "name:nor_x_preferred":[
        "Orda"
    ],
    "name:pol_x_preferred":[
        "Orda"
    ],
    "name:por_x_preferred":[
        "Orda"
    ],
    "name:rus_x_preferred":[
        "\u0423\u0440\u0434\u0430"
    ],
    "name:rus_x_variant":[
        "\u041e\u0440\u0434\u0430"
    ],
    "name:tur_x_preferred":[
        "Orda"
    ],
    "name:ukr_x_preferred":[
        "\u041e\u0440\u0434\u0430"
    ],
    "name:und_x_variant":[
        "Urda"
    ],
    "wof:name":"Orda",
    "wof:placetype":"locality"
},
  "geometry": {"coordinates":[47.42833,48.76972],"type":"Point"}
}