{
  "type": "Feature",
  "properties": {
    "gn:admin1_code":"15.0",
    "gn:asciiname":"Dom Otdykha Oblispolkoma",
    "gn:country_code":"KZ",
    "gn:dem":202,
    "gn:feature_class":"P",
    "gn:feature_code":"PPL",
    "gn:name":"Dom Otdykha Oblispolkoma",
    "gn:population":0,
    "gn:timezone":"Asia/Almaty",
    "iso:country":"KZ",
    "wof:name":"Dom Otdykha Oblispolkoma",
    "wof:placetype":"locality"
},
  "geometry": {"coordinates":[80.10798,50.48521],"type":"Point"}
}