{
  "type": "Feature",
  "properties": {
    "gn:admin1_code":"17.0",
    "gn:asciiname":"Uyym",
    "gn:country_code":"KZ",
    "gn:dem":336,
    "gn:feature_class":"P",
    "gn:feature_code":"PPL",
    "gn:name":"Uyym",
    "gn:population":0,
    "gn:timezone":"Asia/Almaty",
    "iso:country":"KZ",
    "name:kaz_x_preferred":[
        "Uyym"
    ],
    "name:kaz_x_variant":[
        "\u04b0\u0439\u044b\u043c"
    ],
    "wof:name":"Uyym",
    "wof:placetype":"locality"
},
  "geometry": {"coordinates":[69.93283000000001,43.72302],"type":"Point"}
}