{
  "type": "Feature",
  "properties": {
    "gn:admin1_code":"11.0",
    "gn:asciiname":"Presnoye",
    "gn:country_code":"KZ",
    "gn:dem":96,
    "gn:feature_class":"P",
    "gn:feature_code":"PPL",
    "gn:name":"Presnoye",
    "gn:population":0,
    "gn:timezone":"Asia/Almaty",
    "iso:country":"KZ",
    "name:eng_x_preferred":[
        "Presnoye"
    ],
    "name:kaz_x_preferred":[
        "Presnoe"
    ],
    "name:kaz_x_variant":[
        "\u041f\u0440\u0435\u0441\u043d\u043e\u0435"
    ],
    "name:rus_x_preferred":[
        "\u041f\u0440\u0435\u0441\u043d\u043e\u0435"
    ],
    "name:und_x_variant":[
        "Presnyy",
        "Presnoye"
    ],
    "wof:name":"Presnoye",
    "wof:placetype":"locality"
},
  "geometry": {"coordinates":[76.54581999999998,52.85879],"type":"Point"}
}