{
  "type": "Feature",
  "properties": {
    "gn:admin1_code":"3.0",
    "gn:asciiname":"Qarazhar",
    "gn:country_code":"KZ",
    "gn:dem":307,
    "gn:feature_class":"P",
    "gn:feature_code":"PPL",
    "gn:name":"Qarazhar",
    "gn:population":0,
    "gn:timezone":"Asia/Almaty",
    "iso:country":"KZ",
    "name:und_x_variant":[
        "Karazhar",
        "Qarazhar"
    ],
    "wof:name":"Qarazhar",
    "wof:placetype":"locality"
},
  "geometry": {"coordinates":[69.54217,50.47632],"type":"Point"}
}