{
  "type": "Feature",
  "properties": {
    "gn:admin1_code":"3.0",
    "gn:asciiname":"Vedenovka",
    "gn:country_code":"KZ",
    "gn:dem":390,
    "gn:feature_class":"P",
    "gn:feature_code":"PPL",
    "gn:name":"Vedenovka",
    "gn:population":0,
    "gn:timezone":"Asia/Almaty",
    "iso:country":"KZ",
    "name:eng_x_preferred":[
        "Vedenovka"
    ],
    "name:kaz_x_preferred":[
        "Vedenovka"
    ],
    "name:kaz_x_variant":[
        "\u0412\u0435\u0434\u0435\u043d\u043e\u0432\u043a\u0430"
    ],
    "name:rus_x_preferred":[
        "\u0412\u0435\u0434\u0435\u043d\u043e\u0432\u043a\u0430"
    ],
    "wof:name":"Vedenovka",
    "wof:placetype":"locality"
},
  "geometry": {"coordinates":[69.48911,52.60999],"type":"Point"}
}