{
  "type": "Feature",
  "properties": {
    "gn:admin1_code":"0.0",
    "gn:asciiname":"Yefremovskiy",
    "gn:cc2":"KZ",
    "gn:country_code":"KZ",
    "gn:dem":208,
    "gn:feature_class":"P",
    "gn:feature_code":"PPL",
    "gn:name":"Yefremovskiy",
    "gn:population":0,
    "gn:timezone":"Asia/Qyzylorda",
    "iso:country":"KZ",
    "name:und_x_variant":[
        "Yefremovka",
        "Yefremovskiy"
    ],
    "wof:name":"Yefremovskiy",
    "wof:placetype":"locality"
},
  "geometry": {"coordinates":[63.78333000000001,52.01667],"type":"Point"}
}