{
  "type": "Feature",
  "properties": {
    "gn:admin1_code":"16.0",
    "gn:asciiname":"Sadovka",
    "gn:country_code":"KZ",
    "gn:dem":214,
    "gn:feature_class":"P",
    "gn:feature_code":"PPL",
    "gn:name":"Sadovka",
    "gn:population":0,
    "gn:timezone":"Asia/Almaty",
    "iso:country":"KZ",
    "name:eng_x_preferred":[
        "Sadovka"
    ],
    "name:rus_x_preferred":[
        "\u0421\u0430\u0434\u043e\u0432\u043a\u0430"
    ],
    "wof:name":"Sadovka",
    "wof:placetype":"locality"
},
  "geometry": {"coordinates":[67.33179,53.43704],"type":"Point"}
}