{
  "type": "Feature",
  "properties": {
    "gn:admin1_code":"0.0",
    "gn:asciiname":"Makovka",
    "gn:country_code":"KZ",
    "gn:dem":778,
    "gn:feature_class":"P",
    "gn:feature_code":"PPL",
    "gn:name":"Makovka",
    "gn:population":0,
    "gn:timezone":"Asia/Almaty",
    "iso:country":"KZ",
    "name:eng_x_preferred":[
        "Makovka"
    ],
    "name:rus_x_preferred":[
        "\u041c\u0430\u043a\u043e\u0432\u043a\u0430"
    ],
    "name:und_x_variant":[
        "Makovskiy",
        "Makovka"
    ],
    "wof:name":"Makovka",
    "wof:placetype":"locality"
},
  "geometry": {"coordinates":[82.1177,49.33868],"type":"Point"}
}