{
  "type": "Feature",
  "properties": {
    "gn:admin1_code":"14.0",
    "gn:asciiname":"Zhanakurylys",
    "gn:country_code":"KZ",
    "gn:dem":60,
    "gn:feature_class":"P",
    "gn:feature_code":"PPL",
    "gn:name":"Zhanakurylys",
    "gn:population":0,
    "gn:timezone":"Asia/Qyzylorda",
    "iso:country":"KZ",
    "name:kaz_x_preferred":[
        "Zhangaqurylys"
    ],
    "name:und_x_variant":[
        "Zhanakurlys",
        "Zhanakurylys"
    ],
    "wof:name":"Zhanakurylys",
    "wof:placetype":"locality"
},
  "geometry": {"coordinates":[61.35,46.01667],"type":"Point"}
}