{
  "type": "Feature",
  "properties": {
    "gn:admin1_code":"11.0",
    "gn:asciiname":"Shokpar",
    "gn:country_code":"KZ",
    "gn:dem":95,
    "gn:feature_class":"P",
    "gn:feature_code":"PPL",
    "gn:name":"Shokpar",
    "gn:population":0,
    "gn:timezone":"Asia/Almaty",
    "iso:country":"KZ",
    "name:eng_x_preferred":[
        "Shokpar"
    ],
    "name:kaz_x_preferred":[
        "Shoqpar"
    ],
    "name:kaz_x_variant":[
        "\u0428\u043e\u049b\u043f\u0430\u0440"
    ],
    "name:rus_x_preferred":[
        "\u0428\u043e\u043a\u043f\u0430\u0440"
    ],
    "wof:name":"Shokpar",
    "wof:placetype":"locality"
},
  "geometry": {"coordinates":[76.23285,52.92366],"type":"Point"}
}