{
  "type": "Feature",
  "properties": {
    "gn:admin1_code":"16.0",
    "gn:asciiname":"Burluk",
    "gn:country_code":"KZ",
    "gn:dem":260,
    "gn:feature_class":"P",
    "gn:feature_code":"PPL",
    "gn:name":"Burluk",
    "gn:population":0,
    "gn:timezone":"Asia/Almaty",
    "iso:country":"KZ",
    "name:eng_x_preferred":[
        "Burluk"
    ],
    "name:kaz_x_preferred":[
        "Borlyq"
    ],
    "name:kaz_x_variant":[
        "\u0411\u043e\u0440\u043b\u044b\u049b"
    ],
    "name:rus_x_preferred":[
        "\u0411\u0443\u0440\u043b\u0443\u043a"
    ],
    "name:und_x_variant":[
        "Sovkhoz Burlukskiy"
    ],
    "wof:name":"Burluk",
    "wof:placetype":"locality"
},
  "geometry": {"coordinates":[67.97154,53.16706],"type":"Point"}
}