{
  "type": "Feature",
  "properties": {
    "gn:admin1_code":"11.0",
    "gn:asciiname":"Shorabay",
    "gn:country_code":"KZ",
    "gn:dem":345,
    "gn:feature_class":"P",
    "gn:feature_code":"PPL",
    "gn:name":"Shorabay",
    "gn:population":0,
    "gn:timezone":"Asia/Almaty",
    "iso:country":"KZ",
    "name:rus_x_preferred":[
        "\u0428\u043e\u0440\u0430\u0431\u0430\u0439"
    ],
    "wof:name":"Shorabay",
    "wof:placetype":"locality"
},
  "geometry": {"coordinates":[75.34956,50.99636],"type":"Point"}
}