{
  "type": "Feature",
  "properties": {
    "gn:admin1_code":"15.0",
    "gn:asciiname":"Kaynar",
    "gn:country_code":"KZ",
    "gn:dem":849,
    "gn:feature_class":"P",
    "gn:feature_code":"PPL",
    "gn:name":"Kaynar",
    "gn:population":0,
    "gn:timezone":"Asia/Almaty",
    "iso:country":"KZ",
    "name:kat_x_preferred":[
        "\u10d9\u10d0\u10d8\u10dc\u10d0\u10e0\u10d8"
    ],
    "name:kaz_x_preferred":[
        "\u049a\u0430\u0439\u043d\u0430\u0440"
    ],
    "name:kir_x_preferred":[
        "\u041a\u0430\u0439\u043d\u0430\u0440"
    ],
    "name:rus_x_preferred":[
        "\u041a\u0430\u0439\u043d\u0430\u0440"
    ],
    "name:tat_x_preferred":[
        "\u041a\u0430\u0439\u043d\u0430\u0440"
    ],
    "name:uzb_x_preferred":[
        "Qaynar"
    ],
    "wof:name":"Kaynar",
    "wof:placetype":"locality"
},
  "geometry": {"coordinates":[77.38226999999998,49.20041],"type":"Point"}
}