{
  "type": "Feature",
  "properties": {
    "gn:admin1_code":"17.0",
    "gn:asciiname":"Qazan",
    "gn:country_code":"KZ",
    "gn:dem":1014,
    "gn:feature_class":"P",
    "gn:feature_code":"PPL",
    "gn:name":"Qazan",
    "gn:population":0,
    "gn:timezone":"Asia/Almaty",
    "iso:country":"KZ",
    "name:kaz_x_preferred":[
        "Qazan"
    ],
    "name:kaz_x_variant":[
        "\u049a\u0430\u0437\u0430\u043d"
    ],
    "name:rus_x_preferred":[
        "\u041a\u0430\u0437\u0430\u043d\u043a\u0430"
    ],
    "name:und_x_variant":[
        "Kazanskoye",
        "Kazanka"
    ],
    "wof:name":"Qazan",
    "wof:placetype":"locality"
},
  "geometry": {"coordinates":[70.55969,42.68784],"type":"Point"}
}