{
  "type": "Feature",
  "properties": {
    "gn:admin1_code":"10.0",
    "gn:asciiname":"Zhanauyym",
    "gn:country_code":"KZ",
    "gn:dem":855,
    "gn:feature_class":"P",
    "gn:feature_code":"PPL",
    "gn:name":"Zhanauyym",
    "gn:population":0,
    "gn:timezone":"Asia/Almaty",
    "iso:country":"KZ",
    "name:run_x_preferred":[
        "\u0416\u0430\u043d\u0430\u0443\u0439\u044b\u043c"
    ],
    "name:rus_x_preferred":[
        "\u041a\u043e\u043a\u0442\u0435\u0440\u0435\u043d"
    ],
    "name:und_x_variant":[
        "Kokterek",
        "Kokteren"
    ],
    "wof:name":"Zhanauyym",
    "wof:placetype":"locality"
},
  "geometry": {"coordinates":[69.92999,42.1555],"type":"Point"}
}