{
  "type": "Feature",
  "properties": {
    "gn:admin1_code":"10.0",
    "gn:asciiname":"Nysanbek",
    "gn:country_code":"KZ",
    "gn:dem":1266,
    "gn:feature_class":"P",
    "gn:feature_code":"PPL",
    "gn:name":"Nysanbek",
    "gn:population":0,
    "gn:timezone":"Asia/Almaty",
    "iso:country":"KZ",
    "name:rus_x_preferred":[
        "\u041d\u044b\u0441\u0430\u043d\u0431\u0435\u043a"
    ],
    "wof:name":"Nysanbek",
    "wof:placetype":"locality"
},
  "geometry": {"coordinates":[70.07949000000001,42.17642],"type":"Point"}
}