{
  "type": "Feature",
  "properties": {
    "gn:admin1_code":"14.0",
    "gn:asciiname":"Otdeleniye Nomer Tri Kolkhoza Kalinina",
    "gn:country_code":"KZ",
    "gn:dem":743,
    "gn:feature_class":"P",
    "gn:feature_code":"PPLF",
    "gn:name":"Otdeleniye Nomer Tri Kolkhoza Kalinina",
    "gn:population":0,
    "gn:timezone":"Asia/Almaty",
    "iso:country":"KZ",
    "name:rus_x_preferred":[
        "\u041e\u0442\u0434\u0435\u043b\u0435\u043d\u0438\u0435 \u041d\u043e\u043c\u0435\u0440 \u0422\u0440\u0438 \u041a\u043e\u043b\u0445\u043e\u0437\u0430 \u041a\u0430\u043b\u0438\u043d\u0438\u043d\u0430"
    ],
    "wof:name":"Otdeleniye Nomer Tri Kolkhoza Kalinina",
    "wof:placetype":"locality"
},
  "geometry": {"coordinates":[75.18770000000001,43.47729],"type":"Point"}
}