{
  "type": "Feature",
  "properties": {
    "gn:admin1_code":"12.0",
    "gn:asciiname":"Sarbas",
    "gn:country_code":"KZ",
    "gn:dem":220,
    "gn:feature_class":"P",
    "gn:feature_code":"PPL",
    "gn:name":"Sarbas",
    "gn:population":0,
    "gn:timezone":"Asia/Almaty",
    "iso:country":"KZ",
    "name:und_x_variant":[
        "Sarybas",
        "Sarbas"
    ],
    "wof:name":"Sarbas",
    "wof:placetype":"locality"
},
  "geometry": {"coordinates":[66.09466999999999,49.32471],"type":"Point"}
}