{
  "type": "Feature",
  "properties": {
    "gn:admin1_code":"6.0",
    "gn:asciiname":"Monash Letniy",
    "gn:country_code":"KZ",
    "gn:dem":-25,
    "gn:feature_class":"P",
    "gn:feature_code":"PPL",
    "gn:name":"Monash Letniy",
    "gn:population":0,
    "gn:timezone":"Asia/Atyrau",
    "iso:country":"KZ",
    "name:und_x_variant":[
        "Monach",
        "Mokash-Letniy",
        "Monash Letniy"
    ],
    "wof:name":"Monash Letniy",
    "wof:placetype":"locality"
},
  "geometry": {"coordinates":[50.46667,47.05],"type":"Point"}
}