{
  "type": "Feature",
  "properties": {
    "gn:admin1_code":"16.0",
    "gn:asciiname":"Karagay-Terek",
    "gn:country_code":"KZ",
    "gn:dem":136,
    "gn:feature_class":"P",
    "gn:feature_code":"PPL",
    "gn:name":"Karagay-Terek",
    "gn:population":0,
    "gn:timezone":"Asia/Almaty",
    "iso:country":"KZ",
    "wof:name":"Karagay-Terek",
    "wof:placetype":"locality"
},
  "geometry": {"coordinates":[71.28333000000001,53.78333000000001],"type":"Point"}
}