{
  "type": "Feature",
  "properties": {
    "gn:admin1_code":"11.0",
    "gn:asciiname":"Zhanaturmys",
    "gn:country_code":"KZ",
    "gn:dem":150,
    "gn:feature_class":"P",
    "gn:feature_code":"PPL",
    "gn:name":"Zhanaturmys",
    "gn:population":0,
    "gn:timezone":"Asia/Almaty",
    "iso:country":"KZ",
    "name:kaz_x_preferred":[
        "Mayt\u00fcbek"
    ],
    "name:kaz_x_variant":[
        "\u041c\u0430\u0439\u0442\u04af\u0431\u0435\u043a"
    ],
    "name:rus_x_preferred":[
        "\u0416\u0430\u043d\u0430\u0442\u0443\u0440\u043c\u044b\u0441"
    ],
    "name:und_x_variant":[
        "Voroshilovgradskiy",
        "Sputnik",
        "Zhanaturmys",
        "Zhangaturmys"
    ],
    "wof:name":"Zhanaturmys",
    "wof:placetype":"locality"
},
  "geometry": {"coordinates":[78.04528000000001,51.125],"type":"Point"}
}