{
  "type": "Feature",
  "properties": {
    "gn:admin1_code":"12.0",
    "gn:asciiname":"Balabay",
    "gn:country_code":"KZ",
    "gn:dem":420,
    "gn:feature_class":"P",
    "gn:feature_code":"PPL",
    "gn:name":"Balabay",
    "gn:population":0,
    "gn:timezone":"Asia/Almaty",
    "iso:country":"KZ",
    "name:kaz_x_preferred":[
        "Balabay"
    ],
    "name:kaz_x_variant":[
        "\u0411\u0430\u043b\u0430\u0431\u0430\u0439"
    ],
    "wof:name":"Balabay",
    "wof:placetype":"locality"
},
  "geometry": {"coordinates":[68.05785,48.4175],"type":"Point"}
}