{
  "type": "Feature",
  "properties": {
    "iso:country":"KZ",
    "name:ara_x_preferred":[
        "\u0643\u0648\u0644\u0633\u0627\u0631\u064a"
    ],
    "name:bel_x_preferred":[
        "\u041a\u0443\u043b\u044c\u0441\u0430\u0440\u044b"
    ],
    "name:ceb_x_preferred":[
        "Qulsary"
    ],
    "name:deu_x_preferred":[
        "Qulsary"
    ],
    "name:ell_x_preferred":[
        "\u039a\u03bf\u03c5\u03bb\u03c3\u03ac\u03c1\u03b9"
    ],
    "name:eng_x_preferred":[
        "Kulsary"
    ],
    "name:fin_x_preferred":[
        "Qulsar\u0131"
    ],
    "name:fra_x_preferred":[
        "Koulsary"
    ],
    "name:heb_x_preferred":[
        "\u05e7\u05d5\u05dc\u05e1\u05e8\u05d9"
    ],
    "name:hsb_x_preferred":[
        "Kulsary"
    ],
    "name:kaz_x_preferred":[
        "\u049a\u04b1\u043b\u0441\u0430\u0440\u044b"
    ],
    "name:lit_x_preferred":[
        "Kulsari"
    ],
    "name:msa_x_preferred":[
        "Kulsary"
    ],
    "name:nld_x_preferred":[
        "Kulsary"
    ],
    "name:nob_x_preferred":[
        "Qulsary"
    ],
    "name:pol_x_preferred":[
        "Ku\u0142sary"
    ],
    "name:por_x_preferred":[
        "Kulsary"
    ],
    "name:rus_x_preferred":[
        "\u041a\u0443\u043b\u044c\u0441\u0430\u0440\u044b"
    ],
    "name:spa_x_preferred":[
        "Kulsary"
    ],
    "name:swe_x_preferred":[
        "Kulsary"
    ],
    "name:tat_x_preferred":[
        "\u041a\u043e\u043b\u0441\u0430\u0440\u044b"
    ],
    "name:tuk_x_preferred":[
        "Qulsary"
    ],
    "name:udm_x_preferred":[
        "\u041a\u0443\u043b\u0441\u0430\u0440\u044b"
    ],
    "name:ukr_x_preferred":[
        "\u041a\u0443\u043b\u044c\u0441\u0430\u0440\u0438"
    ],
    "name:und_x_variant":[
        "Kul'sary"
    ],
    "name:uzb_x_preferred":[
        "Qulsari"
    ],
    "name:zho_x_preferred":[
        "\u5eab\u5229\u85a9\u96f7"
    ],
    "qs:gn_country":"KZ",
    "qs:gn_fcode":"PPL",
    "qs:gn_pop":51216,
    "qs:name":"Kulsary",
    "qs:name_adm0":"Kazakhstan",
    "qs:name_adm1":"Atyrau",
    "qs:photos":0,
    "qs:photos_1k":0,
    "qs:photos_9k":0,
    "qs:photos_9r":0,
    "qs:photos_all":0,
    "qs:photos_sr":0,
    "qs:placetype":"Town",
    "qs:pop_sr":"8",
    "qs:woe_adm0":23424871,
    "wd:wordcount":123,
    "wof:name":"Kulsary",
    "wof:placetype":"locality",
    "wof:population":51216
},
  "geometry": {"coordinates":[54.01978,46.95307],"type":"Point"}
}