{
  "type": "Feature",
  "properties": {
    "gn:admin1_code":"13.0",
    "gn:asciiname":"Aralbay",
    "gn:country_code":"KZ",
    "gn:dem":102,
    "gn:feature_class":"P",
    "gn:feature_code":"PPL",
    "gn:name":"Aralbay",
    "gn:population":0,
    "gn:timezone":"Asia/Almaty",
    "iso:country":"KZ",
    "name:eng_x_preferred":[
        "Aralbay"
    ],
    "name:rus_x_preferred":[
        "\u0410\u0440\u0430\u043b\u0431\u0430\u0439"
    ],
    "wof:name":"Aralbay",
    "wof:placetype":"locality"
},
  "geometry": {"coordinates":[64.00995999999999,49.77221],"type":"Point"}
}