{
  "type": "Feature",
  "properties": {
    "gn:admin1_code":"10.0",
    "gn:asciiname":"Otdeleniye Nomer Odin Uchastka Nomer Odin Sovkhoza Pobedy",
    "gn:country_code":"KZ",
    "gn:dem":265,
    "gn:feature_class":"P",
    "gn:feature_code":"PPLF",
    "gn:name":"Otdeleniye Nomer Odin Uchastka Nomer Odin Sovkhoza Pobedy",
    "gn:population":0,
    "gn:timezone":"Asia/Almaty",
    "iso:country":"KZ",
    "name:rus_x_preferred":[
        "\u041e\u0442\u0434\u0435\u043b\u0435\u043d\u0438\u0435 \u041d\u043e\u043c\u0435\u0440 \u041e\u0434\u0438\u043d \u0423\u0447\u0430\u0441\u0442\u043a\u0430 \u041d\u043e\u043c\u0435\u0440 \u041e\u0434\u0438\u043d \u0421\u043e\u0432\u0445\u043e\u0437\u0430 \u041f\u043e\u0431\u0435\u0434\u044b"
    ],
    "wof:name":"Otdeleniye Nomer Odin Uchastka Nomer Odin Sovkhoza Pobedy",
    "wof:placetype":"locality"
},
  "geometry": {"coordinates":[68.29173,40.90711],"type":"Point"}
}