{
  "type": "Feature",
  "properties": {
    "gn:admin1_code":"16.0",
    "gn:asciiname":"Afanas'yevka",
    "gn:country_code":"KZ",
    "gn:dem":201,
    "gn:feature_class":"P",
    "gn:feature_code":"PPL",
    "gn:name":"Afanas\u2019yevka",
    "gn:population":0,
    "gn:timezone":"Asia/Almaty",
    "iso:country":"KZ",
    "name:eng_x_preferred":[
        "Afanas'yevka"
    ],
    "name:kaz_x_preferred":[
        "Afanas\u2019evka"
    ],
    "name:rus_x_preferred":[
        "\u0410\u0444\u0430\u043d\u0430\u0441\u044c\u0435\u0432\u043a\u0430"
    ],
    "name:rus_x_variant":[
        "Afanas\u2019yevka"
    ],
    "wof:name":"Afanas'yevka",
    "wof:placetype":"locality"
},
  "geometry": {"coordinates":[67.24231,53.50294],"type":"Point"}
}