{
  "type": "Feature",
  "properties": {
    "gn:admin1_code":"10.0",
    "gn:asciiname":"Malaykuduk",
    "gn:country_code":"KZ",
    "gn:dem":314,
    "gn:feature_class":"P",
    "gn:feature_code":"PPL",
    "gn:name":"Malaykuduk",
    "gn:population":0,
    "gn:timezone":"Asia/Almaty",
    "iso:country":"KZ",
    "name:kaz_x_preferred":[
        "\u00c4limta\u016b"
    ],
    "name:kaz_x_variant":[
        "\u04d8\u043b\u0456\u043c\u0442\u0430\u0443"
    ],
    "name:rus_x_preferred":[
        "\u041c\u0430\u043b\u0430\u0439\u043a\u0443\u0434\u0443\u043a"
    ],
    "name:und_x_variant":[
        "Alimtau"
    ],
    "wof:name":"Malaykuduk",
    "wof:placetype":"locality"
},
  "geometry": {"coordinates":[68.41237,41.70173],"type":"Point"}
}