{
  "type": "Feature",
  "properties": {
    "gn:admin1_code":"10.0",
    "gn:asciiname":"Zhaydak",
    "gn:country_code":"KZ",
    "gn:dem":403,
    "gn:feature_class":"P",
    "gn:feature_code":"PPL",
    "gn:name":"Zhaydak",
    "gn:population":0,
    "gn:timezone":"Asia/Almaty",
    "iso:country":"KZ",
    "name:kaz_x_preferred":[
        "Zhaydaqqudyq"
    ],
    "name:kaz_x_variant":[
        "\u0416\u0430\u0439\u0434\u0430\u049b\u049b\u04b1\u0434\u044b\u049b"
    ],
    "name:rus_x_preferred":[
        "\u0416\u0430\u0439\u0434\u0430\u043a"
    ],
    "name:und_x_variant":[
        "Zhaydakkuduk"
    ],
    "wof:name":"Zhaydak",
    "wof:placetype":"locality"
},
  "geometry": {"coordinates":[68.5647,41.6494],"type":"Point"}
}