{
  "type": "Feature",
  "properties": {
    "gn:admin1_code":"4.0",
    "gn:asciiname":"Sibiryak",
    "gn:country_code":"KZ",
    "gn:dem":392,
    "gn:feature_class":"P",
    "gn:feature_code":"PPL",
    "gn:name":"Sibiryak",
    "gn:population":0,
    "gn:timezone":"Asia/Aqtobe",
    "iso:country":"KZ",
    "name:rus_x_preferred":[
        "\u0421\u0438\u0431\u0438\u0440\u044f\u043a"
    ],
    "wof:name":"Sibiryak",
    "wof:placetype":"locality"
},
  "geometry": {"coordinates":[58.13333000000001,50.31667],"type":"Point"}
}