{
  "type": "Feature",
  "properties": {
    "gn:admin1_code":"11.0",
    "gn:asciiname":"Karazhar",
    "gn:country_code":"KZ",
    "gn:dem":525,
    "gn:feature_class":"P",
    "gn:feature_code":"PPL",
    "gn:name":"Karazhar",
    "gn:population":0,
    "gn:timezone":"Asia/Almaty",
    "iso:country":"KZ",
    "name:kaz_x_preferred":[
        "Qarazhar"
    ],
    "name:kaz_x_variant":[
        "\u049a\u0430\u0440\u0430\u0436\u0430\u0440"
    ],
    "name:rus_x_preferred":[
        "\u041a\u0430\u0440\u0430\u0436\u0430\u0440"
    ],
    "wof:name":"Karazhar",
    "wof:placetype":"locality"
},
  "geometry": {"coordinates":[75.53888000000001,50.72055],"type":"Point"}
}