{
  "type": "Feature",
  "properties": {
    "gn:admin1_code":"6.0",
    "gn:asciiname":"Eltay",
    "gn:country_code":"KZ",
    "gn:dem":-14,
    "gn:feature_class":"P",
    "gn:feature_code":"PPL",
    "gn:name":"Eltay",
    "gn:population":0,
    "gn:timezone":"Asia/Atyrau",
    "iso:country":"KZ",
    "name:eng_x_preferred":[
        "Yel'tay"
    ],
    "name:rus_x_preferred":[
        "\u0415\u043b\u044c\u0442\u0430\u0439"
    ],
    "name:und_x_variant":[
        "Yel\u2019tay",
        "Eltay"
    ],
    "wof:name":"Eltay",
    "wof:placetype":"locality"
},
  "geometry": {"coordinates":[51.61667,48.56667],"type":"Point"}
}