{
  "type": "Feature",
  "properties": {
    "gn:admin1_code":"12.0",
    "gn:asciiname":"Nomir Toghyzynshy",
    "gn:country_code":"KZ",
    "gn:dem":681,
    "gn:feature_class":"P",
    "gn:feature_code":"PPL",
    "gn:name":"N\u00f6mir Toghyzynshy",
    "gn:population":0,
    "gn:timezone":"Asia/Almaty",
    "iso:country":"KZ",
    "name:kaz_x_preferred":[
        "N\u00f6mir Toghyzynshy"
    ],
    "name:kaz_x_variant":[
        "\u041d\u04e9\u043c\u0456\u0440 \u0422\u043e\u0493\u044b\u0437\u044b\u043d\u0448\u044b"
    ],
    "name:rus_x_preferred":[
        "Nomer Devyat\u2019"
    ],
    "name:rus_x_variant":[
        "\u041d\u043e\u043c\u0435\u0440 \u0414\u0435\u0432\u044f\u0442\u044c"
    ],
    "wof:name":"Nomir Toghyzynshy",
    "wof:placetype":"locality"
},
  "geometry": {"coordinates":[75.60695,49.68284],"type":"Point"}
}