{
  "type": "Feature",
  "properties": {
    "gn:admin1_code":"10.0",
    "gn:asciiname":"Sovkhoz Imeni Abaya",
    "gn:country_code":"KZ",
    "gn:dem":290,
    "gn:feature_class":"P",
    "gn:feature_code":"PPL",
    "gn:name":"Sovkhoz Imeni Abaya",
    "gn:population":0,
    "gn:timezone":"Asia/Almaty",
    "iso:country":"KZ",
    "name:kaz_x_preferred":[
        "Zh\u012byrma Eki Parts\u201dyezd"
    ],
    "name:kaz_x_variant":[
        "\u0416\u0438\u044b\u0440\u043c\u0430 \u0415\u043a\u0456\u043d\u0448\u0456 \u041f\u0430\u0440\u0442\u0441\u044a\u0435\u0437\u0434"
    ],
    "name:rus_x_preferred":[
        "Dvatsat\u2019 Vtoroy Parts\u201dyezd"
    ],
    "name:rus_x_variant":[
        "\u0414\u0432\u0430\u0446\u0430\u0442\u044c \u0412\u0442\u043e\u0440\u043e\u0439 \u041f\u0430\u0440\u0442\u0441\u044a\u0435\u0437\u0434"
    ],
    "name:und_x_variant":[
        "XXII Parts\u2019yezd",
        "Otdeleniye Imeni Dvadtsat Vtorogo Parts\u2019yezda Sovkhoza Imeni Abaya",
        "Otdeleniye Imeni Dvadtsat Vtorogo Parts\u2019yezda",
        "Sovkhoz Imeni Abaya",
        "Dvadtsat\u2019 Vtoroy Parts\u2019yezd"
    ],
    "wof:name":"Sovkhoz Imeni Abaya",
    "wof:placetype":"locality"
},
  "geometry": {"coordinates":[68.66174000000001,41.2904],"type":"Point"}
}