{
  "type": "Feature",
  "properties": {
    "gn:admin1_code":"13.0",
    "gn:asciiname":"Nagornoye",
    "gn:cc2":"KZ",
    "gn:country_code":"KZ",
    "gn:dem":178,
    "gn:feature_class":"P",
    "gn:feature_code":"PPL",
    "gn:name":"Nagornoye",
    "gn:population":0,
    "gn:timezone":"Asia/Qyzylorda",
    "iso:country":"KZ",
    "name:kaz_x_preferred":[
        "Nagornoe"
    ],
    "name:kaz_x_variant":[
        "\u041d\u0430\u0433\u043e\u0440\u043d\u043e\u0435"
    ],
    "name:und_x_variant":[
        "Nagornyy",
        "Nagornoye"
    ],
    "wof:name":"Nagornoye",
    "wof:placetype":"locality"
},
  "geometry": {"coordinates":[62.95778000000001,52.83278000000001],"type":"Point"}
}