{
  "type": "Feature",
  "properties": {
    "gn:admin1_code":"4.0",
    "gn:asciiname":"Kyrykkuduk",
    "gn:country_code":"KZ",
    "gn:dem":268,
    "gn:feature_class":"P",
    "gn:feature_code":"PPL",
    "gn:name":"Kyrykkuduk",
    "gn:population":0,
    "gn:timezone":"Asia/Aqtobe",
    "iso:country":"KZ",
    "name:eng_x_preferred":[
        "Kyrykkuduk"
    ],
    "name:kaz_x_preferred":[
        "Qyryqqudyq"
    ],
    "name:rus_x_preferred":[
        "\u041a\u0430\u0440\u044b\u043a\u0443\u0434\u0443\u043a"
    ],
    "wof:name":"Kyrykkuduk",
    "wof:placetype":"locality"
},
  "geometry": {"coordinates":[61.2219,49.91518],"type":"Point"}
}