{
  "type": "Feature",
  "properties": {
    "gn:admin1_code":"3.0",
    "gn:asciiname":"Karabulak",
    "gn:country_code":"KZ",
    "gn:dem":369,
    "gn:feature_class":"P",
    "gn:feature_code":"PPL",
    "gn:name":"Karabulak",
    "gn:population":0,
    "gn:timezone":"Asia/Almaty",
    "iso:country":"KZ",
    "name:ceb_x_preferred":[
        "Karabulak"
    ],
    "name:ces_x_preferred":[
        "Karabulak"
    ],
    "name:che_x_preferred":[
        "\u041a\u0430\u0440\u0430\u0431\u0443\u043b\u0430\u043a"
    ],
    "name:deu_x_preferred":[
        "Karabulak"
    ],
    "name:eng_x_preferred":[
        "Karabulak"
    ],
    "name:ita_x_preferred":[
        "Karabulak"
    ],
    "name:kaz_x_preferred":[
        "Qarabulaq"
    ],
    "name:kaz_x_variant":[
        "\u049a\u0430\u0440\u0430\u0431\u04b1\u043b\u0430\u049b"
    ],
    "name:nld_x_preferred":[
        "Karaboelak"
    ],
    "name:pol_x_preferred":[
        "Karabu\u0142ak"
    ],
    "name:rus_x_preferred":[
        "\u041a\u0430\u0440\u0430\u0431\u0443\u043b\u0430\u043a"
    ],
    "name:swe_x_preferred":[
        "Karabulak"
    ],
    "name:tat_x_preferred":[
        "\u041a\u0430\u0440\u0430\u0431\u0443\u043b\u0430\u043a"
    ],
    "name:tgl_x_preferred":[
        "Karabulak"
    ],
    "name:tur_x_preferred":[
        "Karabulak"
    ],
    "name:ukr_x_preferred":[
        "\u041a\u0430\u0440\u0430\u0431\u0443\u043b\u0430\u043a"
    ],
    "wof:name":"Karabulak",
    "wof:placetype":"locality"
},
  "geometry": {"coordinates":[69.60186999999999,52.92459],"type":"Point"}
}