{
  "type": "Feature",
  "properties": {
    "gn:admin1_code":"11.0",
    "gn:asciiname":"Zhabas",
    "gn:country_code":"KZ",
    "gn:dem":118,
    "gn:feature_class":"P",
    "gn:feature_code":"PPL",
    "gn:name":"Zhabas",
    "gn:population":0,
    "gn:timezone":"Asia/Almaty",
    "iso:country":"KZ",
    "name:und_x_variant":[
        "Dzhabas",
        "Zhabas"
    ],
    "wof:name":"Zhabas",
    "wof:placetype":"locality"
},
  "geometry": {"coordinates":[75.61667,51.86667],"type":"Point"}
}