{
  "type": "Feature",
  "properties": {
    "gn:admin1_code":"4.0",
    "gn:asciiname":"Konzhar",
    "gn:country_code":"KZ",
    "gn:dem":192,
    "gn:feature_class":"P",
    "gn:feature_code":"PPL",
    "gn:name":"Konzhar",
    "gn:population":0,
    "gn:timezone":"Asia/Aqtobe",
    "iso:country":"KZ",
    "name:eng_x_preferred":[
        "Konzhar"
    ],
    "name:rus_x_preferred":[
        "\u041a\u0443\u043d\u0436\u0430\u0440"
    ],
    "wof:name":"Konzhar",
    "wof:placetype":"locality"
},
  "geometry": {"coordinates":[56.71666999999999,49.38333],"type":"Point"}
}