{
  "type": "Feature",
  "properties": {
    "gn:admin1_code":"1.0",
    "gn:asciiname":"Zhetygen",
    "gn:country_code":"KZ",
    "gn:dem":510,
    "gn:feature_class":"P",
    "gn:feature_code":"PPL",
    "gn:name":"Zhetygen",
    "gn:population":0,
    "gn:timezone":"Asia/Almaty",
    "iso:country":"KZ",
    "name:rus_x_preferred":[
        "\u0416\u0435\u0442\u044b\u0433\u0435\u043d"
    ],
    "wof:name":"Zhetygen",
    "wof:placetype":"locality"
},
  "geometry": {"coordinates":[77.13105,43.69575],"type":"Point"}
}