{
  "type": "Feature",
  "properties": {
    "gn:admin1_code":"1.0",
    "gn:asciiname":"Targan",
    "gn:country_code":"KZ",
    "gn:dem":748,
    "gn:feature_class":"P",
    "gn:feature_code":"PPL",
    "gn:name":"Targan",
    "gn:population":0,
    "gn:timezone":"Asia/Almaty",
    "iso:country":"KZ",
    "name:kaz_x_preferred":[
        "Targhap"
    ],
    "name:und_x_variant":[
        "Stanovishche Targap",
        "Targap",
        "Targan"
    ],
    "wof:name":"Targan",
    "wof:placetype":"locality"
},
  "geometry": {"coordinates":[75.84039,43.33062],"type":"Point"}
}