{
  "type": "Feature",
  "properties": {
    "gn:admin1_code":"0.0",
    "gn:asciiname":"Zhanaturmys",
    "gn:country_code":"KZ",
    "gn:dem":135,
    "gn:feature_class":"P",
    "gn:feature_code":"PPL",
    "gn:name":"Zhanaturmys",
    "gn:population":0,
    "gn:timezone":"Asia/Almaty",
    "iso:country":"KZ",
    "name:eng_x_preferred":[
        "Zhanaturmys"
    ],
    "name:rus_x_preferred":[
        "\u0416\u0430\u043d\u0430\u0442\u0443\u0440\u043c\u044b\u0441"
    ],
    "wof:name":"Zhanaturmys",
    "wof:placetype":"locality"
},
  "geometry": {"coordinates":[65.14108,50.16448],"type":"Point"}
}