{
  "type": "Feature",
  "properties": {
    "gn:admin1_code":"0.0",
    "gn:asciiname":"Sholaksandykskiy Tretiy",
    "gn:country_code":"KZ",
    "gn:dem":229,
    "gn:feature_class":"P",
    "gn:feature_code":"PPL",
    "gn:name":"Sholaksandykskiy Tretiy",
    "gn:population":0,
    "gn:timezone":"Asia/Almaty",
    "iso:country":"KZ",
    "wof:name":"Sholaksandykskiy Tretiy",
    "wof:placetype":"locality"
},
  "geometry": {"coordinates":[66.45997,51.63582],"type":"Point"}
}