{
  "type": "Feature",
  "properties": {
    "gn:admin1_code":"1.0",
    "gn:asciiname":"Nadek",
    "gn:country_code":"KZ",
    "gn:dem":835,
    "gn:feature_class":"P",
    "gn:feature_code":"PPL",
    "gn:name":"Nadek",
    "gn:population":0,
    "gn:timezone":"Asia/Almaty",
    "iso:country":"KZ",
    "name:kaz_x_preferred":[
        "\u041d\u0430\u0434\u0435\u043a"
    ],
    "name:und_x_variant":[
        "Akhtypeylyk",
        "Nadek"
    ],
    "wof:name":"Nadek",
    "wof:placetype":"locality"
},
  "geometry": {"coordinates":[80.14203000000001,44.26553],"type":"Point"}
}