{
  "type": "Feature",
  "properties": {
    "iso:country":"KZ",
    "name:dut_x_preferred":[
        "Kurchatov"
    ],
    "name:eng_x_preferred":[
        "Kurchatov"
    ],
    "name:est_x_preferred":[
        "Kurt\u0161atov"
    ],
    "name:fre_x_preferred":[
        "Kourtchatov"
    ],
    "name:ger_x_preferred":[
        "Kurtschatow"
    ],
    "name:jpn_x_preferred":[
        "\u30af\u30eb\u30c1\u30e3\u30c8\u30d5"
    ],
    "name:kaz_x_preferred":[
        "\u041a\u0443\u0440\u0447\u0430\u0442\u043e\u0432"
    ],
    "name:kor_x_preferred":[
        "\ucfe0\ub974\ucc28\ud1a0\ud504"
    ],
    "name:lit_x_preferred":[
        "Kur\u010diatovas"
    ],
    "name:nob_x_preferred":[
        "Kurtsjatov"
    ],
    "name:pol_x_preferred":[
        "Kurczatow"
    ],
    "name:rus_x_preferred":[
        "\u041a\u0443\u0440\u0447\u0430\u0442\u043e\u0432"
    ],
    "name:spa_x_preferred":[
        "Kurch\u00e1tov"
    ],
    "name:swe_x_preferred":[
        "Kurtjatov"
    ],
    "name:unk_x_variant":[
        "Konechnaya"
    ],
    "name:uzb_x_preferred":[
        "Kurchatov"
    ],
    "qs:gn_country":"KZ",
    "qs:gn_fcode":"PPL",
    "qs:gn_pop":10747,
    "qs:name":"Moldary",
    "qs:name_adm0":"Kazakhstan",
    "qs:name_adm1":"Pavlodar",
    "qs:photos":52,
    "qs:photos_1k":11,
    "qs:photos_9k":1,
    "qs:photos_9r":2,
    "qs:photos_all":52,
    "qs:photos_sr":2,
    "qs:placetype":"Town",
    "qs:pop_sr":"6",
    "qs:woe_adm0":23424871,
    "wof:name":"Moldary",
    "wof:placetype":"locality",
    "wof:population":10747
},
  "geometry": {"coordinates":[78.54188000000001,50.75617],"type":"Point"}
}