{
  "type": "Feature",
  "properties": {
    "gn:admin1_code":"11.0",
    "gn:asciiname":"Novoalekseyevka",
    "gn:country_code":"KZ",
    "gn:dem":110,
    "gn:feature_class":"P",
    "gn:feature_code":"PPL",
    "gn:name":"Novoalekseyevka",
    "gn:population":0,
    "gn:timezone":"Asia/Almaty",
    "iso:country":"KZ",
    "name:eng_x_preferred":[
        "Zholboldy"
    ],
    "name:kaz_x_preferred":[
        "\u0416\u043e\u043b\u0431\u043e\u043b\u0434\u044b"
    ],
    "name:rus_x_preferred":[
        "\u041d\u043e\u0432\u043e\u0430\u043b\u0435\u043a\u0441\u0435\u0435\u0432\u043a\u0430"
    ],
    "name:und_x_variant":[
        "Novo-Alekseyevskiy",
        "Novoalekseevka",
        "Novoalekseyevka"
    ],
    "wof:name":"Novoalekseyevka",
    "wof:placetype":"locality"
},
  "geometry": {"coordinates":[74.89782,52.79600000000001],"type":"Point"}
}