{
  "type": "Feature",
  "properties": {
    "gn:admin1_code":"6.0",
    "gn:asciiname":"Kindyksay",
    "gn:country_code":"KZ",
    "gn:dem":36,
    "gn:feature_class":"P",
    "gn:feature_code":"PPL",
    "gn:name":"Kindyksay",
    "gn:population":0,
    "gn:timezone":"Asia/Atyrau",
    "iso:country":"KZ",
    "name:eng_x_preferred":[
        "Kindyksay"
    ],
    "name:rus_x_preferred":[
        "\u041a\u0438\u043d\u0434\u0438\u043a\u0441\u0430\u0439"
    ],
    "wof:name":"Kindyksay",
    "wof:placetype":"locality"
},
  "geometry": {"coordinates":[53.87153000000001,48.94496],"type":"Point"}
}