{
  "type": "Feature",
  "properties": {
    "gn:admin1_code":"17.0",
    "gn:asciiname":"Altynaryk",
    "gn:country_code":"KZ",
    "gn:dem":608,
    "gn:feature_class":"P",
    "gn:feature_code":"PPL",
    "gn:name":"Altynaryk",
    "gn:population":0,
    "gn:timezone":"Asia/Almaty",
    "iso:country":"KZ",
    "name:kaz_x_preferred":[
        "Altynaryq"
    ],
    "name:kaz_x_variant":[
        "\u0410\u043b\u0442\u044b\u043d\u0430\u0440\u044b\u049b"
    ],
    "name:rus_x_preferred":[
        "\u0410\u043b\u0442\u044b\u043d\u0430\u0440\u044b\u043a"
    ],
    "wof:name":"Altynaryk",
    "wof:placetype":"locality"
},
  "geometry": {"coordinates":[73.42574,43.07134],"type":"Point"}
}