{
  "type": "Feature",
  "properties": {
    "gn:admin1_code":"13.0",
    "gn:asciiname":"Maksut",
    "gn:country_code":"KZ",
    "gn:dem":196,
    "gn:feature_class":"P",
    "gn:feature_code":"PPL",
    "gn:name":"Maksut",
    "gn:population":0,
    "gn:timezone":"Asia/Qyzylorda",
    "iso:country":"KZ",
    "name:eng_x_preferred":[
        "Maksut"
    ],
    "name:kaz_x_preferred":[
        "Maqsut"
    ],
    "name:kaz_x_variant":[
        "\u041c\u0430\u049b\u0441\u04b1\u0442"
    ],
    "name:rus_x_preferred":[
        "\u041c\u0430\u043a\u0441\u0443\u0442"
    ],
    "wof:name":"Maksut",
    "wof:placetype":"locality"
},
  "geometry": {"coordinates":[63.00424,52.17065],"type":"Point"}
}