{
  "type": "Feature",
  "properties": {
    "gn:admin1_code":"0.0",
    "gn:asciiname":"Deurechnyy",
    "gn:country_code":"KZ",
    "gn:dem":224,
    "gn:feature_class":"P",
    "gn:feature_code":"PPL",
    "gn:name":"Deurechnyy",
    "gn:population":0,
    "gn:timezone":"Asia/Almaty",
    "iso:country":"KZ",
    "wof:name":"Deurechnyy",
    "wof:placetype":"locality"
},
  "geometry": {"coordinates":[66.43333,51.56667],"type":"Point"}
}