{
  "type": "Feature",
  "properties": {
    "gn:admin1_code":"16.0",
    "gn:asciiname":"Koval'",
    "gn:country_code":"KZ",
    "gn:dem":135,
    "gn:feature_class":"P",
    "gn:feature_code":"PPL",
    "gn:name":"Koval\u2019",
    "gn:population":0,
    "gn:timezone":"Asia/Almaty",
    "iso:country":"KZ",
    "name:eng_x_preferred":[
        "Koval'"
    ],
    "name:kaz_x_preferred":[
        "\u041a\u043e\u0432\u0430\u043b\u044c"
    ],
    "name:rus_x_preferred":[
        "\u041a\u043e\u0432\u0430\u043b\u044c"
    ],
    "name:und_x_variant":[
        "Koval\u2019"
    ],
    "wof:name":"Koval'",
    "wof:placetype":"locality"
},
  "geometry": {"coordinates":[68.29634,55.04909],"type":"Point"}
}