{
  "type": "Feature",
  "properties": {
    "gn:admin1_code":"0.0",
    "gn:asciiname":"Qaynar",
    "gn:country_code":"KZ",
    "gn:dem":835,
    "gn:feature_class":"P",
    "gn:feature_code":"PPL",
    "gn:name":"Qaynar",
    "gn:population":0,
    "gn:timezone":"Asia/Almaty",
    "iso:country":"KZ",
    "name:eng_x_preferred":[
        "Qaynar"
    ],
    "name:rus_x_preferred":[
        "\u0421\u0435\u0440\u0433\u0435\u0435\u0432\u043a\u0430"
    ],
    "name:und_x_variant":[
        "Sergeyevka"
    ],
    "wof:name":"Qaynar",
    "wof:placetype":"locality"
},
  "geometry": {"coordinates":[83.80969,48.81122],"type":"Point"}
}