{
  "type": "Feature",
  "properties": {
    "gn:admin1_code":"0.0",
    "gn:asciiname":"Vos'moye Marta",
    "gn:country_code":"KZ",
    "gn:dem":532,
    "gn:feature_class":"P",
    "gn:feature_code":"PPL",
    "gn:name":"Vos\u2019moye Marta",
    "gn:population":0,
    "gn:timezone":"Asia/Almaty",
    "iso:country":"KZ",
    "name:und_x_variant":[
        "Balykty-Kul\u2019",
        "Zhana-Turmys",
        "Vos\u2019moye Marta"
    ],
    "wof:name":"Vos'moye Marta",
    "wof:placetype":"locality"
},
  "geometry": {"coordinates":[81.00979,49.06334],"type":"Point"}
}