{
  "type": "Feature",
  "properties": {
    "gn:admin1_code":"10.0",
    "gn:asciiname":"Otdeleniye Nomer Dva Sovkhoza Imeni Lenina",
    "gn:country_code":"KZ",
    "gn:dem":258,
    "gn:feature_class":"P",
    "gn:feature_code":"PPLF",
    "gn:name":"Otdeleniye Nomer Dva Sovkhoza Imeni Lenina",
    "gn:population":0,
    "gn:timezone":"Asia/Almaty",
    "iso:country":"KZ",
    "name:rus_x_preferred":[
        "\u041e\u0442\u0434\u0435\u043b\u0435\u043d\u0438\u0435 \u041d\u043e\u043c\u0435\u0440 \u0414\u0432\u0430 \u0421\u043e\u0432\u0445\u043e\u0437\u0430 \u0418\u043c\u0435\u043d\u0438 \u041b\u0435\u043d\u0438\u043d\u0430"
    ],
    "wof:name":"Otdeleniye Nomer Dva Sovkhoza Imeni Lenina",
    "wof:placetype":"locality"
},
  "geometry": {"coordinates":[68.14655999999999,40.79631],"type":"Point"}
}