{
  "type": "Feature",
  "properties": {
    "gn:admin1_code":"15.0",
    "gn:asciiname":"Umurzak",
    "gn:country_code":"KZ",
    "gn:dem":372,
    "gn:feature_class":"P",
    "gn:feature_code":"PPL",
    "gn:name":"Umurzak",
    "gn:population":0,
    "gn:timezone":"Asia/Almaty",
    "iso:country":"KZ",
    "name:eng_x_preferred":[
        "Umurzak"
    ],
    "name:kaz_x_preferred":[
        "\u00d6mirzaq"
    ],
    "name:kaz_x_variant":[
        "\u04e8\u043c\u0456\u0440\u0437\u0430\u049b"
    ],
    "name:rus_x_preferred":[
        "\u0423\u043c\u0443\u0440\u0437\u0430\u043a"
    ],
    "wof:name":"Umurzak",
    "wof:placetype":"locality"
},
  "geometry": {"coordinates":[80.646,50.80444],"type":"Point"}
}