{
  "type": "Feature",
  "properties": {
    "gn:admin1_code":"13.0",
    "gn:asciiname":"Tulengut",
    "gn:country_code":"KZ",
    "gn:dem":96,
    "gn:feature_class":"P",
    "gn:feature_code":"PPL",
    "gn:name":"Tulengut",
    "gn:population":0,
    "gn:timezone":"Asia/Qyzylorda",
    "iso:country":"KZ",
    "name:eng_x_preferred":[
        "Tulengut"
    ],
    "name:kaz_x_preferred":[
        "T\u00f6lenggit"
    ],
    "name:kaz_x_variant":[
        "\u0422\u04e9\u043b\u0435\u04a3\u0433\u0456\u0442"
    ],
    "name:rus_x_preferred":[
        "\u0422\u0443\u043b\u0435\u043d\u0433\u0443\u0442"
    ],
    "wof:name":"Tulengut",
    "wof:placetype":"locality"
},
  "geometry": {"coordinates":[64.50709000000001,54.32755],"type":"Point"}
}