{
  "type": "Feature",
  "properties": {
    "gn:admin1_code":"0.0",
    "gn:asciiname":"Karabuzhar",
    "gn:cc2":"KZ",
    "gn:country_code":"KZ",
    "gn:dem":834,
    "gn:feature_class":"P",
    "gn:feature_code":"PPL",
    "gn:name":"Karabuzhar",
    "gn:population":0,
    "gn:timezone":"Asia/Almaty",
    "iso:country":"KZ",
    "name:und_x_variant":[
        "Karabuzhir",
        "Karabuzhar"
    ],
    "wof:name":"Karabuzhar",
    "wof:placetype":"locality"
},
  "geometry": {"coordinates":[79.25,48.25],"type":"Point"}
}