{
  "type": "Feature",
  "properties": {
    "gn:admin1_code":"7.0",
    "gn:asciiname":"Kosterek",
    "gn:country_code":"KZ",
    "gn:dem":8,
    "gn:feature_class":"P",
    "gn:feature_code":"PPL",
    "gn:name":"Kosterek",
    "gn:population":0,
    "gn:timezone":"Asia/Oral",
    "iso:country":"KZ",
    "name:eng_x_preferred":[
        "Kosterek"
    ],
    "name:rus_x_preferred":[
        "\u041a\u043e\u0441\u0442\u0435\u0440\u0435\u043a"
    ],
    "wof:name":"Kosterek",
    "wof:placetype":"locality"
},
  "geometry": {"coordinates":[49.29253,49.94931],"type":"Point"}
}