{
  "type": "Feature",
  "properties": {
    "gn:admin1_code":"17.0",
    "gn:asciiname":"Kayyr",
    "gn:country_code":"KZ",
    "gn:dem":341,
    "gn:feature_class":"P",
    "gn:feature_code":"PPL",
    "gn:name":"Kayyr",
    "gn:population":0,
    "gn:timezone":"Asia/Almaty",
    "iso:country":"KZ",
    "name:kaz_x_preferred":[
        "Kayyr"
    ],
    "name:kaz_x_variant":[
        "\u041a\u0430\u0439\u044b\u0440"
    ],
    "name:rus_x_preferred":[
        "\u0424\u0435\u0440\u043c\u0430 \u041d\u043e\u043c\u0435\u0440 \u041e\u0434\u0438\u043d \u0421\u043e\u0432\u0445\u043e\u0437\u0430 \u0422\u0430\u043f\u0430\u0441\u0441\u043a\u0438\u0439"
    ],
    "name:und_x_variant":[
        "Ferma Nomer Odin Sovkhoza Tapasskiy"
    ],
    "wof:name":"Kayyr",
    "wof:placetype":"locality"
},
  "geometry": {"coordinates":[70.55691,43.92643],"type":"Point"}
}