{
  "type": "Feature",
  "properties": {
    "gn:admin1_code":"4.0",
    "gn:asciiname":"Kyzyltan",
    "gn:country_code":"KZ",
    "gn:dem":272,
    "gn:feature_class":"P",
    "gn:feature_code":"PPL",
    "gn:name":"Kyzyltan",
    "gn:population":0,
    "gn:timezone":"Asia/Aqtobe",
    "iso:country":"KZ",
    "name:eng_x_preferred":[
        "Kyzyltan"
    ],
    "name:rus_x_preferred":[
        "\u041a\u044b\u0437\u044b\u043b\u0442\u0430\u043d"
    ],
    "name:und_x_variant":[
        "Kzyltan"
    ],
    "wof:name":"Kyzyltan",
    "wof:placetype":"locality"
},
  "geometry": {"coordinates":[59.83333,50.16667],"type":"Point"}
}