{
  "type": "Feature",
  "properties": {
    "gn:admin1_code":"15.0",
    "gn:asciiname":"Svinchatka",
    "gn:country_code":"KZ",
    "gn:dem":395,
    "gn:feature_class":"P",
    "gn:feature_code":"PPL",
    "gn:name":"Svinchatka",
    "gn:population":0,
    "gn:timezone":"Asia/Almaty",
    "iso:country":"KZ",
    "name:eng_x_preferred":[
        "Sv\u012bnchatka"
    ],
    "name:kaz_x_preferred":[
        "\u0421\u0432\u0438\u043d\u0447\u0430\u0442\u043a\u0430"
    ],
    "name:rus_x_preferred":[
        "\u0421\u0432\u0438\u043d\u0447\u0430\u0442\u043a\u0430"
    ],
    "name:und_x_variant":[
        "Sv\u012bnchatka",
        "Svinchatka"
    ],
    "wof:name":"Svinchatka",
    "wof:placetype":"locality"
},
  "geometry": {"coordinates":[84.22957,49.09729],"type":"Point"}
}