{
  "type": "Feature",
  "properties": {
    "gn:admin1_code":"11.0",
    "gn:asciiname":"Shipkol",
    "gn:country_code":"KZ",
    "gn:dem":103,
    "gn:feature_class":"P",
    "gn:feature_code":"PPL",
    "gn:name":"Shipk\u00f6l",
    "gn:population":0,
    "gn:timezone":"Asia/Almaty",
    "iso:country":"KZ",
    "name:eng_x_preferred":[
        "Shipkul'"
    ],
    "name:kaz_x_preferred":[
        "Shipk\u00f6l"
    ],
    "name:kaz_x_variant":[
        "\u0428\u0456\u043f\u043a\u04e9\u043b"
    ],
    "name:rus_x_preferred":[
        "\u0428\u0438\u043f\u043a\u0443\u043b\u044c"
    ],
    "name:rus_x_variant":[
        "Shipkol\u2019",
        "\u0428\u0438\u043f\u043a\u043e\u043b\u044c"
    ],
    "name:und_x_variant":[
        "Shipkul\u2019"
    ],
    "wof:name":"Shipkol",
    "wof:placetype":"locality"
},
  "geometry": {"coordinates":[75.84241,54.04816],"type":"Point"}
}