{
  "type": "Feature",
  "properties": {
    "gn:admin1_code":"17.0",
    "gn:asciiname":"Kamysstroy",
    "gn:country_code":"KZ",
    "gn:dem":480,
    "gn:feature_class":"P",
    "gn:feature_code":"PPL",
    "gn:name":"Kamysstroy",
    "gn:population":0,
    "gn:timezone":"Asia/Almaty",
    "iso:country":"KZ",
    "name:rus_x_preferred":[
        "\u041a\u0430\u043c\u044b\u0441\u0441\u0442\u0440\u043e\u0439"
    ],
    "wof:name":"Kamysstroy",
    "wof:placetype":"locality"
},
  "geometry": {"coordinates":[73.75891,43.54578],"type":"Point"}
}