{
  "type": "Feature",
  "properties": {
    "gn:admin1_code":"17.0",
    "gn:asciiname":"Podgornoye",
    "gn:country_code":"KZ",
    "gn:dem":806,
    "gn:feature_class":"P",
    "gn:feature_code":"PPL",
    "gn:name":"Podgornoye",
    "gn:population":0,
    "gn:timezone":"Asia/Almaty",
    "iso:country":"KZ",
    "name:che_x_preferred":[
        "\u041f\u043e\u0434\u0433\u043e\u0440\u043d\u0438"
    ],
    "name:kaz_x_preferred":[
        "Qumaryq"
    ],
    "name:kaz_x_variant":[
        "\u049a\u04b1\u043c\u0430\u0440\u044b\u049b"
    ],
    "name:rus_x_preferred":[
        "\u041f\u043e\u0434\u0433\u043e\u0440\u043d\u043e\u0435"
    ],
    "name:tat_x_preferred":[
        "\u041f\u043e\u0434\u0433\u043e\u0440\u043d\u043e\u0435"
    ],
    "name:ukr_x_preferred":[
        "\u041f\u0456\u0434\u0433\u0456\u0440\u043d\u0435"
    ],
    "wof:name":"Podgornoye",
    "wof:placetype":"locality"
},
  "geometry": {"coordinates":[72.42716999999998,42.93081],"type":"Point"}
}