{
  "type": "Feature",
  "properties": {
    "gn:admin1_code":"10.0",
    "gn:asciiname":"Tlektes",
    "gn:country_code":"KZ",
    "gn:dem":808,
    "gn:feature_class":"P",
    "gn:feature_code":"PPL",
    "gn:name":"Tlektes",
    "gn:population":0,
    "gn:timezone":"Asia/Almaty",
    "iso:country":"KZ",
    "name:rus_x_preferred":[
        "\u0422\u043b\u0435\u043a\u0442\u0435\u0441"
    ],
    "name:und_x_variant":[
        "Tilektes",
        "Tlektes"
    ],
    "wof:name":"Tlektes",
    "wof:placetype":"locality"
},
  "geometry": {"coordinates":[69.64485000000001,41.9657],"type":"Point"}
}