{
  "type": "Feature",
  "properties": {
    "gn:admin1_code":"15.0",
    "gn:asciiname":"Zhylandy",
    "gn:country_code":"KZ",
    "gn:dem":487,
    "gn:feature_class":"P",
    "gn:feature_code":"PPL",
    "gn:name":"Zhylandy",
    "gn:population":0,
    "gn:timezone":"Asia/Almaty",
    "iso:country":"KZ",
    "wof:name":"Zhylandy",
    "wof:placetype":"locality"
},
  "geometry": {"coordinates":[82.23423000000003,49.6643],"type":"Point"}
}