{
  "type": "Feature",
  "properties": {
    "gn:admin1_code":"13.0",
    "gn:asciiname":"Karaoba",
    "gn:country_code":"KZ",
    "gn:dem":258,
    "gn:feature_class":"P",
    "gn:feature_code":"PPL",
    "gn:name":"Karaoba",
    "gn:population":0,
    "gn:timezone":"Asia/Qyzylorda",
    "iso:country":"KZ",
    "name:eng_x_preferred":[
        "Karaoba"
    ],
    "name:kaz_x_preferred":[
        "Qaraoba"
    ],
    "name:kaz_x_variant":[
        "\u049a\u0430\u0440\u0430\u043e\u0431\u0430"
    ],
    "name:rus_x_preferred":[
        "\u041a\u0430\u0440\u0430\u043e\u0431\u0430"
    ],
    "wof:name":"Karaoba",
    "wof:placetype":"locality"
},
  "geometry": {"coordinates":[61.37226999999999,52.93997],"type":"Point"}
}