{
  "type": "Feature",
  "properties": {
    "gn:admin1_code":"0.0",
    "gn:asciiname":"Nizhayev",
    "gn:country_code":"KZ",
    "gn:dem":71,
    "gn:feature_class":"P",
    "gn:feature_code":"PPL",
    "gn:name":"Nizhayev",
    "gn:population":0,
    "gn:timezone":"Asia/Oral",
    "iso:country":"KZ",
    "wof:name":"Nizhayev",
    "wof:placetype":"locality"
},
  "geometry": {"coordinates":[50.73333,51.53333],"type":"Point"}
}