{
  "type": "Feature",
  "properties": {
    "gn:admin1_code":"0.0",
    "gn:asciiname":"Bazarka",
    "gn:country_code":"KZ",
    "gn:dem":396,
    "gn:feature_class":"P",
    "gn:feature_code":"PPL",
    "gn:name":"Bazarka",
    "gn:population":0,
    "gn:timezone":"Asia/Almaty",
    "iso:country":"KZ",
    "name:eng_x_preferred":[
        "Bazarka"
    ],
    "name:rus_x_preferred":[
        "\u0411\u0430\u0437\u0430\u0440\u043a\u0430"
    ],
    "name:und_x_variant":[
        "Bazarskiy"
    ],
    "wof:name":"Bazarka",
    "wof:placetype":"locality"
},
  "geometry": {"coordinates":[83.11171,48.11056],"type":"Point"}
}