{
  "type": "Feature",
  "properties": {
    "gn:country":"KZ",
    "gn:fcode":"PPL",
    "gn:pop":2678,
    "iso:country":"KZ",
    "name:ara_x_preferred":[
        "\u0623\u0644\u062a\u0627\u064a"
    ],
    "name:aze_x_preferred":[
        "Altay"
    ],
    "name:bre_x_preferred":[
        "Altay"
    ],
    "name:ceb_x_preferred":[
        "Altay"
    ],
    "name:deu_x_preferred":[
        "Altay"
    ],
    "name:eng_x_preferred":[
        "Altay"
    ],
    "name:hun_x_preferred":[
        "Altaj j\u00e1r\u00e1s"
    ],
    "name:kaz_x_preferred":[
        "\u0410\u043b\u0442\u0430\u0439"
    ],
    "name:mlg_x_preferred":[
        "Altay"
    ],
    "name:mon_x_preferred":[
        "\u0410\u043b\u0442\u0430\u0439 \u0441\u0443\u043c"
    ],
    "name:pol_x_preferred":[
        "Altay"
    ],
    "name:rus_x_preferred":[
        "\u0410\u043b\u0442\u0430\u0439\u0441\u043a\u0438\u0439"
    ],
    "name:swe_x_preferred":[
        "Altay"
    ],
    "name:tur_x_preferred":[
        "Altay"
    ],
    "name:unk_x_variant":[
        "Altayskiy"
    ],
    "qs:name":"Altay",
    "qs:photos_9r":0,
    "qs:photos_sr":0,
    "qs:pop_sr":"4",
    "wd:wordcount":182,
    "wof:name":"Altay",
    "wof:placetype":"locality",
    "wof:population":2678
},
  "geometry": {"coordinates":[82.36098,50.24489],"type":"Point"}
}