{
  "type": "Feature",
  "properties": {
    "gn:admin1_code":"1.0",
    "gn:asciiname":"Gvardeyskiy",
    "gn:country_code":"KZ",
    "gn:dem":838,
    "gn:feature_class":"P",
    "gn:feature_code":"PPL",
    "gn:name":"Gvardeyskiy",
    "gn:population":0,
    "gn:timezone":"Asia/Almaty",
    "iso:country":"KZ",
    "name:kaz_x_preferred":[
        "Gvardeysk\u012by"
    ],
    "name:kaz_x_variant":[
        "\u0413\u0432\u0430\u0440\u0434\u0435\u0439\u0441\u043a\u0438\u0439"
    ],
    "wof:name":"Gvardeyskiy",
    "wof:placetype":"locality"
},
  "geometry": {"coordinates":[75.21392,43.57984],"type":"Point"}
}