{
  "type": "Feature",
  "properties": {
    "gn:admin1_code":"16.0",
    "gn:asciiname":"Rovnoye",
    "gn:country_code":"KZ",
    "gn:dem":177,
    "gn:feature_class":"P",
    "gn:feature_code":"PPL",
    "gn:name":"Rovnoye",
    "gn:population":0,
    "gn:timezone":"Asia/Almaty",
    "iso:country":"KZ",
    "name:rus_x_preferred":[
        "\u0420\u043e\u0432\u043d\u043e\u0435"
    ],
    "name:rus_x_variant":[
        "\u041b\u0435\u0441\u0445\u043e\u0437 \u041e\u043a\u0442\u044f\u0431\u0440\u044c\u0441\u043a\u0438\u0439"
    ],
    "name:und_x_variant":[
        "Leskhoz Oktyabr\u2019skiy"
    ],
    "wof:name":"Rovnoye",
    "wof:placetype":"locality"
},
  "geometry": {"coordinates":[67.60658000000001,53.77004],"type":"Point"}
}