{
  "type": "Feature",
  "properties": {
    "gn:admin1_code":"13.0",
    "gn:asciiname":"Beregovoye",
    "gn:country_code":"KZ",
    "gn:dem":170,
    "gn:feature_class":"P",
    "gn:feature_code":"PPL",
    "gn:name":"Beregovoye",
    "gn:population":0,
    "gn:timezone":"Asia/Qyzylorda",
    "iso:country":"KZ",
    "name:eng_x_preferred":[
        "Beregovoye"
    ],
    "name:rus_x_preferred":[
        "\u0411\u0435\u0440\u0435\u0433\u043e\u0432\u043e\u0435"
    ],
    "name:und_x_variant":[
        "Viktorovskiy"
    ],
    "wof:name":"Beregovoye",
    "wof:placetype":"locality"
},
  "geometry": {"coordinates":[63.0564,52.88115],"type":"Point"}
}