{
  "type": "Feature",
  "properties": {
    "gn:admin1_code":"0.0",
    "gn:asciiname":"Kyzyltu",
    "gn:country_code":"KZ",
    "gn:dem":218,
    "gn:feature_class":"P",
    "gn:feature_code":"PPL",
    "gn:name":"Kyzyltu",
    "gn:population":0,
    "gn:timezone":"Asia/Qyzylorda",
    "iso:country":"KZ",
    "name:eng_x_preferred":[
        "Kyzyltu"
    ],
    "name:rus_x_preferred":[
        "\u041a\u044b\u0437\u044b\u043b\u0442\u0443"
    ],
    "wof:name":"Kyzyltu",
    "wof:placetype":"locality"
},
  "geometry": {"coordinates":[62.03333000000001,53.41667],"type":"Point"}
}