{
  "type": "Feature",
  "properties": {
    "gn:admin1_code":"0.0",
    "gn:asciiname":"Kuagash",
    "gn:cc2":"KZ",
    "gn:country_code":"KZ",
    "gn:dem":114,
    "gn:feature_class":"P",
    "gn:feature_code":"PPL",
    "gn:name":"Kuagash",
    "gn:population":0,
    "gn:timezone":"Asia/Oral",
    "iso:country":"KZ",
    "name:und_x_variant":[
        "Kuagach",
        "Kuagash"
    ],
    "wof:name":"Kuagash",
    "wof:placetype":"locality"
},
  "geometry": {"coordinates":[53.93333000000001,50.56667],"type":"Point"}
}