{
  "type": "Feature",
  "properties": {
    "gn:admin1_code":"0.0",
    "gn:asciiname":"Murzachul",
    "gn:cc2":"KZ",
    "gn:country_code":"KZ",
    "gn:dem":713,
    "gn:feature_class":"P",
    "gn:feature_code":"PPL",
    "gn:name":"Murzachul",
    "gn:population":0,
    "gn:timezone":"Asia/Almaty",
    "iso:country":"KZ",
    "name:und_x_variant":[
        "Murgagul",
        "Murzagul",
        "Murzachul"
    ],
    "wof:name":"Murzachul",
    "wof:placetype":"locality"
},
  "geometry": {"coordinates":[80.93333,48.73333],"type":"Point"}
}