{
  "type": "Feature",
  "properties": {
    "gn:admin1_code":"3.0",
    "gn:asciiname":"Yelenovka",
    "gn:country_code":"KZ",
    "gn:dem":265,
    "gn:feature_class":"P",
    "gn:feature_code":"PPL",
    "gn:name":"Yelenovka",
    "gn:population":0,
    "gn:timezone":"Asia/Almaty",
    "iso:country":"KZ",
    "name:aze_x_preferred":[
        "Yelenovka"
    ],
    "name:rus_x_preferred":[
        "\u0415\u043b\u0435\u043d\u043e\u0432\u043a\u0430"
    ],
    "wof:name":"Yelenovka",
    "wof:placetype":"locality"
},
  "geometry": {"coordinates":[72.2856,51.87691],"type":"Point"}
}