{
  "type": "Feature",
  "properties": {
    "gn:admin1_code":"13.0",
    "gn:asciiname":"Akkoshkar",
    "gn:country_code":"KZ",
    "gn:dem":268,
    "gn:feature_class":"P",
    "gn:feature_code":"PPL",
    "gn:name":"Akkoshkar",
    "gn:population":0,
    "gn:timezone":"Asia/Almaty",
    "iso:country":"KZ",
    "wof:name":"Akkoshkar",
    "wof:placetype":"locality"
},
  "geometry": {"coordinates":[66.57250000000001,49.935],"type":"Point"}
}