{
  "type": "Feature",
  "properties": {
    "gn:admin1_code":"17.0",
    "gn:asciiname":"Kyzylkishlak",
    "gn:country_code":"KZ",
    "gn:dem":689,
    "gn:feature_class":"P",
    "gn:feature_code":"PPL",
    "gn:name":"Kyzylkishlak",
    "gn:population":0,
    "gn:timezone":"Asia/Almaty",
    "iso:country":"KZ",
    "name:kaz_x_preferred":[
        "Qyzylqyshlaq"
    ],
    "name:kaz_x_variant":[
        "\u049a\u044b\u0437\u044b\u043b\u049b\u044b\u0448\u043b\u0430\u049b"
    ],
    "name:rus_x_preferred":[
        "\u041a\u044b\u0437\u044b\u043b\u043a\u0438\u0448\u043b\u0430\u043a"
    ],
    "wof:name":"Kyzylkishlak",
    "wof:placetype":"locality"
},
  "geometry": {"coordinates":[73.47081999999997,42.86103],"type":"Point"}
}