{
  "type": "Feature",
  "properties": {
    "gn:admin1_code":"14.0",
    "gn:asciiname":"Aleksandrovskiy",
    "gn:country_code":"KZ",
    "gn:dem":126,
    "gn:feature_class":"P",
    "gn:feature_code":"PPL",
    "gn:name":"Aleksandrovskiy",
    "gn:population":0,
    "gn:timezone":"Asia/Qyzylorda",
    "iso:country":"KZ",
    "name:und_x_variant":[
        "Tal Suat",
        "Aleksandrovski",
        "Aleksandrovskiy"
    ],
    "wof:name":"Aleksandrovskiy",
    "wof:placetype":"locality"
},
  "geometry": {"coordinates":[65.37389,44.92056],"type":"Point"}
}