{
  "type": "Feature",
  "properties": {
    "gn:admin1_code":"14.0",
    "gn:asciiname":"Kokkatyn",
    "gn:country_code":"KZ",
    "gn:dem":68,
    "gn:feature_class":"P",
    "gn:feature_code":"PPL",
    "gn:name":"Kokkatyn",
    "gn:population":0,
    "gn:timezone":"Asia/Qyzylorda",
    "iso:country":"KZ",
    "name:und_x_variant":[
        "Kokkatyk",
        "Kokkatyn"
    ],
    "wof:name":"Kokkatyn",
    "wof:placetype":"locality"
},
  "geometry": {"coordinates":[62.21666999999999,45.63333],"type":"Point"}
}