{
  "type": "Feature",
  "properties": {
    "gn:admin1_code":"0.0",
    "gn:asciiname":"Chistopol'skoye",
    "gn:country_code":"KZ",
    "gn:dem":375,
    "gn:feature_class":"P",
    "gn:feature_code":"PPL",
    "gn:name":"Chistopol\u2019skoye",
    "gn:population":0,
    "gn:timezone":"Asia/Almaty",
    "iso:country":"KZ",
    "wof:name":"Chistopol'skoye",
    "wof:placetype":"locality"
},
  "geometry": {"coordinates":[81.18675,46.15948],"type":"Point"}
}