{
  "type": "Feature",
  "properties": {
    "gn:admin1_code":"4.0",
    "gn:asciiname":"Kokbulak",
    "gn:country_code":"KZ",
    "gn:dem":155,
    "gn:feature_class":"P",
    "gn:feature_code":"PPL",
    "gn:name":"Kokbulak",
    "gn:population":0,
    "gn:timezone":"Asia/Aqtobe",
    "iso:country":"KZ",
    "wof:name":"Kokbulak",
    "wof:placetype":"locality"
},
  "geometry": {"coordinates":[59.93333000000001,46.95],"type":"Point"}
}