{
  "type": "Feature",
  "properties": {
    "gn:admin1_code":"12.0",
    "gn:asciiname":"Qarasu",
    "gn:country_code":"KZ",
    "gn:dem":492,
    "gn:feature_class":"P",
    "gn:feature_code":"PPL",
    "gn:name":"Qaras\u016b",
    "gn:population":0,
    "gn:timezone":"Asia/Almaty",
    "iso:country":"KZ",
    "name:kaz_x_preferred":[
        "Qaras\u016b"
    ],
    "name:und_x_variant":[
        "Ybysh",
        "Karashenzel\u2019",
        "Karashengel\u2019"
    ],
    "wof:name":"Qarasu",
    "wof:placetype":"locality"
},
  "geometry": {"coordinates":[75.58333,47.43333],"type":"Point"}
}