{
  "type": "Feature",
  "properties": {
    "gn:admin1_code":"11.0",
    "gn:asciiname":"Mulyavskoye",
    "gn:country_code":"KZ",
    "gn:dem":100,
    "gn:feature_class":"P",
    "gn:feature_code":"PPL",
    "gn:name":"Mulyavskoye",
    "gn:population":0,
    "gn:timezone":"Asia/Almaty",
    "iso:country":"KZ",
    "name:kaz_x_preferred":[
        "M\u00fctkenov"
    ],
    "name:kaz_x_variant":[
        "\u041c\u04af\u0442\u043a\u0435\u043d\u043e\u0432"
    ],
    "name:rus_x_preferred":[
        "\u041c\u0443\u043b\u044f\u0432\u0441\u043a\u043e\u0435"
    ],
    "name:und_x_variant":[
        "Imeni Chkalova",
        "Mulyavskiy",
        "Mulyavka",
        "Mulavka",
        "Mulyavskoye"
    ],
    "wof:name":"Mulyavskoye",
    "wof:placetype":"locality"
},
  "geometry": {"coordinates":[76.23614000000001,52.90098],"type":"Point"}
}