{
  "type": "Feature",
  "properties": {
    "gn:admin1_code":"7.0",
    "gn:asciiname":"Ashchisay",
    "gn:country_code":"KZ",
    "gn:dem":70,
    "gn:feature_class":"P",
    "gn:feature_code":"PPL",
    "gn:name":"Ashchisay",
    "gn:population":0,
    "gn:timezone":"Asia/Oral",
    "iso:country":"KZ",
    "name:eng_x_preferred":[
        "Ashchisay"
    ],
    "name:kaz_x_preferred":[
        "\u0410\u0449\u044b\u0441\u0430\u0439"
    ],
    "name:rus_x_preferred":[
        "\u0410\u0449\u0438\u0441\u0430\u0439"
    ],
    "name:ukr_x_preferred":[
        "\u0410\u0449\u0438\u0441\u0430\u0439"
    ],
    "name:und_x_variant":[
        "Ashchisayskiy",
        "Ashchisay"
    ],
    "wof:name":"Ashchisay",
    "wof:placetype":"locality"
},
  "geometry": {"coordinates":[53.76614,51.16127],"type":"Point"}
}