{
  "type": "Feature",
  "properties": {
    "gn:admin1_code":"16.0",
    "gn:asciiname":"Idris",
    "gn:country_code":"KZ",
    "gn:dem":120,
    "gn:feature_class":"P",
    "gn:feature_code":"PPL",
    "gn:name":"Idris",
    "gn:population":0,
    "gn:timezone":"Asia/Almaty",
    "iso:country":"KZ",
    "wof:name":"Idris",
    "wof:placetype":"locality"
},
  "geometry": {"coordinates":[73.65000000000001,53.98333],"type":"Point"}
}