{
  "type": "Feature",
  "properties": {
    "gn:admin1_code":"17.0",
    "gn:asciiname":"Kyzylzhar",
    "gn:country_code":"KZ",
    "gn:dem":350,
    "gn:feature_class":"P",
    "gn:feature_code":"PPL",
    "gn:name":"Kyzylzhar",
    "gn:population":0,
    "gn:timezone":"Asia/Almaty",
    "iso:country":"KZ",
    "name:kaz_x_preferred":[
        "Qyzylzhar"
    ],
    "name:kaz_x_variant":[
        "\u049a\u044b\u0437\u044b\u043b\u0436\u0430\u0440"
    ],
    "name:rus_x_preferred":[
        "\u041a\u044b\u0437\u044b\u043b\u0436\u0430\u0440"
    ],
    "wof:name":"Kyzylzhar",
    "wof:placetype":"locality"
},
  "geometry": {"coordinates":[70.69698000000002,43.94931],"type":"Point"}
}