{
  "type": "Feature",
  "properties": {
    "gn:admin1_code":"4.0",
    "gn:asciiname":"Pavlov",
    "gn:country_code":"KZ",
    "gn:dem":73,
    "gn:feature_class":"P",
    "gn:feature_code":"PPL",
    "gn:name":"Pavlov",
    "gn:population":0,
    "gn:timezone":"Asia/Aqtobe",
    "iso:country":"KZ",
    "wof:name":"Pavlov",
    "wof:placetype":"locality"
},
  "geometry": {"coordinates":[54.56667,49.23333],"type":"Point"}
}