{
  "type": "Feature",
  "properties": {
    "gn:admin1_code":"13.0",
    "gn:asciiname":"Zhanakala",
    "gn:country_code":"KZ",
    "gn:dem":181,
    "gn:feature_class":"P",
    "gn:feature_code":"PPL",
    "gn:name":"Zhanakala",
    "gn:population":0,
    "gn:timezone":"Asia/Almaty",
    "iso:country":"KZ",
    "wof:name":"Zhanakala",
    "wof:placetype":"locality"
},
  "geometry": {"coordinates":[66.13396,49.79087],"type":"Point"}
}