{
  "type": "Feature",
  "properties": {
    "gn:admin1_code":"13.0",
    "gn:asciiname":"Zhanakala",
    "gn:country_code":"KZ",
    "gn:dem":181,
    "gn:feature_class":"P",
    "gn:feature_code":"PPL",
    "gn:name":"Zhanakala",
    "gn:population":0,
    "gn:timezone":"Asia/Almaty",
    "iso:country":"KZ",
    "name:ell_x_preferred":[
        "\u0396\u03b1\u03bd\u03b1\u03ba\u03b1\u03bb\u03ac"
    ],
    "name:kaz_x_preferred":[
        "\u0416\u0430\u04a3\u0430\u049b\u0430\u043b\u0430"
    ],
    "name:rus_x_preferred":[
        "\u0416\u0430\u043d\u0433\u0430\u043b\u0430"
    ],
    "name:ukr_x_preferred":[
        "\u0416\u0430\u043d\u0433\u0430\u043b\u0430"
    ],
    "wof:name":"Zhanakala",
    "wof:placetype":"locality"
},
  "geometry": {"coordinates":[66.13396,49.79087],"type":"Point"}
}