{
  "type": "Feature",
  "properties": {
    "gn:admin1_code":"0.0",
    "gn:asciiname":"Burgansu",
    "gn:country_code":"KZ",
    "gn:dem":1563,
    "gn:feature_class":"P",
    "gn:feature_code":"PPL",
    "gn:name":"Burgansu",
    "gn:population":0,
    "gn:timezone":"Asia/Almaty",
    "iso:country":"KZ",
    "wof:name":"Burgansu",
    "wof:placetype":"locality"
},
  "geometry": {"coordinates":[77.81971999999998,43.3975],"type":"Point"}
}