{
  "type": "Feature",
  "properties": {
    "gn:admin1_code":"10.0",
    "gn:asciiname":"Psteli",
    "gn:country_code":"KZ",
    "gn:dem":702,
    "gn:feature_class":"P",
    "gn:feature_code":"PPL",
    "gn:name":"Psteli",
    "gn:population":0,
    "gn:timezone":"Asia/Almaty",
    "iso:country":"KZ",
    "name:rus_x_preferred":[
        "\u041f\u0441\u0442\u0435\u043b\u0438"
    ],
    "wof:name":"Psteli",
    "wof:placetype":"locality"
},
  "geometry": {"coordinates":[70.19879,42.64902],"type":"Point"}
}