{
  "type": "Feature",
  "properties": {
    "gn:admin1_code":"3.0",
    "gn:asciiname":"Oshak",
    "gn:country_code":"KZ",
    "gn:dem":306,
    "gn:feature_class":"P",
    "gn:feature_code":"PPL",
    "gn:name":"Oshak",
    "gn:population":0,
    "gn:timezone":"Asia/Almaty",
    "iso:country":"KZ",
    "name:und_x_variant":[
        "Ozhak",
        "Oshak"
    ],
    "wof:name":"Oshak",
    "wof:placetype":"locality"
},
  "geometry": {"coordinates":[71.66221999999998,51.75795],"type":"Point"}
}