{
  "type": "Feature",
  "properties": {
    "gn:admin1_code":"10.0",
    "gn:asciiname":"Kumkent",
    "gn:country_code":"KZ",
    "gn:dem":325,
    "gn:feature_class":"P",
    "gn:feature_code":"PPL",
    "gn:name":"Kumkent",
    "gn:population":0,
    "gn:timezone":"Asia/Almaty",
    "iso:country":"KZ",
    "name:kaz_x_preferred":[
        "\u049a\u04b1\u043c\u043a\u0435\u043d\u0442"
    ],
    "name:rus_x_preferred":[
        "\u041a\u0443\u043c\u043a\u0435\u043d\u0442"
    ],
    "name:und_x_variant":[
        "Kumgent",
        "Qumkent"
    ],
    "wof:name":"Kumkent",
    "wof:placetype":"locality"
},
  "geometry": {"coordinates":[69.61596,43.77159],"type":"Point"}
}