{
  "type": "Feature",
  "properties": {
    "gn:admin1_code":"0.0",
    "gn:asciiname":"Krasnyy Altay",
    "gn:cc2":"KZ",
    "gn:country_code":"KZ",
    "gn:dem":388,
    "gn:feature_class":"P",
    "gn:feature_code":"PPL",
    "gn:name":"Krasnyy Altay",
    "gn:population":0,
    "gn:timezone":"Asia/Almaty",
    "iso:country":"KZ",
    "name:und_x_variant":[
        "Altay",
        "Krasnyy Altay"
    ],
    "wof:name":"Krasnyy Altay",
    "wof:placetype":"locality"
},
  "geometry": {"coordinates":[83.75,49.58333],"type":"Point"}
}