{
  "type": "Feature",
  "properties": {
    "gn:admin1_code":"15.0",
    "gn:asciiname":"Kamyshinka",
    "gn:country_code":"KZ",
    "gn:dem":336,
    "gn:feature_class":"P",
    "gn:feature_code":"PPL",
    "gn:name":"Kamyshinka",
    "gn:population":0,
    "gn:timezone":"Asia/Almaty",
    "iso:country":"KZ",
    "name:eng_x_preferred":[
        "Kamyshenka"
    ],
    "name:kaz_x_preferred":[
        "\u041a\u0430\u043c\u044b\u0448\u0435\u043d\u043a\u0430"
    ],
    "name:rus_x_preferred":[
        "\u041a\u0430\u043c\u044b\u0448\u0435\u043d\u043a\u0430"
    ],
    "name:rus_x_variant":[
        "\u041a\u0430\u043c\u044b\u0448\u0438\u043d\u043a\u0430"
    ],
    "name:und_x_variant":[
        "Kamyshinskiy",
        "Kamyshenskiy"
    ],
    "wof:name":"Kamyshinka",
    "wof:placetype":"locality"
},
  "geometry": {"coordinates":[80.745,50.70223],"type":"Point"}
}