{
  "type": "Feature",
  "properties": {
    "gn:admin1_code":"0.0",
    "gn:asciiname":"Makarovo",
    "gn:cc2":"KZ",
    "gn:country_code":"KZ",
    "gn:dem":30,
    "gn:feature_class":"P",
    "gn:feature_code":"PPL",
    "gn:name":"Makarovo",
    "gn:population":0,
    "gn:timezone":"Asia/Oral",
    "iso:country":"KZ",
    "name:eng_x_preferred":[
        "Makarovo"
    ],
    "name:rus_x_preferred":[
        "\u041c\u0430\u043a\u0430\u0440\u043e\u0432\u043e"
    ],
    "name:und_x_variant":[
        "Makarov",
        "Makarovo"
    ],
    "wof:name":"Makarovo",
    "wof:placetype":"locality"
},
  "geometry": {"coordinates":[51.48333,51.33333],"type":"Point"}
}