{
  "type": "Feature",
  "properties": {
    "gn:admin1_code":"7.0",
    "gn:asciiname":"Kalmakshabyn",
    "gn:cc2":"KZ",
    "gn:country_code":"KZ",
    "gn:dem":28,
    "gn:feature_class":"P",
    "gn:feature_code":"PPL",
    "gn:name":"Kalmakshabyn",
    "gn:population":0,
    "gn:timezone":"Asia/Oral",
    "iso:country":"KZ",
    "name:eng_x_preferred":[
        "Kalmakshabyn"
    ],
    "name:rus_x_preferred":[
        "\u041a\u0430\u043b\u043c\u0430\u043a\u0448\u0430\u0431\u044b\u043d"
    ],
    "name:und_x_variant":[
        "Kalmyk-Chaban",
        "Kalmykshaban",
        "Kalmakshabyn"
    ],
    "wof:name":"Kalmakshabyn",
    "wof:placetype":"locality"
},
  "geometry": {"coordinates":[49.925,50.77222],"type":"Point"}
}