{
  "type": "Feature",
  "properties": {
    "gn:admin1_code":"15.0",
    "gn:asciiname":"Berezovka",
    "gn:country_code":"KZ",
    "gn:dem":707,
    "gn:feature_class":"P",
    "gn:feature_code":"PPL",
    "gn:name":"Ber\u00ebzovka",
    "gn:population":0,
    "gn:timezone":"Asia/Almaty",
    "iso:country":"KZ",
    "name:ceb_x_preferred":[
        "Berezovka"
    ],
    "name:lav_x_preferred":[
        "Berezovka"
    ],
    "name:lit_x_preferred":[
        "Berezovka"
    ],
    "name:rus_x_preferred":[
        "Ber\u00ebzovka"
    ],
    "name:rus_x_variant":[
        "\u0411\u0435\u0440\u0451\u0437\u043e\u0432\u043a\u0430"
    ],
    "name:swe_x_preferred":[
        "Berezovka"
    ],
    "wof:name":"Berezovka",
    "wof:placetype":"locality"
},
  "geometry": {"coordinates":[84.83525,49.9169],"type":"Point"}
}