{
  "type": "Feature",
  "properties": {
    "gn:admin1_code":"4.0",
    "gn:asciiname":"Karasor Pervyy",
    "gn:country_code":"KZ",
    "gn:dem":207,
    "gn:feature_class":"P",
    "gn:feature_code":"PPL",
    "gn:name":"Karasor Pervyy",
    "gn:population":0,
    "gn:timezone":"Asia/Aqtobe",
    "iso:country":"KZ",
    "wof:name":"Karasor Pervyy",
    "wof:placetype":"locality"
},
  "geometry": {"coordinates":[61.66667,49.81667],"type":"Point"}
}