{
  "type": "Feature",
  "properties": {
    "gn:admin1_code":"10.0",
    "gn:asciiname":"Ordzhonikidze",
    "gn:country_code":"KZ",
    "gn:dem":531,
    "gn:feature_class":"P",
    "gn:feature_code":"PPL",
    "gn:name":"Ordzhonikidze",
    "gn:population":0,
    "gn:timezone":"Asia/Almaty",
    "iso:country":"KZ",
    "name:bul_x_preferred":[
        "\u041e\u0440\u0434\u0436\u043e\u043d\u0438\u043a\u0438\u0434\u0437\u0435"
    ],
    "name:ceb_x_preferred":[
        "Ordzhonikidze"
    ],
    "name:ces_x_preferred":[
        "Ord\u017eonikidze"
    ],
    "name:deu_x_preferred":[
        "Ordschonikidse"
    ],
    "name:est_x_preferred":[
        "Ord\u017eonikidze"
    ],
    "name:fin_x_preferred":[
        "Ord\u017eonikidze"
    ],
    "name:heb_x_preferred":[
        "\u05d0\u05d5\u05e8\u05d3\u05d6'\u05d5\u05e0\u05d9\u05e7\u05d9\u05d3\u05d6\u05d4"
    ],
    "name:hye_x_preferred":[
        "\u0555\u0580\u057b\u0578\u0576\u056b\u056f\u056b\u0571\u0565"
    ],
    "name:ita_x_preferred":[
        "Ord\u017eonikidze"
    ],
    "name:jpn_x_preferred":[
        "\u30aa\u30eb\u30b8\u30e7\u30cb\u30ad\u30fc\u30bc"
    ],
    "name:kat_x_preferred":[
        "\u10dd\u10e0\u10ef\u10dd\u10dc\u10d8\u10d9\u10d8\u10eb\u10d4"
    ],
    "name:kor_x_preferred":[
        "\uc624\ub974\uc870\ub2c8\ud0a4\uc81c"
    ],
    "name:lav_x_preferred":[
        "Ord\u017eonikidze"
    ],
    "name:lit_x_preferred":[
        "Ord\u017eonikidz\u0117"
    ],
    "name:mhr_x_preferred":[
        "\u041e\u0440\u0434\u0436\u043e\u043d\u0438\u043a\u0438\u0434\u0437\u0435"
    ],
    "name:oss_x_preferred":[
        "\u041e\u0440\u0434\u0436\u043e\u043d\u0438\u043a\u0438\u0434\u0437\u0435"
    ],
    "name:rus_x_preferred":[
        "\u041e\u0440\u0434\u0436\u043e\u043d\u0438\u043a\u0438\u0434\u0437\u0435"
    ],
    "name:rus_x_variant":[
        "\u041a\u0430\u0440\u0430\u0431\u0430\u0441\u0442\u0430\u0443"
    ],
    "name:spa_x_preferred":[
        "Ordzhonikidze"
    ],
    "name:swe_x_preferred":[
        "Ordzhonikidze"
    ],
    "name:ukr_x_preferred":[
        "\u041e\u0440\u0434\u0436\u043e\u043d\u0456\u043a\u0456\u0434\u0437\u0435"
    ],
    "name:und_x_variant":[
        "Karabastau"
    ],
    "name:vie_x_preferred":[
        "Ordzhonikidze"
    ],
    "wof:name":"Ordzhonikidze",
    "wof:placetype":"locality"
},
  "geometry": {"coordinates":[69.62617,42.26127],"type":"Point"}
}