{
  "type": "Feature",
  "properties": {
    "gn:admin1_code":"10.0",
    "gn:asciiname":"Ordzhonikidze",
    "gn:country_code":"KZ",
    "gn:dem":531,
    "gn:feature_class":"P",
    "gn:feature_code":"PPL",
    "gn:name":"Ordzhonikidze",
    "gn:population":0,
    "gn:timezone":"Asia/Almaty",
    "iso:country":"KZ",
    "name:rus_x_preferred":[
        "\u041e\u0440\u0434\u0436\u043e\u043d\u0438\u043a\u0438\u0434\u0437\u0435"
    ],
    "name:rus_x_variant":[
        "\u041a\u0430\u0440\u0430\u0431\u0430\u0441\u0442\u0430\u0443"
    ],
    "name:und_x_variant":[
        "Karabastau"
    ],
    "wof:name":"Ordzhonikidze",
    "wof:placetype":"locality"
},
  "geometry": {"coordinates":[69.62617,42.26127],"type":"Point"}
}