{
  "type": "Feature",
  "properties": {
    "gn:admin1_code":"13.0",
    "gn:asciiname":"Tsabelevka",
    "gn:country_code":"KZ",
    "gn:dem":181,
    "gn:feature_class":"P",
    "gn:feature_code":"PPL",
    "gn:name":"Tsabelevka",
    "gn:population":0,
    "gn:timezone":"Asia/Qyzylorda",
    "iso:country":"KZ",
    "name:kaz_x_preferred":[
        "Tsabelevka"
    ],
    "name:kaz_x_variant":[
        "\u0426\u0430\u0431\u0435\u043b\u0435\u0432\u043a\u0430"
    ],
    "wof:name":"Tsabelevka",
    "wof:placetype":"locality"
},
  "geometry": {"coordinates":[62.89705,53.68995],"type":"Point"}
}