{
  "type": "Feature",
  "properties": {
    "gn:admin1_code":"0.0",
    "gn:asciiname":"Karasu",
    "gn:country_code":"KZ",
    "gn:dem":185,
    "gn:feature_class":"P",
    "gn:feature_code":"PPL",
    "gn:name":"Karasu",
    "gn:population":0,
    "gn:timezone":"Asia/Oral",
    "iso:country":"KZ",
    "wof:name":"Karasu",
    "wof:placetype":"locality"
},
  "geometry": {"coordinates":[54.12739000000001,50.65265],"type":"Point"}
}