{
  "type": "Feature",
  "properties": {
    "gn:admin1_code":"3.0",
    "gn:asciiname":"Prirechnoye",
    "gn:country_code":"KZ",
    "gn:dem":282,
    "gn:feature_class":"P",
    "gn:feature_code":"PPL",
    "gn:name":"Prirechnoye",
    "gn:population":0,
    "gn:timezone":"Asia/Almaty",
    "iso:country":"KZ",
    "name:eng_x_preferred":[
        "Pr\u012brechnoe"
    ],
    "name:kaz_x_preferred":[
        "\u041f\u0440\u0438\u0440\u0435\u0447\u043d\u043e\u0435"
    ],
    "name:rus_x_preferred":[
        "\u041f\u0440\u0438\u0440\u0435\u0447\u043d\u043e\u0435"
    ],
    "name:und_x_variant":[
        "Prirechenka",
        "Pr\u012brechnoe"
    ],
    "wof:name":"Prirechnoye",
    "wof:placetype":"locality"
},
  "geometry": {"coordinates":[69.05485999999999,53.14142],"type":"Point"}
}