{
  "type": "Feature",
  "properties": {
    "gn:admin1_code":"1.0",
    "gn:asciiname":"Qayrat",
    "gn:country_code":"KZ",
    "gn:dem":778,
    "gn:feature_class":"P",
    "gn:feature_code":"PPL",
    "gn:name":"Qayrat",
    "gn:population":0,
    "gn:timezone":"Asia/Almaty",
    "iso:country":"KZ",
    "name:kaz_x_preferred":[
        "Qayrat"
    ],
    "name:kaz_x_variant":[
        "\u049a\u0430\u0439\u0440\u0430\u0442"
    ],
    "name:rus_x_preferred":[
        "\u0413\u0430\u0439\u0440\u0430\u0442"
    ],
    "name:und_x_variant":[
        "Gayrat"
    ],
    "wof:name":"Qayrat",
    "wof:placetype":"locality"
},
  "geometry": {"coordinates":[78.35539,43.51703],"type":"Point"}
}