{
  "type": "Feature",
  "properties": {
    "gn:admin1_code":"15.0",
    "gn:asciiname":"Bol'shaya Rechka",
    "gn:country_code":"KZ",
    "gn:dem":340,
    "gn:feature_class":"P",
    "gn:feature_code":"PPL",
    "gn:name":"Bol\u2019shaya Rechka",
    "gn:population":0,
    "gn:timezone":"Asia/Almaty",
    "iso:country":"KZ",
    "name:eng_x_preferred":[
        "Bol'shaya Rechka"
    ],
    "name:kaz_x_preferred":[
        "\u0411\u043e\u043b\u044c\u0448\u0430\u044f \u0420\u0435\u0447\u043a\u0430"
    ],
    "name:rus_x_preferred":[
        "\u0411\u043e\u043b\u044c\u0448\u0430\u044f \u0420\u0435\u0447\u043a\u0430"
    ],
    "name:und_x_variant":[
        "Bol\u2019she-Rechenskoye",
        "Bol\u2019sherechenskiy",
        "Bol\u2019shaya Rechka"
    ],
    "wof:name":"Bol'shaya Rechka",
    "wof:placetype":"locality"
},
  "geometry": {"coordinates":[82.361,50.58216],"type":"Point"}
}