{
  "type": "Feature",
  "properties": {
    "gn:admin1_code":"12.0",
    "gn:asciiname":"Aybyz",
    "gn:country_code":"KZ",
    "gn:dem":892,
    "gn:feature_class":"P",
    "gn:feature_code":"PPL",
    "gn:name":"Aybyz",
    "gn:population":0,
    "gn:timezone":"Asia/Almaty",
    "iso:country":"KZ",
    "name:kaz_x_preferred":[
        "Aybyz"
    ],
    "name:kaz_x_variant":[
        "\u0410\u0439\u0431\u044b\u0437"
    ],
    "wof:name":"Aybyz",
    "wof:placetype":"locality"
},
  "geometry": {"coordinates":[75.53745000000001,48.95675],"type":"Point"}
}