{
  "type": "Feature",
  "properties": {
    "gn:admin1_code":"17.0",
    "gn:asciiname":"Yusupov",
    "gn:country_code":"KZ",
    "gn:dem":972,
    "gn:feature_class":"P",
    "gn:feature_code":"PPL",
    "gn:name":"Yus\u016bpov",
    "gn:population":0,
    "gn:timezone":"Asia/Almaty",
    "iso:country":"KZ",
    "name:kaz_x_preferred":[
        "Yus\u016bpov"
    ],
    "name:kaz_x_variant":[
        "\u042e\u0441\u0443\u043f\u043e\u0432"
    ],
    "wof:name":"Yusupov",
    "wof:placetype":"locality"
},
  "geometry": {"coordinates":[70.72872,42.66812],"type":"Point"}
}