{
  "type": "Feature",
  "properties": {
    "gn:admin1_code":"0.0",
    "gn:asciiname":"Dostay",
    "gn:country_code":"KZ",
    "gn:dem":41,
    "gn:feature_class":"P",
    "gn:feature_code":"PPL",
    "gn:name":"Dostay",
    "gn:population":0,
    "gn:timezone":"Asia/Oral",
    "iso:country":"KZ",
    "wof:name":"Dostay",
    "wof:placetype":"locality"
},
  "geometry": {"coordinates":[47.68333,50.26667],"type":"Point"}
}