{
  "type": "Feature",
  "properties": {
    "gn:admin1_code":"10.0",
    "gn:asciiname":"Mambet",
    "gn:country_code":"KZ",
    "gn:dem":600,
    "gn:feature_class":"P",
    "gn:feature_code":"PPL",
    "gn:name":"Mambet",
    "gn:population":0,
    "gn:timezone":"Asia/Almaty",
    "iso:country":"KZ",
    "wof:name":"Mambet",
    "wof:placetype":"locality"
},
  "geometry": {"coordinates":[69.19360999999999,41.75333],"type":"Point"}
}