{
  "type": "Feature",
  "properties": {
    "gn:admin1_code":"0.0",
    "gn:asciiname":"Begeu",
    "gn:country_code":"KZ",
    "gn:dem":35,
    "gn:feature_class":"P",
    "gn:feature_code":"PPL",
    "gn:name":"Begeu",
    "gn:population":0,
    "gn:timezone":"Asia/Oral",
    "iso:country":"KZ",
    "wof:name":"Begeu",
    "wof:placetype":"locality"
},
  "geometry": {"coordinates":[47.61667,49.35],"type":"Point"}
}