{
  "type": "Feature",
  "properties": {
    "gn:admin1_code":"16.0",
    "gn:asciiname":"Urnek",
    "gn:country_code":"KZ",
    "gn:dem":119,
    "gn:feature_class":"P",
    "gn:feature_code":"PPL",
    "gn:name":"Urnek",
    "gn:population":0,
    "gn:timezone":"Asia/Almaty",
    "iso:country":"KZ",
    "name:eng_x_preferred":[
        "Urnek"
    ],
    "name:kaz_x_preferred":[
        "\u00d6rnek"
    ],
    "name:kaz_x_variant":[
        "\u04e8\u0440\u043d\u0435\u043a"
    ],
    "name:rus_x_preferred":[
        "\u041e\u0440\u043d\u0435\u043a"
    ],
    "name:rus_x_variant":[
        "\u0423\u0440\u043d\u0435\u043a"
    ],
    "wof:name":"Urnek",
    "wof:placetype":"locality"
},
  "geometry": {"coordinates":[67.78085,54.14137],"type":"Point"}
}