{
  "type": "Feature",
  "properties": {
    "iso:country":"KZ",
    "name:ell_x_preferred":[
        "\u03a3\u03b9\u03bd\u03b3\u03ba\u03b9\u03c1\u03bb\u03ac\u03bf\u03c5"
    ],
    "name:eng_x_preferred":[
        "Chingirlau"
    ],
    "name:heb_x_preferred":[
        "\u05e6'\u05d9\u05e0\u05d2\u05d9\u05e8\u05dc\u05d0\u05d5"
    ],
    "name:kaz_x_preferred":[
        "\u0428\u044b\u04a3\u0493\u044b\u0440\u043b\u0430\u0443"
    ],
    "name:kaz_x_variant":[
        "Shyngghyrla\u016b"
    ],
    "name:nld_x_preferred":[
        "Shyngyrlau"
    ],
    "name:rus_x_preferred":[
        "\u0427\u0438\u043d\u0433\u0438\u0440\u043b\u0430\u0443"
    ],
    "name:swe_x_preferred":[
        "Tjingirlau"
    ],
    "name:ukr_x_preferred":[
        "\u0427\u0438\u043d\u0433\u0456\u0440\u043b\u0430\u0443"
    ],
    "qs:gn_country":"KZ",
    "qs:gn_fcode":"PPL",
    "qs:gn_pop":6218,
    "qs:name":"Chingirlau",
    "qs:name_adm0":"Kazakhstan",
    "qs:name_adm1":"Batys Qazaqstan",
    "qs:photos":0,
    "qs:photos_1k":0,
    "qs:photos_9k":0,
    "qs:photos_9r":0,
    "qs:photos_all":0,
    "qs:photos_sr":0,
    "qs:placetype":"Town",
    "qs:pop_sr":"5",
    "qs:woe_adm0":23424871,
    "wd:wordcount":47,
    "wof:name":"Chingirlau",
    "wof:placetype":"locality",
    "wof:population":6218
},
  "geometry": {"coordinates":[54.08426,51.09878],"type":"Point"}
}