{
  "type": "Feature",
  "properties": {
    "gn:admin1_code":"16.0",
    "gn:asciiname":"Amankeldi",
    "gn:country_code":"KZ",
    "gn:dem":114,
    "gn:feature_class":"P",
    "gn:feature_code":"PPL",
    "gn:name":"Amankeldi",
    "gn:population":0,
    "gn:timezone":"Asia/Almaty",
    "iso:country":"KZ",
    "name:eng_x_preferred":[
        "Amankeldi"
    ],
    "name:kaz_x_preferred":[
        "\u0410\u043c\u0430\u043d\u043a\u0435\u043b\u0434\u0456"
    ],
    "name:rus_x_preferred":[
        "\u0410\u043c\u0430\u043d\u0433\u0435\u043b\u044c\u0434\u044b"
    ],
    "name:und_x_variant":[
        "Amangel\u2019dy",
        "Amankeldi"
    ],
    "wof:name":"Amankeldi",
    "wof:placetype":"locality"
},
  "geometry": {"coordinates":[73.32856,53.82766],"type":"Point"}
}