{
  "type": "Feature",
  "properties": {
    "gn:admin1_code":"3.0",
    "gn:asciiname":"Dorstroy",
    "gn:country_code":"KZ",
    "gn:dem":367,
    "gn:feature_class":"P",
    "gn:feature_code":"PPL",
    "gn:name":"Dorstroy",
    "gn:population":0,
    "gn:timezone":"Asia/Almaty",
    "iso:country":"KZ",
    "name:rus_x_preferred":[
        "\u0414\u043e\u0440\u0441\u0442\u0440\u043e\u0439"
    ],
    "wof:name":"Dorstroy",
    "wof:placetype":"locality"
},
  "geometry": {"coordinates":[70.60692,52.72315],"type":"Point"}
}