{
  "type": "Feature",
  "properties": {
    "gn:admin1_code":"6.0",
    "gn:asciiname":"Kyzyluy",
    "gn:country_code":"KZ",
    "gn:dem":-2,
    "gn:feature_class":"P",
    "gn:feature_code":"PPL",
    "gn:name":"Kyzyluy",
    "gn:population":0,
    "gn:timezone":"Asia/Atyrau",
    "iso:country":"KZ",
    "wof:name":"Kyzyluy",
    "wof:placetype":"locality"
},
  "geometry": {"coordinates":[53.03333000000001,48.41667],"type":"Point"}
}