{
  "type": "Feature",
  "properties": {
    "gn:admin1_code":"12.0",
    "gn:asciiname":"Tasaul",
    "gn:country_code":"KZ",
    "gn:dem":483,
    "gn:feature_class":"P",
    "gn:feature_code":"PPL",
    "gn:name":"Tasaul",
    "gn:population":0,
    "gn:timezone":"Asia/Almaty",
    "iso:country":"KZ",
    "name:rus_x_preferred":[
        "\u0422\u0430\u0441\u0430\u0443\u043b"
    ],
    "name:und_x_variant":[
        "Tas"
    ],
    "wof:name":"Tasaul",
    "wof:placetype":"locality"
},
  "geometry": {"coordinates":[72.75315000000001,50.02481],"type":"Point"}
}