{
  "type": "Feature",
  "properties": {
    "gn:admin1_code":"10.0",
    "gn:asciiname":"Imeni Voroshilova",
    "gn:country_code":"KZ",
    "gn:dem":267,
    "gn:feature_class":"P",
    "gn:feature_code":"PPL",
    "gn:name":"Imeni Voroshilova",
    "gn:population":0,
    "gn:timezone":"Asia/Almaty",
    "iso:country":"KZ",
    "name:rus_x_preferred":[
        "\u0418\u043c\u0435\u043d\u0438 \u0412\u043e\u0440\u043e\u0448\u0438\u043b\u043e\u0432\u0430"
    ],
    "wof:name":"Imeni Voroshilova",
    "wof:placetype":"locality"
},
  "geometry": {"coordinates":[68.54401,40.80195],"type":"Point"}
}