{
  "type": "Feature",
  "properties": {
    "gn:admin1_code":"0.0",
    "gn:asciiname":"Korzhin",
    "gn:cc2":"KZ",
    "gn:country_code":"KZ",
    "gn:dem":386,
    "gn:feature_class":"P",
    "gn:feature_code":"PPL",
    "gn:name":"Korzhin",
    "gn:population":0,
    "gn:timezone":"Asia/Almaty",
    "iso:country":"KZ",
    "name:und_x_variant":[
        "Korzhun",
        "Korzhin"
    ],
    "wof:name":"Korzhin",
    "wof:placetype":"locality"
},
  "geometry": {"coordinates":[83.45,48.21667],"type":"Point"}
}