{
  "type": "Feature",
  "properties": {
    "gn:admin1_code":"10.0",
    "gn:asciiname":"Dostyq",
    "gn:country_code":"KZ",
    "gn:dem":215,
    "gn:feature_class":"P",
    "gn:feature_code":"PPL",
    "gn:name":"Dostyq",
    "gn:population":0,
    "gn:timezone":"Asia/Almaty",
    "iso:country":"KZ",
    "name:kaz_x_preferred":[
        "Dostyq"
    ],
    "name:kaz_x_variant":[
        "\u0414\u043e\u0441\u0442\u044b\u049b"
    ],
    "name:rus_x_preferred":[
        "\u0414\u043e\u0441\u0442\u044b\u043a"
    ],
    "name:und_x_variant":[
        "Dostyk"
    ],
    "wof:name":"Dostyq",
    "wof:placetype":"locality"
},
  "geometry": {"coordinates":[68.12383,42.05476],"type":"Point"}
}