{
  "type": "Feature",
  "properties": {
    "gn:admin1_code":"16.0",
    "gn:asciiname":"Oktyabr'skoye",
    "gn:country_code":"KZ",
    "gn:dem":164,
    "gn:feature_class":"P",
    "gn:feature_code":"PPL",
    "gn:name":"Oktyabr\u2019skoye",
    "gn:population":0,
    "gn:timezone":"Asia/Almaty",
    "iso:country":"KZ",
    "name:rus_x_preferred":[
        "Oktyabr\u2019skoye"
    ],
    "name:rus_x_variant":[
        "\u041e\u043a\u0442\u044f\u0431\u0440\u044c\u0441\u043a\u043e\u0435"
    ],
    "wof:name":"Oktyabr'skoye",
    "wof:placetype":"locality"
},
  "geometry": {"coordinates":[67.03885,53.5532],"type":"Point"}
}