{
  "type": "Feature",
  "properties": {
    "gn:admin1_code":"3.0",
    "gn:asciiname":"Vostochnoye",
    "gn:country_code":"KZ",
    "gn:dem":109,
    "gn:feature_class":"P",
    "gn:feature_code":"PPL",
    "gn:name":"Vostochnoye",
    "gn:population":0,
    "gn:timezone":"Asia/Almaty",
    "iso:country":"KZ",
    "name:rus_x_preferred":[
        "\u0412\u043e\u0441\u0442\u043e\u0447\u043d\u043e\u0435"
    ],
    "wof:name":"Vostochnoye",
    "wof:placetype":"locality"
},
  "geometry": {"coordinates":[73.41129000000002,52.54268],"type":"Point"}
}