{
  "type": "Feature",
  "properties": {
    "gn:admin1_code":"4.0",
    "gn:asciiname":"Kopbulak",
    "gn:country_code":"KZ",
    "gn:dem":253,
    "gn:feature_class":"P",
    "gn:feature_code":"PPL",
    "gn:name":"Kopbulak",
    "gn:population":0,
    "gn:timezone":"Asia/Aqtobe",
    "iso:country":"KZ",
    "name:und_x_variant":[
        "Konbulak",
        "Kopbulak"
    ],
    "wof:name":"Kopbulak",
    "wof:placetype":"locality"
},
  "geometry": {"coordinates":[56.75,47.78333],"type":"Point"}
}