{
  "type": "Feature",
  "properties": {
    "gn:admin1_code":"11.0",
    "gn:asciiname":"Syirbay",
    "gn:country_code":"KZ",
    "gn:dem":348,
    "gn:feature_class":"P",
    "gn:feature_code":"PPL",
    "gn:name":"Syirbay",
    "gn:population":0,
    "gn:timezone":"Asia/Almaty",
    "iso:country":"KZ",
    "wof:name":"Syirbay",
    "wof:placetype":"locality"
},
  "geometry": {"coordinates":[76.73333000000002,50.48333],"type":"Point"}
}