{
  "type": "Feature",
  "properties": {
    "gn:admin1_code":"13.0",
    "gn:asciiname":"Mirolyubovka",
    "gn:country_code":"KZ",
    "gn:dem":148,
    "gn:feature_class":"P",
    "gn:feature_code":"PPL",
    "gn:name":"Mirolyubovka",
    "gn:population":0,
    "gn:timezone":"Asia/Qyzylorda",
    "iso:country":"KZ",
    "name:eng_x_preferred":[
        "Mirolyubovka"
    ],
    "name:kaz_x_preferred":[
        "M\u012brolyubovka"
    ],
    "name:kaz_x_variant":[
        "\u041c\u0438\u0440\u043e\u043b\u044e\u0431\u043e\u0432\u043a\u0430"
    ],
    "name:rus_x_preferred":[
        "\u041c\u0438\u0440\u043e\u043b\u044e\u0431\u043e\u0432\u043a\u0430"
    ],
    "name:und_x_variant":[
        "Kiyevskiy"
    ],
    "wof:name":"Mirolyubovka",
    "wof:placetype":"locality"
},
  "geometry": {"coordinates":[65.02656999999999,53.98087],"type":"Point"}
}