{
  "type": "Feature",
  "properties": {
    "gn:admin1_code":"0.0",
    "gn:asciiname":"Kutymkol'",
    "gn:country_code":"KZ",
    "gn:dem":326,
    "gn:feature_class":"P",
    "gn:feature_code":"PPL",
    "gn:name":"Kutymkol\u2019",
    "gn:population":0,
    "gn:timezone":"Asia/Almaty",
    "iso:country":"KZ",
    "name:und_x_variant":[
        "Kuton-Kul\u2019",
        "Kutymkol\u2019"
    ],
    "wof:name":"Kutymkol'",
    "wof:placetype":"locality"
},
  "geometry": {"coordinates":[73.28333000000001,51.58333],"type":"Point"}
}