{
  "type": "Feature",
  "properties": {
    "gn:admin1_code":"11.0",
    "gn:asciiname":"Spartak",
    "gn:country_code":"KZ",
    "gn:dem":105,
    "gn:feature_class":"P",
    "gn:feature_code":"PPL",
    "gn:name":"Spartak",
    "gn:population":0,
    "gn:timezone":"Asia/Almaty",
    "iso:country":"KZ",
    "name:eng_x_preferred":[
        "Spartak"
    ],
    "name:kaz_x_preferred":[
        "\u0421\u043f\u0430\u0440\u0442\u0430\u043a"
    ],
    "name:rus_x_preferred":[
        "\u041a\u0430\u0440\u0430\u043e\u0431\u0430"
    ],
    "name:und_x_variant":[
        "Karaoba",
        "Spartak"
    ],
    "wof:name":"Spartak",
    "wof:placetype":"locality"
},
  "geometry": {"coordinates":[76.45224,52.70319],"type":"Point"}
}