{
  "type": "Feature",
  "properties": {
    "gn:admin1_code":"11.0",
    "gn:asciiname":"Spartak",
    "gn:country_code":"KZ",
    "gn:dem":105,
    "gn:feature_class":"P",
    "gn:feature_code":"PPL",
    "gn:name":"Spartak",
    "gn:population":0,
    "gn:timezone":"Asia/Almaty",
    "iso:country":"KZ",
    "name:ces_x_preferred":[
        "Spartak"
    ],
    "name:deu_x_preferred":[
        "Spartak"
    ],
    "name:eng_x_preferred":[
        "Spartak"
    ],
    "name:est_x_preferred":[
        "Spartak"
    ],
    "name:fin_x_preferred":[
        "Spartak"
    ],
    "name:fra_x_preferred":[
        "Spartak"
    ],
    "name:heb_x_preferred":[
        "\u05e1\u05e4\u05e8\u05d8\u05e7"
    ],
    "name:kaz_x_preferred":[
        "\u0421\u043f\u0430\u0440\u0442\u0430\u043a"
    ],
    "name:kor_x_preferred":[
        "\uc2a4\ud30c\ub974\ud0c0\ud06c"
    ],
    "name:lav_x_preferred":[
        "Spartak"
    ],
    "name:nld_x_preferred":[
        "Spartak"
    ],
    "name:por_x_preferred":[
        "Spartak"
    ],
    "name:rus_x_preferred":[
        "\u041a\u0430\u0440\u0430\u043e\u0431\u0430"
    ],
    "name:rus_x_variant":[
        "\u0421\u043f\u0430\u0440\u0442\u0430\u043a"
    ],
    "name:slv_x_preferred":[
        "Spartak"
    ],
    "name:und_x_variant":[
        "Karaoba"
    ],
    "wof:name":"Spartak",
    "wof:placetype":"locality"
},
  "geometry": {"coordinates":[76.45224,52.70319],"type":"Point"}
}