{
  "type": "Feature",
  "properties": {
    "gn:admin1_code":"11.0",
    "gn:asciiname":"Natashino",
    "gn:country_code":"KZ",
    "gn:dem":107,
    "gn:feature_class":"P",
    "gn:feature_code":"PPL",
    "gn:name":"Natashino",
    "gn:population":0,
    "gn:timezone":"Asia/Almaty",
    "iso:country":"KZ",
    "name:eng_x_preferred":[
        "Natashino"
    ],
    "name:kaz_x_preferred":[
        "Natash\u012bno"
    ],
    "name:kaz_x_variant":[
        "\u041d\u0430\u0442\u0430\u0448\u0438\u043d\u043e"
    ],
    "name:rus_x_preferred":[
        "\u041d\u0430\u0442\u0430\u0448\u0438\u043d\u043e"
    ],
    "wof:name":"Natashino",
    "wof:placetype":"locality"
},
  "geometry": {"coordinates":[76.97403,52.9102],"type":"Point"}
}