{
  "type": "Feature",
  "properties": {
    "gn:admin1_code":"11.0",
    "gn:asciiname":"Sement",
    "gn:country_code":"KZ",
    "gn:dem":263,
    "gn:feature_class":"P",
    "gn:feature_code":"PPL",
    "gn:name":"Sement",
    "gn:population":0,
    "gn:timezone":"Asia/Almaty",
    "iso:country":"KZ",
    "name:rus_x_preferred":[
        "\u0421\u0435\u043c\u0435\u043d\u0442"
    ],
    "wof:name":"Sement",
    "wof:placetype":"locality"
},
  "geometry": {"coordinates":[77.17616,50.76097],"type":"Point"}
}