{
  "type": "Feature",
  "properties": {
    "gn:admin1_code":"10.0",
    "gn:asciiname":"Akbastau",
    "gn:country_code":"KZ",
    "gn:dem":864,
    "gn:feature_class":"P",
    "gn:feature_code":"PPL",
    "gn:name":"Akbastau",
    "gn:population":0,
    "gn:timezone":"Asia/Almaty",
    "iso:country":"KZ",
    "wof:name":"Akbastau",
    "wof:placetype":"locality"
},
  "geometry": {"coordinates":[70.11667,42.88333],"type":"Point"}
}