{
  "type": "Feature",
  "properties": {
    "gn:admin1_code":"17.0",
    "gn:asciiname":"Mar'yanovka",
    "gn:country_code":"KZ",
    "gn:dem":951,
    "gn:feature_class":"P",
    "gn:feature_code":"PPL",
    "gn:name":"Mar\u2019yanovka",
    "gn:population":0,
    "gn:timezone":"Asia/Almaty",
    "iso:country":"KZ",
    "name:rus_x_preferred":[
        "Mar\u2019yanovka"
    ],
    "name:rus_x_variant":[
        "\u041c\u0430\u0440\u044c\u044f\u043d\u043e\u0432\u043a\u0430"
    ],
    "wof:name":"Mar'yanovka",
    "wof:placetype":"locality"
},
  "geometry": {"coordinates":[71.06707,42.6374],"type":"Point"}
}