{
  "type": "Feature",
  "properties": {
    "gn:admin1_code":"16.0",
    "gn:asciiname":"Vishnevka",
    "gn:country_code":"KZ",
    "gn:dem":95,
    "gn:feature_class":"P",
    "gn:feature_code":"PPL",
    "gn:name":"Vishn\u00ebvka",
    "gn:population":0,
    "gn:timezone":"Asia/Almaty",
    "iso:country":"KZ",
    "name:rus_x_preferred":[
        "Vishn\u00ebvka"
    ],
    "name:rus_x_variant":[
        "\u0412\u0438\u0448\u043d\u0451\u0432\u043a\u0430"
    ],
    "wof:name":"Vishnevka",
    "wof:placetype":"locality"
},
  "geometry": {"coordinates":[69.07247,54.93957],"type":"Point"}
}