{
  "type": "Feature",
  "properties": {
    "gn:admin1_code":"14.0",
    "gn:asciiname":"Yekpyndy",
    "gn:country_code":"KZ",
    "gn:dem":155,
    "gn:feature_class":"P",
    "gn:feature_code":"PPL",
    "gn:name":"Yekpyndy",
    "gn:population":0,
    "gn:timezone":"Asia/Qyzylorda",
    "iso:country":"KZ",
    "name:kaz_x_preferred":[
        "Ekpindi"
    ],
    "name:und_x_variant":[
        "Yekpindy",
        "Yekpyndy"
    ],
    "wof:name":"Yekpyndy",
    "wof:placetype":"locality"
},
  "geometry": {"coordinates":[66.95,44.08333],"type":"Point"}
}