{
  "type": "Feature",
  "properties": {
    "gn:admin1_code":"12.0",
    "gn:asciiname":"Zhanatay",
    "gn:country_code":"KZ",
    "gn:dem":591,
    "gn:feature_class":"P",
    "gn:feature_code":"PPL",
    "gn:name":"Zhanatay",
    "gn:population":0,
    "gn:timezone":"Asia/Almaty",
    "iso:country":"KZ",
    "name:rus_x_preferred":[
        "\u0416\u0430\u043d\u0430\u0442\u0430\u0439"
    ],
    "wof:name":"Zhanatay",
    "wof:placetype":"locality"
},
  "geometry": {"coordinates":[72.50243,48.52595],"type":"Point"}
}