{
  "type": "Feature",
  "properties": {
    "gn:admin1_code":"0.0",
    "gn:asciiname":"Beken",
    "gn:country_code":"KZ",
    "gn:dem":32,
    "gn:feature_class":"P",
    "gn:feature_code":"PPL",
    "gn:name":"Beken",
    "gn:population":0,
    "gn:timezone":"Asia/Oral",
    "iso:country":"KZ",
    "wof:name":"Beken",
    "wof:placetype":"locality"
},
  "geometry": {"coordinates":[47.65,49.96667],"type":"Point"}
}