{
  "type": "Feature",
  "properties": {
    "gn:admin1_code":"0.0",
    "gn:asciiname":"Ayakmoildy",
    "gn:country_code":"KZ",
    "gn:dem":148,
    "gn:feature_class":"P",
    "gn:feature_code":"PPL",
    "gn:name":"Ayakmoildy",
    "gn:population":0,
    "gn:timezone":"Asia/Almaty",
    "iso:country":"KZ",
    "wof:name":"Ayakmoildy",
    "wof:placetype":"locality"
},
  "geometry": {"coordinates":[65.13333,51.03333],"type":"Point"}
}