{
  "type": "Feature",
  "properties": {
    "gn:admin1_code":"17.0",
    "gn:asciiname":"Algatart",
    "gn:country_code":"KZ",
    "gn:dem":446,
    "gn:feature_class":"P",
    "gn:feature_code":"PPL",
    "gn:name":"Algatart",
    "gn:population":0,
    "gn:timezone":"Asia/Almaty",
    "iso:country":"KZ",
    "wof:name":"Algatart",
    "wof:placetype":"locality"
},
  "geometry": {"coordinates":[73.56667,43.75],"type":"Point"}
}