{
  "type": "Feature",
  "properties": {
    "gn:admin1_code":"4.0",
    "gn:asciiname":"Stavropol'skiy",
    "gn:country_code":"KZ",
    "gn:dem":236,
    "gn:feature_class":"P",
    "gn:feature_code":"PPL",
    "gn:name":"Stavropol\u2019skiy",
    "gn:population":0,
    "gn:timezone":"Asia/Aqtobe",
    "iso:country":"KZ",
    "name:eng_x_preferred":[
        "Stavropol'skiy"
    ],
    "name:rus_x_preferred":[
        "\u0421\u0442\u0430\u0432\u0440\u043e\u043f\u043e\u043b\u044c"
    ],
    "name:und_x_variant":[
        "Stavropol\u2019skiy"
    ],
    "wof:name":"Stavropol'skiy",
    "wof:placetype":"locality"
},
  "geometry": {"coordinates":[56.35,49.25],"type":"Point"}
}