{
  "type": "Feature",
  "properties": {
    "gn:admin1_code":"11.0",
    "gn:asciiname":"Qarashat",
    "gn:country_code":"KZ",
    "gn:dem":502,
    "gn:feature_class":"P",
    "gn:feature_code":"PPL",
    "gn:name":"Qarashat",
    "gn:population":0,
    "gn:timezone":"Asia/Almaty",
    "iso:country":"KZ",
    "name:kaz_x_preferred":[
        "Qarashat"
    ],
    "name:kaz_x_variant":[
        "\u049a\u0430\u0440\u0430\u0448\u0430\u0442"
    ],
    "name:rus_x_preferred":[
        "\u041a\u0430\u0440\u0430\u0448\u0430\u0442"
    ],
    "name:und_x_variant":[
        "Karashat"
    ],
    "wof:name":"Qarashat",
    "wof:placetype":"locality"
},
  "geometry": {"coordinates":[75.45309,50.6942],"type":"Point"}
}