{
  "type": "Feature",
  "properties": {
    "gn:admin1_code":"12.0",
    "gn:asciiname":"Gul'densin",
    "gn:country_code":"KZ",
    "gn:dem":760,
    "gn:feature_class":"P",
    "gn:feature_code":"PPL",
    "gn:name":"Gul\u2019densin",
    "gn:population":0,
    "gn:timezone":"Asia/Almaty",
    "iso:country":"KZ",
    "name:rus_x_preferred":[
        "Gul\u2019densin"
    ],
    "name:rus_x_variant":[
        "\u0413\u0443\u043b\u044c\u0434\u0435\u043d\u0441\u0438\u043d"
    ],
    "wof:name":"Gul'densin",
    "wof:placetype":"locality"
},
  "geometry": {"coordinates":[73.13332,48.58006],"type":"Point"}
}