{
  "type": "Feature",
  "properties": {
    "gn:admin1_code":"0.0",
    "gn:asciiname":"Shakpak",
    "gn:country_code":"KZ",
    "gn:dem":131,
    "gn:feature_class":"P",
    "gn:feature_code":"PPL",
    "gn:name":"Shakpak",
    "gn:population":0,
    "gn:timezone":"Asia/Almaty",
    "iso:country":"KZ",
    "wof:name":"Shakpak",
    "wof:placetype":"locality"
},
  "geometry": {"coordinates":[65.15000000000001,50.06667],"type":"Point"}
}