{
  "type": "Feature",
  "properties": {
    "gn:admin1_code":"11.0",
    "gn:asciiname":"Oktyabr'skoye",
    "gn:country_code":"KZ",
    "gn:dem":109,
    "gn:feature_class":"P",
    "gn:feature_code":"PPL",
    "gn:name":"Oktyabr\u2019skoye",
    "gn:population":0,
    "gn:timezone":"Asia/Almaty",
    "iso:country":"KZ",
    "name:eng_x_preferred":[
        "Oktyabr'"
    ],
    "name:kaz_x_preferred":[
        "Oktyabr\u2019skoe"
    ],
    "name:kaz_x_variant":[
        "\u041e\u043a\u0442\u044f\u0431\u0440\u044c\u0441\u043a\u043e\u0435"
    ],
    "name:rus_x_preferred":[
        "\u041e\u043a\u0442\u044f\u0431\u0440\u044c"
    ],
    "name:und_x_variant":[
        "Bogoyavlenka",
        "Oktyabr\u2019skoye",
        "Oktyabr\u2019"
    ],
    "wof:name":"Oktyabr'skoye",
    "wof:placetype":"locality"
},
  "geometry": {"coordinates":[75.56075,53.92799],"type":"Point"}
}