{
  "type": "Feature",
  "properties": {
    "gn:admin1_code":"0.0",
    "gn:asciiname":"Bayaktobe",
    "gn:country_code":"KZ",
    "gn:dem":-5,
    "gn:feature_class":"P",
    "gn:feature_code":"PPL",
    "gn:name":"Bayaktobe",
    "gn:population":0,
    "gn:timezone":"Asia/Oral",
    "iso:country":"KZ",
    "name:eng_x_preferred":[
        "Bayaktobe"
    ],
    "name:rus_x_preferred":[
        "\u0411\u0430\u044f\u043d\u0442\u043e\u0431\u0435"
    ],
    "wof:name":"Bayaktobe",
    "wof:placetype":"locality"
},
  "geometry": {"coordinates":[51.98333,49.06667],"type":"Point"}
}