{
  "type": "Feature",
  "properties": {
    "gn:admin1_code":"16.0",
    "gn:asciiname":"Shukyrkol'",
    "gn:country_code":"KZ",
    "gn:dem":262,
    "gn:feature_class":"P",
    "gn:feature_code":"PPL",
    "gn:name":"Shukyrkol\u2019",
    "gn:population":0,
    "gn:timezone":"Asia/Almaty",
    "iso:country":"KZ",
    "name:eng_x_preferred":[
        "Shuqyrk\u00f6l"
    ],
    "name:kaz_x_preferred":[
        "\u0428\u04b1\u049b\u044b\u0440\u043a\u04e9\u043b"
    ],
    "name:rus_x_preferred":[
        "\u0428\u0443\u043a\u044b\u0440\u043a\u043e\u043b\u044c"
    ],
    "name:rus_x_variant":[
        "\u0410\u043d\u0434\u0430\u0433\u0443\u043b"
    ],
    "name:und_x_variant":[
        "Andagay",
        "Shukurgul\u2019",
        "Andagul",
        "Shukyrkol\u2019",
        "Shuqyrk\u00f6l"
    ],
    "wof:name":"Shukyrkol'",
    "wof:placetype":"locality"
},
  "geometry": {"coordinates":[67.30433000000001,53.1256],"type":"Point"}
}