{
  "type": "Feature",
  "properties": {
    "iso:country":"KZ",
    "name:eng_x_preferred":[
        "Mayqayyng"
    ],
    "name:fra_x_preferred":[
        "Mayqayyng"
    ],
    "name:kaz_x_preferred":[
        "\u041c\u0430\u0439\u049b\u0430\u0439\u044b\u04a3"
    ],
    "name:rus_x_preferred":[
        "\u041c\u0430\u0439\u043a\u0430\u0439\u043d"
    ],
    "name:swe_x_preferred":[
        "Mayqayyng"
    ],
    "name:unk_x_variant":[
        "Maykainskiy"
    ],
    "qs:gn_country":"KZ",
    "qs:gn_fcode":"PPL",
    "qs:gn_pop":7695,
    "qs:name":"Maykain",
    "qs:name_adm0":"Kazakhstan",
    "qs:name_adm1":"Pavlodar",
    "qs:photos":0,
    "qs:photos_1k":0,
    "qs:photos_9k":0,
    "qs:photos_9r":0,
    "qs:photos_all":0,
    "qs:photos_sr":0,
    "qs:placetype":"Town",
    "qs:pop_sr":"5",
    "qs:woe_adm0":23424871,
    "wof:name":"Maykain",
    "wof:placetype":"locality",
    "wof:population":7695
},
  "geometry": {"coordinates":[75.80481,51.46088],"type":"Point"}
}