{
  "type": "Feature",
  "properties": {
    "gn:admin1_code":"16.0",
    "gn:asciiname":"Novoprirechnoye",
    "gn:country_code":"KZ",
    "gn:dem":161,
    "gn:feature_class":"P",
    "gn:feature_code":"PPL",
    "gn:name":"Novoprirechnoye",
    "gn:population":0,
    "gn:timezone":"Asia/Almaty",
    "iso:country":"KZ",
    "name:eng_x_preferred":[
        "Novoprirechnoye"
    ],
    "name:kaz_x_preferred":[
        "Novopr\u012brechnoe"
    ],
    "name:kaz_x_variant":[
        "\u041d\u043e\u0432\u043e\u043f\u0440\u0438\u0440\u0435\u0447\u043d\u043e\u0435"
    ],
    "name:rus_x_preferred":[
        "\u041d\u043e\u0432\u043e\u043f\u0440\u0438\u0440\u0435\u0447\u043d\u043e\u0435"
    ],
    "wof:name":"Novoprirechnoye",
    "wof:placetype":"locality"
},
  "geometry": {"coordinates":[69.71536999999999,53.7945],"type":"Point"}
}