{
  "type": "Feature",
  "properties": {
    "gn:admin1_code":"10.0",
    "gn:asciiname":"Bugun'",
    "gn:country_code":"KZ",
    "gn:dem":246,
    "gn:feature_class":"P",
    "gn:feature_code":"PPL",
    "gn:name":"Bugun\u2019",
    "gn:population":0,
    "gn:timezone":"Asia/Almaty",
    "iso:country":"KZ",
    "name:kaz_x_preferred":[
        "\u0411\u04e9\u0433\u0435\u043d"
    ],
    "name:rus_x_preferred":[
        "\u0411\u0443\u0433\u0443\u043d\u044c"
    ],
    "name:und_x_variant":[
        "Bugun\u2019",
        "B\u00f6gen"
    ],
    "wof:name":"Bugun'",
    "wof:placetype":"locality"
},
  "geometry": {"coordinates":[68.98254,42.73815],"type":"Point"}
}