{
  "type": "Feature",
  "properties": {
    "gn:admin1_code":"16.0",
    "gn:asciiname":"Ol'zhansk",
    "gn:country_code":"KZ",
    "gn:dem":388,
    "gn:feature_class":"P",
    "gn:feature_code":"PPL",
    "gn:name":"Ol\u2019zhansk",
    "gn:population":0,
    "gn:timezone":"Asia/Almaty",
    "iso:country":"KZ",
    "name:eng_x_preferred":[
        "Al'zhanka"
    ],
    "name:kaz_x_preferred":[
        "\u00c4lzhan"
    ],
    "name:kaz_x_variant":[
        "\u04d8\u043b\u0436\u0430\u043d"
    ],
    "name:rus_x_preferred":[
        "\u0410\u043b\u044c\u0436\u0430\u043d\u043a\u0430"
    ],
    "name:rus_x_variant":[
        "\u041e\u043b\u044c\u0436\u0430\u043d\u0441\u043a"
    ],
    "name:und_x_variant":[
        "Stalino",
        "Imeni Stalina",
        "Ol\u2019zhansk",
        "Al\u2019zhanka"
    ],
    "wof:name":"Ol'zhansk",
    "wof:placetype":"locality"
},
  "geometry": {"coordinates":[68.64312,53.06372],"type":"Point"}
}