{
  "type": "Feature",
  "properties": {
    "gn:admin1_code":"16.0",
    "gn:asciiname":"Mironovka",
    "gn:country_code":"KZ",
    "gn:dem":153,
    "gn:feature_class":"P",
    "gn:feature_code":"PPL",
    "gn:name":"Mironovka",
    "gn:population":0,
    "gn:timezone":"Asia/Almaty",
    "iso:country":"KZ",
    "name:eng_x_preferred":[
        "Mironovka"
    ],
    "name:kaz_x_preferred":[
        "M\u012bronovka"
    ],
    "name:kaz_x_variant":[
        "\u041c\u0438\u0440\u043e\u043d\u043e\u0432\u043a\u0430"
    ],
    "name:rus_x_preferred":[
        "\u041c\u0438\u0440\u043e\u043d\u043e\u0432\u043a\u0430"
    ],
    "name:und_x_variant":[
        "Mironovskoye"
    ],
    "wof:name":"Mironovka",
    "wof:placetype":"locality"
},
  "geometry": {"coordinates":[69.83623,53.83977],"type":"Point"}
}