{
  "type": "Feature",
  "properties": {
    "gn:admin1_code":"16.0",
    "gn:asciiname":"Kokterek",
    "gn:country_code":"KZ",
    "gn:dem":119,
    "gn:feature_class":"P",
    "gn:feature_code":"PPL",
    "gn:name":"Kokterek",
    "gn:population":0,
    "gn:timezone":"Asia/Almaty",
    "iso:country":"KZ",
    "name:eng_x_preferred":[
        "K\u00f6kterek"
    ],
    "name:kaz_x_preferred":[
        "\u041a\u04e9\u043a\u0442\u0435\u0440\u0435\u043a"
    ],
    "name:rus_x_preferred":[
        "\u041a\u043e\u043a\u0442\u0435\u0440\u0435\u043a"
    ],
    "name:und_x_variant":[
        "Kokterek"
    ],
    "wof:name":"Kokterek",
    "wof:placetype":"locality"
},
  "geometry": {"coordinates":[73.19790999999999,53.47671999999999],"type":"Point"}
}