{
  "type": "Feature",
  "properties": {
    "gn:admin1_code":"11.0",
    "gn:asciiname":"Malinovka",
    "gn:country_code":"KZ",
    "gn:dem":145,
    "gn:feature_class":"P",
    "gn:feature_code":"PPL",
    "gn:name":"Malinovka",
    "gn:population":0,
    "gn:timezone":"Asia/Almaty",
    "iso:country":"KZ",
    "name:kaz_x_preferred":[
        "Mal\u012bnovka"
    ],
    "name:kaz_x_variant":[
        "\u041c\u0430\u043b\u0438\u043d\u043e\u0432\u043a\u0430"
    ],
    "wof:name":"Malinovka",
    "wof:placetype":"locality"
},
  "geometry": {"coordinates":[78.23701,52.42266],"type":"Point"}
}