{
  "type": "Feature",
  "properties": {
    "gn:admin1_code":"15.0",
    "gn:asciiname":"Solnechnoe",
    "gn:country_code":"KZ",
    "gn:dem":435,
    "gn:feature_class":"P",
    "gn:feature_code":"PPL",
    "gn:name":"Solnechnoe",
    "gn:population":0,
    "gn:timezone":"Asia/Almaty",
    "iso:country":"KZ",
    "name:kaz_x_preferred":[
        "Solnechnoe"
    ],
    "name:kaz_x_variant":[
        "\u0421\u043e\u043b\u043d\u0435\u0447\u043d\u043e\u0435"
    ],
    "name:rus_x_preferred":[
        "\u0421\u043e\u043b\u043d\u0435\u0447\u043d\u044b\u0439"
    ],
    "name:und_x_variant":[
        "Solnechnyy"
    ],
    "wof:name":"Solnechnoe",
    "wof:placetype":"locality"
},
  "geometry": {"coordinates":[81.59883000000001,49.70052],"type":"Point"}
}