{
  "type": "Feature",
  "properties": {
    "gn:admin1_code":"0.0",
    "gn:asciiname":"Novo-Orlinskoye",
    "gn:country_code":"KZ",
    "gn:dem":377,
    "gn:feature_class":"P",
    "gn:feature_code":"PPL",
    "gn:name":"Novo-Orlinskoye",
    "gn:population":0,
    "gn:timezone":"Asia/Almaty",
    "iso:country":"KZ",
    "wof:name":"Novo-Orlinskoye",
    "wof:placetype":"locality"
},
  "geometry": {"coordinates":[71.09999999999999,51.93333],"type":"Point"}
}