{
  "type": "Feature",
  "properties": {
    "gn:admin1_code":"10.0",
    "gn:asciiname":"Sarykol",
    "gn:country_code":"KZ",
    "gn:dem":201,
    "gn:feature_class":"P",
    "gn:feature_code":"PPL",
    "gn:name":"Saryk\u00f6l",
    "gn:population":0,
    "gn:timezone":"Asia/Almaty",
    "iso:country":"KZ",
    "name:kaz_x_preferred":[
        "Saryk\u00f6l"
    ],
    "name:kaz_x_variant":[
        "\u0421\u0430\u0440\u044b\u043a\u04e9\u043b"
    ],
    "name:rus_x_preferred":[
        "Sarykol\u2019"
    ],
    "name:rus_x_variant":[
        "\u0421\u0430\u0440\u044b\u043a\u043e\u043b\u044c"
    ],
    "wof:name":"Sarykol",
    "wof:placetype":"locality"
},
  "geometry": {"coordinates":[68.29411999999999,42.63261],"type":"Point"}
}