{
  "type": "Feature",
  "properties": {
    "gn:admin1_code":"16.0",
    "gn:asciiname":"Benzostroy",
    "gn:country_code":"KZ",
    "gn:dem":132,
    "gn:feature_class":"P",
    "gn:feature_code":"PPL",
    "gn:name":"Benzostroy",
    "gn:population":0,
    "gn:timezone":"Asia/Almaty",
    "iso:country":"KZ",
    "name:rus_x_preferred":[
        "\u0411\u0435\u043d\u0437\u043e\u0441\u0442\u0440\u043e\u0439"
    ],
    "name:und_x_variant":[
        "Banzostroy"
    ],
    "wof:name":"Benzostroy",
    "wof:placetype":"locality"
},
  "geometry": {"coordinates":[70.34333000000001,54.91242],"type":"Point"}
}