{
  "type": "Feature",
  "properties": {
    "gn:admin1_code":"13.0",
    "gn:asciiname":"Taysoygan",
    "gn:country_code":"KZ",
    "gn:dem":162,
    "gn:feature_class":"P",
    "gn:feature_code":"PPL",
    "gn:name":"Taysoygan",
    "gn:population":0,
    "gn:timezone":"Asia/Qyzylorda",
    "iso:country":"KZ",
    "name:eng_x_preferred":[
        "Taysoygan"
    ],
    "name:kaz_x_preferred":[
        "Taysoyghan"
    ],
    "name:kaz_x_variant":[
        "\u0422\u0430\u0439\u0441\u043e\u0439\u0493\u0430\u043d"
    ],
    "name:rus_x_preferred":[
        "\u0422\u0430\u0439\u0441\u043e\u0439\u0433\u0430\u043d"
    ],
    "name:und_x_variant":[
        "Aysagan",
        "Aysugan",
        "Taysoygan"
    ],
    "wof:name":"Taysoygan",
    "wof:placetype":"locality"
},
  "geometry": {"coordinates":[64.9849,54.31158000000001],"type":"Point"}
}