{
  "type": "Feature",
  "properties": {
    "gn:admin1_code":"0.0",
    "gn:asciiname":"Kol'bastau",
    "gn:country_code":"KZ",
    "gn:dem":2007,
    "gn:feature_class":"P",
    "gn:feature_code":"PPL",
    "gn:name":"Kol\u2019bastau",
    "gn:population":0,
    "gn:timezone":"Asia/Almaty",
    "iso:country":"KZ",
    "name:und_x_variant":[
        "Kontora Kazlesa",
        "Kol\u2019bastau"
    ],
    "wof:name":"Kol'bastau",
    "wof:placetype":"locality"
},
  "geometry": {"coordinates":[78.56667,43.03333],"type":"Point"}
}