{
  "type": "Feature",
  "properties": {
    "gn:admin1_code":"0.0",
    "gn:asciiname":"Aksay",
    "gn:country_code":"KZ",
    "gn:dem":0,
    "gn:feature_class":"P",
    "gn:feature_code":"PPL",
    "gn:name":"Aksay",
    "gn:population":0,
    "gn:timezone":"Asia/Oral",
    "iso:country":"KZ",
    "wof:name":"Aksay",
    "wof:placetype":"locality"
},
  "geometry": {"coordinates":[50.18333,49.33333],"type":"Point"}
}