{
  "type": "Feature",
  "properties": {
    "gn:admin1_code":"1.0",
    "gn:asciiname":"Sartasu",
    "gn:country_code":"KZ",
    "gn:dem":2070,
    "gn:feature_class":"P",
    "gn:feature_code":"PPL",
    "gn:name":"Sartasu",
    "gn:population":0,
    "gn:timezone":"Asia/Almaty",
    "iso:country":"KZ",
    "name:rus_x_preferred":[
        "\u0421\u0430\u0440\u0442\u0430\u0441\u0443"
    ],
    "wof:name":"Sartasu",
    "wof:placetype":"locality"
},
  "geometry": {"coordinates":[79.23340999999998,42.75026],"type":"Point"}
}