{
  "type": "Feature",
  "properties": {
    "gn:admin1_code":"12.0",
    "gn:asciiname":"Zhambay",
    "gn:country_code":"KZ",
    "gn:dem":623,
    "gn:feature_class":"P",
    "gn:feature_code":"PPL",
    "gn:name":"Zhambay",
    "gn:population":0,
    "gn:timezone":"Asia/Almaty",
    "iso:country":"KZ",
    "name:und_x_variant":[
        "Dzhambay",
        "Zhambay"
    ],
    "wof:name":"Zhambay",
    "wof:placetype":"locality"
},
  "geometry": {"coordinates":[74.66667,50.05],"type":"Point"}
}