{
  "type": "Feature",
  "properties": {
    "gn:admin1_code":"1.0",
    "gn:asciiname":"Zhanaarka",
    "gn:cc2":"KZ",
    "gn:country_code":"KZ",
    "gn:dem":546,
    "gn:feature_class":"P",
    "gn:feature_code":"PPL",
    "gn:name":"Zhanaarka",
    "gn:population":0,
    "gn:timezone":"Asia/Almaty",
    "iso:country":"KZ",
    "name:und_x_variant":[
        "Zhanaarna",
        "Zhanaarka"
    ],
    "wof:name":"Zhanaarka",
    "wof:placetype":"locality"
},
  "geometry": {"coordinates":[77.02221999999998,43.61333],"type":"Point"}
}