{
  "type": "Feature",
  "properties": {
    "gn:admin1_code":"0.0",
    "gn:asciiname":"Zhetybay",
    "gn:country_code":"KZ",
    "gn:dem":129,
    "gn:feature_class":"P",
    "gn:feature_code":"PPL",
    "gn:name":"Zhetybay",
    "gn:population":0,
    "gn:timezone":"Asia/Almaty",
    "iso:country":"KZ",
    "name:eng_x_preferred":[
        "Zhetybay"
    ],
    "name:rus_x_preferred":[
        "\u0416\u0435\u0442\u0438\u0431\u0430\u0439"
    ],
    "wof:name":"Zhetybay",
    "wof:placetype":"locality"
},
  "geometry": {"coordinates":[64.90968000000001,50.11915],"type":"Point"}
}