{
  "type": "Feature",
  "properties": {
    "gn:admin1_code":"0.0",
    "gn:asciiname":"Karabutak",
    "gn:country_code":"KZ",
    "gn:dem":71,
    "gn:feature_class":"P",
    "gn:feature_code":"PPL",
    "gn:name":"Karabutak",
    "gn:population":0,
    "gn:timezone":"Asia/Oral",
    "iso:country":"KZ",
    "name:und_x_variant":[
        "Karabutakskiy",
        "Karabutak"
    ],
    "wof:name":"Karabutak",
    "wof:placetype":"locality"
},
  "geometry": {"coordinates":[52.71014,50.5948],"type":"Point"}
}