{
  "type": "Feature",
  "properties": {
    "gn:admin1_code":"6.0",
    "gn:asciiname":"Goloshchekin",
    "gn:country_code":"KZ",
    "gn:dem":-28,
    "gn:feature_class":"P",
    "gn:feature_code":"PPL",
    "gn:name":"Goloshch\u00ebkin",
    "gn:population":0,
    "gn:timezone":"Asia/Atyrau",
    "iso:country":"KZ",
    "wof:name":"Goloshchekin",
    "wof:placetype":"locality"
},
  "geometry": {"coordinates":[49.21667,46.51667],"type":"Point"}
}