{
  "type": "Feature",
  "properties": {
    "gn:admin1_code":"0.0",
    "gn:asciiname":"Karpovka",
    "gn:country_code":"KZ",
    "gn:dem":271,
    "gn:feature_class":"P",
    "gn:feature_code":"PPL",
    "gn:name":"Karpovka",
    "gn:population":0,
    "gn:timezone":"Asia/Almaty",
    "iso:country":"KZ",
    "name:eng_x_preferred":[
        "Karpovka"
    ],
    "name:rus_x_preferred":[
        "\u041a\u0430\u0440\u043f\u043e\u0432\u043a\u0430"
    ],
    "name:und_x_variant":[
        "Karpovskoye",
        "Karpovka"
    ],
    "wof:name":"Karpovka",
    "wof:placetype":"locality"
},
  "geometry": {"coordinates":[80.74507,49.98449],"type":"Point"}
}