{
  "type": "Feature",
  "properties": {
    "gn:admin1_code":"10.0",
    "gn:asciiname":"Nefterazvedka",
    "gn:country_code":"KZ",
    "gn:dem":660,
    "gn:feature_class":"P",
    "gn:feature_code":"PPL",
    "gn:name":"Nefterazvedka",
    "gn:population":0,
    "gn:timezone":"Asia/Almaty",
    "iso:country":"KZ",
    "name:rus_x_preferred":[
        "\u041d\u0435\u0444\u0442\u0435\u0440\u0430\u0437\u0432\u0435\u0434\u043a\u0430"
    ],
    "wof:name":"Nefterazvedka",
    "wof:placetype":"locality"
},
  "geometry": {"coordinates":[69.80253,42.21911],"type":"Point"}
}