{
  "type": "Feature",
  "properties": {
    "gn:admin1_code":"3.0",
    "gn:asciiname":"Romanovka",
    "gn:country_code":"KZ",
    "gn:dem":365,
    "gn:feature_class":"P",
    "gn:feature_code":"PPL",
    "gn:name":"Romanovka",
    "gn:population":0,
    "gn:timezone":"Asia/Almaty",
    "iso:country":"KZ",
    "name:und_x_variant":[
        "Romanovskoye",
        "Romanovskiy",
        "Romanovka"
    ],
    "wof:name":"Romanovka",
    "wof:placetype":"locality"
},
  "geometry": {"coordinates":[71.33259,50.82167000000001],"type":"Point"}
}