{
  "type": "Feature",
  "properties": {
    "gn:admin1_code":"4.0",
    "gn:asciiname":"Chernovodsk",
    "gn:country_code":"KZ",
    "gn:dem":310,
    "gn:feature_class":"P",
    "gn:feature_code":"PPL",
    "gn:name":"Chernovodsk",
    "gn:population":0,
    "gn:timezone":"Asia/Aqtobe",
    "iso:country":"KZ",
    "name:ell_x_preferred":[
        "\u03a4\u03c3\u03b5\u03c1\u03bd\u03bf\u03b2\u03cc\u03bd\u03c4\u03c3\u03ba"
    ],
    "name:eng_x_preferred":[
        "Chernovodsk"
    ],
    "name:msa_x_preferred":[
        "Chernovodsk"
    ],
    "name:rus_x_preferred":[
        "\u0427\u0435\u0440\u043d\u043e\u0432\u043e\u0434\u0441\u043a"
    ],
    "name:und_x_variant":[
        "Chernovodskiy",
        "Chernovodsk"
    ],
    "wof:name":"Chernovodsk",
    "wof:placetype":"locality"
},
  "geometry": {"coordinates":[56.79353,50.18023],"type":"Point"}
}