{
  "type": "Feature",
  "properties": {
    "gn:admin1_code":"0.0",
    "gn:asciiname":"Karakuduk",
    "gn:country_code":"KZ",
    "gn:dem":20,
    "gn:feature_class":"P",
    "gn:feature_code":"PPL",
    "gn:name":"Karakuduk",
    "gn:population":0,
    "gn:timezone":"Asia/Oral",
    "iso:country":"KZ",
    "wof:name":"Karakuduk",
    "wof:placetype":"locality"
},
  "geometry": {"coordinates":[52.09724,50.2736],"type":"Point"}
}