{
  "type": "Feature",
  "properties": {
    "gn:admin1_code":"3.0",
    "gn:asciiname":"Staryy Koluton",
    "gn:country_code":"KZ",
    "gn:dem":288,
    "gn:feature_class":"P",
    "gn:feature_code":"PPL",
    "gn:name":"Staryy Koluton",
    "gn:population":0,
    "gn:timezone":"Asia/Almaty",
    "iso:country":"KZ",
    "name:und_x_variant":[
        "Koluton",
        "Starr Koluton",
        "Staryy Koluton"
    ],
    "wof:name":"Staryy Koluton",
    "wof:placetype":"locality"
},
  "geometry": {"coordinates":[69.44859,51.76693],"type":"Point"}
}