{
  "type": "Feature",
  "properties": {
    "gn:admin1_code":"0.0",
    "gn:asciiname":"Dzhumuki",
    "gn:country_code":"KZ",
    "gn:dem":6,
    "gn:feature_class":"P",
    "gn:feature_code":"PPL",
    "gn:name":"Dzhumuki",
    "gn:population":0,
    "gn:timezone":"Asia/Oral",
    "iso:country":"KZ",
    "wof:name":"Dzhumuki",
    "wof:placetype":"locality"
},
  "geometry": {"coordinates":[51.43333,49.95],"type":"Point"}
}