{
  "type": "Feature",
  "properties": {
    "gn:admin1_code":"17.0",
    "gn:asciiname":"Zimovka Kogaly",
    "gn:country_code":"KZ",
    "gn:dem":1086,
    "gn:feature_class":"P",
    "gn:feature_code":"PPL",
    "gn:name":"Zimovka Kogaly",
    "gn:population":0,
    "gn:timezone":"Asia/Almaty",
    "iso:country":"KZ",
    "name:rus_x_preferred":[
        "\u0417\u0438\u043c\u043e\u0432\u043a\u0430 \u041a\u043e\u0433\u0430\u043b\u044b"
    ],
    "name:und_x_variant":[
        "Kogaly"
    ],
    "wof:name":"Zimovka Kogaly",
    "wof:placetype":"locality"
},
  "geometry": {"coordinates":[70.4354,42.8175],"type":"Point"}
}