{
  "type": "Feature",
  "properties": {
    "gn:admin1_code":"16.0",
    "gn:asciiname":"Makashevka",
    "gn:country_code":"KZ",
    "gn:dem":136,
    "gn:feature_class":"P",
    "gn:feature_code":"PPL",
    "gn:name":"Makashevka",
    "gn:population":0,
    "gn:timezone":"Asia/Almaty",
    "iso:country":"KZ",
    "name:eng_x_preferred":[
        "Makashevka"
    ],
    "name:kaz_x_preferred":[
        "\u041c\u0430\u043a\u0430\u0448\u0435\u0432\u043a\u0430"
    ],
    "name:rus_x_preferred":[
        "\u041c\u0430\u043a\u0430\u0448\u0435\u0432\u043a\u0430"
    ],
    "wof:name":"Makashevka",
    "wof:placetype":"locality"
},
  "geometry": {"coordinates":[68.94577,54.05217],"type":"Point"}
}