{
  "type": "Feature",
  "properties": {
    "gn:country":"KZ",
    "gn:fcode":"PPL",
    "gn:pop":16773,
    "iso:country":"KZ",
    "name:eng_x_preferred":[
        "Akkol'"
    ],
    "name:kaz_x_preferred":[
        "Aqk\u00f6l"
    ],
    "name:kaz_x_variant":[
        "\u0410\u049b\u043a\u04e9\u043b"
    ],
    "name:rus_x_preferred":[
        "\u0410\u043a\u043a\u043e\u043b\u044c"
    ],
    "name:unk_x_variant":[
        "Alexeyevka"
    ],
    "qs:name":"Akkol\u2019",
    "qs:photos_9r":0,
    "qs:photos_sr":0,
    "qs:pop_sr":"6",
    "wd:wordcount":286,
    "wof:name":"Akkol\u2019",
    "wof:placetype":"locality",
    "wof:population":16773
},
  "geometry": {"coordinates":[69.59997,53.29617],"type":"Point"}
}