{
  "type": "Feature",
  "properties": {
    "gn:country":"KZ",
    "gn:fcode":"PPL",
    "gn:population":16773,
    "iso:country":"KZ",
    "name:bel_x_preferred":[
        "\u0410\u043a\u043e\u043b\u044c"
    ],
    "name:ceb_x_preferred":[
        "Aqk\u00f6l"
    ],
    "name:ces_x_preferred":[
        "Akkol"
    ],
    "name:deu_x_preferred":[
        "Aqk\u00f6l"
    ],
    "name:eng_x_preferred":[
        "Akkol'"
    ],
    "name:fas_x_preferred":[
        "\u0622\u0642\u200c\u06a9\u0648\u0644"
    ],
    "name:fra_x_preferred":[
        "Akkol"
    ],
    "name:hsb_x_preferred":[
        "Akkol"
    ],
    "name:kaz_x_preferred":[
        "Aqk\u00f6l"
    ],
    "name:kaz_x_variant":[
        "\u0410\u049b\u043a\u04e9\u043b"
    ],
    "name:lit_x_preferred":[
        "Akolis"
    ],
    "name:pol_x_preferred":[
        "Akk\u00f6l"
    ],
    "name:rus_x_preferred":[
        "\u0410\u043a\u043a\u043e\u043b\u044c"
    ],
    "name:sco_x_preferred":[
        "Akkol"
    ],
    "name:spa_x_preferred":[
        "Akkol"
    ],
    "name:swe_x_preferred":[
        "Aleksejevka"
    ],
    "name:tat_x_preferred":[
        "\u0410\u043a\u043a\u04af\u043b"
    ],
    "name:tur_x_preferred":[
        "Akk\u00f6l"
    ],
    "name:ukr_x_preferred":[
        "\u0410\u043a\u043a\u043e\u043b\u044c"
    ],
    "name:und_x_variant":[
        "Alexeyevka"
    ],
    "name:uzb_x_preferred":[
        "Oqko\u02bbl"
    ],
    "name:vie_x_preferred":[
        "Akkol"
    ],
    "name:zho_x_preferred":[
        "\u963f\u79d1\u5c14"
    ],
    "qs:name":"Akkol\u2019",
    "qs:photos_9r":0,
    "qs:photos_sr":0,
    "qs:pop_sr":"6",
    "wd:wordcount":286,
    "wof:name":"Akkol\u2019",
    "wof:placetype":"locality",
    "wof:population":16773
},
  "geometry": {"coordinates":[69.59997,53.29617],"type":"Point"}
}