{
  "type": "Feature",
  "properties": {
    "gn:admin1_code":"15.0",
    "gn:asciiname":"Novovoskresenovka",
    "gn:country_code":"KZ",
    "gn:dem":724,
    "gn:feature_class":"P",
    "gn:feature_code":"PPL",
    "gn:name":"Novovoskresenovka",
    "gn:population":0,
    "gn:timezone":"Asia/Almaty",
    "iso:country":"KZ",
    "name:che_x_preferred":[
        "\u041d\u043e\u0432\u043e\u0432\u043e\u0441\u043a\u0440\u0435\u0441\u0435\u043d\u043e\u0432\u043a\u0430"
    ],
    "name:rus_x_preferred":[
        "\u041d\u043e\u0432\u043e\u0432\u043e\u0441\u043a\u0440\u0435\u0441\u0435\u043d\u043e\u0432\u043a\u0430"
    ],
    "wof:name":"Novovoskresenovka",
    "wof:placetype":"locality"
},
  "geometry": {"coordinates":[73.50139,42.8275],"type":"Point"}
}