{
  "type": "Feature",
  "properties": {
    "gn:admin1_code":"12.0",
    "gn:asciiname":"Rodnichki",
    "gn:country_code":"KZ",
    "gn:dem":552,
    "gn:feature_class":"P",
    "gn:feature_code":"PPL",
    "gn:name":"Rodnichki",
    "gn:population":0,
    "gn:timezone":"Asia/Almaty",
    "iso:country":"KZ",
    "name:kaz_x_preferred":[
        "Rodn\u012bchk\u012b"
    ],
    "name:kaz_x_variant":[
        "\u0420\u043e\u0434\u043d\u0438\u0447\u043a\u0438"
    ],
    "wof:name":"Rodnichki",
    "wof:placetype":"locality"
},
  "geometry": {"coordinates":[72.36748,50.19679],"type":"Point"}
}