{
  "type": "Feature",
  "properties": {
    "gn:admin1_code":"15.0",
    "gn:asciiname":"Bazar",
    "gn:country_code":"KZ",
    "gn:dem":517,
    "gn:feature_class":"P",
    "gn:feature_code":"PPL",
    "gn:name":"Bazar",
    "gn:population":0,
    "gn:timezone":"Asia/Almaty",
    "iso:country":"KZ",
    "name:aze_x_preferred":[
        "Bazar"
    ],
    "name:cat_x_preferred":[
        "Bazar"
    ],
    "name:ceb_x_preferred":[
        "Bazar"
    ],
    "name:eus_x_preferred":[
        "Bazar"
    ],
    "name:fra_x_preferred":[
        "Bazar"
    ],
    "name:glg_x_preferred":[
        "Bazar"
    ],
    "name:kat_x_preferred":[
        "\u10d1\u10d0\u10d6\u10d0\u10e0\u10d8"
    ],
    "name:kaz_x_preferred":[
        "Karl Marks"
    ],
    "name:kaz_x_variant":[
        "\u041a\u0430\u0440\u043b \u041c\u0430\u0440\u043a\u0441",
        "K\u00f6kt\u00fcbek",
        "\u041a\u04e9\u043a\u0442\u04af\u0431\u0435\u043a"
    ],
    "name:nld_x_preferred":[
        "Bazar"
    ],
    "name:nor_x_preferred":[
        "Bazar"
    ],
    "name:ron_x_preferred":[
        "Bazar"
    ],
    "name:rus_x_preferred":[
        "\u0411\u0430\u0437\u0430\u0440"
    ],
    "name:rus_x_variant":[
        "\u041a\u043e\u043a\u0442\u0443\u0431\u0435\u043a"
    ],
    "name:slv_x_preferred":[
        "Bazar"
    ],
    "name:spa_x_preferred":[
        "Bazar"
    ],
    "name:swe_x_preferred":[
        "Bazar"
    ],
    "name:und_x_variant":[
        "Koktubek"
    ],
    "wof:name":"Bazar",
    "wof:placetype":"locality"
},
  "geometry": {"coordinates":[82.71899000000001,47.85645],"type":"Point"}
}