{
  "type": "Feature",
  "properties": {
    "gn:admin1_code":"16.0",
    "gn:asciiname":"Rebrovka",
    "gn:country_code":"KZ",
    "gn:dem":130,
    "gn:feature_class":"P",
    "gn:feature_code":"PPL",
    "gn:name":"Rebrovka",
    "gn:population":0,
    "gn:timezone":"Asia/Almaty",
    "iso:country":"KZ",
    "name:rus_x_preferred":[
        "\u0420\u0435\u0431\u0440\u043e\u0432\u043a\u0430"
    ],
    "wof:name":"Rebrovka",
    "wof:placetype":"locality"
},
  "geometry": {"coordinates":[70.01994999999999,55.03096],"type":"Point"}
}