{
  "type": "Feature",
  "properties": {
    "gn:admin1_code":"15.0",
    "gn:asciiname":"Volchanka",
    "gn:country_code":"KZ",
    "gn:dem":330,
    "gn:feature_class":"P",
    "gn:feature_code":"PPL",
    "gn:name":"Volchanka",
    "gn:population":0,
    "gn:timezone":"Asia/Almaty",
    "iso:country":"KZ",
    "name:eng_x_preferred":[
        "Volchanka"
    ],
    "name:kaz_x_preferred":[
        "\u0412\u043e\u043b\u0447\u0430\u043d\u043a\u0430"
    ],
    "name:rus_x_preferred":[
        "\u0412\u043e\u043b\u0447\u0430\u043d\u043a\u0430"
    ],
    "wof:name":"Volchanka",
    "wof:placetype":"locality"
},
  "geometry": {"coordinates":[82.14264,50.5654],"type":"Point"}
}