{
  "type": "Feature",
  "properties": {
    "gn:admin1_code":"15.0",
    "gn:asciiname":"Troynitskoye",
    "gn:country_code":"KZ",
    "gn:dem":526,
    "gn:feature_class":"P",
    "gn:feature_code":"PPL",
    "gn:name":"Troynitskoye",
    "gn:population":0,
    "gn:timezone":"Asia/Almaty",
    "iso:country":"KZ",
    "name:eng_x_preferred":[
        "Troyn\u012btskoe"
    ],
    "name:kaz_x_preferred":[
        "\u0422\u0440\u043e\u0439\u043d\u0438\u0446\u043a\u043e\u0435"
    ],
    "name:rus_x_preferred":[
        "\u0422\u0440\u043e\u0439\u043d\u0438\u0446\u043a\u043e\u0435"
    ],
    "name:und_x_variant":[
        "Troinitskoye",
        "Troynitskoye",
        "Troyn\u012btskoe"
    ],
    "wof:name":"Troynitskoye",
    "wof:placetype":"locality"
},
  "geometry": {"coordinates":[81.75482,49.93451],"type":"Point"}
}