{
  "type": "Feature",
  "properties": {
    "gn:admin1_code":"12.0",
    "gn:asciiname":"Malaykuduk",
    "gn:country_code":"KZ",
    "gn:dem":378,
    "gn:feature_class":"P",
    "gn:feature_code":"PPL",
    "gn:name":"Malaykuduk",
    "gn:population":0,
    "gn:timezone":"Asia/Almaty",
    "iso:country":"KZ",
    "wof:name":"Malaykuduk",
    "wof:placetype":"locality"
},
  "geometry": {"coordinates":[70.82947,50.07304],"type":"Point"}
}