{
  "type": "Feature",
  "properties": {
    "gn:admin1_code":"0.0",
    "gn:asciiname":"Kubok-Mola",
    "gn:country_code":"KZ",
    "gn:dem":43,
    "gn:feature_class":"P",
    "gn:feature_code":"PPL",
    "gn:name":"Kubok-Mola",
    "gn:population":0,
    "gn:timezone":"Asia/Oral",
    "iso:country":"KZ",
    "wof:name":"Kubok-Mola",
    "wof:placetype":"locality"
},
  "geometry": {"coordinates":[52.85,50.31667],"type":"Point"}
}