{
  "type": "Feature",
  "properties": {
    "gn:admin1_code":"3.0",
    "gn:asciiname":"Mendysh",
    "gn:country_code":"KZ",
    "gn:dem":271,
    "gn:feature_class":"P",
    "gn:feature_code":"PPL",
    "gn:name":"Mendysh",
    "gn:population":0,
    "gn:timezone":"Asia/Almaty",
    "iso:country":"KZ",
    "name:und_x_variant":[
        "Mendesh"
    ],
    "wof:name":"Mendysh",
    "wof:placetype":"locality"
},
  "geometry": {"coordinates":[67.72779,50.97928],"type":"Point"}
}