{
  "type": "Feature",
  "properties": {
    "gn:admin1_code":"4.0",
    "gn:asciiname":"Tabotayskiy",
    "gn:country_code":"KZ",
    "gn:dem":204,
    "gn:feature_class":"P",
    "gn:feature_code":"PPL",
    "gn:name":"Tabotayskiy",
    "gn:population":0,
    "gn:timezone":"Asia/Aqtobe",
    "iso:country":"KZ",
    "wof:name":"Tabotayskiy",
    "wof:placetype":"locality"
},
  "geometry": {"coordinates":[56.45,49.88333],"type":"Point"}
}