{
  "type": "Feature",
  "properties": {
    "gn:admin1_code":"1.0",
    "gn:asciiname":"Dubun",
    "gn:country_code":"KZ",
    "gn:dem":578,
    "gn:feature_class":"P",
    "gn:feature_code":"PPL",
    "gn:name":"Dubun",
    "gn:population":0,
    "gn:timezone":"Asia/Almaty",
    "iso:country":"KZ",
    "name:kaz_x_preferred":[
        "Dobyn"
    ],
    "name:kaz_x_variant":[
        "\u0414\u043e\u0431\u044b\u043d"
    ],
    "name:rus_x_preferred":[
        "\u0414\u0443\u0431\u0443\u043d"
    ],
    "name:und_x_variant":[
        "Dobun",
        "Dubun",
        "Dubunskaya"
    ],
    "wof:name":"Dubun",
    "wof:placetype":"locality"
},
  "geometry": {"coordinates":[80.07129,43.69366],"type":"Point"}
}