{
  "type": "Feature",
  "properties": {
    "gn:admin1_code":"16.0",
    "gn:asciiname":"Sarman",
    "gn:country_code":"KZ",
    "gn:dem":147,
    "gn:feature_class":"P",
    "gn:feature_code":"PPL",
    "gn:name":"Sarman",
    "gn:population":0,
    "gn:timezone":"Asia/Almaty",
    "iso:country":"KZ",
    "name:eng_x_preferred":[
        "Sarman"
    ],
    "name:kaz_x_preferred":[
        "Saryman"
    ],
    "name:kaz_x_variant":[
        "\u0421\u0430\u0440\u044b\u043c\u0430\u043d"
    ],
    "name:rus_x_preferred":[
        "\u0421\u0430\u0440\u044b\u043c\u0430\u043d"
    ],
    "name:rus_x_variant":[
        "\u0421\u0430\u0440\u043c\u0430\u043d"
    ],
    "wof:name":"Sarman",
    "wof:placetype":"locality"
},
  "geometry": {"coordinates":[67.82106999999999,54.30985],"type":"Point"}
}