{
  "type": "Feature",
  "properties": {
    "gn:admin1_code":"15.0",
    "gn:asciiname":"Bozanbay",
    "gn:country_code":"KZ",
    "gn:dem":619,
    "gn:feature_class":"P",
    "gn:feature_code":"PPL",
    "gn:name":"Bozanbay",
    "gn:population":0,
    "gn:timezone":"Asia/Almaty",
    "iso:country":"KZ",
    "name:eng_x_preferred":[
        "Bozanbay"
    ],
    "name:rus_x_preferred":[
        "\u041d\u0438\u043a\u0438\u0442\u0438\u043d\u043a\u0430"
    ],
    "name:und_x_variant":[
        "Bozanbai",
        "N\u012bk\u012bt\u012bnka",
        "Bozanbay"
    ],
    "wof:name":"Bozanbay",
    "wof:placetype":"locality"
},
  "geometry": {"coordinates":[82.40963000000001,49.5326],"type":"Point"}
}