{
  "type": "Feature",
  "properties": {
    "gn:admin1_code":"13.0",
    "gn:asciiname":"Volkovka",
    "gn:country_code":"KZ",
    "gn:dem":190,
    "gn:feature_class":"P",
    "gn:feature_code":"PPL",
    "gn:name":"Volkovka",
    "gn:population":0,
    "gn:timezone":"Asia/Qyzylorda",
    "iso:country":"KZ",
    "name:rus_x_preferred":[
        "\u0412\u043e\u043b\u043a\u043e\u0432\u043a\u0430"
    ],
    "wof:name":"Volkovka",
    "wof:placetype":"locality"
},
  "geometry": {"coordinates":[62.65638000000001,53.86391999999999],"type":"Point"}
}