{
  "type": "Feature",
  "properties": {
    "gn:admin1_code":"12.0",
    "gn:asciiname":"Yenbek",
    "gn:country_code":"KZ",
    "gn:dem":964,
    "gn:feature_class":"P",
    "gn:feature_code":"PPL",
    "gn:name":"Yenbek",
    "gn:population":0,
    "gn:timezone":"Asia/Almaty",
    "iso:country":"KZ",
    "name:kaz_x_preferred":[
        "Mystybulaq"
    ],
    "name:kaz_x_variant":[
        "\u041c\u044b\u0441\u0442\u044b\u0431\u04b1\u043b\u0430\u049b"
    ],
    "name:rus_x_preferred":[
        "\u0415\u043d\u0431\u0435\u043a"
    ],
    "wof:name":"Yenbek",
    "wof:placetype":"locality"
},
  "geometry": {"coordinates":[75.15106999999998,48.78158],"type":"Point"}
}