{
  "type": "Feature",
  "properties": {
    "gn:admin1_code":"16.0",
    "gn:asciiname":"Intymak",
    "gn:country_code":"KZ",
    "gn:dem":160,
    "gn:feature_class":"P",
    "gn:feature_code":"PPL",
    "gn:name":"Intymak",
    "gn:population":0,
    "gn:timezone":"Asia/Almaty",
    "iso:country":"KZ",
    "name:msa_x_preferred":[
        "Intymak"
    ],
    "name:rus_x_preferred":[
        "\u0418\u043d\u0442\u044b\u043c\u0430\u043a"
    ],
    "wof:name":"Intymak",
    "wof:placetype":"locality"
},
  "geometry": {"coordinates":[67.0808,53.94138],"type":"Point"}
}