{
  "type": "Feature",
  "properties": {
    "gn:admin1_code":"15.0",
    "gn:asciiname":"Karamayli",
    "gn:country_code":"KZ",
    "gn:dem":466,
    "gn:feature_class":"P",
    "gn:feature_code":"PPL",
    "gn:name":"Karamayli",
    "gn:population":0,
    "gn:timezone":"Asia/Almaty",
    "iso:country":"KZ",
    "wof:name":"Karamayli",
    "wof:placetype":"locality"
},
  "geometry": {"coordinates":[81.54451999999998,47.1035],"type":"Point"}
}