{
  "type": "Feature",
  "properties": {
    "gn:admin1_code":"0.0",
    "gn:asciiname":"Chalokozakov",
    "gn:country_code":"KZ",
    "gn:dem":401,
    "gn:feature_class":"P",
    "gn:feature_code":"PPL",
    "gn:name":"Chalokozakov",
    "gn:population":0,
    "gn:timezone":"Asia/Almaty",
    "iso:country":"KZ",
    "wof:name":"Chalokozakov",
    "wof:placetype":"locality"
},
  "geometry": {"coordinates":[83.26666999999998,48.61667],"type":"Point"}
}