{
  "type": "Feature",
  "properties": {
    "gn:admin1_code":"7.0",
    "gn:asciiname":"Kumekshi",
    "gn:country_code":"KZ",
    "gn:dem":6,
    "gn:feature_class":"P",
    "gn:feature_code":"PPL",
    "gn:name":"Kumekshi",
    "gn:population":0,
    "gn:timezone":"Asia/Oral",
    "iso:country":"KZ",
    "name:eng_x_preferred":[
        "Kumekshi"
    ],
    "name:rus_x_preferred":[
        "\u041a\u0443\u043c\u0435\u043a\u0448\u0438"
    ],
    "name:und_x_variant":[
        "Komekshi",
        "Kumekshi"
    ],
    "wof:name":"Kumekshi",
    "wof:placetype":"locality"
},
  "geometry": {"coordinates":[49.42841,49.56222],"type":"Point"}
}