{
  "type": "Feature",
  "properties": {
    "gn:admin1_code":"15.0",
    "gn:asciiname":"Dunenbay",
    "gn:country_code":"KZ",
    "gn:dem":785,
    "gn:feature_class":"P",
    "gn:feature_code":"PPL",
    "gn:name":"D\u00fcnenbay",
    "gn:population":0,
    "gn:timezone":"Asia/Almaty",
    "iso:country":"KZ",
    "name:eng_x_preferred":[
        "D\u00f6nenbay"
    ],
    "name:kaz_x_preferred":[
        "D\u00fcnenbay"
    ],
    "name:rus_x_preferred":[
        "\u0414\u0443\u043d\u0435\u043d\u0431\u0430\u0439"
    ],
    "name:und_x_variant":[
        "Akshatau",
        "Donenbay",
        "Dunanbay",
        "D\u00f6nenbay"
    ],
    "wof:name":"Dunenbay",
    "wof:placetype":"locality"
},
  "geometry": {"coordinates":[80.03364000000001,48.14794000000001],"type":"Point"}
}