{
  "type": "Feature",
  "properties": {
    "gn:admin1_code":"17.0",
    "gn:asciiname":"Imeni Kalinina",
    "gn:country_code":"KZ",
    "gn:dem":324,
    "gn:feature_class":"P",
    "gn:feature_code":"PPL",
    "gn:name":"Imeni Kalinina",
    "gn:population":0,
    "gn:timezone":"Asia/Almaty",
    "iso:country":"KZ",
    "name:kaz_x_preferred":[
        "Zhayylma"
    ],
    "name:kaz_x_variant":[
        "\u0416\u0430\u0439\u044b\u043b\u043c\u0430"
    ],
    "name:rus_x_preferred":[
        "\u0418\u043c\u0435\u043d\u0438 \u041a\u0430\u043b\u0438\u043d\u0438\u043d\u0430"
    ],
    "wof:name":"Imeni Kalinina",
    "wof:placetype":"locality"
},
  "geometry": {"coordinates":[69.78534000000001,43.76018],"type":"Point"}
}