{
  "type": "Feature",
  "properties": {
    "gn:admin1_code":"11.0",
    "gn:asciiname":"Bozalang",
    "gn:country_code":"KZ",
    "gn:dem":155,
    "gn:feature_class":"P",
    "gn:feature_code":"PPL",
    "gn:name":"Bozalang",
    "gn:population":0,
    "gn:timezone":"Asia/Almaty",
    "iso:country":"KZ",
    "name:kaz_x_preferred":[
        "Bozalang"
    ],
    "name:kaz_x_variant":[
        "\u0411\u043e\u0437\u0430\u043b\u0430\u04a3"
    ],
    "name:rus_x_preferred":[
        "\u0411\u043e\u0437\u0430\u043b\u0430\u043d"
    ],
    "name:und_x_variant":[
        "Bozalan"
    ],
    "wof:name":"Bozalang",
    "wof:placetype":"locality"
},
  "geometry": {"coordinates":[78.94014,52.04857],"type":"Point"}
}