{
  "type": "Feature",
  "properties": {
    "gn:admin1_code":"14.0",
    "gn:asciiname":"Kaukey",
    "gn:country_code":"KZ",
    "gn:dem":57,
    "gn:feature_class":"P",
    "gn:feature_code":"PPL",
    "gn:name":"Ka\u016bkey",
    "gn:population":0,
    "gn:timezone":"Asia/Qyzylorda",
    "iso:country":"KZ",
    "wof:name":"Kaukey",
    "wof:placetype":"locality"
},
  "geometry": {"coordinates":[61.75333000000001,45.275],"type":"Point"}
}