{
  "type": "Feature",
  "properties": {
    "gn:admin1_code":"10.0",
    "gn:asciiname":"Donyztau",
    "gn:country_code":"KZ",
    "gn:dem":1004,
    "gn:feature_class":"P",
    "gn:feature_code":"PPL",
    "gn:name":"Donyztau",
    "gn:population":0,
    "gn:timezone":"Asia/Almaty",
    "iso:country":"KZ",
    "name:rus_x_preferred":[
        "\u0414\u043e\u043d\u044b\u0437\u0442\u0430\u0443"
    ],
    "wof:name":"Donyztau",
    "wof:placetype":"locality"
},
  "geometry": {"coordinates":[69.96935999999999,42.119],"type":"Point"}
}