{
  "type": "Feature",
  "properties": {
    "gn:admin1_code":"10.0",
    "gn:asciiname":"Ushkain",
    "gn:country_code":"KZ",
    "gn:dem":182,
    "gn:feature_class":"P",
    "gn:feature_code":"PPL",
    "gn:name":"Ushkain",
    "gn:population":0,
    "gn:timezone":"Asia/Almaty",
    "iso:country":"KZ",
    "name:und_x_variant":[
        "Ushkaik",
        "Ushkain"
    ],
    "wof:name":"Ushkain",
    "wof:placetype":"locality"
},
  "geometry": {"coordinates":[67.90000000000001,43.16667],"type":"Point"}
}