{
  "type": "Feature",
  "properties": {
    "gn:admin1_code":"3.0",
    "gn:asciiname":"Enbekbirlik",
    "gn:country_code":"KZ",
    "gn:dem":394,
    "gn:feature_class":"P",
    "gn:feature_code":"PPL",
    "gn:name":"Enbekbirlik",
    "gn:population":0,
    "gn:timezone":"Asia/Almaty",
    "iso:country":"KZ",
    "name:rus_x_preferred":[
        "\u042d\u043d\u0431\u0435\u043a\u0431\u0438\u0440\u043b\u0438\u043a"
    ],
    "wof:name":"Enbekbirlik",
    "wof:placetype":"locality"
},
  "geometry": {"coordinates":[69.35434000000001,53.05428000000001],"type":"Point"}
}