{
  "type": "Feature",
  "properties": {
    "gn:admin1_code":"1.0",
    "gn:asciiname":"Kirovo",
    "gn:country_code":"KZ",
    "gn:dem":815,
    "gn:feature_class":"P",
    "gn:feature_code":"PPL",
    "gn:name":"Kirovo",
    "gn:population":0,
    "gn:timezone":"Asia/Almaty",
    "iso:country":"KZ",
    "name:und_x_variant":[
        "Cholak-Kargal\u00f6",
        "Cholak-Kargaly",
        "Kirovo"
    ],
    "wof:name":"Kirovo",
    "wof:placetype":"locality"
},
  "geometry": {"coordinates":[76.36049,43.25291],"type":"Point"}
}