{
  "type": "Feature",
  "properties": {
    "gn:admin1_code":"14.0",
    "gn:asciiname":"Krasnaya Zvezda",
    "gn:country_code":"KZ",
    "gn:dem":157,
    "gn:feature_class":"P",
    "gn:feature_code":"PPL",
    "gn:name":"Krasnaya Zvezda",
    "gn:population":0,
    "gn:timezone":"Asia/Qyzylorda",
    "iso:country":"KZ",
    "name:kaz_x_preferred":[
        "Krasnaya Zvezda"
    ],
    "wof:name":"Krasnaya Zvezda",
    "wof:placetype":"locality"
},
  "geometry": {"coordinates":[67.11667,44.08333],"type":"Point"}
}