{
  "type": "Feature",
  "properties": {
    "gn:admin1_code":"4.0",
    "gn:asciiname":"Kemershi",
    "gn:country_code":"KZ",
    "gn:dem":124,
    "gn:feature_class":"P",
    "gn:feature_code":"PPL",
    "gn:name":"Kemershi",
    "gn:population":0,
    "gn:timezone":"Asia/Aqtobe",
    "iso:country":"KZ",
    "name:eng_x_preferred":[
        "Kemersh\u012b"
    ],
    "name:kaz_x_preferred":[
        "Kemersh\u012b"
    ],
    "name:rus_x_preferred":[
        "\u041a\u0435\u043c\u0435\u0440\u0448\u0438"
    ],
    "wof:name":"Kemershi",
    "wof:placetype":"locality"
},
  "geometry": {"coordinates":[56.76578000000001,48.08076],"type":"Point"}
}