{
  "type": "Feature",
  "properties": {
    "gn:admin1_code":"4.0",
    "gn:asciiname":"Amangeldi",
    "gn:country_code":"KZ",
    "gn:dem":180,
    "gn:feature_class":"P",
    "gn:feature_code":"PPL",
    "gn:name":"Amangeldi",
    "gn:population":0,
    "gn:timezone":"Asia/Aqtobe",
    "iso:country":"KZ",
    "name:eng_x_preferred":[
        "Amangeldi"
    ],
    "name:rus_x_preferred":[
        "\u0410\u043c\u0430\u043d\u0433\u0435\u043b\u044c\u0434\u044b"
    ],
    "name:und_x_variant":[
        "Amangel\u2019dy",
        "Amangeldi"
    ],
    "wof:name":"Amangeldi",
    "wof:placetype":"locality"
},
  "geometry": {"coordinates":[62.28563000000001,50.53405],"type":"Point"}
}