{
  "type": "Feature",
  "properties": {
    "gn:admin1_code":"4.0",
    "gn:asciiname":"Akzhar",
    "gn:country_code":"KZ",
    "gn:dem":258,
    "gn:feature_class":"P",
    "gn:feature_code":"PPL",
    "gn:name":"Akzhar",
    "gn:population":0,
    "gn:timezone":"Asia/Aqtobe",
    "iso:country":"KZ",
    "name:eng_x_preferred":[
        "Akzhar"
    ],
    "name:rus_x_preferred":[
        "\u0410\u043a\u0436\u0430\u0440"
    ],
    "wof:name":"Akzhar",
    "wof:placetype":"locality"
},
  "geometry": {"coordinates":[56.86666999999999,49.18333],"type":"Point"}
}