{
  "type": "Feature",
  "properties": {
    "gn:admin1_code":"15.0",
    "gn:asciiname":"Tepkashi",
    "gn:country_code":"KZ",
    "gn:dem":210,
    "gn:feature_class":"P",
    "gn:feature_code":"PPL",
    "gn:name":"Tepkashi",
    "gn:population":0,
    "gn:timezone":"Asia/Almaty",
    "iso:country":"KZ",
    "name:eng_x_preferred":[
        "Tepkashi"
    ],
    "name:kaz_x_preferred":[
        "Tepkash\u012b"
    ],
    "name:kaz_x_variant":[
        "\u0422\u0435\u043f\u043a\u0430\u0448\u0438"
    ],
    "name:rus_x_preferred":[
        "\u0422\u0435\u043f\u043a\u0430\u0448\u0438"
    ],
    "name:und_x_variant":[
        "Tipkashi",
        "Tepkashi"
    ],
    "wof:name":"Tepkashi",
    "wof:placetype":"locality"
},
  "geometry": {"coordinates":[80.72948000000002,50.39177],"type":"Point"}
}