{
  "type": "Feature",
  "properties": {
    "gn:admin1_code":"1.0",
    "gn:asciiname":"Mynbayevo",
    "gn:country_code":"KZ",
    "gn:dem":796,
    "gn:feature_class":"P",
    "gn:feature_code":"PPL",
    "gn:name":"Mynbayevo",
    "gn:population":0,
    "gn:timezone":"Asia/Almaty",
    "iso:country":"KZ",
    "name:eng_x_preferred":[
        "Mynbayevo"
    ],
    "name:rus_x_preferred":[
        "\u041c\u044b\u043d\u0431\u0430\u0435\u0432\u043e"
    ],
    "wof:name":"Mynbayevo",
    "wof:placetype":"locality"
},
  "geometry": {"coordinates":[76.44781,43.29073],"type":"Point"}
}