{
  "type": "Feature",
  "properties": {
    "gn:admin1_code":"16.0",
    "gn:asciiname":"Kustovoye",
    "gn:country_code":"KZ",
    "gn:dem":98,
    "gn:feature_class":"P",
    "gn:feature_code":"PPL",
    "gn:name":"Kustovoye",
    "gn:population":0,
    "gn:timezone":"Asia/Almaty",
    "iso:country":"KZ",
    "name:eng_x_preferred":[
        "Kustovoye"
    ],
    "name:kaz_x_preferred":[
        "K\u016bstovoe"
    ],
    "name:kaz_x_variant":[
        "\u041a\u0443\u0441\u0442\u043e\u0432\u043e\u0435"
    ],
    "name:rus_x_preferred":[
        "\u041a\u0443\u0441\u0442\u043e\u0432\u043e\u0435"
    ],
    "wof:name":"Kustovoye",
    "wof:placetype":"locality"
},
  "geometry": {"coordinates":[69.38961999999999,55.19844000000001],"type":"Point"}
}