{
  "type": "Feature",
  "properties": {
    "gn:admin1_code":"15.0",
    "gn:asciiname":"Zhelomanovka",
    "gn:country_code":"KZ",
    "gn:dem":207,
    "gn:feature_class":"P",
    "gn:feature_code":"PPL",
    "gn:name":"Zhelomanovka",
    "gn:population":0,
    "gn:timezone":"Asia/Almaty",
    "iso:country":"KZ",
    "name:rus_x_preferred":[
        "\u0416\u0435\u043b\u043e\u043c\u0430\u043d\u043e\u0432\u043a\u0430"
    ],
    "wof:name":"Zhelomanovka",
    "wof:placetype":"locality"
},
  "geometry": {"coordinates":[80.2561,50.37107],"type":"Point"}
}