{
  "type": "Feature",
  "properties": {
    "gn:admin1_code":"1.0",
    "gn:asciiname":"Uzunagach",
    "gn:country_code":"KZ",
    "gn:dem":822,
    "gn:feature_class":"P",
    "gn:feature_code":"PPL",
    "gn:name":"Uzunagach",
    "gn:population":0,
    "gn:timezone":"Asia/Almaty",
    "iso:country":"KZ",
    "name:kaz_x_preferred":[
        "Uzynaghash"
    ],
    "wof:name":"Uzunagach",
    "wof:placetype":"locality"
},
  "geometry": {"coordinates":[76.31506999999998,43.22336],"type":"Point"}
}