{
  "type": "Feature",
  "properties": {
    "gn:admin1_code":"10.0",
    "gn:asciiname":"Tashkulak",
    "gn:country_code":"KZ",
    "gn:dem":497,
    "gn:feature_class":"P",
    "gn:feature_code":"PPL",
    "gn:name":"Tashkulak",
    "gn:population":0,
    "gn:timezone":"Asia/Qyzylorda",
    "iso:country":"KZ",
    "name:rus_x_preferred":[
        "\u0422\u0430\u0448\u043a\u0443\u043b\u0430\u043a"
    ],
    "wof:name":"Tashkulak",
    "wof:placetype":"locality"
},
  "geometry": {"coordinates":[69.30958000000001,41.45299],"type":"Point"}
}