{
  "type": "Feature",
  "properties": {
    "gn:admin1_code":"13.0",
    "gn:asciiname":"Raskol'",
    "gn:country_code":"KZ",
    "gn:dem":177,
    "gn:feature_class":"P",
    "gn:feature_code":"PPL",
    "gn:name":"Raskol\u2019",
    "gn:population":0,
    "gn:timezone":"Asia/Qyzylorda",
    "iso:country":"KZ",
    "name:rus_x_preferred":[
        "Raskol\u2019"
    ],
    "name:rus_x_variant":[
        "\u0420\u0430\u0441\u043a\u043e\u043b\u044c"
    ],
    "wof:name":"Raskol'",
    "wof:placetype":"locality"
},
  "geometry": {"coordinates":[64.06801,53.79695],"type":"Point"}
}