{
  "type": "Feature",
  "properties": {
    "gn:admin1_code":"12.0",
    "gn:asciiname":"Kyzylshin",
    "gn:country_code":"KZ",
    "gn:dem":470,
    "gn:feature_class":"P",
    "gn:feature_code":"PPL",
    "gn:name":"Kyzylshin",
    "gn:population":0,
    "gn:timezone":"Asia/Almaty",
    "iso:country":"KZ",
    "wof:name":"Kyzylshin",
    "wof:placetype":"locality"
},
  "geometry": {"coordinates":[67.36667,48.33333],"type":"Point"}
}