{
  "type": "Feature",
  "properties": {
    "gn:admin1_code":"0.0",
    "gn:asciiname":"Akshiganak",
    "gn:country_code":"KZ",
    "gn:dem":79,
    "gn:feature_class":"P",
    "gn:feature_code":"PPL",
    "gn:name":"Akshiganak",
    "gn:population":0,
    "gn:timezone":"Asia/Almaty",
    "iso:country":"KZ",
    "wof:name":"Akshiganak",
    "wof:placetype":"locality"
},
  "geometry": {"coordinates":[62.73333,49.26667],"type":"Point"}
}