{
  "type": "Feature",
  "properties": {
    "gn:admin1_code":"6.0",
    "gn:asciiname":"Talyau",
    "gn:country_code":"KZ",
    "gn:dem":-11,
    "gn:feature_class":"P",
    "gn:feature_code":"PPL",
    "gn:name":"Talyau",
    "gn:population":0,
    "gn:timezone":"Asia/Atyrau",
    "iso:country":"KZ",
    "wof:name":"Talyau",
    "wof:placetype":"locality"
},
  "geometry": {"coordinates":[51.78333,48.31667],"type":"Point"}
}