{
  "type": "Feature",
  "properties": {
    "gn:admin1_code":"15.0",
    "gn:asciiname":"Suyqbulaq",
    "gn:country_code":"KZ",
    "gn:dem":296,
    "gn:feature_class":"P",
    "gn:feature_code":"PPL",
    "gn:name":"S\u016byqbulaq",
    "gn:population":0,
    "gn:timezone":"Asia/Almaty",
    "iso:country":"KZ",
    "name:eng_x_preferred":[
        "S\u016byqbulaq"
    ],
    "name:rus_x_preferred":[
        "\u0421\u0443\u044b\u043a\u0431\u0443\u043b\u0430\u043a"
    ],
    "name:und_x_variant":[
        "Suykbulak",
        "S\u016byqbulaq"
    ],
    "wof:name":"Suyqbulaq",
    "wof:placetype":"locality"
},
  "geometry": {"coordinates":[80.82279,49.79555],"type":"Point"}
}