{
  "type": "Feature",
  "properties": {
    "gn:admin1_code":"10.0",
    "gn:asciiname":"Vtoroy Tyul'kubas",
    "gn:country_code":"KZ",
    "gn:dem":771,
    "gn:feature_class":"P",
    "gn:feature_code":"PPL",
    "gn:name":"Vtoroy Tyul\u2019kubas",
    "gn:population":0,
    "gn:timezone":"Asia/Almaty",
    "iso:country":"KZ",
    "name:rus_x_preferred":[
        "Vtoroy Tyul\u2019kubas"
    ],
    "name:rus_x_variant":[
        "\u0412\u0442\u043e\u0440\u043e\u0439 \u0422\u044e\u043b\u044c\u043a\u0443\u0431\u0430\u0441"
    ],
    "wof:name":"Vtoroy Tyul'kubas",
    "wof:placetype":"locality"
},
  "geometry": {"coordinates":[70.29552,42.50062],"type":"Point"}
}