{
  "type": "Feature",
  "properties": {
    "gn:admin1_code":"0.0",
    "gn:asciiname":"Atakan",
    "gn:country_code":"KZ",
    "gn:dem":176,
    "gn:feature_class":"P",
    "gn:feature_code":"PPL",
    "gn:name":"Atakan",
    "gn:population":0,
    "gn:timezone":"Asia/Almaty",
    "iso:country":"KZ",
    "name:deu_x_preferred":[
        "Atakan"
    ],
    "wof:name":"Atakan",
    "wof:placetype":"locality"
},
  "geometry": {"coordinates":[78.61667,51.05],"type":"Point"}
}