{
  "type": "Feature",
  "properties": {
    "gn:admin1_code":"0.0",
    "gn:asciiname":"Tore",
    "gn:country_code":"KZ",
    "gn:dem":739,
    "gn:feature_class":"P",
    "gn:feature_code":"PPL",
    "gn:name":"Tore",
    "gn:population":0,
    "gn:timezone":"Asia/Almaty",
    "iso:country":"KZ",
    "name:dan_x_preferred":[
        "Tore"
    ],
    "name:deu_x_preferred":[
        "Tore"
    ],
    "name:fin_x_preferred":[
        "Tore"
    ],
    "name:ita_x_preferred":[
        "Tore"
    ],
    "name:nno_x_preferred":[
        "Tore"
    ],
    "name:nor_x_preferred":[
        "Tore"
    ],
    "name:por_x_preferred":[
        "Tore"
    ],
    "name:swe_x_preferred":[
        "Tore"
    ],
    "wof:name":"Tore",
    "wof:placetype":"locality"
},
  "geometry": {"coordinates":[82.43333,49.61667],"type":"Point"}
}