{
  "type": "Feature",
  "properties": {
    "gn:admin1_code":"1.0",
    "gn:asciiname":"Shugyla",
    "gn:country_code":"KZ",
    "gn:dem":816,
    "gn:feature_class":"P",
    "gn:feature_code":"PPL",
    "gn:name":"Shugyla",
    "gn:population":0,
    "gn:timezone":"Asia/Almaty",
    "iso:country":"KZ",
    "wof:name":"Shugyla",
    "wof:placetype":"locality"
},
  "geometry": {"coordinates":[76.80083,43.20889],"type":"Point"}
}