{
  "type": "Feature",
  "properties": {
    "gn:admin1_code":"17.0",
    "gn:asciiname":"Rgayty",
    "gn:country_code":"KZ",
    "gn:dem":751,
    "gn:feature_class":"P",
    "gn:feature_code":"PPL",
    "gn:name":"Rgayty",
    "gn:population":0,
    "gn:timezone":"Asia/Almaty",
    "iso:country":"KZ",
    "name:kaz_x_preferred":[
        "Yrghayty"
    ],
    "name:kaz_x_variant":[
        "\u042b\u0440\u0493\u0430\u0439\u0442\u044b"
    ],
    "name:rus_x_preferred":[
        "\u0420\u0433\u0430\u0439\u0442\u044b"
    ],
    "name:und_x_variant":[
        "Chokpor",
        "Shokpar",
        "Chokpar",
        "Shoqpar",
        "Rgayty"
    ],
    "wof:name":"Rgayty",
    "wof:placetype":"locality"
},
  "geometry": {"coordinates":[74.84656,43.13058],"type":"Point"}
}