{
  "type": "Feature",
  "properties": {
    "gn:admin1_code":"17.0",
    "gn:asciiname":"Bugun'",
    "gn:country_code":"KZ",
    "gn:dem":749,
    "gn:feature_class":"P",
    "gn:feature_code":"PPL",
    "gn:name":"Bugun\u2019",
    "gn:population":0,
    "gn:timezone":"Asia/Almaty",
    "iso:country":"KZ",
    "name:rus_x_preferred":[
        "\u0411\u0443\u0433\u0443\u043d\u044c"
    ],
    "name:und_x_variant":[
        "Aksay",
        "Bugun\u2019"
    ],
    "wof:name":"Bugun'",
    "wof:placetype":"locality"
},
  "geometry": {"coordinates":[70.18595999999999,43.36023],"type":"Point"}
}