{
  "type": "Feature",
  "properties": {
    "gn:admin1_code":"17.0",
    "gn:asciiname":"Leninskoye",
    "gn:country_code":"KZ",
    "gn:dem":466,
    "gn:feature_class":"P",
    "gn:feature_code":"PPL",
    "gn:name":"Leninskoye",
    "gn:population":0,
    "gn:timezone":"Asia/Almaty",
    "iso:country":"KZ",
    "name:kaz_x_preferred":[
        "Len\u012bnskoe"
    ],
    "name:kaz_x_variant":[
        "\u041b\u0435\u043d\u0438\u043d\u0441\u043a\u043e\u0435"
    ],
    "wof:name":"Leninskoye",
    "wof:placetype":"locality"
},
  "geometry": {"coordinates":[73.81033000000002,43.62877],"type":"Point"}
}