{
  "type": "Feature",
  "properties": {
    "gn:admin1_code":"16.0",
    "gn:asciiname":"Chirikovka",
    "gn:country_code":"KZ",
    "gn:dem":118,
    "gn:feature_class":"P",
    "gn:feature_code":"PPL",
    "gn:name":"Chirikovka",
    "gn:population":0,
    "gn:timezone":"Asia/Almaty",
    "iso:country":"KZ",
    "name:eng_x_preferred":[
        "Chirikovka"
    ],
    "name:kaz_x_preferred":[
        "Ch\u012br\u012bkovka"
    ],
    "name:kaz_x_variant":[
        "\u0427\u0438\u0440\u0438\u043a\u043e\u0432\u043a\u0430"
    ],
    "name:rus_x_preferred":[
        "\u0427\u0438\u0440\u0438\u043a\u043e\u0432\u043a\u0430"
    ],
    "wof:name":"Chirikovka",
    "wof:placetype":"locality"
},
  "geometry": {"coordinates":[68.61894000000001,54.40255],"type":"Point"}
}