{
  "type": "Feature",
  "properties": {
    "gn:admin1_code":"0.0",
    "gn:asciiname":"Kuntemes",
    "gn:country_code":"KZ",
    "gn:dem":192,
    "gn:feature_class":"P",
    "gn:feature_code":"PPL",
    "gn:name":"Kuntemes",
    "gn:population":0,
    "gn:timezone":"Asia/Qyzylorda",
    "iso:country":"KZ",
    "wof:name":"Kuntemes",
    "wof:placetype":"locality"
},
  "geometry": {"coordinates":[65.40000000000001,53.71666999999999],"type":"Point"}
}