{
  "type": "Feature",
  "properties": {
    "gn:admin1_code":"16.0",
    "gn:asciiname":"Vysokoye",
    "gn:country_code":"KZ",
    "gn:dem":257,
    "gn:feature_class":"P",
    "gn:feature_code":"PPL",
    "gn:name":"Vysokoye",
    "gn:population":0,
    "gn:timezone":"Asia/Almaty",
    "iso:country":"KZ",
    "name:eng_x_preferred":[
        "Vysokoye"
    ],
    "name:kaz_x_preferred":[
        "Vysokoe"
    ],
    "name:kaz_x_variant":[
        "\u0412\u044b\u0441\u043e\u043a\u043e\u0435"
    ],
    "name:rus_x_preferred":[
        "\u0412\u044b\u0441\u043e\u043a\u043e\u0435"
    ],
    "name:und_x_variant":[
        "Shangal"
    ],
    "wof:name":"Vysokoye",
    "wof:placetype":"locality"
},
  "geometry": {"coordinates":[67.67735999999999,53.27817],"type":"Point"}
}