{
  "type": "Feature",
  "properties": {
    "gn:admin1_code":"11.0",
    "gn:asciiname":"Kuban'",
    "gn:country_code":"KZ",
    "gn:dem":94,
    "gn:feature_class":"P",
    "gn:feature_code":"PPL",
    "gn:name":"Kuban\u2019",
    "gn:population":0,
    "gn:timezone":"Asia/Almaty",
    "iso:country":"KZ",
    "name:rus_x_preferred":[
        "\u041a\u0443\u0431\u0430\u043d\u044c"
    ],
    "name:und_x_variant":[
        "Kubanskiy",
        "Kuban\u2019"
    ],
    "wof:name":"Kuban'",
    "wof:placetype":"locality"
},
  "geometry": {"coordinates":[75.76251999999999,53.08653],"type":"Point"}
}