{
  "type": "Feature",
  "properties": {
    "gn:admin1_code":"14.0",
    "gn:asciiname":"Kyrkense",
    "gn:country_code":"KZ",
    "gn:dem":163,
    "gn:feature_class":"P",
    "gn:feature_code":"PPL",
    "gn:name":"Kyrkense",
    "gn:population":0,
    "gn:timezone":"Asia/Qyzylorda",
    "iso:country":"KZ",
    "name:kaz_x_preferred":[
        "Qyrkengse"
    ],
    "name:kaz_x_variant":[
        "\u049a\u044b\u0440\u043a\u0435\u04a3\u0441\u0435"
    ],
    "name:rus_x_preferred":[
        "\u041a\u044b\u0440\u043a\u0435\u043d\u0441\u0435"
    ],
    "name:und_x_variant":[
        "Zhanaaryk",
        "Kyrkense"
    ],
    "wof:name":"Kyrkense",
    "wof:placetype":"locality"
},
  "geometry": {"coordinates":[67.12666999999999,43.80194],"type":"Point"}
}