{
  "type": "Feature",
  "properties": {
    "gn:admin1_code":"11.0",
    "gn:asciiname":"Aleksandrovka",
    "gn:country_code":"KZ",
    "gn:dem":298,
    "gn:feature_class":"P",
    "gn:feature_code":"PPL",
    "gn:name":"Aleksandrovka",
    "gn:population":0,
    "gn:timezone":"Asia/Almaty",
    "iso:country":"KZ",
    "name:kaz_x_preferred":[
        "\u0410\u043b\u0435\u043a\u0441\u0430\u043d\u0434\u0440\u043e\u0432\u043a\u0430"
    ],
    "name:und_x_variant":[
        "Aleksandrovsk",
        "Aleksandrovka"
    ],
    "wof:name":"Aleksandrovka",
    "wof:placetype":"locality"
},
  "geometry": {"coordinates":[75.62891999999999,50.96826],"type":"Point"}
}