{
  "type": "Feature",
  "properties": {
    "gn:admin1_code":"3.0",
    "gn:asciiname":"Kumkosyak",
    "gn:country_code":"KZ",
    "gn:dem":306,
    "gn:feature_class":"P",
    "gn:feature_code":"PPL",
    "gn:name":"Kumkosyak",
    "gn:population":0,
    "gn:timezone":"Asia/Almaty",
    "iso:country":"KZ",
    "name:rus_x_preferred":[
        "\u041a\u0443\u043c\u043a\u043e\u0441\u044f\u043a"
    ],
    "wof:name":"Kumkosyak",
    "wof:placetype":"locality"
},
  "geometry": {"coordinates":[70.48408000000001,53.13386],"type":"Point"}
}