{
  "type": "Feature",
  "properties": {
    "gn:admin1_code":"11.0",
    "gn:asciiname":"Sadyk-Makysh",
    "gn:country_code":"KZ",
    "gn:dem":293,
    "gn:feature_class":"P",
    "gn:feature_code":"PPL",
    "gn:name":"Sadyk-Makysh",
    "gn:population":0,
    "gn:timezone":"Asia/Almaty",
    "iso:country":"KZ",
    "name:rus_x_preferred":[
        "\u0421\u0430\u0434\u044b\u043a-\u041c\u0430\u043a\u044b\u0448"
    ],
    "name:und_x_variant":[
        "Satek-Makysh",
        "Satykmakysh",
        "Sadyk-Makysh"
    ],
    "wof:name":"Sadyk-Makysh",
    "wof:placetype":"locality"
},
  "geometry": {"coordinates":[76.76911,50.79429],"type":"Point"}
}