{
  "type": "Feature",
  "properties": {
    "gn:admin1_code":"15.0",
    "gn:asciiname":"Orlovka",
    "gn:country_code":"KZ",
    "gn:dem":1091,
    "gn:feature_class":"P",
    "gn:feature_code":"PPL",
    "gn:name":"Orlovka",
    "gn:population":0,
    "gn:timezone":"Asia/Almaty",
    "iso:country":"KZ",
    "name:eng_x_preferred":[
        "Orlovka"
    ],
    "name:kaz_x_preferred":[
        "Shanaghatty"
    ],
    "name:kaz_x_variant":[
        "\u0428\u0430\u043d\u0430\u0493\u0430\u0442\u0442\u044b"
    ],
    "name:rus_x_preferred":[
        "\u041e\u0440\u043b\u043e\u0432\u043a\u0430"
    ],
    "wof:name":"Orlovka",
    "wof:placetype":"locality"
},
  "geometry": {"coordinates":[86.48586999999998,48.69662],"type":"Point"}
}