{
  "type": "Feature",
  "properties": {
    "gn:admin1_code":"11.0",
    "gn:asciiname":"Karasuk",
    "gn:country_code":"KZ",
    "gn:dem":93,
    "gn:feature_class":"P",
    "gn:feature_code":"PPL",
    "gn:name":"Karasuk",
    "gn:population":0,
    "gn:timezone":"Asia/Almaty",
    "iso:country":"KZ",
    "name:bel_x_preferred":[
        "\u041a\u0430\u0440\u0430\u0441\u0443\u043a"
    ],
    "name:ceb_x_preferred":[
        "Karasuk"
    ],
    "name:deu_x_preferred":[
        "Karassuk"
    ],
    "name:eng_x_preferred":[
        "Karasuk"
    ],
    "name:fra_x_preferred":[
        "Karassouk"
    ],
    "name:ita_x_preferred":[
        "Karasuk"
    ],
    "name:kaz_x_preferred":[
        "Qaras\u016byq"
    ],
    "name:kaz_x_variant":[
        "\u049a\u0430\u0440\u0430\u0441\u0443\u044b\u049b"
    ],
    "name:nor_x_preferred":[
        "Karasuk"
    ],
    "name:rus_x_preferred":[
        "\u041a\u0430\u0440\u0430\u0441\u0443\u043a"
    ],
    "name:swe_x_preferred":[
        "Karasuk"
    ],
    "wof:name":"Karasuk",
    "wof:placetype":"locality"
},
  "geometry": {"coordinates":[76.25049,53.0221],"type":"Point"}
}