{
  "type": "Feature",
  "properties": {
    "gn:admin1_code":"0.0",
    "gn:asciiname":"Maskar",
    "gn:country_code":"KZ",
    "gn:dem":108,
    "gn:feature_class":"P",
    "gn:feature_code":"PPL",
    "gn:name":"Maskar",
    "gn:population":0,
    "gn:timezone":"Asia/Oral",
    "iso:country":"KZ",
    "name:fas_x_preferred":[
        "\u0645\u0633\u06a9\u0631"
    ],
    "name:nno_x_preferred":[
        "Maskar"
    ],
    "wof:name":"Maskar",
    "wof:placetype":"locality"
},
  "geometry": {"coordinates":[53.31667,50.53333],"type":"Point"}
}