{
  "type": "Feature",
  "properties": {
    "gn:admin1_code":"0.0",
    "gn:asciiname":"Kishiyespe",
    "gn:country_code":"KZ",
    "gn:dem":484,
    "gn:feature_class":"P",
    "gn:feature_code":"PPL",
    "gn:name":"Kishiyespe",
    "gn:population":0,
    "gn:timezone":"Asia/Almaty",
    "iso:country":"KZ",
    "wof:name":"Kishiyespe",
    "wof:placetype":"locality"
},
  "geometry": {"coordinates":[83.09999999999999,48.83333],"type":"Point"}
}