{
  "type": "Feature",
  "properties": {
    "iso:country":"KZ",
    "name:kaz_x_preferred":[
        "Sholaqqkorghan"
    ],
    "name:kaz_x_variant":[
        "Sholaqqorghan",
        "\u0428\u043e\u043b\u0430\u049b\u049b\u043e\u0440\u0493\u0430\u043d"
    ],
    "name:rus_x_preferred":[
        "\u0427\u0443\u043b\u0430\u043a\u043a\u0443\u0440\u0433\u0430\u043d"
    ],
    "name:unk_x_variant":[
        "Sholakkorgan"
    ],
    "qs:gn_country":"KZ",
    "qs:gn_fcode":"PPL",
    "qs:gn_pop":10836,
    "qs:name":"Chulakkurgan",
    "qs:name_adm0":"Kazakhstan",
    "qs:name_adm1":"Ongtustik Qazaqstan",
    "qs:photos":0,
    "qs:photos_1k":0,
    "qs:photos_9k":0,
    "qs:photos_9r":0,
    "qs:photos_all":0,
    "qs:photos_sr":0,
    "qs:placetype":"Town",
    "qs:pop_sr":"6",
    "qs:woe_adm0":23424871,
    "wof:name":"Chulakkurgan",
    "wof:placetype":"locality",
    "wof:population":10836
},
  "geometry": {"coordinates":[69.18138999999999,43.765],"type":"Point"}
}