{
  "type": "Feature",
  "properties": {
    "gn:admin1_code":"16.0",
    "gn:asciiname":"Samsonovka",
    "gn:country_code":"KZ",
    "gn:dem":205,
    "gn:feature_class":"P",
    "gn:feature_code":"PPL",
    "gn:name":"Samsonovka",
    "gn:population":0,
    "gn:timezone":"Asia/Almaty",
    "iso:country":"KZ",
    "name:rus_x_preferred":[
        "\u0421\u0430\u043c\u0441\u043e\u043d\u043e\u0432\u043a\u0430"
    ],
    "wof:name":"Samsonovka",
    "wof:placetype":"locality"
},
  "geometry": {"coordinates":[67.40267,53.3712],"type":"Point"}
}