{
  "type": "Feature",
  "properties": {
    "gn:admin1_code":"16.0",
    "gn:asciiname":"Kuybyshevskoye",
    "gn:country_code":"KZ",
    "gn:dem":112,
    "gn:feature_class":"P",
    "gn:feature_code":"PPL",
    "gn:name":"Kuybyshevskoye",
    "gn:population":0,
    "gn:timezone":"Asia/Almaty",
    "iso:country":"KZ",
    "name:eng_x_preferred":[
        "K\u016bybyshevskoe"
    ],
    "name:kaz_x_preferred":[
        "D\u00e4\u016bit"
    ],
    "name:kaz_x_variant":[
        "\u0414\u04d9\u0443\u0456\u0442"
    ],
    "name:rus_x_preferred":[
        "\u041a\u0443\u0439\u0431\u044b\u0448\u0435\u0432\u0441\u043a\u043e\u0435"
    ],
    "name:und_x_variant":[
        "Kuybyshevskiy"
    ],
    "wof:name":"Kuybyshevskoye",
    "wof:placetype":"locality"
},
  "geometry": {"coordinates":[71.47591,53.60914],"type":"Point"}
}