{
  "type": "Feature",
  "properties": {
    "gn:admin1_code":"12.0",
    "gn:asciiname":"Staryy Sklad",
    "gn:country_code":"KZ",
    "gn:dem":504,
    "gn:feature_class":"P",
    "gn:feature_code":"PPL",
    "gn:name":"Staryy Sklad",
    "gn:population":0,
    "gn:timezone":"Asia/Almaty",
    "iso:country":"KZ",
    "name:rus_x_preferred":[
        "\u0421\u0442\u0430\u0440\u044b\u0439 \u0421\u043a\u043b\u0430\u0434"
    ],
    "wof:name":"Staryy Sklad",
    "wof:placetype":"locality"
},
  "geometry": {"coordinates":[76.67625,50.15199000000001],"type":"Point"}
}