{
  "type": "Feature",
  "properties": {
    "gn:admin1_code":"10.0",
    "gn:asciiname":"Chirkino",
    "gn:country_code":"KZ",
    "gn:dem":483,
    "gn:feature_class":"P",
    "gn:feature_code":"PPL",
    "gn:name":"Chirkino",
    "gn:population":0,
    "gn:timezone":"Asia/Almaty",
    "iso:country":"KZ",
    "name:rus_x_preferred":[
        "\u0427\u0438\u0440\u043a\u0438\u043d\u043e"
    ],
    "name:und_x_variant":[
        "Stalina",
        "Chirkino"
    ],
    "wof:name":"Chirkino",
    "wof:placetype":"locality"
},
  "geometry": {"coordinates":[69.68196999999999,42.47923],"type":"Point"}
}