{
  "type": "Feature",
  "properties": {
    "gn:admin1_code":"15.0",
    "gn:asciiname":"Shubartas",
    "gn:country_code":"KZ",
    "gn:dem":861,
    "gn:feature_class":"P",
    "gn:feature_code":"PPL",
    "gn:name":"Shubartas",
    "gn:population":0,
    "gn:timezone":"Asia/Almaty",
    "iso:country":"KZ",
    "name:kaz_x_preferred":[
        "Shubartas"
    ],
    "name:kaz_x_variant":[
        "\u0428\u04b1\u0431\u0430\u0440\u0442\u0430\u0441"
    ],
    "name:rus_x_preferred":[
        "\u0428\u0443\u0431\u0430\u0440\u0442\u0430\u0441"
    ],
    "wof:name":"Shubartas",
    "wof:placetype":"locality"
},
  "geometry": {"coordinates":[81.29281,48.20767],"type":"Point"}
}