{
  "type": "Feature",
  "properties": {
    "gn:admin1_code":"9.0",
    "gn:asciiname":"Sadyrnyn",
    "gn:country_code":"KZ",
    "gn:dem":70,
    "gn:feature_class":"P",
    "gn:feature_code":"PPL",
    "gn:name":"Sadyrnyn",
    "gn:population":0,
    "gn:timezone":"Asia/Aqtau",
    "iso:country":"KZ",
    "wof:name":"Sadyrnyn",
    "wof:placetype":"locality"
},
  "geometry": {"coordinates":[52.03333,43.15],"type":"Point"}
}