{
  "type": "Feature",
  "properties": {
    "gn:admin1_code":"11.0",
    "gn:asciiname":"Yuzhnoe",
    "gn:country_code":"KZ",
    "gn:dem":591,
    "gn:feature_class":"P",
    "gn:feature_code":"PPL",
    "gn:name":"Yuzhnoe",
    "gn:population":0,
    "gn:timezone":"Asia/Almaty",
    "iso:country":"KZ",
    "name:kaz_x_preferred":[
        "Yuzhnoe"
    ],
    "name:kaz_x_variant":[
        "\u042e\u0436\u043d\u043e\u0435"
    ],
    "name:und_x_variant":[
        "Yuzhnoye"
    ],
    "wof:name":"Yuzhnoe",
    "wof:placetype":"locality"
},
  "geometry": {"coordinates":[75.75354,50.40723],"type":"Point"}
}