{
  "type": "Feature",
  "properties": {
    "gn:admin1_code":"16.0",
    "gn:asciiname":"Dombraly",
    "gn:country_code":"KZ",
    "gn:dem":216,
    "gn:feature_class":"P",
    "gn:feature_code":"PPL",
    "gn:name":"Dombraly",
    "gn:population":0,
    "gn:timezone":"Asia/Almaty",
    "iso:country":"KZ",
    "name:eng_x_preferred":[
        "Dombraly"
    ],
    "name:kaz_x_preferred":[
        "Dombyraly"
    ],
    "name:kaz_x_variant":[
        "\u0414\u043e\u043c\u0431\u044b\u0440\u0430\u043b\u044b"
    ],
    "name:rus_x_preferred":[
        "\u0414\u043e\u043c\u0431\u0440\u0430\u043b\u044b"
    ],
    "wof:name":"Dombraly",
    "wof:placetype":"locality"
},
  "geometry": {"coordinates":[72.11256,52.97576],"type":"Point"}
}