{
  "type": "Feature",
  "properties": {
    "gn:admin1_code":"17.0",
    "gn:asciiname":"Aul Bertamar",
    "gn:country_code":"KZ",
    "gn:dem":558,
    "gn:feature_class":"P",
    "gn:feature_code":"PPL",
    "gn:name":"Aul Bertamar",
    "gn:population":0,
    "gn:timezone":"Asia/Almaty",
    "iso:country":"KZ",
    "wof:name":"Aul Bertamar",
    "wof:placetype":"locality"
},
  "geometry": {"coordinates":[74.40000000000001,43.21667],"type":"Point"}
}