{
  "type": "Feature",
  "properties": {
    "gn:admin1_code":"3.0",
    "gn:asciiname":"Uyaly",
    "gn:country_code":"KZ",
    "gn:dem":396,
    "gn:feature_class":"P",
    "gn:feature_code":"PPL",
    "gn:name":"Uyaly",
    "gn:population":0,
    "gn:timezone":"Asia/Almaty",
    "iso:country":"KZ",
    "name:kaz_x_preferred":[
        "Uyaly"
    ],
    "name:kaz_x_variant":[
        "\u04b0\u044f\u043b\u044b"
    ],
    "name:rus_x_preferred":[
        "\u0423\u044f\u043b\u044b"
    ],
    "wof:name":"Uyaly",
    "wof:placetype":"locality"
},
  "geometry": {"coordinates":[69.37246,52.56162],"type":"Point"}
}