{
  "type": "Feature",
  "properties": {
    "gn:admin1_code":"10.0",
    "gn:asciiname":"Orynbay Taymanov",
    "gn:country_code":"KZ",
    "gn:dem":409,
    "gn:feature_class":"P",
    "gn:feature_code":"PPL",
    "gn:name":"Orynbay Taymanov",
    "gn:population":0,
    "gn:timezone":"Asia/Almaty",
    "iso:country":"KZ",
    "name:kaz_x_preferred":[
        "Orynbay Taymanov"
    ],
    "name:kaz_x_variant":[
        "\u041e\u0440\u044b\u043d\u0431\u0430\u0439 \u0422\u0430\u0439\u043c\u0430\u043d\u043e\u0432"
    ],
    "name:rus_x_preferred":[
        "\u041d\u0438\u0436\u043d\u0438\u0439 \u0411\u043e\u0440\u0430\u043b\u0434\u0430\u0439"
    ],
    "name:und_x_variant":[
        "Nizhniy Boralday"
    ],
    "wof:name":"Orynbay Taymanov",
    "wof:placetype":"locality"
},
  "geometry": {"coordinates":[69.5936,42.73879],"type":"Point"}
}