{
  "type": "Feature",
  "properties": {
    "gn:admin1_code":"0.0",
    "gn:asciiname":"Konkha",
    "gn:country_code":"KZ",
    "gn:dem":16,
    "gn:feature_class":"P",
    "gn:feature_code":"PPL",
    "gn:name":"Konkha",
    "gn:population":0,
    "gn:timezone":"Asia/Oral",
    "iso:country":"KZ",
    "wof:name":"Konkha",
    "wof:placetype":"locality"
},
  "geometry": {"coordinates":[53.36136,49.21034],"type":"Point"}
}