{
  "type": "Feature",
  "properties": {
    "gn:admin1_code":"4.0",
    "gn:asciiname":"Karaagash",
    "gn:country_code":"KZ",
    "gn:dem":380,
    "gn:feature_class":"P",
    "gn:feature_code":"PPL",
    "gn:name":"Karaagash",
    "gn:population":0,
    "gn:timezone":"Asia/Aqtobe",
    "iso:country":"KZ",
    "name:che_x_preferred":[
        "\u041a\u0430\u0440\u0430\u0430\u0433\u0430\u0448"
    ],
    "name:rus_x_preferred":[
        "\u041a\u0430\u0440\u0430\u0430\u0433\u0430\u0448"
    ],
    "name:tat_x_preferred":[
        "\u041a\u0430\u0440\u0430\u0433\u0430\u0447"
    ],
    "name:tgk_x_preferred":[
        "\u041a\u0430\u0440\u0430\u0430\u0433\u0430\u0448"
    ],
    "wof:name":"Karaagash",
    "wof:placetype":"locality"
},
  "geometry": {"coordinates":[58.41667,50.48333],"type":"Point"}
}