{
  "type": "Feature",
  "properties": {
    "gn:admin1_code":"13.0",
    "gn:asciiname":"Sevastopol'",
    "gn:country_code":"KZ",
    "gn:dem":207,
    "gn:feature_class":"P",
    "gn:feature_code":"PPL",
    "gn:name":"Sevastopol\u2019",
    "gn:population":0,
    "gn:timezone":"Asia/Qyzylorda",
    "iso:country":"KZ",
    "name:eng_x_preferred":[
        "Sevastopol'"
    ],
    "name:kaz_x_preferred":[
        "Sevastopol\u2019"
    ],
    "name:rus_x_preferred":[
        "\u0421\u0435\u0432\u0430\u0441\u0442\u043e\u043f\u043e\u043b\u044c\u0441\u043a\u0438\u0439"
    ],
    "name:und_x_variant":[
        "Sevastopol\u2019skiy"
    ],
    "wof:name":"Sevastopol'",
    "wof:placetype":"locality"
},
  "geometry": {"coordinates":[65.79164,53.13433000000001],"type":"Point"}
}