{
  "type": "Feature",
  "properties": {
    "gn:admin1_code":"14.0",
    "gn:asciiname":"Birlestik",
    "gn:country_code":"KZ",
    "gn:dem":165,
    "gn:feature_class":"P",
    "gn:feature_code":"PPL",
    "gn:name":"Birlestik",
    "gn:population":0,
    "gn:timezone":"Asia/Qyzylorda",
    "iso:country":"KZ",
    "name:und_x_variant":[
        "Zhalakash",
        "Zhalanash",
        "Birlestik"
    ],
    "wof:name":"Birlestik",
    "wof:placetype":"locality"
},
  "geometry": {"coordinates":[67.26971999999999,43.83],"type":"Point"}
}