{
  "type": "Feature",
  "properties": {
    "gn:admin1_code":"1.0",
    "gn:asciiname":"Qyzylsharyq",
    "gn:country_code":"KZ",
    "gn:dem":694,
    "gn:feature_class":"P",
    "gn:feature_code":"PPL",
    "gn:name":"Qyzylsharyq",
    "gn:population":0,
    "gn:timezone":"Asia/Almaty",
    "iso:country":"KZ",
    "name:kaz_x_preferred":[
        "Qyzylsharyq"
    ],
    "name:kaz_x_variant":[
        "\u049a\u044b\u0437\u044b\u043b\u0448\u0430\u0440\u044b\u049b"
    ],
    "name:rus_x_preferred":[
        "\u041a\u044b\u0437\u044b\u043b\u0448\u0430\u0440\u043a"
    ],
    "name:und_x_variant":[
        "Kyzylshark"
    ],
    "wof:name":"Qyzylsharyq",
    "wof:placetype":"locality"
},
  "geometry": {"coordinates":[78.2757,43.53099],"type":"Point"}
}