{
  "type": "Feature",
  "properties": {
    "gn:admin1_code":"13.0",
    "gn:asciiname":"Oktyabr'skiy",
    "gn:country_code":"KZ",
    "gn:dem":283,
    "gn:feature_class":"P",
    "gn:feature_code":"PPL",
    "gn:name":"Oktyabr\u2019skiy",
    "gn:population":0,
    "gn:timezone":"Asia/Qyzylorda",
    "iso:country":"KZ",
    "name:kaz_x_preferred":[
        "Oktyabr\u2019sk\u012by"
    ],
    "name:rus_x_preferred":[
        "Oktyabr\u2019skiy"
    ],
    "name:rus_x_variant":[
        "\u041e\u043a\u0442\u044f\u0431\u0440\u044c\u0441\u043a\u0438\u0439"
    ],
    "wof:name":"Oktyabr'skiy",
    "wof:placetype":"locality"
},
  "geometry": {"coordinates":[60.9627,52.59491],"type":"Point"}
}