{
  "type": "Feature",
  "properties": {
    "gn:country":"KZ",
    "gn:fcode":"PPL",
    "gn:population":13457,
    "iso:country":"KZ",
    "name:bel_x_preferred":[
        "\u041f\u0440\u044b\u0430\u0437\u0451\u0440\u0441\u043a"
    ],
    "name:deu_x_preferred":[
        "Priosersk"
    ],
    "name:eng_x_preferred":[
        "Priozersk"
    ],
    "name:epo_x_preferred":[
        "Priozjorsk"
    ],
    "name:fra_x_preferred":[
        "Prioziorsk"
    ],
    "name:hsb_x_preferred":[
        "Priozjorsk"
    ],
    "name:kaz_x_preferred":[
        "\u041f\u0440\u0438\u043e\u0437\u0435\u0440\u0441\u043a"
    ],
    "name:lit_x_preferred":[
        "Prioziorskas"
    ],
    "name:nld_x_preferred":[
        "Priozersk"
    ],
    "name:pol_x_preferred":[
        "Prioziorsk"
    ],
    "name:rus_x_preferred":[
        "\u041f\u0440\u0438\u043e\u0437\u0435\u0440\u0441\u043a"
    ],
    "name:rus_x_variant":[
        "\u041f\u0440\u0438\u043e\u0437\u0451\u0440\u0441\u043a"
    ],
    "name:tat_x_preferred":[
        "\u041f\u0440\u0438\u043e\u0437\u0451\u0440"
    ],
    "name:ukr_x_preferred":[
        "\u041f\u0440\u0438\u043e\u0437\u0435\u0440\u0441\u044c\u043a"
    ],
    "name:zho_x_preferred":[
        "\u8428\u96f7\u00b7\u6c99\u7518\u57fa\u5730"
    ],
    "qs:name":"Priozersk",
    "qs:photos_9r":0,
    "qs:photos_sr":0,
    "qs:pop_sr":"6",
    "wd:wordcount":1571,
    "wof:name":"Priozersk",
    "wof:placetype":"locality",
    "wof:population":13457
},
  "geometry": {"coordinates":[73.70247000000001,46.03106],"type":"Point"}
}