{
  "type": "Feature",
  "properties": {
    "gn:admin1_code":"3.0",
    "gn:asciiname":"Sosnovka",
    "gn:country_code":"KZ",
    "gn:dem":471,
    "gn:feature_class":"P",
    "gn:feature_code":"PPL",
    "gn:name":"Sosnovka",
    "gn:population":0,
    "gn:timezone":"Asia/Almaty",
    "iso:country":"KZ",
    "name:kaz_x_preferred":[
        "Sosnovka"
    ],
    "name:kaz_x_variant":[
        "\u0421\u043e\u0441\u043d\u043e\u0432\u043a\u0430"
    ],
    "wof:name":"Sosnovka",
    "wof:placetype":"locality"
},
  "geometry": {"coordinates":[70.44314,52.8717],"type":"Point"}
}