{
  "type": "Feature",
  "properties": {
    "gn:admin1_code":"11.0",
    "gn:asciiname":"Nayzatas",
    "gn:country_code":"KZ",
    "gn:dem":461,
    "gn:feature_class":"P",
    "gn:feature_code":"PPL",
    "gn:name":"Nayzatas",
    "gn:population":0,
    "gn:timezone":"Asia/Almaty",
    "iso:country":"KZ",
    "wof:name":"Nayzatas",
    "wof:placetype":"locality"
},
  "geometry": {"coordinates":[75.09999999999999,50.78333],"type":"Point"}
}