{
  "type": "Feature",
  "properties": {
    "gn:admin1_code":"0.0",
    "gn:asciiname":"Abel'-Mula",
    "gn:country_code":"KZ",
    "gn:dem":63,
    "gn:feature_class":"P",
    "gn:feature_code":"PPL",
    "gn:name":"Abel\u2019-Mula",
    "gn:population":0,
    "gn:timezone":"Asia/Oral",
    "iso:country":"KZ",
    "wof:name":"Abel'-Mula",
    "wof:placetype":"locality"
},
  "geometry": {"coordinates":[53.05,50.26667],"type":"Point"}
}