{
  "type": "Feature",
  "properties": {
    "gn:admin1_code":"3.0",
    "gn:asciiname":"Zhanaturmys",
    "gn:country_code":"KZ",
    "gn:dem":294,
    "gn:feature_class":"P",
    "gn:feature_code":"PPL",
    "gn:name":"Zhanaturmys",
    "gn:population":0,
    "gn:timezone":"Asia/Almaty",
    "iso:country":"KZ",
    "name:und_x_variant":[
        "Kyzylzhar",
        "Zhanaturmys"
    ],
    "wof:name":"Zhanaturmys",
    "wof:placetype":"locality"
},
  "geometry": {"coordinates":[69.91893,51.84153],"type":"Point"}
}