{
  "type": "Feature",
  "properties": {
    "gn:admin1_code":"3.0",
    "gn:asciiname":"Vasil'kovka",
    "gn:country_code":"KZ",
    "gn:dem":207,
    "gn:feature_class":"P",
    "gn:feature_code":"PPL",
    "gn:name":"Vasil\u2019kovka",
    "gn:population":0,
    "gn:timezone":"Asia/Almaty",
    "iso:country":"KZ",
    "name:eng_x_preferred":[
        "Vasil'kovka"
    ],
    "name:kaz_x_preferred":[
        "Vas\u012bl\u2019kovka"
    ],
    "name:kaz_x_variant":[
        "\u0412\u0430\u0441\u0438\u043b\u044c\u043a\u043e\u0432\u043a\u0430"
    ],
    "name:rus_x_preferred":[
        "\u0412\u0430\u0441\u0438\u043b\u044c\u043a\u043e\u0432\u043a\u0430"
    ],
    "name:und_x_variant":[
        "Vasil\u2019yevka",
        "Vasil\u2019yevskoye",
        "Vasil\u2019kovka"
    ],
    "wof:name":"Vasil'kovka",
    "wof:placetype":"locality"
},
  "geometry": {"coordinates":[69.36754999999999,53.44375],"type":"Point"}
}