{
  "type": "Feature",
  "properties": {
    "gn:admin1_code":"13.0",
    "gn:asciiname":"Mayskoye",
    "gn:cc2":"KZ",
    "gn:country_code":"KZ",
    "gn:dem":176,
    "gn:feature_class":"P",
    "gn:feature_code":"PPL",
    "gn:name":"Mayskoye",
    "gn:population":0,
    "gn:timezone":"Asia/Qyzylorda",
    "iso:country":"KZ",
    "name:eng_x_preferred":[
        "Mayskoye"
    ],
    "name:kaz_x_preferred":[
        "Mayskoe"
    ],
    "name:kaz_x_variant":[
        "\u041c\u0430\u0439\u0441\u043a\u043e\u0435"
    ],
    "name:rus_x_preferred":[
        "\u041c\u0430\u0439\u0441\u043a\u0438\u0439"
    ],
    "name:und_x_variant":[
        "Mayskiy"
    ],
    "wof:name":"Mayskoye",
    "wof:placetype":"locality"
},
  "geometry": {"coordinates":[62.64,52.82889],"type":"Point"}
}