{
  "type": "Feature",
  "properties": {
    "gn:admin1_code":"0.0",
    "gn:asciiname":"Akimovskoye",
    "gn:country_code":"KZ",
    "gn:dem":319,
    "gn:feature_class":"P",
    "gn:feature_code":"PPL",
    "gn:name":"Akimovskoye",
    "gn:population":0,
    "gn:timezone":"Asia/Almaty",
    "iso:country":"KZ",
    "wof:name":"Akimovskoye",
    "wof:placetype":"locality"
},
  "geometry": {"coordinates":[67.83333,51.85],"type":"Point"}
}