{
  "type": "Feature",
  "properties": {
    "gn:admin1_code":"0.0",
    "gn:asciiname":"Akbidaik",
    "gn:country_code":"KZ",
    "gn:dem":230,
    "gn:feature_class":"P",
    "gn:feature_code":"PPL",
    "gn:name":"Akbidaik",
    "gn:population":0,
    "gn:timezone":"Asia/Qyzylorda",
    "iso:country":"KZ",
    "wof:name":"Akbidaik",
    "wof:placetype":"locality"
},
  "geometry": {"coordinates":[63.15358000000001,51.27009],"type":"Point"}
}