{
  "type": "Feature",
  "properties": {
    "gn:admin1_code":"15.0",
    "gn:asciiname":"Burabay",
    "gn:country_code":"KZ",
    "gn:dem":569,
    "gn:feature_class":"P",
    "gn:feature_code":"PPL",
    "gn:name":"Burabay",
    "gn:population":0,
    "gn:timezone":"Asia/Almaty",
    "iso:country":"KZ",
    "name:rus_x_preferred":[
        "\u0411\u0443\u0440\u0430\u0431\u0430\u0439"
    ],
    "wof:name":"Burabay",
    "wof:placetype":"locality"
},
  "geometry": {"coordinates":[84.17281,48.66347],"type":"Point"}
}