{
  "type": "Feature",
  "properties": {
    "gn:admin1_code":"3.0",
    "gn:asciiname":"Gusarka",
    "gn:country_code":"KZ",
    "gn:dem":378,
    "gn:feature_class":"P",
    "gn:feature_code":"PPL",
    "gn:name":"Gusarka",
    "gn:population":0,
    "gn:timezone":"Asia/Almaty",
    "iso:country":"KZ",
    "name:kaz_x_preferred":[
        "G\u016bsarka"
    ],
    "name:und_x_variant":[
        "Gusarskoye"
    ],
    "wof:name":"Gusarka",
    "wof:placetype":"locality"
},
  "geometry": {"coordinates":[71.07928000000003,51.99616],"type":"Point"}
}