{
  "type": "Feature",
  "properties": {
    "gn:admin1_code":"0.0",
    "gn:asciiname":"Karasu",
    "gn:country_code":"KZ",
    "gn:dem":68,
    "gn:feature_class":"P",
    "gn:feature_code":"PPL",
    "gn:name":"Karasu",
    "gn:population":0,
    "gn:timezone":"Asia/Oral",
    "iso:country":"KZ",
    "name:azb_x_preferred":[
        "\u0642\u0627\u0631\u0627\u0633\u0648"
    ],
    "name:ceb_x_preferred":[
        "Karasu \u0130l\u00e7esi"
    ],
    "name:deu_x_preferred":[
        "Karasu"
    ],
    "name:fas_x_preferred":[
        "\u0642\u0631\u0647\u200c\u0633\u0648"
    ],
    "name:fra_x_preferred":[
        "Karasu"
    ],
    "name:gag_x_preferred":[
        "Karasu"
    ],
    "name:lit_x_preferred":[
        "Karasu"
    ],
    "name:min_x_preferred":[
        "Karasu"
    ],
    "name:mrj_x_preferred":[
        "\u041a\u0430\u0440\u0430\u0441\u0443"
    ],
    "name:msa_x_preferred":[
        "Karasu"
    ],
    "name:nno_x_preferred":[
        "Karasu"
    ],
    "name:nor_x_preferred":[
        "Karasu"
    ],
    "name:pnb_x_preferred":[
        "\u0636\u0644\u0639 \u06a9\u0627\u0631\u0627\u0633\u0648"
    ],
    "name:rus_x_preferred":[
        "\u041a\u0430\u0440\u0430\u0441\u0443"
    ],
    "name:swa_x_preferred":[
        "Karasu"
    ],
    "name:tur_x_preferred":[
        "Karasu"
    ],
    "name:urd_x_preferred":[
        "\u06a9\u0627\u0631\u0627\u0633\u0648"
    ],
    "name:vie_x_preferred":[
        "Karasu"
    ],
    "name:zho_x_preferred":[
        "\u5361\u62c9\u8607"
    ],
    "wof:name":"Karasu",
    "wof:placetype":"locality"
},
  "geometry": {"coordinates":[53.44488000000001,49.95478],"type":"Point"}
}