{
  "type": "Feature",
  "properties": {
    "gn:admin1_code":"12.0",
    "gn:asciiname":"Tasaral",
    "gn:cc2":"KZ",
    "gn:country_code":"KZ",
    "gn:dem":338,
    "gn:feature_class":"P",
    "gn:feature_code":"PPL",
    "gn:name":"Tasaral",
    "gn:population":0,
    "gn:timezone":"Asia/Almaty",
    "iso:country":"KZ",
    "name:und_x_variant":[
        "Rybalka Tas-Aral",
        "Tasaral"
    ],
    "wof:name":"Tasaral",
    "wof:placetype":"locality"
},
  "geometry": {"coordinates":[73.97610999999998,46.30472],"type":"Point"}
}