{
  "type": "Feature",
  "properties": {
    "gn:admin1_code":"1.0",
    "gn:asciiname":"Birlik",
    "gn:cc2":"KZ",
    "gn:country_code":"KZ",
    "gn:dem":879,
    "gn:feature_class":"P",
    "gn:feature_code":"PPL",
    "gn:name":"Birlik",
    "gn:population":0,
    "gn:timezone":"Asia/Almaty",
    "iso:country":"KZ",
    "name:fra_x_preferred":[
        "Birlik"
    ],
    "name:kaz_x_preferred":[
        "Birlik"
    ],
    "name:kaz_x_variant":[
        "\u0411\u0456\u0440\u043b\u0456\u043a"
    ],
    "name:mkd_x_preferred":[
        "\u0411\u0438\u0440\u043b\u0438\u043a"
    ],
    "name:msa_x_preferred":[
        "Birlik"
    ],
    "name:rus_x_preferred":[
        "\u0411\u0438\u0440\u043b\u0438\u043a"
    ],
    "name:und_x_variant":[
        "Byrlyk",
        "Byrlik"
    ],
    "wof:name":"Birlik",
    "wof:placetype":"locality"
},
  "geometry": {"coordinates":[77.14166999999998,43.30806],"type":"Point"}
}