{
  "type": "Feature",
  "properties": {
    "gn:admin1_code":"16.0",
    "gn:asciiname":"Il'ichevka",
    "gn:country_code":"KZ",
    "gn:dem":210,
    "gn:feature_class":"P",
    "gn:feature_code":"PPL",
    "gn:name":"\u012al\u2019\u012bchevka",
    "gn:population":0,
    "gn:timezone":"Asia/Almaty",
    "iso:country":"KZ",
    "name:eng_x_preferred":[
        "\u012al'\u012bchevka"
    ],
    "name:kaz_x_preferred":[
        "\u0418\u043b\u044c\u0438\u0447\u0435\u0432\u043a\u0430"
    ],
    "name:rus_x_preferred":[
        "\u0418\u043b\u044c\u0438\u0447\u0435\u0432\u043a\u0430"
    ],
    "name:rus_x_variant":[
        "Il\u2019ich\u00ebvka",
        "\u0418\u043b\u044c\u0438\u0447\u0451\u0432\u043a\u0430"
    ],
    "name:und_x_variant":[
        "\u012al\u2019\u012bchevka"
    ],
    "wof:name":"Il'ichevka",
    "wof:placetype":"locality"
},
  "geometry": {"coordinates":[70.38814000000001,53.50306],"type":"Point"}
}