{
  "type": "Feature",
  "properties": {
    "gn:admin1_code":"16.0",
    "gn:asciiname":"Rakitnoye",
    "gn:country_code":"KZ",
    "gn:dem":164,
    "gn:feature_class":"P",
    "gn:feature_code":"PPL",
    "gn:name":"Rakitnoye",
    "gn:population":0,
    "gn:timezone":"Asia/Almaty",
    "iso:country":"KZ",
    "name:eng_x_preferred":[
        "Rakitnoye"
    ],
    "name:kaz_x_preferred":[
        "Rak\u012btnoe"
    ],
    "name:kaz_x_variant":[
        "\u0420\u0430\u043a\u0438\u0442\u043d\u043e\u0435"
    ],
    "name:rus_x_preferred":[
        "\u0420\u0430\u043a\u0438\u0442\u043d\u043e\u0435"
    ],
    "name:rus_x_variant":[
        "\u041a\u0443\u0440\u0442\u0430\u0439"
    ],
    "name:und_x_variant":[
        "Kurtay"
    ],
    "wof:name":"Rakitnoye",
    "wof:placetype":"locality"
},
  "geometry": {"coordinates":[66.82143000000001,53.93075],"type":"Point"}
}