{
  "type": "Feature",
  "properties": {
    "gn:admin1_code":"4.0",
    "gn:asciiname":"Kumsay",
    "gn:country_code":"KZ",
    "gn:dem":326,
    "gn:feature_class":"P",
    "gn:feature_code":"PPL",
    "gn:name":"Kumsay",
    "gn:population":0,
    "gn:timezone":"Asia/Aqtobe",
    "iso:country":"KZ",
    "name:eng_x_preferred":[
        "Kumsay"
    ],
    "name:kaz_x_preferred":[
        "Qumsay"
    ],
    "name:rus_x_preferred":[
        "\u041a\u0443\u043c\u0441\u0430\u0439"
    ],
    "wof:name":"Kumsay",
    "wof:placetype":"locality"
},
  "geometry": {"coordinates":[58.51333,49.4902],"type":"Point"}
}