{
  "type": "Feature",
  "properties": {
    "gn:admin1_code":"0.0",
    "gn:asciiname":"Ul'kenenbek",
    "gn:country_code":"KZ",
    "gn:dem":21,
    "gn:feature_class":"P",
    "gn:feature_code":"PPL",
    "gn:name":"Ul\u2019kenenbek",
    "gn:population":0,
    "gn:timezone":"Asia/Oral",
    "iso:country":"KZ",
    "name:eng_x_preferred":[
        "Ul'kenenbek"
    ],
    "name:rus_x_preferred":[
        "\u0423\u043b\u043a\u0435\u043d_\u0435\u043d\u0431\u0435\u043a"
    ],
    "name:und_x_variant":[
        "Ul\u2019kenenbek"
    ],
    "wof:name":"Ul'kenenbek",
    "wof:placetype":"locality"
},
  "geometry": {"coordinates":[51.23333,50.66667],"type":"Point"}
}