{
  "type": "Feature",
  "properties": {
    "gn:admin1_code":"0.0",
    "gn:asciiname":"Alteke",
    "gn:country_code":"KZ",
    "gn:dem":35,
    "gn:feature_class":"P",
    "gn:feature_code":"PPL",
    "gn:name":"Alteke",
    "gn:population":0,
    "gn:timezone":"Asia/Oral",
    "iso:country":"KZ",
    "wof:name":"Alteke",
    "wof:placetype":"locality"
},
  "geometry": {"coordinates":[47.93333,49.85],"type":"Point"}
}