{
  "type": "Feature",
  "properties": {
    "gn:admin1_code":"3.0",
    "gn:asciiname":"Sergeevka",
    "gn:country_code":"KZ",
    "gn:dem":272,
    "gn:feature_class":"P",
    "gn:feature_code":"PPL",
    "gn:name":"Sergeevka",
    "gn:population":0,
    "gn:timezone":"Asia/Almaty",
    "iso:country":"KZ",
    "name:und_x_variant":[
        "Sergevskiy",
        "Sergeyevskiy",
        "Sergiyevskiy",
        "Sergeyevka",
        "Sergeevka"
    ],
    "wof:name":"Sergeevka",
    "wof:placetype":"locality"
},
  "geometry": {"coordinates":[68.19773000000001,51.65635],"type":"Point"}
}