{
  "type": "Feature",
  "properties": {
    "gn:admin1_code":"12.0",
    "gn:asciiname":"Atasu",
    "gn:country_code":"KZ",
    "gn:dem":463,
    "gn:feature_class":"P",
    "gn:feature_code":"PPL",
    "gn:name":"Atasu",
    "gn:population":0,
    "gn:timezone":"Asia/Almaty",
    "iso:country":"KZ",
    "name:ben_x_preferred":[
        "\u0986\u09a4\u09be\u09b8\u09c1"
    ],
    "name:ceb_x_preferred":[
        "Atasu"
    ],
    "name:ell_x_preferred":[
        "\u0391\u03c4\u03ac\u03c3\u03bf\u03c5"
    ],
    "name:fas_x_preferred":[
        "\u0622\u062a\u0627\u0633\u0648"
    ],
    "name:fra_x_preferred":[
        "Atasu"
    ],
    "name:heb_x_preferred":[
        "\u05d0\u05d8\u05e1\u05d5"
    ],
    "name:hin_x_preferred":[
        "\u0905\u0924\u093e\u0938\u0941"
    ],
    "name:hun_x_preferred":[
        "Atasu"
    ],
    "name:ind_x_preferred":[
        "Atasu"
    ],
    "name:ita_x_preferred":[
        "Atasu"
    ],
    "name:jpn_x_preferred":[
        "\u30a2\u30bf\u30b9"
    ],
    "name:kaz_x_preferred":[
        "Atas\u016b"
    ],
    "name:kaz_x_variant":[
        "\u0410\u0442\u0430\u0441\u0443"
    ],
    "name:kor_x_preferred":[
        "\uc544\ud0c0\uc2a4"
    ],
    "name:pol_x_preferred":[
        "Atasu"
    ],
    "name:por_x_preferred":[
        "Atasu"
    ],
    "name:spa_x_preferred":[
        "Atasu"
    ],
    "name:swe_x_preferred":[
        "Atasu"
    ],
    "name:tur_x_preferred":[
        "Atasu"
    ],
    "name:urd_x_preferred":[
        "\u0627\u062a\u0627\u0633\u0648"
    ],
    "name:vie_x_preferred":[
        "Atasu"
    ],
    "name:zho_cn_x_preferred":[
        "\u963f\u5854\u82cf"
    ],
    "name:zho_tw_x_preferred":[
        "\u963f\u5854\u8607"
    ],
    "wof:name":"Atasu",
    "wof:placetype":"locality"
},
  "geometry": {"coordinates":[71.38200999999999,48.63809],"type":"Point"}
}