{
  "type": "Feature",
  "properties": {
    "gn:admin1_code":"12.0",
    "gn:asciiname":"Atasu",
    "gn:country_code":"KZ",
    "gn:dem":463,
    "gn:feature_class":"P",
    "gn:feature_code":"PPL",
    "gn:name":"Atasu",
    "gn:population":0,
    "gn:timezone":"Asia/Almaty",
    "iso:country":"KZ",
    "name:ceb_x_preferred":[
        "Atasu"
    ],
    "name:ell_x_preferred":[
        "\u0391\u03c4\u03ac\u03c3\u03bf\u03c5"
    ],
    "name:kaz_x_preferred":[
        "Atas\u016b"
    ],
    "name:kaz_x_variant":[
        "\u0410\u0442\u0430\u0441\u0443"
    ],
    "name:pol_x_preferred":[
        "Atasu"
    ],
    "name:swe_x_preferred":[
        "Atasu"
    ],
    "name:vie_x_preferred":[
        "Atasu"
    ],
    "wof:name":"Atasu",
    "wof:placetype":"locality"
},
  "geometry": {"coordinates":[71.38200999999999,48.63809000000001],"type":"Point"}
}