{
  "type": "Feature",
  "properties": {
    "gn:admin1_code":"15.0",
    "gn:asciiname":"Makhovka",
    "gn:country_code":"KZ",
    "gn:dem":371,
    "gn:feature_class":"P",
    "gn:feature_code":"PPL",
    "gn:name":"Makhovka",
    "gn:population":0,
    "gn:timezone":"Asia/Almaty",
    "iso:country":"KZ",
    "name:kaz_x_preferred":[
        "Makhovka"
    ],
    "name:kaz_x_variant":[
        "\u041c\u0430\u0445\u043e\u0432\u043a\u0430"
    ],
    "wof:name":"Makhovka",
    "wof:placetype":"locality"
},
  "geometry": {"coordinates":[82.67055000000001,50.49945],"type":"Point"}
}