{
  "type": "Feature",
  "properties": {
    "gn:admin1_code":"16.0",
    "gn:asciiname":"Baumanskoye",
    "gn:country_code":"KZ",
    "gn:dem":160,
    "gn:feature_class":"P",
    "gn:feature_code":"PPL",
    "gn:name":"Baumanskoye",
    "gn:population":0,
    "gn:timezone":"Asia/Almaty",
    "iso:country":"KZ",
    "name:eng_x_preferred":[
        "Baumanskoye"
    ],
    "name:kaz_x_preferred":[
        "Ba\u016bmanskoe"
    ],
    "name:kaz_x_variant":[
        "\u0411\u0430\u0443\u043c\u0430\u043d\u0441\u043a\u043e\u0435"
    ],
    "name:rus_x_preferred":[
        "\u0411\u0430\u0443\u043c\u0430\u043d\u0441\u043a\u043e\u0435"
    ],
    "name:rus_x_variant":[
        "\u0416\u0430\u0440\u043a\u043e\u043b\u044c"
    ],
    "name:und_x_variant":[
        "Zharkol\u2019"
    ],
    "wof:name":"Baumanskoye",
    "wof:placetype":"locality"
},
  "geometry": {"coordinates":[66.2338,54.2359],"type":"Point"}
}