{
  "type": "Feature",
  "properties": {
    "gn:admin1_code":"0.0",
    "gn:asciiname":"Beksaut",
    "gn:cc2":"KZ",
    "gn:country_code":"KZ",
    "gn:dem":-5,
    "gn:feature_class":"P",
    "gn:feature_code":"PPL",
    "gn:name":"Beksaut",
    "gn:population":0,
    "gn:timezone":"Asia/Oral",
    "iso:country":"KZ",
    "name:und_x_variant":[
        "Beksaul",
        "Beksaut"
    ],
    "wof:name":"Beksaut",
    "wof:placetype":"locality"
},
  "geometry": {"coordinates":[47.84389,48.54167],"type":"Point"}
}