{
  "type": "Feature",
  "properties": {
    "gn:admin1_code":"1.0",
    "gn:asciiname":"Akbastau",
    "gn:country_code":"KZ",
    "gn:dem":614,
    "gn:feature_class":"P",
    "gn:feature_code":"PPL",
    "gn:name":"Akbastau",
    "gn:population":0,
    "gn:timezone":"Asia/Almaty",
    "iso:country":"KZ",
    "name:rus_x_preferred":[
        "\u0410\u043a\u0431\u0430\u0441\u0442\u0430\u0443"
    ],
    "wof:name":"Akbastau",
    "wof:placetype":"locality"
},
  "geometry": {"coordinates":[77.48206999999999,43.52184000000001],"type":"Point"}
}