{
  "type": "Feature",
  "properties": {
    "gn:admin1_code":"15.0",
    "gn:asciiname":"Vos'moy Kilometr",
    "gn:country_code":"KZ",
    "gn:dem":435,
    "gn:feature_class":"P",
    "gn:feature_code":"PPL",
    "gn:name":"Vos\u2019moy Kilometr",
    "gn:population":0,
    "gn:timezone":"Asia/Almaty",
    "iso:country":"KZ",
    "name:rus_x_preferred":[
        "Vos\u2019moy Kilometr"
    ],
    "wof:name":"Vos'moy Kilometr",
    "wof:placetype":"locality"
},
  "geometry": {"coordinates":[81.53045999999998,47.05222],"type":"Point"}
}