{
  "type": "Feature",
  "properties": {
    "gn:admin1_code":"16.0",
    "gn:asciiname":"Ivangorod",
    "gn:country_code":"KZ",
    "gn:dem":178,
    "gn:feature_class":"P",
    "gn:feature_code":"PPL",
    "gn:name":"Ivangorod",
    "gn:population":0,
    "gn:timezone":"Asia/Almaty",
    "iso:country":"KZ",
    "name:eng_x_preferred":[
        "Ivangorod"
    ],
    "name:kaz_x_preferred":[
        "\u012avangorod"
    ],
    "name:kaz_x_variant":[
        "\u0418\u0432\u0430\u043d\u0433\u043e\u0440\u043e\u0434"
    ],
    "name:rus_x_preferred":[
        "\u0418\u0432\u0430\u043d\u0433\u043e\u0440\u043e\u0434"
    ],
    "wof:name":"Ivangorod",
    "wof:placetype":"locality"
},
  "geometry": {"coordinates":[69.32284,53.77284],"type":"Point"}
}