{
  "type": "Feature",
  "properties": {
    "gn:admin1_code":"13.0",
    "gn:asciiname":"Amangeldi",
    "gn:country_code":"KZ",
    "gn:dem":138,
    "gn:feature_class":"P",
    "gn:feature_code":"PPL",
    "gn:name":"Amangeldi",
    "gn:population":0,
    "gn:timezone":"Asia/Almaty",
    "iso:country":"KZ",
    "name:eng_x_preferred":[
        "Amangeldi"
    ],
    "name:kaz_x_preferred":[
        "\u0410\u043c\u0430\u043d\u0433\u0435\u043b\u0434\u0456"
    ],
    "name:rus_x_preferred":[
        "\u0410\u043c\u0430\u043d\u0433\u0435\u043b\u044c\u0434\u044b"
    ],
    "name:und_x_variant":[
        "Batbakkara",
        "Amangeldin",
        "Amankeldy",
        "Batpaqqara",
        "Amangel\u2019dy",
        "Amangeldi"
    ],
    "wof:name":"Amangeldi",
    "wof:placetype":"locality"
},
  "geometry": {"coordinates":[65.18966,50.18271],"type":"Point"}
}