{
  "type": "Feature",
  "properties": {
    "gn:admin1_code":"0.0",
    "gn:asciiname":"Sopoy",
    "gn:country_code":"KZ",
    "gn:dem":18,
    "gn:feature_class":"P",
    "gn:feature_code":"PPL",
    "gn:name":"Sopoy",
    "gn:population":0,
    "gn:timezone":"Asia/Oral",
    "iso:country":"KZ",
    "wof:name":"Sopoy",
    "wof:placetype":"locality"
},
  "geometry": {"coordinates":[52.58333,49.98333],"type":"Point"}
}