{
  "type": "Feature",
  "properties": {
    "gn:admin1_code":"3.0",
    "gn:asciiname":"Vozdvizhenka",
    "gn:country_code":"KZ",
    "gn:dem":339,
    "gn:feature_class":"P",
    "gn:feature_code":"PPL",
    "gn:name":"Vozdvizhenka",
    "gn:population":0,
    "gn:timezone":"Asia/Almaty",
    "iso:country":"KZ",
    "name:kaz_x_preferred":[
        "Vozdv\u012bzhenka"
    ],
    "name:und_x_variant":[
        "Vozdvizhenskoye"
    ],
    "wof:name":"Vozdvizhenka",
    "wof:placetype":"locality"
},
  "geometry": {"coordinates":[71.11918,51.21438],"type":"Point"}
}