{
  "type": "Feature",
  "properties": {
    "gn:admin1_code":"6.0",
    "gn:asciiname":"Starchiy",
    "gn:cc2":"KZ",
    "gn:country_code":"KZ",
    "gn:dem":-23,
    "gn:feature_class":"P",
    "gn:feature_code":"PPL",
    "gn:name":"Starchiy",
    "gn:population":0,
    "gn:timezone":"Asia/Atyrau",
    "iso:country":"KZ",
    "name:und_x_variant":[
        "Starniy"
    ],
    "wof:name":"Starchiy",
    "wof:placetype":"locality"
},
  "geometry": {"coordinates":[48.68333,46.58333],"type":"Point"}
}