{
  "type": "Feature",
  "properties": {
    "gn:admin1_code":"4.0",
    "gn:asciiname":"Aqqaban",
    "gn:country_code":"KZ",
    "gn:dem":130,
    "gn:feature_class":"P",
    "gn:feature_code":"PPL",
    "gn:name":"Aqqaban",
    "gn:population":0,
    "gn:timezone":"Asia/Aqtobe",
    "iso:country":"KZ",
    "name:und_x_variant":[
        "Akkabak"
    ],
    "wof:name":"Aqqaban",
    "wof:placetype":"locality"
},
  "geometry": {"coordinates":[62.44107,49.85097],"type":"Point"}
}