{
  "type": "Feature",
  "properties": {
    "gn:admin1_code":"0.0",
    "gn:asciiname":"Ak-Tumsuk",
    "gn:country_code":"KZ",
    "gn:dem":167,
    "gn:feature_class":"P",
    "gn:feature_code":"PPL",
    "gn:name":"Ak-Tumsuk",
    "gn:population":0,
    "gn:timezone":"Asia/Almaty",
    "iso:country":"KZ",
    "wof:name":"Ak-Tumsuk",
    "wof:placetype":"locality"
},
  "geometry": {"coordinates":[78.93011,51.36737],"type":"Point"}
}