{
  "type": "Feature",
  "properties": {
    "gn:admin1_code":"6.0",
    "gn:asciiname":"Urnek",
    "gn:country_code":"KZ",
    "gn:dem":19,
    "gn:feature_class":"P",
    "gn:feature_code":"PPL",
    "gn:name":"Urnek",
    "gn:population":0,
    "gn:timezone":"Asia/Atyrau",
    "iso:country":"KZ",
    "wof:name":"Urnek",
    "wof:placetype":"locality"
},
  "geometry": {"coordinates":[53.33954,48.93535],"type":"Point"}
}