{
  "type": "Feature",
  "properties": {
    "gn:admin1_code":"15.0",
    "gn:asciiname":"Solnechnyy",
    "gn:country_code":"KZ",
    "gn:dem":336,
    "gn:feature_class":"P",
    "gn:feature_code":"PPL",
    "gn:name":"Solnechnyy",
    "gn:population":0,
    "gn:timezone":"Asia/Almaty",
    "iso:country":"KZ",
    "name:kaz_x_preferred":[
        "Solnechnyy"
    ],
    "name:kaz_x_variant":[
        "\u0421\u043e\u043b\u043d\u0435\u0447\u043d\u044b\u0439"
    ],
    "wof:name":"Solnechnyy",
    "wof:placetype":"locality"
},
  "geometry": {"coordinates":[82.72084,50.04909],"type":"Point"}
}