{
  "type": "Feature",
  "properties": {
    "gn:admin1_code":"11.0",
    "gn:asciiname":"Ol'ginka",
    "gn:country_code":"KZ",
    "gn:dem":147,
    "gn:feature_class":"P",
    "gn:feature_code":"PPL",
    "gn:name":"Ol\u2019g\u012bnka",
    "gn:population":0,
    "gn:timezone":"Asia/Almaty",
    "iso:country":"KZ",
    "name:kaz_x_preferred":[
        "\u041e\u043b\u044c\u0433\u0438\u043d\u043a\u0430"
    ],
    "name:rus_x_preferred":[
        "\u041e\u043b\u044c\u0433\u0438\u043d\u043e"
    ],
    "name:und_x_variant":[
        "Ol\u2019govka",
        "Ol\u2019ginskiy",
        "Ol\u2019gino",
        "Ol\u2019g\u012bnka"
    ],
    "wof:name":"Ol'ginka",
    "wof:placetype":"locality"
},
  "geometry": {"coordinates":[77.64155,51.96557],"type":"Point"}
}