{
  "type": "Feature",
  "properties": {
    "gn:admin1_code":"12.0",
    "gn:asciiname":"Kreshchyonovka",
    "gn:country_code":"KZ",
    "gn:dem":558,
    "gn:feature_class":"P",
    "gn:feature_code":"PPL",
    "gn:name":"Kreshchyonovka",
    "gn:population":0,
    "gn:timezone":"Asia/Almaty",
    "iso:country":"KZ",
    "name:kaz_x_preferred":[
        "Kreshchyonovka"
    ],
    "name:kaz_x_variant":[
        "\u041a\u0440\u0435\u0449\u0451\u043d\u043e\u0432\u043a\u0430"
    ],
    "wof:name":"Kreshchyonovka",
    "wof:placetype":"locality"
},
  "geometry": {"coordinates":[73.10351,50.6583],"type":"Point"}
}