{
  "type": "Feature",
  "properties": {
    "gn:admin1_code":"7.0",
    "gn:asciiname":"Maslov",
    "gn:country_code":"KZ",
    "gn:dem":16,
    "gn:feature_class":"P",
    "gn:feature_code":"PPL",
    "gn:name":"Maslov",
    "gn:population":0,
    "gn:timezone":"Asia/Oral",
    "iso:country":"KZ",
    "name:eng_x_preferred":[
        "Maslov"
    ],
    "name:rus_x_preferred":[
        "\u041c\u0430\u0441\u043b\u043e\u0432"
    ],
    "name:slv_x_preferred":[
        "Maslov"
    ],
    "name:zho_x_preferred":[
        "\u99ac\u65af\u6d1b\u592b"
    ],
    "wof:name":"Maslov",
    "wof:placetype":"locality"
},
  "geometry": {"coordinates":[48.82556,50.16222],"type":"Point"}
}