{
  "type": "Feature",
  "properties": {
    "gn:admin1_code":"15.0",
    "gn:asciiname":"Zhantay",
    "gn:country_code":"KZ",
    "gn:dem":377,
    "gn:feature_class":"P",
    "gn:feature_code":"PPL",
    "gn:name":"Zhantay",
    "gn:population":0,
    "gn:timezone":"Asia/Almaty",
    "iso:country":"KZ",
    "name:eng_x_preferred":[
        "Zhantay"
    ],
    "name:rus_x_preferred":[
        "\u0416\u0430\u043d\u0442\u0430\u0439"
    ],
    "wof:name":"Zhantay",
    "wof:placetype":"locality"
},
  "geometry": {"coordinates":[82.08456,49.84134],"type":"Point"}
}