{
  "type": "Feature",
  "properties": {
    "gn:admin1_code":"12.0",
    "gn:asciiname":"Pushkino",
    "gn:country_code":"KZ",
    "gn:dem":420,
    "gn:feature_class":"P",
    "gn:feature_code":"PPL",
    "gn:name":"Pushkino",
    "gn:population":0,
    "gn:timezone":"Asia/Almaty",
    "iso:country":"KZ",
    "name:ceb_x_preferred":[
        "Pushkino"
    ],
    "name:sco_x_preferred":[
        "Pushkino"
    ],
    "name:swe_x_preferred":[
        "Pushkino"
    ],
    "name:und_x_variant":[
        "Baronskoye",
        "Pushkinskiy"
    ],
    "wof:name":"Pushkino",
    "wof:placetype":"locality"
},
  "geometry": {"coordinates":[71.61845,49.90017],"type":"Point"}
}