{
  "type": "Feature",
  "properties": {
    "gn:admin1_code":"10.0",
    "gn:asciiname":"Darbaza",
    "gn:country_code":"KZ",
    "gn:dem":430,
    "gn:feature_class":"P",
    "gn:feature_code":"PPL",
    "gn:name":"Darbaza",
    "gn:population":0,
    "gn:timezone":"Asia/Almaty",
    "iso:country":"KZ",
    "name:kaz_x_preferred":[
        "Darbaza"
    ],
    "name:kaz_x_variant":[
        "\u0414\u0430\u0440\u0431\u0430\u0437\u0430"
    ],
    "wof:name":"Darbaza",
    "wof:placetype":"locality"
},
  "geometry": {"coordinates":[69.08266999999999,41.56611],"type":"Point"}
}