{
  "type": "Feature",
  "properties": {
    "gn:admin1_code":"1.0",
    "gn:asciiname":"Arasan",
    "gn:cc2":"KZ",
    "gn:country_code":"KZ",
    "gn:dem":988,
    "gn:feature_class":"P",
    "gn:feature_code":"PPL",
    "gn:name":"Arasan",
    "gn:population":0,
    "gn:timezone":"Asia/Almaty",
    "iso:country":"KZ",
    "name:ceb_x_preferred":[
        "Arasan"
    ],
    "name:kaz_x_preferred":[
        "\u0410\u0440\u0430\u0441\u0430\u043d"
    ],
    "name:mkd_x_preferred":[
        "\u0410\u0440\u0430\u0441\u0430\u043d"
    ],
    "name:msa_x_preferred":[
        "Arasan"
    ],
    "name:rus_x_preferred":[
        "\u0410\u0440\u0430\u0441\u0430\u043d"
    ],
    "name:swe_x_preferred":[
        "Arasan"
    ],
    "name:ukr_x_preferred":[
        "\u0410\u0440\u0430\u0441\u0430\u043d"
    ],
    "name:und_x_variant":[
        "Arasanskiy"
    ],
    "wof:name":"Arasan",
    "wof:placetype":"locality"
},
  "geometry": {"coordinates":[79.355,45.27806],"type":"Point"}
}