{
  "type": "Feature",
  "properties": {
    "gn:admin1_code":"0.0",
    "gn:asciiname":"Zhaksy-Balakty",
    "gn:country_code":"KZ",
    "gn:dem":1,
    "gn:feature_class":"P",
    "gn:feature_code":"PPL",
    "gn:name":"Zhaksy-Balakty",
    "gn:population":0,
    "gn:timezone":"Asia/Oral",
    "iso:country":"KZ",
    "wof:name":"Zhaksy-Balakty",
    "wof:placetype":"locality"
},
  "geometry": {"coordinates":[51.91667,49.58333],"type":"Point"}
}