{
  "type": "Feature",
  "properties": {
    "gn:admin1_code":"10.0",
    "gn:asciiname":"Aynatas",
    "gn:country_code":"KZ",
    "gn:dem":591,
    "gn:feature_class":"P",
    "gn:feature_code":"PPL",
    "gn:name":"Aynatas",
    "gn:population":0,
    "gn:timezone":"Asia/Almaty",
    "iso:country":"KZ",
    "name:rus_x_preferred":[
        "\u0410\u0439\u043d\u0430\u0442\u0430\u0441"
    ],
    "name:und_x_variant":[
        "Anaas",
        "Ayna-Tash",
        "Aynatas"
    ],
    "wof:name":"Aynatas",
    "wof:placetype":"locality"
},
  "geometry": {"coordinates":[69.32474000000001,41.7142],"type":"Point"}
}