{
  "type": "Feature",
  "properties": {
    "gn:admin1_code":"0.0",
    "gn:asciiname":"Varvarinskoye",
    "gn:country_code":"KZ",
    "gn:dem":139,
    "gn:feature_class":"P",
    "gn:feature_code":"PPL",
    "gn:name":"Varvarinskoye",
    "gn:population":0,
    "gn:timezone":"Asia/Qyzylorda",
    "iso:country":"KZ",
    "name:eng_x_preferred":[
        "Varvarinskoye"
    ],
    "name:rus_x_preferred":[
        "\u0412\u0430\u0440\u0432\u0430\u0440\u0438\u043d\u043a\u0430"
    ],
    "name:und_x_variant":[
        "Varvarinka",
        "Varvarinskoye"
    ],
    "wof:name":"Varvarinskoye",
    "wof:placetype":"locality"
},
  "geometry": {"coordinates":[62.5255,53.92529],"type":"Point"}
}