{
  "type": "Feature",
  "properties": {
    "gn:admin1_code":"0.0",
    "gn:asciiname":"Kuskopa",
    "gn:country_code":"KZ",
    "gn:dem":248,
    "gn:feature_class":"P",
    "gn:feature_code":"PPL",
    "gn:name":"Kuskopa",
    "gn:population":0,
    "gn:timezone":"Asia/Qyzylorda",
    "iso:country":"KZ",
    "name:eng_x_preferred":[
        "Kuskopa"
    ],
    "name:rus_x_preferred":[
        "\u041a\u0443\u0441\u043a\u043e\u043f\u0430"
    ],
    "wof:name":"Kuskopa",
    "wof:placetype":"locality"
},
  "geometry": {"coordinates":[61.45,51.81667],"type":"Point"}
}