{
  "type": "Feature",
  "properties": {
    "gn:admin1_code":"16.0",
    "gn:asciiname":"Bayskulan",
    "gn:country_code":"KZ",
    "gn:dem":186,
    "gn:feature_class":"P",
    "gn:feature_code":"PPL",
    "gn:name":"Bayskulan",
    "gn:population":0,
    "gn:timezone":"Asia/Almaty",
    "iso:country":"KZ",
    "wof:name":"Bayskulan",
    "wof:placetype":"locality"
},
  "geometry": {"coordinates":[68.51666999999999,53.83333],"type":"Point"}
}