{
  "type": "Feature",
  "properties": {
    "gn:admin1_code":"16.0",
    "gn:asciiname":"Zhumysshi",
    "gn:country_code":"KZ",
    "gn:dem":57,
    "gn:feature_class":"P",
    "gn:feature_code":"PPL",
    "gn:name":"Zhumysshi",
    "gn:population":0,
    "gn:timezone":"Asia/Almaty",
    "iso:country":"KZ",
    "name:eng_x_preferred":[
        "Zhumysshi"
    ],
    "name:kaz_x_preferred":[
        "Zhumysshy"
    ],
    "name:kaz_x_variant":[
        "\u0416\u04b1\u043c\u044b\u0441\u0448\u044b"
    ],
    "name:rus_x_preferred":[
        "\u0416\u0443\u043c\u044b\u0441\u0448\u0438"
    ],
    "wof:name":"Zhumysshi",
    "wof:placetype":"locality"
},
  "geometry": {"coordinates":[72.96654000000002,53.9736],"type":"Point"}
}