{
  "type": "Feature",
  "properties": {
    "gn:admin1_code":"3.0",
    "gn:asciiname":"Nevskoe",
    "gn:country_code":"KZ",
    "gn:dem":294,
    "gn:feature_class":"P",
    "gn:feature_code":"PPL",
    "gn:name":"Nevskoe",
    "gn:population":0,
    "gn:timezone":"Asia/Almaty",
    "iso:country":"KZ",
    "name:eng_x_preferred":[
        "Nevskiy"
    ],
    "name:kaz_x_preferred":[
        "Nevskoe"
    ],
    "name:kaz_x_variant":[
        "\u041d\u0435\u0432\u0441\u043a\u043e\u0435"
    ],
    "name:rus_x_preferred":[
        "\u041d\u0435\u0432\u0441\u043a\u043e\u0435"
    ],
    "name:und_x_variant":[
        "Nevskoye"
    ],
    "wof:name":"Nevskoe",
    "wof:placetype":"locality"
},
  "geometry": {"coordinates":[70.75439,53.0194],"type":"Point"}
}