{
  "type": "Feature",
  "properties": {
    "gn:admin1_code":"0.0",
    "gn:asciiname":"Karasu",
    "gn:country_code":"KZ",
    "gn:dem":144,
    "gn:feature_class":"P",
    "gn:feature_code":"PPL",
    "gn:name":"Karasu",
    "gn:population":0,
    "gn:timezone":"Asia/Almaty",
    "iso:country":"KZ",
    "name:eng_x_preferred":[
        "Karasu"
    ],
    "name:rus_x_preferred":[
        "\u041a\u0430\u0440\u0430\u0441\u0443"
    ],
    "wof:name":"Karasu",
    "wof:placetype":"locality"
},
  "geometry": {"coordinates":[65.37494000000001,50.28516],"type":"Point"}
}