{
  "type": "Feature",
  "properties": {
    "gn:admin1_code":"6.0",
    "gn:asciiname":"Bayda",
    "gn:country_code":"KZ",
    "gn:dem":-27,
    "gn:feature_class":"P",
    "gn:feature_code":"PPL",
    "gn:name":"Bayda",
    "gn:population":0,
    "gn:timezone":"Asia/Atyrau",
    "iso:country":"KZ",
    "wof:name":"Bayda",
    "wof:placetype":"locality"
},
  "geometry": {"coordinates":[48.76389,46.59444000000001],"type":"Point"}
}