{
  "type": "Feature",
  "properties": {
    "gn:admin1_code":"17.0",
    "gn:asciiname":"Ornek",
    "gn:country_code":"KZ",
    "gn:dem":655,
    "gn:feature_class":"P",
    "gn:feature_code":"PPL",
    "gn:name":"Ornek",
    "gn:population":0,
    "gn:timezone":"Asia/Almaty",
    "iso:country":"KZ",
    "name:kaz_x_preferred":[
        "\u00d6rnek"
    ],
    "name:kaz_x_variant":[
        "\u04e8\u0440\u043d\u0435\u043a"
    ],
    "name:rus_x_preferred":[
        "\u041e\u0440\u043d\u0435\u043a"
    ],
    "wof:name":"Ornek",
    "wof:placetype":"locality"
},
  "geometry": {"coordinates":[72.15174,42.97127],"type":"Point"}
}