{
  "type": "Feature",
  "properties": {
    "gn:admin1_code":"15.0",
    "gn:asciiname":"Qarghyba",
    "gn:country_code":"KZ",
    "gn:dem":547,
    "gn:feature_class":"P",
    "gn:feature_code":"PPL",
    "gn:name":"Qarghyba",
    "gn:population":0,
    "gn:timezone":"Asia/Almaty",
    "iso:country":"KZ",
    "name:kaz_x_preferred":[
        "Qarghyba"
    ],
    "name:kaz_x_variant":[
        "\u049a\u0430\u0440\u0493\u044b\u0431\u0430"
    ],
    "name:rus_x_preferred":[
        "\u0416\u0430\u043d\u0430\u0436\u043e\u043b"
    ],
    "name:und_x_variant":[
        "Sotsial",
        "Zhanazhol"
    ],
    "wof:name":"Qarghyba",
    "wof:placetype":"locality"
},
  "geometry": {"coordinates":[82.83626,47.73723],"type":"Point"}
}