{
  "type": "Feature",
  "properties": {
    "gn:admin1_code":"15.0",
    "gn:asciiname":"Kyzylkain",
    "gn:country_code":"KZ",
    "gn:dem":574,
    "gn:feature_class":"P",
    "gn:feature_code":"PPL",
    "gn:name":"Kyzylkain",
    "gn:population":0,
    "gn:timezone":"Asia/Almaty",
    "iso:country":"KZ",
    "name:rus_x_preferred":[
        "\u041a\u044b\u0437\u044b\u043b\u043a\u0430\u0438\u043d"
    ],
    "wof:name":"Kyzylkain",
    "wof:placetype":"locality"
},
  "geometry": {"coordinates":[82.801,47.71032],"type":"Point"}
}