{
  "type": "Feature",
  "properties": {
    "gn:admin1_code":"6.0",
    "gn:asciiname":"Tingizbay",
    "gn:country_code":"KZ",
    "gn:dem":-16,
    "gn:feature_class":"P",
    "gn:feature_code":"PPL",
    "gn:name":"Tingizbay",
    "gn:population":0,
    "gn:timezone":"Asia/Atyrau",
    "iso:country":"KZ",
    "name:und_x_variant":[
        "Tingisbay",
        "Tingizbay"
    ],
    "wof:name":"Tingizbay",
    "wof:placetype":"locality"
},
  "geometry": {"coordinates":[50.55,48.35],"type":"Point"}
}