{
  "type": "Feature",
  "properties": {
    "gn:admin1_code":"15.0",
    "gn:asciiname":"Korosteli",
    "gn:country_code":"KZ",
    "gn:dem":243,
    "gn:feature_class":"P",
    "gn:feature_code":"PPL",
    "gn:name":"Korosteli",
    "gn:population":0,
    "gn:timezone":"Asia/Almaty",
    "iso:country":"KZ",
    "name:eng_x_preferred":[
        "Korosteli"
    ],
    "name:kaz_x_preferred":[
        "Korostel\u012b"
    ],
    "name:kaz_x_variant":[
        "\u041a\u043e\u0440\u043e\u0441\u0442\u0435\u043b\u0438"
    ],
    "name:rus_x_preferred":[
        "\u041a\u043e\u0440\u043e\u0441\u0442\u0435\u043b\u0438"
    ],
    "name:und_x_variant":[
        "Korostel\u00ebvskiy",
        "Korosteli"
    ],
    "wof:name":"Korosteli",
    "wof:placetype":"locality"
},
  "geometry": {"coordinates":[80.99977,51.04737],"type":"Point"}
}