{
  "type": "Feature",
  "properties": {
    "gn:admin1_code":"12.0",
    "gn:asciiname":"Aytymbet",
    "gn:country_code":"KZ",
    "gn:dem":959,
    "gn:feature_class":"P",
    "gn:feature_code":"PPL",
    "gn:name":"Aytymbet",
    "gn:population":0,
    "gn:timezone":"Asia/Almaty",
    "iso:country":"KZ",
    "wof:name":"Aytymbet",
    "wof:placetype":"locality"
},
  "geometry": {"coordinates":[75.93333,49.03333],"type":"Point"}
}