{
  "type": "Feature",
  "properties": {
    "gn:admin1_code":"13.0",
    "gn:asciiname":"Obaghan",
    "gn:country_code":"KZ",
    "gn:dem":190,
    "gn:feature_class":"P",
    "gn:feature_code":"PPL",
    "gn:name":"Obaghan",
    "gn:population":0,
    "gn:timezone":"Asia/Qyzylorda",
    "iso:country":"KZ",
    "name:kaz_x_preferred":[
        "Obaghan"
    ],
    "name:kaz_x_variant":[
        "\u041e\u0431\u0430\u0493\u0430\u043d"
    ],
    "wof:name":"Obaghan",
    "wof:placetype":"locality"
},
  "geometry": {"coordinates":[64.29521,53.07952],"type":"Point"}
}