{
  "type": "Feature",
  "properties": {
    "gn:admin1_code":"17.0",
    "gn:asciiname":"Il'inskoye",
    "gn:country_code":"KZ",
    "gn:dem":406,
    "gn:feature_class":"P",
    "gn:feature_code":"PPL",
    "gn:name":"Il\u2019inskoye",
    "gn:population":0,
    "gn:timezone":"Asia/Almaty",
    "iso:country":"KZ",
    "wof:name":"Il'inskoye",
    "wof:placetype":"locality"
},
  "geometry": {"coordinates":[73.59999999999999,44.08333],"type":"Point"}
}