{
  "type": "Feature",
  "properties": {
    "gn:admin1_code":"16.0",
    "gn:asciiname":"Botay",
    "gn:country_code":"KZ",
    "gn:dem":259,
    "gn:feature_class":"P",
    "gn:feature_code":"PPL",
    "gn:name":"Botay",
    "gn:population":0,
    "gn:timezone":"Asia/Almaty",
    "iso:country":"KZ",
    "name:rus_x_preferred":[
        "\u0411\u043e\u0442\u0430\u0439"
    ],
    "wof:name":"Botay",
    "wof:placetype":"locality"
},
  "geometry": {"coordinates":[67.64713,53.30441999999999],"type":"Point"}
}