{
  "type": "Feature",
  "properties": {
    "gn:admin1_code":"10.0",
    "gn:asciiname":"Sotsialistik Kazakhstan",
    "gn:country_code":"KZ",
    "gn:dem":273,
    "gn:feature_class":"P",
    "gn:feature_code":"PPL",
    "gn:name":"Sotsialistik Kazakhstan",
    "gn:population":0,
    "gn:timezone":"Asia/Almaty",
    "iso:country":"KZ",
    "name:kaz_x_preferred":[
        "Sots\u012bal\u012bstik Qazaqstan"
    ],
    "name:kaz_x_variant":[
        "\u0421\u043e\u0446\u0438\u0430\u043b\u0438\u0441\u0442\u0456\u043a \u049a\u0430\u0437\u0430\u049b\u0441\u0442\u0430\u043d"
    ],
    "name:rus_x_preferred":[
        "\u0421\u043e\u0446\u0438\u0430\u043b\u0438\u0441\u0442\u0438\u043a \u041a\u0430\u0437\u0430\u0445\u0441\u0442\u0430\u043d"
    ],
    "name:und_x_variant":[
        "Sotsialisticheskiy Kazakhstan",
        "Sotskazakhstan",
        "Sotsialistik Kazakhstan"
    ],
    "name:uzb_x_preferred":[
        "Qokbuloq"
    ],
    "wof:name":"Sotsialistik Kazakhstan",
    "wof:placetype":"locality"
},
  "geometry": {"coordinates":[68.65994999999999,41.05486],"type":"Point"}
}