{
  "type": "Feature",
  "properties": {
    "gn:admin1_code":"4.0",
    "gn:asciiname":"Karagandy",
    "gn:cc2":"KZ",
    "gn:country_code":"KZ",
    "gn:dem":247,
    "gn:feature_class":"P",
    "gn:feature_code":"PPL",
    "gn:name":"Karagandy",
    "gn:population":0,
    "gn:timezone":"Asia/Aqtobe",
    "iso:country":"KZ",
    "name:kaz_x_preferred":[
        "Qaraghandy"
    ],
    "wof:name":"Karagandy",
    "wof:placetype":"locality"
},
  "geometry": {"coordinates":[59.125,48.35972],"type":"Point"}
}