{
  "type": "Feature",
  "properties": {
    "gn:admin1_code":"11.0",
    "gn:asciiname":"Panfilovo",
    "gn:country_code":"KZ",
    "gn:dem":121,
    "gn:feature_class":"P",
    "gn:feature_code":"PPL",
    "gn:name":"Panfilovo",
    "gn:population":0,
    "gn:timezone":"Asia/Almaty",
    "iso:country":"KZ",
    "name:eng_x_preferred":[
        "Panf\u012blovo"
    ],
    "name:kaz_x_preferred":[
        "\u041f\u0430\u043d\u0444\u0438\u043b\u043e\u0432\u043e"
    ],
    "name:rus_x_preferred":[
        "\u041f\u0430\u043d\u0444\u0438\u043b\u043e\u0432\u043e"
    ],
    "name:ukr_x_preferred":[
        "\u041f\u0430\u043d\u0444\u0456\u043b\u043e\u0432\u043e"
    ],
    "name:und_x_variant":[
        "Imeni Panfilova",
        "Panf\u012blovsk\u012by",
        "Panfilovo"
    ],
    "wof:name":"Panfilovo",
    "wof:placetype":"locality"
},
  "geometry": {"coordinates":[74.8976,53.2412],"type":"Point"}
}