{
  "type": "Feature",
  "properties": {
    "gn:admin1_code":"17.0",
    "gn:asciiname":"Aul Ayt-Kozha",
    "gn:country_code":"KZ",
    "gn:dem":530,
    "gn:feature_class":"P",
    "gn:feature_code":"PPL",
    "gn:name":"Aul Ayt-Kozha",
    "gn:population":0,
    "gn:timezone":"Asia/Almaty",
    "iso:country":"KZ",
    "wof:name":"Aul Ayt-Kozha",
    "wof:placetype":"locality"
},
  "geometry": {"coordinates":[74.13333,43.28333],"type":"Point"}
}