{
  "type": "Feature",
  "properties": {
    "gn:admin1_code":"16.0",
    "gn:asciiname":"Sugurbay",
    "gn:country_code":"KZ",
    "gn:dem":167,
    "gn:feature_class":"P",
    "gn:feature_code":"PPL",
    "gn:name":"Sugurbay",
    "gn:population":0,
    "gn:timezone":"Asia/Almaty",
    "iso:country":"KZ",
    "name:eng_x_preferred":[
        "Sugurbay"
    ],
    "name:kaz_x_preferred":[
        "S\u00fcgirbay"
    ],
    "name:kaz_x_variant":[
        "\u0421\u04af\u0433\u0456\u0440\u0431\u0430\u0439"
    ],
    "name:rus_x_preferred":[
        "\u0421\u0443\u0433\u0443\u0440\u0431\u0430\u0439"
    ],
    "wof:name":"Sugurbay",
    "wof:placetype":"locality"
},
  "geometry": {"coordinates":[70.93886999999999,53.49977],"type":"Point"}
}