{
  "type": "Feature",
  "properties": {
    "gn:admin1_code":"15.0",
    "gn:asciiname":"Andronovka",
    "gn:country_code":"KZ",
    "gn:dem":292,
    "gn:feature_class":"P",
    "gn:feature_code":"PPL",
    "gn:name":"Andronovka",
    "gn:population":0,
    "gn:timezone":"Asia/Almaty",
    "iso:country":"KZ",
    "name:eng_x_preferred":[
        "Andronovka"
    ],
    "name:kaz_x_preferred":[
        "\u0410\u043d\u0434\u0440\u043e\u043d\u043e\u0432\u043a\u0430"
    ],
    "name:rus_x_preferred":[
        "\u0410\u043d\u0434\u0440\u043e\u043d\u043e\u0432\u043a\u0430"
    ],
    "wof:name":"Andronovka",
    "wof:placetype":"locality"
},
  "geometry": {"coordinates":[81.26534000000002,50.81163],"type":"Point"}
}