{
  "type": "Feature",
  "properties": {
    "iso:country":"KZ",
    "name:kaz_x_preferred":[
        "\u0428\u0430\u0440\u044b\u043d"
    ],
    "name:rus_x_preferred":[
        "\u0427\u0430\u0440\u044b\u043d"
    ],
    "name:und_x_variant":[
        "Char\u00f6n"
    ],
    "qs:gn_country":"KZ",
    "qs:gn_fcode":"PPL",
    "qs:gn_pop":0,
    "qs:name":"Charyn",
    "qs:name_adm0":"Kazakhstan",
    "qs:name_adm1":"Almaty",
    "qs:photos":27,
    "qs:photos_1k":5,
    "qs:photos_9k":1,
    "qs:photos_9r":2,
    "qs:photos_all":27,
    "qs:photos_sr":2,
    "qs:placetype":"Town",
    "qs:pop_sr":"3",
    "qs:woe_adm0":23424871,
    "wof:name":"Charyn",
    "wof:placetype":"locality"
},
  "geometry": {"coordinates":[79.39064,43.77349],"type":"Point"}
}