{
  "type": "Feature",
  "properties": {
    "gn:admin1_code":"13.0",
    "gn:asciiname":"Loba",
    "gn:country_code":"KZ",
    "gn:dem":92,
    "gn:feature_class":"P",
    "gn:feature_code":"PPL",
    "gn:name":"Loba",
    "gn:population":0,
    "gn:timezone":"Asia/Qyzylorda",
    "iso:country":"KZ",
    "name:eng_x_preferred":[
        "Loba"
    ],
    "name:kaz_x_preferred":[
        "\u041b\u043e\u0431\u0430"
    ],
    "name:rus_x_preferred":[
        "\u041b\u043e\u0431\u0430"
    ],
    "name:und_x_variant":[
        "Doba",
        "Loba"
    ],
    "wof:name":"Loba",
    "wof:placetype":"locality"
},
  "geometry": {"coordinates":[64.70751,54.19756],"type":"Point"}
}