{
  "type": "Feature",
  "properties": {
    "gn:admin1_code":"10.0",
    "gn:asciiname":"Badam Nomer Odin",
    "gn:country_code":"KZ",
    "gn:dem":513,
    "gn:feature_class":"P",
    "gn:feature_code":"PPL",
    "gn:name":"Badam Nomer Odin",
    "gn:population":0,
    "gn:timezone":"Asia/Almaty",
    "iso:country":"KZ",
    "name:rus_x_preferred":[
        "\u0411\u0430\u0434\u0430\u043c \u041d\u043e\u043c\u0435\u0440 \u041e\u0434\u0438\u043d"
    ],
    "wof:name":"Badam Nomer Odin",
    "wof:placetype":"locality"
},
  "geometry": {"coordinates":[69.60075999999999,42.27461],"type":"Point"}
}