{
  "type": "Feature",
  "properties": {
    "gn:admin1_code":"0.0",
    "gn:asciiname":"Kalpe",
    "gn:country_code":"KZ",
    "gn:dem":440,
    "gn:feature_class":"P",
    "gn:feature_code":"PPL",
    "gn:name":"Kalpe",
    "gn:population":0,
    "gn:timezone":"Asia/Almaty",
    "iso:country":"KZ",
    "name:rus_x_preferred":[
        "\u041a\u0430\u043b\u043f\u0435"
    ],
    "wof:name":"Kalpe",
    "wof:placetype":"locality"
},
  "geometry": {"coordinates":[77.91667,45.08333],"type":"Point"}
}