{
  "type": "Feature",
  "properties": {
    "gn:admin1_code":"15.0",
    "gn:asciiname":"Novonikolayevka",
    "gn:country_code":"KZ",
    "gn:dem":245,
    "gn:feature_class":"P",
    "gn:feature_code":"PPL",
    "gn:name":"Novonikolayevka",
    "gn:population":0,
    "gn:timezone":"Asia/Almaty",
    "iso:country":"KZ",
    "name:kaz_x_preferred":[
        "\u041d\u043e\u0432\u043e\u043d\u0438\u043a\u043e\u043b\u0430\u0435\u0432\u043a\u0430"
    ],
    "name:und_x_variant":[
        "Nikolayevskiy",
        "Novon\u012bkolaevka"
    ],
    "wof:name":"Novonikolayevka",
    "wof:placetype":"locality"
},
  "geometry": {"coordinates":[79.40451999999998,51.06786],"type":"Point"}
}