{
  "type": "Feature",
  "properties": {
    "gn:admin1_code":"11.0",
    "gn:asciiname":"Rebrovka",
    "gn:country_code":"KZ",
    "gn:dem":105,
    "gn:feature_class":"P",
    "gn:feature_code":"PPL",
    "gn:name":"Rebrovka",
    "gn:population":0,
    "gn:timezone":"Asia/Almaty",
    "iso:country":"KZ",
    "name:eng_x_preferred":[
        "Rebrovka"
    ],
    "name:kaz_x_preferred":[
        "\u0420\u0435\u0431\u0440\u043e\u0432\u043a\u0430"
    ],
    "name:rus_x_preferred":[
        "\u0420\u0435\u0431\u0440\u043e\u0432\u043a\u0430"
    ],
    "name:und_x_variant":[
        "Rebovka"
    ],
    "wof:name":"Rebrovka",
    "wof:placetype":"locality"
},
  "geometry": {"coordinates":[76.70695000000001,52.39565],"type":"Point"}
}