{
  "type": "Feature",
  "properties": {
    "gn:admin1_code":"0.0",
    "gn:asciiname":"Berezovka",
    "gn:country_code":"KZ",
    "gn:dem":409,
    "gn:feature_class":"P",
    "gn:feature_code":"PPL",
    "gn:name":"Berezovka",
    "gn:population":0,
    "gn:timezone":"Asia/Almaty",
    "iso:country":"KZ",
    "name:ceb_x_preferred":[
        "Berezovka"
    ],
    "name:lav_x_preferred":[
        "Berezovka"
    ],
    "name:lit_x_preferred":[
        "Berezovka"
    ],
    "name:swe_x_preferred":[
        "Berezovka"
    ],
    "name:und_x_variant":[
        "Ber\u00ebzovskiy"
    ],
    "wof:name":"Berezovka",
    "wof:placetype":"locality"
},
  "geometry": {"coordinates":[82.63333,50.58333],"type":"Point"}
}