{
  "type": "Feature",
  "properties": {
    "gn:admin1_code":"11.0",
    "gn:asciiname":"Tat'yanovka",
    "gn:country_code":"KZ",
    "gn:dem":142,
    "gn:feature_class":"P",
    "gn:feature_code":"PPL",
    "gn:name":"Tat\u2019yanovka",
    "gn:population":0,
    "gn:timezone":"Asia/Almaty",
    "iso:country":"KZ",
    "name:kaz_x_preferred":[
        "Tat\u2019yanovka"
    ],
    "name:kaz_x_variant":[
        "\u0422\u0430\u0442\u044c\u044f\u043d\u043e\u0432\u043a\u0430"
    ],
    "wof:name":"Tat'yanovka",
    "wof:placetype":"locality"
},
  "geometry": {"coordinates":[78.3107,52.4358],"type":"Point"}
}