{
  "type": "Feature",
  "properties": {
    "gn:admin1_code":"14.0",
    "gn:asciiname":"Kabylbau",
    "gn:country_code":"KZ",
    "gn:dem":134,
    "gn:feature_class":"P",
    "gn:feature_code":"PPL",
    "gn:name":"Kabylbau",
    "gn:population":0,
    "gn:timezone":"Asia/Qyzylorda",
    "iso:country":"KZ",
    "wof:name":"Kabylbau",
    "wof:placetype":"locality"
},
  "geometry": {"coordinates":[66.05444,44.69417],"type":"Point"}
}