{
  "type": "Feature",
  "properties": {
    "gn:admin1_code":"14.0",
    "gn:asciiname":"Assa",
    "gn:country_code":"KZ",
    "gn:dem":511,
    "gn:feature_class":"P",
    "gn:feature_code":"PPL",
    "gn:name":"Assa",
    "gn:population":0,
    "gn:timezone":"Asia/Almaty",
    "iso:country":"KZ",
    "name:kaz_x_preferred":[
        "Asa"
    ],
    "name:kaz_x_variant":[
        "\u0410\u0441\u0430"
    ],
    "name:rus_x_preferred":[
        "\u0410\u0441\u0441\u0430"
    ],
    "wof:name":"Assa",
    "wof:placetype":"locality"
},
  "geometry": {"coordinates":[71.14819,43.03783],"type":"Point"}
}