{
  "type": "Feature",
  "properties": {
    "gn:admin1_code":"16.0",
    "gn:asciiname":"Yubileynoye",
    "gn:country_code":"KZ",
    "gn:dem":263,
    "gn:feature_class":"P",
    "gn:feature_code":"PPL",
    "gn:name":"Yubileynoye",
    "gn:population":0,
    "gn:timezone":"Asia/Almaty",
    "iso:country":"KZ",
    "name:rus_x_preferred":[
        "\u042e\u0431\u0438\u043b\u0435\u0439\u043d\u043e\u0435"
    ],
    "wof:name":"Yubileynoye",
    "wof:placetype":"locality"
},
  "geometry": {"coordinates":[67.26839,52.58249],"type":"Point"}
}