{
  "type": "Feature",
  "properties": {
    "gn:admin1_code":"12.0",
    "gn:asciiname":"Togam",
    "gn:country_code":"KZ",
    "gn:dem":611,
    "gn:feature_class":"P",
    "gn:feature_code":"PPL",
    "gn:name":"Togam",
    "gn:population":0,
    "gn:timezone":"Asia/Almaty",
    "iso:country":"KZ",
    "wof:name":"Togam",
    "wof:placetype":"locality"
},
  "geometry": {"coordinates":[73.59999999999999,49.78333],"type":"Point"}
}