{
  "type": "Feature",
  "properties": {
    "gn:admin1_code":"10.0",
    "gn:asciiname":"Khatynkopir",
    "gn:country_code":"KZ",
    "gn:dem":491,
    "gn:feature_class":"P",
    "gn:feature_code":"PPL",
    "gn:name":"Khatynkopir",
    "gn:population":0,
    "gn:timezone":"Asia/Almaty",
    "iso:country":"KZ",
    "name:und_x_variant":[
        "Imeni Tel\u2019mana",
        "Khatynkupyr",
        "Khatynkopir"
    ],
    "wof:name":"Khatynkopir",
    "wof:placetype":"locality"
},
  "geometry": {"coordinates":[69.56667,42.35],"type":"Point"}
}