{
  "type": "Feature",
  "properties": {
    "gn:admin1_code":"0.0",
    "gn:asciiname":"Zabrodin",
    "gn:country_code":"KZ",
    "gn:dem":20,
    "gn:feature_class":"P",
    "gn:feature_code":"PPL",
    "gn:name":"Zabrodin",
    "gn:population":0,
    "gn:timezone":"Asia/Oral",
    "iso:country":"KZ",
    "wof:name":"Zabrodin",
    "wof:placetype":"locality"
},
  "geometry": {"coordinates":[50.81667,50.61667],"type":"Point"}
}