{
  "type": "Feature",
  "properties": {
    "gn:admin1_code":"15.0",
    "gn:asciiname":"Smetanino",
    "gn:country_code":"KZ",
    "gn:dem":435,
    "gn:feature_class":"P",
    "gn:feature_code":"PPL",
    "gn:name":"Smetanino",
    "gn:population":0,
    "gn:timezone":"Asia/Almaty",
    "iso:country":"KZ",
    "name:kaz_x_preferred":[
        "Smetan\u012bno"
    ],
    "name:kaz_x_variant":[
        "\u0421\u043c\u0435\u0442\u0430\u043d\u0438\u043d\u043e"
    ],
    "wof:name":"Smetanino",
    "wof:placetype":"locality"
},
  "geometry": {"coordinates":[82.32236999999998,50.23387],"type":"Point"}
}