{
  "type": "Feature",
  "properties": {
    "gn:admin1_code":"12.0",
    "gn:asciiname":"Qayraqty",
    "gn:country_code":"KZ",
    "gn:dem":694,
    "gn:feature_class":"P",
    "gn:feature_code":"PPL",
    "gn:name":"Qayraqty",
    "gn:population":0,
    "gn:timezone":"Asia/Almaty",
    "iso:country":"KZ",
    "name:kaz_x_preferred":[
        "Qayraqty"
    ],
    "name:kaz_x_variant":[
        "\u049a\u0430\u0439\u0440\u0430\u049b\u0442\u044b"
    ],
    "name:rus_x_preferred":[
        "\u041a\u0430\u0439\u0440\u0430\u043a\u0442\u044b"
    ],
    "name:und_x_variant":[
        "Kayrakty"
    ],
    "wof:name":"Qayraqty",
    "wof:placetype":"locality"
},
  "geometry": {"coordinates":[73.60373,48.84857],"type":"Point"}
}