{
  "type": "Feature",
  "properties": {
    "gn:admin1_code":"1.0",
    "gn:asciiname":"Sungqar",
    "gn:country_code":"KZ",
    "gn:dem":1212,
    "gn:feature_class":"P",
    "gn:feature_code":"PPL",
    "gn:name":"Sungqar",
    "gn:population":0,
    "gn:timezone":"Asia/Almaty",
    "iso:country":"KZ",
    "name:kaz_x_preferred":[
        "Sungqar"
    ],
    "name:kaz_x_variant":[
        "\u0421\u04b1\u04a3\u049b\u0430\u0440"
    ],
    "name:rus_x_preferred":[
        "\u0428\u0443\u043d\u043a\u044b\u0440"
    ],
    "name:und_x_variant":[
        "Zhungar",
        "Shunkor",
        "Shunkar",
        "Shunkyr"
    ],
    "wof:name":"Sungqar",
    "wof:placetype":"locality"
},
  "geometry": {"coordinates":[80.16604,43.47821],"type":"Point"}
}