{
  "type": "Feature",
  "properties": {
    "gn:admin1_code":"17.0",
    "gn:asciiname":"Sugandy",
    "gn:country_code":"KZ",
    "gn:dem":891,
    "gn:feature_class":"P",
    "gn:feature_code":"PPL",
    "gn:name":"Sugandy",
    "gn:population":0,
    "gn:timezone":"Asia/Almaty",
    "iso:country":"KZ",
    "name:kaz_x_preferred":[
        "\u0421\u043e\u0493\u044b\u043d\u0434\u044b"
    ],
    "name:rus_x_preferred":[
        "\u0421\u0443\u0433\u0430\u043d\u0434\u044b"
    ],
    "name:und_x_variant":[
        "Sogindy",
        "Sugandy",
        "Soghyndy"
    ],
    "wof:name":"Sugandy",
    "wof:placetype":"locality"
},
  "geometry": {"coordinates":[74.61494,43.44273],"type":"Point"}
}