{
  "type": "Feature",
  "properties": {
    "gn:admin1_code":"4.0",
    "gn:asciiname":"Karagandy-Say",
    "gn:country_code":"KZ",
    "gn:dem":191,
    "gn:feature_class":"P",
    "gn:feature_code":"PPL",
    "gn:name":"Karagandy-Say",
    "gn:population":0,
    "gn:timezone":"Asia/Oral",
    "iso:country":"KZ",
    "name:und_x_variant":[
        "Karagandy-Sai",
        "Karagandy-Say"
    ],
    "wof:name":"Karagandy-Say",
    "wof:placetype":"locality"
},
  "geometry": {"coordinates":[54.93333000000001,48.66667],"type":"Point"}
}