{
  "type": "Feature",
  "properties": {
    "gn:admin1_code":"4.0",
    "gn:asciiname":"Rodniki",
    "gn:country_code":"KZ",
    "gn:dem":304,
    "gn:feature_class":"P",
    "gn:feature_code":"PPL",
    "gn:name":"Rodniki",
    "gn:population":0,
    "gn:timezone":"Asia/Aqtobe",
    "iso:country":"KZ",
    "name:eng_x_preferred":[
        "Rodniki"
    ],
    "name:rus_x_preferred":[
        "\u0420\u043e\u0434\u043d\u0438\u043a\u0438"
    ],
    "wof:name":"Rodniki",
    "wof:placetype":"locality"
},
  "geometry": {"coordinates":[58.42061,49.18037],"type":"Point"}
}