{
  "type": "Feature",
  "properties": {
    "gn:admin1_code":"0.0",
    "gn:asciiname":"Talap",
    "gn:country_code":"KZ",
    "gn:dem":22,
    "gn:feature_class":"P",
    "gn:feature_code":"PPL",
    "gn:name":"Talap",
    "gn:population":0,
    "gn:timezone":"Asia/Oral",
    "iso:country":"KZ",
    "wof:name":"Talap",
    "wof:placetype":"locality"
},
  "geometry": {"coordinates":[51.83333,50.16667],"type":"Point"}
}