{
  "type": "Feature",
  "properties": {
    "gn:admin1_code":"0.0",
    "gn:asciiname":"Makey",
    "gn:country_code":"KZ",
    "gn:dem":73,
    "gn:feature_class":"P",
    "gn:feature_code":"PPL",
    "gn:name":"Makey",
    "gn:population":0,
    "gn:timezone":"Asia/Oral",
    "iso:country":"KZ",
    "wof:name":"Makey",
    "wof:placetype":"locality"
},
  "geometry": {"coordinates":[53.84513000000001,51.08823],"type":"Point"}
}