{
  "type": "Feature",
  "properties": {
    "gn:admin1_code":"0.0",
    "gn:asciiname":"Togyzkuduk",
    "gn:country_code":"KZ",
    "gn:dem":10,
    "gn:feature_class":"P",
    "gn:feature_code":"PPL",
    "gn:name":"Togyzkuduk",
    "gn:population":0,
    "gn:timezone":"Asia/Oral",
    "iso:country":"KZ",
    "wof:name":"Togyzkuduk",
    "wof:placetype":"locality"
},
  "geometry": {"coordinates":[49.18333,50.03333],"type":"Point"}
}