{
  "type": "Feature",
  "properties": {
    "gn:admin1_code":"10.0",
    "gn:asciiname":"Otdeleniye Nomer Odin Sovkhoza Imeni Muratbayeva",
    "gn:country_code":"KZ",
    "gn:dem":300,
    "gn:feature_class":"P",
    "gn:feature_code":"PPLF",
    "gn:name":"Otdeleniye Nomer Odin Sovkhoza Imeni Muratbayeva",
    "gn:population":0,
    "gn:timezone":"Asia/Almaty",
    "iso:country":"KZ",
    "name:rus_x_preferred":[
        "\u041e\u0442\u0434\u0435\u043b\u0435\u043d\u0438\u0435 \u041d\u043e\u043c\u0435\u0440 \u041e\u0434\u0438\u043d \u0421\u043e\u0432\u0445\u043e\u0437\u0430 \u0418\u043c\u0435\u043d\u0438 \u041c\u0443\u0440\u0430\u0442\u0431\u0430\u0435\u0432\u0430"
    ],
    "wof:name":"Otdeleniye Nomer Odin Sovkhoza Imeni Muratbayeva",
    "wof:placetype":"locality"
},
  "geometry": {"coordinates":[68.76801,41.16594],"type":"Point"}
}