{
  "type": "Feature",
  "properties": {
    "gn:admin1_code":"12.0",
    "gn:asciiname":"Karaagash",
    "gn:country_code":"KZ",
    "gn:dem":508,
    "gn:feature_class":"P",
    "gn:feature_code":"PPL",
    "gn:name":"Karaagash",
    "gn:population":0,
    "gn:timezone":"Asia/Almaty",
    "iso:country":"KZ",
    "wof:name":"Karaagash",
    "wof:placetype":"locality"
},
  "geometry": {"coordinates":[70.91608000000002,48.91454],"type":"Point"}
}