{
  "type": "Feature",
  "properties": {
    "gn:admin1_code":"9.0",
    "gn:asciiname":"Turlen",
    "gn:country_code":"KZ",
    "gn:dem":-18,
    "gn:feature_class":"P",
    "gn:feature_code":"PPL",
    "gn:name":"Turlen",
    "gn:population":0,
    "gn:timezone":"Asia/Aqtau",
    "iso:country":"KZ",
    "name:und_x_variant":[
        "Torlun"
    ],
    "wof:name":"Turlen",
    "wof:placetype":"locality"
},
  "geometry": {"coordinates":[51.46667,44.73333],"type":"Point"}
}