{
  "type": "Feature",
  "properties": {
    "gn:admin1_code":"6.0",
    "gn:asciiname":"Sargiz",
    "gn:country_code":"KZ",
    "gn:dem":24,
    "gn:feature_class":"P",
    "gn:feature_code":"PPL",
    "gn:name":"Sargiz",
    "gn:population":0,
    "gn:timezone":"Asia/Atyrau",
    "iso:country":"KZ",
    "wof:name":"Sargiz",
    "wof:placetype":"locality"
},
  "geometry": {"coordinates":[53.66667,48.55],"type":"Point"}
}