{
  "type": "Feature",
  "properties": {
    "gn:admin1_code":"15.0",
    "gn:asciiname":"Mynshunkyr",
    "gn:country_code":"KZ",
    "gn:dem":535,
    "gn:feature_class":"P",
    "gn:feature_code":"PPL",
    "gn:name":"Mynshunkyr",
    "gn:population":0,
    "gn:timezone":"Asia/Almaty",
    "iso:country":"KZ",
    "name:eng_x_preferred":[
        "Mynshunkyr"
    ],
    "name:rus_x_preferred":[
        "\u041c\u044b\u043d\u0448\u0443\u043d\u043a\u044b\u0440"
    ],
    "wof:name":"Mynshunkyr",
    "wof:placetype":"locality"
},
  "geometry": {"coordinates":[82.12026999999998,49.59658],"type":"Point"}
}