{
  "type": "Feature",
  "properties": {
    "gn:admin1_code":"13.0",
    "gn:asciiname":"Sulyagash",
    "gn:country_code":"KZ",
    "gn:dem":182,
    "gn:feature_class":"P",
    "gn:feature_code":"PPL",
    "gn:name":"Sulyagash",
    "gn:population":0,
    "gn:timezone":"Asia/Qyzylorda",
    "iso:country":"KZ",
    "name:rus_x_preferred":[
        "\u0421\u0443\u043b\u044b\u0430\u0433\u0430\u0448"
    ],
    "name:und_x_variant":[
        "Suluagash"
    ],
    "wof:name":"Sulyagash",
    "wof:placetype":"locality"
},
  "geometry": {"coordinates":[65.72955999999999,53.77159],"type":"Point"}
}