{
  "type": "Feature",
  "properties": {
    "gn:admin1_code":"11.0",
    "gn:asciiname":"Alakol",
    "gn:country_code":"KZ",
    "gn:dem":103,
    "gn:feature_class":"P",
    "gn:feature_code":"PPL",
    "gn:name":"Alak\u00f6l",
    "gn:population":0,
    "gn:timezone":"Asia/Almaty",
    "iso:country":"KZ",
    "name:ben_x_preferred":[
        "\u0986\u09b2\u09be\u0995\u09cb\u09b2"
    ],
    "name:ceb_x_preferred":[
        "Alakol"
    ],
    "name:eng_x_preferred":[
        "Alak\u00f6l"
    ],
    "name:fas_x_preferred":[
        "\u0622\u0644\u0627\u06a9\u0648\u0644"
    ],
    "name:heb_x_preferred":[
        "\u05d0\u05d2\u05dd \u05d0\u05dc\u05d0\u05e7\u05d5\u05dc"
    ],
    "name:hin_x_preferred":[
        "\u0905\u0932\u093e\u0915\u094b\u0932 "
    ],
    "name:hun_x_preferred":[
        "Alakol-t\u00f3"
    ],
    "name:ind_x_preferred":[
        "Alakol"
    ],
    "name:kaz_x_preferred":[
        "\u0410\u043b\u0430\u043a\u04e9\u043b"
    ],
    "name:kor_x_preferred":[
        "\uc54c\ub77c\ucf5c"
    ],
    "name:rus_x_preferred":[
        "\u0410\u043b\u0430\u043a\u043e\u043b\u044c"
    ],
    "name:rus_x_variant":[
        "Alakol\u2019"
    ],
    "name:swe_x_preferred":[
        "Alakol"
    ],
    "name:und_x_variant":[
        "XIX Partsezd Atyndaghy",
        "On Toghyzynshy Partsezd Atyndaghy",
        "Apakul\u2019",
        "Ala-Aguly"
    ],
    "name:urd_x_preferred":[
        "\u0627\u06cc\u0644\u0627\u06a9\u0648\u0644"
    ],
    "name:vie_x_preferred":[
        "H\u1ed3 Alakol"
    ],
    "wof:name":"Alakol",
    "wof:placetype":"locality"
},
  "geometry": {"coordinates":[75.92757,54.01897],"type":"Point"}
}