{
  "type": "Feature",
  "properties": {
    "gn:admin1_code":"11.0",
    "gn:asciiname":"Alakol",
    "gn:country_code":"KZ",
    "gn:dem":103,
    "gn:feature_class":"P",
    "gn:feature_code":"PPL",
    "gn:name":"Alak\u00f6l",
    "gn:population":0,
    "gn:timezone":"Asia/Almaty",
    "iso:country":"KZ",
    "name:ceb_x_preferred":[
        "Alakol"
    ],
    "name:eng_x_preferred":[
        "Alak\u00f6l"
    ],
    "name:kaz_x_preferred":[
        "\u0410\u043b\u0430\u043a\u04e9\u043b"
    ],
    "name:rus_x_preferred":[
        "\u0410\u043b\u0430\u043a\u043e\u043b\u044c"
    ],
    "name:rus_x_variant":[
        "Alakol\u2019"
    ],
    "name:swe_x_preferred":[
        "Alakol"
    ],
    "name:und_x_variant":[
        "XIX Partsezd Atyndaghy",
        "On Toghyzynshy Partsezd Atyndaghy",
        "Apakul\u2019",
        "Ala-Aguly"
    ],
    "wof:name":"Alakol",
    "wof:placetype":"locality"
},
  "geometry": {"coordinates":[75.92756999999997,54.01897],"type":"Point"}
}