{
  "type": "Feature",
  "properties": {
    "gn:admin1_code":"11.0",
    "gn:asciiname":"Taldyqamys",
    "gn:country_code":"KZ",
    "gn:dem":137,
    "gn:feature_class":"P",
    "gn:feature_code":"PPL",
    "gn:name":"Taldyqamys",
    "gn:population":0,
    "gn:timezone":"Asia/Almaty",
    "iso:country":"KZ",
    "name:kaz_x_preferred":[
        "Taldyqamys"
    ],
    "name:kaz_x_variant":[
        "\u0422\u0430\u043b\u0434\u044b\u049b\u0430\u043c\u044b\u0441"
    ],
    "name:rus_x_preferred":[
        "\u0422\u0430\u043b\u0434\u044b\u043a\u0430\u043c\u044b\u0441"
    ],
    "name:und_x_variant":[
        "Taldykamys"
    ],
    "wof:name":"Taldyqamys",
    "wof:placetype":"locality"
},
  "geometry": {"coordinates":[74.57939,52.21133],"type":"Point"}
}