{
  "type": "Feature",
  "properties": {
    "gn:admin1_code":"3.0",
    "gn:asciiname":"Karamyshevka",
    "gn:country_code":"KZ",
    "gn:dem":389,
    "gn:feature_class":"P",
    "gn:feature_code":"PPL",
    "gn:name":"Karamyshevka",
    "gn:population":0,
    "gn:timezone":"Asia/Almaty",
    "iso:country":"KZ",
    "name:eng_x_preferred":[
        "Karamyshevka"
    ],
    "name:kaz_x_preferred":[
        "\u041a\u0430\u0440\u0430\u043c\u044b\u0448\u0435\u0432\u043a\u0430"
    ],
    "name:rus_x_preferred":[
        "\u041a\u0430\u0440\u0430\u043c\u044b\u0448\u0435\u0432\u043a\u0430"
    ],
    "wof:name":"Karamyshevka",
    "wof:placetype":"locality"
},
  "geometry": {"coordinates":[69.80275999999999,52.34377],"type":"Point"}
}