{
  "type": "Feature",
  "properties": {
    "gn:admin1_code":"6.0",
    "gn:asciiname":"Kurzhum",
    "gn:country_code":"KZ",
    "gn:dem":-26,
    "gn:feature_class":"P",
    "gn:feature_code":"PPL",
    "gn:name":"Kurzhum",
    "gn:population":0,
    "gn:timezone":"Asia/Atyrau",
    "iso:country":"KZ",
    "wof:name":"Kurzhum",
    "wof:placetype":"locality"
},
  "geometry": {"coordinates":[51.83333,47.43333],"type":"Point"}
}