{
  "type": "Feature",
  "properties": {
    "gn:admin1_code":"0.0",
    "gn:asciiname":"Sar-Kul'",
    "gn:country_code":"KZ",
    "gn:dem":63,
    "gn:feature_class":"P",
    "gn:feature_code":"PPL",
    "gn:name":"Sar-Kul\u2019",
    "gn:population":0,
    "gn:timezone":"Asia/Oral",
    "iso:country":"KZ",
    "wof:name":"Sar-Kul'",
    "wof:placetype":"locality"
},
  "geometry": {"coordinates":[53.39566,50.09532],"type":"Point"}
}