{
  "type": "Feature",
  "properties": {
    "gn:admin1_code":"0.0",
    "gn:asciiname":"Sagakurus",
    "gn:cc2":"KZ",
    "gn:country_code":"KZ",
    "gn:dem":845,
    "gn:feature_class":"P",
    "gn:feature_code":"PPL",
    "gn:name":"Sagakurus",
    "gn:population":0,
    "gn:timezone":"Asia/Almaty",
    "iso:country":"KZ",
    "name:und_x_variant":[
        "Sagabiyen",
        "Sagakures",
        "Sogakurus",
        "Sagakurus"
    ],
    "wof:name":"Sagakurus",
    "wof:placetype":"locality"
},
  "geometry": {"coordinates":[79.25,45.38333],"type":"Point"}
}