{
  "type": "Feature",
  "properties": {
    "gn:admin1_code":"17.0",
    "gn:asciiname":"Amangeldi",
    "gn:country_code":"KZ",
    "gn:dem":1156,
    "gn:feature_class":"P",
    "gn:feature_code":"PPL",
    "gn:name":"Amangeldi",
    "gn:population":0,
    "gn:timezone":"Asia/Almaty",
    "iso:country":"KZ",
    "name:ell_x_preferred":[
        "\u0391\u03bc\u03b1\u03bd\u03b3\u03ba\u03b5\u03bb\u03bd\u03c4\u03af"
    ],
    "name:ind_x_preferred":[
        "Amangeldi"
    ],
    "name:kaz_x_preferred":[
        "Amangeldi"
    ],
    "name:kaz_x_variant":[
        "\u0410\u043c\u0430\u043d\u0433\u0435\u043b\u0434\u0456"
    ],
    "name:msa_x_preferred":[
        "Amangeldi"
    ],
    "name:rus_x_preferred":[
        "Amangel\u2019dy"
    ],
    "name:rus_x_variant":[
        "\u0410\u043c\u0430\u043d\u0433\u0435\u043b\u044c\u0434\u044b"
    ],
    "name:ukr_x_preferred":[
        "\u0410\u043c\u0430\u043d\u0433\u0435\u043b\u044c\u0434\u0438"
    ],
    "name:uzb_x_preferred":[
        "Amangeldi"
    ],
    "wof:name":"Amangeldi",
    "wof:placetype":"locality"
},
  "geometry": {"coordinates":[70.66803,42.52927],"type":"Point"}
}