{
  "type": "Feature",
  "properties": {
    "gn:admin1_code":"4.0",
    "gn:asciiname":"Shet-Yrghyz",
    "gn:cc2":"KZ",
    "gn:country_code":"KZ",
    "gn:dem":175,
    "gn:feature_class":"P",
    "gn:feature_code":"PPL",
    "gn:name":"Shet-Yrghyz",
    "gn:population":0,
    "gn:timezone":"Asia/Aqtobe",
    "iso:country":"KZ",
    "name:eng_x_preferred":[
        "Shet-Yrghyz"
    ],
    "name:rus_x_preferred":[
        "\u0428\u0435\u0442\u0438\u0440\u0433\u0438\u0437"
    ],
    "name:und_x_variant":[
        "Shet-Irgiz"
    ],
    "wof:name":"Shet-Yrghyz",
    "wof:placetype":"locality"
},
  "geometry": {"coordinates":[59.60333000000001,48.72028],"type":"Point"}
}