{
  "type": "Feature",
  "properties": {
    "gn:admin1_code":"10.0",
    "gn:asciiname":"Shipan",
    "gn:country_code":"KZ",
    "gn:dem":235,
    "gn:feature_class":"P",
    "gn:feature_code":"PPL",
    "gn:name":"Shipan",
    "gn:population":0,
    "gn:timezone":"Asia/Almaty",
    "iso:country":"KZ",
    "name:rus_x_preferred":[
        "\u0428\u0438\u043f\u0430\u043d"
    ],
    "wof:name":"Shipan",
    "wof:placetype":"locality"
},
  "geometry": {"coordinates":[68.26028000000001,43.40177],"type":"Point"}
}