{
  "type": "Feature",
  "properties": {
    "gn:admin1_code":"11.0",
    "gn:asciiname":"Urlyutyub",
    "gn:country_code":"KZ",
    "gn:dem":111,
    "gn:feature_class":"P",
    "gn:feature_code":"PPL",
    "gn:name":"Urlyutyub",
    "gn:population":0,
    "gn:timezone":"Asia/Almaty",
    "iso:country":"KZ",
    "name:kaz_x_preferred":[
        "\u00dcyirlit\u00fcp"
    ],
    "name:kaz_x_variant":[
        "\u04ae\u0439\u0456\u0440\u043b\u0456\u0442\u04af\u043f"
    ],
    "name:rus_x_preferred":[
        "\u0423\u0440\u043b\u044e\u0442\u044e\u0431"
    ],
    "wof:name":"Urlyutyub",
    "wof:placetype":"locality"
},
  "geometry": {"coordinates":[75.33634000000001,53.85754],"type":"Point"}
}