{
  "type": "Feature",
  "properties": {
    "gn:admin1_code":"11.0",
    "gn:asciiname":"Komaritsyno",
    "gn:country_code":"KZ",
    "gn:dem":119,
    "gn:feature_class":"P",
    "gn:feature_code":"PPL",
    "gn:name":"Komaritsyno",
    "gn:population":0,
    "gn:timezone":"Asia/Almaty",
    "iso:country":"KZ",
    "name:kaz_x_preferred":[
        "Komar\u012btsyno"
    ],
    "name:kaz_x_variant":[
        "\u041a\u043e\u043c\u0430\u0440\u0438\u0446\u044b\u043d\u043e"
    ],
    "wof:name":"Komaritsyno",
    "wof:placetype":"locality"
},
  "geometry": {"coordinates":[77.18881999999998,52.00759],"type":"Point"}
}