{
  "type": "Feature",
  "properties": {
    "gn:admin1_code":"17.0",
    "gn:asciiname":"Teris-Ashchybulak",
    "gn:country_code":"KZ",
    "gn:dem":949,
    "gn:feature_class":"P",
    "gn:feature_code":"PPL",
    "gn:name":"Teris-Ashchybulak",
    "gn:population":0,
    "gn:timezone":"Asia/Almaty",
    "iso:country":"KZ",
    "name:rus_x_preferred":[
        "\u0422\u0435\u0440\u0438\u0441-\u0410\u0449\u044b\u0431\u0443\u043b\u0430\u043a"
    ],
    "wof:name":"Teris-Ashchybulak",
    "wof:placetype":"locality"
},
  "geometry": {"coordinates":[70.96303,42.66442],"type":"Point"}
}