{
  "type": "Feature",
  "properties": {
    "gn:admin1_code":"15.0",
    "gn:asciiname":"Bogomolovo",
    "gn:country_code":"KZ",
    "gn:dem":382,
    "gn:feature_class":"P",
    "gn:feature_code":"PPL",
    "gn:name":"Bogomolovo",
    "gn:population":0,
    "gn:timezone":"Asia/Almaty",
    "iso:country":"KZ",
    "name:eng_x_preferred":[
        "Bogomolovo"
    ],
    "name:kaz_x_preferred":[
        "\u0411\u043e\u0433\u043e\u043c\u043e\u043b\u043e\u0432\u043e"
    ],
    "name:rus_x_preferred":[
        "\u0411\u043e\u0433\u043e\u043c\u043e\u043b\u043e\u0432\u043e"
    ],
    "wof:name":"Bogomolovo",
    "wof:placetype":"locality"
},
  "geometry": {"coordinates":[81.49215,50.73609],"type":"Point"}
}