{
  "type": "Feature",
  "properties": {
    "gn:admin1_code":"0.0",
    "gn:asciiname":"Chigrin",
    "gn:country_code":"KZ",
    "gn:dem":73,
    "gn:feature_class":"P",
    "gn:feature_code":"PPL",
    "gn:name":"Chigrin",
    "gn:population":0,
    "gn:timezone":"Asia/Oral",
    "iso:country":"KZ",
    "wof:name":"Chigrin",
    "wof:placetype":"locality"
},
  "geometry": {"coordinates":[52.33333,51.68333],"type":"Point"}
}