{
  "type": "Feature",
  "properties": {
    "gn:admin1_code":"16.0",
    "gn:asciiname":"Zapadnoye",
    "gn:country_code":"KZ",
    "gn:dem":183,
    "gn:feature_class":"P",
    "gn:feature_code":"PPL",
    "gn:name":"Zapadnoye",
    "gn:population":0,
    "gn:timezone":"Asia/Almaty",
    "iso:country":"KZ",
    "name:kaz_x_preferred":[
        "Zapadnoe"
    ],
    "name:kaz_x_variant":[
        "\u0417\u0430\u043f\u0430\u0434\u043d\u043e\u0435"
    ],
    "name:und_x_variant":[
        "Sovkhoz Zapadnyy",
        "Zapadnyy"
    ],
    "wof:name":"Zapadnoye",
    "wof:placetype":"locality"
},
  "geometry": {"coordinates":[66.62153000000001,52.96114],"type":"Point"}
}