{
  "type": "Feature",
  "properties": {
    "gn:admin1_code":"0.0",
    "gn:asciiname":"Akhmedshkola",
    "gn:country_code":"KZ",
    "gn:dem":-16,
    "gn:feature_class":"P",
    "gn:feature_code":"PPL",
    "gn:name":"Akhmedshkola",
    "gn:population":0,
    "gn:timezone":"Asia/Oral",
    "iso:country":"KZ",
    "wof:name":"Akhmedshkola",
    "wof:placetype":"locality"
},
  "geometry": {"coordinates":[50.86667,48.53333],"type":"Point"}
}