{
  "type": "Feature",
  "properties": {
    "gn:admin1_code":"0.0",
    "gn:asciiname":"Slashchevka",
    "gn:cc2":"KZ",
    "gn:country_code":"KZ",
    "gn:dem":295,
    "gn:feature_class":"P",
    "gn:feature_code":"PPL",
    "gn:name":"Slashchevka",
    "gn:population":0,
    "gn:timezone":"Asia/Almaty",
    "iso:country":"KZ",
    "name:und_x_variant":[
        "Slashchevskoye",
        "Slashchevka"
    ],
    "wof:name":"Slashchevka",
    "wof:placetype":"locality"
},
  "geometry": {"coordinates":[70.01666999999999,51.76667],"type":"Point"}
}