{
  "type": "Feature",
  "properties": {
    "gn:admin1_code":"15.0",
    "gn:asciiname":"Donskoye",
    "gn:country_code":"KZ",
    "gn:dem":291,
    "gn:feature_class":"P",
    "gn:feature_code":"PPL",
    "gn:name":"Donskoye",
    "gn:population":0,
    "gn:timezone":"Asia/Almaty",
    "iso:country":"KZ",
    "name:eng_x_preferred":[
        "Donskoye"
    ],
    "name:kaz_x_preferred":[
        "Donskoe"
    ],
    "name:kaz_x_variant":[
        "\u0414\u043e\u043d\u0441\u043a\u043e\u0435"
    ],
    "name:rus_x_preferred":[
        "\u0414\u043e\u043d\u0441\u043a\u043e\u0435"
    ],
    "name:und_x_variant":[
        "Pobeda",
        "Donskoye"
    ],
    "wof:name":"Donskoye",
    "wof:placetype":"locality"
},
  "geometry": {"coordinates":[82.26991,50.08506],"type":"Point"}
}