{
  "type": "Feature",
  "properties": {
    "gn:admin1_code":"14.0",
    "gn:asciiname":"Stantsiya Talap",
    "gn:country_code":"KZ",
    "gn:dem":189,
    "gn:feature_class":"P",
    "gn:feature_code":"PPL",
    "gn:name":"Stantsiya Talap",
    "gn:population":0,
    "gn:timezone":"Asia/Qyzylorda",
    "iso:country":"KZ",
    "name:rus_x_preferred":[
        "\u0421\u0442\u0430\u043d\u0446\u0438\u044f \u0422\u0430\u043b\u0430\u043f"
    ],
    "wof:name":"Stantsiya Talap",
    "wof:placetype":"locality"
},
  "geometry": {"coordinates":[67.52802,43.64589],"type":"Point"}
}