{
  "type": "Feature",
  "properties": {
    "gn:admin1_code":"4.0",
    "gn:asciiname":"Kopmula",
    "gn:country_code":"KZ",
    "gn:dem":213,
    "gn:feature_class":"P",
    "gn:feature_code":"PPL",
    "gn:name":"Kopmula",
    "gn:population":0,
    "gn:timezone":"Asia/Aqtobe",
    "iso:country":"KZ",
    "name:kaz_x_preferred":[
        "K\u00f6pmola"
    ],
    "name:und_x_variant":[
        "Kopmola",
        "Kop-Mulla",
        "Kompola",
        "Kopmula"
    ],
    "wof:name":"Kopmula",
    "wof:placetype":"locality"
},
  "geometry": {"coordinates":[59.91667,47.71667],"type":"Point"}
}