{
  "type": "Feature",
  "properties": {
    "gn:admin1_code":"0.0",
    "gn:asciiname":"Oyambirlik",
    "gn:cc2":"KZ",
    "gn:country_code":"KZ",
    "gn:dem":486,
    "gn:feature_class":"P",
    "gn:feature_code":"PPL",
    "gn:name":"Oyambirlik",
    "gn:population":0,
    "gn:timezone":"Asia/Almaty",
    "iso:country":"KZ",
    "name:und_x_variant":[
        "Oyan-Berlik",
        "Oyambirlik"
    ],
    "wof:name":"Oyambirlik",
    "wof:placetype":"locality"
},
  "geometry": {"coordinates":[83.40000000000001,47.76667],"type":"Point"}
}