{
  "type": "Feature",
  "properties": {
    "gn:admin1_code":"10.0",
    "gn:asciiname":"Bazar-Ak-Tyube",
    "gn:country_code":"KZ",
    "gn:dem":248,
    "gn:feature_class":"P",
    "gn:feature_code":"PPL",
    "gn:name":"Bazar-Ak-Tyube",
    "gn:population":0,
    "gn:timezone":"Asia/Almaty",
    "iso:country":"KZ",
    "wof:name":"Bazar-Ak-Tyube",
    "wof:placetype":"locality"
},
  "geometry": {"coordinates":[67.91667,41.21667],"type":"Point"}
}