{
  "type": "Feature",
  "properties": {
    "gn:admin1_code":"3.0",
    "gn:asciiname":"Kurkem",
    "gn:country_code":"KZ",
    "gn:dem":322,
    "gn:feature_class":"P",
    "gn:feature_code":"PPL",
    "gn:name":"Kurkem",
    "gn:population":0,
    "gn:timezone":"Asia/Almaty",
    "iso:country":"KZ",
    "wof:name":"Kurkem",
    "wof:placetype":"locality"
},
  "geometry": {"coordinates":[69.79134000000001,51.16764000000001],"type":"Point"}
}