{
  "type": "Feature",
  "properties": {
    "gn:admin1_code":"13.0",
    "gn:asciiname":"Khar'kovka",
    "gn:country_code":"KZ",
    "gn:dem":126,
    "gn:feature_class":"P",
    "gn:feature_code":"PPL",
    "gn:name":"Khar\u2019kovka",
    "gn:population":0,
    "gn:timezone":"Asia/Qyzylorda",
    "iso:country":"KZ",
    "name:eng_x_preferred":[
        "Khar'kovka"
    ],
    "name:rus_x_preferred":[
        "\u0425\u0430\u0440\u044c\u043a\u043e\u0432\u043a\u0430"
    ],
    "name:rus_x_variant":[
        "Khar\u2019kovka"
    ],
    "name:und_x_variant":[
        "Khar\u2019kovskiy"
    ],
    "wof:name":"Khar'kovka",
    "wof:placetype":"locality"
},
  "geometry": {"coordinates":[64.37205,52.2892],"type":"Point"}
}