{
  "type": "Feature",
  "properties": {
    "gn:admin1_code":"3.0",
    "gn:asciiname":"Aqbulaq",
    "gn:country_code":"KZ",
    "gn:dem":442,
    "gn:feature_class":"P",
    "gn:feature_code":"PPL",
    "gn:name":"Aqbulaq",
    "gn:population":0,
    "gn:timezone":"Asia/Almaty",
    "iso:country":"KZ",
    "name:kaz_x_preferred":[
        "Aqbulaq"
    ],
    "name:kaz_x_variant":[
        "\u0410\u049b\u0431\u04b1\u043b\u0430\u049b"
    ],
    "name:rus_x_preferred":[
        "\u0410\u043a\u0431\u0443\u043b\u0430\u043a"
    ],
    "name:und_x_variant":[
        "Akbulak"
    ],
    "wof:name":"Aqbulaq",
    "wof:placetype":"locality"
},
  "geometry": {"coordinates":[72.01145,50.72945],"type":"Point"}
}