{
  "type": "Feature",
  "properties": {
    "gn:admin1_code":"13.0",
    "gn:asciiname":"Mayskoe",
    "gn:country_code":"KZ",
    "gn:dem":211,
    "gn:feature_class":"P",
    "gn:feature_code":"PPL",
    "gn:name":"Mayskoe",
    "gn:population":0,
    "gn:timezone":"Asia/Qyzylorda",
    "iso:country":"KZ",
    "name:eng_x_preferred":[
        "Mayskoe"
    ],
    "name:rus_x_preferred":[
        "\u0422\u0430\u043a\u044b\u0440\u043a\u043e\u043b\u044c"
    ],
    "name:und_x_variant":[
        "Yeltay",
        "Tykyrkol\u2019",
        "Mayskoye",
        "Takyrkol\u2019"
    ],
    "wof:name":"Mayskoe",
    "wof:placetype":"locality"
},
  "geometry": {"coordinates":[65.89201,52.89049],"type":"Point"}
}