{
  "type": "Feature",
  "properties": {
    "gn:admin1_code":"7.0",
    "gn:asciiname":"Karakemer",
    "gn:country_code":"KZ",
    "gn:dem":64,
    "gn:feature_class":"P",
    "gn:feature_code":"PPL",
    "gn:name":"Karakemer",
    "gn:population":0,
    "gn:timezone":"Asia/Oral",
    "iso:country":"KZ",
    "name:ell_x_preferred":[
        "\u039a\u03b1\u03c1\u03b1\u03ba\u03b5\u03bc\u03ad\u03c1"
    ],
    "name:eng_x_preferred":[
        "Karakemer"
    ],
    "name:msa_x_preferred":[
        "Karakemer"
    ],
    "name:rus_x_preferred":[
        "\u041a\u0430\u0440\u0430\u043a\u0435\u043c\u0435\u0440"
    ],
    "name:und_x_variant":[
        "Karakemir",
        "Karakemer"
    ],
    "wof:name":"Karakemer",
    "wof:placetype":"locality"
},
  "geometry": {"coordinates":[53.58335,51.30648],"type":"Point"}
}