{
  "type": "Feature",
  "properties": {
    "gn:admin1_code":"10.0",
    "gn:asciiname":"Inke",
    "gn:country_code":"KZ",
    "gn:dem":331,
    "gn:feature_class":"P",
    "gn:feature_code":"PPL",
    "gn:name":"Inke",
    "gn:population":0,
    "gn:timezone":"Asia/Almaty",
    "iso:country":"KZ",
    "wof:name":"Inke",
    "wof:placetype":"locality"
},
  "geometry": {"coordinates":[68.83333,41.36667],"type":"Point"}
}