{
  "type": "Feature",
  "properties": {
    "gn:admin1_code":"14.0",
    "gn:asciiname":"Aqbulym",
    "gn:country_code":"KZ",
    "gn:dem":511,
    "gn:feature_class":"P",
    "gn:feature_code":"PPL",
    "gn:name":"Aqbulym",
    "gn:population":0,
    "gn:timezone":"Asia/Almaty",
    "iso:country":"KZ",
    "name:kaz_x_preferred":[
        "Aqbulym"
    ],
    "name:kaz_x_variant":[
        "\u0410\u049b\u0431\u04b1\u043b\u044b\u043c"
    ],
    "wof:name":"Aqbulym",
    "wof:placetype":"locality"
},
  "geometry": {"coordinates":[71.16608000000002,43.05232],"type":"Point"}
}