{
  "type": "Feature",
  "properties": {
    "gn:admin1_code":"17.0",
    "gn:asciiname":"Syugandy",
    "gn:country_code":"KZ",
    "gn:dem":1341,
    "gn:feature_class":"P",
    "gn:feature_code":"PPL",
    "gn:name":"Syugandy",
    "gn:population":0,
    "gn:timezone":"Asia/Almaty",
    "iso:country":"KZ",
    "wof:name":"Syugandy",
    "wof:placetype":"locality"
},
  "geometry": {"coordinates":[75.48333000000002,42.93333],"type":"Point"}
}