{
  "type": "Feature",
  "properties": {
    "gn:admin1_code":"3.0",
    "gn:asciiname":"Trudovoe",
    "gn:country_code":"KZ",
    "gn:dem":241,
    "gn:feature_class":"P",
    "gn:feature_code":"PPL",
    "gn:name":"Tr\u016bdovoe",
    "gn:population":0,
    "gn:timezone":"Asia/Almaty",
    "iso:country":"KZ",
    "name:kaz_x_preferred":[
        "Tr\u016bdovoe"
    ],
    "name:kaz_x_variant":[
        "\u0422\u0440\u0443\u0434\u043e\u0432\u043e\u0435"
    ],
    "wof:name":"Trudovoe",
    "wof:placetype":"locality"
},
  "geometry": {"coordinates":[71.52985,52.77533],"type":"Point"}
}