{
  "type": "Feature",
  "properties": {
    "gn:admin1_code":"0.0",
    "gn:asciiname":"Daulet-Yar",
    "gn:country_code":"KZ",
    "gn:dem":12,
    "gn:feature_class":"P",
    "gn:feature_code":"PPL",
    "gn:name":"Daulet-Yar",
    "gn:population":0,
    "gn:timezone":"Asia/Oral",
    "iso:country":"KZ",
    "wof:name":"Daulet-Yar",
    "wof:placetype":"locality"
},
  "geometry": {"coordinates":[52.13333,50.03333],"type":"Point"}
}