{
  "type": "Feature",
  "properties": {
    "gn:admin1_code":"0.0",
    "gn:asciiname":"Kairly",
    "gn:country_code":"KZ",
    "gn:dem":368,
    "gn:feature_class":"P",
    "gn:feature_code":"PPL",
    "gn:name":"Kairly",
    "gn:population":0,
    "gn:timezone":"Asia/Almaty",
    "iso:country":"KZ",
    "name:und_x_variant":[
        "Kayrly",
        "Kairly"
    ],
    "wof:name":"Kairly",
    "wof:placetype":"locality"
},
  "geometry": {"coordinates":[70.83058,50.60403],"type":"Point"}
}