{
  "type": "Feature",
  "properties": {
    "gn:admin1_code":"13.0",
    "gn:asciiname":"Dal'niy",
    "gn:country_code":"KZ",
    "gn:dem":224,
    "gn:feature_class":"P",
    "gn:feature_code":"PPL",
    "gn:name":"Dal\u2019niy",
    "gn:population":0,
    "gn:timezone":"Asia/Qyzylorda",
    "iso:country":"KZ",
    "name:rus_x_preferred":[
        "Dal\u2019niy"
    ],
    "name:rus_x_variant":[
        "\u0414\u0430\u043b\u044c\u043d\u0438\u0439"
    ],
    "wof:name":"Dal'niy",
    "wof:placetype":"locality"
},
  "geometry": {"coordinates":[61.76456999999999,53.90785],"type":"Point"}
}