{
  "type": "Feature",
  "properties": {
    "gn:admin1_code":"3.0",
    "gn:asciiname":"Sovetskoe",
    "gn:country_code":"KZ",
    "gn:dem":227,
    "gn:feature_class":"P",
    "gn:feature_code":"PPL",
    "gn:name":"Sovetskoe",
    "gn:population":0,
    "gn:timezone":"Asia/Almaty",
    "iso:country":"KZ",
    "name:kaz_x_preferred":[
        "Sovetskoe"
    ],
    "name:kaz_x_variant":[
        "\u0421\u043e\u0432\u0435\u0442\u0441\u043a\u043e\u0435"
    ],
    "name:und_x_variant":[
        "Sovetskoye",
        "Sovetskiy"
    ],
    "wof:name":"Sovetskoe",
    "wof:placetype":"locality"
},
  "geometry": {"coordinates":[72.30565,52.5171],"type":"Point"}
}