{
  "type": "Feature",
  "properties": {
    "gn:admin1_code":"15.0",
    "gn:asciiname":"Dachnyy Poselok",
    "gn:country_code":"KZ",
    "gn:dem":189,
    "gn:feature_class":"P",
    "gn:feature_code":"PPL",
    "gn:name":"Dachnyy Poselok",
    "gn:population":0,
    "gn:timezone":"Asia/Almaty",
    "iso:country":"KZ",
    "wof:name":"Dachnyy Poselok",
    "wof:placetype":"locality"
},
  "geometry": {"coordinates":[80.19039000000002,50.43663],"type":"Point"}
}