{
  "type": "Feature",
  "properties": {
    "gn:admin1_code":"7.0",
    "gn:asciiname":"Malyy Sarykuduk",
    "gn:country_code":"KZ",
    "gn:dem":4,
    "gn:feature_class":"P",
    "gn:feature_code":"PPL",
    "gn:name":"Malyy Sarykuduk",
    "gn:population":0,
    "gn:timezone":"Asia/Oral",
    "iso:country":"KZ",
    "wof:name":"Malyy Sarykuduk",
    "wof:placetype":"locality"
},
  "geometry": {"coordinates":[49.93094,49.79841],"type":"Point"}
}