{
  "type": "Feature",
  "properties": {
    "gn:admin1_code":"10.0",
    "gn:asciiname":"Otdeleniye Sovkhoza Kommuna",
    "gn:country_code":"KZ",
    "gn:dem":354,
    "gn:feature_class":"P",
    "gn:feature_code":"PPLF",
    "gn:name":"Otdeleniye Sovkhoza Kommuna",
    "gn:population":0,
    "gn:timezone":"Asia/Almaty",
    "iso:country":"KZ",
    "name:rus_x_preferred":[
        "\u041e\u0442\u0434\u0435\u043b\u0435\u043d\u0438\u0435 \u0421\u043e\u0432\u0445\u043e\u0437\u0430 \u041a\u043e\u043c\u043c\u0443\u043d\u0430"
    ],
    "wof:name":"Otdeleniye Sovkhoza Kommuna",
    "wof:placetype":"locality"
},
  "geometry": {"coordinates":[68.94739,41.2926],"type":"Point"}
}