{
  "type": "Feature",
  "properties": {
    "gn:admin1_code":"4.0",
    "gn:asciiname":"Tyay-Tyay",
    "gn:country_code":"KZ",
    "gn:dem":111,
    "gn:feature_class":"P",
    "gn:feature_code":"PPL",
    "gn:name":"Tyay-Tyay",
    "gn:population":0,
    "gn:timezone":"Asia/Aqtobe",
    "iso:country":"KZ",
    "wof:name":"Tyay-Tyay",
    "wof:placetype":"locality"
},
  "geometry": {"coordinates":[56.43333000000001,47.88333],"type":"Point"}
}