{
  "type": "Feature",
  "properties": {
    "gn:admin1_code":"11.0",
    "gn:asciiname":"Tasym",
    "gn:country_code":"KZ",
    "gn:dem":164,
    "gn:feature_class":"P",
    "gn:feature_code":"PPL",
    "gn:name":"Tasym",
    "gn:population":0,
    "gn:timezone":"Asia/Almaty",
    "iso:country":"KZ",
    "name:rus_x_preferred":[
        "\u0422\u0430\u0441\u044b\u043c"
    ],
    "wof:name":"Tasym",
    "wof:placetype":"locality"
},
  "geometry": {"coordinates":[78.95057,51.55242],"type":"Point"}
}