{
  "type": "Feature",
  "properties": {
    "gn:admin1_code":"0.0",
    "gn:asciiname":"Akmola",
    "gn:country_code":"KZ",
    "gn:dem":46,
    "gn:feature_class":"P",
    "gn:feature_code":"PPL",
    "gn:name":"Akmola",
    "gn:population":0,
    "gn:timezone":"Asia/Oral",
    "iso:country":"KZ",
    "wof:name":"Akmola",
    "wof:placetype":"locality"
},
  "geometry": {"coordinates":[52.78333000000001,51.36667],"type":"Point"}
}