{
  "type": "Feature",
  "properties": {
    "gn:admin1_code":"13.0",
    "gn:asciiname":"Ozero Sorkol'",
    "gn:country_code":"KZ",
    "gn:dem":173,
    "gn:feature_class":"P",
    "gn:feature_code":"PPL",
    "gn:name":"Ozero Sorkol\u2019",
    "gn:population":0,
    "gn:timezone":"Asia/Qyzylorda",
    "iso:country":"KZ",
    "name:rus_x_preferred":[
        "Vishn\u00ebvyy"
    ],
    "name:rus_x_variant":[
        "Ozero Sorkol\u2019",
        "\u041e\u0437\u0435\u0440\u043e \u0421\u043e\u0440\u043a\u043e\u043b\u044c"
    ],
    "name:und_x_variant":[
        "Minskiy"
    ],
    "wof:name":"Ozero Sorkol'",
    "wof:placetype":"locality"
},
  "geometry": {"coordinates":[63.46919000000001,54.09303000000001],"type":"Point"}
}