{
  "type": "Feature",
  "properties": {
    "gn:admin1_code":"15.0",
    "gn:asciiname":"Saratovka",
    "gn:country_code":"KZ",
    "gn:dem":556,
    "gn:feature_class":"P",
    "gn:feature_code":"PPL",
    "gn:name":"Saratovka",
    "gn:population":0,
    "gn:timezone":"Asia/Almaty",
    "iso:country":"KZ",
    "name:aze_x_preferred":[
        "Saratovka"
    ],
    "name:hye_x_preferred":[
        "\u054d\u0561\u0580\u0561\u057f\u0578\u057e\u056f\u0561"
    ],
    "name:kaz_x_preferred":[
        "\u049a\u043e\u0439\u0442\u0430\u0441"
    ],
    "name:kaz_x_variant":[
        "\u0421\u0430\u0440\u0430\u0442\u043e\u0432\u043a\u0430"
    ],
    "name:rus_x_preferred":[
        "\u0421\u0430\u0440\u0430\u0442\u043e\u0432\u043a\u0430"
    ],
    "name:ukr_x_preferred":[
        "\u0421\u0430\u0440\u0430\u0442\u043e\u0432\u043a\u0430"
    ],
    "name:und_x_variant":[
        "Qoytas"
    ],
    "wof:name":"Saratovka",
    "wof:placetype":"locality"
},
  "geometry": {"coordinates":[81.98796999999998,49.48004],"type":"Point"}
}