{
  "type": "Feature",
  "properties": {
    "gn:admin1_code":"16.0",
    "gn:asciiname":"Aydabul",
    "gn:country_code":"KZ",
    "gn:dem":409,
    "gn:feature_class":"P",
    "gn:feature_code":"PPL",
    "gn:name":"Aydabul",
    "gn:population":0,
    "gn:timezone":"Asia/Almaty",
    "iso:country":"KZ",
    "name:eng_x_preferred":[
        "Aydabul"
    ],
    "name:kaz_x_preferred":[
        "Aydabol"
    ],
    "name:rus_x_preferred":[
        "\u0410\u0439\u0434\u0430\u0431\u0443\u043b"
    ],
    "name:und_x_variant":[
        "Aydabul\u2019skiy"
    ],
    "wof:name":"Aydabul",
    "wof:placetype":"locality"
},
  "geometry": {"coordinates":[68.98737,52.69167],"type":"Point"}
}