{
  "type": "Feature",
  "properties": {
    "gn:admin1_code":"17.0",
    "gn:asciiname":"Kazbastau",
    "gn:country_code":"KZ",
    "gn:dem":1012,
    "gn:feature_class":"P",
    "gn:feature_code":"PPL",
    "gn:name":"Kazbastau",
    "gn:population":0,
    "gn:timezone":"Asia/Almaty",
    "iso:country":"KZ",
    "name:rus_x_preferred":[
        "\u041a\u0430\u0437\u0431\u0430\u0441\u0442\u0430\u0443"
    ],
    "wof:name":"Kazbastau",
    "wof:placetype":"locality"
},
  "geometry": {"coordinates":[70.88973,42.65091],"type":"Point"}
}