{
  "type": "Feature",
  "properties": {
    "gn:admin1_code":"3.0",
    "gn:asciiname":"Dal'niy",
    "gn:country_code":"KZ",
    "gn:dem":219,
    "gn:feature_class":"P",
    "gn:feature_code":"PPL",
    "gn:name":"Dal\u2019n\u012by",
    "gn:population":0,
    "gn:timezone":"Asia/Almaty",
    "iso:country":"KZ",
    "name:kaz_x_preferred":[
        "Dal\u2019n\u012by"
    ],
    "name:kaz_x_variant":[
        "\u0414\u0430\u043b\u044c\u043d\u0438\u0439"
    ],
    "wof:name":"Dal'niy",
    "wof:placetype":"locality"
},
  "geometry": {"coordinates":[71.55861999999998,53.33111],"type":"Point"}
}