{
  "type": "Feature",
  "properties": {
    "gn:admin1_code":"12.0",
    "gn:asciiname":"Severo-Zapadnyy",
    "gn:country_code":"KZ",
    "gn:dem":484,
    "gn:feature_class":"P",
    "gn:feature_code":"PPL",
    "gn:name":"Severo-Zapadnyy",
    "gn:population":0,
    "gn:timezone":"Asia/Almaty",
    "iso:country":"KZ",
    "name:rus_x_preferred":[
        "\u0421\u0435\u0432\u0435\u0440\u043e-\u0417\u0430\u043f\u0430\u0434\u043d\u044b\u0439"
    ],
    "wof:name":"Severo-Zapadnyy",
    "wof:placetype":"locality"
},
  "geometry": {"coordinates":[72.63633,49.69847],"type":"Point"}
}