{
  "type": "Feature",
  "properties": {
    "gn:admin1_code":"0.0",
    "gn:asciiname":"Vetelki",
    "gn:country_code":"KZ",
    "gn:dem":64,
    "gn:feature_class":"P",
    "gn:feature_code":"PPL",
    "gn:name":"Vetelki",
    "gn:population":0,
    "gn:timezone":"Asia/Oral",
    "iso:country":"KZ",
    "wof:name":"Vetelki",
    "wof:placetype":"locality"
},
  "geometry": {"coordinates":[51.08333,51.38333],"type":"Point"}
}