{
  "type": "Feature",
  "properties": {
    "gn:admin1_code":"0.0",
    "gn:asciiname":"Altyapan",
    "gn:country_code":"KZ",
    "gn:dem":63,
    "gn:feature_class":"P",
    "gn:feature_code":"PPL",
    "gn:name":"Altyapan",
    "gn:population":0,
    "gn:timezone":"Asia/Oral",
    "iso:country":"KZ",
    "name:und_x_variant":[
        "Alta-Apan",
        "Altyapan"
    ],
    "wof:name":"Altyapan",
    "wof:placetype":"locality"
},
  "geometry": {"coordinates":[53.04078000000001,50.28418],"type":"Point"}
}