{
  "type": "Feature",
  "properties": {
    "gn:admin1_code":"1.0",
    "gn:asciiname":"Shalkudysu",
    "gn:country_code":"KZ",
    "gn:dem":1932,
    "gn:feature_class":"P",
    "gn:feature_code":"PPL",
    "gn:name":"Shalkudysu",
    "gn:population":0,
    "gn:timezone":"Asia/Almaty",
    "iso:country":"KZ",
    "name:rus_x_preferred":[
        "\u0428\u0430\u043b\u043a\u0443\u0434\u044b\u0441\u0443"
    ],
    "name:und_x_variant":[
        "Chalkudy-Su",
        "Shalkudysu"
    ],
    "wof:name":"Shalkudysu",
    "wof:placetype":"locality"
},
  "geometry": {"coordinates":[79.87798000000002,43.06647],"type":"Point"}
}