{
  "type": "Feature",
  "properties": {
    "gn:admin1_code":"0.0",
    "gn:asciiname":"Karasu",
    "gn:country_code":"KZ",
    "gn:dem":567,
    "gn:feature_class":"P",
    "gn:feature_code":"PPL",
    "gn:name":"Karasu",
    "gn:population":0,
    "gn:timezone":"Asia/Almaty",
    "iso:country":"KZ",
    "wof:name":"Karasu",
    "wof:placetype":"locality"
},
  "geometry": {"coordinates":[80.18333,45.76667],"type":"Point"}
}