{
  "type": "Feature",
  "properties": {
    "gn:admin1_code":"13.0",
    "gn:asciiname":"Koshkinbay",
    "gn:country_code":"KZ",
    "gn:dem":191,
    "gn:feature_class":"P",
    "gn:feature_code":"PPL",
    "gn:name":"Koshkinbay",
    "gn:population":0,
    "gn:timezone":"Asia/Almaty",
    "iso:country":"KZ",
    "name:eng_x_preferred":[
        "Koshkinbay"
    ],
    "name:rus_x_preferred":[
        "\u041a\u043e\u0448\u043a\u0438\u043d\u0431\u0430\u0439"
    ],
    "wof:name":"Koshkinbay",
    "wof:placetype":"locality"
},
  "geometry": {"coordinates":[65.48778,49.00778],"type":"Point"}
}