{
  "type": "Feature",
  "properties": {
    "gn:admin1_code":"17.0",
    "gn:asciiname":"Kyzylaut",
    "gn:country_code":"KZ",
    "gn:dem":457,
    "gn:feature_class":"P",
    "gn:feature_code":"PPL",
    "gn:name":"Kyzylaut",
    "gn:population":0,
    "gn:timezone":"Asia/Almaty",
    "iso:country":"KZ",
    "name:kaz_x_preferred":[
        "Qyzyl\u00e4\u016bit"
    ],
    "name:kaz_x_variant":[
        "\u049a\u044b\u0437\u044b\u043b\u04d9\u0443\u0456\u0442"
    ],
    "name:rus_x_preferred":[
        "\u041a\u044b\u0437\u044b\u043b\u0430\u0443\u0442"
    ],
    "name:rus_x_variant":[
        "\u041a\u043e\u043c\u0441\u043e\u043c\u043e\u043b"
    ],
    "name:und_x_variant":[
        "Komsomol"
    ],
    "wof:name":"Kyzylaut",
    "wof:placetype":"locality"
},
  "geometry": {"coordinates":[70.43594,43.41516],"type":"Point"}
}