{
  "type": "Feature",
  "properties": {
    "gn:admin1_code":"13.0",
    "gn:asciiname":"Kurguus",
    "gn:country_code":"KZ",
    "gn:dem":191,
    "gn:feature_class":"P",
    "gn:feature_code":"PPL",
    "gn:name":"Kurguus",
    "gn:population":0,
    "gn:timezone":"Asia/Qyzylorda",
    "iso:country":"KZ",
    "name:kaz_x_preferred":[
        "Qurq\u016bys"
    ],
    "name:kaz_x_variant":[
        "\u049a\u04b1\u0440\u049b\u0443\u044b\u0441"
    ],
    "name:rus_x_preferred":[
        "\u041a\u0443\u0440\u0433\u0443\u0443\u0441"
    ],
    "wof:name":"Kurguus",
    "wof:placetype":"locality"
},
  "geometry": {"coordinates":[63.87868,52.17255],"type":"Point"}
}