{
  "type": "Feature",
  "properties": {
    "gn:admin1_code":"1.0",
    "gn:asciiname":"Qopaly",
    "gn:country_code":"KZ",
    "gn:dem":937,
    "gn:feature_class":"P",
    "gn:feature_code":"PPL",
    "gn:name":"Qopaly",
    "gn:population":0,
    "gn:timezone":"Asia/Almaty",
    "iso:country":"KZ",
    "name:kaz_x_preferred":[
        "Qopaly"
    ],
    "name:kaz_x_variant":[
        "\u049a\u043e\u043f\u0430\u043b\u044b"
    ],
    "name:rus_x_preferred":[
        "\u041a\u043e\u043f\u0430\u043b\u044b"
    ],
    "name:und_x_variant":[
        "Kopaly"
    ],
    "wof:name":"Qopaly",
    "wof:placetype":"locality"
},
  "geometry": {"coordinates":[77.55495000000001,44.30699],"type":"Point"}
}