{
  "type": "Feature",
  "properties": {
    "gn:admin1_code":"0.0",
    "gn:asciiname":"Krutaya",
    "gn:country_code":"KZ",
    "gn:dem":113,
    "gn:feature_class":"P",
    "gn:feature_code":"PPL",
    "gn:name":"Krutaya",
    "gn:population":0,
    "gn:timezone":"Asia/Oral",
    "iso:country":"KZ",
    "name:eng_x_preferred":[
        "Krutaya"
    ],
    "name:rus_x_preferred":[
        "\u041a\u0440\u0443\u0442\u0430\u044f"
    ],
    "wof:name":"Krutaya",
    "wof:placetype":"locality"
},
  "geometry": {"coordinates":[50.01667,51.11667],"type":"Point"}
}