{
  "type": "Feature",
  "properties": {
    "gn:admin1_code":"10.0",
    "gn:asciiname":"Politotdel",
    "gn:country_code":"KZ",
    "gn:dem":267,
    "gn:feature_class":"P",
    "gn:feature_code":"PPL",
    "gn:name":"Politotdel",
    "gn:population":0,
    "gn:timezone":"Asia/Almaty",
    "iso:country":"KZ",
    "name:kaz_x_preferred":[
        "Pol\u012btotdel"
    ],
    "name:kaz_x_variant":[
        "\u041f\u043e\u043b\u0438\u0442\u043e\u0442\u0434\u0435\u043b"
    ],
    "name:rus_x_preferred":[
        "\u041f\u043e\u043b\u0438\u0442\u043e\u0442\u0433\u0435\u043b"
    ],
    "name:uzb_x_preferred":[
        "Odjol"
    ],
    "wof:name":"Politotdel",
    "wof:placetype":"locality"
},
  "geometry": {"coordinates":[68.52613000000001,40.66761],"type":"Point"}
}