{
  "type": "Feature",
  "properties": {
    "gn:admin1_code":"11.0",
    "gn:asciiname":"Uzynkamys",
    "gn:country_code":"KZ",
    "gn:dem":104,
    "gn:feature_class":"P",
    "gn:feature_code":"PPL",
    "gn:name":"Uzynkamys",
    "gn:population":0,
    "gn:timezone":"Asia/Almaty",
    "iso:country":"KZ",
    "name:eng_x_preferred":[
        "Uzynkamys"
    ],
    "name:kaz_x_preferred":[
        "Uzynqamys"
    ],
    "name:kaz_x_variant":[
        "\u04b0\u0437\u044b\u043d\u049b\u0430\u043c\u044b\u0441"
    ],
    "name:rus_x_preferred":[
        "\u0423\u0437\u044b\u043d\u043a\u0430\u043c\u044b\u0441"
    ],
    "wof:name":"Uzynkamys",
    "wof:placetype":"locality"
},
  "geometry": {"coordinates":[75.39055999999999,53.80434],"type":"Point"}
}