{
  "type": "Feature",
  "properties": {
    "gn:admin1_code":"4.0",
    "gn:asciiname":"Brusilovka",
    "gn:country_code":"KZ",
    "gn:dem":105,
    "gn:feature_class":"P",
    "gn:feature_code":"PPL",
    "gn:name":"Br\u016bs\u012blovka",
    "gn:population":0,
    "gn:timezone":"Asia/Aqtobe",
    "iso:country":"KZ",
    "name:eng_x_preferred":[
        "Br\u016bs\u012blovka"
    ],
    "name:rus_x_preferred":[
        "\u0411\u0440\u0443\u0441\u0438\u043b\u043e\u0432\u043a\u0430"
    ],
    "wof:name":"Brusilovka",
    "wof:placetype":"locality"
},
  "geometry": {"coordinates":[54.9509,50.75366],"type":"Point"}
}