{
  "type": "Feature",
  "properties": {
    "gn:admin1_code":"7.0",
    "gn:asciiname":"Kaldygayty",
    "gn:country_code":"KZ",
    "gn:dem":22,
    "gn:feature_class":"P",
    "gn:feature_code":"PPL",
    "gn:name":"Kaldygayty",
    "gn:population":0,
    "gn:timezone":"Asia/Oral",
    "iso:country":"KZ",
    "name:eng_x_preferred":[
        "Kaldygayty"
    ],
    "name:kaz_x_preferred":[
        "Qaldyghayty"
    ],
    "name:rus_x_preferred":[
        "\u041a\u0430\u043b\u0434\u044b\u0433\u0430\u0439\u0442\u044b"
    ],
    "wof:name":"Kaldygayty",
    "wof:placetype":"locality"
},
  "geometry": {"coordinates":[53.10309,49.58569],"type":"Point"}
}