{
  "type": "Feature",
  "properties": {
    "gn:admin1_code":"7.0",
    "gn:asciiname":"Malyy Taldykuduk",
    "gn:country_code":"KZ",
    "gn:dem":7,
    "gn:feature_class":"P",
    "gn:feature_code":"PPL",
    "gn:name":"Malyy Taldykuduk",
    "gn:population":0,
    "gn:timezone":"Asia/Oral",
    "iso:country":"KZ",
    "name:eng_x_preferred":[
        "Malyy Taldykuduk"
    ],
    "name:rus_x_preferred":[
        "\u041c\u0430\u043b.\u0422\u0430\u043b\u0434\u044b\u043a\u0443\u0434\u0443\u043a"
    ],
    "name:und_x_variant":[
        "Taldykuduk"
    ],
    "wof:name":"Malyy Taldykuduk",
    "wof:placetype":"locality"
},
  "geometry": {"coordinates":[49.78294,49.90054],"type":"Point"}
}