{
  "type": "Feature",
  "properties": {
    "gn:admin1_code":"13.0",
    "gn:asciiname":"Novotroitskoye",
    "gn:country_code":"KZ",
    "gn:dem":225,
    "gn:feature_class":"P",
    "gn:feature_code":"PPL",
    "gn:name":"Novotroitskoye",
    "gn:population":0,
    "gn:timezone":"Asia/Qyzylorda",
    "iso:country":"KZ",
    "name:eng_x_preferred":[
        "Novotro\u012btskoe"
    ],
    "name:kaz_x_preferred":[
        "Novotro\u012btskoe"
    ],
    "name:kaz_x_variant":[
        "\u041d\u043e\u0432\u043e\u0442\u0440\u043e\u0438\u0446\u043a\u043e\u0435"
    ],
    "name:rus_x_preferred":[
        "\u041d\u043e\u0432\u043e\u0442\u0440\u043e\u0438\u0446\u043a\u0438\u0439"
    ],
    "name:und_x_variant":[
        "Novotroitskiy",
        "Novo Troitsk"
    ],
    "wof:name":"Novotroitskoye",
    "wof:placetype":"locality"
},
  "geometry": {"coordinates":[61.527,53.90482],"type":"Point"}
}