{
  "type": "Feature",
  "properties": {
    "gn:admin1_code":"16.0",
    "gn:asciiname":"Zhekekol'",
    "gn:country_code":"KZ",
    "gn:dem":142,
    "gn:feature_class":"P",
    "gn:feature_code":"PPL",
    "gn:name":"Zhekekol\u2019",
    "gn:population":0,
    "gn:timezone":"Asia/Almaty",
    "iso:country":"KZ",
    "name:rus_x_preferred":[
        "Zhekekol\u2019"
    ],
    "name:rus_x_variant":[
        "\u0416\u0435\u043a\u0435\u043a\u043e\u043b\u044c"
    ],
    "wof:name":"Zhekekol'",
    "wof:placetype":"locality"
},
  "geometry": {"coordinates":[68.15741,54.45354],"type":"Point"}
}