{
  "type": "Feature",
  "properties": {
    "gn:admin1_code":"10.0",
    "gn:asciiname":"Zhanatalap",
    "gn:country_code":"KZ",
    "gn:dem":790,
    "gn:feature_class":"P",
    "gn:feature_code":"PPL",
    "gn:name":"Zhanatalap",
    "gn:population":0,
    "gn:timezone":"Asia/Almaty",
    "iso:country":"KZ",
    "name:rus_x_preferred":[
        "\u0416\u0430\u043d\u0430\u0442\u0430\u043b\u0430\u043f"
    ],
    "wof:name":"Zhanatalap",
    "wof:placetype":"locality"
},
  "geometry": {"coordinates":[70.28324000000001,42.61257],"type":"Point"}
}