{
  "type": "Feature",
  "properties": {
    "gn:admin1_code":"12.0",
    "gn:asciiname":"Baymashlyk",
    "gn:country_code":"KZ",
    "gn:dem":651,
    "gn:feature_class":"P",
    "gn:feature_code":"PPL",
    "gn:name":"Baymashlyk",
    "gn:population":0,
    "gn:timezone":"Asia/Almaty",
    "iso:country":"KZ",
    "name:und_x_variant":[
        "Vaynashlik",
        "Kazanskiy",
        "Baynashlik",
        "Baymashlik",
        "Baymashlyk"
    ],
    "wof:name":"Baymashlyk",
    "wof:placetype":"locality"
},
  "geometry": {"coordinates":[75.86667,49.83333],"type":"Point"}
}