{
  "type": "Feature",
  "properties": {
    "gn:admin1_code":"17.0",
    "gn:asciiname":"Blagoveshchenskiy",
    "gn:country_code":"KZ",
    "gn:dem":617,
    "gn:feature_class":"P",
    "gn:feature_code":"PPL",
    "gn:name":"Blagoveshchenskiy",
    "gn:population":0,
    "gn:timezone":"Asia/Almaty",
    "iso:country":"KZ",
    "name:rus_x_preferred":[
        "\u0411\u043b\u0430\u0433\u043e\u0432\u0435\u0449\u0435\u043d\u0441\u043a\u0438\u0439"
    ],
    "wof:name":"Blagoveshchenskiy",
    "wof:placetype":"locality"
},
  "geometry": {"coordinates":[74.26911,43.38079000000001],"type":"Point"}
}