{
  "type": "Feature",
  "properties": {
    "gn:admin1_code":"15.0",
    "gn:asciiname":"Mezhovka",
    "gn:country_code":"KZ",
    "gn:dem":333,
    "gn:feature_class":"P",
    "gn:feature_code":"PPL",
    "gn:name":"Mezhovka",
    "gn:population":0,
    "gn:timezone":"Asia/Almaty",
    "iso:country":"KZ",
    "name:rus_x_preferred":[
        "\u041c\u0435\u0436\u043e\u0432\u043a\u0430"
    ],
    "wof:name":"Mezhovka",
    "wof:placetype":"locality"
},
  "geometry": {"coordinates":[82.01437,50.57789],"type":"Point"}
}