{
  "type": "Feature",
  "properties": {
    "gn:admin1_code":"10.0",
    "gn:asciiname":"Poltoratskoye",
    "gn:country_code":"KZ",
    "gn:dem":592,
    "gn:feature_class":"P",
    "gn:feature_code":"PPL",
    "gn:name":"Poltoratskoye",
    "gn:population":0,
    "gn:timezone":"Asia/Qyzylorda",
    "iso:country":"KZ",
    "name:rus_x_preferred":[
        "\u041f\u043e\u043b\u0442\u043e\u0440\u0430\u0446\u043a\u043e\u0435"
    ],
    "name:und_x_variant":[
        "Selektsionnaya Stantsiya",
        "Poltoratski",
        "Poltoratskiy",
        "Poltoratskoye"
    ],
    "wof:name":"Poltoratskoye",
    "wof:placetype":"locality"
},
  "geometry": {"coordinates":[69.43365,41.46381],"type":"Point"}
}