{
  "type": "Feature",
  "properties": {
    "gn:admin1_code":"13.0",
    "gn:asciiname":"Mayak",
    "gn:country_code":"KZ",
    "gn:dem":206,
    "gn:feature_class":"P",
    "gn:feature_code":"PPL",
    "gn:name":"Mayak",
    "gn:population":0,
    "gn:timezone":"Asia/Qyzylorda",
    "iso:country":"KZ",
    "name:kaz_x_preferred":[
        "\u041c\u0430\u044f\u043a"
    ],
    "wof:name":"Mayak",
    "wof:placetype":"locality"
},
  "geometry": {"coordinates":[65.49947,53.52361],"type":"Point"}
}