{
  "type": "Feature",
  "properties": {
    "gn:admin1_code":"15.0",
    "gn:asciiname":"Baskol'",
    "gn:country_code":"KZ",
    "gn:dem":245,
    "gn:feature_class":"P",
    "gn:feature_code":"PPL",
    "gn:name":"Baskol\u2019",
    "gn:population":0,
    "gn:timezone":"Asia/Almaty",
    "iso:country":"KZ",
    "name:eng_x_preferred":[
        "Bask\u00f6l"
    ],
    "name:kaz_x_preferred":[
        "\u0411\u0430\u0441\u043a\u04e9\u043b"
    ],
    "name:rus_x_preferred":[
        "\u0411\u0430\u0441\u043a\u043e\u043b\u044c"
    ],
    "name:und_x_variant":[
        "Baskol\u2019",
        "Bashkul\u2019",
        "Bashkul\u2019skiy",
        "Bashkol\u2019"
    ],
    "wof:name":"Baskol'",
    "wof:placetype":"locality"
},
  "geometry": {"coordinates":[79.30039000000002,51.1874],"type":"Point"}
}