{
  "type": "Feature",
  "properties": {
    "gn:admin1_code":"3.0",
    "gn:asciiname":"Baymen",
    "gn:country_code":"KZ",
    "gn:dem":513,
    "gn:feature_class":"P",
    "gn:feature_code":"PPL",
    "gn:name":"Baymen",
    "gn:population":0,
    "gn:timezone":"Asia/Almaty",
    "iso:country":"KZ",
    "name:kaz_x_preferred":[
        "Baymen"
    ],
    "name:kaz_x_variant":[
        "\u0411\u0430\u0439\u043c\u0435\u043d"
    ],
    "wof:name":"Baymen",
    "wof:placetype":"locality"
},
  "geometry": {"coordinates":[73.01493000000001,51.2431],"type":"Point"}
}