{
  "type": "Feature",
  "properties": {
    "gn:admin1_code":"11.0",
    "gn:asciiname":"Zagotzerno",
    "gn:country_code":"KZ",
    "gn:dem":133,
    "gn:feature_class":"P",
    "gn:feature_code":"PPL",
    "gn:name":"Zagotzerno",
    "gn:population":0,
    "gn:timezone":"Asia/Almaty",
    "iso:country":"KZ",
    "name:rus_x_preferred":[
        "\u0417\u0430\u0433\u043e\u0442\u0437\u0435\u0440\u043d\u043e"
    ],
    "wof:name":"Zagotzerno",
    "wof:placetype":"locality"
},
  "geometry": {"coordinates":[77.44985,51.54937],"type":"Point"}
}