{
  "type": "Feature",
  "properties": {
    "gn:admin1_code":"3.0",
    "gn:asciiname":"Mikhaylovka",
    "gn:country_code":"KZ",
    "gn:dem":380,
    "gn:feature_class":"P",
    "gn:feature_code":"PPL",
    "gn:name":"Mikhaylovka",
    "gn:population":0,
    "gn:timezone":"Asia/Almaty",
    "iso:country":"KZ",
    "name:ceb_x_preferred":[
        "Mikhaylovka"
    ],
    "name:kaz_x_preferred":[
        "M\u012bkhaylovka"
    ],
    "name:kaz_x_variant":[
        "\u041c\u0438\u0445\u0430\u0439\u043b\u043e\u0432\u043a\u0430"
    ],
    "name:swe_x_preferred":[
        "Mikhaylovka"
    ],
    "name:ukr_x_preferred":[
        "\u041c\u0438\u0445\u0430\u0439\u043b\u043e\u0432\u043a\u0430"
    ],
    "name:und_x_variant":[
        "Mikhaylovskoye"
    ],
    "wof:name":"Mikhaylovka",
    "wof:placetype":"locality"
},
  "geometry": {"coordinates":[68.54115999999999,52.62835],"type":"Point"}
}