{
  "type": "Feature",
  "properties": {
    "gn:admin1_code":"16.0",
    "gn:asciiname":"Yelizavetinka",
    "gn:country_code":"KZ",
    "gn:dem":137,
    "gn:feature_class":"P",
    "gn:feature_code":"PPL",
    "gn:name":"Yelizavetinka",
    "gn:population":0,
    "gn:timezone":"Asia/Almaty",
    "iso:country":"KZ",
    "name:rus_x_preferred":[
        "\u0415\u043b\u0438\u0437\u0430\u0432\u0435\u0442\u0438\u043d\u043a\u0430"
    ],
    "name:und_x_variant":[
        "Yelizavetinskiy",
        "Yelizavetinka"
    ],
    "wof:name":"Yelizavetinka",
    "wof:placetype":"locality"
},
  "geometry": {"coordinates":[69.75638000000001,54.11861],"type":"Point"}
}