{
  "type": "Feature",
  "properties": {
    "gn:admin1_code":"15.0",
    "gn:asciiname":"Kanayka",
    "gn:country_code":"KZ",
    "gn:dem":346,
    "gn:feature_class":"P",
    "gn:feature_code":"PPL",
    "gn:name":"Kanayka",
    "gn:population":0,
    "gn:timezone":"Asia/Almaty",
    "iso:country":"KZ",
    "name:eng_x_preferred":[
        "Kanayka"
    ],
    "name:rus_x_preferred":[
        "\u041a\u0430\u043d\u0430\u0439\u043a\u0430"
    ],
    "wof:name":"Kanayka",
    "wof:placetype":"locality"
},
  "geometry": {"coordinates":[82.09733,49.87129],"type":"Point"}
}