{
  "type": "Feature",
  "properties": {
    "gn:admin1_code":"1.0",
    "gn:asciiname":"Qarakemer",
    "gn:country_code":"KZ",
    "gn:dem":917,
    "gn:feature_class":"P",
    "gn:feature_code":"PPL",
    "gn:name":"Qarakemer",
    "gn:population":0,
    "gn:timezone":"Asia/Almaty",
    "iso:country":"KZ",
    "name:kaz_x_preferred":[
        "Qarakemer"
    ],
    "name:kaz_x_variant":[
        "\u049a\u0430\u0440\u0430\u043a\u0435\u043c\u0435\u0440"
    ],
    "name:und_x_variant":[
        "Kara-Kemm",
        "Kara-Kemir",
        "Karakemyr"
    ],
    "wof:name":"Qarakemer",
    "wof:placetype":"locality"
},
  "geometry": {"coordinates":[77.61946999999998,43.42291],"type":"Point"}
}