{
  "type": "Feature",
  "properties": {
    "gn:admin1_code":"0.0",
    "gn:asciiname":"Qala",
    "gn:country_code":"KZ",
    "gn:dem":143,
    "gn:feature_class":"P",
    "gn:feature_code":"PPL",
    "gn:name":"Qala",
    "gn:population":0,
    "gn:timezone":"Asia/Almaty",
    "iso:country":"KZ",
    "name:aze_x_preferred":[
        "Qala"
    ],
    "name:ceb_x_preferred":[
        "Qala"
    ],
    "name:swe_x_preferred":[
        "Qala"
    ],
    "wof:name":"Qala",
    "wof:placetype":"locality"
},
  "geometry": {"coordinates":[65.41806,50.25111],"type":"Point"}
}