{
  "type": "Feature",
  "properties": {
    "gn:admin1_code":"12.0",
    "gn:asciiname":"Alikhan",
    "gn:country_code":"KZ",
    "gn:dem":546,
    "gn:feature_class":"P",
    "gn:feature_code":"PPL",
    "gn:name":"Alikhan",
    "gn:population":0,
    "gn:timezone":"Asia/Almaty",
    "iso:country":"KZ",
    "name:kaz_x_preferred":[
        "\u00c4l\u012bkhan"
    ],
    "name:kaz_x_variant":[
        "\u04d8\u043b\u0438\u0445\u0430\u043d"
    ],
    "name:rus_x_preferred":[
        "\u0410\u043b\u0438\u0445\u0430\u043d"
    ],
    "wof:name":"Alikhan",
    "wof:placetype":"locality"
},
  "geometry": {"coordinates":[72.30611,48.73972],"type":"Point"}
}