{
  "type": "Feature",
  "properties": {
    "gn:admin1_code":"13.0",
    "gn:asciiname":"Suzharghan",
    "gn:country_code":"KZ",
    "gn:dem":97,
    "gn:feature_class":"P",
    "gn:feature_code":"PPL",
    "gn:name":"S\u016bzharghan",
    "gn:population":0,
    "gn:timezone":"Asia/Almaty",
    "iso:country":"KZ",
    "name:eng_x_preferred":[
        "S\u016bzharghan"
    ],
    "name:rus_x_preferred":[
        "\u0421\u0443\u0436\u0430\u0440\u0433\u0430\u043d"
    ],
    "name:und_x_variant":[
        "Suzhargan"
    ],
    "wof:name":"Suzharghan",
    "wof:placetype":"locality"
},
  "geometry": {"coordinates":[63.66394,49.78806],"type":"Point"}
}