{
  "type": "Feature",
  "properties": {
    "gn:admin1_code":"0.0",
    "gn:asciiname":"Borodinskiy",
    "gn:country_code":"KZ",
    "gn:dem":-7,
    "gn:feature_class":"P",
    "gn:feature_code":"PPL",
    "gn:name":"Borodinskiy",
    "gn:population":0,
    "gn:timezone":"Asia/Oral",
    "iso:country":"KZ",
    "wof:name":"Borodinskiy",
    "wof:placetype":"locality"
},
  "geometry": {"coordinates":[49.86667,48.98333],"type":"Point"}
}