{
  "type": "Feature",
  "properties": {
    "gn:admin1_code":"15.0",
    "gn:asciiname":"Solonovka",
    "gn:country_code":"KZ",
    "gn:dem":518,
    "gn:feature_class":"P",
    "gn:feature_code":"PPL",
    "gn:name":"Solonovka",
    "gn:population":0,
    "gn:timezone":"Asia/Almaty",
    "iso:country":"KZ",
    "name:che_x_preferred":[
        "\u0421\u043e\u043b\u043e\u043d\u043e\u0432\u043a\u0430"
    ],
    "name:eng_x_preferred":[
        "Solonovka"
    ],
    "name:kaz_x_preferred":[
        "\u0421\u043e\u043b\u043e\u043d\u043e\u0432\u043a\u0430"
    ],
    "name:rus_x_preferred":[
        "\u0421\u043e\u043b\u043e\u043d\u043e\u0432\u043a\u0430"
    ],
    "wof:name":"Solonovka",
    "wof:placetype":"locality"
},
  "geometry": {"coordinates":[84.75321,49.30237],"type":"Point"}
}