{
  "type": "Feature",
  "properties": {
    "gn:admin1_code":"11.0",
    "gn:asciiname":"Potanino",
    "gn:country_code":"KZ",
    "gn:dem":108,
    "gn:feature_class":"P",
    "gn:feature_code":"PPL",
    "gn:name":"Potanino",
    "gn:population":0,
    "gn:timezone":"Asia/Almaty",
    "iso:country":"KZ",
    "name:rus_x_preferred":[
        "\u041f\u043e\u0442\u0430\u043d\u0438\u043d\u043e"
    ],
    "name:und_x_variant":[
        "Potaninskoye",
        "Potaninskiy",
        "Potanino"
    ],
    "wof:name":"Potanino",
    "wof:placetype":"locality"
},
  "geometry": {"coordinates":[76.84013,52.19661],"type":"Point"}
}