{
  "type": "Feature",
  "properties": {
    "gn:admin1_code":"1.0",
    "gn:asciiname":"Dostyk",
    "gn:country_code":"KZ",
    "gn:dem":605,
    "gn:feature_class":"P",
    "gn:feature_code":"PPL",
    "gn:name":"Dostyk",
    "gn:population":0,
    "gn:timezone":"Asia/Almaty",
    "iso:country":"KZ",
    "name:ceb_x_preferred":[
        "Dostyq"
    ],
    "name:deu_x_preferred":[
        "Dostyk"
    ],
    "name:ell_x_preferred":[
        "\u039d\u03c4\u03bf\u03c3\u03c4\u03af\u03ba"
    ],
    "name:fra_x_preferred":[
        "Dostyk"
    ],
    "name:kaz_x_preferred":[
        "\u0414\u043e\u0441\u0442\u044b\u049b"
    ],
    "name:mkd_x_preferred":[
        "\u0414\u043e\u0441\u0442\u0438\u043a"
    ],
    "name:msa_x_preferred":[
        "Dostyk"
    ],
    "name:nld_x_preferred":[
        "Dostyq"
    ],
    "name:rus_x_preferred":[
        "\u0414\u043e\u0441\u0442\u044b\u043a"
    ],
    "name:sco_x_preferred":[
        "Dostyk"
    ],
    "name:tur_x_preferred":[
        "Dost\u0131k"
    ],
    "name:ukr_x_preferred":[
        "\u0414\u043e\u0441\u0442\u0438\u043a"
    ],
    "name:zho_x_preferred":[
        "\u591a\u65af\u7279\u514b"
    ],
    "wof:name":"Dostyk",
    "wof:placetype":"locality"
},
  "geometry": {"coordinates":[77.04201999999999,43.4762],"type":"Point"}
}