{
  "type": "Feature",
  "properties": {
    "gn:admin1_code":"1.0",
    "gn:asciiname":"Dostyk",
    "gn:country_code":"KZ",
    "gn:dem":605,
    "gn:feature_class":"P",
    "gn:feature_code":"PPL",
    "gn:name":"Dostyk",
    "gn:population":0,
    "gn:timezone":"Asia/Almaty",
    "iso:country":"KZ",
    "name:rus_x_preferred":[
        "\u0414\u043e\u0441\u0442\u044b\u043a"
    ],
    "wof:name":"Dostyk",
    "wof:placetype":"locality"
},
  "geometry": {"coordinates":[77.04201999999999,43.4762],"type":"Point"}
}