{
  "type": "Feature",
  "properties": {
    "gn:admin1_code":"13.0",
    "gn:asciiname":"Lugovoye",
    "gn:country_code":"KZ",
    "gn:dem":121,
    "gn:feature_class":"P",
    "gn:feature_code":"PPL",
    "gn:name":"Lugovoye",
    "gn:population":0,
    "gn:timezone":"Asia/Qyzylorda",
    "iso:country":"KZ",
    "name:kaz_x_preferred":[
        "L\u016bgovoe"
    ],
    "name:kaz_x_variant":[
        "\u041b\u0443\u0433\u043e\u0432\u043e\u0435"
    ],
    "wof:name":"Lugovoye",
    "wof:placetype":"locality"
},
  "geometry": {"coordinates":[63.86933000000001,53.65303],"type":"Point"}
}