{
  "type": "Feature",
  "properties": {
    "gn:admin1_code":"16.0",
    "gn:asciiname":"Vladimirovka",
    "gn:country_code":"KZ",
    "gn:dem":122,
    "gn:feature_class":"P",
    "gn:feature_code":"PPL",
    "gn:name":"Vladimirovka",
    "gn:population":0,
    "gn:timezone":"Asia/Almaty",
    "iso:country":"KZ",
    "name:rus_x_preferred":[
        "\u0412\u043b\u0430\u0434\u0438\u043c\u0438\u0440\u043e\u0432\u043a\u0430"
    ],
    "wof:name":"Vladimirovka",
    "wof:placetype":"locality"
},
  "geometry": {"coordinates":[70.94583,54.90715],"type":"Point"}
}