{
  "type": "Feature",
  "properties": {
    "gn:admin1_code":"16.0",
    "gn:asciiname":"Izobil'noye",
    "gn:country_code":"KZ",
    "gn:dem":126,
    "gn:feature_class":"P",
    "gn:feature_code":"PPL",
    "gn:name":"Izobil\u2019noye",
    "gn:population":0,
    "gn:timezone":"Asia/Almaty",
    "iso:country":"KZ",
    "name:eng_x_preferred":[
        "Izobil'noye"
    ],
    "name:kaz_x_preferred":[
        "\u012azob\u012bl\u2019noe"
    ],
    "name:kaz_x_variant":[
        "\u0418\u0437\u043e\u0431\u0438\u043b\u044c\u043d\u043e\u0435"
    ],
    "name:rus_x_preferred":[
        "\u0418\u0437\u043e\u0431\u0438\u043b\u044c\u043d\u043e\u0435"
    ],
    "name:und_x_variant":[
        "Izobil\u2019noye"
    ],
    "wof:name":"Izobil'noye",
    "wof:placetype":"locality"
},
  "geometry": {"coordinates":[70.92009,54.499],"type":"Point"}
}