{
  "type": "Feature",
  "properties": {
    "gn:admin1_code":"1.0",
    "gn:asciiname":"Shirganak",
    "gn:country_code":"KZ",
    "gn:dem":1930,
    "gn:feature_class":"P",
    "gn:feature_code":"PPL",
    "gn:name":"Shirganak",
    "gn:population":0,
    "gn:timezone":"Asia/Almaty",
    "iso:country":"KZ",
    "name:rus_x_preferred":[
        "\u0428\u0438\u0440\u0433\u0430\u043d\u0430\u043a"
    ],
    "wof:name":"Shirganak",
    "wof:placetype":"locality"
},
  "geometry": {"coordinates":[79.07338,42.90925],"type":"Point"}
}