{
  "type": "Feature",
  "properties": {
    "gn:admin1_code":"4.0",
    "gn:asciiname":"Quyylys",
    "gn:cc2":"KZ",
    "gn:country_code":"KZ",
    "gn:dem":75,
    "gn:feature_class":"P",
    "gn:feature_code":"PPL",
    "gn:name":"Quyylys",
    "gn:population":0,
    "gn:timezone":"Asia/Aqtobe",
    "iso:country":"KZ",
    "name:eng_x_preferred":[
        "Quyylys"
    ],
    "name:rus_x_preferred":[
        "\u041a\u0443\u0439\u043b\u044b\u0441"
    ],
    "name:und_x_variant":[
        "Kuylys"
    ],
    "wof:name":"Quyylys",
    "wof:placetype":"locality"
},
  "geometry": {"coordinates":[62.07361,48.24694],"type":"Point"}
}