{
  "type": "Feature",
  "properties": {
    "gn:admin1_code":"3.0",
    "gn:asciiname":"Koysalgan",
    "gn:country_code":"KZ",
    "gn:dem":403,
    "gn:feature_class":"P",
    "gn:feature_code":"PPL",
    "gn:name":"Koysalgan",
    "gn:population":0,
    "gn:timezone":"Asia/Almaty",
    "iso:country":"KZ",
    "name:rus_x_preferred":[
        "\u041a\u043e\u0439\u0441\u0430\u043b\u0433\u0430\u043d"
    ],
    "name:rus_x_variant":[
        "\u0418\u043c\u0435\u043d\u0438 \u041c\u0430\u043b\u0438\u043a\u0430 \u0413\u0430\u0431\u0434\u0443\u043b\u0438\u043d\u0430"
    ],
    "name:und_x_variant":[
        "Imeni Malika Gabdulina",
        "Koysalgan"
    ],
    "wof:name":"Koysalgan",
    "wof:placetype":"locality"
},
  "geometry": {"coordinates":[69.43585999999999,52.98923000000001],"type":"Point"}
}