{
  "type": "Feature",
  "properties": {
    "gn:admin1_code":"16.0",
    "gn:asciiname":"Razgul'noye",
    "gn:country_code":"KZ",
    "gn:dem":201,
    "gn:feature_class":"P",
    "gn:feature_code":"PPL",
    "gn:name":"Razgul\u2019noye",
    "gn:population":0,
    "gn:timezone":"Asia/Almaty",
    "iso:country":"KZ",
    "name:eng_x_preferred":[
        "Razgul'noye"
    ],
    "name:kaz_x_preferred":[
        "Razg\u016bl\u2019noe"
    ],
    "name:kaz_x_variant":[
        "\u0420\u0430\u0437\u0433\u0443\u043b\u044c\u043d\u043e\u0435"
    ],
    "name:rus_x_preferred":[
        "\u0420\u0430\u0437\u0433\u0443\u043b\u044c\u043d\u043e\u0435"
    ],
    "name:rus_x_variant":[
        "Razgul\u2019noye"
    ],
    "name:und_x_variant":[
        "Priishimskiy"
    ],
    "wof:name":"Razgul'noye",
    "wof:placetype":"locality"
},
  "geometry": {"coordinates":[66.68134000000001,52.39708],"type":"Point"}
}