{
  "type": "Feature",
  "properties": {
    "gn:admin1_code":"15.0",
    "gn:asciiname":"Pravyy Ust'-Qalzhyr",
    "gn:country_code":"KZ",
    "gn:dem":411,
    "gn:feature_class":"P",
    "gn:feature_code":"PPL",
    "gn:name":"Pravyy \u016ast\u2019-Qalzhyr",
    "gn:population":0,
    "gn:timezone":"Asia/Almaty",
    "iso:country":"KZ",
    "name:kaz_x_preferred":[
        "Pravyy \u016ast\u2019-Qalzhyr"
    ],
    "name:kaz_x_variant":[
        "\u041f\u0440\u0430\u0432\u044b\u0439 \u0423\u0441\u0442\u044c-\u049a\u0430\u043b\u0436\u044b\u0440"
    ],
    "name:rus_x_preferred":[
        "Pravyy Ust\u2019-Kal\u2019zhir"
    ],
    "name:rus_x_variant":[
        "\u041f\u0440\u0430\u0432\u044b\u0439 \u0423\u0441\u0442\u044c-\u041a\u0430\u043b\u044c\u0436\u0438\u0440"
    ],
    "wof:name":"Pravyy Ust'-Qalzhyr",
    "wof:placetype":"locality"
},
  "geometry": {"coordinates":[85.17281,48.01105],"type":"Point"}
}