{
  "type": "Feature",
  "properties": {
    "gn:admin1_code":"12.0",
    "gn:asciiname":"Abay",
    "gn:country_code":"KZ",
    "gn:dem":642,
    "gn:feature_class":"P",
    "gn:feature_code":"PPL",
    "gn:name":"Abay",
    "gn:population":0,
    "gn:timezone":"Asia/Almaty",
    "iso:country":"KZ",
    "name:kaz_x_preferred":[
        "Abay"
    ],
    "name:kaz_x_variant":[
        "\u0410\u0431\u0430\u0439"
    ],
    "wof:name":"Abay",
    "wof:placetype":"locality"
},
  "geometry": {"coordinates":[75.85881999999999,48.04644],"type":"Point"}
}