{
  "type": "Feature",
  "properties": {
    "gn:admin1_code":"10.0",
    "gn:asciiname":"Kizen'",
    "gn:country_code":"KZ",
    "gn:dem":775,
    "gn:feature_class":"P",
    "gn:feature_code":"PPL",
    "gn:name":"Kizen\u2019",
    "gn:population":0,
    "gn:timezone":"Asia/Almaty",
    "iso:country":"KZ",
    "name:rus_x_preferred":[
        "Kizen\u2019"
    ],
    "name:rus_x_variant":[
        "\u041a\u0438\u0437\u0435\u043d\u044c"
    ],
    "wof:name":"Kizen'",
    "wof:placetype":"locality"
},
  "geometry": {"coordinates":[70.33689,42.52308],"type":"Point"}
}