{
  "type": "Feature",
  "properties": {
    "gn:admin1_code":"3.0",
    "gn:asciiname":"Karatubek",
    "gn:country_code":"KZ",
    "gn:dem":285,
    "gn:feature_class":"P",
    "gn:feature_code":"PPL",
    "gn:name":"Karatubek",
    "gn:population":0,
    "gn:timezone":"Asia/Almaty",
    "iso:country":"KZ",
    "name:und_x_variant":[
        "Karatyubek",
        "Karatubek"
    ],
    "wof:name":"Karatubek",
    "wof:placetype":"locality"
},
  "geometry": {"coordinates":[69.30071,51.61263],"type":"Point"}
}