{
  "type": "Feature",
  "properties": {
    "gn:admin1_code":"13.0",
    "gn:asciiname":"Ostrovnoy",
    "gn:country_code":"KZ",
    "gn:dem":214,
    "gn:feature_class":"P",
    "gn:feature_code":"PPL",
    "gn:name":"Ostrovnoy",
    "gn:population":0,
    "gn:timezone":"Asia/Qyzylorda",
    "iso:country":"KZ",
    "name:rus_x_preferred":[
        "\u041e\u0441\u0442\u0440\u043e\u0432\u043d\u043e\u0439"
    ],
    "name:rus_x_variant":[
        "\u041b\u0435\u0441\u0445\u043e\u0437"
    ],
    "name:tgl_x_preferred":[
        "Ostrovnoy"
    ],
    "name:und_x_variant":[
        "Leskhoz"
    ],
    "wof:name":"Ostrovnoy",
    "wof:placetype":"locality"
},
  "geometry": {"coordinates":[65.47528,53.34179],"type":"Point"}
}