{
  "type": "Feature",
  "properties": {
    "gn:admin1_code":"12.0",
    "gn:asciiname":"Sarytogan",
    "gn:country_code":"KZ",
    "gn:dem":519,
    "gn:feature_class":"P",
    "gn:feature_code":"PPL",
    "gn:name":"Sarytogan",
    "gn:population":0,
    "gn:timezone":"Asia/Almaty",
    "iso:country":"KZ",
    "wof:name":"Sarytogan",
    "wof:placetype":"locality"
},
  "geometry": {"coordinates":[67.45662,49.47908],"type":"Point"}
}