{
  "type": "Feature",
  "properties": {
    "gn:admin1_code":"0.0",
    "gn:asciiname":"Krasnoyarskiy Pitomnik",
    "gn:country_code":"KZ",
    "gn:dem":362,
    "gn:feature_class":"P",
    "gn:feature_code":"PPL",
    "gn:name":"Krasnoyarskiy Pitomnik",
    "gn:population":0,
    "gn:timezone":"Asia/Almaty",
    "iso:country":"KZ",
    "wof:name":"Krasnoyarskiy Pitomnik",
    "wof:placetype":"locality"
},
  "geometry": {"coordinates":[71.61667,51.13333],"type":"Point"}
}