{
  "type": "Feature",
  "properties": {
    "gn:admin1_code":"16.0",
    "gn:asciiname":"Chistovskoye",
    "gn:country_code":"KZ",
    "gn:dem":116,
    "gn:feature_class":"P",
    "gn:feature_code":"PPL",
    "gn:name":"Chistovskoye",
    "gn:population":0,
    "gn:timezone":"Asia/Almaty",
    "iso:country":"KZ",
    "name:eng_x_preferred":[
        "Ch\u012bstovskoe"
    ],
    "name:kaz_x_preferred":[
        "\u0427\u0438\u0441\u0442\u043e\u0432\u0441\u043a\u043e\u0435"
    ],
    "name:rus_x_preferred":[
        "\u0427\u0438\u0441\u0442\u043e\u0432\u0441\u043a\u043e\u0435"
    ],
    "name:und_x_variant":[
        "Krasnyy Or\u00ebl",
        "Chistovskiy",
        "Chistovskoye"
    ],
    "wof:name":"Chistovskoye",
    "wof:placetype":"locality"
},
  "geometry": {"coordinates":[70.62505999999998,54.89353000000001],"type":"Point"}
}