{
  "type": "Feature",
  "properties": {
    "gn:admin1_code":"3.0",
    "gn:asciiname":"Koytas",
    "gn:country_code":"KZ",
    "gn:dem":216,
    "gn:feature_class":"P",
    "gn:feature_code":"PPL",
    "gn:name":"Koytas",
    "gn:population":0,
    "gn:timezone":"Asia/Almaty",
    "iso:country":"KZ",
    "name:kaz_x_preferred":[
        "\u049a\u043e\u0439\u0442\u0430\u0441"
    ],
    "name:rus_x_preferred":[
        "\u041a\u043e\u0439\u0442\u0430\u0441"
    ],
    "name:und_x_variant":[
        "Qoytas"
    ],
    "wof:name":"Koytas",
    "wof:placetype":"locality"
},
  "geometry": {"coordinates":[72.56596999999999,52.80045],"type":"Point"}
}