{
  "type": "Feature",
  "properties": {
    "gn:admin1_code":"0.0",
    "gn:asciiname":"Tyustas",
    "gn:country_code":"KZ",
    "gn:dem":405,
    "gn:feature_class":"P",
    "gn:feature_code":"PPL",
    "gn:name":"Tyustas",
    "gn:population":0,
    "gn:timezone":"Asia/Almaty",
    "iso:country":"KZ",
    "wof:name":"Tyustas",
    "wof:placetype":"locality"
},
  "geometry": {"coordinates":[84.94974000000001,47.93485],"type":"Point"}
}