{
  "type": "Feature",
  "properties": {
    "gn:admin1_code":"12.0",
    "gn:asciiname":"Karatoka",
    "gn:country_code":"KZ",
    "gn:dem":567,
    "gn:feature_class":"P",
    "gn:feature_code":"PPL",
    "gn:name":"Karatoka",
    "gn:population":0,
    "gn:timezone":"Asia/Almaty",
    "iso:country":"KZ",
    "name:rus_x_preferred":[
        "\u041a\u0430\u0440\u0430\u0442\u043e\u043a\u0430"
    ],
    "wof:name":"Karatoka",
    "wof:placetype":"locality"
},
  "geometry": {"coordinates":[74.73973000000002,50.34842],"type":"Point"}
}