{
  "type": "Feature",
  "properties": {
    "gn:admin1_code":"3.0",
    "gn:asciiname":"Zhanalyk",
    "gn:country_code":"KZ",
    "gn:dem":247,
    "gn:feature_class":"P",
    "gn:feature_code":"PPL",
    "gn:name":"Zhanalyk",
    "gn:population":0,
    "gn:timezone":"Asia/Almaty",
    "iso:country":"KZ",
    "name:eng_x_preferred":[
        "Zhanalyk"
    ],
    "name:kaz_x_preferred":[
        "Zhangalyq"
    ],
    "name:kaz_x_variant":[
        "\u0416\u0430\u04a3\u0430\u043b\u044b\u049b"
    ],
    "name:rus_x_preferred":[
        "\u0416\u0430\u043d\u0430\u043b\u044b\u043a"
    ],
    "name:und_x_variant":[
        "Zhana-Aul"
    ],
    "wof:name":"Zhanalyk",
    "wof:placetype":"locality"
},
  "geometry": {"coordinates":[71.00225,53.2756],"type":"Point"}
}