{
  "type": "Feature",
  "properties": {
    "gn:admin1_code":"10.0",
    "gn:asciiname":"Zhuldyz",
    "gn:country_code":"KZ",
    "gn:dem":242,
    "gn:feature_class":"P",
    "gn:feature_code":"PPL",
    "gn:name":"Zhuldyz",
    "gn:population":0,
    "gn:timezone":"Asia/Almaty",
    "iso:country":"KZ",
    "name:und_x_variant":[
        "\u0416\u0443\u043b\u0434\u044b\u0437"
    ],
    "wof:name":"Zhuldyz",
    "wof:placetype":"locality"
},
  "geometry": {"coordinates":[68.97762,42.43397],"type":"Point"}
}