{
  "type": "Feature",
  "properties": {
    "gn:admin1_code":"10.0",
    "gn:asciiname":"Kushata",
    "gn:country_code":"KZ",
    "gn:dem":339,
    "gn:feature_class":"P",
    "gn:feature_code":"PPL",
    "gn:name":"Kushata",
    "gn:population":0,
    "gn:timezone":"Asia/Almaty",
    "iso:country":"KZ",
    "name:rus_x_preferred":[
        "\u041a\u0443\u0448\u0430\u0442\u0430"
    ],
    "wof:name":"Kushata",
    "wof:placetype":"locality"
},
  "geometry": {"coordinates":[68.43764,43.44946],"type":"Point"}
}