{
  "type": "Feature",
  "properties": {
    "gn:admin1_code":"16.0",
    "gn:asciiname":"Krasnaya Gorka",
    "gn:country_code":"KZ",
    "gn:dem":287,
    "gn:feature_class":"P",
    "gn:feature_code":"PPL",
    "gn:name":"Krasnaya Gorka",
    "gn:population":0,
    "gn:timezone":"Asia/Almaty",
    "iso:country":"KZ",
    "name:kaz_x_preferred":[
        "\u041a\u0440\u0430\u0441\u043d\u043e\u0433\u043e\u0440\u043a\u0430"
    ],
    "name:rus_x_preferred":[
        "\u041a\u0440\u0430\u0441\u043d\u0430\u044f \u0413\u043e\u0440\u043a\u0430"
    ],
    "name:und_x_variant":[
        "Krasnogorka"
    ],
    "wof:name":"Krasnaya Gorka",
    "wof:placetype":"locality"
},
  "geometry": {"coordinates":[68.21007,53.27309],"type":"Point"}
}