{
  "type": "Feature",
  "properties": {
    "gn:admin1_code":"16.0",
    "gn:asciiname":"Kuspek",
    "gn:country_code":"KZ",
    "gn:dem":356,
    "gn:feature_class":"P",
    "gn:feature_code":"PPL",
    "gn:name":"Kuspek",
    "gn:population":0,
    "gn:timezone":"Asia/Almaty",
    "iso:country":"KZ",
    "name:eng_x_preferred":[
        "Qusbek"
    ],
    "name:kaz_x_preferred":[
        "Qusbek"
    ],
    "name:kaz_x_variant":[
        "Quspek",
        "\u049a\u04b1\u0441\u043f\u0435\u043a"
    ],
    "name:rus_x_preferred":[
        "\u041a\u0443\u0441\u043f\u0435\u043a"
    ],
    "wof:name":"Kuspek",
    "wof:placetype":"locality"
},
  "geometry": {"coordinates":[68.00129,52.74518000000001],"type":"Point"}
}