{
  "type": "Feature",
  "properties": {
    "gn:admin1_code":"1.0",
    "gn:asciiname":"Pokrovka",
    "gn:country_code":"KZ",
    "gn:dem":644,
    "gn:feature_class":"P",
    "gn:feature_code":"PPL",
    "gn:name":"Pokrovka",
    "gn:population":0,
    "gn:timezone":"Asia/Almaty",
    "iso:country":"KZ",
    "name:aze_x_preferred":[
        "Pokrovka"
    ],
    "name:bel_x_preferred":[
        "\u041f\u0430\u043a\u0440\u043e\u045e\u043a\u0430"
    ],
    "name:ceb_x_preferred":[
        "Pokrovka"
    ],
    "name:deu_x_preferred":[
        "Pokrowka"
    ],
    "name:hye_x_preferred":[
        "\u054a\u0578\u056f\u0580\u0578\u057e\u056f\u0561"
    ],
    "name:ita_x_preferred":[
        "Pokrovka"
    ],
    "name:kaz_x_preferred":[
        "Pokrovka"
    ],
    "name:kaz_x_variant":[
        "\u041f\u043e\u043a\u0440\u043e\u0432\u043a\u0430"
    ],
    "name:nld_x_preferred":[
        "Pokrovka"
    ],
    "name:ron_x_preferred":[
        "Pocrovca"
    ],
    "name:rus_x_preferred":[
        "\u041f\u043e\u043a\u0440\u043e\u0432\u043a\u0430"
    ],
    "name:swe_x_preferred":[
        "Pokrovka"
    ],
    "name:ukr_x_preferred":[
        "\u041f\u043e\u043a\u0440\u043e\u0432\u043a\u0430"
    ],
    "name:zho_x_preferred":[
        "\u6ce2\u514b\u7f57\u592b\u5361\u5e02\u9547"
    ],
    "wof:name":"Pokrovka",
    "wof:placetype":"locality"
},
  "geometry": {"coordinates":[77.0059,43.39744],"type":"Point"}
}