{
  "type": "Feature",
  "properties": {
    "gn:admin1_code":"0.0",
    "gn:asciiname":"Muzhiksu",
    "gn:country_code":"KZ",
    "gn:dem":436,
    "gn:feature_class":"P",
    "gn:feature_code":"PPL",
    "gn:name":"Muzhiksu",
    "gn:population":0,
    "gn:timezone":"Asia/Almaty",
    "iso:country":"KZ",
    "name:und_x_variant":[
        "Muzhuk-Su",
        "Muzhiksu"
    ],
    "wof:name":"Muzhiksu",
    "wof:placetype":"locality"
},
  "geometry": {"coordinates":[84.93824000000002,47.65846],"type":"Point"}
}