{
  "type": "Feature",
  "properties": {
    "gn:admin1_code":"17.0",
    "gn:asciiname":"Kokkaynar",
    "gn:country_code":"KZ",
    "gn:dem":530,
    "gn:feature_class":"P",
    "gn:feature_code":"PPL",
    "gn:name":"Kokkaynar",
    "gn:population":0,
    "gn:timezone":"Asia/Almaty",
    "iso:country":"KZ",
    "name:kaz_x_preferred":[
        "K\u00f6kqaynar"
    ],
    "name:kaz_x_variant":[
        "\u041a\u04e9\u043a\u049b\u0430\u0439\u043d\u0430\u0440"
    ],
    "name:rus_x_preferred":[
        "\u041a\u043e\u043a\u043a\u0430\u0439\u043d\u0430\u0440"
    ],
    "wof:name":"Kokkaynar",
    "wof:placetype":"locality"
},
  "geometry": {"coordinates":[74.09196,43.35047],"type":"Point"}
}