{
  "type": "Feature",
  "properties": {
    "gn:admin1_code":"11.0",
    "gn:asciiname":"Kerey",
    "gn:country_code":"KZ",
    "gn:dem":154,
    "gn:feature_class":"P",
    "gn:feature_code":"PPL",
    "gn:name":"Kerey",
    "gn:population":0,
    "gn:timezone":"Asia/Almaty",
    "iso:country":"KZ",
    "name:eng_x_preferred":[
        "Kerey"
    ],
    "name:kaz_x_preferred":[
        "\u041a\u0435\u0440\u0435\u0439"
    ],
    "name:rus_x_preferred":[
        "\u041a\u0435\u0440\u0435\u0439"
    ],
    "wof:name":"Kerey",
    "wof:placetype":"locality"
},
  "geometry": {"coordinates":[78.36705000000001,51.51463],"type":"Point"}
}