{
  "type": "Feature",
  "properties": {
    "gn:admin1_code":"0.0",
    "gn:asciiname":"Alakol'",
    "gn:country_code":"KZ",
    "gn:dem":87,
    "gn:feature_class":"P",
    "gn:feature_code":"PPL",
    "gn:name":"Alakol\u2019",
    "gn:population":0,
    "gn:timezone":"Asia/Almaty",
    "iso:country":"KZ",
    "name:und_x_variant":[
        "Ala-Kul\u2019",
        "Alakol\u2019"
    ],
    "wof:name":"Alakol'",
    "wof:placetype":"locality"
},
  "geometry": {"coordinates":[62.93333000000001,49.31667],"type":"Point"}
}