{
  "type": "Feature",
  "properties": {
    "gn:admin1_code":"10.0",
    "gn:asciiname":"Terekty",
    "gn:country_code":"KZ",
    "gn:dem":700,
    "gn:feature_class":"P",
    "gn:feature_code":"PPL",
    "gn:name":"Terekty",
    "gn:population":0,
    "gn:timezone":"Asia/Almaty",
    "iso:country":"KZ",
    "name:rus_x_preferred":[
        "\u0422\u0435\u0440\u0435\u043a\u0442\u044b"
    ],
    "wof:name":"Terekty",
    "wof:placetype":"locality"
},
  "geometry": {"coordinates":[69.26715,41.77208],"type":"Point"}
}