{
  "type": "Feature",
  "properties": {
    "gn:admin1_code":"7.0",
    "gn:asciiname":"Dar'inskoe",
    "gn:country_code":"KZ",
    "gn:dem":30,
    "gn:feature_class":"P",
    "gn:feature_code":"PPL",
    "gn:name":"Dar\u2019\u012bnskoe",
    "gn:population":0,
    "gn:timezone":"Asia/Oral",
    "iso:country":"KZ",
    "name:eng_x_preferred":[
        "Dar'\u012bnskoe"
    ],
    "name:rus_x_preferred":[
        "\u0414\u0430\u0440\u044c\u0438\u043d\u0441\u043a\u043e\u0435"
    ],
    "name:und_x_variant":[
        "Dar\u2019inskiy",
        "Dar\u2019inskoye",
        "Dar\u2019\u012bnskoe"
    ],
    "wof:name":"Dar'inskoe",
    "wof:placetype":"locality"
},
  "geometry": {"coordinates":[51.73333,51.33333],"type":"Point"}
}