{
  "type": "Feature",
  "properties": {
    "gn:admin1_code":"15.0",
    "gn:asciiname":"Shynzhy",
    "gn:country_code":"KZ",
    "gn:dem":253,
    "gn:feature_class":"P",
    "gn:feature_code":"PPL",
    "gn:name":"Shynzhy",
    "gn:population":0,
    "gn:timezone":"Asia/Almaty",
    "iso:country":"KZ",
    "name:eng_x_preferred":[
        "Chinzhi"
    ],
    "name:kaz_x_preferred":[
        "Shynzhy"
    ],
    "name:rus_x_preferred":[
        "\u0427\u0438\u043d\u0436\u0438"
    ],
    "name:und_x_variant":[
        "Chinzhi"
    ],
    "wof:name":"Shynzhy",
    "wof:placetype":"locality"
},
  "geometry": {"coordinates":[79.26463000000003,50.18003],"type":"Point"}
}