{
  "type": "Feature",
  "properties": {
    "gn:admin1_code":"0.0",
    "gn:asciiname":"Kirovskoye",
    "gn:country_code":"KZ",
    "gn:dem":629,
    "gn:feature_class":"P",
    "gn:feature_code":"PPL",
    "gn:name":"Kirovskoye",
    "gn:population":0,
    "gn:timezone":"Asia/Almaty",
    "iso:country":"KZ",
    "name:eng_x_preferred":[
        "Kirovskoye"
    ],
    "name:rus_x_preferred":[
        "\u041a\u0438\u0440\u043e\u0432\u0441\u043a\u043e\u0435"
    ],
    "wof:name":"Kirovskoye",
    "wof:placetype":"locality"
},
  "geometry": {"coordinates":[83.05324,49.88979000000001],"type":"Point"}
}