{
  "type": "Feature",
  "properties": {
    "gn:admin1_code":"14.0",
    "gn:asciiname":"Baykenzhe",
    "gn:country_code":"KZ",
    "gn:dem":156,
    "gn:feature_class":"P",
    "gn:feature_code":"PPL",
    "gn:name":"Baykenzhe",
    "gn:population":0,
    "gn:timezone":"Asia/Qyzylorda",
    "iso:country":"KZ",
    "name:kaz_x_preferred":[
        "Baykenzhe"
    ],
    "name:kaz_x_variant":[
        "\u0411\u0430\u0439\u043a\u0435\u043d\u0436\u0435"
    ],
    "wof:name":"Baykenzhe",
    "wof:placetype":"locality"
},
  "geometry": {"coordinates":[66.91661999999999,43.88948],"type":"Point"}
}