{
  "type": "Feature",
  "properties": {
    "gn:admin1_code":"15.0",
    "gn:asciiname":"Moyaldy-Kupal'naya",
    "gn:country_code":"KZ",
    "gn:dem":165,
    "gn:feature_class":"P",
    "gn:feature_code":"PPL",
    "gn:name":"Moyaldy-Kupal\u2019naya",
    "gn:population":0,
    "gn:timezone":"Asia/Almaty",
    "iso:country":"KZ",
    "name:eng_x_preferred":[
        "Moyaldy-Kupal'naya"
    ],
    "name:rus_x_preferred":[
        "\u041c\u043e\u044f\u043b\u0434\u044b-\u041a\u0443\u043f\u0430\u043b\u044c\u043d\u0430\u044f"
    ],
    "name:und_x_variant":[
        "Moyaldy-Kupal\u2019naya"
    ],
    "wof:name":"Moyaldy-Kupal'naya",
    "wof:placetype":"locality"
},
  "geometry": {"coordinates":[79.11381,51.35928],"type":"Point"}
}