{
  "type": "Feature",
  "properties": {
    "gn:admin1_code":"4.0",
    "gn:asciiname":"Batpakty",
    "gn:country_code":"KZ",
    "gn:dem":285,
    "gn:feature_class":"P",
    "gn:feature_code":"PPL",
    "gn:name":"Batpakty",
    "gn:population":0,
    "gn:timezone":"Asia/Aqtobe",
    "iso:country":"KZ",
    "wof:name":"Batpakty",
    "wof:placetype":"locality"
},
  "geometry": {"coordinates":[57.15,49.71667],"type":"Point"}
}