{
  "type": "Feature",
  "properties": {
    "gn:admin1_code":"4.0",
    "gn:asciiname":"Aul Nomer Devyatyy",
    "gn:country_code":"KZ",
    "gn:dem":95,
    "gn:feature_class":"P",
    "gn:feature_code":"PPL",
    "gn:name":"Aul Nomer Devyatyy",
    "gn:population":0,
    "gn:timezone":"Asia/Aqtobe",
    "iso:country":"KZ",
    "wof:name":"Aul Nomer Devyatyy",
    "wof:placetype":"locality"
},
  "geometry": {"coordinates":[55.73333,48.15],"type":"Point"}
}