{
  "type": "Feature",
  "properties": {
    "gn:admin1_code":"12.0",
    "gn:asciiname":"Zhumabek",
    "gn:country_code":"KZ",
    "gn:dem":549,
    "gn:feature_class":"P",
    "gn:feature_code":"PPL",
    "gn:name":"Zhumabek",
    "gn:population":0,
    "gn:timezone":"Asia/Almaty",
    "iso:country":"KZ",
    "name:kaz_x_preferred":[
        "Zhumabek"
    ],
    "name:kaz_x_variant":[
        "\u0416\u04b1\u043c\u0430\u0431\u0435\u043a"
    ],
    "name:rus_x_preferred":[
        "\u0416\u0443\u043c\u0430\u0431\u0435\u043a"
    ],
    "wof:name":"Zhumabek",
    "wof:placetype":"locality"
},
  "geometry": {"coordinates":[73.22051999999999,49.59784000000001],"type":"Point"}
}