{
  "type": "Feature",
  "properties": {
    "gn:admin1_code":"14.0",
    "gn:asciiname":"Karasha",
    "gn:country_code":"KZ",
    "gn:dem":167,
    "gn:feature_class":"P",
    "gn:feature_code":"PPL",
    "gn:name":"Karasha",
    "gn:population":0,
    "gn:timezone":"Asia/Qyzylorda",
    "iso:country":"KZ",
    "name:rus_x_preferred":[
        "\u041a\u0430\u0440\u0430\u0448\u0430"
    ],
    "wof:name":"Karasha",
    "wof:placetype":"locality"
},
  "geometry": {"coordinates":[67.2419,43.74552],"type":"Point"}
}