{
  "type": "Feature",
  "properties": {
    "gn:admin1_code":"0.0",
    "gn:asciiname":"Bokhtygirey",
    "gn:cc2":"KZ",
    "gn:country_code":"KZ",
    "gn:dem":12,
    "gn:feature_class":"P",
    "gn:feature_code":"PPL",
    "gn:name":"Bokhtygirey",
    "gn:population":0,
    "gn:timezone":"Asia/Oral",
    "iso:country":"KZ",
    "name:und_x_variant":[
        "Baktygirey",
        "Bokhtygirey"
    ],
    "wof:name":"Bokhtygirey",
    "wof:placetype":"locality"
},
  "geometry": {"coordinates":[51.53333,50.16667],"type":"Point"}
}