{
  "type": "Feature",
  "properties": {
    "gn:admin1_code":"10.0",
    "gn:asciiname":"Ani-Muratbay",
    "gn:country_code":"KZ",
    "gn:dem":252,
    "gn:feature_class":"P",
    "gn:feature_code":"PPL",
    "gn:name":"Ani-Muratbay",
    "gn:population":0,
    "gn:timezone":"Asia/Almaty",
    "iso:country":"KZ",
    "wof:name":"Ani-Muratbay",
    "wof:placetype":"locality"
},
  "geometry": {"coordinates":[68.61667,41.03333],"type":"Point"}
}