{
  "type": "Feature",
  "properties": {
    "gn:admin1_code":"16.0",
    "gn:asciiname":"Vsevolodovka",
    "gn:country_code":"KZ",
    "gn:dem":198,
    "gn:feature_class":"P",
    "gn:feature_code":"PPL",
    "gn:name":"Vsevolodovka",
    "gn:population":0,
    "gn:timezone":"Asia/Almaty",
    "iso:country":"KZ",
    "name:eng_x_preferred":[
        "Vsevolodovka"
    ],
    "name:kaz_x_preferred":[
        "\u0412\u0441\u0435\u0432\u043e\u043b\u043e\u0434\u043e\u0432\u043a\u0430"
    ],
    "name:rus_x_preferred":[
        "\u0412\u0441\u0435\u0432\u043e\u043b\u043e\u0434\u043e\u0432\u043a\u0430"
    ],
    "wof:name":"Vsevolodovka",
    "wof:placetype":"locality"
},
  "geometry": {"coordinates":[67.42487,53.43819000000001],"type":"Point"}
}