{
  "type": "Feature",
  "properties": {
    "gn:admin1_code":"14.0",
    "gn:asciiname":"Bulyuk-Bay",
    "gn:country_code":"KZ",
    "gn:dem":160,
    "gn:feature_class":"P",
    "gn:feature_code":"PPL",
    "gn:name":"Bulyuk-Bay",
    "gn:population":0,
    "gn:timezone":"Asia/Qyzylorda",
    "iso:country":"KZ",
    "wof:name":"Bulyuk-Bay",
    "wof:placetype":"locality"
},
  "geometry": {"coordinates":[67.09999999999999,43.95],"type":"Point"}
}