{
  "type": "Feature",
  "properties": {
    "gn:admin1_code":"1.0",
    "gn:asciiname":"Novoalekseyevka",
    "gn:country_code":"KZ",
    "gn:dem":663,
    "gn:feature_class":"P",
    "gn:feature_code":"PPL",
    "gn:name":"Novoalekseyevka",
    "gn:population":0,
    "gn:timezone":"Asia/Almaty",
    "iso:country":"KZ",
    "name:ceb_x_preferred":[
        "Novoalekseyevka"
    ],
    "name:kaz_x_preferred":[
        "Novoalekseevka"
    ],
    "name:kaz_x_variant":[
        "\u041d\u043e\u0432\u043e\u0430\u043b\u0435\u043a\u0441\u0435\u0435\u0432\u043a\u0430",
        "\u0411\u04d9\u0439\u0442\u0435\u0440\u0435\u043a"
    ],
    "name:msa_x_preferred":[
        "Novoalekseevka"
    ],
    "name:rus_x_preferred":[
        "\u0411\u0430\u0439\u0442\u0435\u0440\u0435\u043a"
    ],
    "name:ukr_x_preferred":[
        "\u0411\u0430\u0439\u0442\u0435\u0440\u0435\u043a"
    ],
    "name:und_x_variant":[
        "Alekseyevka",
        "Novo-Alekseyevskoye"
    ],
    "wof:name":"Novoalekseyevka",
    "wof:placetype":"locality"
},
  "geometry": {"coordinates":[77.23881999999998,43.41743],"type":"Point"}
}