{
  "type": "Feature",
  "properties": {
    "gn:admin1_code":"11.0",
    "gn:asciiname":"Shangdy",
    "gn:country_code":"KZ",
    "gn:dem":122,
    "gn:feature_class":"P",
    "gn:feature_code":"PPL",
    "gn:name":"Shangdy",
    "gn:population":0,
    "gn:timezone":"Asia/Almaty",
    "iso:country":"KZ",
    "name:kaz_x_preferred":[
        "Shangdy"
    ],
    "name:kaz_x_variant":[
        "\u0428\u0430\u04a3\u0434\u044b"
    ],
    "name:rus_x_preferred":[
        "\u0428\u0430\u043d\u0434\u044b"
    ],
    "name:und_x_variant":[
        "Shandy"
    ],
    "wof:name":"Shangdy",
    "wof:placetype":"locality"
},
  "geometry": {"coordinates":[77.25124,52.3321],"type":"Point"}
}