{
  "type": "Feature",
  "properties": {
    "gn:admin1_code":"16.0",
    "gn:asciiname":"Cherkasskoye",
    "gn:country_code":"KZ",
    "gn:dem":136,
    "gn:feature_class":"P",
    "gn:feature_code":"PPL",
    "gn:name":"Cherkasskoye",
    "gn:population":0,
    "gn:timezone":"Asia/Almaty",
    "iso:country":"KZ",
    "name:eng_x_preferred":[
        "Cherkasskoe"
    ],
    "name:kaz_x_preferred":[
        "Cherkasskoe"
    ],
    "name:kaz_x_variant":[
        "\u0427\u0435\u0440\u043a\u0430\u0441\u0441\u043a\u043e\u0435"
    ],
    "name:rus_x_preferred":[
        "\u0427\u0435\u0440\u043a\u0430\u0441\u0441\u043a\u043e\u0435"
    ],
    "name:und_x_variant":[
        "Cherkasskiy"
    ],
    "wof:name":"Cherkasskoye",
    "wof:placetype":"locality"
},
  "geometry": {"coordinates":[69.76671,54.36904000000001],"type":"Point"}
}