{
  "type": "Feature",
  "properties": {
    "gn:admin1_code":"1.0",
    "gn:asciiname":"Bereke",
    "gn:country_code":"KZ",
    "gn:dem":676,
    "gn:feature_class":"P",
    "gn:feature_code":"PPL",
    "gn:name":"Bereke",
    "gn:population":0,
    "gn:timezone":"Asia/Almaty",
    "iso:country":"KZ",
    "name:kaz_x_preferred":[
        "\u0411\u0435\u0440\u0435\u043a\u0435"
    ],
    "name:und_x_variant":[
        "Yel\u2019tay",
        "El\u2019tay",
        "Bekete",
        "Bereke"
    ],
    "wof:name":"Bereke",
    "wof:placetype":"locality"
},
  "geometry": {"coordinates":[76.71087,43.3757],"type":"Point"}
}