{
  "type": "Feature",
  "properties": {
    "gn:admin1_code":"0.0",
    "gn:asciiname":"Solodovnikov",
    "gn:cc2":"KZ",
    "gn:country_code":"KZ",
    "gn:dem":56,
    "gn:feature_class":"P",
    "gn:feature_code":"PPL",
    "gn:name":"Solodovnikov",
    "gn:population":0,
    "gn:timezone":"Asia/Oral",
    "iso:country":"KZ",
    "name:und_x_variant":[
        "Solodovenikov",
        "Solodovnikov"
    ],
    "wof:name":"Solodovnikov",
    "wof:placetype":"locality"
},
  "geometry": {"coordinates":[51.25,51.38333],"type":"Point"}
}