{
  "type": "Feature",
  "properties": {
    "gn:admin1_code":"0.0",
    "gn:asciiname":"Malyy Sherbakov",
    "gn:cc2":"KZ",
    "gn:country_code":"KZ",
    "gn:dem":25,
    "gn:feature_class":"P",
    "gn:feature_code":"PPL",
    "gn:name":"Malyy Sherbakov",
    "gn:population":0,
    "gn:timezone":"Asia/Oral",
    "iso:country":"KZ",
    "name:und_x_variant":[
        "Malaya Sherba",
        "Malyy Sherbakov"
    ],
    "wof:name":"Malyy Sherbakov",
    "wof:placetype":"locality"
},
  "geometry": {"coordinates":[50.95,50.91667],"type":"Point"}
}