{
  "type": "Feature",
  "properties": {
    "gn:admin1_code":"0.0",
    "gn:asciiname":"Kryk-Uru",
    "gn:country_code":"KZ",
    "gn:dem":1,
    "gn:feature_class":"P",
    "gn:feature_code":"PPL",
    "gn:name":"Kryk-Uru",
    "gn:population":0,
    "gn:timezone":"Asia/Oral",
    "iso:country":"KZ",
    "wof:name":"Kryk-Uru",
    "wof:placetype":"locality"
},
  "geometry": {"coordinates":[49.08333,49.76667],"type":"Point"}
}