{
  "type": "Feature",
  "properties": {
    "gn:admin1_code":"3.0",
    "gn:asciiname":"Novoishimka",
    "gn:country_code":"KZ",
    "gn:dem":326,
    "gn:feature_class":"P",
    "gn:feature_code":"PPL",
    "gn:name":"Novoishimka",
    "gn:population":0,
    "gn:timezone":"Asia/Almaty",
    "iso:country":"KZ",
    "name:kaz_x_preferred":[
        "Novo\u012bsh\u012bmka"
    ],
    "name:und_x_variant":[
        "Novoishimskiy"
    ],
    "wof:name":"Novoishimka",
    "wof:placetype":"locality"
},
  "geometry": {"coordinates":[70.72575000000001,51.29942],"type":"Point"}
}