{
  "type": "Feature",
  "properties": {
    "gn:admin1_code":"0.0",
    "gn:asciiname":"Zhiyenbet",
    "gn:cc2":"KZ",
    "gn:country_code":"KZ",
    "gn:dem":7,
    "gn:feature_class":"P",
    "gn:feature_code":"PPL",
    "gn:name":"Zhiyenbet",
    "gn:population":0,
    "gn:timezone":"Asia/Oral",
    "iso:country":"KZ",
    "name:eng_x_preferred":[
        "Zhiyenbet"
    ],
    "name:rus_x_preferred":[
        "\u0416\u0438\u0435\u043d\u0431\u0435\u0442"
    ],
    "name:und_x_variant":[
        "Dzhiyembet",
        "Zhiyembet",
        "Dizhiembet",
        "Zhiyenbet"
    ],
    "wof:name":"Zhiyenbet",
    "wof:placetype":"locality"
},
  "geometry": {"coordinates":[47.85,49.51667],"type":"Point"}
}