{
  "type": "Feature",
  "properties": {
    "gn:admin1_code":"12.0",
    "gn:asciiname":"Shenber",
    "gn:country_code":"KZ",
    "gn:dem":422,
    "gn:feature_class":"P",
    "gn:feature_code":"PPL",
    "gn:name":"Shenber",
    "gn:population":0,
    "gn:timezone":"Asia/Almaty",
    "iso:country":"KZ",
    "wof:name":"Shenber",
    "wof:placetype":"locality"
},
  "geometry": {"coordinates":[67.41667,49.71667],"type":"Point"}
}