{
  "type": "Feature",
  "properties": {
    "gn:admin1_code":"12.0",
    "gn:asciiname":"Zhanganegiz",
    "gn:country_code":"KZ",
    "gn:dem":778,
    "gn:feature_class":"P",
    "gn:feature_code":"PPL",
    "gn:name":"Zhanganegiz",
    "gn:population":0,
    "gn:timezone":"Asia/Almaty",
    "iso:country":"KZ",
    "name:kaz_x_preferred":[
        "Zhanganegiz"
    ],
    "name:kaz_x_variant":[
        "\u0416\u0430\u04a3\u0430\u043d\u0435\u0433\u0456\u0437"
    ],
    "name:rus_x_preferred":[
        "\u0416\u0430\u043d\u0430\u043d\u0435\u0433\u0438\u0437"
    ],
    "name:und_x_variant":[
        "Zhananegiz"
    ],
    "wof:name":"Zhanganegiz",
    "wof:placetype":"locality"
},
  "geometry": {"coordinates":[75.51408000000001,49.47712],"type":"Point"}
}