{
  "type": "Feature",
  "properties": {
    "gn:admin1_code":"4.0",
    "gn:asciiname":"Blagoveshchenskoye",
    "gn:country_code":"KZ",
    "gn:dem":288,
    "gn:feature_class":"P",
    "gn:feature_code":"PPL",
    "gn:name":"Blagoveshchenskoye",
    "gn:population":0,
    "gn:timezone":"Asia/Aqtobe",
    "iso:country":"KZ",
    "name:eng_x_preferred":[
        "Blagoveshchenskoye"
    ],
    "name:rus_x_preferred":[
        "\u0411\u043b\u0430\u0433\u043e\u0432\u0435\u0449\u0435\u043d\u0441\u043a\u043e\u0435"
    ],
    "name:und_x_variant":[
        "Blagoveshchenskiy",
        "Blagoveshchenskoye"
    ],
    "wof:name":"Blagoveshchenskoye",
    "wof:placetype":"locality"
},
  "geometry": {"coordinates":[56.37041,49.65174],"type":"Point"}
}