{
  "type": "Feature",
  "properties": {
    "gn:admin1_code":"11.0",
    "gn:asciiname":"Tleubay",
    "gn:country_code":"KZ",
    "gn:dem":104,
    "gn:feature_class":"P",
    "gn:feature_code":"PPL",
    "gn:name":"Tleubay",
    "gn:population":0,
    "gn:timezone":"Asia/Almaty",
    "iso:country":"KZ",
    "name:eng_x_preferred":[
        "Tleubay"
    ],
    "name:kaz_x_preferred":[
        "Tile\u016bbay"
    ],
    "name:kaz_x_variant":[
        "\u0422\u0456\u043b\u0435\u0443\u0431\u0430\u0439"
    ],
    "name:rus_x_preferred":[
        "\u0422\u043b\u0435\u0443\u0431\u0430\u0439"
    ],
    "wof:name":"Tleubay",
    "wof:placetype":"locality"
},
  "geometry": {"coordinates":[76.65552,53.03343],"type":"Point"}
}