{
  "type": "Feature",
  "properties": {
    "gn:admin1_code":"1.0",
    "gn:asciiname":"Arkabay",
    "gn:country_code":"KZ",
    "gn:dem":647,
    "gn:feature_class":"P",
    "gn:feature_code":"PPL",
    "gn:name":"Arkabay",
    "gn:population":0,
    "gn:timezone":"Asia/Almaty",
    "iso:country":"KZ",
    "name:mkd_x_preferred":[
        "\u0410\u0440\u043a\u0430\u0431\u0430\u0458"
    ],
    "name:msa_x_preferred":[
        "Arkabay"
    ],
    "name:rus_x_preferred":[
        "\u0410\u0440\u043a\u0430\u0431\u0430\u0439"
    ],
    "name:und_x_variant":[
        "Molochno Tovarnaya Ferma Brigady Nomer Dva Kolkhoza Kyzyltu",
        "Arkabay"
    ],
    "wof:name":"Arkabay",
    "wof:placetype":"locality"
},
  "geometry": {"coordinates":[77.09390999999999,43.41694],"type":"Point"}
}