{
  "type": "Feature",
  "properties": {
    "gn:admin1_code":"1.0",
    "gn:asciiname":"Alatay",
    "gn:country_code":"KZ",
    "gn:dem":766,
    "gn:feature_class":"P",
    "gn:feature_code":"PPL",
    "gn:name":"Alatay",
    "gn:population":0,
    "gn:timezone":"Asia/Almaty",
    "iso:country":"KZ",
    "name:kaz_x_preferred":[
        "Alata\u016b"
    ],
    "name:kaz_x_variant":[
        "\u0410\u043b\u0430\u0442\u0430\u0443"
    ],
    "wof:name":"Alatay",
    "wof:placetype":"locality"
},
  "geometry": {"coordinates":[77.14119000000002,43.35831],"type":"Point"}
}