{
  "type": "Feature",
  "properties": {
    "gn:admin1_code":"6.0",
    "gn:asciiname":"Burankol'",
    "gn:country_code":"KZ",
    "gn:dem":120,
    "gn:feature_class":"P",
    "gn:feature_code":"PPL",
    "gn:name":"Burankol\u2019",
    "gn:population":0,
    "gn:timezone":"Asia/Atyrau",
    "iso:country":"KZ",
    "name:und_x_variant":[
        "Burakol\u2019",
        "Birakol\u2019",
        "Burankol\u2019"
    ],
    "wof:name":"Burankol'",
    "wof:placetype":"locality"
},
  "geometry": {"coordinates":[54.83333,47.86667],"type":"Point"}
}