{
  "type": "Feature",
  "properties": {
    "gn:admin1_code":"0.0",
    "gn:asciiname":"Kopeni",
    "gn:country_code":"KZ",
    "gn:dem":92,
    "gn:feature_class":"P",
    "gn:feature_code":"PPL",
    "gn:name":"Kopeni",
    "gn:population":0,
    "gn:timezone":"Asia/Oral",
    "iso:country":"KZ",
    "wof:name":"Kopeni",
    "wof:placetype":"locality"
},
  "geometry": {"coordinates":[50.73333,51.45],"type":"Point"}
}