{
  "type": "Feature",
  "properties": {
    "gn:admin1_code":"11.0",
    "gn:asciiname":"Tendik",
    "gn:country_code":"KZ",
    "gn:dem":406,
    "gn:feature_class":"P",
    "gn:feature_code":"PPL",
    "gn:name":"Tendik",
    "gn:population":0,
    "gn:timezone":"Asia/Almaty",
    "iso:country":"KZ",
    "name:kaz_x_preferred":[
        "Tengdik"
    ],
    "name:kaz_x_variant":[
        "\u0422\u0435\u04a3\u0434\u0456\u043a"
    ],
    "name:rus_x_preferred":[
        "\u0422\u0435\u043d\u0434\u0438\u043a"
    ],
    "name:und_x_variant":[
        "Tendyk",
        "Tendik"
    ],
    "wof:name":"Tendik",
    "wof:placetype":"locality"
},
  "geometry": {"coordinates":[74.76867,50.63468],"type":"Point"}
}