{
  "type": "Feature",
  "properties": {
    "gn:admin1_code":"10.0",
    "gn:asciiname":"Pushkino",
    "gn:country_code":"KZ",
    "gn:dem":387,
    "gn:feature_class":"P",
    "gn:feature_code":"PPL",
    "gn:name":"P\u016bshk\u012bno",
    "gn:population":0,
    "gn:timezone":"Asia/Almaty",
    "iso:country":"KZ",
    "name:kaz_x_preferred":[
        "P\u016bshk\u012bno"
    ],
    "name:kaz_x_variant":[
        "\u041f\u0443\u0448\u043a\u0438\u043d\u043e"
    ],
    "wof:name":"Pushkino",
    "wof:placetype":"locality"
},
  "geometry": {"coordinates":[68.61827,43.41692000000001],"type":"Point"}
}