{
  "type": "Feature",
  "properties": {
    "gn:admin1_code":"0.0",
    "gn:asciiname":"Simonovskiy",
    "gn:country_code":"KZ",
    "gn:dem":222,
    "gn:feature_class":"P",
    "gn:feature_code":"PPL",
    "gn:name":"Simonovskiy",
    "gn:population":0,
    "gn:timezone":"Asia/Qyzylorda",
    "iso:country":"KZ",
    "wof:name":"Simonovskiy",
    "wof:placetype":"locality"
},
  "geometry": {"coordinates":[62.13333000000001,52.41667],"type":"Point"}
}