{
  "type": "Feature",
  "properties": {
    "iso:country":"KZ",
    "name:dut_x_preferred":[
        "Chagan"
    ],
    "name:eng_x_preferred":[
        "Shaghan"
    ],
    "name:fra_x_preferred":[
        "Chagan"
    ],
    "name:kaz_x_preferred":[
        "\u0428\u0430\u0493\u0430\u043d"
    ],
    "name:pol_x_preferred":[
        "Czagan"
    ],
    "name:rus_x_preferred":[
        "\u0427\u0430\u0433\u0430\u043d"
    ],
    "name:ukr_x_preferred":[
        "\u0427\u0430\u0433\u0430\u043d"
    ],
    "name:unk_x_variant":[
        "Shagan"
    ],
    "qs:gn_country":"KZ",
    "qs:gn_fcode":"PPL",
    "qs:gn_pop":478,
    "qs:name":"Chagan",
    "qs:name_adm0":"Kazakhstan",
    "qs:name_adm1":"Shyghys Qazaqstan",
    "qs:photos":0,
    "qs:photos_1k":0,
    "qs:photos_9k":0,
    "qs:photos_9r":0,
    "qs:photos_all":0,
    "qs:photos_sr":0,
    "qs:placetype":"Town",
    "qs:pop_sr":"2",
    "qs:woe_adm0":23424871,
    "wd:wordcount":123,
    "wof:name":"Chagan",
    "wof:placetype":"locality",
    "wof:population":478
},
  "geometry": {"coordinates":[79.24742999999999,50.62178],"type":"Point"}
}