{
  "type": "Feature",
  "properties": {
    "gn:admin1_code":"0.0",
    "gn:asciiname":"Kazakhstan",
    "gn:country_code":"KZ",
    "gn:dem":383,
    "gn:feature_class":"P",
    "gn:feature_code":"PPL",
    "gn:name":"Kazakhstan",
    "gn:population":0,
    "gn:timezone":"Asia/Almaty",
    "iso:country":"KZ",
    "wof:name":"Kazakhstan",
    "wof:placetype":"locality"
},
  "geometry": {"coordinates":[81.01906,46.19679],"type":"Point"}
}