{
  "type": "Feature",
  "properties": {
    "gn:admin1_code":"4.0",
    "gn:asciiname":"Romanovskiy",
    "gn:country_code":"KZ",
    "gn:dem":356,
    "gn:feature_class":"P",
    "gn:feature_code":"PPL",
    "gn:name":"Romanovskiy",
    "gn:population":0,
    "gn:timezone":"Asia/Aqtobe",
    "iso:country":"KZ",
    "name:eng_x_preferred":[
        "Romanovskiy"
    ],
    "name:rus_x_preferred":[
        "\u0420\u043e\u043c\u0430\u043d\u043e\u0432\u043a\u0430"
    ],
    "wof:name":"Romanovskiy",
    "wof:placetype":"locality"
},
  "geometry": {"coordinates":[58.46666999999999,49.46667],"type":"Point"}
}