{
  "type": "Feature",
  "properties": {
    "gn:admin1_code":"16.0",
    "gn:asciiname":"Bereslavka",
    "gn:country_code":"KZ",
    "gn:dem":357,
    "gn:feature_class":"P",
    "gn:feature_code":"PPL",
    "gn:name":"Bereslavka",
    "gn:population":0,
    "gn:timezone":"Asia/Almaty",
    "iso:country":"KZ",
    "name:eng_x_preferred":[
        "Bereslavka"
    ],
    "name:ita_x_preferred":[
        "Bereslavka"
    ],
    "name:kaz_x_preferred":[
        "\u0411\u0435\u0440\u0435\u0441\u043b\u0430\u0432\u043a\u0430"
    ],
    "name:rus_x_preferred":[
        "\u0411\u0435\u0440\u0435\u0441\u043b\u0430\u0432\u043a\u0430"
    ],
    "name:rus_x_variant":[
        "\u0411\u0435\u0440\u0438\u0441\u043b\u0430\u0432\u043a\u0430"
    ],
    "name:sco_x_preferred":[
        "Bereslavka"
    ],
    "name:ukr_x_preferred":[
        "\u0411\u0435\u0440\u0435\u0441\u043b\u0430\u0432\u043a\u0430"
    ],
    "name:und_x_variant":[
        "Berislavko",
        "Bereslavka",
        "Berislavka"
    ],
    "wof:name":"Bereslavka",
    "wof:placetype":"locality"
},
  "geometry": {"coordinates":[67.30126,52.74301],"type":"Point"}
}