{
  "type": "Feature",
  "properties": {
    "gn:admin1_code":"3.0",
    "gn:asciiname":"Chernoyarka",
    "gn:country_code":"KZ",
    "gn:dem":174,
    "gn:feature_class":"P",
    "gn:feature_code":"PPL",
    "gn:name":"Chernoyarka",
    "gn:population":0,
    "gn:timezone":"Asia/Almaty",
    "iso:country":"KZ",
    "name:eng_x_preferred":[
        "Chernoyarka"
    ],
    "name:rus_x_preferred":[
        "\u0427\u0435\u0440\u043d\u043e\u044f\u0440\u043a\u0430"
    ],
    "name:rus_x_variant":[
        "\u0423\u0439\u0442\u0435\u043a\u0435"
    ],
    "name:und_x_variant":[
        "Uyteke",
        "Chernoyarka"
    ],
    "wof:name":"Chernoyarka",
    "wof:placetype":"locality"
},
  "geometry": {"coordinates":[72.80150999999999,52.81968000000001],"type":"Point"}
}