{
  "type": "Feature",
  "properties": {
    "gn:admin1_code":"12.0",
    "gn:asciiname":"Imeni Karla Marksa",
    "gn:country_code":"KZ",
    "gn:dem":422,
    "gn:feature_class":"P",
    "gn:feature_code":"PPL",
    "gn:name":"Imeni Karla Marksa",
    "gn:population":0,
    "gn:timezone":"Asia/Almaty",
    "iso:country":"KZ",
    "wof:name":"Imeni Karla Marksa",
    "wof:placetype":"locality"
},
  "geometry": {"coordinates":[70.48333000000002,48.73333],"type":"Point"}
}