{
  "type": "Feature",
  "properties": {
    "gn:admin1_code":"10.0",
    "gn:asciiname":"Imeni Stalina",
    "gn:country_code":"KZ",
    "gn:dem":287,
    "gn:feature_class":"P",
    "gn:feature_code":"PPL",
    "gn:name":"Imeni Stalina",
    "gn:population":0,
    "gn:timezone":"Asia/Almaty",
    "iso:country":"KZ",
    "wof:name":"Imeni Stalina",
    "wof:placetype":"locality"
},
  "geometry": {"coordinates":[68.65000000000001,41.26667],"type":"Point"}
}