{
  "type": "Feature",
  "properties": {
    "gn:admin1_code":"14.0",
    "gn:asciiname":"Tyupboget",
    "gn:country_code":"KZ",
    "gn:dem":97,
    "gn:feature_class":"P",
    "gn:feature_code":"PPL",
    "gn:name":"Tyupboget",
    "gn:population":0,
    "gn:timezone":"Asia/Qyzylorda",
    "iso:country":"KZ",
    "name:und_x_variant":[
        "Tupboget",
        "Tyupboget"
    ],
    "wof:name":"Tyupboget",
    "wof:placetype":"locality"
},
  "geometry": {"coordinates":[63.83333,45.03333],"type":"Point"}
}