{
  "type": "Feature",
  "properties": {
    "gn:admin1_code":"3.0",
    "gn:asciiname":"Zhasyl",
    "gn:country_code":"KZ",
    "gn:dem":385,
    "gn:feature_class":"P",
    "gn:feature_code":"PPL",
    "gn:name":"Zhasyl",
    "gn:population":0,
    "gn:timezone":"Asia/Almaty",
    "iso:country":"KZ",
    "name:kaz_x_preferred":[
        "Zhasyl"
    ],
    "name:kaz_x_variant":[
        "\u0416\u0430\u0441\u044b\u043b"
    ],
    "wof:name":"Zhasyl",
    "wof:placetype":"locality"
},
  "geometry": {"coordinates":[70.28914,52.78765],"type":"Point"}
}