{
  "type": "Feature",
  "properties": {
    "gn:admin1_code":"0.0",
    "gn:asciiname":"Taldapak",
    "gn:country_code":"KZ",
    "gn:dem":3,
    "gn:feature_class":"P",
    "gn:feature_code":"PPL",
    "gn:name":"Taldapak",
    "gn:population":0,
    "gn:timezone":"Asia/Oral",
    "iso:country":"KZ",
    "name:eng_x_preferred":[
        "Taldapak"
    ],
    "name:rus_x_preferred":[
        "\u0422\u0430\u043b\u0434\u0430\u043f\u0430\u043d"
    ],
    "wof:name":"Taldapak",
    "wof:placetype":"locality"
},
  "geometry": {"coordinates":[47.11667,48.16667],"type":"Point"}
}