{
  "type": "Feature",
  "properties": {
    "gn:admin1_code":"0.0",
    "gn:asciiname":"Chul-Adyr",
    "gn:country_code":"KZ",
    "gn:dem":1904,
    "gn:feature_class":"P",
    "gn:feature_code":"PPL",
    "gn:name":"Chul-Adyr",
    "gn:population":0,
    "gn:timezone":"Asia/Almaty",
    "iso:country":"KZ",
    "wof:name":"Chul-Adyr",
    "wof:placetype":"locality"
},
  "geometry": {"coordinates":[79.33333,42.93333],"type":"Point"}
}