{
  "type": "Feature",
  "properties": {
    "gn:admin1_code":"11.0",
    "gn:asciiname":"Nurbay",
    "gn:country_code":"KZ",
    "gn:dem":160,
    "gn:feature_class":"P",
    "gn:feature_code":"PPL",
    "gn:name":"Nurbay",
    "gn:population":0,
    "gn:timezone":"Asia/Almaty",
    "iso:country":"KZ",
    "name:kaz_x_preferred":[
        "Nurbay"
    ],
    "name:kaz_x_variant":[
        "\u041d\u04b1\u0440\u0431\u0430\u0439"
    ],
    "name:rus_x_preferred":[
        "\u041d\u0443\u0440\u0431\u0430\u0439"
    ],
    "wof:name":"Nurbay",
    "wof:placetype":"locality"
},
  "geometry": {"coordinates":[78.33598000000001,51.46561],"type":"Point"}
}