{
  "type": "Feature",
  "properties": {
    "gn:admin1_code":"16.0",
    "gn:asciiname":"Malkara",
    "gn:country_code":"KZ",
    "gn:dem":125,
    "gn:feature_class":"P",
    "gn:feature_code":"PPL",
    "gn:name":"Malkara",
    "gn:population":0,
    "gn:timezone":"Asia/Almaty",
    "iso:country":"KZ",
    "name:eng_x_preferred":[
        "Malkara"
    ],
    "name:kaz_x_preferred":[
        "Malqara"
    ],
    "name:kaz_x_variant":[
        "\u041c\u0430\u043b\u049b\u0430\u0440\u0430"
    ],
    "name:rus_x_preferred":[
        "\u041c\u0430\u043b\u043a\u0430\u0440\u0430"
    ],
    "wof:name":"Malkara",
    "wof:placetype":"locality"
},
  "geometry": {"coordinates":[73.5883,53.95218000000001],"type":"Point"}
}