{
  "type": "Feature",
  "properties": {
    "gn:admin1_code":"16.0",
    "gn:asciiname":"Malkara",
    "gn:country_code":"KZ",
    "gn:dem":125,
    "gn:feature_class":"P",
    "gn:feature_code":"PPL",
    "gn:name":"Malkara",
    "gn:population":0,
    "gn:timezone":"Asia/Almaty",
    "iso:country":"KZ",
    "name:ara_x_preferred":[
        "\u0645\u0627\u0644\u0643\u0631\u0627"
    ],
    "name:azb_x_preferred":[
        "\u0645\u0627\u0644\u0642\u0627\u0631\u0627"
    ],
    "name:bul_x_preferred":[
        "\u041c\u0430\u043b\u0433\u0430\u0440\u0430"
    ],
    "name:cat_x_preferred":[
        "Malkara"
    ],
    "name:ceb_x_preferred":[
        "Malkara"
    ],
    "name:deu_x_preferred":[
        "Malkara"
    ],
    "name:eng_x_preferred":[
        "Malkara"
    ],
    "name:fas_x_preferred":[
        "\u0645\u0627\u0644\u200c\u06a9\u0627\u0631\u0627"
    ],
    "name:fra_x_preferred":[
        "Malkara"
    ],
    "name:kaz_x_preferred":[
        "Malqara"
    ],
    "name:kaz_x_variant":[
        "\u041c\u0430\u043b\u049b\u0430\u0440\u0430"
    ],
    "name:min_x_preferred":[
        "Malkara"
    ],
    "name:mrj_x_preferred":[
        "\u041c\u0430\u043b\u043a\u0430\u0440\u0430"
    ],
    "name:msa_x_preferred":[
        "Malkara"
    ],
    "name:nld_x_preferred":[
        "Malkara"
    ],
    "name:nno_x_preferred":[
        "Malkara"
    ],
    "name:nor_x_preferred":[
        "Malkara"
    ],
    "name:pnb_x_preferred":[
        "\u0636\u0644\u0639 \u0645\u0627\u0644\u06a9\u0627\u0631\u0627"
    ],
    "name:rus_x_preferred":[
        "\u041c\u0430\u043b\u043a\u0430\u0440\u0430"
    ],
    "name:swa_x_preferred":[
        "Malkara"
    ],
    "name:tur_x_preferred":[
        "Malkara"
    ],
    "name:urd_x_preferred":[
        "\u0645\u0627\u0644\u06a9\u0627\u0631\u0627"
    ],
    "name:vie_x_preferred":[
        "Malkara"
    ],
    "name:zho_x_preferred":[
        "\u99ac\u723e\u5361\u62c9"
    ],
    "wof:name":"Malkara",
    "wof:placetype":"locality"
},
  "geometry": {"coordinates":[73.5883,53.95218000000001],"type":"Point"}
}