{
  "type": "Feature",
  "properties": {
    "gn:admin1_code":"3.0",
    "gn:asciiname":"Krasnyy Gornyak",
    "gn:country_code":"KZ",
    "gn:dem":388,
    "gn:feature_class":"P",
    "gn:feature_code":"PPL",
    "gn:name":"Krasnyy Gornyak",
    "gn:population":0,
    "gn:timezone":"Asia/Almaty",
    "iso:country":"KZ",
    "name:rus_x_preferred":[
        "\u041a\u0440\u0430\u0441\u043d\u044b\u0439 \u0413\u043e\u0440\u043d\u044f\u043a"
    ],
    "wof:name":"Krasnyy Gornyak",
    "wof:placetype":"locality"
},
  "geometry": {"coordinates":[70.96693,52.14232],"type":"Point"}
}