{
  "type": "Feature",
  "properties": {
    "gn:admin1_code":"1.0",
    "gn:asciiname":"Kokozek",
    "gn:cc2":"KZ",
    "gn:country_code":"KZ",
    "gn:dem":702,
    "gn:feature_class":"P",
    "gn:feature_code":"PPL",
    "gn:name":"Kokozek",
    "gn:population":0,
    "gn:timezone":"Asia/Almaty",
    "iso:country":"KZ",
    "name:rus_x_preferred":[
        "\u041a\u043e\u043a\u043e\u0437\u0435\u043a"
    ],
    "name:und_x_variant":[
        "Kok-Uzek",
        "Kogozek",
        "Kokozek"
    ],
    "wof:name":"Kokozek",
    "wof:placetype":"locality"
},
  "geometry": {"coordinates":[76.76805999999998,43.3475],"type":"Point"}
}