{
  "type": "Feature",
  "properties": {
    "gn:admin1_code":"11.0",
    "gn:asciiname":"Zhapalaq",
    "gn:country_code":"KZ",
    "gn:dem":403,
    "gn:feature_class":"P",
    "gn:feature_code":"PPL",
    "gn:name":"Zhapalaq",
    "gn:population":0,
    "gn:timezone":"Asia/Almaty",
    "iso:country":"KZ",
    "name:kaz_x_preferred":[
        "Zhapalaq"
    ],
    "name:kaz_x_variant":[
        "\u0416\u0430\u043f\u0430\u043b\u0430\u049b"
    ],
    "name:rus_x_preferred":[
        "\u0416\u0430\u043f\u0430\u043b\u0430\u043a"
    ],
    "name:und_x_variant":[
        "Zhapalak"
    ],
    "wof:name":"Zhapalaq",
    "wof:placetype":"locality"
},
  "geometry": {"coordinates":[75.87120999999998,50.68561],"type":"Point"}
}