{
  "type": "Feature",
  "properties": {
    "gn:admin1_code":"3.0",
    "gn:asciiname":"Verenka",
    "gn:country_code":"KZ",
    "gn:dem":319,
    "gn:feature_class":"P",
    "gn:feature_code":"PPL",
    "gn:name":"Verenka",
    "gn:population":0,
    "gn:timezone":"Asia/Almaty",
    "iso:country":"KZ",
    "name:kaz_x_preferred":[
        "\u0412\u0435\u0440\u0435\u043d\u043a\u0430"
    ],
    "name:und_x_variant":[
        "Verinskiy",
        "Verinskoye",
        "Verenka"
    ],
    "wof:name":"Verenka",
    "wof:placetype":"locality"
},
  "geometry": {"coordinates":[72.55216999999998,51.52626],"type":"Point"}
}