{
  "type": "Feature",
  "properties": {
    "gn:admin1_code":"12.0",
    "gn:asciiname":"Dzhakpek",
    "gn:country_code":"KZ",
    "gn:dem":293,
    "gn:feature_class":"P",
    "gn:feature_code":"PPL",
    "gn:name":"Dzhakpek",
    "gn:population":0,
    "gn:timezone":"Asia/Almaty",
    "iso:country":"KZ",
    "wof:name":"Dzhakpek",
    "wof:placetype":"locality"
},
  "geometry": {"coordinates":[69.03333000000001,47.26667],"type":"Point"}
}