{
  "type": "Feature",
  "properties": {
    "gn:admin1_code":"10.0",
    "gn:asciiname":"Imeni Sabira Rakhimova",
    "gn:country_code":"KZ",
    "gn:dem":268,
    "gn:feature_class":"P",
    "gn:feature_code":"PPL",
    "gn:name":"Imeni Sabira Rakhimova",
    "gn:population":0,
    "gn:timezone":"Asia/Almaty",
    "iso:country":"KZ",
    "name:rus_x_preferred":[
        "\u0418\u043c\u0435\u043d\u0438 \u0421\u0430\u0431\u0438\u0440\u0430 \u0420\u0430\u0445\u0438\u043c\u043e\u0432\u0430"
    ],
    "wof:name":"Imeni Sabira Rakhimova",
    "wof:placetype":"locality"
},
  "geometry": {"coordinates":[68.60261,40.67542],"type":"Point"}
}