{
  "type": "Feature",
  "properties": {
    "gn:admin1_code":"0.0",
    "gn:asciiname":"Ishchan-Kub",
    "gn:country_code":"KZ",
    "gn:dem":6,
    "gn:feature_class":"P",
    "gn:feature_code":"PPL",
    "gn:name":"Ishchan-Kub",
    "gn:population":0,
    "gn:timezone":"Asia/Oral",
    "iso:country":"KZ",
    "wof:name":"Ishchan-Kub",
    "wof:placetype":"locality"
},
  "geometry": {"coordinates":[49.56667,50.03333],"type":"Point"}
}