{
  "type": "Feature",
  "properties": {
    "gn:admin1_code":"0.0",
    "gn:asciiname":"Kuznetsov",
    "gn:country_code":"KZ",
    "gn:dem":98,
    "gn:feature_class":"P",
    "gn:feature_code":"PPL",
    "gn:name":"Kuznetsov",
    "gn:population":0,
    "gn:timezone":"Asia/Oral",
    "iso:country":"KZ",
    "wof:name":"Kuznetsov",
    "wof:placetype":"locality"
},
  "geometry": {"coordinates":[50.21667,51.13333],"type":"Point"}
}