{
  "type": "Feature",
  "properties": {
    "gn:admin1_code":"0.0",
    "gn:asciiname":"Kuznetsov",
    "gn:country_code":"KZ",
    "gn:dem":98,
    "gn:feature_class":"P",
    "gn:feature_code":"PPL",
    "gn:name":"Kuznetsov",
    "gn:population":0,
    "gn:timezone":"Asia/Oral",
    "iso:country":"KZ",
    "name:deu_x_preferred":[
        "Kusnezow"
    ],
    "name:kor_x_preferred":[
        "\ucfe0\uc988\ub124\ucd08\ud504"
    ],
    "name:rus_x_preferred":[
        "\u041a\u0443\u0437\u043d\u0435\u0446\u043e\u0432"
    ],
    "wof:name":"Kuznetsov",
    "wof:placetype":"locality"
},
  "geometry": {"coordinates":[50.21667,51.13333],"type":"Point"}
}