{
  "type": "Feature",
  "properties": {
    "gn:admin1_code":"15.0",
    "gn:asciiname":"Krasnaya Shemonaikha",
    "gn:country_code":"KZ",
    "gn:dem":341,
    "gn:feature_class":"P",
    "gn:feature_code":"PPL",
    "gn:name":"Krasnaya Shemonaikha",
    "gn:population":0,
    "gn:timezone":"Asia/Almaty",
    "iso:country":"KZ",
    "name:eng_x_preferred":[
        "Krasnaya Shemonaikha"
    ],
    "name:kaz_x_preferred":[
        "Krasnaya Shemona\u012bkha"
    ],
    "name:kaz_x_variant":[
        "\u041a\u0440\u0430\u0441\u043d\u0430\u044f \u0428\u0435\u043c\u043e\u043d\u0430\u0438\u0445\u0430"
    ],
    "name:rus_x_preferred":[
        "\u041a\u0440\u0430\u0441\u043d\u0430\u044f \u0428\u0435\u043c\u043e\u043d\u0430\u0438\u0445\u0430"
    ],
    "wof:name":"Krasnaya Shemonaikha",
    "wof:placetype":"locality"
},
  "geometry": {"coordinates":[81.91741999999998,50.68513],"type":"Point"}
}