{
  "type": "Feature",
  "properties": {
    "gn:admin1_code":"17.0",
    "gn:asciiname":"Beszhyldyq",
    "gn:country_code":"KZ",
    "gn:dem":560,
    "gn:feature_class":"P",
    "gn:feature_code":"PPL",
    "gn:name":"Beszhyldyq",
    "gn:population":0,
    "gn:timezone":"Asia/Almaty",
    "iso:country":"KZ",
    "name:kaz_x_preferred":[
        "Beszhyldyq"
    ],
    "name:kaz_x_variant":[
        "\u0411\u0435\u0441\u0436\u044b\u043b\u0434\u044b\u049b"
    ],
    "name:rus_x_preferred":[
        "\u0411\u0435\u0441\u0436\u0438\u043b\u0434\u044b\u043a"
    ],
    "name:und_x_variant":[
        "Beszhildyk",
        "Beszhyldyk"
    ],
    "wof:name":"Beszhyldyq",
    "wof:placetype":"locality"
},
  "geometry": {"coordinates":[71.31503000000002,42.99665],"type":"Point"}
}