{
  "type": "Feature",
  "properties": {
    "gn:admin1_code":"11.0",
    "gn:asciiname":"Staraya Zhayma",
    "gn:country_code":"KZ",
    "gn:dem":723,
    "gn:feature_class":"P",
    "gn:feature_code":"PPL",
    "gn:name":"Staraya Zhayma",
    "gn:population":0,
    "gn:timezone":"Asia/Almaty",
    "iso:country":"KZ",
    "name:rus_x_preferred":[
        "\u0421\u0442\u0430\u0440\u0430\u044f \u0416\u0430\u0439\u043c\u0430"
    ],
    "wof:name":"Staraya Zhayma",
    "wof:placetype":"locality"
},
  "geometry": {"coordinates":[75.03473000000002,50.16491],"type":"Point"}
}