{
  "type": "Feature",
  "properties": {
    "gn:admin1_code":"0.0",
    "gn:asciiname":"Nikolayevskiy",
    "gn:cc2":"KZ",
    "gn:country_code":"KZ",
    "gn:dem":396,
    "gn:feature_class":"P",
    "gn:feature_code":"PPL",
    "gn:name":"Nikolayevskiy",
    "gn:population":0,
    "gn:timezone":"Asia/Almaty",
    "iso:country":"KZ",
    "name:und_x_variant":[
        "Nikylevskoe",
        "Nikolayevskiy"
    ],
    "wof:name":"Nikolayevskiy",
    "wof:placetype":"locality"
},
  "geometry": {"coordinates":[81.93333,50.51667],"type":"Point"}
}