{
  "type": "Feature",
  "properties": {
    "gn:admin1_code":"7.0",
    "gn:asciiname":"Rozhkovo",
    "gn:country_code":"KZ",
    "gn:dem":72,
    "gn:feature_class":"P",
    "gn:feature_code":"PPL",
    "gn:name":"Rozhkovo",
    "gn:population":0,
    "gn:timezone":"Asia/Oral",
    "iso:country":"KZ",
    "name:eng_x_preferred":[
        "Rozhkovo"
    ],
    "name:rus_x_preferred":[
        "\u0420\u043e\u0436\u043a\u043e\u0432\u043e"
    ],
    "name:und_x_variant":[
        "Rozhkov",
        "Rozhkovo"
    ],
    "wof:name":"Rozhkovo",
    "wof:placetype":"locality"
},
  "geometry": {"coordinates":[52.30773,51.66424],"type":"Point"}
}