{
  "type": "Feature",
  "properties": {
    "gn:admin1_code":"3.0",
    "gn:asciiname":"Karakol'",
    "gn:country_code":"KZ",
    "gn:dem":244,
    "gn:feature_class":"P",
    "gn:feature_code":"PPL",
    "gn:name":"Karakol\u2019",
    "gn:population":0,
    "gn:timezone":"Asia/Almaty",
    "iso:country":"KZ",
    "name:eng_x_preferred":[
        "Karakol'"
    ],
    "name:kaz_x_preferred":[
        "Qarak\u00f6l"
    ],
    "name:rus_x_preferred":[
        "\u041a\u0430\u0440\u0430\u043a\u043e\u043b\u044c"
    ],
    "name:und_x_variant":[
        "Karakol\u2019skiy",
        "Karakol\u2019"
    ],
    "wof:name":"Karakol'",
    "wof:placetype":"locality"
},
  "geometry": {"coordinates":[65.95619000000001,51.7501],"type":"Point"}
}