{
  "type": "Feature",
  "properties": {
    "gn:admin1_code":"11.0",
    "gn:asciiname":"Shubarkulun",
    "gn:country_code":"KZ",
    "gn:dem":125,
    "gn:feature_class":"P",
    "gn:feature_code":"PPL",
    "gn:name":"Shubarkulun",
    "gn:population":0,
    "gn:timezone":"Asia/Almaty",
    "iso:country":"KZ",
    "name:rus_x_preferred":[
        "\u0428\u0443\u0431\u0430\u0440\u043a\u0443\u043b\u0443\u043d"
    ],
    "wof:name":"Shubarkulun",
    "wof:placetype":"locality"
},
  "geometry": {"coordinates":[75.45524,52.58651],"type":"Point"}
}