{
  "type": "Feature",
  "properties": {
    "gn:admin1_code":"13.0",
    "gn:asciiname":"Lysanovka",
    "gn:country_code":"KZ",
    "gn:dem":183,
    "gn:feature_class":"P",
    "gn:feature_code":"PPL",
    "gn:name":"Lysanovka",
    "gn:population":0,
    "gn:timezone":"Asia/Qyzylorda",
    "iso:country":"KZ",
    "name:rus_x_preferred":[
        "\u041b\u044b\u0441\u0430\u043d\u043e\u0432\u043a\u0430"
    ],
    "wof:name":"Lysanovka",
    "wof:placetype":"locality"
},
  "geometry": {"coordinates":[63.10261,53.50795],"type":"Point"}
}