{
  "type": "Feature",
  "properties": {
    "gn:admin1_code":"10.0",
    "gn:asciiname":"Zhuldyz",
    "gn:country_code":"KZ",
    "gn:dem":513,
    "gn:feature_class":"P",
    "gn:feature_code":"PPL",
    "gn:name":"Zhuldyz",
    "gn:population":0,
    "gn:timezone":"Asia/Almaty",
    "iso:country":"KZ",
    "name:kaz_x_preferred":[
        "Zhuldyz"
    ],
    "name:kaz_x_variant":[
        "\u0416\u04b1\u043b\u0434\u044b\u0437"
    ],
    "name:rus_x_preferred":[
        "\u0416\u0443\u043b\u0434\u044b\u0437"
    ],
    "wof:name":"Zhuldyz",
    "wof:placetype":"locality"
},
  "geometry": {"coordinates":[69.60587,43.18475],"type":"Point"}
}