{
  "type": "Feature",
  "properties": {
    "gn:admin1_code":"1.0",
    "gn:asciiname":"Konovalovka",
    "gn:country_code":"KZ",
    "gn:dem":1346,
    "gn:feature_class":"P",
    "gn:feature_code":"PPL",
    "gn:name":"Konovalovka",
    "gn:population":0,
    "gn:timezone":"Asia/Almaty",
    "iso:country":"KZ",
    "name:kaz_x_preferred":[
        "Konovalovka"
    ],
    "wof:name":"Konovalovka",
    "wof:placetype":"locality"
},
  "geometry": {"coordinates":[78.59747,44.48556],"type":"Point"}
}