{
  "type": "Feature",
  "properties": {
    "gn:admin1_code":"0.0",
    "gn:asciiname":"Tubek",
    "gn:country_code":"KZ",
    "gn:dem":213,
    "gn:feature_class":"P",
    "gn:feature_code":"PPL",
    "gn:name":"Tubek",
    "gn:population":0,
    "gn:timezone":"Asia/Almaty",
    "iso:country":"KZ",
    "name:eng_x_preferred":[
        "Tubek"
    ],
    "name:rus_x_preferred":[
        "\u0422\u0443\u0431\u0435\u043a"
    ],
    "name:und_x_variant":[
        "Karateke",
        "Qarateke",
        "Tubek"
    ],
    "wof:name":"Tubek",
    "wof:placetype":"locality"
},
  "geometry": {"coordinates":[65.10365999999999,51.78049],"type":"Point"}
}