{
  "type": "Feature",
  "properties": {
    "gn:admin1_code":"6.0",
    "gn:asciiname":"Ibekshi",
    "gn:country_code":"KZ",
    "gn:dem":-18,
    "gn:feature_class":"P",
    "gn:feature_code":"PPL",
    "gn:name":"Ibekshi",
    "gn:population":0,
    "gn:timezone":"Asia/Atyrau",
    "iso:country":"KZ",
    "wof:name":"Ibekshi",
    "wof:placetype":"locality"
},
  "geometry": {"coordinates":[48.71667,47.58333],"type":"Point"}
}