{
  "type": "Feature",
  "properties": {
    "gn:admin1_code":"17.0",
    "gn:asciiname":"Kyztoghan",
    "gn:country_code":"KZ",
    "gn:dem":1030,
    "gn:feature_class":"P",
    "gn:feature_code":"PPL",
    "gn:name":"Kyztoghan",
    "gn:population":0,
    "gn:timezone":"Asia/Almaty",
    "iso:country":"KZ",
    "name:kaz_x_preferred":[
        "Kyztoghan"
    ],
    "name:kaz_x_variant":[
        "\u041a\u044b\u0437\u0442\u043e\u0493\u0430\u043d"
    ],
    "name:rus_x_preferred":[
        "\u041a\u044b\u0437\u0442\u043e\u0433\u0430\u043d"
    ],
    "name:und_x_variant":[
        "Kyztogan"
    ],
    "wof:name":"Kyztoghan",
    "wof:placetype":"locality"
},
  "geometry": {"coordinates":[70.32625999999999,42.8889],"type":"Point"}
}