{
  "type": "Feature",
  "properties": {
    "gn:admin1_code":"3.0",
    "gn:asciiname":"Karsak",
    "gn:country_code":"KZ",
    "gn:dem":317,
    "gn:feature_class":"P",
    "gn:feature_code":"PPL",
    "gn:name":"Karsak",
    "gn:population":0,
    "gn:timezone":"Asia/Almaty",
    "iso:country":"KZ",
    "name:eng_x_preferred":[
        "Karsak"
    ],
    "name:kaz_x_preferred":[
        "Qarsaq"
    ],
    "name:kaz_x_variant":[
        "\u049a\u0430\u0440\u0441\u0430\u049b"
    ],
    "name:rus_x_preferred":[
        "\u041a\u0430\u0440\u0441\u0430\u043a"
    ],
    "wof:name":"Karsak",
    "wof:placetype":"locality"
},
  "geometry": {"coordinates":[68.8145,52.95761],"type":"Point"}
}