{
  "type": "Feature",
  "properties": {
    "gn:admin1_code":"4.0",
    "gn:asciiname":"Aralcha",
    "gn:country_code":"KZ",
    "gn:dem":291,
    "gn:feature_class":"P",
    "gn:feature_code":"PPL",
    "gn:name":"Aralcha",
    "gn:population":0,
    "gn:timezone":"Asia/Aqtobe",
    "iso:country":"KZ",
    "name:eng_x_preferred":[
        "Aralcha"
    ],
    "name:rus_x_preferred":[
        "\u0410\u0440\u0430\u043b\u0447\u0430"
    ],
    "name:und_x_variant":[
        "Zara"
    ],
    "wof:name":"Aralcha",
    "wof:placetype":"locality"
},
  "geometry": {"coordinates":[59.46023,50.56425],"type":"Point"}
}