{
  "type": "Feature",
  "properties": {
    "gn:admin1_code":"3.0",
    "gn:asciiname":"Chilinka",
    "gn:country_code":"KZ",
    "gn:dem":252,
    "gn:feature_class":"P",
    "gn:feature_code":"PPL",
    "gn:name":"Chilinka",
    "gn:population":0,
    "gn:timezone":"Asia/Almaty",
    "iso:country":"KZ",
    "name:kaz_x_preferred":[
        "Ch\u012bl\u012bnka"
    ],
    "name:kaz_x_variant":[
        "\u0427\u0438\u043b\u0438\u043d\u043a\u0430"
    ],
    "wof:name":"Chilinka",
    "wof:placetype":"locality"
},
  "geometry": {"coordinates":[72.99016999999998,52.03907],"type":"Point"}
}