{
  "type": "Feature",
  "properties": {
    "gn:admin1_code":"16.0",
    "gn:asciiname":"Prudovoye",
    "gn:country_code":"KZ",
    "gn:dem":172,
    "gn:feature_class":"P",
    "gn:feature_code":"PPL",
    "gn:name":"Prudovoye",
    "gn:population":0,
    "gn:timezone":"Asia/Almaty",
    "iso:country":"KZ",
    "name:rus_x_preferred":[
        "\u041f\u0440\u0443\u0434\u043e\u0432\u043e\u0435"
    ],
    "wof:name":"Prudovoye",
    "wof:placetype":"locality"
},
  "geometry": {"coordinates":[66.73749000000001,53.64502],"type":"Point"}
}