{
  "type": "Feature",
  "properties": {
    "gn:admin1_code":"11.0",
    "gn:asciiname":"Babaly",
    "gn:country_code":"KZ",
    "gn:dem":415,
    "gn:feature_class":"P",
    "gn:feature_code":"PPL",
    "gn:name":"Babaly",
    "gn:population":0,
    "gn:timezone":"Asia/Almaty",
    "iso:country":"KZ",
    "name:kaz_x_preferred":[
        "Babaly"
    ],
    "name:kaz_x_variant":[
        "\u0411\u0430\u0431\u0430\u043b\u044b"
    ],
    "wof:name":"Babaly",
    "wof:placetype":"locality"
},
  "geometry": {"coordinates":[76.61964999999999,50.34902],"type":"Point"}
}