{
  "type": "Feature",
  "properties": {
    "gn:admin1_code":"0.0",
    "gn:asciiname":"Burash",
    "gn:cc2":"KZ",
    "gn:country_code":"KZ",
    "gn:dem":336,
    "gn:feature_class":"P",
    "gn:feature_code":"PPL",
    "gn:name":"Burash",
    "gn:population":0,
    "gn:timezone":"Asia/Almaty",
    "iso:country":"KZ",
    "name:und_x_variant":[
        "Aul Burash",
        "Burash"
    ],
    "wof:name":"Burash",
    "wof:placetype":"locality"
},
  "geometry": {"coordinates":[70.43333,50.81667],"type":"Point"}
}