{
  "type": "Feature",
  "properties": {
    "gn:admin1_code":"10.0",
    "gn:asciiname":"Qyzyldala",
    "gn:country_code":"KZ",
    "gn:dem":478,
    "gn:feature_class":"P",
    "gn:feature_code":"PPL",
    "gn:name":"Qyzyldala",
    "gn:population":0,
    "gn:timezone":"Asia/Almaty",
    "iso:country":"KZ",
    "name:kaz_x_preferred":[
        "Qyzyldala"
    ],
    "name:kaz_x_variant":[
        "\u049a\u044b\u0437\u044b\u043b\u0434\u0430\u043b\u0430"
    ],
    "name:rus_x_preferred":[
        "\u041a\u044b\u0437\u044b\u043b\u0434\u0430\u043b\u0430"
    ],
    "name:und_x_variant":[
        "Kyzyldala"
    ],
    "wof:name":"Qyzyldala",
    "wof:placetype":"locality"
},
  "geometry": {"coordinates":[69.41194,42.15564000000001],"type":"Point"}
}