{
  "type": "Feature",
  "properties": {
    "gn:admin1_code":"15.0",
    "gn:asciiname":"Stepnoye",
    "gn:country_code":"KZ",
    "gn:dem":316,
    "gn:feature_class":"P",
    "gn:feature_code":"PPL",
    "gn:name":"Stepnoye",
    "gn:population":0,
    "gn:timezone":"Asia/Almaty",
    "iso:country":"KZ",
    "name:eng_x_preferred":[
        "Stepnoye"
    ],
    "name:rus_x_preferred":[
        "\u0421\u0442\u0435\u043f\u043d\u043e\u0435"
    ],
    "wof:name":"Stepnoye",
    "wof:placetype":"locality"
},
  "geometry": {"coordinates":[82.68361999999998,49.97586],"type":"Point"}
}