{
  "type": "Feature",
  "properties": {
    "gn:admin1_code":"0.0",
    "gn:asciiname":"Ulanerge",
    "gn:country_code":"KZ",
    "gn:dem":675,
    "gn:feature_class":"P",
    "gn:feature_code":"PPL",
    "gn:name":"Ulanerge",
    "gn:population":0,
    "gn:timezone":"Asia/Almaty",
    "iso:country":"KZ",
    "wof:name":"Ulanerge",
    "wof:placetype":"locality"
},
  "geometry": {"coordinates":[83.01666999999998,47.61667],"type":"Point"}
}