{
  "type": "Feature",
  "properties": {
    "gn:admin1_code":"10.0",
    "gn:asciiname":"Akkum Pervyy",
    "gn:country_code":"KZ",
    "gn:dem":911,
    "gn:feature_class":"P",
    "gn:feature_code":"PPL",
    "gn:name":"Akkum Pervyy",
    "gn:population":0,
    "gn:timezone":"Asia/Almaty",
    "iso:country":"KZ",
    "name:rus_x_preferred":[
        "\u0410\u043a\u043a\u0443\u043c \u041f\u0435\u0440\u0432\u044b\u0439"
    ],
    "wof:name":"Akkum Pervyy",
    "wof:placetype":"locality"
},
  "geometry": {"coordinates":[69.96670999999999,42.1937],"type":"Point"}
}