{
  "type": "Feature",
  "properties": {
    "gn:admin1_code":"6.0",
    "gn:asciiname":"Kamokol'",
    "gn:country_code":"KZ",
    "gn:dem":25,
    "gn:feature_class":"P",
    "gn:feature_code":"PPL",
    "gn:name":"Kamokol\u2019",
    "gn:population":0,
    "gn:timezone":"Asia/Atyrau",
    "iso:country":"KZ",
    "wof:name":"Kamokol'",
    "wof:placetype":"locality"
},
  "geometry": {"coordinates":[53.53333000000001,48.83333],"type":"Point"}
}