{
  "type": "Feature",
  "properties": {
    "gn:asciiname":"Tulkubas",
    "gn:country_code":"KZ",
    "gn:dem":827,
    "gn:feature_class":"P",
    "gn:feature_code":"PPL",
    "gn:name":"Tulkubas",
    "gn:population":0,
    "gn:timezone":"Asia/Almaty",
    "iso:country":"KZ",
    "wof:name":"Tulkubas",
    "wof:placetype":"locality"
},
  "geometry": {"coordinates":[70.29087,42.48425],"type":"Point"}
}