{
  "type": "Feature",
  "properties": {
    "gn:admin1_code":"10.0",
    "gn:asciiname":"Georgiyevka",
    "gn:country_code":"KZ",
    "gn:dem":942,
    "gn:feature_class":"P",
    "gn:feature_code":"PPL",
    "gn:name":"Georgiyevka",
    "gn:population":0,
    "gn:timezone":"Asia/Almaty",
    "iso:country":"KZ",
    "name:rus_x_preferred":[
        "\u0413\u0435\u043e\u0440\u0433\u0438\u0435\u0432\u043a\u0430"
    ],
    "name:und_x_variant":[
        "Vetka Lengerugol\u2019",
        "Georgiyevka"
    ],
    "wof:name":"Georgiyevka",
    "wof:placetype":"locality"
},
  "geometry": {"coordinates":[70.0021,42.25237],"type":"Point"}
}