{
  "type": "Feature",
  "properties": {
    "gn:admin1_code":"10.0",
    "gn:asciiname":"Kurdabas",
    "gn:country_code":"KZ",
    "gn:dem":353,
    "gn:feature_class":"P",
    "gn:feature_code":"PPL",
    "gn:name":"Kurdabas",
    "gn:population":0,
    "gn:timezone":"Asia/Almaty",
    "iso:country":"KZ",
    "name:rus_x_preferred":[
        "\u041a\u0443\u0440\u0434\u0430\u0431\u0430\u0441"
    ],
    "wof:name":"Kurdabas",
    "wof:placetype":"locality"
},
  "geometry": {"coordinates":[69.21908000000001,42.29534],"type":"Point"}
}