{
  "type": "Feature",
  "properties": {
    "gn:admin1_code":"0.0",
    "gn:asciiname":"Urazbay",
    "gn:country_code":"KZ",
    "gn:dem":4,
    "gn:feature_class":"P",
    "gn:feature_code":"PPL",
    "gn:name":"Urazbay",
    "gn:population":0,
    "gn:timezone":"Asia/Oral",
    "iso:country":"KZ",
    "wof:name":"Urazbay",
    "wof:placetype":"locality"
},
  "geometry": {"coordinates":[50.03333,49.81667],"type":"Point"}
}