{
  "type": "Feature",
  "properties": {
    "gn:admin1_code":"10.0",
    "gn:asciiname":"Pobeda",
    "gn:country_code":"KZ",
    "gn:dem":267,
    "gn:feature_class":"P",
    "gn:feature_code":"PPL",
    "gn:name":"Pobeda",
    "gn:population":0,
    "gn:timezone":"Asia/Almaty",
    "iso:country":"KZ",
    "name:kaz_x_preferred":[
        "Pobeda"
    ],
    "name:kaz_x_variant":[
        "\u041f\u043e\u0431\u0435\u0434\u0430"
    ],
    "name:uzb_x_preferred":[
        "Alash"
    ],
    "wof:name":"Pobeda",
    "wof:placetype":"locality"
},
  "geometry": {"coordinates":[68.56274000000001,40.72685],"type":"Point"}
}