{
  "type": "Feature",
  "properties": {
    "gn:admin1_code":"17.0",
    "gn:asciiname":"Oktyabr'-Charva",
    "gn:country_code":"KZ",
    "gn:dem":732,
    "gn:feature_class":"P",
    "gn:feature_code":"PPL",
    "gn:name":"Oktyabr\u2019-Charva",
    "gn:population":0,
    "gn:timezone":"Asia/Almaty",
    "iso:country":"KZ",
    "name:rus_x_preferred":[
        "\u041e\u043a\u0442\u044f\u0431\u0440\u044c\u0447\u0430\u0440\u0432\u0430"
    ],
    "name:rus_x_variant":[
        "Oktyabr\u2019-Charva",
        "\u041e\u043a\u0442\u044f\u0431\u0440\u044c-\u0427\u0430\u0440\u0432\u0430"
    ],
    "name:und_x_variant":[
        "Oktyabr\u2019charva"
    ],
    "wof:name":"Oktyabr'-Charva",
    "wof:placetype":"locality"
},
  "geometry": {"coordinates":[72.74804,42.88932],"type":"Point"}
}