{
  "type": "Feature",
  "properties": {
    "gn:admin1_code":"0.0",
    "gn:asciiname":"Otradnoye",
    "gn:country_code":"KZ",
    "gn:dem":298,
    "gn:feature_class":"P",
    "gn:feature_code":"PPL",
    "gn:name":"Otradnoye",
    "gn:population":0,
    "gn:timezone":"Asia/Almaty",
    "iso:country":"KZ",
    "name:eng_x_preferred":[
        "Otradnoye"
    ],
    "name:rus_x_preferred":[
        "\u041e\u0442\u0440\u0430\u0434\u043d\u043e\u0435"
    ],
    "name:und_x_variant":[
        "Otradnyy",
        "Otradny"
    ],
    "wof:name":"Otradnoye",
    "wof:placetype":"locality"
},
  "geometry": {"coordinates":[82.25278,49.98498],"type":"Point"}
}