{
  "type": "Feature",
  "properties": {
    "gn:admin1_code":"3.0",
    "gn:asciiname":"Tasoba",
    "gn:country_code":"KZ",
    "gn:dem":305,
    "gn:feature_class":"P",
    "gn:feature_code":"PPL",
    "gn:name":"Tasoba",
    "gn:population":0,
    "gn:timezone":"Asia/Almaty",
    "iso:country":"KZ",
    "wof:name":"Tasoba",
    "wof:placetype":"locality"
},
  "geometry": {"coordinates":[66.90263,51.83124],"type":"Point"}
}