{
  "type": "Feature",
  "properties": {
    "gn:admin1_code":"0.0",
    "gn:asciiname":"Petropavlovka",
    "gn:cc2":"KZ",
    "gn:country_code":"KZ",
    "gn:dem":29,
    "gn:feature_class":"P",
    "gn:feature_code":"PPL",
    "gn:name":"Petropavlovka",
    "gn:population":0,
    "gn:timezone":"Asia/Oral",
    "iso:country":"KZ",
    "name:aze_x_preferred":[
        "Petropavlovka"
    ],
    "name:bak_x_preferred":[
        "\u041f\u0435\u0442\u0440\u043e\u043f\u0430\u0432\u043b\u043e\u0432\u043a\u0430"
    ],
    "name:bel_x_preferred":[
        "\u041f\u0435\u0442\u0440\u0430\u043f\u0430\u045e\u043b\u0430\u045e\u043a\u0430"
    ],
    "name:ceb_x_preferred":[
        "\u041f\u0435\u0442\u0440\u043e\u043f\u0430\u0432\u043b\u043e\u0432\u043a\u0430"
    ],
    "name:deu_x_preferred":[
        "Petropawlowka"
    ],
    "name:eng_x_preferred":[
        "Petropavlovka"
    ],
    "name:kaz_x_preferred":[
        "\u041f\u0435\u0442\u0440\u043e\u043f\u0430\u0432\u043b\u043e\u0432\u043a\u0430"
    ],
    "name:rus_x_preferred":[
        "\u041f\u0435\u0442\u0440\u043e\u043f\u0430\u0432\u043b\u043e\u0432\u043a\u0430"
    ],
    "name:swe_x_preferred":[
        "Petropavlovka"
    ],
    "name:ukr_x_preferred":[
        "\u041f\u0435\u0442\u0440\u043e\u043f\u0430\u0432\u043b\u043e\u0432\u043a\u0430"
    ],
    "name:und_x_variant":[
        "Petropavloka",
        "Petropavlovka"
    ],
    "wof:name":"Petropavlovka",
    "wof:placetype":"locality"
},
  "geometry": {"coordinates":[47.91667,50.26667],"type":"Point"}
}