{
  "type": "Feature",
  "properties": {
    "gn:admin1_code":"16.0",
    "gn:asciiname":"Selekty",
    "gn:country_code":"KZ",
    "gn:dem":131,
    "gn:feature_class":"P",
    "gn:feature_code":"PPL",
    "gn:name":"Selekty",
    "gn:population":0,
    "gn:timezone":"Asia/Almaty",
    "iso:country":"KZ",
    "name:eng_x_preferred":[
        "Selekty"
    ],
    "name:kaz_x_preferred":[
        "Sileti"
    ],
    "name:kaz_x_variant":[
        "\u0421\u0456\u043b\u0435\u0442\u0456"
    ],
    "name:rus_x_preferred":[
        "\u0421\u0438\u043b\u0435\u043a\u0442\u0438"
    ],
    "name:rus_x_variant":[
        "\u0421\u0435\u043b\u0435\u043a\u0442\u044b"
    ],
    "wof:name":"Selekty",
    "wof:placetype":"locality"
},
  "geometry": {"coordinates":[70.33121,54.36662],"type":"Point"}
}