{
  "type": "Feature",
  "properties": {
    "gn:admin1_code":"1.0",
    "gn:asciiname":"Kundyzdy",
    "gn:country_code":"KZ",
    "gn:dem":521,
    "gn:feature_class":"P",
    "gn:feature_code":"PPL",
    "gn:name":"Kundyzdy",
    "gn:population":0,
    "gn:timezone":"Asia/Almaty",
    "iso:country":"KZ",
    "name:rus_x_preferred":[
        "\u041a\u0443\u043d\u0434\u044b\u0437\u0434\u044b"
    ],
    "wof:name":"Kundyzdy",
    "wof:placetype":"locality"
},
  "geometry": {"coordinates":[80.03426,43.82264],"type":"Point"}
}