{
  "type": "Feature",
  "properties": {
    "gn:admin1_code":"12.0",
    "gn:asciiname":"Ayryk",
    "gn:country_code":"KZ",
    "gn:dem":346,
    "gn:feature_class":"P",
    "gn:feature_code":"PPL",
    "gn:name":"Ayryk",
    "gn:population":0,
    "gn:timezone":"Asia/Almaty",
    "iso:country":"KZ",
    "name:kaz_x_preferred":[
        "\u0410\u0439\u0440\u044b\u049b"
    ],
    "name:rus_x_preferred":[
        "\u0410\u0439\u0440\u044b\u043a"
    ],
    "name:und_x_variant":[
        "Ayryq"
    ],
    "wof:name":"Ayryk",
    "wof:placetype":"locality"
},
  "geometry": {"coordinates":[76.81789000000001,50.47322],"type":"Point"}
}