{
  "type": "Feature",
  "properties": {
    "iso:country":"KZ",
    "name:ara_x_preferred":[
        "\u062c\u0627\u0646\u0627\u062a\u0627\u0633"
    ],
    "name:baq_x_preferred":[
        "Janatas"
    ],
    "name:deu_x_preferred":[
        "Schangatas"
    ],
    "name:dut_x_preferred":[
        "Janatas"
    ],
    "name:eng_x_preferred":[
        "Janatas"
    ],
    "name:eus_x_preferred":[
        "Janatas"
    ],
    "name:fas_x_preferred":[
        "\u0698\u0627\u0646\u0627\u062a\u0627\u0633"
    ],
    "name:fra_x_preferred":[
        "Janatas"
    ],
    "name:fre_x_preferred":[
        "Janatas"
    ],
    "name:ger_x_preferred":[
        "Schangatas"
    ],
    "name:heb_x_preferred":[
        "\u05d2'\u05e0\u05d8\u05e1"
    ],
    "name:kaz_x_preferred":[
        "\u0416\u0430\u04a3\u0430\u0442\u0430\u0441"
    ],
    "name:kaz_x_variant":[
        "Zhangatas"
    ],
    "name:lit_x_preferred":[
        "\u017danatasas"
    ],
    "name:per_x_preferred":[
        "\u0698\u0627\u0646\u0627\u062a\u0627\u0633"
    ],
    "name:pol_x_preferred":[
        "\u017bangatas"
    ],
    "name:rus_x_preferred":[
        "\u0416\u0430\u043d\u0430\u0442\u0430\u0441"
    ],
    "name:tat_x_preferred":[
        "\u042f\u04a3\u0430\u0442\u0430\u0448"
    ],
    "name:ukr_x_preferred":[
        "\u0416\u0430\u043d\u0430\u0442\u0430\u0441"
    ],
    "name:unk_x_variant":[
        "Dzhanytas"
    ],
    "name:uzb_x_preferred":[
        "Janatas"
    ],
    "qs:gn_country":"KZ",
    "qs:gn_fcode":"PPL",
    "qs:gn_pop":33492,
    "qs:name":"Zhanatas",
    "qs:name_adm0":"Kazakhstan",
    "qs:name_adm1":"Zhambyl",
    "qs:photos":0,
    "qs:photos_1k":0,
    "qs:photos_9k":0,
    "qs:photos_9r":0,
    "qs:photos_all":0,
    "qs:photos_sr":0,
    "qs:placetype":"Town",
    "qs:pop_sr":"7",
    "qs:woe_adm0":23424871,
    "wd:wordcount":222,
    "wof:name":"Zhanatas",
    "wof:placetype":"locality",
    "wof:population":33492
},
  "geometry": {"coordinates":[69.75,43.56667],"type":"Point"}
}