{
  "type": "Feature",
  "properties": {
    "gn:admin1_code":"13.0",
    "gn:asciiname":"Fadeevka",
    "gn:country_code":"KZ",
    "gn:dem":200,
    "gn:feature_class":"P",
    "gn:feature_code":"PPL",
    "gn:name":"Fadeevka",
    "gn:population":0,
    "gn:timezone":"Asia/Qyzylorda",
    "iso:country":"KZ",
    "name:kaz_x_preferred":[
        "Fadeevka"
    ],
    "name:kaz_x_variant":[
        "\u0424\u0430\u0434\u0435\u0435\u0432\u043a\u0430"
    ],
    "name:und_x_variant":[
        "Fadeyevka"
    ],
    "wof:name":"Fadeevka",
    "wof:placetype":"locality"
},
  "geometry": {"coordinates":[61.91883000000001,53.9377],"type":"Point"}
}