{
  "type": "Feature",
  "properties": {
    "gn:admin1_code":"12.0",
    "gn:asciiname":"Shotan",
    "gn:country_code":"KZ",
    "gn:dem":553,
    "gn:feature_class":"P",
    "gn:feature_code":"PPL",
    "gn:name":"Shotan",
    "gn:population":0,
    "gn:timezone":"Asia/Almaty",
    "iso:country":"KZ",
    "name:rus_x_preferred":[
        "\u0428\u043e\u0442\u0430\u043d"
    ],
    "wof:name":"Shotan",
    "wof:placetype":"locality"
},
  "geometry": {"coordinates":[72.07711,48.87059],"type":"Point"}
}