{
  "type": "Feature",
  "properties": {
    "gn:admin1_code":"4.0",
    "gn:asciiname":"Zharyk",
    "gn:country_code":"KZ",
    "gn:dem":279,
    "gn:feature_class":"P",
    "gn:feature_code":"PPL",
    "gn:name":"Zharyk",
    "gn:population":0,
    "gn:timezone":"Asia/Aqtobe",
    "iso:country":"KZ",
    "name:kaz_x_preferred":[
        "Zharyq"
    ],
    "wof:name":"Zharyk",
    "wof:placetype":"locality"
},
  "geometry": {"coordinates":[57.57909,49.53568],"type":"Point"}
}