{
  "type": "Feature",
  "properties": {
    "gn:admin1_code":"0.0",
    "gn:asciiname":"Ushasha Pervaya",
    "gn:country_code":"KZ",
    "gn:dem":223,
    "gn:feature_class":"P",
    "gn:feature_code":"PPL",
    "gn:name":"Ushasha Pervaya",
    "gn:population":0,
    "gn:timezone":"Asia/Almaty",
    "iso:country":"KZ",
    "name:und_x_variant":[
        "Ush-Aga",
        "Ushasha Pervaya"
    ],
    "wof:name":"Ushasha Pervaya",
    "wof:placetype":"locality"
},
  "geometry": {"coordinates":[79.30547,50.39606],"type":"Point"}
}