{
  "type": "Feature",
  "properties": {
    "gn:admin1_code":"4.0",
    "gn:asciiname":"Konysbay",
    "gn:country_code":"KZ",
    "gn:dem":222,
    "gn:feature_class":"P",
    "gn:feature_code":"PPL",
    "gn:name":"Konysbay",
    "gn:population":0,
    "gn:timezone":"Asia/Almaty",
    "iso:country":"KZ",
    "name:eng_x_preferred":[
        "Qonysbay"
    ],
    "name:kaz_x_preferred":[
        "Qonysbay"
    ],
    "name:kaz_x_variant":[
        "\u049a\u043e\u043d\u044b\u0441\u0431\u0430\u0439"
    ],
    "name:rus_x_preferred":[
        "\u041a\u043e\u043d\u044b\u0441\u0431\u0430\u0439"
    ],
    "name:und_x_variant":[
        "Konyspay",
        "Konuspay"
    ],
    "wof:name":"Konysbay",
    "wof:placetype":"locality"
},
  "geometry": {"coordinates":[69.28504000000001,53.40801],"type":"Point"}
}