{
  "type": "Feature",
  "properties": {
    "gn:admin1_code":"0.0",
    "gn:asciiname":"Zhanakonys",
    "gn:cc2":"KZ",
    "gn:country_code":"KZ",
    "gn:dem":23,
    "gn:feature_class":"P",
    "gn:feature_code":"PPL",
    "gn:name":"Zhanakonys",
    "gn:population":0,
    "gn:timezone":"Asia/Oral",
    "iso:country":"KZ",
    "name:und_x_variant":[
        "Zhana-Konus",
        "Zhanakonys"
    ],
    "wof:name":"Zhanakonys",
    "wof:placetype":"locality"
},
  "geometry": {"coordinates":[50.26667,50.76667],"type":"Point"}
}