{
  "type": "Feature",
  "properties": {
    "gn:admin1_code":"15.0",
    "gn:asciiname":"Kliment'yevka",
    "gn:country_code":"KZ",
    "gn:dem":228,
    "gn:feature_class":"P",
    "gn:feature_code":"PPL",
    "gn:name":"Kliment\u2019yevka",
    "gn:population":0,
    "gn:timezone":"Asia/Almaty",
    "iso:country":"KZ",
    "name:eng_x_preferred":[
        "Klement'evka"
    ],
    "name:kaz_x_preferred":[
        "Kl\u012bment\u2019evka"
    ],
    "name:kaz_x_variant":[
        "\u041a\u043b\u0438\u043c\u0435\u043d\u0442\u044c\u0435\u0432\u043a\u0430"
    ],
    "name:rus_x_preferred":[
        "\u041a\u043b\u0438\u043c\u0435\u043d\u044c\u0442\u044c\u0435\u0432\u043a\u0430"
    ],
    "name:und_x_variant":[
        "Klement\u2019yevka",
        "Kliment\u2019yevka",
        "Klement\u2019yevskiy",
        "Klement\u2019evka"
    ],
    "wof:name":"Kliment'yevka",
    "wof:placetype":"locality"
},
  "geometry": {"coordinates":[80.92926999999997,50.26145],"type":"Point"}
}