{
  "type": "Feature",
  "properties": {
    "gn:admin1_code":"15.0",
    "gn:asciiname":"Chernovoye",
    "gn:country_code":"KZ",
    "gn:dem":886,
    "gn:feature_class":"P",
    "gn:feature_code":"PPL",
    "gn:name":"Chernovoye",
    "gn:population":0,
    "gn:timezone":"Asia/Almaty",
    "iso:country":"KZ",
    "name:eng_x_preferred":[
        "Chernovoye"
    ],
    "name:rus_x_preferred":[
        "\u0427\u0435\u0440\u043d\u043e\u0432\u043e\u0435"
    ],
    "name:und_x_variant":[
        "Chernovaya",
        "Chernovan",
        "Chernovoye"
    ],
    "wof:name":"Chernovoye",
    "wof:placetype":"locality"
},
  "geometry": {"coordinates":[85.88686,49.22222],"type":"Point"}
}