{
  "type": "Feature",
  "properties": {
    "gn:admin1_code":"10.0",
    "gn:asciiname":"Yasykichu",
    "gn:country_code":"KZ",
    "gn:dem":487,
    "gn:feature_class":"P",
    "gn:feature_code":"PPL",
    "gn:name":"Yasykichu",
    "gn:population":0,
    "gn:timezone":"Asia/Almaty",
    "iso:country":"KZ",
    "name:rus_x_preferred":[
        "\u042f\u0441\u044b\u043a\u0438\u0447\u0443"
    ],
    "name:und_x_variant":[
        "Yasy-Kychu",
        "Yasykichu"
    ],
    "wof:name":"Yasykichu",
    "wof:placetype":"locality"
},
  "geometry": {"coordinates":[69.2659,41.55073],"type":"Point"}
}