{
  "type": "Feature",
  "properties": {
    "gn:admin1_code":"12.0",
    "gn:asciiname":"Bol'shevik",
    "gn:country_code":"KZ",
    "gn:dem":527,
    "gn:feature_class":"P",
    "gn:feature_code":"PPL",
    "gn:name":"Bol\u2019shevik",
    "gn:population":0,
    "gn:timezone":"Asia/Almaty",
    "iso:country":"KZ",
    "wof:name":"Bol'shevik",
    "wof:placetype":"locality"
},
  "geometry": {"coordinates":[66.58333,48.21667],"type":"Point"}
}