{
  "type": "Feature",
  "properties": {
    "gn:admin1_code":"15.0",
    "gn:asciiname":"Yesenbay",
    "gn:country_code":"KZ",
    "gn:dem":177,
    "gn:feature_class":"P",
    "gn:feature_code":"PPL",
    "gn:name":"Yesenbay",
    "gn:population":0,
    "gn:timezone":"Asia/Almaty",
    "iso:country":"KZ",
    "name:eng_x_preferred":[
        "Yesimbay"
    ],
    "name:rus_x_preferred":[
        "\u0415\u0441\u0435\u043d\u0431\u0430\u0439"
    ],
    "name:und_x_variant":[
        "Yesembay",
        "Yesenbay"
    ],
    "wof:name":"Yesenbay",
    "wof:placetype":"locality"
},
  "geometry": {"coordinates":[78.66773000000001,51.11209],"type":"Point"}
}