{
  "type": "Feature",
  "properties": {
    "gn:admin1_code":"15.0",
    "gn:asciiname":"Laptikha",
    "gn:country_code":"KZ",
    "gn:dem":562,
    "gn:feature_class":"P",
    "gn:feature_code":"PPL",
    "gn:name":"Laptikha",
    "gn:population":0,
    "gn:timezone":"Asia/Almaty",
    "iso:country":"KZ",
    "name:eng_x_preferred":[
        "Laptikha"
    ],
    "name:kaz_x_preferred":[
        "Lapt\u012bkha"
    ],
    "name:kaz_x_variant":[
        "\u041b\u0430\u043f\u0442\u0438\u0445\u0430"
    ],
    "name:rus_x_preferred":[
        "\u041b\u0430\u043f\u0442\u0438\u0445\u0430"
    ],
    "wof:name":"Laptikha",
    "wof:placetype":"locality"
},
  "geometry": {"coordinates":[84.76475000000001,49.82242],"type":"Point"}
}