{
  "type": "Feature",
  "properties": {
    "gn:admin1_code":"10.0",
    "gn:asciiname":"Kyzylbastau",
    "gn:country_code":"KZ",
    "gn:dem":463,
    "gn:feature_class":"P",
    "gn:feature_code":"PPL",
    "gn:name":"Kyzylbastau",
    "gn:population":0,
    "gn:timezone":"Asia/Almaty",
    "iso:country":"KZ",
    "name:rus_x_preferred":[
        "\u041a\u044b\u0437\u044b\u043b\u0431\u0430\u0441\u0442\u0430\u0443"
    ],
    "wof:name":"Kyzylbastau",
    "wof:placetype":"locality"
},
  "geometry": {"coordinates":[69.85874,42.56572],"type":"Point"}
}