{
  "type": "Feature",
  "properties": {
    "gn:admin1_code":"10.0",
    "gn:asciiname":"Yenbekshi",
    "gn:country_code":"KZ",
    "gn:dem":521,
    "gn:feature_class":"P",
    "gn:feature_code":"PPL",
    "gn:name":"Yenbekshi",
    "gn:population":0,
    "gn:timezone":"Asia/Almaty",
    "iso:country":"KZ",
    "name:rus_x_preferred":[
        "\u0415\u043d\u0431\u0435\u043a\u0448\u0438"
    ],
    "wof:name":"Yenbekshi",
    "wof:placetype":"locality"
},
  "geometry": {"coordinates":[69.53175999999999,42.14737],"type":"Point"}
}