{
  "type": "Feature",
  "properties": {
    "gn:admin1_code":"15.0",
    "gn:asciiname":"Zhogharghy-Eginsu",
    "gn:country_code":"KZ",
    "gn:dem":439,
    "gn:feature_class":"P",
    "gn:feature_code":"PPL",
    "gn:name":"Zhogharghy-Egins\u016b",
    "gn:population":0,
    "gn:timezone":"Asia/Almaty",
    "iso:country":"KZ",
    "name:kaz_x_preferred":[
        "Zhogharghy-Egins\u016b"
    ],
    "name:und_x_variant":[
        "Imeni Pevogo Maya",
        "Yeginsu"
    ],
    "wof:name":"Zhogharghy-Eginsu",
    "wof:placetype":"locality"
},
  "geometry": {"coordinates":[81.39378000000001,47.024],"type":"Point"}
}