{
  "type": "Feature",
  "properties": {
    "gn:admin1_code":"16.0",
    "gn:asciiname":"Tselinnoye",
    "gn:country_code":"KZ",
    "gn:dem":166,
    "gn:feature_class":"P",
    "gn:feature_code":"PPL",
    "gn:name":"Tselinnoye",
    "gn:population":0,
    "gn:timezone":"Asia/Almaty",
    "iso:country":"KZ",
    "name:eng_x_preferred":[
        "Tsel\u012bnnoe"
    ],
    "name:kaz_x_preferred":[
        "\u0426\u0435\u043b\u0438\u043d\u043d\u043e\u0435"
    ],
    "name:rus_x_preferred":[
        "\u0426\u0435\u043b\u0438\u043d\u043d\u043e\u0435"
    ],
    "name:rus_x_variant":[
        "\u041f\u043e\u0431\u0435\u0434\u0430"
    ],
    "name:und_x_variant":[
        "Imeni Michurina",
        "Pobeda",
        "Tselinnoye"
    ],
    "wof:name":"Tselinnoye",
    "wof:placetype":"locality"
},
  "geometry": {"coordinates":[66.07210000000001,53.98931],"type":"Point"}
}