{
  "type": "Feature",
  "properties": {
    "gn:admin1_code":"12.0",
    "gn:asciiname":"Zhingishke",
    "gn:country_code":"KZ",
    "gn:dem":776,
    "gn:feature_class":"P",
    "gn:feature_code":"PPL",
    "gn:name":"Zhingishke",
    "gn:population":0,
    "gn:timezone":"Asia/Almaty",
    "iso:country":"KZ",
    "name:kaz_x_preferred":[
        "Zhingishke"
    ],
    "name:kaz_x_variant":[
        "\u0416\u0456\u04a3\u0456\u0448\u043a\u0435"
    ],
    "name:rus_x_preferred":[
        "\u0416\u0438\u043d\u0438\u0448\u043a\u0435"
    ],
    "name:und_x_variant":[
        "Zhinishke"
    ],
    "wof:name":"Zhingishke",
    "wof:placetype":"locality"
},
  "geometry": {"coordinates":[75.59493000000001,48.23625],"type":"Point"}
}