{
  "type": "Feature",
  "properties": {
    "gn:admin1_code":"16.0",
    "gn:asciiname":"Molodaya Gvardiya",
    "gn:country_code":"KZ",
    "gn:dem":108,
    "gn:feature_class":"P",
    "gn:feature_code":"PPL",
    "gn:name":"Molodaya Gvardiya",
    "gn:population":0,
    "gn:timezone":"Asia/Almaty",
    "iso:country":"KZ",
    "name:eng_x_preferred":[
        "Molodaya Gvard\u012bya"
    ],
    "name:kaz_x_preferred":[
        "\u041c\u043e\u043b\u043e\u0434\u0430\u044f \u0413\u0432\u0430\u0440\u0434\u0438\u044f"
    ],
    "name:rus_x_preferred":[
        "\u041c\u043e\u043b\u043e\u0434\u0430\u044f \u0413\u0432\u0430\u0440\u0434\u0438\u044f"
    ],
    "name:und_x_variant":[
        "Molodaya Gvardiya"
    ],
    "wof:name":"Molodaya Gvardiya",
    "wof:placetype":"locality"
},
  "geometry": {"coordinates":[72.75804000000002,53.41936],"type":"Point"}
}