{
  "type": "Feature",
  "properties": {
    "gn:admin1_code":"11.0",
    "gn:asciiname":"Yestay",
    "gn:country_code":"KZ",
    "gn:dem":96,
    "gn:feature_class":"P",
    "gn:feature_code":"PPL",
    "gn:name":"Yestay",
    "gn:population":0,
    "gn:timezone":"Asia/Almaty",
    "iso:country":"KZ",
    "name:kaz_x_preferred":[
        "Estay"
    ],
    "name:kaz_x_variant":[
        "\u0415\u0441\u0442\u0430\u0439"
    ],
    "name:rus_x_preferred":[
        "\u0418\u043d\u0442\u044b\u043c\u0430\u043a"
    ],
    "name:und_x_variant":[
        "Intyman",
        "Yestay",
        "Intymak"
    ],
    "wof:name":"Yestay",
    "wof:placetype":"locality"
},
  "geometry": {"coordinates":[76.29349000000001,52.8773],"type":"Point"}
}