{
  "type": "Feature",
  "properties": {
    "gn:admin1_code":"13.0",
    "gn:asciiname":"Dosovka",
    "gn:country_code":"KZ",
    "gn:dem":224,
    "gn:feature_class":"P",
    "gn:feature_code":"PPL",
    "gn:name":"Dosovka",
    "gn:population":0,
    "gn:timezone":"Asia/Qyzylorda",
    "iso:country":"KZ",
    "name:eng_x_preferred":[
        "Dosovka"
    ],
    "name:rus_x_preferred":[
        "\u0414\u043e\u0441\u043e\u0432\u043a\u0430"
    ],
    "name:und_x_variant":[
        "Dosovskiy",
        "Dosovka"
    ],
    "wof:name":"Dosovka",
    "wof:placetype":"locality"
},
  "geometry": {"coordinates":[62.07834,52.38323],"type":"Point"}
}