{
  "type": "Feature",
  "properties": {
    "gn:admin1_code":"15.0",
    "gn:asciiname":"Koshek",
    "gn:country_code":"KZ",
    "gn:dem":381,
    "gn:feature_class":"P",
    "gn:feature_code":"PPL",
    "gn:name":"Koshek",
    "gn:population":0,
    "gn:timezone":"Asia/Almaty",
    "iso:country":"KZ",
    "name:kaz_x_preferred":[
        "K\u00f6shek"
    ],
    "name:kaz_x_variant":[
        "\u041a\u04e9\u0448\u0435\u043a"
    ],
    "name:rus_x_preferred":[
        "\u041a\u043e\u0448\u0435\u043a"
    ],
    "wof:name":"Koshek",
    "wof:placetype":"locality"
},
  "geometry": {"coordinates":[81.24226999999998,49.43159],"type":"Point"}
}