{
  "type": "Feature",
  "properties": {
    "gn:admin1_code":"3.0",
    "gn:asciiname":"Seyten",
    "gn:country_code":"KZ",
    "gn:dem":531,
    "gn:feature_class":"P",
    "gn:feature_code":"PPL",
    "gn:name":"Seyten",
    "gn:population":0,
    "gn:timezone":"Asia/Almaty",
    "iso:country":"KZ",
    "name:kaz_x_preferred":[
        "Seyten"
    ],
    "name:kaz_x_variant":[
        "\u0421\u0435\u0439\u0442\u0435\u043d"
    ],
    "name:rus_x_preferred":[
        "\u0421\u0435\u0439\u0442\u0435\u043d\u044c"
    ],
    "name:und_x_variant":[
        "Seytenskoye",
        "Seitenskoye",
        "Seyten\u2019"
    ],
    "wof:name":"Seyten",
    "wof:placetype":"locality"
},
  "geometry": {"coordinates":[72.79648,51.0102],"type":"Point"}
}