{
  "type": "Feature",
  "properties": {
    "gn:admin1_code":"4.0",
    "gn:asciiname":"Baykat",
    "gn:country_code":"KZ",
    "gn:dem":242,
    "gn:feature_class":"P",
    "gn:feature_code":"PPL",
    "gn:name":"Baykat",
    "gn:population":0,
    "gn:timezone":"Asia/Aqtobe",
    "iso:country":"KZ",
    "name:eng_x_preferred":[
        "Baykat"
    ],
    "name:rus_x_preferred":[
        "\u0411\u0430\u0439\u043a\u0430\u0442"
    ],
    "wof:name":"Baykat",
    "wof:placetype":"locality"
},
  "geometry": {"coordinates":[61.41667,50.36667],"type":"Point"}
}