{
  "type": "Feature",
  "properties": {
    "gn:admin1_code":"13.0",
    "gn:asciiname":"Lesnoy",
    "gn:country_code":"KZ",
    "gn:dem":226,
    "gn:feature_class":"P",
    "gn:feature_code":"PPL",
    "gn:name":"Lesnoy",
    "gn:population":0,
    "gn:timezone":"Asia/Qyzylorda",
    "iso:country":"KZ",
    "name:bel_x_preferred":[
        "\u041b\u044f\u0441\u043d\u044b"
    ],
    "name:ceb_x_preferred":[
        "Lesnoy"
    ],
    "name:deu_x_preferred":[
        "Lesnoi"
    ],
    "name:fin_x_preferred":[
        "Lesnoi"
    ],
    "name:hun_x_preferred":[
        "Lesznoj"
    ],
    "name:hye_x_preferred":[
        "\u053c\u0565\u057d\u0576\u0578\u0575"
    ],
    "name:ita_x_preferred":[
        "Lesnoj"
    ],
    "name:kaz_x_preferred":[
        "\u041b\u0435\u0441\u043d\u043e\u0439"
    ],
    "name:mhr_x_preferred":[
        "\u041b\u0435\u0441\u043d\u043e\u0439"
    ],
    "name:nld_x_preferred":[
        "Lesnoj"
    ],
    "name:rus_x_preferred":[
        "\u041b\u0435\u0441\u043d\u043e\u0439"
    ],
    "name:slk_x_preferred":[
        "Lesnoj"
    ],
    "name:spa_x_preferred":[
        "Lesn\u00f3i"
    ],
    "name:swe_x_preferred":[
        "Lesnoy"
    ],
    "name:ukr_x_preferred":[
        "\u041b\u0456\u0441\u043d\u0438\u0439"
    ],
    "wof:name":"Lesnoy",
    "wof:placetype":"locality"
},
  "geometry": {"coordinates":[61.61482,53.62376],"type":"Point"}
}