{
  "type": "Feature",
  "properties": {
    "gn:admin1_code":"0.0",
    "gn:asciiname":"Krasnoznamennoye",
    "gn:country_code":"KZ",
    "gn:dem":129,
    "gn:feature_class":"P",
    "gn:feature_code":"PPL",
    "gn:name":"Krasnoznam\u00ebnnoye",
    "gn:population":0,
    "gn:timezone":"Asia/Almaty",
    "iso:country":"KZ",
    "name:eng_x_preferred":[
        "Krasnoznamennoye"
    ],
    "name:rus_x_preferred":[
        "\u041a\u0440\u0430\u0441\u043d\u043e\u0437\u043d\u0430\u043c\u0435\u043d\u043d\u043e\u0435"
    ],
    "name:rus_x_variant":[
        "Krasnoznam\u00ebnnoye"
    ],
    "name:und_x_variant":[
        "Mamlyutskiy",
        "Kazanka",
        "Sovkhoz Mamlyutskiy"
    ],
    "wof:name":"Krasnoznamennoye",
    "wof:placetype":"locality"
},
  "geometry": {"coordinates":[68.80708,54.9772],"type":"Point"}
}