{
  "type": "Feature",
  "properties": {
    "iso:country":"KZ",
    "name:eng_x_preferred":[
        "Qaraton"
    ],
    "name:rus_x_preferred":[
        "\u041a\u0430\u0440\u0430\u0442\u043e\u043d"
    ],
    "name:unk_x_variant":[
        "Karatan"
    ],
    "qs:gn_country":"KZ",
    "qs:gn_fcode":"PPL",
    "qs:gn_pop":8905,
    "qs:name":"Karaton",
    "qs:name_adm0":"Kazakhstan",
    "qs:name_adm1":"Atyrau",
    "qs:photos":0,
    "qs:photos_1k":0,
    "qs:photos_9k":0,
    "qs:photos_9r":0,
    "qs:photos_all":0,
    "qs:photos_sr":0,
    "qs:placetype":"Town",
    "qs:pop_sr":"5",
    "qs:woe_adm0":23424871,
    "wof:name":"Karaton",
    "wof:placetype":"locality",
    "wof:population":8905
},
  "geometry": {"coordinates":[53.48639,46.43528],"type":"Point"}
}