{
  "type": "Feature",
  "properties": {
    "gn:admin1_code":"16.0",
    "gn:asciiname":"Boztal",
    "gn:country_code":"KZ",
    "gn:dem":58,
    "gn:feature_class":"P",
    "gn:feature_code":"PPL",
    "gn:name":"Boztal",
    "gn:population":0,
    "gn:timezone":"Asia/Almaty",
    "iso:country":"KZ",
    "name:eng_x_preferred":[
        "Boztal"
    ],
    "name:rus_x_preferred":[
        "\u0411\u043e\u0437\u0442\u0430\u043b"
    ],
    "wof:name":"Boztal",
    "wof:placetype":"locality"
},
  "geometry": {"coordinates":[72.01475000000001,53.82105],"type":"Point"}
}