{
  "type": "Feature",
  "properties": {
    "gn:admin1_code":"6.0",
    "gn:asciiname":"Mantyube",
    "gn:country_code":"KZ",
    "gn:dem":-18,
    "gn:feature_class":"P",
    "gn:feature_code":"PPL",
    "gn:name":"Mantyube",
    "gn:population":0,
    "gn:timezone":"Asia/Atyrau",
    "iso:country":"KZ",
    "wof:name":"Mantyube",
    "wof:placetype":"locality"
},
  "geometry": {"coordinates":[50.06667,47.46667],"type":"Point"}
}