{
  "type": "Feature",
  "properties": {
    "gn:admin1_code":"3.0",
    "gn:asciiname":"Kazakhstan",
    "gn:country_code":"KZ",
    "gn:dem":278,
    "gn:feature_class":"P",
    "gn:feature_code":"PPL",
    "gn:name":"Kazakhstan",
    "gn:population":0,
    "gn:timezone":"Asia/Almaty",
    "iso:country":"KZ",
    "name:eng_x_preferred":[
        "Kazakhstan"
    ],
    "name:kaz_x_preferred":[
        "Qazaqstan"
    ],
    "name:kaz_x_variant":[
        "\u049a\u0430\u0437\u0430\u049b\u0441\u0442\u0430\u043d"
    ],
    "name:rus_x_preferred":[
        "\u041a\u0430\u0437\u0430\u0445\u0441\u0442\u0430\u043d"
    ],
    "wof:name":"Kazakhstan",
    "wof:placetype":"locality"
},
  "geometry": {"coordinates":[69.71158,53.29517],"type":"Point"}
}