{
  "type": "Feature",
  "properties": {
    "gn:admin1_code":"4.0",
    "gn:asciiname":"Mugodzharskoye",
    "gn:country_code":"KZ",
    "gn:dem":402,
    "gn:feature_class":"P",
    "gn:feature_code":"PPL",
    "gn:name":"Mugodzharskoye",
    "gn:population":0,
    "gn:timezone":"Asia/Aqtobe",
    "iso:country":"KZ",
    "name:eng_x_preferred":[
        "Mugodzharskoye"
    ],
    "name:kaz_x_preferred":[
        "M\u016bgalzhar"
    ],
    "name:rus_x_preferred":[
        "\u041c\u0443\u0433\u043e\u0434\u0436\u0430\u0440\u0441\u043a\u043e\u0435"
    ],
    "wof:name":"Mugodzharskoye",
    "wof:placetype":"locality"
},
  "geometry": {"coordinates":[58.46216,48.58578],"type":"Point"}
}