{
  "type": "Feature",
  "properties": {
    "gn:admin1_code":"16.0",
    "gn:asciiname":"Mnogotsvetnoye",
    "gn:country_code":"KZ",
    "gn:dem":158,
    "gn:feature_class":"P",
    "gn:feature_code":"PPL",
    "gn:name":"Mnogotsvetnoye",
    "gn:population":0,
    "gn:timezone":"Asia/Almaty",
    "iso:country":"KZ",
    "name:eng_x_preferred":[
        "Mnogotsvetnoye"
    ],
    "name:kaz_x_preferred":[
        "Mnogotsvetnoe"
    ],
    "name:kaz_x_variant":[
        "\u041c\u043d\u043e\u0433\u043e\u0446\u0432\u0435\u0442\u043d\u043e\u0435"
    ],
    "name:rus_x_preferred":[
        "\u041c\u043d\u043e\u0433\u043e\u0446\u0432\u0435\u0442\u043d\u043e\u0435"
    ],
    "wof:name":"Mnogotsvetnoye",
    "wof:placetype":"locality"
},
  "geometry": {"coordinates":[69.53788,53.88811],"type":"Point"}
}