{
  "type": "Feature",
  "properties": {
    "gn:admin1_code":"15.0",
    "gn:asciiname":"Berezovskiy",
    "gn:country_code":"KZ",
    "gn:dem":202,
    "gn:feature_class":"P",
    "gn:feature_code":"PPL",
    "gn:name":"Berezovskiy",
    "gn:population":0,
    "gn:timezone":"Asia/Almaty",
    "iso:country":"KZ",
    "name:rus_x_preferred":[
        "\u0411\u0435\u0440\u0435\u0437\u043e\u0432\u0441\u043a\u0438\u0439"
    ],
    "name:und_x_variant":[
        "Berezovsk\u012by"
    ],
    "wof:name":"Berezovskiy",
    "wof:placetype":"locality"
},
  "geometry": {"coordinates":[80.32559000000001,50.42514],"type":"Point"}
}