{
  "type": "Feature",
  "properties": {
    "gn:admin1_code":"10.0",
    "gn:asciiname":"Zhararyk",
    "gn:country_code":"KZ",
    "gn:dem":727,
    "gn:feature_class":"P",
    "gn:feature_code":"PPL",
    "gn:name":"Zhararyk",
    "gn:population":0,
    "gn:timezone":"Asia/Almaty",
    "iso:country":"KZ",
    "name:rus_x_preferred":[
        "\u0416\u0430\u0440\u0430\u0440\u044b\u043a"
    ],
    "wof:name":"Zhararyk",
    "wof:placetype":"locality"
},
  "geometry": {"coordinates":[69.67045999999999,42.11835],"type":"Point"}
}