{
  "type": "Feature",
  "properties": {
    "gn:country":"KZ",
    "gn:fcode":"PPLQ",
    "gn:population":828,
    "iso:country":"KZ",
    "name:eng_x_preferred":[
        "Biikzhal"
    ],
    "name:kaz_x_preferred":[
        "\u0411\u0438\u0456\u043a\u0436\u0430\u043b"
    ],
    "name:msa_x_preferred":[
        "Biikzhal"
    ],
    "name:nld_x_preferred":[
        "Biikzhal"
    ],
    "name:rus_x_preferred":[
        "\u0411\u0438\u0438\u043a\u0436\u0430\u043b"
    ],
    "qs:name":"B\u012bikzhal",
    "qs:photos_9r":0,
    "qs:photos_sr":0,
    "qs:pop_sr":"2",
    "wof:name":"B\u012bikzhal",
    "wof:placetype":"locality",
    "wof:population":828
},
  "geometry": {"coordinates":[54.71871,46.7983],"type":"Point"}
}