{
  "type": "Feature",
  "properties": {
    "gn:admin1_code":"10.0",
    "gn:asciiname":"Baybota",
    "gn:country_code":"KZ",
    "gn:dem":263,
    "gn:feature_class":"P",
    "gn:feature_code":"PPL",
    "gn:name":"Baybota",
    "gn:population":0,
    "gn:timezone":"Asia/Almaty",
    "iso:country":"KZ",
    "wof:name":"Baybota",
    "wof:placetype":"locality"
},
  "geometry": {"coordinates":[68.43333,40.63333],"type":"Point"}
}