{
  "type": "Feature",
  "properties": {
    "gn:admin1_code":"10.0",
    "gn:asciiname":"Sayram",
    "gn:country_code":"KZ",
    "gn:dem":667,
    "gn:feature_class":"P",
    "gn:feature_code":"PPL",
    "gn:name":"Sayram",
    "gn:population":0,
    "gn:timezone":"Asia/Almaty",
    "iso:country":"KZ",
    "name:kaz_x_preferred":[
        "\u0421\u0430\u0439\u0440\u0430\u043c"
    ],
    "name:und_x_variant":[
        "Sairam",
        "Sayram"
    ],
    "wof:name":"Sayram",
    "wof:placetype":"locality"
},
  "geometry": {"coordinates":[69.75758,42.3025],"type":"Point"}
}