{
  "type": "Feature",
  "properties": {
    "gn:admin1_code":"0.0",
    "gn:asciiname":"Tselinnyy",
    "gn:country_code":"KZ",
    "gn:dem":268,
    "gn:feature_class":"P",
    "gn:feature_code":"PPL",
    "gn:name":"Tsel\u012bnnyy",
    "gn:population":0,
    "gn:timezone":"Asia/Qyzylorda",
    "iso:country":"KZ",
    "name:und_x_variant":[
        "Imeni Gor\u2019kogo",
        "Tsel\u012bnnyy"
    ],
    "wof:name":"Tselinnyy",
    "wof:placetype":"locality"
},
  "geometry": {"coordinates":[62.0992,51.76522],"type":"Point"}
}