{
  "type": "Feature",
  "properties": {
    "gn:admin1_code":"0.0",
    "gn:asciiname":"Romadan",
    "gn:country_code":"KZ",
    "gn:dem":373,
    "gn:feature_class":"P",
    "gn:feature_code":"PPL",
    "gn:name":"Romadan",
    "gn:population":0,
    "gn:timezone":"Asia/Almaty",
    "iso:country":"KZ",
    "wof:name":"Romadan",
    "wof:placetype":"locality"
},
  "geometry": {"coordinates":[71.13715999999999,51.92088],"type":"Point"}
}