{
  "type": "Feature",
  "properties": {
    "gn:admin1_code":"11.0",
    "gn:asciiname":"Tosagash",
    "gn:country_code":"KZ",
    "gn:dem":159,
    "gn:feature_class":"P",
    "gn:feature_code":"PPL",
    "gn:name":"Tosagash",
    "gn:population":0,
    "gn:timezone":"Asia/Almaty",
    "iso:country":"KZ",
    "name:eng_x_preferred":[
        "Tuzagash"
    ],
    "name:kaz_x_preferred":[
        "T\u00f6saghash"
    ],
    "name:kaz_x_variant":[
        "\u0422\u04e9\u0441\u0430\u0493\u0430\u0448"
    ],
    "name:rus_x_preferred":[
        "\u0422\u043e\u0441\u0430\u0433\u0430\u0448"
    ],
    "name:rus_x_variant":[
        "\u0417\u043e\u0440\u0438 \u041e\u043a\u0442\u044f\u0431\u0440\u044f"
    ],
    "name:und_x_variant":[
        "Tuz-Agach",
        "Tuzagash",
        "Tosagash",
        "Zori Oktyabrya"
    ],
    "wof:name":"Tosagash",
    "wof:placetype":"locality"
},
  "geometry": {"coordinates":[78.69604,51.31879],"type":"Point"}
}