{
  "type": "Feature",
  "properties": {
    "gn:admin1_code":"15.0",
    "gn:asciiname":"Saryoleng",
    "gn:country_code":"KZ",
    "gn:dem":1006,
    "gn:feature_class":"P",
    "gn:feature_code":"PPL",
    "gn:name":"Sary\u00f6leng",
    "gn:population":0,
    "gn:timezone":"Asia/Almaty",
    "iso:country":"KZ",
    "name:und_x_variant":[
        "Sarulen",
        "Saryolen",
        "Saryulen",
        "Sary\u00f6leng"
    ],
    "wof:name":"Saryoleng",
    "wof:placetype":"locality"
},
  "geometry": {"coordinates":[84.08946,47.28077],"type":"Point"}
}