{
  "type": "Feature",
  "properties": {
    "gn:admin1_code":"3.0",
    "gn:asciiname":"Azhibay",
    "gn:country_code":"KZ",
    "gn:dem":332,
    "gn:feature_class":"P",
    "gn:feature_code":"PPL",
    "gn:name":"Azhibay",
    "gn:population":0,
    "gn:timezone":"Asia/Almaty",
    "iso:country":"KZ",
    "name:rus_x_preferred":[
        "\u0410\u0436\u0438\u0431\u0430\u0439"
    ],
    "wof:name":"Azhibay",
    "wof:placetype":"locality"
},
  "geometry": {"coordinates":[72.26817,52.05469],"type":"Point"}
}