{
  "type": "Feature",
  "properties": {
    "gn:admin1_code":"0.0",
    "gn:asciiname":"D'yakov",
    "gn:country_code":"KZ",
    "gn:dem":33,
    "gn:feature_class":"P",
    "gn:feature_code":"PPL",
    "gn:name":"D\u2019yakov",
    "gn:population":0,
    "gn:timezone":"Asia/Oral",
    "iso:country":"KZ",
    "wof:name":"D'yakov",
    "wof:placetype":"locality"
},
  "geometry": {"coordinates":[51.83333,51.35],"type":"Point"}
}