{
  "type": "Feature",
  "properties": {
    "gn:admin1_code":"17.0",
    "gn:asciiname":"Eltaytoyghan",
    "gn:country_code":"KZ",
    "gn:dem":442,
    "gn:feature_class":"P",
    "gn:feature_code":"PPL",
    "gn:name":"Eltaytoyghan",
    "gn:population":0,
    "gn:timezone":"Asia/Almaty",
    "iso:country":"KZ",
    "name:kaz_x_preferred":[
        "Eltaytoyghan"
    ],
    "name:kaz_x_variant":[
        "\u0415\u043b\u0442\u0430\u0439\u0442\u043e\u0439\u0493\u0430\u043d"
    ],
    "name:rus_x_preferred":[
        "\u0415\u043b\u0433\u0430\u0442\u0442\u0430\u0433\u0430\u043d"
    ],
    "name:und_x_variant":[
        "Yelgattagan"
    ],
    "wof:name":"Eltaytoyghan",
    "wof:placetype":"locality"
},
  "geometry": {"coordinates":[71.65745,43.56167],"type":"Point"}
}