{
  "type": "Feature",
  "properties": {
    "gn:admin1_code":"7.0",
    "gn:asciiname":"Bulikshubar",
    "gn:country_code":"KZ",
    "gn:dem":7,
    "gn:feature_class":"P",
    "gn:feature_code":"PPL",
    "gn:name":"Bulikshubar",
    "gn:population":0,
    "gn:timezone":"Asia/Oral",
    "iso:country":"KZ",
    "name:eng_x_preferred":[
        "Bulikshubar"
    ],
    "name:rus_x_preferred":[
        "\u0411\u0443\u043b\u0438\u043a\u0448\u0443\u0431\u0430\u0440"
    ],
    "wof:name":"Bulikshubar",
    "wof:placetype":"locality"
},
  "geometry": {"coordinates":[49.61226,49.94564],"type":"Point"}
}