{
  "type": "Feature",
  "properties": {
    "gn:admin1_code":"0.0",
    "gn:asciiname":"Tyumen'",
    "gn:country_code":"KZ",
    "gn:dem":344,
    "gn:feature_class":"P",
    "gn:feature_code":"PPL",
    "gn:name":"Tyumen\u2019",
    "gn:population":0,
    "gn:timezone":"Asia/Almaty",
    "iso:country":"KZ",
    "name:und_x_variant":[
        "Aul Tyumen\u2019",
        "Tyumen\u2019"
    ],
    "wof:name":"Tyumen'",
    "wof:placetype":"locality"
},
  "geometry": {"coordinates":[70.36667,50.83333],"type":"Point"}
}