{
  "type": "Feature",
  "properties": {
    "gn:admin1_code":"0.0",
    "gn:asciiname":"Ibrayevskiy",
    "gn:country_code":"KZ",
    "gn:dem":296,
    "gn:feature_class":"P",
    "gn:feature_code":"PPL",
    "gn:name":"Ibrayevskiy",
    "gn:population":0,
    "gn:timezone":"Asia/Almaty",
    "iso:country":"KZ",
    "wof:name":"Ibrayevskiy",
    "wof:placetype":"locality"
},
  "geometry": {"coordinates":[79.53333000000001,49.93333],"type":"Point"}
}