{
  "type": "Feature",
  "properties": {
    "gn:admin1_code":"11.0",
    "gn:asciiname":"Otdeleniye Nomer Dva Sovkhoza Novoivanovskiy",
    "gn:country_code":"KZ",
    "gn:dem":110,
    "gn:feature_class":"P",
    "gn:feature_code":"PPL",
    "gn:name":"Otdeleniye Nomer Dva Sovkhoza Novoivanovskiy",
    "gn:population":0,
    "gn:timezone":"Asia/Almaty",
    "iso:country":"KZ",
    "name:kaz_x_preferred":[
        "Tasqudyq"
    ],
    "name:kaz_x_variant":[
        "\u0422\u0430\u0441\u049b\u04b1\u0434\u044b\u049b"
    ],
    "name:rus_x_preferred":[
        "\u041e\u0442\u0434\u0435\u043b\u0435\u043d\u0438\u0435 \u041d\u043e\u043c\u0435\u0440 \u0414\u0432\u0430 \u0421\u043e\u0432\u0445\u043e\u0437\u0430 \u041d\u043e\u0432\u043e\u0438\u0432\u0430\u043d\u043e\u0432\u0441\u043a\u0438\u0439"
    ],
    "name:und_x_variant":[
        "Sovkhoz Novoivanovskiy",
        "Otdeleniye Nomer Dva Sovkhoza Novoivanovskiy"
    ],
    "wof:name":"Otdeleniye Nomer Dva Sovkhoza Novoivanovskiy",
    "wof:placetype":"locality"
},
  "geometry": {"coordinates":[74.76469,53.07198],"type":"Point"}
}