{
  "type": "Feature",
  "properties": {
    "gn:admin1_code":"4.0",
    "gn:asciiname":"Koshensay",
    "gn:country_code":"KZ",
    "gn:dem":284,
    "gn:feature_class":"P",
    "gn:feature_code":"PPL",
    "gn:name":"Koshensay",
    "gn:population":0,
    "gn:timezone":"Asia/Aqtobe",
    "iso:country":"KZ",
    "name:eng_x_preferred":[
        "Koshensay"
    ],
    "name:rus_x_preferred":[
        "\u041a\u043e\u0448\u0435\u043d\u0441\u0430\u0439"
    ],
    "name:und_x_variant":[
        "Vostok",
        "Kashensay",
        "Koshensay"
    ],
    "wof:name":"Koshensay",
    "wof:placetype":"locality"
},
  "geometry": {"coordinates":[59.45544,50.61239000000001],"type":"Point"}
}