{
  "type": "Feature",
  "properties": {
    "gn:admin1_code":"12.0",
    "gn:asciiname":"Nurinskiy Pyatyy",
    "gn:country_code":"KZ",
    "gn:dem":355,
    "gn:feature_class":"P",
    "gn:feature_code":"PPL",
    "gn:name":"Nurinskiy Pyatyy",
    "gn:population":0,
    "gn:timezone":"Asia/Almaty",
    "iso:country":"KZ",
    "wof:name":"Nurinskiy Pyatyy",
    "wof:placetype":"locality"
},
  "geometry": {"coordinates":[70.26666999999999,49.95],"type":"Point"}
}