{
  "type": "Feature",
  "properties": {
    "gn:admin1_code":"0.0",
    "gn:asciiname":"Kustanayskiy",
    "gn:country_code":"KZ",
    "gn:dem":189,
    "gn:feature_class":"P",
    "gn:feature_code":"PPL",
    "gn:name":"Kustanayskiy",
    "gn:population":0,
    "gn:timezone":"Asia/Qyzylorda",
    "iso:country":"KZ",
    "wof:name":"Kustanayskiy",
    "wof:placetype":"locality"
},
  "geometry": {"coordinates":[62.05,53.75],"type":"Point"}
}