{
  "type": "Feature",
  "properties": {
    "gn:admin1_code":"0.0",
    "gn:asciiname":"Sartol'gen",
    "gn:country_code":"KZ",
    "gn:dem":22,
    "gn:feature_class":"P",
    "gn:feature_code":"PPL",
    "gn:name":"Sartol\u2019gen",
    "gn:population":0,
    "gn:timezone":"Asia/Oral",
    "iso:country":"KZ",
    "wof:name":"Sartol'gen",
    "wof:placetype":"locality"
},
  "geometry": {"coordinates":[47.05,49.01667],"type":"Point"}
}