{
  "type": "Feature",
  "properties": {
    "gn:admin1_code":"11.0",
    "gn:asciiname":"Koksiyr",
    "gn:country_code":"KZ",
    "gn:dem":134,
    "gn:feature_class":"P",
    "gn:feature_code":"PPL",
    "gn:name":"Koksiyr",
    "gn:population":0,
    "gn:timezone":"Asia/Almaty",
    "iso:country":"KZ",
    "name:kaz_x_preferred":[
        "K\u00f6ks\u012byr"
    ],
    "name:kaz_x_variant":[
        "\u041a\u04e9\u043a\u0441\u0438\u044b\u0440"
    ],
    "name:rus_x_preferred":[
        "\u041a\u043e\u043a\u0441\u0438\u044b\u0440"
    ],
    "wof:name":"Koksiyr",
    "wof:placetype":"locality"
},
  "geometry": {"coordinates":[74.64521999999999,52.17077000000001],"type":"Point"}
}