{
  "type": "Feature",
  "properties": {
    "gn:admin1_code":"10.0",
    "gn:asciiname":"Fogelevo",
    "gn:country_code":"KZ",
    "gn:dem":648,
    "gn:feature_class":"P",
    "gn:feature_code":"PPL",
    "gn:name":"Fogelevo",
    "gn:population":0,
    "gn:timezone":"Asia/Almaty",
    "iso:country":"KZ",
    "name:kaz_x_preferred":[
        "\u0420\u0430\u0431\u0430\u0442"
    ],
    "name:rus_x_preferred":[
        "\u0424\u043e\u0433\u0435\u043b\u0435\u0432\u043e"
    ],
    "name:und_x_variant":[
        "Fogolevo",
        "Fogelevka",
        "Fogelevo",
        "Rabat"
    ],
    "wof:name":"Fogelevo",
    "wof:placetype":"locality"
},
  "geometry": {"coordinates":[69.52015,42.05787],"type":"Point"}
}