{
  "type": "Feature",
  "properties": {
    "gn:admin1_code":"16.0",
    "gn:asciiname":"Bogatyrovka",
    "gn:country_code":"KZ",
    "gn:dem":172,
    "gn:feature_class":"P",
    "gn:feature_code":"PPL",
    "gn:name":"Bogatyrovka",
    "gn:population":0,
    "gn:timezone":"Asia/Almaty",
    "iso:country":"KZ",
    "name:ceb_x_preferred":[
        "Bogatyrovka"
    ],
    "name:eng_x_preferred":[
        "Bogatyrevka"
    ],
    "name:kaz_x_preferred":[
        "Bogatyrovka"
    ],
    "name:kaz_x_variant":[
        "\u0411\u043e\u0433\u0430\u0442\u044b\u0440\u043e\u0432\u043a\u0430"
    ],
    "name:kir_x_preferred":[
        "\u0411\u043e\u0433\u0430\u0442\u044b\u0440\u043e\u0432\u043a\u0430"
    ],
    "name:rus_x_preferred":[
        "\u0411\u043e\u0433\u043e\u0442\u044b\u0440\u043e\u0432\u043a\u0430"
    ],
    "name:rus_x_variant":[
        "Bogatyr\u00ebvka",
        "\u0411\u043e\u0433\u0430\u0442\u044b\u0440\u0451\u0432\u043a\u0430",
        "\u0411\u043e\u0433\u0430\u0442\u044b\u0440\u043e\u0432\u043a\u0430"
    ],
    "name:swe_x_preferred":[
        "Bogatyrovka"
    ],
    "name:und_x_variant":[
        "Bogatyrevka"
    ],
    "wof:name":"Bogatyrovka",
    "wof:placetype":"locality"
},
  "geometry": {"coordinates":[69.33164000000001,53.83199000000001],"type":"Point"}
}