{
  "type": "Feature",
  "properties": {
    "gn:admin1_code":"7.0",
    "gn:asciiname":"Bisen",
    "gn:country_code":"KZ",
    "gn:dem":39,
    "gn:feature_class":"P",
    "gn:feature_code":"PPL",
    "gn:name":"B\u012bsen",
    "gn:population":0,
    "gn:timezone":"Asia/Oral",
    "iso:country":"KZ",
    "name:eng_x_preferred":[
        "B\u012bsen"
    ],
    "name:rus_x_preferred":[
        "\u0411\u0438\u0441\u0435\u043d"
    ],
    "name:und_x_variant":[
        "Urdinskiy",
        "Bisanskiy",
        "Bisinskiy",
        "B\u012bsen"
    ],
    "wof:name":"Bisen",
    "wof:placetype":"locality"
},
  "geometry": {"coordinates":[47.6619,48.99299],"type":"Point"}
}