{
  "type": "Feature",
  "properties": {
    "gn:admin1_code":"10.0",
    "gn:asciiname":"Otdeleniye Sovkhoza Birlik",
    "gn:country_code":"KZ",
    "gn:dem":283,
    "gn:feature_class":"P",
    "gn:feature_code":"PPLF",
    "gn:name":"Otdeleniye Sovkhoza Birlik",
    "gn:population":0,
    "gn:timezone":"Asia/Almaty",
    "iso:country":"KZ",
    "name:rus_x_preferred":[
        "\u041e\u0442\u0434\u0435\u043b\u0435\u043d\u0438\u0435 \u0421\u043e\u0432\u0445\u043e\u0437\u0430 \u0411\u0438\u0440\u043b\u0438\u043a"
    ],
    "wof:name":"Otdeleniye Sovkhoza Birlik",
    "wof:placetype":"locality"
},
  "geometry": {"coordinates":[68.63128,41.21297],"type":"Point"}
}