{
  "type": "Feature",
  "properties": {
    "iso:country":"KZ",
    "name:bul_x_preferred":[
        "\u041c\u043e\u043b\u0430\u043b\u0439"
    ],
    "name:ceb_x_preferred":[
        "Molaly"
    ],
    "name:che_x_preferred":[
        "\u041c\u043e\u043b\u0430\u043b\u044b"
    ],
    "name:ell_x_preferred":[
        "\u039c\u03bf\u03bb\u03ac\u03bb\u03b9"
    ],
    "name:eng_x_preferred":[
        "Molaly"
    ],
    "name:fas_x_preferred":[
        "\u0645\u0644\u0627\u0644\u06cc"
    ],
    "name:kaz_x_preferred":[
        "\u041c\u043e\u043b\u0430\u043b\u044b"
    ],
    "name:msa_x_preferred":[
        "Molaly"
    ],
    "name:nld_x_preferred":[
        "Molaly"
    ],
    "name:rus_x_preferred":[
        "\u041c\u043e\u043b\u0430\u043b\u044b"
    ],
    "name:swe_x_preferred":[
        "Molaly"
    ],
    "name:tat_x_preferred":[
        "\u041c\u043e\u043b\u0430\u043b\u044b"
    ],
    "name:tgk_x_preferred":[
        "\u041c\u043e\u043b\u0430\u043b\u04e3"
    ],
    "name:ukr_x_preferred":[
        "\u041c\u043e\u043b\u0430\u043b\u0438"
    ],
    "name:ukr_x_variant":[
        "\u0410\u0439\u0442\u0435\u043a\u0435-\u0431\u0456"
    ],
    "name:zho_x_preferred":[
        "\u7a46\u62c9\u96f7"
    ],
    "qs:gn_country":"KZ",
    "qs:gn_fcode":"PPL",
    "qs:gn_pop":707,
    "qs:name":"Mulaly",
    "qs:name_adm0":"Kazakhstan",
    "qs:name_adm1":"Almaty",
    "qs:photos":0,
    "qs:photos_1k":0,
    "qs:photos_9k":0,
    "qs:photos_9r":0,
    "qs:photos_all":0,
    "qs:photos_sr":0,
    "qs:placetype":"Town",
    "qs:pop_sr":"2",
    "qs:woe_adm0":23424871,
    "wd:wordcount":25,
    "wof:name":"Mulaly",
    "wof:placetype":"locality",
    "wof:population":707
},
  "geometry": {"coordinates":[78.31471999999999,45.45278],"type":"Point"}
}