{
  "type": "Feature",
  "properties": {
    "gn:admin1_code":"13.0",
    "gn:asciiname":"Ul'ken",
    "gn:country_code":"KZ",
    "gn:dem":245,
    "gn:feature_class":"P",
    "gn:feature_code":"PPL",
    "gn:name":"Ul\u2019ken",
    "gn:population":0,
    "gn:timezone":"Asia/Qyzylorda",
    "iso:country":"KZ",
    "name:rus_x_preferred":[
        "Ul\u2019ken"
    ],
    "name:rus_x_variant":[
        "\u0423\u043b\u044c\u043a\u0435\u043d"
    ],
    "wof:name":"Ul'ken",
    "wof:placetype":"locality"
},
  "geometry": {"coordinates":[61.15322,53.60647],"type":"Point"}
}