{
  "type": "Feature",
  "properties": {
    "gn:admin1_code":"0.0",
    "gn:asciiname":"Birlik",
    "gn:country_code":"KZ",
    "gn:dem":717,
    "gn:feature_class":"P",
    "gn:feature_code":"PPL",
    "gn:name":"Birlik",
    "gn:population":0,
    "gn:timezone":"Asia/Almaty",
    "iso:country":"KZ",
    "name:deu_x_preferred":[
        "Birlik"
    ],
    "name:kaz_x_preferred":[
        "\u0411\u0456\u0440\u043b\u0456\u043a"
    ],
    "name:kir_x_preferred":[
        "\u0411\u0438\u0440\u043b\u0438\u043a"
    ],
    "name:rus_x_preferred":[
        "\u0411\u0438\u0440\u043b\u0438\u043a"
    ],
    "name:tur_x_preferred":[
        "Birlik"
    ],
    "name:ukr_x_preferred":[
        "\u0411\u0456\u0440\u043b\u0456\u043a"
    ],
    "wof:name":"Birlik",
    "wof:placetype":"locality"
},
  "geometry": {"coordinates":[79.33333,48.78333],"type":"Point"}
}