{
  "type": "Feature",
  "properties": {
    "gn:admin1_code":"0.0",
    "gn:asciiname":"Birlik",
    "gn:country_code":"KZ",
    "gn:dem":717,
    "gn:feature_class":"P",
    "gn:feature_code":"PPL",
    "gn:name":"Birlik",
    "gn:population":0,
    "gn:timezone":"Asia/Almaty",
    "iso:country":"KZ",
    "wof:name":"Birlik",
    "wof:placetype":"locality"
},
  "geometry": {"coordinates":[79.33333,48.78333],"type":"Point"}
}