{
  "type": "Feature",
  "properties": {
    "gn:admin1_code":"3.0",
    "gn:asciiname":"Granitnyy",
    "gn:country_code":"KZ",
    "gn:dem":239,
    "gn:feature_class":"P",
    "gn:feature_code":"PPL",
    "gn:name":"Granitnyy",
    "gn:population":0,
    "gn:timezone":"Asia/Almaty",
    "iso:country":"KZ",
    "name:eng_x_preferred":[
        "Granitnyy"
    ],
    "name:kaz_x_preferred":[
        "Gran\u012btnyy"
    ],
    "name:kaz_x_variant":[
        "\u0413\u0440\u0430\u043d\u0438\u0442\u043d\u044b\u0439"
    ],
    "name:rus_x_preferred":[
        "\u0413\u0440\u0430\u043d\u0438\u0442\u043d\u044b\u0439"
    ],
    "wof:name":"Granitnyy",
    "wof:placetype":"locality"
},
  "geometry": {"coordinates":[69.39055999999999,53.41589000000001],"type":"Point"}
}