{
  "type": "Feature",
  "properties": {
    "gn:admin1_code":"0.0",
    "gn:asciiname":"Sayakskaya Pristan'",
    "gn:country_code":"KZ",
    "gn:dem":338,
    "gn:feature_class":"P",
    "gn:feature_code":"PPL",
    "gn:name":"Sayakskaya Pristan\u2019",
    "gn:population":0,
    "gn:timezone":"Asia/Almaty",
    "iso:country":"KZ",
    "wof:name":"Sayakskaya Pristan'",
    "wof:placetype":"locality"
},
  "geometry": {"coordinates":[77.58333,46.58333],"type":"Point"}
}