{
  "type": "Feature",
  "properties": {
    "gn:admin1_code":"13.0",
    "gn:asciiname":"Vikent'yevka",
    "gn:country_code":"KZ",
    "gn:dem":218,
    "gn:feature_class":"P",
    "gn:feature_code":"PPL",
    "gn:name":"Vikent\u2019yevka",
    "gn:population":0,
    "gn:timezone":"Asia/Qyzylorda",
    "iso:country":"KZ",
    "name:eng_x_preferred":[
        "Vikent'yevka"
    ],
    "name:rus_x_preferred":[
        "\u0412\u0438\u043a\u0435\u043d\u0442\u044c\u0435\u0432\u043a\u0430"
    ],
    "name:rus_x_variant":[
        "Vikent\u2019yevka"
    ],
    "name:und_x_variant":[
        "Vikent\u2019yevskiy"
    ],
    "wof:name":"Vikent'yevka",
    "wof:placetype":"locality"
},
  "geometry": {"coordinates":[62.97136,52.44281],"type":"Point"}
}