{
  "type": "Feature",
  "properties": {
    "gn:admin1_code":"10.0",
    "gn:asciiname":"Tan",
    "gn:country_code":"KZ",
    "gn:dem":1064,
    "gn:feature_class":"P",
    "gn:feature_code":"PPL",
    "gn:name":"Tan",
    "gn:population":0,
    "gn:timezone":"Asia/Almaty",
    "iso:country":"KZ",
    "name:bul_x_preferred":[
        "\u0422\u0430\u043d"
    ],
    "name:ceb_x_preferred":[
        "Tan"
    ],
    "name:ces_x_preferred":[
        "Tan"
    ],
    "name:deu_x_preferred":[
        "Tan"
    ],
    "name:fin_x_preferred":[
        "Tan"
    ],
    "name:frr_x_preferred":[
        "Tan"
    ],
    "name:nld_x_preferred":[
        "Tan"
    ],
    "name:nno_x_preferred":[
        "Tan"
    ],
    "name:nor_x_preferred":[
        "Tan"
    ],
    "name:pol_x_preferred":[
        "Tan"
    ],
    "name:rus_x_preferred":[
        "\u0422\u0430\u043d"
    ],
    "name:swe_x_preferred":[
        "Tan"
    ],
    "name:tur_x_preferred":[
        "Tan"
    ],
    "name:ukr_x_preferred":[
        "\u0422\u0430\u043d"
    ],
    "wof:name":"Tan",
    "wof:placetype":"locality"
},
  "geometry": {"coordinates":[69.67114000000001,41.74782],"type":"Point"}
}