{
  "type": "Feature",
  "properties": {
    "gn:admin1_code":"12.0",
    "gn:asciiname":"Uyzbay",
    "gn:country_code":"KZ",
    "gn:dem":440,
    "gn:feature_class":"P",
    "gn:feature_code":"PPL",
    "gn:name":"\u016ayzbay",
    "gn:population":0,
    "gn:timezone":"Asia/Almaty",
    "iso:country":"KZ",
    "name:und_x_variant":[
        "Morozovka",
        "\u016ayzbay"
    ],
    "wof:name":"Uyzbay",
    "wof:placetype":"locality"
},
  "geometry": {"coordinates":[71.95456,50.38115],"type":"Point"}
}