{
  "type": "Feature",
  "properties": {
    "gn:admin1_code":"3.0",
    "gn:asciiname":"Mortyk",
    "gn:country_code":"KZ",
    "gn:dem":328,
    "gn:feature_class":"P",
    "gn:feature_code":"PPL",
    "gn:name":"Mortyk",
    "gn:population":0,
    "gn:timezone":"Asia/Almaty",
    "iso:country":"KZ",
    "name:und_x_variant":[
        "Martuk",
        "Mortyk"
    ],
    "wof:name":"Mortyk",
    "wof:placetype":"locality"
},
  "geometry": {"coordinates":[70.77537,51.27202],"type":"Point"}
}